Workbook

Sheet Resumo_Compilacao
A1: Resumo da compilação de indicadores sugeridos
A2: Ficheiro gerado a partir do workbook original, com dados 2015-2025 para os indicadores sugeridos quando disponíveis em fontes estruturadas.
A4: Dimensão | B4: Indicadores atuais | C4: Indicadores sugeridos | D4: Sugeridos com algum dado | E4: Sugeridos sem dados automáticos
A5: 1. Governança e Estado de Direito | B5: 5 | C5: 8 | D5: 4 | E5: 4
A6: 2. Estabilidade Macroeconómica | B6: 7 | C6: 9 | D6: 8 | E6: 1
A7: 3. Capital Humano | B7: 6 | C7: 9 | D7: 7 | E7: 2
A8: 4. Inclusão Social e Protecção | B8: 5 | C8: 10 | D8: 8 | E8: 2
A9: 5. Infraestruturas e Serviços | B9: 6 | C9: 10 | D9: 8 | E9: 2
A10: 6. Mercado de Trabalho | B10: 6 | C10: 10 | D10: 9 | E10: 1
A11: 7. Segurança Alimentar e Saúde | B11: 6 | C11: 12 | D11: 12 | E11: 0
A14: Fontes automáticas usadas
A15: Banco Mundial API/CSV | B15: https://api.worldbank.org/v2/en/indicator/{codigo}?downloadformat=csv
A16: World Bank WGI 2025 Revision | B16: https://datacatalogfiles.worldbank.org/ddh-published/0038026/DR0095947/wgidataset_with_sourcedata-2025.xlsx
A17: Demais fontes | B17: Mantidas como metadados/URLs na folha Compilacao_Sugeridos; exigem recolha manual se não houver código/API.
A20: Notas metodológicas
A21: A folha Base_Alargada combina indicadores atuais e sugeridos; a folha Compilacao_Sugeridos isola apenas os sugeridos.
A22: Indicadores sem código/API ficam compilados com fonte, URL, parâmetros sugeridos e estado "recolha manual".
A23: A variação cambial foi calculada como variação absoluta anual da taxa oficial PA.NUS.FCRF.
A24: As fórmulas de normalização usam mínimos/máximos sugeridos. Estes parâmetros devem ser revistos antes de publicação final do índice.

Sheet Instruções
A1: ÍNDICE DE DESENVOLVIMENTO DE ANGOLA (IGDA-BDA)
A3: INSTRUÇÕES DE UTILIZAÇÃO
A5: 1. ESTRUTURA DO FICHEIRO
A6: Este ficheiro está organizado nas seguintes folhas:
A7: • Instruções - Esta folha com orientações de utilização
A8: • Input_Dados - Onde deve introduzir os valores dos indicadores (células azuis)
A9: • Parametros - Definição de pesos, mínimos e máximos para normalização
A10: • Normalizacao - Cálculo automático da normalização (0-100)
A11: • Subindices - Cálculo dos 7 subíndices temáticos
A12: • Indice_Global - Cálculo do IGDA-BDA e dashboard
A14: 2. COMO UTILIZAR
A15: a) Vá à folha 'Input_Dados' e introduza os valores dos indicadores (pode modificar os indicadores)
... A47: - Subíndices continuam a ser média aritmética ponderada dos indicadores (igual ao Output 1).

Sheet Input_Dados
A1: Subíndice | B1: Indicador | C1: Unidade | D1: Sentido | E1: Fonte | F1: 2015 | G1: 2016 | H1: 2017 | I1: 2018 | J1: 2019 | K1: 2020 | L1: 2021 | M1: 2022 | N1: 2023 | O1: 2024 | P1: 2025
A2: 1. Governança | B2: Índice de Percepção da Corrupção | C2: 0-100 | D2: + | E2: Transparency Int. | F2: 15 | G2: 18 | H2: 19 | I2: 19 | J2: 26 | K2: 27 | L2: 29 | M2: 33 | N2: 33 | O2: 32 | Q2: Angola - Corruption Perceptions Index 2023 | countryeconomy.com
A3: 1. Governança | B3: WGI - Estado de Direito | C3: -2.5 a 2.5 | D3: + | E3: Banco Mundial | F3: -1.3086297 | G3: -1.3287764 | H3: -1.3317055 | I3: -1.1105522 | J3: -1.0519682 | K3: -0.9475038 | L3: -1.0980135 | M3: -1.1625439 | N3: -1.1944432 | O3: -1.1697408 | Q3: Angola's Income Inequality (2018) – Trends & Historical Data
A4: 1. Governança | B4: WGI - Eficiência do Governo | C4: -2.5 a 2.5 | D4: + | E4: Banco Mundial | F4: -0.9378237 | G4: -0.9493847 | H4: -0.9681157 | I4: -0.9784602 | J4: -0.9116965 | K4: -1.0163604 | L4: -0.9347008 | M4: -0.8325718 | N4: -0.8287026 | O4: -0.7851909
A5: 1. Governança | B5: Estabilidade Política (WGI) | C5: -2.5 a 2.5 | D5: + | E5: Banco Mundial | F5: -0.5591026 | G5: -0.434628 | H5: -0.5372145 | I5: -0.4058117 | J5: -0.4207039 | K5: -0.6427634 | L5: -0.7936068 | M5: -0.5414068 | N5: -0.3131654 | O5: -0.5735964
A6: 1. Governança | B6: Doing Business / Ease of Business | C6: 0-100 | D6: + | E6: Banco Mundial | F6: 37.09 | G6: 38.46 | H6: 38.41 | I6: 41.49 | J6: 43.86 | K6: 41.9 | Q6: Internet Users in Angola | 2025 Trends & Rankings | World View Data
A7: 2. Macroeconomia | B7: Taxa de Crescimento do PIB | C7: % | D7: + | E7: INE/MEP | F7: 0.76317771 | G7: -1.7005304 | H7: -0.14939623 | I7: -0.59441123 | J7: -0.20468025 | K7: -4.0424472 | L7: 2.1027525 | M7: 4.2160026 | N7: 1.2633081 | O7: 4.4239066 | Q7: Repositório de Conhecimento Aberto
A8: 2. Macroeconomia | B8: PIB per Capita (USD) | C8: USD | D8: + | E8: INE/MEP | F8: 4400.1341 | G8: 4136.7763 | H8: 4955.1922 | I8: 3214.8018 | J8: 2397.7613 | K8: 1902.3184 | L8: 2990.8603 | M8: 3935.501 | N8: 2773.0062 | O8: 3181.6243
A9: 2. Macroeconomia | B9: Inflação (IPC) | C9: % | D9: - | E9: INE/BNA | F9: 12.094268 | G9: 41.121135 | H9: 23.66655 | I9: 18.601105 | J9: 16.897288 | K9: 25.09653 | L9: 27.029944 | M9: 13.860475 | N9: 20.00716 | O9: 26.480339 | P9: 15.69722
A10: 2. Macroeconomia | B10: Dívida Pública (% do PIB) | C10: % | D10: - | E10: MINFIN | F10: 50 | G10: 67 | H10: 60 | I10: 83 | J10: 101 | K10: 119 | L10: 74 | M10: 56 | N10: 72 | O10: 60 | P10: 63 | Q10: PUBLIC DEBT STATISTICAL BULLETIN AS OF []
A11: 2. Macroeconomia | B11: Saldo Orçamental (% do PIB) | C11: % | D11: + | E11: MINFIN | F11: -2 | G11: -3 | H11: 1.5 | I11: -0.5 | J11: 0.5 | K11: -5 | L11: 1.5 | M11: 0.7 | N11: -1.9 | O11: -1.5 | P11: -1.65
A12: 2. Macroeconomia | B12: IDE não-petrolífero (% PIB) | C12: % | D12: + | E12: AIPEX/BNA
A13: 2. Macroeconomia | B13: Reservas Internacionais (meses) | C13: Meses | D13: + | E13: BNA | F13: =+F47 | G13: =+G47 | H13: =+H47 | I13: =+I47 | J13: =+J47 | K13: =+K47 | L13: =+L47 | M13: =+M47 | ... P13: =+P47
A14: 3. Capital Humano | B14: Índice de Desenvolvimento Humano | C14: 0-1 | D14: + | E14: PNUD | F14: 0.591 | G14: 0.595 | H14: 0.597 | I14: 0.598 | J14: 0.597 | K14: 0.594 | L14: 0.59 | M14: 0.591 | N14: 0.616 | Q14: Relatório do Desenvolvimento Humano (RDH) 2023-2024 | United Nations Development Programme
A15: 3. Capital Humano | B15: Esperança Média de Vida | C15: Anos | D15: + | E15: INE/OMS | F15: 61.042 | G15: 61.619 | H15: 61.7 | I15: 61.7 | J15: 62.2 | K15: 62.48 | L15: 62.72 | M15: 62.95 | N15: 64.617 | O15: 64 | P15: 65 | Q15: Life Expectancy at Birth, Total for Angola (SPDYNLE00INAGO) | FRED | St. Louis Fed
A16: 3. Capital Humano | B16: Taxa de Alfabetização (+15 anos) | C16: % | D16: + | E16: INE/MED
A17: 3. Capital Humano | B17: Taxa de Matrícula (primário) | C17: % | D17: + | E17: MED
A18: 3. Capital Humano | B18: Anos Médios de Escolaridade | C18: Anos | D18: + | E18: UNESCO
A19: 3. Capital Humano | B19: Mortalidade Infantil (por 1000) | C19: ‰ | D19: - | E19: INE/MINSA | H19: 61.1 | I19: 60 | J19: 58.9 | K19: 57.8 | L19: 56.81 | M19: 55.84
A20: 4. Inclusão Social | B20: Taxa de Pobreza (< 2.15 USD/dia) | C20: % | D20: - | E20: INE/BM | I20: 31.1 | Q20: UNdata | record view | Poverty headcount ratio at $2.15 a day (2017 PPP) (% of population)
A21: 4. Inclusão Social | B21: Índice de Gini | C21: 0-100 | D21: - | E21: INE/BM | I21: 51.3 | Q21: Gini index - Angola | Data
A22: 4. Inclusão Social | B22: Cobertura Protecção Social | C22: % | D22: + | E22: INSS
A23: 4. Inclusão Social | B23: Global Gender Gap Index | C23: 0-1 | D23: + | E23: WEF | F23: 0.637 | G23: 0.643 | H23: 0.64 | I23: 0.633 | K23: 0.66 | L23: 0.657 | M23: 0.638 | N23: 0.656 | O23: 0.668 | P23: 0.668 | Q23: Angola - Global Gender Gap Index 2024 | countryeconomy.com
A24: 4. Inclusão Social | B24: RNB per Capita (USD) | C24: USD | D24: + | E24: INE | F24: 2350 | G24: 3100 | H24: 2850 | I24: 2450 | J24: 2300 | K24: 2250 | L24: 2300 | M24: 2400 | N24: 2500 | O24: 2840 | P24: 2900 | Q24: GNI per capita, Atlas method (current US$) - Angola | Data
A25: 5. Infraestruturas | B25: Taxa de Electrificação | C25: % | D25: + | E25: MINEA | F25: 42 | G25: 41.8 | H25: 42.9 | I25: 45.3 | J25: 45.6 | K25: 47 | L25: 48.2 | M25: 48.5 | N25: 51.1 | Q25: Angola - Access To Electricity (% Of Population) - 2026 Data 2027 Forecast 1990-2023 Historical
A26: 5. Infraestruturas | B26: Acesso a Água Potável | C26: % | D26: + | E26: MINEA/INE | F26: 54.3 | G26: 55.1 | H26: 55.8 | I26: 56.6 | J26: 56.9 | K26: 57.2 | L26: 57.4 | M26: 57.7 | Q26: Access to Basic Drinking Water in Angola | 2025 Trends & Rankings | World View Data
A27: 5. Infraestruturas | B27: Acesso a Saneamento Básico | C27: % | D27: + | E27: MINEA/INE | F27: 47 | G27: 48 | H27: 48 | I27: 49 | J27: 50 | K27: 50 | L27: 50 | M27: 50 | Q27: People using at least basic sanitation services (% of population) - Angola | Data
A28: 5. Infraestruturas | B28: Cobertura de Rede 4G | C28: % | D28: + | E28: INACOM | Q28: Não tem estatísticas anuais
A29: 5. Infraestruturas | B29: Utilizadores de Internet (%) | C29: % | D29: + | E29: INACOM | F29: 22 | G29: 23.2 | H29: 26 | I29: 29 | J29: 32.1 | K29: 36.6 | L29: 39.3 | M29: 42 | N29: 44 | Q29: Table Data - Internet users for Angola | FRED | St. Louis Fed
A30: 5. Infraestruturas | B30: Densidade Rodoviária (km/1000km²) | C30: km | D30: + | E30: MINTRANS | F30: 29 | G30: 29 | H30: 29 | I30: 29 | J30: 29 | K30: 30 | L30: 31 | M30: 31 | N30: 32 | O30: 33 | Q30: World Bank Document
A31: 6. Mercado Trabalho | B31: Taxa de Emprego | C31: % | D31: + | E31: INE | J31: 61.190162 | K31: 60.774759 | L31: 61.491468 | M31: 62.715613 | N31: 60.653315 | O31: 61.666148 | P31: 64.441287
A32: 6. Mercado Trabalho | B32: Taxa de Desemprego | C32: % | D32: - | E32: INE | J32: 30.208847 | K32: 32.181087 | L32: 32.320726 | M32: 30.155336 | N32: 31.852861 | O32: 31.466353 | P32: 26.860611
A33: 6. Mercado Trabalho | B33: Desemprego Juvenil (15-25) | C33: % | D33: - | E33: INE
A34: 6. Mercado Trabalho | B34: Emprego Informal (%) | C34: % | D34: - | E34: INE | J34: 74.541816 | K34: 80.353575 | L34: 80.447518 | M34: 79.860137 | N34: 80.488095 | O34: 79.759923 | P34: 77.120842
A35: 6. Mercado Trabalho | B35: Taxa de Formalização | C35: % | D35: + | E35: INSS | J35: 25.458184 | K35: 19.646425 | L35: 19.552482 | M35: 20.139863 | N35: 19.511905 | O35: 20.240077 | P35: 22.879158
A36: 6. Mercado Trabalho | B36: Crescimento da Produtividade | C36: % | D36: + | E36: INE/MEP
A37: 7. Seg. Alimentar/Saúde | B37: Índice Global Seg. Alimentar | C37: 0-100 | D37: + | E37: EIU | F37: 35.1 | O37: 26 | P37: 29.7 | Q37: Indicadores Segurança Alimentar
A38: 7. Seg. Alimentar/Saúde | B38: Prevalência de Desnutrição | C38: % | D38: - | E38: MINSA/FAO | G38: 15.2 | H38: 15.4 | I38: 15.9 | J38: 18.2 | K38: 20.8 | L38: 22.6 | M38: 23.1 | N38: 22.5 | Q38: Angola Prevalence of undernourishment - data, chart | TheGlobalEconomy.com
A39: 7. Seg. Alimentar/Saúde | B39: Mortalidade Materna (por 100k) | C39: por 100k | D39: - | E39: MINSA/OMS | F39: 477 | G39: 442 | H39: 400 | I39: 370 | J39: 330 | K39: 300 | L39: 290 | M39: 250 | N39: 183 | O39: 185 | P39: 170 | Q39: Lifetime risk of maternal death (%) - Angola | Data
A40: 7. Seg. Alimentar/Saúde | B40: Despesas Saúde (% PIB) | C40: % | D40: + | E40: MINFIN/OMS | F40: 2.61 | G40: 2.71 | H40: 2.79 | I40: 2.59 | J40: 2.48 | K40: 3.27 | L40: 3.09 | M40: 2.93 | Q40: Angola Health spending as percent of GDP - data, chart | TheGlobalEconomy.com
A41: 7. Seg. Alimentar/Saúde | B41: Camas Hospitalares (por 1000) | C41: por 1000 | D41: + | E41: MINSA | H41: 0.38 | M41: 1.02
A42: 7. Seg. Alimentar/Saúde | B42: Cobertura Vacinal (%) | C42: % | D42: + | E42: MINSA/OMS | F42: 45 | G42: 42 | H42: 50 | I42: 51 | J42: 44 | K42: 36 | L42: 37 | M42: 37 | N42: 50 | Q42: https://cdn.who.int/media/docs/default-source/country-profiles/immunization/2024-country-profiles/immunization-2024-ago.pdf?utm_source=chatgpt.co
F44: =+F1 | G44: =+G1 | H44: =+H1 | I44: =+I1 | J44: =+J1 | K44: =+K1 | L44: =+L1 | M44: =+M1 | ... P44: =+P1
E45: RIL USD | F45: 24419.495 | G45: 24352.542 | H45: 18227.754 | I45: 16170.244 | J45: 17211.496 | K45: 14878.529 | L45: 15508.1 | M45: 14660.603 | N45: 14726.574 | O45: 15767.562 | P45: 15236.539
E46: Importações | F46: 37968.765 | G46: 25657.887 | H46: 28256.537 | I46: 25887.356 | J46: 22299.329 | K46: 15145.687 | L46: 18845.212 | M46: 28564.199 | N46: 23687.832 | O46: 22682.525 | P46: 17595.332
E47: Meses de Importação | F47: =+(F45*12)/F46 | G47: =+(G45*12)/G46 | H47: =+(H45*12)/H46 | I47: =+(I45*12)/I46 | J47: =+(J45*12)/J46 | K47: =+(K45*12)/K46 | L47: =+(L45*12)/L46 | M47: =+(M45*12)/M46 | ... P47: =+(P45*12)/P46

Sheet Parametros
A1: PARÂMETROS DE NORMALIZAÇÃO E PONDERAÇÃO
A3: Indicador | B3: Mínimo Teórico | C3: Máximo Teórico | D3: Meta 2027 | E3: Peso no Subíndice
A4: Índice de Percepção da Corrupção | B4: 0 | C4: 100 | D4: 35 | E4: 1
A5: WGI - Estado de Direito | B5: -2.5 | C5: 2.5 | D5: 0 | E5: 1
A6: WGI - Eficiência do Governo | B6: -2.5 | C6: 2.5 | D6: 0 | E6: 1
A7: Estabilidade Política (WGI) | B7: -2.5 | C7: 2.5 | D7: 0 | E7: 1
A8: Doing Business / Ease of Business | B8: 0 | C8: 100 | D8: 55 | E8: 1
A9: Taxa de Crescimento do PIB | B9: -10 | C9: 15 | D9: 5 | E9: 1
A10: PIB per Capita (USD) | B10: 500 | C10: 15000 | D10: 5000 | E10: 1
A11: Inflação (IPC) | B11: 0 | C11: 50 | D11: 10 | E11: 1
A12: Dívida Pública (% do PIB) | B12: 0 | C12: 150 | D12: 60 | E12: 1
A13: Saldo Orçamental (% do PIB) | B13: -15 | C13: 10 | D13: 0 | E13: 1
A14: IDE não-petrolífero (% PIB) | B14: 0 | C14: 10 | D14: 3 | E14: 1
A15: Reservas Internacionais (meses) | B15: 0 | C15: 12 | D15: 6 | E15: 1
... A44: Cobertura Vacinal (%) | B44: 0 | C44: 100 | D44: 80 | E44: 1
A46: Limiar de Cobertura Mínima por Subíndice (fração 0-1) | B46: 0.5
A47: Nº Mínimo de Subíndices para calcular o IGDA (de 7) | B47: 4
A50: PESOS DOS SUBÍNDICES
A51: Subíndice | B51: Peso
A52: 1. Governança e Estado de Direito | B52: 1
A53: 2. Estabilidade Macroeconómica | B53: 1
A54: 3. Capital Humano | B54: 1
A55: 4. Inclusão Social | B55: 1
A56: 5. Infraestruturas | B56: 1
A57: 6. Mercado de Trabalho | B57: 1
A58: 7. Segurança Alimentar e Saúde | B58: 1

Sheet Normalizacao
A1: Indicador | B1: Sentido | C1: 2015 | D1: 2016 | E1: 2017 | F1: 2018 | G1: 2019 | H1: 2020 | I1: 2021 | J1: 2022 | K1: 2023 | L1: 2024 | M1: 2025
A2: Índice de Percepção da Corrupção | B2: + | C2: =IF(Input_Dados!F$2="","",MIN(100,MAX(0,(Input_Dados!F$2-Parametros!$B$4)/(Parametros!$C$4-Parametros!$B$4)*100))) | D2: =IF(Input_Dados!G$2="","",MIN(100,MAX(0,(Input_Dados!G$2-Parametros!$B$4)/(Parametros!$C$4-Parametros!$B$4)*100))) | E2: =IF(Input_Dados!H$2="","",MIN(100,MAX(0,(Input_Dados!H$2-Parametros!$B$4)/(Parametros!$C$4-Parametros!$B$4)*100))) | F2: =IF(Input_Dados!I$2="","",MIN(100,MAX(0,(Input_Dados!I$2-Parametros!$B$4)/(Parametros!$C$4-Parametros!$B$4)*100))) | G2: =IF(Input_Dados!J$2="","",MIN(100,MAX(0,(Input_Dados!J$2-Parametros!$B$4)/(Parametros!$C$4-Parametros!$B$4)*100))) | H2: =IF(Input_Dados!K$2="","",MIN(100,MAX(0,(Input_Dados!K$2-Parametros!$B$4)/(Parametros!$C$4-Parametros!$B$4)*100))) | I2: =IF(Input_Dados!L$2="","",MIN(100,MAX(0,(Input_Dados!L$2-Parametros!$B$4)/(Parametros!$C$4-Parametros!$B$4)*100))) | J2: =IF(Input_Dados!M$2="","",MIN(100,MAX(0,(Input_Dados!M$2-Parametros!$B$4)/(Parametros!$C$4-Parametros!$B$4)*100))) | ... M2: =IF(Input_Dados!P$2="","",MIN(100,MAX(0,(Input_Dados!P$2-Parametros!$B$4)/(Parametros!$C$4-Parametros!$B$4)*100)))
A3: WGI - Estado de Direito | B3: + | C3: =IF(Input_Dados!F$3="","",MIN(100,MAX(0,(Input_Dados!F$3-Parametros!$B$5)/(Parametros!$C$5-Parametros!$B$5)*100))) | D3: =IF(Input_Dados!G$3="","",MIN(100,MAX(0,(Input_Dados!G$3-Parametros!$B$5)/(Parametros!$C$5-Parametros!$B$5)*100))) | E3: =IF(Input_Dados!H$3="","",MIN(100,MAX(0,(Input_Dados!H$3-Parametros!$B$5)/(Parametros!$C$5-Parametros!$B$5)*100))) | F3: =IF(Input_Dados!I$3="","",MIN(100,MAX(0,(Input_Dados!I$3-Parametros!$B$5)/(Parametros!$C$5-Parametros!$B$5)*100))) | G3: =IF(Input_Dados!J$3="","",MIN(100,MAX(0,(Input_Dados!J$3-Parametros!$B$5)/(Parametros!$C$5-Parametros!$B$5)*100))) | H3: =IF(Input_Dados!K$3="","",MIN(100,MAX(0,(Input_Dados!K$3-Parametros!$B$5)/(Parametros!$C$5-Parametros!$B$5)*100))) | I3: =IF(Input_Dados!L$3="","",MIN(100,MAX(0,(Input_Dados!L$3-Parametros!$B$5)/(Parametros!$C$5-Parametros!$B$5)*100))) | J3: =IF(Input_Dados!M$3="","",MIN(100,MAX(0,(Input_Dados!M$3-Parametros!$B$5)/(Parametros!$C$5-Parametros!$B$5)*100))) | ... M3: =IF(Input_Dados!P$3="","",MIN(100,MAX(0,(Input_Dados!P$3-Parametros!$B$5)/(Parametros!$C$5-Parametros!$B$5)*100)))
A4: WGI - Eficiência do Governo | B4: + | C4: =IF(Input_Dados!F$4="","",MIN(100,MAX(0,(Input_Dados!F$4-Parametros!$B$6)/(Parametros!$C$6-Parametros!$B$6)*100))) | D4: =IF(Input_Dados!G$4="","",MIN(100,MAX(0,(Input_Dados!G$4-Parametros!$B$6)/(Parametros!$C$6-Parametros!$B$6)*100))) | E4: =IF(Input_Dados!H$4="","",MIN(100,MAX(0,(Input_Dados!H$4-Parametros!$B$6)/(Parametros!$C$6-Parametros!$B$6)*100))) | F4: =IF(Input_Dados!I$4="","",MIN(100,MAX(0,(Input_Dados!I$4-Parametros!$B$6)/(Parametros!$C$6-Parametros!$B$6)*100))) | G4: =IF(Input_Dados!J$4="","",MIN(100,MAX(0,(Input_Dados!J$4-Parametros!$B$6)/(Parametros!$C$6-Parametros!$B$6)*100))) | H4: =IF(Input_Dados!K$4="","",MIN(100,MAX(0,(Input_Dados!K$4-Parametros!$B$6)/(Parametros!$C$6-Parametros!$B$6)*100))) | I4: =IF(Input_Dados!L$4="","",MIN(100,MAX(0,(Input_Dados!L$4-Parametros!$B$6)/(Parametros!$C$6-Parametros!$B$6)*100))) | J4: =IF(Input_Dados!M$4="","",MIN(100,MAX(0,(Input_Dados!M$4-Parametros!$B$6)/(Parametros!$C$6-Parametros!$B$6)*100))) | ... M4: =IF(Input_Dados!P$4="","",MIN(100,MAX(0,(Input_Dados!P$4-Parametros!$B$6)/(Parametros!$C$6-Parametros!$B$6)*100)))
A5: Estabilidade Política (WGI) | B5: + | C5: =IF(Input_Dados!F$5="","",MIN(100,MAX(0,(Input_Dados!F$5-Parametros!$B$7)/(Parametros!$C$7-Parametros!$B$7)*100))) | D5: =IF(Input_Dados!G$5="","",MIN(100,MAX(0,(Input_Dados!G$5-Parametros!$B$7)/(Parametros!$C$7-Parametros!$B$7)*100))) | E5: =IF(Input_Dados!H$5="","",MIN(100,MAX(0,(Input_Dados!H$5-Parametros!$B$7)/(Parametros!$C$7-Parametros!$B$7)*100))) | F5: =IF(Input_Dados!I$5="","",MIN(100,MAX(0,(Input_Dados!I$5-Parametros!$B$7)/(Parametros!$C$7-Parametros!$B$7)*100))) | G5: =IF(Input_Dados!J$5="","",MIN(100,MAX(0,(Input_Dados!J$5-Parametros!$B$7)/(Parametros!$C$7-Parametros!$B$7)*100))) | H5: =IF(Input_Dados!K$5="","",MIN(100,MAX(0,(Input_Dados!K$5-Parametros!$B$7)/(Parametros!$C$7-Parametros!$B$7)*100))) | I5: =IF(Input_Dados!L$5="","",MIN(100,MAX(0,(Input_Dados!L$5-Parametros!$B$7)/(Parametros!$C$7-Parametros!$B$7)*100))) | J5: =IF(Input_Dados!M$5="","",MIN(100,MAX(0,(Input_Dados!M$5-Parametros!$B$7)/(Parametros!$C$7-Parametros!$B$7)*100))) | ... M5: =IF(Input_Dados!P$5="","",MIN(100,MAX(0,(Input_Dados!P$5-Parametros!$B$7)/(Parametros!$C$7-Parametros!$B$7)*100)))
A6: Doing Business / Ease of Business | B6: + | C6: =IF(Input_Dados!F$6="","",MIN(100,MAX(0,(Input_Dados!F$6-Parametros!$B$8)/(Parametros!$C$8-Parametros!$B$8)*100))) | D6: =IF(Input_Dados!G$6="","",MIN(100,MAX(0,(Input_Dados!G$6-Parametros!$B$8)/(Parametros!$C$8-Parametros!$B$8)*100))) | E6: =IF(Input_Dados!H$6="","",MIN(100,MAX(0,(Input_Dados!H$6-Parametros!$B$8)/(Parametros!$C$8-Parametros!$B$8)*100))) | F6: =IF(Input_Dados!I$6="","",MIN(100,MAX(0,(Input_Dados!I$6-Parametros!$B$8)/(Parametros!$C$8-Parametros!$B$8)*100))) | G6: =IF(Input_Dados!J$6="","",MIN(100,MAX(0,(Input_Dados!J$6-Parametros!$B$8)/(Parametros!$C$8-Parametros!$B$8)*100))) | H6: =IF(Input_Dados!K$6="","",MIN(100,MAX(0,(Input_Dados!K$6-Parametros!$B$8)/(Parametros!$C$8-Parametros!$B$8)*100))) | I6: =IF(Input_Dados!L$6="","",MIN(100,MAX(0,(Input_Dados!L$6-Parametros!$B$8)/(Parametros!$C$8-Parametros!$B$8)*100))) | J6: =IF(Input_Dados!M$6="","",MIN(100,MAX(0,(Input_Dados!M$6-Parametros!$B$8)/(Parametros!$C$8-Parametros!$B$8)*100))) | ... M6: =IF(Input_Dados!P$6="","",MIN(100,MAX(0,(Input_Dados!P$6-Parametros!$B$8)/(Parametros!$C$8-Parametros!$B$8)*100)))
A7: Taxa de Crescimento do PIB | B7: + | C7: =IF(Input_Dados!F$7="","",MIN(100,MAX(0,(Input_Dados!F$7-Parametros!$B$9)/(Parametros!$C$9-Parametros!$B$9)*100))) | D7: =IF(Input_Dados!G$7="","",MIN(100,MAX(0,(Input_Dados!G$7-Parametros!$B$9)/(Parametros!$C$9-Parametros!$B$9)*100))) | E7: =IF(Input_Dados!H$7="","",MIN(100,MAX(0,(Input_Dados!H$7-Parametros!$B$9)/(Parametros!$C$9-Parametros!$B$9)*100))) | F7: =IF(Input_Dados!I$7="","",MIN(100,MAX(0,(Input_Dados!I$7-Parametros!$B$9)/(Parametros!$C$9-Parametros!$B$9)*100))) | G7: =IF(Input_Dados!J$7="","",MIN(100,MAX(0,(Input_Dados!J$7-Parametros!$B$9)/(Parametros!$C$9-Parametros!$B$9)*100))) | H7: =IF(Input_Dados!K$7="","",MIN(100,MAX(0,(Input_Dados!K$7-Parametros!$B$9)/(Parametros!$C$9-Parametros!$B$9)*100))) | I7: =IF(Input_Dados!L$7="","",MIN(100,MAX(0,(Input_Dados!L$7-Parametros!$B$9)/(Parametros!$C$9-Parametros!$B$9)*100))) | J7: =IF(Input_Dados!M$7="","",MIN(100,MAX(0,(Input_Dados!M$7-Parametros!$B$9)/(Parametros!$C$9-Parametros!$B$9)*100))) | ... M7: =IF(Input_Dados!P$7="","",MIN(100,MAX(0,(Input_Dados!P$7-Parametros!$B$9)/(Parametros!$C$9-Parametros!$B$9)*100)))
A8: PIB per Capita (USD) | B8: + | C8: =IF(Input_Dados!F$8="","",MIN(100,MAX(0,(Input_Dados!F$8-Parametros!$B$10)/(Parametros!$C$10-Parametros!$B$10)*100))) | D8: =IF(Input_Dados!G$8="","",MIN(100,MAX(0,(Input_Dados!G$8-Parametros!$B$10)/(Parametros!$C$10-Parametros!$B$10)*100))) | E8: =IF(Input_Dados!H$8="","",MIN(100,MAX(0,(Input_Dados!H$8-Parametros!$B$10)/(Parametros!$C$10-Parametros!$B$10)*100))) | F8: =IF(Input_Dados!I$8="","",MIN(100,MAX(0,(Input_Dados!I$8-Parametros!$B$10)/(Parametros!$C$10-Parametros!$B$10)*100))) | G8: =IF(Input_Dados!J$8="","",MIN(100,MAX(0,(Input_Dados!J$8-Parametros!$B$10)/(Parametros!$C$10-Parametros!$B$10)*100))) | H8: =IF(Input_Dados!K$8="","",MIN(100,MAX(0,(Input_Dados!K$8-Parametros!$B$10)/(Parametros!$C$10-Parametros!$B$10)*100))) | I8: =IF(Input_Dados!L$8="","",MIN(100,MAX(0,(Input_Dados!L$8-Parametros!$B$10)/(Parametros!$C$10-Parametros!$B$10)*100))) | J8: =IF(Input_Dados!M$8="","",MIN(100,MAX(0,(Input_Dados!M$8-Parametros!$B$10)/(Parametros!$C$10-Parametros!$B$10)*100))) | ... M8: =IF(Input_Dados!P$8="","",MIN(100,MAX(0,(Input_Dados!P$8-Parametros!$B$10)/(Parametros!$C$10-Parametros!$B$10)*100)))
A9: Inflação (IPC) | B9: - | C9: =IF(Input_Dados!F$9="","",MIN(100,MAX(0,(Parametros!$C$11-Input_Dados!F$9)/(Parametros!$C$11-Parametros!$B$11)*100))) | D9: =IF(Input_Dados!G$9="","",MIN(100,MAX(0,(Parametros!$C$11-Input_Dados!G$9)/(Parametros!$C$11-Parametros!$B$11)*100))) | E9: =IF(Input_Dados!H$9="","",MIN(100,MAX(0,(Parametros!$C$11-Input_Dados!H$9)/(Parametros!$C$11-Parametros!$B$11)*100))) | F9: =IF(Input_Dados!I$9="","",MIN(100,MAX(0,(Parametros!$C$11-Input_Dados!I$9)/(Parametros!$C$11-Parametros!$B$11)*100))) | G9: =IF(Input_Dados!J$9="","",MIN(100,MAX(0,(Parametros!$C$11-Input_Dados!J$9)/(Parametros!$C$11-Parametros!$B$11)*100))) | H9: =IF(Input_Dados!K$9="","",MIN(100,MAX(0,(Parametros!$C$11-Input_Dados!K$9)/(Parametros!$C$11-Parametros!$B$11)*100))) | I9: =IF(Input_Dados!L$9="","",MIN(100,MAX(0,(Parametros!$C$11-Input_Dados!L$9)/(Parametros!$C$11-Parametros!$B$11)*100))) | J9: =IF(Input_Dados!M$9="","",MIN(100,MAX(0,(Parametros!$C$11-Input_Dados!M$9)/(Parametros!$C$11-Parametros!$B$11)*100))) | ... M9: =IF(Input_Dados!P$9="","",MIN(100,MAX(0,(Parametros!$C$11-Input_Dados!P$9)/(Parametros!$C$11-Parametros!$B$11)*100)))
A10: Dívida Pública (% do PIB) | B10: - | C10: =IF(Input_Dados!F$10="","",MIN(100,MAX(0,(Parametros!$C$12-Input_Dados!F$10)/(Parametros!$C$12-Parametros!$B$12)*100))) | D10: =IF(Input_Dados!G$10="","",MIN(100,MAX(0,(Parametros!$C$12-Input_Dados!G$10)/(Parametros!$C$12-Parametros!$B$12)*100))) | E10: =IF(Input_Dados!H$10="","",MIN(100,MAX(0,(Parametros!$C$12-Input_Dados!H$10)/(Parametros!$C$12-Parametros!$B$12)*100))) | F10: =IF(Input_Dados!I$10="","",MIN(100,MAX(0,(Parametros!$C$12-Input_Dados!I$10)/(Parametros!$C$12-Parametros!$B$12)*100))) | G10: =IF(Input_Dados!J$10="","",MIN(100,MAX(0,(Parametros!$C$12-Input_Dados!J$10)/(Parametros!$C$12-Parametros!$B$12)*100))) | H10: =IF(Input_Dados!K$10="","",MIN(100,MAX(0,(Parametros!$C$12-Input_Dados!K$10)/(Parametros!$C$12-Parametros!$B$12)*100))) | I10: =IF(Input_Dados!L$10="","",MIN(100,MAX(0,(Parametros!$C$12-Input_Dados!L$10)/(Parametros!$C$12-Parametros!$B$12)*100))) | J10: =IF(Input_Dados!M$10="","",MIN(100,MAX(0,(Parametros!$C$12-Input_Dados!M$10)/(Parametros!$C$12-Parametros!$B$12)*100))) | ... M10: =IF(Input_Dados!P$10="","",MIN(100,MAX(0,(Parametros!$C$12-Input_Dados!P$10)/(Parametros!$C$12-Parametros!$B$12)*100)))
A11: Saldo Orçamental (% do PIB) | B11: + | C11: =IF(Input_Dados!F$11="","",MIN(100,MAX(0,(Input_Dados!F$11-Parametros!$B$13)/(Parametros!$C$13-Parametros!$B$13)*100))) | D11: =IF(Input_Dados!G$11="","",MIN(100,MAX(0,(Input_Dados!G$11-Parametros!$B$13)/(Parametros!$C$13-Parametros!$B$13)*100))) | E11: =IF(Input_Dados!H$11="","",MIN(100,MAX(0,(Input_Dados!H$11-Parametros!$B$13)/(Parametros!$C$13-Parametros!$B$13)*100))) | F11: =IF(Input_Dados!I$11="","",MIN(100,MAX(0,(Input_Dados!I$11-Parametros!$B$13)/(Parametros!$C$13-Parametros!$B$13)*100))) | G11: =IF(Input_Dados!J$11="","",MIN(100,MAX(0,(Input_Dados!J$11-Parametros!$B$13)/(Parametros!$C$13-Parametros!$B$13)*100))) | H11: =IF(Input_Dados!K$11="","",MIN(100,MAX(0,(Input_Dados!K$11-Parametros!$B$13)/(Parametros!$C$13-Parametros!$B$13)*100))) | I11: =IF(Input_Dados!L$11="","",MIN(100,MAX(0,(Input_Dados!L$11-Parametros!$B$13)/(Parametros!$C$13-Parametros!$B$13)*100))) | J11: =IF(Input_Dados!M$11="","",MIN(100,MAX(0,(Input_Dados!M$11-Parametros!$B$13)/(Parametros!$C$13-Parametros!$B$13)*100))) | ... M11: =IF(Input_Dados!P$11="","",MIN(100,MAX(0,(Input_Dados!P$11-Parametros!$B$13)/(Parametros!$C$13-Parametros!$B$13)*100)))
A12: IDE não-petrolífero (% PIB) | B12: + | C12: =IF(Input_Dados!F$12="","",MIN(100,MAX(0,(Input_Dados!F$12-Parametros!$B$14)/(Parametros!$C$14-Parametros!$B$14)*100))) | D12: =IF(Input_Dados!G$12="","",MIN(100,MAX(0,(Input_Dados!G$12-Parametros!$B$14)/(Parametros!$C$14-Parametros!$B$14)*100))) | E12: =IF(Input_Dados!H$12="","",MIN(100,MAX(0,(Input_Dados!H$12-Parametros!$B$14)/(Parametros!$C$14-Parametros!$B$14)*100))) | F12: =IF(Input_Dados!I$12="","",MIN(100,MAX(0,(Input_Dados!I$12-Parametros!$B$14)/(Parametros!$C$14-Parametros!$B$14)*100))) | G12: =IF(Input_Dados!J$12="","",MIN(100,MAX(0,(Input_Dados!J$12-Parametros!$B$14)/(Parametros!$C$14-Parametros!$B$14)*100))) | H12: =IF(Input_Dados!K$12="","",MIN(100,MAX(0,(Input_Dados!K$12-Parametros!$B$14)/(Parametros!$C$14-Parametros!$B$14)*100))) | I12: =IF(Input_Dados!L$12="","",MIN(100,MAX(0,(Input_Dados!L$12-Parametros!$B$14)/(Parametros!$C$14-Parametros!$B$14)*100))) | J12: =IF(Input_Dados!M$12="","",MIN(100,MAX(0,(Input_Dados!M$12-Parametros!$B$14)/(Parametros!$C$14-Parametros!$B$14)*100))) | ... M12: =IF(Input_Dados!P$12="","",MIN(100,MAX(0,(Input_Dados!P$12-Parametros!$B$14)/(Parametros!$C$14-Parametros!$B$14)*100)))
A13: Reservas Internacionais (meses) | B13: + | C13: =IF(Input_Dados!F$13="","",MIN(100,MAX(0,(Input_Dados!F$13-Parametros!$B$15)/(Parametros!$C$15-Parametros!$B$15)*100))) | D13: =IF(Input_Dados!G$13="","",MIN(100,MAX(0,(Input_Dados!G$13-Parametros!$B$15)/(Parametros!$C$15-Parametros!$B$15)*100))) | E13: =IF(Input_Dados!H$13="","",MIN(100,MAX(0,(Input_Dados!H$13-Parametros!$B$15)/(Parametros!$C$15-Parametros!$B$15)*100))) | F13: =IF(Input_Dados!I$13="","",MIN(100,MAX(0,(Input_Dados!I$13-Parametros!$B$15)/(Parametros!$C$15-Parametros!$B$15)*100))) | G13: =IF(Input_Dados!J$13="","",MIN(100,MAX(0,(Input_Dados!J$13-Parametros!$B$15)/(Parametros!$C$15-Parametros!$B$15)*100))) | H13: =IF(Input_Dados!K$13="","",MIN(100,MAX(0,(Input_Dados!K$13-Parametros!$B$15)/(Parametros!$C$15-Parametros!$B$15)*100))) | I13: =IF(Input_Dados!L$13="","",MIN(100,MAX(0,(Input_Dados!L$13-Parametros!$B$15)/(Parametros!$C$15-Parametros!$B$15)*100))) | J13: =IF(Input_Dados!M$13="","",MIN(100,MAX(0,(Input_Dados!M$13-Parametros!$B$15)/(Parametros!$C$15-Parametros!$B$15)*100))) | ... M13: =IF(Input_Dados!P$13="","",MIN(100,MAX(0,(Input_Dados!P$13-Parametros!$B$15)/(Parametros!$C$15-Parametros!$B$15)*100)))
A14: Índice de Desenvolvimento Humano | B14: + | C14: =IF(Input_Dados!F$14="","",MIN(100,MAX(0,(Input_Dados!F$14-Parametros!$B$16)/(Parametros!$C$16-Parametros!$B$16)*100))) | D14: =IF(Input_Dados!G$14="","",MIN(100,MAX(0,(Input_Dados!G$14-Parametros!$B$16)/(Parametros!$C$16-Parametros!$B$16)*100))) | E14: =IF(Input_Dados!H$14="","",MIN(100,MAX(0,(Input_Dados!H$14-Parametros!$B$16)/(Parametros!$C$16-Parametros!$B$16)*100))) | F14: =IF(Input_Dados!I$14="","",MIN(100,MAX(0,(Input_Dados!I$14-Parametros!$B$16)/(Parametros!$C$16-Parametros!$B$16)*100))) | G14: =IF(Input_Dados!J$14="","",MIN(100,MAX(0,(Input_Dados!J$14-Parametros!$B$16)/(Parametros!$C$16-Parametros!$B$16)*100))) | H14: =IF(Input_Dados!K$14="","",MIN(100,MAX(0,(Input_Dados!K$14-Parametros!$B$16)/(Parametros!$C$16-Parametros!$B$16)*100))) | I14: =IF(Input_Dados!L$14="","",MIN(100,MAX(0,(Input_Dados!L$14-Parametros!$B$16)/(Parametros!$C$16-Parametros!$B$16)*100))) | J14: =IF(Input_Dados!M$14="","",MIN(100,MAX(0,(Input_Dados!M$14-Parametros!$B$16)/(Parametros!$C$16-Parametros!$B$16)*100))) | ... M14: =IF(Input_Dados!P$14="","",MIN(100,MAX(0,(Input_Dados!P$14-Parametros!$B$16)/(Parametros!$C$16-Parametros!$B$16)*100)))
A15: Esperança Média de Vida | B15: + | C15: =IF(Input_Dados!F$15="","",MIN(100,MAX(0,(Input_Dados!F$15-Parametros!$B$17)/(Parametros!$C$17-Parametros!$B$17)*100))) | D15: =IF(Input_Dados!G$15="","",MIN(100,MAX(0,(Input_Dados!G$15-Parametros!$B$17)/(Parametros!$C$17-Parametros!$B$17)*100))) | E15: =IF(Input_Dados!H$15="","",MIN(100,MAX(0,(Input_Dados!H$15-Parametros!$B$17)/(Parametros!$C$17-Parametros!$B$17)*100))) | F15: =IF(Input_Dados!I$15="","",MIN(100,MAX(0,(Input_Dados!I$15-Parametros!$B$17)/(Parametros!$C$17-Parametros!$B$17)*100))) | G15: =IF(Input_Dados!J$15="","",MIN(100,MAX(0,(Input_Dados!J$15-Parametros!$B$17)/(Parametros!$C$17-Parametros!$B$17)*100))) | H15: =IF(Input_Dados!K$15="","",MIN(100,MAX(0,(Input_Dados!K$15-Parametros!$B$17)/(Parametros!$C$17-Parametros!$B$17)*100))) | I15: =IF(Input_Dados!L$15="","",MIN(100,MAX(0,(Input_Dados!L$15-Parametros!$B$17)/(Parametros!$C$17-Parametros!$B$17)*100))) | J15: =IF(Input_Dados!M$15="","",MIN(100,MAX(0,(Input_Dados!M$15-Parametros!$B$17)/(Parametros!$C$17-Parametros!$B$17)*100))) | ... M15: =IF(Input_Dados!P$15="","",MIN(100,MAX(0,(Input_Dados!P$15-Parametros!$B$17)/(Parametros!$C$17-Parametros!$B$17)*100)))
A16: Taxa de Alfabetização (+15 anos) | B16: + | C16: =IF(Input_Dados!F$16="","",MIN(100,MAX(0,(Input_Dados!F$16-Parametros!$B$18)/(Parametros!$C$18-Parametros!$B$18)*100))) | D16: =IF(Input_Dados!G$16="","",MIN(100,MAX(0,(Input_Dados!G$16-Parametros!$B$18)/(Parametros!$C$18-Parametros!$B$18)*100))) | E16: =IF(Input_Dados!H$16="","",MIN(100,MAX(0,(Input_Dados!H$16-Parametros!$B$18)/(Parametros!$C$18-Parametros!$B$18)*100))) | F16: =IF(Input_Dados!I$16="","",MIN(100,MAX(0,(Input_Dados!I$16-Parametros!$B$18)/(Parametros!$C$18-Parametros!$B$18)*100))) | G16: =IF(Input_Dados!J$16="","",MIN(100,MAX(0,(Input_Dados!J$16-Parametros!$B$18)/(Parametros!$C$18-Parametros!$B$18)*100))) | H16: =IF(Input_Dados!K$16="","",MIN(100,MAX(0,(Input_Dados!K$16-Parametros!$B$18)/(Parametros!$C$18-Parametros!$B$18)*100))) | I16: =IF(Input_Dados!L$16="","",MIN(100,MAX(0,(Input_Dados!L$16-Parametros!$B$18)/(Parametros!$C$18-Parametros!$B$18)*100))) | J16: =IF(Input_Dados!M$16="","",MIN(100,MAX(0,(Input_Dados!M$16-Parametros!$B$18)/(Parametros!$C$18-Parametros!$B$18)*100))) | ... M16: =IF(Input_Dados!P$16="","",MIN(100,MAX(0,(Input_Dados!P$16-Parametros!$B$18)/(Parametros!$C$18-Parametros!$B$18)*100)))
A17: Taxa de Matrícula (primário) | B17: + | C17: =IF(Input_Dados!F$17="","",MIN(100,MAX(0,(Input_Dados!F$17-Parametros!$B$19)/(Parametros!$C$19-Parametros!$B$19)*100))) | D17: =IF(Input_Dados!G$17="","",MIN(100,MAX(0,(Input_Dados!G$17-Parametros!$B$19)/(Parametros!$C$19-Parametros!$B$19)*100))) | E17: =IF(Input_Dados!H$17="","",MIN(100,MAX(0,(Input_Dados!H$17-Parametros!$B$19)/(Parametros!$C$19-Parametros!$B$19)*100))) | F17: =IF(Input_Dados!I$17="","",MIN(100,MAX(0,(Input_Dados!I$17-Parametros!$B$19)/(Parametros!$C$19-Parametros!$B$19)*100))) | G17: =IF(Input_Dados!J$17="","",MIN(100,MAX(0,(Input_Dados!J$17-Parametros!$B$19)/(Parametros!$C$19-Parametros!$B$19)*100))) | H17: =IF(Input_Dados!K$17="","",MIN(100,MAX(0,(Input_Dados!K$17-Parametros!$B$19)/(Parametros!$C$19-Parametros!$B$19)*100))) | I17: =IF(Input_Dados!L$17="","",MIN(100,MAX(0,(Input_Dados!L$17-Parametros!$B$19)/(Parametros!$C$19-Parametros!$B$19)*100))) | J17: =IF(Input_Dados!M$17="","",MIN(100,MAX(0,(Input_Dados!M$17-Parametros!$B$19)/(Parametros!$C$19-Parametros!$B$19)*100))) | ... M17: =IF(Input_Dados!P$17="","",MIN(100,MAX(0,(Input_Dados!P$17-Parametros!$B$19)/(Parametros!$C$19-Parametros!$B$19)*100)))
A18: Anos Médios de Escolaridade | B18: + | C18: =IF(Input_Dados!F$18="","",MIN(100,MAX(0,(Input_Dados!F$18-Parametros!$B$20)/(Parametros!$C$20-Parametros!$B$20)*100))) | D18: =IF(Input_Dados!G$18="","",MIN(100,MAX(0,(Input_Dados!G$18-Parametros!$B$20)/(Parametros!$C$20-Parametros!$B$20)*100))) | E18: =IF(Input_Dados!H$18="","",MIN(100,MAX(0,(Input_Dados!H$18-Parametros!$B$20)/(Parametros!$C$20-Parametros!$B$20)*100))) | F18: =IF(Input_Dados!I$18="","",MIN(100,MAX(0,(Input_Dados!I$18-Parametros!$B$20)/(Parametros!$C$20-Parametros!$B$20)*100))) | G18: =IF(Input_Dados!J$18="","",MIN(100,MAX(0,(Input_Dados!J$18-Parametros!$B$20)/(Parametros!$C$20-Parametros!$B$20)*100))) | H18: =IF(Input_Dados!K$18="","",MIN(100,MAX(0,(Input_Dados!K$18-Parametros!$B$20)/(Parametros!$C$20-Parametros!$B$20)*100))) | I18: =IF(Input_Dados!L$18="","",MIN(100,MAX(0,(Input_Dados!L$18-Parametros!$B$20)/(Parametros!$C$20-Parametros!$B$20)*100))) | J18: =IF(Input_Dados!M$18="","",MIN(100,MAX(0,(Input_Dados!M$18-Parametros!$B$20)/(Parametros!$C$20-Parametros!$B$20)*100))) | ... M18: =IF(Input_Dados!P$18="","",MIN(100,MAX(0,(Input_Dados!P$18-Parametros!$B$20)/(Parametros!$C$20-Parametros!$B$20)*100)))
A19: Mortalidade Infantil (por 1000) | B19: - | C19: =IF(Input_Dados!F$19="","",MIN(100,MAX(0,(Parametros!$C$21-Input_Dados!F$19)/(Parametros!$C$21-Parametros!$B$21)*100))) | D19: =IF(Input_Dados!G$19="","",MIN(100,MAX(0,(Parametros!$C$21-Input_Dados!G$19)/(Parametros!$C$21-Parametros!$B$21)*100))) | E19: =IF(Input_Dados!H$19="","",MIN(100,MAX(0,(Parametros!$C$21-Input_Dados!H$19)/(Parametros!$C$21-Parametros!$B$21)*100))) | F19: =IF(Input_Dados!I$19="","",MIN(100,MAX(0,(Parametros!$C$21-Input_Dados!I$19)/(Parametros!$C$21-Parametros!$B$21)*100))) | G19: =IF(Input_Dados!J$19="","",MIN(100,MAX(0,(Parametros!$C$21-Input_Dados!J$19)/(Parametros!$C$21-Parametros!$B$21)*100))) | H19: =IF(Input_Dados!K$19="","",MIN(100,MAX(0,(Parametros!$C$21-Input_Dados!K$19)/(Parametros!$C$21-Parametros!$B$21)*100))) | I19: =IF(Input_Dados!L$19="","",MIN(100,MAX(0,(Parametros!$C$21-Input_Dados!L$19)/(Parametros!$C$21-Parametros!$B$21)*100))) | J19: =IF(Input_Dados!M$19="","",MIN(100,MAX(0,(Parametros!$C$21-Input_Dados!M$19)/(Parametros!$C$21-Parametros!$B$21)*100))) | ... M19: =IF(Input_Dados!P$19="","",MIN(100,MAX(0,(Parametros!$C$21-Input_Dados!P$19)/(Parametros!$C$21-Parametros!$B$21)*100)))
A20: Taxa de Pobreza (< 2.15 USD/dia) | B20: - | C20: =IF(Input_Dados!F$20="","",MIN(100,MAX(0,(Parametros!$C$22-Input_Dados!F$20)/(Parametros!$C$22-Parametros!$B$22)*100))) | D20: =IF(Input_Dados!G$20="","",MIN(100,MAX(0,(Parametros!$C$22-Input_Dados!G$20)/(Parametros!$C$22-Parametros!$B$22)*100))) | E20: =IF(Input_Dados!H$20="","",MIN(100,MAX(0,(Parametros!$C$22-Input_Dados!H$20)/(Parametros!$C$22-Parametros!$B$22)*100))) | F20: =IF(Input_Dados!I$20="","",MIN(100,MAX(0,(Parametros!$C$22-Input_Dados!I$20)/(Parametros!$C$22-Parametros!$B$22)*100))) | G20: =IF(Input_Dados!J$20="","",MIN(100,MAX(0,(Parametros!$C$22-Input_Dados!J$20)/(Parametros!$C$22-Parametros!$B$22)*100))) | H20: =IF(Input_Dados!K$20="","",MIN(100,MAX(0,(Parametros!$C$22-Input_Dados!K$20)/(Parametros!$C$22-Parametros!$B$22)*100))) | I20: =IF(Input_Dados!L$20="","",MIN(100,MAX(0,(Parametros!$C$22-Input_Dados!L$20)/(Parametros!$C$22-Parametros!$B$22)*100))) | J20: =IF(Input_Dados!M$20="","",MIN(100,MAX(0,(Parametros!$C$22-Input_Dados!M$20)/(Parametros!$C$22-Parametros!$B$22)*100))) | ... M20: =IF(Input_Dados!P$20="","",MIN(100,MAX(0,(Parametros!$C$22-Input_Dados!P$20)/(Parametros!$C$22-Parametros!$B$22)*100)))
A21: Índice de Gini | B21: - | C21: =IF(Input_Dados!F$21="","",MIN(100,MAX(0,(Parametros!$C$23-Input_Dados!F$21)/(Parametros!$C$23-Parametros!$B$23)*100))) | D21: =IF(Input_Dados!G$21="","",MIN(100,MAX(0,(Parametros!$C$23-Input_Dados!G$21)/(Parametros!$C$23-Parametros!$B$23)*100))) | E21: =IF(Input_Dados!H$21="","",MIN(100,MAX(0,(Parametros!$C$23-Input_Dados!H$21)/(Parametros!$C$23-Parametros!$B$23)*100))) | F21: =IF(Input_Dados!I$21="","",MIN(100,MAX(0,(Parametros!$C$23-Input_Dados!I$21)/(Parametros!$C$23-Parametros!$B$23)*100))) | G21: =IF(Input_Dados!J$21="","",MIN(100,MAX(0,(Parametros!$C$23-Input_Dados!J$21)/(Parametros!$C$23-Parametros!$B$23)*100))) | H21: =IF(Input_Dados!K$21="","",MIN(100,MAX(0,(Parametros!$C$23-Input_Dados!K$21)/(Parametros!$C$23-Parametros!$B$23)*100))) | I21: =IF(Input_Dados!L$21="","",MIN(100,MAX(0,(Parametros!$C$23-Input_Dados!L$21)/(Parametros!$C$23-Parametros!$B$23)*100))) | J21: =IF(Input_Dados!M$21="","",MIN(100,MAX(0,(Parametros!$C$23-Input_Dados!M$21)/(Parametros!$C$23-Parametros!$B$23)*100))) | ... M21: =IF(Input_Dados!P$21="","",MIN(100,MAX(0,(Parametros!$C$23-Input_Dados!P$21)/(Parametros!$C$23-Parametros!$B$23)*100)))
A22: Cobertura Protecção Social | B22: + | C22: =IF(Input_Dados!F$22="","",MIN(100,MAX(0,(Input_Dados!F$22-Parametros!$B$24)/(Parametros!$C$24-Parametros!$B$24)*100))) | D22: =IF(Input_Dados!G$22="","",MIN(100,MAX(0,(Input_Dados!G$22-Parametros!$B$24)/(Parametros!$C$24-Parametros!$B$24)*100))) | E22: =IF(Input_Dados!H$22="","",MIN(100,MAX(0,(Input_Dados!H$22-Parametros!$B$24)/(Parametros!$C$24-Parametros!$B$24)*100))) | F22: =IF(Input_Dados!I$22="","",MIN(100,MAX(0,(Input_Dados!I$22-Parametros!$B$24)/(Parametros!$C$24-Parametros!$B$24)*100))) | G22: =IF(Input_Dados!J$22="","",MIN(100,MAX(0,(Input_Dados!J$22-Parametros!$B$24)/(Parametros!$C$24-Parametros!$B$24)*100))) | H22: =IF(Input_Dados!K$22="","",MIN(100,MAX(0,(Input_Dados!K$22-Parametros!$B$24)/(Parametros!$C$24-Parametros!$B$24)*100))) | I22: =IF(Input_Dados!L$22="","",MIN(100,MAX(0,(Input_Dados!L$22-Parametros!$B$24)/(Parametros!$C$24-Parametros!$B$24)*100))) | J22: =IF(Input_Dados!M$22="","",MIN(100,MAX(0,(Input_Dados!M$22-Parametros!$B$24)/(Parametros!$C$24-Parametros!$B$24)*100))) | ... M22: =IF(Input_Dados!P$22="","",MIN(100,MAX(0,(Input_Dados!P$22-Parametros!$B$24)/(Parametros!$C$24-Parametros!$B$24)*100)))
A23: Global Gender Gap Index | B23: + | C23: =IF(Input_Dados!F$23="","",MIN(100,MAX(0,(Input_Dados!F$23-Parametros!$B$25)/(Parametros!$C$25-Parametros!$B$25)*100))) | D23: =IF(Input_Dados!G$23="","",MIN(100,MAX(0,(Input_Dados!G$23-Parametros!$B$25)/(Parametros!$C$25-Parametros!$B$25)*100))) | E23: =IF(Input_Dados!H$23="","",MIN(100,MAX(0,(Input_Dados!H$23-Parametros!$B$25)/(Parametros!$C$25-Parametros!$B$25)*100))) | F23: =IF(Input_Dados!I$23="","",MIN(100,MAX(0,(Input_Dados!I$23-Parametros!$B$25)/(Parametros!$C$25-Parametros!$B$25)*100))) | G23: =IF(Input_Dados!J$23="","",MIN(100,MAX(0,(Input_Dados!J$23-Parametros!$B$25)/(Parametros!$C$25-Parametros!$B$25)*100))) | H23: =IF(Input_Dados!K$23="","",MIN(100,MAX(0,(Input_Dados!K$23-Parametros!$B$25)/(Parametros!$C$25-Parametros!$B$25)*100))) | I23: =IF(Input_Dados!L$23="","",MIN(100,MAX(0,(Input_Dados!L$23-Parametros!$B$25)/(Parametros!$C$25-Parametros!$B$25)*100))) | J23: =IF(Input_Dados!M$23="","",MIN(100,MAX(0,(Input_Dados!M$23-Parametros!$B$25)/(Parametros!$C$25-Parametros!$B$25)*100))) | ... M23: =IF(Input_Dados!P$23="","",MIN(100,MAX(0,(Input_Dados!P$23-Parametros!$B$25)/(Parametros!$C$25-Parametros!$B$25)*100)))
A24: RNB per Capita (USD) | B24: + | C24: =IF(Input_Dados!F$24="","",MIN(100,MAX(0,(Input_Dados!F$24-Parametros!$B$26)/(Parametros!$C$26-Parametros!$B$26)*100))) | D24: =IF(Input_Dados!G$24="","",MIN(100,MAX(0,(Input_Dados!G$24-Parametros!$B$26)/(Parametros!$C$26-Parametros!$B$26)*100))) | E24: =IF(Input_Dados!H$24="","",MIN(100,MAX(0,(Input_Dados!H$24-Parametros!$B$26)/(Parametros!$C$26-Parametros!$B$26)*100))) | F24: =IF(Input_Dados!I$24="","",MIN(100,MAX(0,(Input_Dados!I$24-Parametros!$B$26)/(Parametros!$C$26-Parametros!$B$26)*100))) | G24: =IF(Input_Dados!J$24="","",MIN(100,MAX(0,(Input_Dados!J$24-Parametros!$B$26)/(Parametros!$C$26-Parametros!$B$26)*100))) | H24: =IF(Input_Dados!K$24="","",MIN(100,MAX(0,(Input_Dados!K$24-Parametros!$B$26)/(Parametros!$C$26-Parametros!$B$26)*100))) | I24: =IF(Input_Dados!L$24="","",MIN(100,MAX(0,(Input_Dados!L$24-Parametros!$B$26)/(Parametros!$C$26-Parametros!$B$26)*100))) | J24: =IF(Input_Dados!M$24="","",MIN(100,MAX(0,(Input_Dados!M$24-Parametros!$B$26)/(Parametros!$C$26-Parametros!$B$26)*100))) | ... M24: =IF(Input_Dados!P$24="","",MIN(100,MAX(0,(Input_Dados!P$24-Parametros!$B$26)/(Parametros!$C$26-Parametros!$B$26)*100)))
A25: Taxa de Electrificação | B25: + | C25: =IF(Input_Dados!F$25="","",MIN(100,MAX(0,(Input_Dados!F$25-Parametros!$B$27)/(Parametros!$C$27-Parametros!$B$27)*100))) | D25: =IF(Input_Dados!G$25="","",MIN(100,MAX(0,(Input_Dados!G$25-Parametros!$B$27)/(Parametros!$C$27-Parametros!$B$27)*100))) | E25: =IF(Input_Dados!H$25="","",MIN(100,MAX(0,(Input_Dados!H$25-Parametros!$B$27)/(Parametros!$C$27-Parametros!$B$27)*100))) | F25: =IF(Input_Dados!I$25="","",MIN(100,MAX(0,(Input_Dados!I$25-Parametros!$B$27)/(Parametros!$C$27-Parametros!$B$27)*100))) | G25: =IF(Input_Dados!J$25="","",MIN(100,MAX(0,(Input_Dados!J$25-Parametros!$B$27)/(Parametros!$C$27-Parametros!$B$27)*100))) | H25: =IF(Input_Dados!K$25="","",MIN(100,MAX(0,(Input_Dados!K$25-Parametros!$B$27)/(Parametros!$C$27-Parametros!$B$27)*100))) | I25: =IF(Input_Dados!L$25="","",MIN(100,MAX(0,(Input_Dados!L$25-Parametros!$B$27)/(Parametros!$C$27-Parametros!$B$27)*100))) | J25: =IF(Input_Dados!M$25="","",MIN(100,MAX(0,(Input_Dados!M$25-Parametros!$B$27)/(Parametros!$C$27-Parametros!$B$27)*100))) | ... M25: =IF(Input_Dados!P$25="","",MIN(100,MAX(0,(Input_Dados!P$25-Parametros!$B$27)/(Parametros!$C$27-Parametros!$B$27)*100)))
A26: Acesso a Água Potável | B26: + | C26: =IF(Input_Dados!F$26="","",MIN(100,MAX(0,(Input_Dados!F$26-Parametros!$B$28)/(Parametros!$C$28-Parametros!$B$28)*100))) | D26: =IF(Input_Dados!G$26="","",MIN(100,MAX(0,(Input_Dados!G$26-Parametros!$B$28)/(Parametros!$C$28-Parametros!$B$28)*100))) | E26: =IF(Input_Dados!H$26="","",MIN(100,MAX(0,(Input_Dados!H$26-Parametros!$B$28)/(Parametros!$C$28-Parametros!$B$28)*100))) | F26: =IF(Input_Dados!I$26="","",MIN(100,MAX(0,(Input_Dados!I$26-Parametros!$B$28)/(Parametros!$C$28-Parametros!$B$28)*100))) | G26: =IF(Input_Dados!J$26="","",MIN(100,MAX(0,(Input_Dados!J$26-Parametros!$B$28)/(Parametros!$C$28-Parametros!$B$28)*100))) | H26: =IF(Input_Dados!K$26="","",MIN(100,MAX(0,(Input_Dados!K$26-Parametros!$B$28)/(Parametros!$C$28-Parametros!$B$28)*100))) | I26: =IF(Input_Dados!L$26="","",MIN(100,MAX(0,(Input_Dados!L$26-Parametros!$B$28)/(Parametros!$C$28-Parametros!$B$28)*100))) | J26: =IF(Input_Dados!M$26="","",MIN(100,MAX(0,(Input_Dados!M$26-Parametros!$B$28)/(Parametros!$C$28-Parametros!$B$28)*100))) | ... M26: =IF(Input_Dados!P$26="","",MIN(100,MAX(0,(Input_Dados!P$26-Parametros!$B$28)/(Parametros!$C$28-Parametros!$B$28)*100)))
A27: Acesso a Saneamento Básico | B27: + | C27: =IF(Input_Dados!F$27="","",MIN(100,MAX(0,(Input_Dados!F$27-Parametros!$B$29)/(Parametros!$C$29-Parametros!$B$29)*100))) | D27: =IF(Input_Dados!G$27="","",MIN(100,MAX(0,(Input_Dados!G$27-Parametros!$B$29)/(Parametros!$C$29-Parametros!$B$29)*100))) | E27: =IF(Input_Dados!H$27="","",MIN(100,MAX(0,(Input_Dados!H$27-Parametros!$B$29)/(Parametros!$C$29-Parametros!$B$29)*100))) | F27: =IF(Input_Dados!I$27="","",MIN(100,MAX(0,(Input_Dados!I$27-Parametros!$B$29)/(Parametros!$C$29-Parametros!$B$29)*100))) | G27: =IF(Input_Dados!J$27="","",MIN(100,MAX(0,(Input_Dados!J$27-Parametros!$B$29)/(Parametros!$C$29-Parametros!$B$29)*100))) | H27: =IF(Input_Dados!K$27="","",MIN(100,MAX(0,(Input_Dados!K$27-Parametros!$B$29)/(Parametros!$C$29-Parametros!$B$29)*100))) | I27: =IF(Input_Dados!L$27="","",MIN(100,MAX(0,(Input_Dados!L$27-Parametros!$B$29)/(Parametros!$C$29-Parametros!$B$29)*100))) | J27: =IF(Input_Dados!M$27="","",MIN(100,MAX(0,(Input_Dados!M$27-Parametros!$B$29)/(Parametros!$C$29-Parametros!$B$29)*100))) | ... M27: =IF(Input_Dados!P$27="","",MIN(100,MAX(0,(Input_Dados!P$27-Parametros!$B$29)/(Parametros!$C$29-Parametros!$B$29)*100)))
A28: Cobertura de Rede 4G | B28: + | C28: =IF(Input_Dados!F$28="","",MIN(100,MAX(0,(Input_Dados!F$28-Parametros!$B$30)/(Parametros!$C$30-Parametros!$B$30)*100))) | D28: =IF(Input_Dados!G$28="","",MIN(100,MAX(0,(Input_Dados!G$28-Parametros!$B$30)/(Parametros!$C$30-Parametros!$B$30)*100))) | E28: =IF(Input_Dados!H$28="","",MIN(100,MAX(0,(Input_Dados!H$28-Parametros!$B$30)/(Parametros!$C$30-Parametros!$B$30)*100))) | F28: =IF(Input_Dados!I$28="","",MIN(100,MAX(0,(Input_Dados!I$28-Parametros!$B$30)/(Parametros!$C$30-Parametros!$B$30)*100))) | G28: =IF(Input_Dados!J$28="","",MIN(100,MAX(0,(Input_Dados!J$28-Parametros!$B$30)/(Parametros!$C$30-Parametros!$B$30)*100))) | H28: =IF(Input_Dados!K$28="","",MIN(100,MAX(0,(Input_Dados!K$28-Parametros!$B$30)/(Parametros!$C$30-Parametros!$B$30)*100))) | I28: =IF(Input_Dados!L$28="","",MIN(100,MAX(0,(Input_Dados!L$28-Parametros!$B$30)/(Parametros!$C$30-Parametros!$B$30)*100))) | J28: =IF(Input_Dados!M$28="","",MIN(100,MAX(0,(Input_Dados!M$28-Parametros!$B$30)/(Parametros!$C$30-Parametros!$B$30)*100))) | ... M28: =IF(Input_Dados!P$28="","",MIN(100,MAX(0,(Input_Dados!P$28-Parametros!$B$30)/(Parametros!$C$30-Parametros!$B$30)*100)))
A29: Utilizadores de Internet (%) | B29: + | C29: =IF(Input_Dados!F$29="","",MIN(100,MAX(0,(Input_Dados!F$29-Parametros!$B$31)/(Parametros!$C$31-Parametros!$B$31)*100))) | D29: =IF(Input_Dados!G$29="","",MIN(100,MAX(0,(Input_Dados!G$29-Parametros!$B$31)/(Parametros!$C$31-Parametros!$B$31)*100))) | E29: =IF(Input_Dados!H$29="","",MIN(100,MAX(0,(Input_Dados!H$29-Parametros!$B$31)/(Parametros!$C$31-Parametros!$B$31)*100))) | F29: =IF(Input_Dados!I$29="","",MIN(100,MAX(0,(Input_Dados!I$29-Parametros!$B$31)/(Parametros!$C$31-Parametros!$B$31)*100))) | G29: =IF(Input_Dados!J$29="","",MIN(100,MAX(0,(Input_Dados!J$29-Parametros!$B$31)/(Parametros!$C$31-Parametros!$B$31)*100))) | H29: =IF(Input_Dados!K$29="","",MIN(100,MAX(0,(Input_Dados!K$29-Parametros!$B$31)/(Parametros!$C$31-Parametros!$B$31)*100))) | I29: =IF(Input_Dados!L$29="","",MIN(100,MAX(0,(Input_Dados!L$29-Parametros!$B$31)/(Parametros!$C$31-Parametros!$B$31)*100))) | J29: =IF(Input_Dados!M$29="","",MIN(100,MAX(0,(Input_Dados!M$29-Parametros!$B$31)/(Parametros!$C$31-Parametros!$B$31)*100))) | ... M29: =IF(Input_Dados!P$29="","",MIN(100,MAX(0,(Input_Dados!P$29-Parametros!$B$31)/(Parametros!$C$31-Parametros!$B$31)*100)))
A30: Densidade Rodoviária (km/1000km²) | B30: + | C30: =IF(Input_Dados!F$30="","",MIN(100,MAX(0,(Input_Dados!F$30-Parametros!$B$32)/(Parametros!$C$32-Parametros!$B$32)*100))) | D30: =IF(Input_Dados!G$30="","",MIN(100,MAX(0,(Input_Dados!G$30-Parametros!$B$32)/(Parametros!$C$32-Parametros!$B$32)*100))) | E30: =IF(Input_Dados!H$30="","",MIN(100,MAX(0,(Input_Dados!H$30-Parametros!$B$32)/(Parametros!$C$32-Parametros!$B$32)*100))) | F30: =IF(Input_Dados!I$30="","",MIN(100,MAX(0,(Input_Dados!I$30-Parametros!$B$32)/(Parametros!$C$32-Parametros!$B$32)*100))) | G30: =IF(Input_Dados!J$30="","",MIN(100,MAX(0,(Input_Dados!J$30-Parametros!$B$32)/(Parametros!$C$32-Parametros!$B$32)*100))) | H30: =IF(Input_Dados!K$30="","",MIN(100,MAX(0,(Input_Dados!K$30-Parametros!$B$32)/(Parametros!$C$32-Parametros!$B$32)*100))) | I30: =IF(Input_Dados!L$30="","",MIN(100,MAX(0,(Input_Dados!L$30-Parametros!$B$32)/(Parametros!$C$32-Parametros!$B$32)*100))) | J30: =IF(Input_Dados!M$30="","",MIN(100,MAX(0,(Input_Dados!M$30-Parametros!$B$32)/(Parametros!$C$32-Parametros!$B$32)*100))) | ... M30: =IF(Input_Dados!P$30="","",MIN(100,MAX(0,(Input_Dados!P$30-Parametros!$B$32)/(Parametros!$C$32-Parametros!$B$32)*100)))
A31: Taxa de Emprego | B31: + | C31: =IF(Input_Dados!F$31="","",MIN(100,MAX(0,(Input_Dados!F$31-Parametros!$B$33)/(Parametros!$C$33-Parametros!$B$33)*100))) | D31: =IF(Input_Dados!G$31="","",MIN(100,MAX(0,(Input_Dados!G$31-Parametros!$B$33)/(Parametros!$C$33-Parametros!$B$33)*100))) | E31: =IF(Input_Dados!H$31="","",MIN(100,MAX(0,(Input_Dados!H$31-Parametros!$B$33)/(Parametros!$C$33-Parametros!$B$33)*100))) | F31: =IF(Input_Dados!I$31="","",MIN(100,MAX(0,(Input_Dados!I$31-Parametros!$B$33)/(Parametros!$C$33-Parametros!$B$33)*100))) | G31: =IF(Input_Dados!J$31="","",MIN(100,MAX(0,(Input_Dados!J$31-Parametros!$B$33)/(Parametros!$C$33-Parametros!$B$33)*100))) | H31: =IF(Input_Dados!K$31="","",MIN(100,MAX(0,(Input_Dados!K$31-Parametros!$B$33)/(Parametros!$C$33-Parametros!$B$33)*100))) | I31: =IF(Input_Dados!L$31="","",MIN(100,MAX(0,(Input_Dados!L$31-Parametros!$B$33)/(Parametros!$C$33-Parametros!$B$33)*100))) | J31: =IF(Input_Dados!M$31="","",MIN(100,MAX(0,(Input_Dados!M$31-Parametros!$B$33)/(Parametros!$C$33-Parametros!$B$33)*100))) | ... M31: =IF(Input_Dados!P$31="","",MIN(100,MAX(0,(Input_Dados!P$31-Parametros!$B$33)/(Parametros!$C$33-Parametros!$B$33)*100)))
A32: Taxa de Desemprego | B32: - | C32: =IF(Input_Dados!F$32="","",MIN(100,MAX(0,(Parametros!$C$34-Input_Dados!F$32)/(Parametros!$C$34-Parametros!$B$34)*100))) | D32: =IF(Input_Dados!G$32="","",MIN(100,MAX(0,(Parametros!$C$34-Input_Dados!G$32)/(Parametros!$C$34-Parametros!$B$34)*100))) | E32: =IF(Input_Dados!H$32="","",MIN(100,MAX(0,(Parametros!$C$34-Input_Dados!H$32)/(Parametros!$C$34-Parametros!$B$34)*100))) | F32: =IF(Input_Dados!I$32="","",MIN(100,MAX(0,(Parametros!$C$34-Input_Dados!I$32)/(Parametros!$C$34-Parametros!$B$34)*100))) | G32: =IF(Input_Dados!J$32="","",MIN(100,MAX(0,(Parametros!$C$34-Input_Dados!J$32)/(Parametros!$C$34-Parametros!$B$34)*100))) | H32: =IF(Input_Dados!K$32="","",MIN(100,MAX(0,(Parametros!$C$34-Input_Dados!K$32)/(Parametros!$C$34-Parametros!$B$34)*100))) | I32: =IF(Input_Dados!L$32="","",MIN(100,MAX(0,(Parametros!$C$34-Input_Dados!L$32)/(Parametros!$C$34-Parametros!$B$34)*100))) | J32: =IF(Input_Dados!M$32="","",MIN(100,MAX(0,(Parametros!$C$34-Input_Dados!M$32)/(Parametros!$C$34-Parametros!$B$34)*100))) | ... M32: =IF(Input_Dados!P$32="","",MIN(100,MAX(0,(Parametros!$C$34-Input_Dados!P$32)/(Parametros!$C$34-Parametros!$B$34)*100)))
A33: Desemprego Juvenil | B33: - | C33: =IF(Input_Dados!F$33="","",MIN(100,MAX(0,(Parametros!$C$35-Input_Dados!F$33)/(Parametros!$C$35-Parametros!$B$35)*100))) | D33: =IF(Input_Dados!G$33="","",MIN(100,MAX(0,(Parametros!$C$35-Input_Dados!G$33)/(Parametros!$C$35-Parametros!$B$35)*100))) | E33: =IF(Input_Dados!H$33="","",MIN(100,MAX(0,(Parametros!$C$35-Input_Dados!H$33)/(Parametros!$C$35-Parametros!$B$35)*100))) | F33: =IF(Input_Dados!I$33="","",MIN(100,MAX(0,(Parametros!$C$35-Input_Dados!I$33)/(Parametros!$C$35-Parametros!$B$35)*100))) | G33: =IF(Input_Dados!J$33="","",MIN(100,MAX(0,(Parametros!$C$35-Input_Dados!J$33)/(Parametros!$C$35-Parametros!$B$35)*100))) | H33: =IF(Input_Dados!K$33="","",MIN(100,MAX(0,(Parametros!$C$35-Input_Dados!K$33)/(Parametros!$C$35-Parametros!$B$35)*100))) | I33: =IF(Input_Dados!L$33="","",MIN(100,MAX(0,(Parametros!$C$35-Input_Dados!L$33)/(Parametros!$C$35-Parametros!$B$35)*100))) | J33: =IF(Input_Dados!M$33="","",MIN(100,MAX(0,(Parametros!$C$35-Input_Dados!M$33)/(Parametros!$C$35-Parametros!$B$35)*100))) | ... M33: =IF(Input_Dados!P$33="","",MIN(100,MAX(0,(Parametros!$C$35-Input_Dados!P$33)/(Parametros!$C$35-Parametros!$B$35)*100)))
A34: Emprego Informal (%) | B34: - | C34: =IF(Input_Dados!F$34="","",MIN(100,MAX(0,(Parametros!$C$36-Input_Dados!F$34)/(Parametros!$C$36-Parametros!$B$36)*100))) | D34: =IF(Input_Dados!G$34="","",MIN(100,MAX(0,(Parametros!$C$36-Input_Dados!G$34)/(Parametros!$C$36-Parametros!$B$36)*100))) | E34: =IF(Input_Dados!H$34="","",MIN(100,MAX(0,(Parametros!$C$36-Input_Dados!H$34)/(Parametros!$C$36-Parametros!$B$36)*100))) | F34: =IF(Input_Dados!I$34="","",MIN(100,MAX(0,(Parametros!$C$36-Input_Dados!I$34)/(Parametros!$C$36-Parametros!$B$36)*100))) | G34: =IF(Input_Dados!J$34="","",MIN(100,MAX(0,(Parametros!$C$36-Input_Dados!J$34)/(Parametros!$C$36-Parametros!$B$36)*100))) | H34: =IF(Input_Dados!K$34="","",MIN(100,MAX(0,(Parametros!$C$36-Input_Dados!K$34)/(Parametros!$C$36-Parametros!$B$36)*100))) | I34: =IF(Input_Dados!L$34="","",MIN(100,MAX(0,(Parametros!$C$36-Input_Dados!L$34)/(Parametros!$C$36-Parametros!$B$36)*100))) | J34: =IF(Input_Dados!M$34="","",MIN(100,MAX(0,(Parametros!$C$36-Input_Dados!M$34)/(Parametros!$C$36-Parametros!$B$36)*100))) | ... M34: =IF(Input_Dados!P$34="","",MIN(100,MAX(0,(Parametros!$C$36-Input_Dados!P$34)/(Parametros!$C$36-Parametros!$B$36)*100)))
A35: Taxa de Formalização | B35: + | C35: =IF(Input_Dados!F$35="","",MIN(100,MAX(0,(Input_Dados!F$35-Parametros!$B$37)/(Parametros!$C$37-Parametros!$B$37)*100))) | D35: =IF(Input_Dados!G$35="","",MIN(100,MAX(0,(Input_Dados!G$35-Parametros!$B$37)/(Parametros!$C$37-Parametros!$B$37)*100))) | E35: =IF(Input_Dados!H$35="","",MIN(100,MAX(0,(Input_Dados!H$35-Parametros!$B$37)/(Parametros!$C$37-Parametros!$B$37)*100))) | F35: =IF(Input_Dados!I$35="","",MIN(100,MAX(0,(Input_Dados!I$35-Parametros!$B$37)/(Parametros!$C$37-Parametros!$B$37)*100))) | G35: =IF(Input_Dados!J$35="","",MIN(100,MAX(0,(Input_Dados!J$35-Parametros!$B$37)/(Parametros!$C$37-Parametros!$B$37)*100))) | H35: =IF(Input_Dados!K$35="","",MIN(100,MAX(0,(Input_Dados!K$35-Parametros!$B$37)/(Parametros!$C$37-Parametros!$B$37)*100))) | I35: =IF(Input_Dados!L$35="","",MIN(100,MAX(0,(Input_Dados!L$35-Parametros!$B$37)/(Parametros!$C$37-Parametros!$B$37)*100))) | J35: =IF(Input_Dados!M$35="","",MIN(100,MAX(0,(Input_Dados!M$35-Parametros!$B$37)/(Parametros!$C$37-Parametros!$B$37)*100))) | ... M35: =IF(Input_Dados!P$35="","",MIN(100,MAX(0,(Input_Dados!P$35-Parametros!$B$37)/(Parametros!$C$37-Parametros!$B$37)*100)))
A36: Crescimento da Produtividade | B36: + | C36: =IF(Input_Dados!F$36="","",MIN(100,MAX(0,(Input_Dados!F$36-Parametros!$B$38)/(Parametros!$C$38-Parametros!$B$38)*100))) | D36: =IF(Input_Dados!G$36="","",MIN(100,MAX(0,(Input_Dados!G$36-Parametros!$B$38)/(Parametros!$C$38-Parametros!$B$38)*100))) | E36: =IF(Input_Dados!H$36="","",MIN(100,MAX(0,(Input_Dados!H$36-Parametros!$B$38)/(Parametros!$C$38-Parametros!$B$38)*100))) | F36: =IF(Input_Dados!I$36="","",MIN(100,MAX(0,(Input_Dados!I$36-Parametros!$B$38)/(Parametros!$C$38-Parametros!$B$38)*100))) | G36: =IF(Input_Dados!J$36="","",MIN(100,MAX(0,(Input_Dados!J$36-Parametros!$B$38)/(Parametros!$C$38-Parametros!$B$38)*100))) | H36: =IF(Input_Dados!K$36="","",MIN(100,MAX(0,(Input_Dados!K$36-Parametros!$B$38)/(Parametros!$C$38-Parametros!$B$38)*100))) | I36: =IF(Input_Dados!L$36="","",MIN(100,MAX(0,(Input_Dados!L$36-Parametros!$B$38)/(Parametros!$C$38-Parametros!$B$38)*100))) | J36: =IF(Input_Dados!M$36="","",MIN(100,MAX(0,(Input_Dados!M$36-Parametros!$B$38)/(Parametros!$C$38-Parametros!$B$38)*100))) | ... M36: =IF(Input_Dados!P$36="","",MIN(100,MAX(0,(Input_Dados!P$36-Parametros!$B$38)/(Parametros!$C$38-Parametros!$B$38)*100)))
A37: Índice Global Seg. Alimentar | B37: + | C37: =IF(Input_Dados!F$37="","",MIN(100,MAX(0,(Input_Dados!F$37-Parametros!$B$39)/(Parametros!$C$39-Parametros!$B$39)*100))) | D37: =IF(Input_Dados!G$37="","",MIN(100,MAX(0,(Input_Dados!G$37-Parametros!$B$39)/(Parametros!$C$39-Parametros!$B$39)*100))) | E37: =IF(Input_Dados!H$37="","",MIN(100,MAX(0,(Input_Dados!H$37-Parametros!$B$39)/(Parametros!$C$39-Parametros!$B$39)*100))) | F37: =IF(Input_Dados!I$37="","",MIN(100,MAX(0,(Input_Dados!I$37-Parametros!$B$39)/(Parametros!$C$39-Parametros!$B$39)*100))) | G37: =IF(Input_Dados!J$37="","",MIN(100,MAX(0,(Input_Dados!J$37-Parametros!$B$39)/(Parametros!$C$39-Parametros!$B$39)*100))) | H37: =IF(Input_Dados!K$37="","",MIN(100,MAX(0,(Input_Dados!K$37-Parametros!$B$39)/(Parametros!$C$39-Parametros!$B$39)*100))) | I37: =IF(Input_Dados!L$37="","",MIN(100,MAX(0,(Input_Dados!L$37-Parametros!$B$39)/(Parametros!$C$39-Parametros!$B$39)*100))) | J37: =IF(Input_Dados!M$37="","",MIN(100,MAX(0,(Input_Dados!M$37-Parametros!$B$39)/(Parametros!$C$39-Parametros!$B$39)*100))) | ... M37: =IF(Input_Dados!P$37="","",MIN(100,MAX(0,(Input_Dados!P$37-Parametros!$B$39)/(Parametros!$C$39-Parametros!$B$39)*100)))
A38: Prevalência de Desnutrição | B38: - | C38: =IF(Input_Dados!F$38="","",MIN(100,MAX(0,(Parametros!$C$40-Input_Dados!F$38)/(Parametros!$C$40-Parametros!$B$40)*100))) | D38: =IF(Input_Dados!G$38="","",MIN(100,MAX(0,(Parametros!$C$40-Input_Dados!G$38)/(Parametros!$C$40-Parametros!$B$40)*100))) | E38: =IF(Input_Dados!H$38="","",MIN(100,MAX(0,(Parametros!$C$40-Input_Dados!H$38)/(Parametros!$C$40-Parametros!$B$40)*100))) | F38: =IF(Input_Dados!I$38="","",MIN(100,MAX(0,(Parametros!$C$40-Input_Dados!I$38)/(Parametros!$C$40-Parametros!$B$40)*100))) | G38: =IF(Input_Dados!J$38="","",MIN(100,MAX(0,(Parametros!$C$40-Input_Dados!J$38)/(Parametros!$C$40-Parametros!$B$40)*100))) | H38: =IF(Input_Dados!K$38="","",MIN(100,MAX(0,(Parametros!$C$40-Input_Dados!K$38)/(Parametros!$C$40-Parametros!$B$40)*100))) | I38: =IF(Input_Dados!L$38="","",MIN(100,MAX(0,(Parametros!$C$40-Input_Dados!L$38)/(Parametros!$C$40-Parametros!$B$40)*100))) | J38: =IF(Input_Dados!M$38="","",MIN(100,MAX(0,(Parametros!$C$40-Input_Dados!M$38)/(Parametros!$C$40-Parametros!$B$40)*100))) | ... M38: =IF(Input_Dados!P$38="","",MIN(100,MAX(0,(Parametros!$C$40-Input_Dados!P$38)/(Parametros!$C$40-Parametros!$B$40)*100)))
A39: Mortalidade Materna (por 100k) | B39: - | C39: =IF(Input_Dados!F$39="","",MIN(100,MAX(0,(Parametros!$C$41-Input_Dados!F$39)/(Parametros!$C$41-Parametros!$B$41)*100))) | D39: =IF(Input_Dados!G$39="","",MIN(100,MAX(0,(Parametros!$C$41-Input_Dados!G$39)/(Parametros!$C$41-Parametros!$B$41)*100))) | E39: =IF(Input_Dados!H$39="","",MIN(100,MAX(0,(Parametros!$C$41-Input_Dados!H$39)/(Parametros!$C$41-Parametros!$B$41)*100))) | F39: =IF(Input_Dados!I$39="","",MIN(100,MAX(0,(Parametros!$C$41-Input_Dados!I$39)/(Parametros!$C$41-Parametros!$B$41)*100))) | G39: =IF(Input_Dados!J$39="","",MIN(100,MAX(0,(Parametros!$C$41-Input_Dados!J$39)/(Parametros!$C$41-Parametros!$B$41)*100))) | H39: =IF(Input_Dados!K$39="","",MIN(100,MAX(0,(Parametros!$C$41-Input_Dados!K$39)/(Parametros!$C$41-Parametros!$B$41)*100))) | I39: =IF(Input_Dados!L$39="","",MIN(100,MAX(0,(Parametros!$C$41-Input_Dados!L$39)/(Parametros!$C$41-Parametros!$B$41)*100))) | J39: =IF(Input_Dados!M$39="","",MIN(100,MAX(0,(Parametros!$C$41-Input_Dados!M$39)/(Parametros!$C$41-Parametros!$B$41)*100))) | ... M39: =IF(Input_Dados!P$39="","",MIN(100,MAX(0,(Parametros!$C$41-Input_Dados!P$39)/(Parametros!$C$41-Parametros!$B$41)*100)))
A40: Despesas Saúde (% PIB) | B40: + | C40: =IF(Input_Dados!F$40="","",MIN(100,MAX(0,(Input_Dados!F$40-Parametros!$B$42)/(Parametros!$C$42-Parametros!$B$42)*100))) | D40: =IF(Input_Dados!G$40="","",MIN(100,MAX(0,(Input_Dados!G$40-Parametros!$B$42)/(Parametros!$C$42-Parametros!$B$42)*100))) | E40: =IF(Input_Dados!H$40="","",MIN(100,MAX(0,(Input_Dados!H$40-Parametros!$B$42)/(Parametros!$C$42-Parametros!$B$42)*100))) | F40: =IF(Input_Dados!I$40="","",MIN(100,MAX(0,(Input_Dados!I$40-Parametros!$B$42)/(Parametros!$C$42-Parametros!$B$42)*100))) | G40: =IF(Input_Dados!J$40="","",MIN(100,MAX(0,(Input_Dados!J$40-Parametros!$B$42)/(Parametros!$C$42-Parametros!$B$42)*100))) | H40: =IF(Input_Dados!K$40="","",MIN(100,MAX(0,(Input_Dados!K$40-Parametros!$B$42)/(Parametros!$C$42-Parametros!$B$42)*100))) | I40: =IF(Input_Dados!L$40="","",MIN(100,MAX(0,(Input_Dados!L$40-Parametros!$B$42)/(Parametros!$C$42-Parametros!$B$42)*100))) | J40: =IF(Input_Dados!M$40="","",MIN(100,MAX(0,(Input_Dados!M$40-Parametros!$B$42)/(Parametros!$C$42-Parametros!$B$42)*100))) | ... M40: =IF(Input_Dados!P$40="","",MIN(100,MAX(0,(Input_Dados!P$40-Parametros!$B$42)/(Parametros!$C$42-Parametros!$B$42)*100)))
A41: Camas Hospitalares (por 1000) | B41: + | C41: =IF(Input_Dados!F$41="","",MIN(100,MAX(0,(Input_Dados!F$41-Parametros!$B$43)/(Parametros!$C$43-Parametros!$B$43)*100))) | D41: =IF(Input_Dados!G$41="","",MIN(100,MAX(0,(Input_Dados!G$41-Parametros!$B$43)/(Parametros!$C$43-Parametros!$B$43)*100))) | E41: =IF(Input_Dados!H$41="","",MIN(100,MAX(0,(Input_Dados!H$41-Parametros!$B$43)/(Parametros!$C$43-Parametros!$B$43)*100))) | F41: =IF(Input_Dados!I$41="","",MIN(100,MAX(0,(Input_Dados!I$41-Parametros!$B$43)/(Parametros!$C$43-Parametros!$B$43)*100))) | G41: =IF(Input_Dados!J$41="","",MIN(100,MAX(0,(Input_Dados!J$41-Parametros!$B$43)/(Parametros!$C$43-Parametros!$B$43)*100))) | H41: =IF(Input_Dados!K$41="","",MIN(100,MAX(0,(Input_Dados!K$41-Parametros!$B$43)/(Parametros!$C$43-Parametros!$B$43)*100))) | I41: =IF(Input_Dados!L$41="","",MIN(100,MAX(0,(Input_Dados!L$41-Parametros!$B$43)/(Parametros!$C$43-Parametros!$B$43)*100))) | J41: =IF(Input_Dados!M$41="","",MIN(100,MAX(0,(Input_Dados!M$41-Parametros!$B$43)/(Parametros!$C$43-Parametros!$B$43)*100))) | ... M41: =IF(Input_Dados!P$41="","",MIN(100,MAX(0,(Input_Dados!P$41-Parametros!$B$43)/(Parametros!$C$43-Parametros!$B$43)*100)))
A42: Cobertura Vacinal (%) | B42: + | C42: =IF(Input_Dados!F$42="","",MIN(100,MAX(0,(Input_Dados!F$42-Parametros!$B$44)/(Parametros!$C$44-Parametros!$B$44)*100))) | D42: =IF(Input_Dados!G$42="","",MIN(100,MAX(0,(Input_Dados!G$42-Parametros!$B$44)/(Parametros!$C$44-Parametros!$B$44)*100))) | E42: =IF(Input_Dados!H$42="","",MIN(100,MAX(0,(Input_Dados!H$42-Parametros!$B$44)/(Parametros!$C$44-Parametros!$B$44)*100))) | F42: =IF(Input_Dados!I$42="","",MIN(100,MAX(0,(Input_Dados!I$42-Parametros!$B$44)/(Parametros!$C$44-Parametros!$B$44)*100))) | G42: =IF(Input_Dados!J$42="","",MIN(100,MAX(0,(Input_Dados!J$42-Parametros!$B$44)/(Parametros!$C$44-Parametros!$B$44)*100))) | H42: =IF(Input_Dados!K$42="","",MIN(100,MAX(0,(Input_Dados!K$42-Parametros!$B$44)/(Parametros!$C$44-Parametros!$B$44)*100))) | I42: =IF(Input_Dados!L$42="","",MIN(100,MAX(0,(Input_Dados!L$42-Parametros!$B$44)/(Parametros!$C$44-Parametros!$B$44)*100))) | J42: =IF(Input_Dados!M$42="","",MIN(100,MAX(0,(Input_Dados!M$42-Parametros!$B$44)/(Parametros!$C$44-Parametros!$B$44)*100))) | ... M42: =IF(Input_Dados!P$42="","",MIN(100,MAX(0,(Input_Dados!P$42-Parametros!$B$44)/(Parametros!$C$44-Parametros!$B$44)*100)))

Sheet Subindices
A1: Subíndice | B1: 2015 | C1: 2016 | D1: 2017 | E1: 2018 | F1: 2019 | G1: 2020 | H1: 2021 | I1: 2022 | J1: 2023 | K1: 2024 | L1: 2025
A2: 1. Governança e Estado de Direito | B2: =IF(SUMPRODUCT((Normalizacao!C$2:C$6<>"")*1)<Parametros!$B$46*5,"",SUMPRODUCT(IFERROR(Normalizacao!C$2:C$6*Parametros!$E$4:$E$8,0))/SUMPRODUCT((Normalizacao!C$2:C$6<>"")*Parametros!$E$4:$E$8)) | C2: =IF(SUMPRODUCT((Normalizacao!D$2:D$6<>"")*1)<Parametros!$B$46*5,"",SUMPRODUCT(IFERROR(Normalizacao!D$2:D$6*Parametros!$E$4:$E$8,0))/SUMPRODUCT((Normalizacao!D$2:D$6<>"")*Parametros!$E$4:$E$8)) | D2: =IF(SUMPRODUCT((Normalizacao!E$2:E$6<>"")*1)<Parametros!$B$46*5,"",SUMPRODUCT(IFERROR(Normalizacao!E$2:E$6*Parametros!$E$4:$E$8,0))/SUMPRODUCT((Normalizacao!E$2:E$6<>"")*Parametros!$E$4:$E$8)) | E2: =IF(SUMPRODUCT((Normalizacao!F$2:F$6<>"")*1)<Parametros!$B$46*5,"",SUMPRODUCT(IFERROR(Normalizacao!F$2:F$6*Parametros!$E$4:$E$8,0))/SUMPRODUCT((Normalizacao!F$2:F$6<>"")*Parametros!$E$4:$E$8)) | F2: =IF(SUMPRODUCT((Normalizacao!G$2:G$6<>"")*1)<Parametros!$B$46*5,"",SUMPRODUCT(IFERROR(Normalizacao!G$2:G$6*Parametros!$E$4:$E$8,0))/SUMPRODUCT((Normalizacao!G$2:G$6<>"")*Parametros!$E$4:$E$8)) | G2: =IF(SUMPRODUCT((Normalizacao!H$2:H$6<>"")*1)<Parametros!$B$46*5,"",SUMPRODUCT(IFERROR(Normalizacao!H$2:H$6*Parametros!$E$4:$E$8,0))/SUMPRODUCT((Normalizacao!H$2:H$6<>"")*Parametros!$E$4:$E$8)) | H2: =IF(SUMPRODUCT((Normalizacao!I$2:I$6<>"")*1)<Parametros!$B$46*5,"",SUMPRODUCT(IFERROR(Normalizacao!I$2:I$6*Parametros!$E$4:$E$8,0))/SUMPRODUCT((Normalizacao!I$2:I$6<>"")*Parametros!$E$4:$E$8)) | I2: =IF(SUMPRODUCT((Normalizacao!J$2:J$6<>"")*1)<Parametros!$B$46*5,"",SUMPRODUCT(IFERROR(Normalizacao!J$2:J$6*Parametros!$E$4:$E$8,0))/SUMPRODUCT((Normalizacao!J$2:J$6<>"")*Parametros!$E$4:$E$8)) | ... L2: =IF(SUMPRODUCT((Normalizacao!M$2:M$6<>"")*1)<Parametros!$B$46*5,"",SUMPRODUCT(IFERROR(Normalizacao!M$2:M$6*Parametros!$E$4:$E$8,0))/SUMPRODUCT((Normalizacao!M$2:M$6<>"")*Parametros!$E$4:$E$8))
A3: 2. Estabilidade Macroeconómica | B3: =IF(SUMPRODUCT((Normalizacao!C$7:C$13<>"")*1)<Parametros!$B$46*7,"",SUMPRODUCT(IFERROR(Normalizacao!C$7:C$13*Parametros!$E$9:$E$15,0))/SUMPRODUCT((Normalizacao!C$7:C$13<>"")*Parametros!$E$9:$E$15)) | C3: =IF(SUMPRODUCT((Normalizacao!D$7:D$13<>"")*1)<Parametros!$B$46*7,"",SUMPRODUCT(IFERROR(Normalizacao!D$7:D$13*Parametros!$E$9:$E$15,0))/SUMPRODUCT((Normalizacao!D$7:D$13<>"")*Parametros!$E$9:$E$15)) | D3: =IF(SUMPRODUCT((Normalizacao!E$7:E$13<>"")*1)<Parametros!$B$46*7,"",SUMPRODUCT(IFERROR(Normalizacao!E$7:E$13*Parametros!$E$9:$E$15,0))/SUMPRODUCT((Normalizacao!E$7:E$13<>"")*Parametros!$E$9:$E$15)) | E3: =IF(SUMPRODUCT((Normalizacao!F$7:F$13<>"")*1)<Parametros!$B$46*7,"",SUMPRODUCT(IFERROR(Normalizacao!F$7:F$13*Parametros!$E$9:$E$15,0))/SUMPRODUCT((Normalizacao!F$7:F$13<>"")*Parametros!$E$9:$E$15)) | F3: =IF(SUMPRODUCT((Normalizacao!G$7:G$13<>"")*1)<Parametros!$B$46*7,"",SUMPRODUCT(IFERROR(Normalizacao!G$7:G$13*Parametros!$E$9:$E$15,0))/SUMPRODUCT((Normalizacao!G$7:G$13<>"")*Parametros!$E$9:$E$15)) | G3: =IF(SUMPRODUCT((Normalizacao!H$7:H$13<>"")*1)<Parametros!$B$46*7,"",SUMPRODUCT(IFERROR(Normalizacao!H$7:H$13*Parametros!$E$9:$E$15,0))/SUMPRODUCT((Normalizacao!H$7:H$13<>"")*Parametros!$E$9:$E$15)) | H3: =IF(SUMPRODUCT((Normalizacao!I$7:I$13<>"")*1)<Parametros!$B$46*7,"",SUMPRODUCT(IFERROR(Normalizacao!I$7:I$13*Parametros!$E$9:$E$15,0))/SUMPRODUCT((Normalizacao!I$7:I$13<>"")*Parametros!$E$9:$E$15)) | I3: =IF(SUMPRODUCT((Normalizacao!J$7:J$13<>"")*1)<Parametros!$B$46*7,"",SUMPRODUCT(IFERROR(Normalizacao!J$7:J$13*Parametros!$E$9:$E$15,0))/SUMPRODUCT((Normalizacao!J$7:J$13<>"")*Parametros!$E$9:$E$15)) | ... L3: =IF(SUMPRODUCT((Normalizacao!M$7:M$13<>"")*1)<Parametros!$B$46*7,"",SUMPRODUCT(IFERROR(Normalizacao!M$7:M$13*Parametros!$E$9:$E$15,0))/SUMPRODUCT((Normalizacao!M$7:M$13<>"")*Parametros!$E$9:$E$15))
A4: 3. Capital Humano | B4: =IF(SUMPRODUCT((Normalizacao!C$14:C$19<>"")*1)<Parametros!$B$46*6,"",SUMPRODUCT(IFERROR(Normalizacao!C$14:C$19*Parametros!$E$16:$E$21,0))/SUMPRODUCT((Normalizacao!C$14:C$19<>"")*Parametros!$E$16:$E$21)) | C4: =IF(SUMPRODUCT((Normalizacao!D$14:D$19<>"")*1)<Parametros!$B$46*6,"",SUMPRODUCT(IFERROR(Normalizacao!D$14:D$19*Parametros!$E$16:$E$21,0))/SUMPRODUCT((Normalizacao!D$14:D$19<>"")*Parametros!$E$16:$E$21)) | D4: =IF(SUMPRODUCT((Normalizacao!E$14:E$19<>"")*1)<Parametros!$B$46*6,"",SUMPRODUCT(IFERROR(Normalizacao!E$14:E$19*Parametros!$E$16:$E$21,0))/SUMPRODUCT((Normalizacao!E$14:E$19<>"")*Parametros!$E$16:$E$21)) | E4: =IF(SUMPRODUCT((Normalizacao!F$14:F$19<>"")*1)<Parametros!$B$46*6,"",SUMPRODUCT(IFERROR(Normalizacao!F$14:F$19*Parametros!$E$16:$E$21,0))/SUMPRODUCT((Normalizacao!F$14:F$19<>"")*Parametros!$E$16:$E$21)) | F4: =IF(SUMPRODUCT((Normalizacao!G$14:G$19<>"")*1)<Parametros!$B$46*6,"",SUMPRODUCT(IFERROR(Normalizacao!G$14:G$19*Parametros!$E$16:$E$21,0))/SUMPRODUCT((Normalizacao!G$14:G$19<>"")*Parametros!$E$16:$E$21)) | G4: =IF(SUMPRODUCT((Normalizacao!H$14:H$19<>"")*1)<Parametros!$B$46*6,"",SUMPRODUCT(IFERROR(Normalizacao!H$14:H$19*Parametros!$E$16:$E$21,0))/SUMPRODUCT((Normalizacao!H$14:H$19<>"")*Parametros!$E$16:$E$21)) | H4: =IF(SUMPRODUCT((Normalizacao!I$14:I$19<>"")*1)<Parametros!$B$46*6,"",SUMPRODUCT(IFERROR(Normalizacao!I$14:I$19*Parametros!$E$16:$E$21,0))/SUMPRODUCT((Normalizacao!I$14:I$19<>"")*Parametros!$E$16:$E$21)) | I4: =IF(SUMPRODUCT((Normalizacao!J$14:J$19<>"")*1)<Parametros!$B$46*6,"",SUMPRODUCT(IFERROR(Normalizacao!J$14:J$19*Parametros!$E$16:$E$21,0))/SUMPRODUCT((Normalizacao!J$14:J$19<>"")*Parametros!$E$16:$E$21)) | ... L4: =IF(SUMPRODUCT((Normalizacao!M$14:M$19<>"")*1)<Parametros!$B$46*6,"",SUMPRODUCT(IFERROR(Normalizacao!M$14:M$19*Parametros!$E$16:$E$21,0))/SUMPRODUCT((Normalizacao!M$14:M$19<>"")*Parametros!$E$16:$E$21))
A5: 4. Inclusão Social e Protecção | B5: =IF(SUMPRODUCT((Normalizacao!C$20:C$24<>"")*1)<Parametros!$B$46*5,"",SUMPRODUCT(IFERROR(Normalizacao!C$20:C$24*Parametros!$E$22:$E$26,0))/SUMPRODUCT((Normalizacao!C$20:C$24<>"")*Parametros!$E$22:$E$26)) | C5: =IF(SUMPRODUCT((Normalizacao!D$20:D$24<>"")*1)<Parametros!$B$46*5,"",SUMPRODUCT(IFERROR(Normalizacao!D$20:D$24*Parametros!$E$22:$E$26,0))/SUMPRODUCT((Normalizacao!D$20:D$24<>"")*Parametros!$E$22:$E$26)) | D5: =IF(SUMPRODUCT((Normalizacao!E$20:E$24<>"")*1)<Parametros!$B$46*5,"",SUMPRODUCT(IFERROR(Normalizacao!E$20:E$24*Parametros!$E$22:$E$26,0))/SUMPRODUCT((Normalizacao!E$20:E$24<>"")*Parametros!$E$22:$E$26)) | E5: =IF(SUMPRODUCT((Normalizacao!F$20:F$24<>"")*1)<Parametros!$B$46*5,"",SUMPRODUCT(IFERROR(Normalizacao!F$20:F$24*Parametros!$E$22:$E$26,0))/SUMPRODUCT((Normalizacao!F$20:F$24<>"")*Parametros!$E$22:$E$26)) | F5: =IF(SUMPRODUCT((Normalizacao!G$20:G$24<>"")*1)<Parametros!$B$46*5,"",SUMPRODUCT(IFERROR(Normalizacao!G$20:G$24*Parametros!$E$22:$E$26,0))/SUMPRODUCT((Normalizacao!G$20:G$24<>"")*Parametros!$E$22:$E$26)) | G5: =IF(SUMPRODUCT((Normalizacao!H$20:H$24<>"")*1)<Parametros!$B$46*5,"",SUMPRODUCT(IFERROR(Normalizacao!H$20:H$24*Parametros!$E$22:$E$26,0))/SUMPRODUCT((Normalizacao!H$20:H$24<>"")*Parametros!$E$22:$E$26)) | H5: =IF(SUMPRODUCT((Normalizacao!I$20:I$24<>"")*1)<Parametros!$B$46*5,"",SUMPRODUCT(IFERROR(Normalizacao!I$20:I$24*Parametros!$E$22:$E$26,0))/SUMPRODUCT((Normalizacao!I$20:I$24<>"")*Parametros!$E$22:$E$26)) | I5: =IF(SUMPRODUCT((Normalizacao!J$20:J$24<>"")*1)<Parametros!$B$46*5,"",SUMPRODUCT(IFERROR(Normalizacao!J$20:J$24*Parametros!$E$22:$E$26,0))/SUMPRODUCT((Normalizacao!J$20:J$24<>"")*Parametros!$E$22:$E$26)) | ... L5: =IF(SUMPRODUCT((Normalizacao!M$20:M$24<>"")*1)<Parametros!$B$46*5,"",SUMPRODUCT(IFERROR(Normalizacao!M$20:M$24*Parametros!$E$22:$E$26,0))/SUMPRODUCT((Normalizacao!M$20:M$24<>"")*Parametros!$E$22:$E$26))
A6: 5. Infraestruturas e Serviços | B6: =IF(SUMPRODUCT((Normalizacao!C$25:C$30<>"")*1)<Parametros!$B$46*6,"",SUMPRODUCT(IFERROR(Normalizacao!C$25:C$30*Parametros!$E$27:$E$32,0))/SUMPRODUCT((Normalizacao!C$25:C$30<>"")*Parametros!$E$27:$E$32)) | C6: =IF(SUMPRODUCT((Normalizacao!D$25:D$30<>"")*1)<Parametros!$B$46*6,"",SUMPRODUCT(IFERROR(Normalizacao!D$25:D$30*Parametros!$E$27:$E$32,0))/SUMPRODUCT((Normalizacao!D$25:D$30<>"")*Parametros!$E$27:$E$32)) | D6: =IF(SUMPRODUCT((Normalizacao!E$25:E$30<>"")*1)<Parametros!$B$46*6,"",SUMPRODUCT(IFERROR(Normalizacao!E$25:E$30*Parametros!$E$27:$E$32,0))/SUMPRODUCT((Normalizacao!E$25:E$30<>"")*Parametros!$E$27:$E$32)) | E6: =IF(SUMPRODUCT((Normalizacao!F$25:F$30<>"")*1)<Parametros!$B$46*6,"",SUMPRODUCT(IFERROR(Normalizacao!F$25:F$30*Parametros!$E$27:$E$32,0))/SUMPRODUCT((Normalizacao!F$25:F$30<>"")*Parametros!$E$27:$E$32)) | F6: =IF(SUMPRODUCT((Normalizacao!G$25:G$30<>"")*1)<Parametros!$B$46*6,"",SUMPRODUCT(IFERROR(Normalizacao!G$25:G$30*Parametros!$E$27:$E$32,0))/SUMPRODUCT((Normalizacao!G$25:G$30<>"")*Parametros!$E$27:$E$32)) | G6: =IF(SUMPRODUCT((Normalizacao!H$25:H$30<>"")*1)<Parametros!$B$46*6,"",SUMPRODUCT(IFERROR(Normalizacao!H$25:H$30*Parametros!$E$27:$E$32,0))/SUMPRODUCT((Normalizacao!H$25:H$30<>"")*Parametros!$E$27:$E$32)) | H6: =IF(SUMPRODUCT((Normalizacao!I$25:I$30<>"")*1)<Parametros!$B$46*6,"",SUMPRODUCT(IFERROR(Normalizacao!I$25:I$30*Parametros!$E$27:$E$32,0))/SUMPRODUCT((Normalizacao!I$25:I$30<>"")*Parametros!$E$27:$E$32)) | I6: =IF(SUMPRODUCT((Normalizacao!J$25:J$30<>"")*1)<Parametros!$B$46*6,"",SUMPRODUCT(IFERROR(Normalizacao!J$25:J$30*Parametros!$E$27:$E$32,0))/SUMPRODUCT((Normalizacao!J$25:J$30<>"")*Parametros!$E$27:$E$32)) | ... L6: =IF(SUMPRODUCT((Normalizacao!M$25:M$30<>"")*1)<Parametros!$B$46*6,"",SUMPRODUCT(IFERROR(Normalizacao!M$25:M$30*Parametros!$E$27:$E$32,0))/SUMPRODUCT((Normalizacao!M$25:M$30<>"")*Parametros!$E$27:$E$32))
A7: 6. Mercado de Trabalho | B7: =IF(SUMPRODUCT((Normalizacao!C$31:C$36<>"")*1)<Parametros!$B$46*6,"",SUMPRODUCT(IFERROR(Normalizacao!C$31:C$36*Parametros!$E$33:$E$38,0))/SUMPRODUCT((Normalizacao!C$31:C$36<>"")*Parametros!$E$33:$E$38)) | C7: =IF(SUMPRODUCT((Normalizacao!D$31:D$36<>"")*1)<Parametros!$B$46*6,"",SUMPRODUCT(IFERROR(Normalizacao!D$31:D$36*Parametros!$E$33:$E$38,0))/SUMPRODUCT((Normalizacao!D$31:D$36<>"")*Parametros!$E$33:$E$38)) | D7: =IF(SUMPRODUCT((Normalizacao!E$31:E$36<>"")*1)<Parametros!$B$46*6,"",SUMPRODUCT(IFERROR(Normalizacao!E$31:E$36*Parametros!$E$33:$E$38,0))/SUMPRODUCT((Normalizacao!E$31:E$36<>"")*Parametros!$E$33:$E$38)) | E7: =IF(SUMPRODUCT((Normalizacao!F$31:F$36<>"")*1)<Parametros!$B$46*6,"",SUMPRODUCT(IFERROR(Normalizacao!F$31:F$36*Parametros!$E$33:$E$38,0))/SUMPRODUCT((Normalizacao!F$31:F$36<>"")*Parametros!$E$33:$E$38)) | F7: =IF(SUMPRODUCT((Normalizacao!G$31:G$36<>"")*1)<Parametros!$B$46*6,"",SUMPRODUCT(IFERROR(Normalizacao!G$31:G$36*Parametros!$E$33:$E$38,0))/SUMPRODUCT((Normalizacao!G$31:G$36<>"")*Parametros!$E$33:$E$38)) | G7: =IF(SUMPRODUCT((Normalizacao!H$31:H$36<>"")*1)<Parametros!$B$46*6,"",SUMPRODUCT(IFERROR(Normalizacao!H$31:H$36*Parametros!$E$33:$E$38,0))/SUMPRODUCT((Normalizacao!H$31:H$36<>"")*Parametros!$E$33:$E$38)) | H7: =IF(SUMPRODUCT((Normalizacao!I$31:I$36<>"")*1)<Parametros!$B$46*6,"",SUMPRODUCT(IFERROR(Normalizacao!I$31:I$36*Parametros!$E$33:$E$38,0))/SUMPRODUCT((Normalizacao!I$31:I$36<>"")*Parametros!$E$33:$E$38)) | I7: =IF(SUMPRODUCT((Normalizacao!J$31:J$36<>"")*1)<Parametros!$B$46*6,"",SUMPRODUCT(IFERROR(Normalizacao!J$31:J$36*Parametros!$E$33:$E$38,0))/SUMPRODUCT((Normalizacao!J$31:J$36<>"")*Parametros!$E$33:$E$38)) | ... L7: =IF(SUMPRODUCT((Normalizacao!M$31:M$36<>"")*1)<Parametros!$B$46*6,"",SUMPRODUCT(IFERROR(Normalizacao!M$31:M$36*Parametros!$E$33:$E$38,0))/SUMPRODUCT((Normalizacao!M$31:M$36<>"")*Parametros!$E$33:$E$38))
A8: 7. Segurança Alimentar e Saúde | B8: =IF(SUMPRODUCT((Normalizacao!C$37:C$42<>"")*1)<Parametros!$B$46*6,"",SUMPRODUCT(IFERROR(Normalizacao!C$37:C$42*Parametros!$E$39:$E$44,0))/SUMPRODUCT((Normalizacao!C$37:C$42<>"")*Parametros!$E$39:$E$44)) | C8: =IF(SUMPRODUCT((Normalizacao!D$37:D$42<>"")*1)<Parametros!$B$46*6,"",SUMPRODUCT(IFERROR(Normalizacao!D$37:D$42*Parametros!$E$39:$E$44,0))/SUMPRODUCT((Normalizacao!D$37:D$42<>"")*Parametros!$E$39:$E$44)) | D8: =IF(SUMPRODUCT((Normalizacao!E$37:E$42<>"")*1)<Parametros!$B$46*6,"",SUMPRODUCT(IFERROR(Normalizacao!E$37:E$42*Parametros!$E$39:$E$44,0))/SUMPRODUCT((Normalizacao!E$37:E$42<>"")*Parametros!$E$39:$E$44)) | E8: =IF(SUMPRODUCT((Normalizacao!F$37:F$42<>"")*1)<Parametros!$B$46*6,"",SUMPRODUCT(IFERROR(Normalizacao!F$37:F$42*Parametros!$E$39:$E$44,0))/SUMPRODUCT((Normalizacao!F$37:F$42<>"")*Parametros!$E$39:$E$44)) | F8: =IF(SUMPRODUCT((Normalizacao!G$37:G$42<>"")*1)<Parametros!$B$46*6,"",SUMPRODUCT(IFERROR(Normalizacao!G$37:G$42*Parametros!$E$39:$E$44,0))/SUMPRODUCT((Normalizacao!G$37:G$42<>"")*Parametros!$E$39:$E$44)) | G8: =IF(SUMPRODUCT((Normalizacao!H$37:H$42<>"")*1)<Parametros!$B$46*6,"",SUMPRODUCT(IFERROR(Normalizacao!H$37:H$42*Parametros!$E$39:$E$44,0))/SUMPRODUCT((Normalizacao!H$37:H$42<>"")*Parametros!$E$39:$E$44)) | H8: =IF(SUMPRODUCT((Normalizacao!I$37:I$42<>"")*1)<Parametros!$B$46*6,"",SUMPRODUCT(IFERROR(Normalizacao!I$37:I$42*Parametros!$E$39:$E$44,0))/SUMPRODUCT((Normalizacao!I$37:I$42<>"")*Parametros!$E$39:$E$44)) | I8: =IF(SUMPRODUCT((Normalizacao!J$37:J$42<>"")*1)<Parametros!$B$46*6,"",SUMPRODUCT(IFERROR(Normalizacao!J$37:J$42*Parametros!$E$39:$E$44,0))/SUMPRODUCT((Normalizacao!J$37:J$42<>"")*Parametros!$E$39:$E$44)) | ... L8: =IF(SUMPRODUCT((Normalizacao!M$37:M$42<>"")*1)<Parametros!$B$46*6,"",SUMPRODUCT(IFERROR(Normalizacao!M$37:M$42*Parametros!$E$39:$E$44,0))/SUMPRODUCT((Normalizacao!M$37:M$42<>"")*Parametros!$E$39:$E$44))
A10: DIAGNÓSTICO DE COBERTURA (nº de indicadores com dados / total)
A11: Subíndice | B11: 2015 | C11: 2016 | D11: 2017 | E11: 2018 | F11: 2019 | G11: 2020 | H11: 2021 | I11: 2022 | J11: 2023 | K11: 2024 | L11: 2025
A12: 1. Governança e Estado de Direito | B12: =SUMPRODUCT((Normalizacao!C$2:C$6<>"")*1)&"/5" | C12: =SUMPRODUCT((Normalizacao!D$2:D$6<>"")*1)&"/5" | D12: =SUMPRODUCT((Normalizacao!E$2:E$6<>"")*1)&"/5" | E12: =SUMPRODUCT((Normalizacao!F$2:F$6<>"")*1)&"/5" | F12: =SUMPRODUCT((Normalizacao!G$2:G$6<>"")*1)&"/5" | G12: =SUMPRODUCT((Normalizacao!H$2:H$6<>"")*1)&"/5" | H12: =SUMPRODUCT((Normalizacao!I$2:I$6<>"")*1)&"/5" | I12: =SUMPRODUCT((Normalizacao!J$2:J$6<>"")*1)&"/5" | ... L12: =SUMPRODUCT((Normalizacao!M$2:M$6<>"")*1)&"/5"
A13: 2. Estabilidade Macroeconómica | B13: =SUMPRODUCT((Normalizacao!C$7:C$13<>"")*1)&"/7" | C13: =SUMPRODUCT((Normalizacao!D$7:D$13<>"")*1)&"/7" | D13: =SUMPRODUCT((Normalizacao!E$7:E$13<>"")*1)&"/7" | E13: =SUMPRODUCT((Normalizacao!F$7:F$13<>"")*1)&"/7" | F13: =SUMPRODUCT((Normalizacao!G$7:G$13<>"")*1)&"/7" | G13: =SUMPRODUCT((Normalizacao!H$7:H$13<>"")*1)&"/7" | H13: =SUMPRODUCT((Normalizacao!I$7:I$13<>"")*1)&"/7" | I13: =SUMPRODUCT((Normalizacao!J$7:J$13<>"")*1)&"/7" | ... L13: =SUMPRODUCT((Normalizacao!M$7:M$13<>"")*1)&"/7"
A14: 3. Capital Humano | B14: =SUMPRODUCT((Normalizacao!C$14:C$19<>"")*1)&"/6" | C14: =SUMPRODUCT((Normalizacao!D$14:D$19<>"")*1)&"/6" | D14: =SUMPRODUCT((Normalizacao!E$14:E$19<>"")*1)&"/6" | E14: =SUMPRODUCT((Normalizacao!F$14:F$19<>"")*1)&"/6" | F14: =SUMPRODUCT((Normalizacao!G$14:G$19<>"")*1)&"/6" | G14: =SUMPRODUCT((Normalizacao!H$14:H$19<>"")*1)&"/6" | H14: =SUMPRODUCT((Normalizacao!I$14:I$19<>"")*1)&"/6" | I14: =SUMPRODUCT((Normalizacao!J$14:J$19<>"")*1)&"/6" | ... L14: =SUMPRODUCT((Normalizacao!M$14:M$19<>"")*1)&"/6"
A15: 4. Inclusão Social e Protecção | B15: =SUMPRODUCT((Normalizacao!C$20:C$24<>"")*1)&"/5" | C15: =SUMPRODUCT((Normalizacao!D$20:D$24<>"")*1)&"/5" | D15: =SUMPRODUCT((Normalizacao!E$20:E$24<>"")*1)&"/5" | E15: =SUMPRODUCT((Normalizacao!F$20:F$24<>"")*1)&"/5" | F15: =SUMPRODUCT((Normalizacao!G$20:G$24<>"")*1)&"/5" | G15: =SUMPRODUCT((Normalizacao!H$20:H$24<>"")*1)&"/5" | H15: =SUMPRODUCT((Normalizacao!I$20:I$24<>"")*1)&"/5" | I15: =SUMPRODUCT((Normalizacao!J$20:J$24<>"")*1)&"/5" | ... L15: =SUMPRODUCT((Normalizacao!M$20:M$24<>"")*1)&"/5"
A16: 5. Infraestruturas e Serviços | B16: =SUMPRODUCT((Normalizacao!C$25:C$30<>"")*1)&"/6" | C16: =SUMPRODUCT((Normalizacao!D$25:D$30<>"")*1)&"/6" | D16: =SUMPRODUCT((Normalizacao!E$25:E$30<>"")*1)&"/6" | E16: =SUMPRODUCT((Normalizacao!F$25:F$30<>"")*1)&"/6" | F16: =SUMPRODUCT((Normalizacao!G$25:G$30<>"")*1)&"/6" | G16: =SUMPRODUCT((Normalizacao!H$25:H$30<>"")*1)&"/6" | H16: =SUMPRODUCT((Normalizacao!I$25:I$30<>"")*1)&"/6" | I16: =SUMPRODUCT((Normalizacao!J$25:J$30<>"")*1)&"/6" | ... L16: =SUMPRODUCT((Normalizacao!M$25:M$30<>"")*1)&"/6"
A17: 6. Mercado de Trabalho | B17: =SUMPRODUCT((Normalizacao!C$31:C$36<>"")*1)&"/6" | C17: =SUMPRODUCT((Normalizacao!D$31:D$36<>"")*1)&"/6" | D17: =SUMPRODUCT((Normalizacao!E$31:E$36<>"")*1)&"/6" | E17: =SUMPRODUCT((Normalizacao!F$31:F$36<>"")*1)&"/6" | F17: =SUMPRODUCT((Normalizacao!G$31:G$36<>"")*1)&"/6" | G17: =SUMPRODUCT((Normalizacao!H$31:H$36<>"")*1)&"/6" | H17: =SUMPRODUCT((Normalizacao!I$31:I$36<>"")*1)&"/6" | I17: =SUMPRODUCT((Normalizacao!J$31:J$36<>"")*1)&"/6" | ... L17: =SUMPRODUCT((Normalizacao!M$31:M$36<>"")*1)&"/6"
A18: 7. Segurança Alimentar e Saúde | B18: =SUMPRODUCT((Normalizacao!C$37:C$42<>"")*1)&"/6" | C18: =SUMPRODUCT((Normalizacao!D$37:D$42<>"")*1)&"/6" | D18: =SUMPRODUCT((Normalizacao!E$37:E$42<>"")*1)&"/6" | E18: =SUMPRODUCT((Normalizacao!F$37:F$42<>"")*1)&"/6" | F18: =SUMPRODUCT((Normalizacao!G$37:G$42<>"")*1)&"/6" | G18: =SUMPRODUCT((Normalizacao!H$37:H$42<>"")*1)&"/6" | H18: =SUMPRODUCT((Normalizacao!I$37:I$42<>"")*1)&"/6" | I18: =SUMPRODUCT((Normalizacao!J$37:J$42<>"")*1)&"/6" | ... L18: =SUMPRODUCT((Normalizacao!M$37:M$42<>"")*1)&"/6"
A20: Subíndices com dados (de 7) | B20: =SUMPRODUCT((B2:B8<>"")*1) | C20: =SUMPRODUCT((C2:C8<>"")*1) | D20: =SUMPRODUCT((D2:D8<>"")*1) | E20: =SUMPRODUCT((E2:E8<>"")*1) | F20: =SUMPRODUCT((F2:F8<>"")*1) | G20: =SUMPRODUCT((G2:G8<>"")*1) | H20: =SUMPRODUCT((H2:H8<>"")*1) | I20: =SUMPRODUCT((I2:I8<>"")*1) | ... L20: =SUMPRODUCT((L2:L8<>"")*1)

Sheet Indice_Global
C2: EVOLUÇÃO DO ÍNDICE DE DESENVOLVIMENTO DE ANGOLA (IGDA-BDA)
C4: Componente | D4: Peso | E4: 2015 | F4: 2016 | G4: 2017 | H4: 2018 | I4: 2019 | J4: 2020 | K4: 2021 | L4: 2022 | M4: 2023 | N4: 2024 | O4: 2025
C5: 1. Governança e Estado de Direito | D5: =Parametros!B52 | E5: =Subindices!B$2 | F5: =Subindices!C$2 | G5: =Subindices!D$2 | H5: =Subindices!E$2 | I5: =Subindices!F$2 | J5: =Subindices!G$2 | K5: =Subindices!H$2 | L5: =Subindices!I$2 | ... O5: =Subindices!L$2
C6: 2. Estabilidade Macroeconómica | D6: =Parametros!B53 | E6: =Subindices!B$3 | F6: =Subindices!C$3 | G6: =Subindices!D$3 | H6: =Subindices!E$3 | I6: =Subindices!F$3 | J6: =Subindices!G$3 | K6: =Subindices!H$3 | L6: =Subindices!I$3 | ... O6: =Subindices!L$3
C7: 3. Capital Humano | D7: =Parametros!B54 | E7: =Subindices!B$4 | F7: =Subindices!C$4 | G7: =Subindices!D$4 | H7: =Subindices!E$4 | I7: =Subindices!F$4 | J7: =Subindices!G$4 | K7: =Subindices!H$4 | L7: =Subindices!I$4 | ... O7: =Subindices!L$4
C8: 4. Inclusão Social e Protecção | D8: =Parametros!B55 | E8: =Subindices!B$5 | F8: =Subindices!C$5 | G8: =Subindices!D$5 | H8: =Subindices!E$5 | I8: =Subindices!F$5 | J8: =Subindices!G$5 | K8: =Subindices!H$5 | L8: =Subindices!I$5 | ... O8: =Subindices!L$5
C9: 5. Infraestruturas e Serviços | D9: =Parametros!B56 | E9: =Subindices!B$6 | F9: =Subindices!C$6 | G9: =Subindices!D$6 | H9: =Subindices!E$6 | I9: =Subindices!F$6 | J9: =Subindices!G$6 | K9: =Subindices!H$6 | L9: =Subindices!I$6 | ... O9: =Subindices!L$6
C10: 6. Mercado de Trabalho | D10: =Parametros!B57 | E10: =Subindices!B$7 | F10: =Subindices!C$7 | G10: =Subindices!D$7 | H10: =Subindices!E$7 | I10: =Subindices!F$7 | J10: =Subindices!G$7 | K10: =Subindices!H$7 | L10: =Subindices!I$7 | ... O10: =Subindices!L$7
C11: 7. Segurança Alimentar e Saúde | D11: =Parametros!B58 | E11: =Subindices!B$8 | F11: =Subindices!C$8 | G11: =Subindices!D$8 | H11: =Subindices!E$8 | I11: =Subindices!F$8 | J11: =Subindices!G$8 | K11: =Subindices!H$8 | L11: =Subindices!I$8 | ... O11: =Subindices!L$8
C13: EVOLUÇÃO DO IGDA-BDA (Índice Global) | E13: =IF(SUMPRODUCT((E5:E11<>"")*1)<Parametros!$B$47,"",IF(SUMPRODUCT((E5:E11<>"")*(E5:E11<=0))>0,0,EXP(SUMPRODUCT(IFERROR(LN(E5:E11)*$D$5:$D$11,0))/SUMPRODUCT((E5:E11<>"")*$D$5:$D$11)))) | F13: =IF(SUMPRODUCT((F5:F11<>"")*1)<Parametros!$B$47,"",IF(SUMPRODUCT((F5:F11<>"")*(F5:F11<=0))>0,0,EXP(SUMPRODUCT(IFERROR(LN(F5:F11)*$D$5:$D$11,0))/SUMPRODUCT((F5:F11<>"")*$D$5:$D$11)))) | G13: =IF(SUMPRODUCT((G5:G11<>"")*1)<Parametros!$B$47,"",IF(SUMPRODUCT((G5:G11<>"")*(G5:G11<=0))>0,0,EXP(SUMPRODUCT(IFERROR(LN(G5:G11)*$D$5:$D$11,0))/SUMPRODUCT((G5:G11<>"")*$D$5:$D$11)))) | H13: =IF(SUMPRODUCT((H5:H11<>"")*1)<Parametros!$B$47,"",IF(SUMPRODUCT((H5:H11<>"")*(H5:H11<=0))>0,0,EXP(SUMPRODUCT(IFERROR(LN(H5:H11)*$D$5:$D$11,0))/SUMPRODUCT((H5:H11<>"")*$D$5:$D$11)))) | I13: =IF(SUMPRODUCT((I5:I11<>"")*1)<Parametros!$B$47,"",IF(SUMPRODUCT((I5:I11<>"")*(I5:I11<=0))>0,0,EXP(SUMPRODUCT(IFERROR(LN(I5:I11)*$D$5:$D$11,0))/SUMPRODUCT((I5:I11<>"")*$D$5:$D$11)))) | J13: =IF(SUMPRODUCT((J5:J11<>"")*1)<Parametros!$B$47,"",IF(SUMPRODUCT((J5:J11<>"")*(J5:J11<=0))>0,0,EXP(SUMPRODUCT(IFERROR(LN(J5:J11)*$D$5:$D$11,0))/SUMPRODUCT((J5:J11<>"")*$D$5:$D$11)))) | K13: =IF(SUMPRODUCT((K5:K11<>"")*1)<Parametros!$B$47,"",IF(SUMPRODUCT((K5:K11<>"")*(K5:K11<=0))>0,0,EXP(SUMPRODUCT(IFERROR(LN(K5:K11)*$D$5:$D$11,0))/SUMPRODUCT((K5:K11<>"")*$D$5:$D$11)))) | L13: =IF(SUMPRODUCT((L5:L11<>"")*1)<Parametros!$B$47,"",IF(SUMPRODUCT((L5:L11<>"")*(L5:L11<=0))>0,0,EXP(SUMPRODUCT(IFERROR(LN(L5:L11)*$D$5:$D$11,0))/SUMPRODUCT((L5:L11<>"")*$D$5:$D$11)))) | ... O13: =IF(SUMPRODUCT((O5:O11<>"")*1)<Parametros!$B$47,"",IF(SUMPRODUCT((O5:O11<>"")*(O5:O11<=0))>0,0,EXP(SUMPRODUCT(IFERROR(LN(O5:O11)*$D$5:$D$11,0))/SUMPRODUCT((O5:O11<>"")*$D$5:$D$11))))
E14: =IF(E13="","",IF(E13>=70,"Bom",IF(E13>=50,"Moderado","Fraco"))) | F14: =IF(F13="","",IF(F13>=70,"Bom",IF(F13>=50,"Moderado","Fraco"))) | G14: =IF(G13="","",IF(G13>=70,"Bom",IF(G13>=50,"Moderado","Fraco"))) | H14: =IF(H13="","",IF(H13>=70,"Bom",IF(H13>=50,"Moderado","Fraco"))) | I14: =IF(I13="","",IF(I13>=70,"Bom",IF(I13>=50,"Moderado","Fraco"))) | J14: =IF(J13="","",IF(J13>=70,"Bom",IF(J13>=50,"Moderado","Fraco"))) | K14: =IF(K13="","",IF(K13>=70,"Bom",IF(K13>=50,"Moderado","Fraco"))) | L14: =IF(L13="","",IF(L13>=70,"Bom",IF(L13>=50,"Moderado","Fraco"))) | ... O14: =IF(O13="","",IF(O13>=70,"Bom",IF(O13>=50,"Moderado","Fraco")))
C15: Variação Anual (p.p.) | F15: =IF(OR(F13="",E13=""),"",F13-E13) | G15: =IF(OR(G13="",F13=""),"",G13-F13) | H15: =IF(OR(H13="",G13=""),"",H13-G13) | I15: =IF(OR(I13="",H13=""),"",I13-H13) | J15: =IF(OR(J13="",I13=""),"",J13-I13) | K15: =IF(OR(K13="",J13=""),"",K13-J13) | L15: =IF(OR(L13="",K13=""),"",L13-K13) | M15: =IF(OR(M13="",L13=""),"",M13-L13) | ... O15: =IF(OR(O13="",N13=""),"",O13-N13)
C16: SEMÁFORO DE DESEMPENHO
C17: ≥ 70: Bom | 50-70: Moderado | < 50: Fraco
B41: EVOLUÇÃO DOS SUB ÍNDICES

Sheet Diagnostico_Lacunas
A1: Diagnóstico de lacunas do IGDA-BDA
A2: Cobertura calculada apenas sobre as colunas 2015-2025 da folha Input_Dados. A coluna Q foi tratada como notas/fonte, não como série anual.
A4: Dimensão | B4: Nº indicadores atuais | C4: Indicadores sem dados 2015-2025 | D4: Indicadores com baixa cobertura (<6/11) | E4: Observação
A5: 1. Governança | B5: 5 | C5: Nenhum | D5: Nenhum | E5: Cobertura razoável; sugerem-se indicadores concorrentes para robustez metodológica.
A6: 2. Macroeconomia | B6: 7 | C6: IDE não-petrolífero (% PIB) | D6: Nenhum | E6: Reforçar com substitutos internacionais e/ou séries nacionais administrativas.
A7: 3. Capital Humano | B7: 6 | C7: Taxa de Alfabetização (+15 anos); Taxa de Matrícula (primário); Anos Médios de Escolaridade | D7: Nenhum | E7: Reforçar com substitutos internacionais e/ou séries nacionais administrativas.
A8: 4. Inclusão Social | B8: 5 | C8: Cobertura Protecção Social | D8: Taxa de Pobreza (< 2.15 USD/dia) (1/11); Índice de Gini (1/11) | E8: Reforçar com substitutos internacionais e/ou séries nacionais administrativas.
A9: 5. Infraestruturas | B9: 6 | C9: Cobertura de Rede 4G | D9: Nenhum | E9: Reforçar com substitutos internacionais e/ou séries nacionais administrativas.
A10: 6. Mercado Trabalho | B10: 6 | C10: Desemprego Juvenil (15-25); Crescimento da Produtividade | D10: Nenhum | E10: Reforçar com substitutos internacionais e/ou séries nacionais administrativas.
A11: 7. Seg. Alimentar/Saúde | B11: 6 | C11: Nenhum | D11: Índice Global Seg. Alimentar (3/11); Camas Hospitalares (por 1000) (2/11) | E11: Reforçar com substitutos internacionais e/ou séries nacionais administrativas.

Sheet Sugestoes_Indicadores
A1: Indicadores concorrentes/candidatos para reforçar o IGDA-BDA
A2: Estas linhas são sugestões metodológicas. Para entrarem no cálculo, devem ser copiadas para Input_Dados, Parametros e Normalizacao, ajustando os intervalos dos subíndices.
A3: Fontes priorizadas: Banco Mundial/WDI/WGI, PNUD/HDR, OIT/ILOSTAT, ITU, FAO/FAOSTAT, OMS/WHO, UNICEF/JMP, INE/BNA/MEP/MINFIN para séries nacionais.
A4: Dimensão | B4: Indicador sugerido | C4: Tipo | D4: Código | E4: Nome oficial/API | F4: Fonte | G4: Fonte_URL | H4: Unidade | I4: Sentido | J4: Mín. sugerido | K4: Máx. sugerido | L4: Meta 2027 sugerida | M4: Peso sugerido | N4: Prioridade | O4: Cobertura AGO 2015-2025 | P4: Último ano com dado | Q4: Racional / uso recomendado
A5: 1. Governança e Estado de Direito | B5: WGI - Controlo da Corrupção | C5: Substituto/Complementar | D5: CC.EST | E5: Control of Corruption: Estimate | F5: WGI/Banco Mundial | G5: https://datacatalog.worldbank.org/search/dataset/0038026/worldwide-governance-indicators | H5: -2.5 a 2.5 | I5: + | J5: -2.5 | K5: 2.5 | L5: 0 | M5: 1 | N5: Alta | O5: 10/11 (WGI 2015-2024) | P5: 2024 | Q5: Complementa o CPI com uma medida anual comparável e alinhada com os restantes WGI. Cobertura estimada pela periodicidade WGI; o endpoint WDI simples não devolve esta série.
A6: 1. Governança e Estado de Direito | B6: WGI - Qualidade Regulatória | C6: Substituto | D6: RQ.EST | E6: Regulatory Quality: Estimate | F6: WGI/Banco Mundial | G6: https://datacatalog.worldbank.org/search/dataset/0038026/worldwide-governance-indicators | H6: -2.5 a 2.5 | I6: + | J6: -2.5 | K6: 2.5 | L6: 0 | M6: 1 | N6: Alta | O6: 10/11 (WGI 2015-2024) | P6: 2024 | Q6: Bom substituto para Doing Business, que foi descontinuado. Cobertura estimada pela periodicidade WGI; o endpoint WDI simples não devolve esta série.
A7: 1. Governança e Estado de Direito | B7: WGI - Voz e Responsabilização | C7: Complementar | D7: VA.EST | E7: Voice and Accountability: Estimate | F7: WGI/Banco Mundial | G7: https://datacatalog.worldbank.org/search/dataset/0038026/worldwide-governance-indicators | H7: -2.5 a 2.5 | I7: + | J7: -2.5 | K7: 2.5 | L7: 0 | M7: 1 | N7: Média | O7: 10/11 (WGI 2015-2024) | P7: 2024 | Q7: Acrescenta dimensão de responsabilização pública e participação. Cobertura estimada pela periodicidade WGI; o endpoint WDI simples não devolve esta série.
A8: 1. Governança e Estado de Direito | B8: Índice Ibrahim - Governação Global | C8: Complementar | F8: Mo Ibrahim Foundation | G8: https://iiag.online/ | H8: 0-100 | I8: + | J8: 0 | K8: 100 | L8: 55 | M8: 1 | N8: Alta | Q8: Benchmark africano com várias dimensões institucionais.
A9: 1. Governança e Estado de Direito | B9: Índice Ibrahim - Segurança e Estado de Direito | C9: Complementar | F9: Mo Ibrahim Foundation | G9: https://iiag.online/ | H9: 0-100 | I9: + | J9: 0 | K9: 100 | L9: 55 | M9: 1 | N9: Média | Q9: Aproxima governança de segurança, justiça e direitos no contexto africano.
A10: 1. Governança e Estado de Direito | B10: Open Budget Index | C10: Complementar | F10: International Budget Partnership | G10: https://internationalbudget.org/open-budget-survey/ | H10: 0-100 | I10: + | J10: 0 | K10: 100 | L10: 50 | M10: 1 | N10: Média | Q10: Mede transparência orçamental, relevante para responsabilização fiscal.
A11: 1. Governança e Estado de Direito | B11: Empresas solicitadas a fazer pagamentos informais | C11: Complementar | F11: World Bank Enterprise Surveys | G11: https://www.enterprisesurveys.org/ | H11: % | I11: - | J11: 0 | K11: 100 | L11: 10 | M11: 1 | N11: Média | Q11: Capta corrupção administrativa sentida pelas empresas.
A12: 1. Governança e Estado de Direito | B12: Statistical Performance Index - score geral | C12: Complementar | D12: IQ.SPI.OVRL | E12: Statistical performance indicators (SPI): Overall score (scale 0-100) | F12: Banco Mundial | G12: https://data.worldbank.org/indicator/IQ.SPI.OVRL?locations=AO | H12: 0-100 | I12: + | J12: 0 | K12: 100 | L12: 65 | M12: 1 | N12: Média | O12: 9/11 | P12: 2024 | Q12: Mede capacidade estatística, útil para qualidade de políticas públicas e monitorização.
A13: 2. Estabilidade Macroeconómica | B13: Saldo da conta corrente (% PIB) | C13: Complementar | D13: BN.CAB.XOKA.GD.ZS | E13: Current account balance (% of GDP) | F13: Banco Mundial/WDI | G13: https://data.worldbank.org/indicator/BN.CAB.XOKA.GD.ZS?locations=AO | H13: % | I13: + | J13: -30 | K13: 30 | L13: 0 | M13: 1 | N13: Alta | O13: 10/11 | P13: 2024 | Q13: Acrescenta sustentabilidade externa, ausente do subíndice atual.
A14: 2. Estabilidade Macroeconómica | B14: Receita fiscal (% PIB) | C14: Complementar | D14: GC.TAX.TOTL.GD.ZS | E14: Tax revenue (% of GDP) | F14: Banco Mundial/WDI | G14: https://data.worldbank.org/indicator/GC.TAX.TOTL.GD.ZS?locations=AO | H14: % | I14: + | J14: 0 | K14: 40 | L14: 18 | M14: 1 | N14: Alta | O14: 10/11 | P14: 2024 | Q14: Capta capacidade interna de financiamento do Estado.
A15: 2. Estabilidade Macroeconómica | B15: IDE líquido total (% PIB) | C15: Substituto | D15: BX.KLT.DINV.WD.GD.ZS | E15: Foreign direct investment, net inflows (% of GDP) | F15: Banco Mundial/WDI | G15: https://data.worldbank.org/indicator/BX.KLT.DINV.WD.GD.ZS?locations=AO | H15: % | I15: + | J15: -10 | K15: 20 | L15: 5 | M15: 1 | N15: Alta | O15: 10/11 | P15: 2024 | Q15: Substitui provisoriamente o IDE não-petrolífero quando a série setorial estiver vazia.
A16: 2. Estabilidade Macroeconómica | B16: Rendas petrolíferas (% PIB) | C16: Complementar | D16: NY.GDP.PETR.RT.ZS | E16: Oil rents (% of GDP) | F16: Banco Mundial/WDI | G16: https://data.worldbank.org/indicator/NY.GDP.PETR.RT.ZS?locations=AO | H16: % | I16: - | J16: 0 | K16: 60 | L16: 15 | M16: 1 | N16: Alta | O16: 7/11 | P16: 2021 | Q16: Proxy de dependência petrolífera; menor dependência é melhor para diversificação.
A17: 2. Estabilidade Macroeconómica | B17: Exportações de bens e serviços (% PIB) | C17: Complementar | D17: NE.EXP.GNFS.ZS | E17: Exports of goods and services (% of GDP) | F17: Banco Mundial/WDI | G17: https://data.worldbank.org/indicator/NE.EXP.GNFS.ZS?locations=AO | H17: % | I17: + | J17: 0 | K17: 100 | L17: 40 | M17: 1 | N17: Média | O17: 10/11 | P17: 2024 | Q17: Acompanha abertura e capacidade exportadora, mas deve ser lido com composição setorial.
A18: 2. Estabilidade Macroeconómica | B18: Reservas internacionais em meses de importações | C18: Substituto | D18: FI.RES.TOTL.MO | E18: Total reserves in months of imports | F18: Banco Mundial/WDI | G18: https://data.worldbank.org/indicator/FI.RES.TOTL.MO?locations=AO | H18: Meses | I18: + | J18: 0 | K18: 12 | L18: 6 | M18: 1 | N18: Alta | O18: 10/11 | P18: 2024 | Q18: Pode substituir o cálculo manual atualmente colocado abaixo da tabela.
A19: 2. Estabilidade Macroeconómica | B19: Crédito doméstico ao setor privado (% PIB) | C19: Complementar | D19: FS.AST.PRVT.GD.ZS | E19: Domestic credit to private sector (% of GDP) | F19: Banco Mundial/WDI | G19: https://data.worldbank.org/indicator/FS.AST.PRVT.GD.ZS?locations=AO | H19: % | I19: + | J19: 0 | K19: 100 | L19: 35 | M19: 1 | N19: Média | O19: 10/11 | P19: 2024 | Q19: Acrescenta profundidade financeira e apoio ao investimento privado.
A20: 2. Estabilidade Macroeconómica | B20: Crescimento do PIB não petrolífero | C20: Complementar | F20: INE/MEP/BNA | G20: https://www.ine.gov.ao/ | H20: % | I20: + | J20: -10 | K20: 15 | L20: 5 | M20: 1 | N20: Alta | Q20: Mais alinhado com a diversificação económica do que o PIB total.
A21: 2. Estabilidade Macroeconómica | B21: Volatilidade da taxa de câmbio nominal | C21: Complementar | D21: PA.NUS.FCRF | E21: Official exchange rate (LCU per US$, period average) | F21: Banco Mundial/WDI ou BNA | G21: https://data.worldbank.org/indicator/PA.NUS.FCRF?locations=AO | H21: % variação anual | I21: - | J21: 0 | K21: 80 | L21: 10 | M21: 1 | N21: Média | O21: 10/11 | P21: 2024 | Q21: Capta instabilidade cambial que afeta preços, dívida e importações.
A22: 3. Capital Humano | B22: Taxa de alfabetização adulta | C22: Substituto | D22: SE.ADT.LITR.ZS | E22: Literacy rate, adult total (% of people ages 15 and above) | F22: Banco Mundial/UNESCO | G22: https://data.worldbank.org/indicator/SE.ADT.LITR.ZS?locations=AO | H22: % | I22: + | J22: 0 | K22: 100 | L22: 75 | M22: 1 | N22: Alta | O22: 2/11 | P22: 2023 | Q22: Preenche a linha existente com fonte internacional comparável.
A23: 3. Capital Humano | B23: Taxa de conclusão do ensino primário | C23: Complementar | D23: SE.PRM.CMPT.ZS | E23: Primary completion rate, total (% of relevant age group) | F23: Banco Mundial/UNESCO | G23: https://data.worldbank.org/indicator/SE.PRM.CMPT.ZS?locations=AO | H23: % | I23: + | J23: 0 | K23: 100 | L23: 90 | M23: 1 | N23: Alta | O23: 2/11 | P23: 2023 | Q23: Mais robusta que matrícula para medir progressão efetiva.
A24: 3. Capital Humano | B24: Matrícula no ensino secundário, bruta | C24: Complementar | D24: SE.SEC.ENRR | E24: School enrollment, secondary (% gross) | F24: Banco Mundial/UNESCO | G24: https://data.worldbank.org/indicator/SE.SEC.ENRR?locations=AO | H24: % | I24: + | J24: 0 | K24: 150 | L24: 80 | M24: 1 | N24: Alta | O24: 3/11 | P24: 2023 | Q24: Captura continuidade pós-primária.
A25: 3. Capital Humano | B25: Matrícula no ensino terciário, bruta | C25: Complementar | D25: SE.TER.ENRR | E25: School enrollment, tertiary (% gross) | F25: Banco Mundial/UNESCO | G25: https://data.worldbank.org/indicator/SE.TER.ENRR?locations=AO | H25: % | I25: + | J25: 0 | K25: 100 | L25: 20 | M25: 1 | N25: Média | O25: 4/11 | P25: 2024 | Q25: Ajuda a medir formação avançada e capacidade técnica.
A26: 3. Capital Humano | B26: Despesa pública em educação (% PIB) | C26: Complementar | D26: SE.XPD.TOTL.GD.ZS | E26: Government expenditure on education, total (% of GDP) | F26: Banco Mundial/UNESCO | G26: https://data.worldbank.org/indicator/SE.XPD.TOTL.GD.ZS?locations=AO | H26: % | I26: + | J26: 0 | K26: 10 | L26: 5 | M26: 1 | N26: Média | O26: 9/11 | P26: 2023 | Q26: Input de política pública; deve ser combinado com resultados de aprendizagem.
A27: 3. Capital Humano | B27: Learning poverty - crianças sem proficiência mínima de leitura | C27: Complementar | D27: SE.LPV.PRIM | E27: Learning poverty: Share of Children at the End-of-Primary age below minimum reading proficiency adjusted by Out-of-School Children (%) | F27: Banco Mundial/UNESCO | G27: https://data.worldbank.org/indicator/SE.LPV.PRIM?locations=AO | H27: % | I27: - | J27: 0 | K27: 100 | L27: 50 | M27: 1 | N27: Baixa | O27: 0/11 | Q27: Mede aprendizagem, não apenas acesso à escola. Usar como benchmark de qualidade; a cobertura anual para Angola é limitada.
A28: 3. Capital Humano | B28: Rácio alunos/professor no primário | C28: Complementar | D28: SE.PRM.ENRL.TC.ZS | E28: Pupil-teacher ratio, primary | F28: Banco Mundial/UNESCO | G28: https://data.worldbank.org/indicator/SE.PRM.ENRL.TC.ZS?locations=AO | H28: Alunos por professor | I28: - | J28: 10 | K28: 80 | L28: 35 | M28: 1 | N28: Média | O28: 1/11 | P28: 2015 | Q28: Proxy simples de pressão sobre qualidade de ensino.
A29: 3. Capital Humano | B29: Índice de Capital Humano | C29: Complementar | D29: HD.HCI.OVRL | E29: Human Capital Index (HCI) (scale 0-1) | F29: Banco Mundial | G29: https://data.worldbank.org/indicator/HD.HCI.OVRL?locations=AO | H29: 0-1 | I29: + | J29: 0 | K29: 1 | L29: 0.5 | M29: 1 | N29: Baixa | O29: 3/11 | P29: 2020 | Q29: Útil como benchmark, mas menos anual do que os restantes indicadores.
A30: 3. Capital Humano | B30: Anos esperados de escolaridade | C30: Substituto | F30: PNUD/HDR | G30: https://hdr.undp.org/data-center | H30: Anos | I30: + | J30: 0 | K30: 18 | L30: 12 | M30: 1 | N30: Alta | Q30: Substitui ou complementa anos médios de escolaridade quando a série nacional estiver vazia.
A31: 4. Inclusão Social e Protecção | B31: Pobreza pela linha nacional | C31: Substituto | D31: SI.POV.NAHC | E31: Poverty headcount ratio at national poverty lines (% of population) | F31: Banco Mundial/PIP | G31: https://data.worldbank.org/indicator/SI.POV.NAHC?locations=AO | H31: % | I31: - | J31: 0 | K31: 80 | L31: 30 | M31: 1 | N31: Alta | O31: 1/11 | P31: 2018 | Q31: Mais diretamente ligada à linha oficial de pobreza do país.
A32: 4. Inclusão Social e Protecção | B32: Pobreza internacional a 3,00 USD/dia, PPP 2021 | C32: Substituto | D32: SI.POV.DDAY | E32: Poverty headcount ratio at $3.00 a day (2021 PPP) (% of population) | F32: Banco Mundial/PIP | G32: https://data.worldbank.org/indicator/SI.POV.DDAY?locations=AO | H32: % | I32: - | J32: 0 | K32: 90 | L32: 40 | M32: 1 | N32: Alta | O32: 1/11 | P32: 2018 | Q32: Atualiza a referência internacional que substituiu linhas PPP antigas.
A33: 4. Inclusão Social e Protecção | B33: Índice de Gini | C33: Substituto | D33: SI.POV.GINI | E33: Gini index | F33: Banco Mundial/PIP | G33: https://data.worldbank.org/indicator/SI.POV.GINI?locations=AO | H33: 0-100 | I33: - | J33: 0 | K33: 70 | L33: 40 | M33: 1 | N33: Alta | O33: 1/11 | P33: 2018 | Q33: Mantém comparabilidade internacional para desigualdade.
A34: 4. Inclusão Social e Protecção | B34: Quota de rendimento dos 20% mais pobres | C34: Complementar | D34: SI.DST.FRST.20 | E34: Income share held by lowest 20% | F34: Banco Mundial/PIP | G34: https://data.worldbank.org/indicator/SI.DST.FRST.20?locations=AO | H34: % | I34: + | J34: 0 | K34: 20 | L34: 7 | M34: 1 | N34: Média | O34: 1/11 | P34: 2018 | Q34: Lê inclusão distributiva de forma complementar ao Gini.
A35: 4. Inclusão Social e Protecção | B35: Cobertura de proteção social da população | C35: Substituto | F35: Banco Mundial ASPIRE/OIT | G35: https://www.worldbank.org/en/data/datatopics/aspire | H35: % | I35: + | J35: 0 | K35: 100 | L35: 40 | M35: 1 | N35: Alta | Q35: Preenche a lacuna existente de proteção social se houver série ASPIRE/OIT ou INSS.
A36: 4. Inclusão Social e Protecção | B36: Índice de Pobreza Multidimensional - incidência | C36: Complementar | F36: PNUD/OPHI | G36: https://hdr.undp.org/data-center/thematic-composite-indices | H36: % | I36: - | J36: 0 | K36: 80 | L36: 25 | M36: 1 | N36: Média | Q36: Capta privações simultâneas além de rendimento.
A37: 4. Inclusão Social e Protecção | B37: Jovens NEET | C37: Complementar | D37: SL.UEM.NEET.ZS | E37: Share of youth not in education, employment or training, total (% of youth population) | F37: Banco Mundial/OIT | G37: https://data.worldbank.org/indicator/SL.UEM.NEET.ZS?locations=AO | H37: % | I37: - | J37: 0 | K37: 70 | L37: 30 | M37: 1 | N37: Alta | O37: 6/11 | P37: 2024 | Q37: Forte indicador de exclusão de jovens.
A38: 4. Inclusão Social e Protecção | B38: Mulheres no parlamento | C38: Complementar | D38: SG.GEN.PARL.ZS | E38: Proportion of seats held by women in national parliaments (%) | F38: Banco Mundial/IPU | G38: https://data.worldbank.org/indicator/SG.GEN.PARL.ZS?locations=AO | H38: % | I38: + | J38: 0 | K38: 60 | L38: 35 | M38: 1 | N38: Média | O38: 11/11 | P38: 2025 | Q38: Mede inclusão política de género.
A39: 4. Inclusão Social e Protecção | B39: Participação feminina na força de trabalho | C39: Complementar | D39: SL.TLF.CACT.FE.ZS | E39: Labor force participation rate, female (% of female population ages 15+) (modeled ILO estimate) | F39: Banco Mundial/OIT | G39: https://data.worldbank.org/indicator/SL.TLF.CACT.FE.ZS?locations=AO | H39: % | I39: + | J39: 0 | K39: 100 | L39: 65 | M39: 1 | N39: Média | O39: 11/11 | P39: 2025 | Q39: Complementa o Global Gender Gap com uma métrica económica anual.
A40: 4. Inclusão Social e Protecção | B40: Registo de nascimento completo | C40: Complementar | D40: SP.REG.BRTH.ZS | E40: Completeness of birth registration (%) | F40: Banco Mundial/UNICEF | G40: https://data.worldbank.org/indicator/SP.REG.BRTH.ZS?locations=AO | H40: % | I40: + | J40: 0 | K40: 100 | L40: 80 | M40: 1 | N40: Média | O40: 1/11 | P40: 2016 | Q40: Proxy de inclusão administrativa e acesso a direitos básicos.
A41: 5. Infraestruturas e Serviços | B41: Acesso rural à eletricidade | C41: Complementar | D41: EG.ELC.ACCS.RU.ZS | E41: Access to electricity, rural (% of rural population) | F41: Banco Mundial/IEA | G41: https://data.worldbank.org/indicator/EG.ELC.ACCS.RU.ZS?locations=AO | H41: % | I41: + | J41: 0 | K41: 100 | L41: 50 | M41: 1 | N41: Alta | O41: 2/11 | P41: 2018 | Q41: Evidencia desigualdade territorial no acesso à energia.
A42: 5. Infraestruturas e Serviços | B42: Acesso a energia limpa para cozinhar | C42: Complementar | D42: EG.CFT.ACCS.ZS | E42: Access to clean fuels and technologies for cooking (% of population) | F42: Banco Mundial/OMS | G42: https://data.worldbank.org/indicator/EG.CFT.ACCS.ZS?locations=AO | H42: % | I42: + | J42: 0 | K42: 100 | L42: 35 | M42: 1 | N42: Alta | O42: 9/11 | P42: 2023 | Q42: Indicador de infraestrutura doméstica com impacto ambiental e de saúde.
A43: 5. Infraestruturas e Serviços | B43: Perdas de transmissão e distribuição elétrica | C43: Complementar | D43: EG.ELC.LOSS.ZS | E43: Electric power transmission and distribution losses (% of output) | F43: Banco Mundial/IEA | G43: https://data.worldbank.org/indicator/EG.ELC.LOSS.ZS?locations=AO | H43: % | I43: - | J43: 0 | K43: 60 | L43: 15 | M43: 1 | N43: Média | O43: 9/11 | P43: 2023 | Q43: Mede eficiência da rede elétrica, não apenas acesso.
A44: 5. Infraestruturas e Serviços | B44: Subscrições móveis por 100 habitantes | C44: Substituto/Complementar | D44: IT.CEL.SETS.P2 | E44: Mobile cellular subscriptions (per 100 people) | F44: Banco Mundial/ITU | G44: https://data.worldbank.org/indicator/IT.CEL.SETS.P2?locations=AO | H44: por 100 hab. | I44: + | J44: 0 | K44: 160 | L44: 100 | M44: 1 | N44: Alta | O44: 10/11 | P44: 2024 | Q44: Alternativa anual à cobertura 4G quando a série INACOM estiver incompleta.
A45: 5. Infraestruturas e Serviços | B45: Banda larga fixa por 100 habitantes | C45: Complementar | D45: IT.NET.BBND.P2 | E45: Fixed broadband subscriptions (per 100 people) | F45: Banco Mundial/ITU | G45: https://data.worldbank.org/indicator/IT.NET.BBND.P2?locations=AO | H45: por 100 hab. | I45: + | J45: 0 | K45: 50 | L45: 8 | M45: 1 | N45: Média | O45: 10/11 | P45: 2024 | Q45: Mede infraestrutura digital fixa, distinta do uso de internet.
A46: 5. Infraestruturas e Serviços | B46: Preço de cabaz móvel-banda larga (% RNB per capita) | C46: Complementar | F46: ITU DataHub | G46: https://datahub.itu.int/ | H46: % RNB per capita | I46: - | J46: 0 | K46: 30 | L46: 5 | M46: 1 | N46: Média | Q46: Capta acessibilidade económica da conectividade.
A47: 5. Infraestruturas e Serviços | B47: Água potável básica - população total | C47: Substituto | D47: SH.H2O.BASW.ZS | E47: People using at least basic drinking water services (% of population) | F47: Banco Mundial/JMP | G47: https://data.worldbank.org/indicator/SH.H2O.BASW.ZS?locations=AO | H47: % | I47: + | J47: 0 | K47: 100 | L47: 70 | M47: 1 | N47: Alta | O47: 10/11 | P47: 2024 | Q47: Fonte comparável para preencher/validar a linha de água potável.
A48: 5. Infraestruturas e Serviços | B48: Saneamento básico - população total | C48: Substituto | D48: SH.STA.BASS.ZS | E48: People using at least basic sanitation services (% of population) | F48: Banco Mundial/JMP | G48: https://data.worldbank.org/indicator/SH.STA.BASS.ZS?locations=AO | H48: % | I48: + | J48: 0 | K48: 100 | L48: 60 | M48: 1 | N48: Alta | O48: 8/11 | P48: 2022 | Q48: Fonte comparável para preencher/validar saneamento.
A49: 5. Infraestruturas e Serviços | B49: Estradas pavimentadas (% total) | C49: Complementar | D49: IS.ROD.PAVE.ZS | E49: Roads, paved (% of total roads) | F49: Banco Mundial/WDI | G49: https://data.worldbank.org/indicator/IS.ROD.PAVE.ZS?locations=AO | H49: % | I49: + | J49: 0 | K49: 100 | L49: 30 | M49: 1 | N49: Média | O49: 3/11 | P49: 2001 | Q49: Complementa densidade rodoviária com qualidade da rede.
A50: 5. Infraestruturas e Serviços | B50: Logistics Performance Index - geral | C50: Complementar | D50: LP.LPI.OVRL.XQ | E50: Logistics performance index: Overall (1=low to 5=high) | F50: Banco Mundial/LPI | G50: https://data.worldbank.org/indicator/LP.LPI.OVRL.XQ?locations=AO | H50: 1-5 | I50: + | J50: 1 | K50: 5 | L50: 3 | M50: 1 | N50: Baixa | O50: 3/11 | P50: 2022 | Q50: Indicador sintético de logística; útil, mas não anual.
A51: 6. Mercado de Trabalho | B51: Emprego/população 15+ | C51: Substituto | D51: SL.EMP.TOTL.SP.ZS | E51: Employment to population ratio, 15+, total (%) (modeled ILO estimate) | F51: Banco Mundial/OIT | G51: https://data.worldbank.org/indicator/SL.EMP.TOTL.SP.ZS?locations=AO | H51: % | I51: + | J51: 0 | K51: 100 | L51: 65 | M51: 1 | N51: Alta | O51: 11/11 | P51: 2025 | Q51: Série internacional para validar a taxa de emprego.
A52: 6. Mercado de Trabalho | B52: Desemprego total modelado OIT | C52: Substituto | D52: SL.UEM.TOTL.ZS | E52: Unemployment, total (% of total labor force) (modeled ILO estimate) | F52: Banco Mundial/OIT | G52: https://data.worldbank.org/indicator/SL.UEM.TOTL.ZS?locations=AO | H52: % | I52: - | J52: 0 | K52: 50 | L52: 15 | M52: 1 | N52: Alta | O52: 11/11 | P52: 2025 | Q52: Série anual comparável para anos sem inquérito nacional.
A53: 6. Mercado de Trabalho | B53: Desemprego juvenil 15-24 | C53: Substituto | D53: SL.UEM.1524.ZS | E53: Unemployment, youth total (% of total labor force ages 15-24) (modeled ILO estimate) | F53: Banco Mundial/OIT | G53: https://data.worldbank.org/indicator/SL.UEM.1524.ZS?locations=AO | H53: % | I53: - | J53: 0 | K53: 70 | L53: 30 | M53: 1 | N53: Alta | O53: 11/11 | P53: 2025 | Q53: Preenche a lacuna existente de desemprego juvenil.
A54: 6. Mercado de Trabalho | B54: Participação na força de trabalho | C54: Complementar | D54: SL.TLF.CACT.ZS | E54: Labor force participation rate, total (% of total population ages 15+) (modeled ILO estimate) | F54: Banco Mundial/OIT | G54: https://data.worldbank.org/indicator/SL.TLF.CACT.ZS?locations=AO | H54: % | I54: + | J54: 0 | K54: 100 | L54: 70 | M54: 1 | N54: Alta | O54: 11/11 | P54: 2025 | Q54: Ajuda a interpretar desemprego junto com atividade laboral.
A55: 6. Mercado de Trabalho | B55: Emprego vulnerável | C55: Complementar | D55: SL.EMP.VULN.ZS | E55: Vulnerable employment, total (% of total employment) (modeled ILO estimate) | F55: Banco Mundial/OIT | G55: https://data.worldbank.org/indicator/SL.EMP.VULN.ZS?locations=AO | H55: % | I55: - | J55: 0 | K55: 100 | L55: 50 | M55: 1 | N55: Alta | O55: 11/11 | P55: 2025 | Q55: Qualidade do emprego; boa alternativa a informalidade quando esta estiver incompleta.
A56: 6. Mercado de Trabalho | B56: Trabalhadores assalariados | C56: Complementar | D56: SL.EMP.WORK.ZS | E56: Wage and salaried workers, total (% of total employment) (modeled ILO estimate) | F56: Banco Mundial/OIT | G56: https://data.worldbank.org/indicator/SL.EMP.WORK.ZS?locations=AO | H56: % emprego total | I56: + | J56: 0 | K56: 100 | L56: 50 | M56: 1 | N56: Alta | O56: 11/11 | P56: 2025 | Q56: Proxy de formalização/estrutura moderna do emprego.
A57: 6. Mercado de Trabalho | B57: Emprego na agricultura | C57: Complementar | D57: SL.AGR.EMPL.ZS | E57: Employment in agriculture (% of total employment) (modeled ILO estimate) | F57: Banco Mundial/OIT | G57: https://data.worldbank.org/indicator/SL.AGR.EMPL.ZS?locations=AO | H57: % emprego total | I57: - | J57: 0 | K57: 100 | L57: 35 | M57: 1 | N57: Média | O57: 11/11 | P57: 2025 | Q57: Proxy de transformação estrutural; deve ser lido com produtividade agrícola.
A58: 6. Mercado de Trabalho | B58: PIB por pessoa empregada | C58: Substituto | D58: SL.GDP.PCAP.EM.KD | E58: GDP per person employed (constant 2021 PPP $) | F58: Banco Mundial/OIT | G58: https://data.worldbank.org/indicator/SL.GDP.PCAP.EM.KD?locations=AO | H58: USD PPP constantes | I58: + | J58: 1000 | K58: 50000 | L58: 12000 | M58: 1 | N58: Alta | O58: 10/11 | P58: 2024 | Q58: Preenche crescimento de produtividade com uma medida de nível anual.
A59: 6. Mercado de Trabalho | B59: Jovens NEET | C59: Complementar | D59: SL.UEM.NEET.ZS | E59: Share of youth not in education, employment or training, total (% of youth population) | F59: Banco Mundial/OIT | G59: https://data.worldbank.org/indicator/SL.UEM.NEET.ZS?locations=AO | H59: % | I59: - | J59: 0 | K59: 70 | L59: 25 | M59: 1 | N59: Alta | O59: 6/11 | P59: 2024 | Q59: Indicador concorrente do desemprego juvenil porque inclui jovens fora da força de trabalho.
A60: 6. Mercado de Trabalho | B60: Emprego informal fora da agricultura | C60: Complementar | F60: INE/OIT ILOSTAT | G60: https://ilostat.ilo.org/data/ | H60: % emprego | I60: - | J60: 0 | K60: 100 | L60: 55 | M60: 1 | N60: Alta | Q60: Mantém a dimensão de informalidade, idealmente com microdados/inquéritos nacionais.
A61: 7. Segurança Alimentar e Saúde | B61: Insegurança alimentar moderada ou severa | C61: Substituto/Complementar | D61: SN.ITK.MSFI.ZS | E61: Prevalence of moderate or severe food insecurity in the population (%) | F61: Banco Mundial/FAO | G61: https://data.worldbank.org/indicator/SN.ITK.MSFI.ZS?locations=AO | H61: % | I61: - | J61: 0 | K61: 100 | L61: 45 | M61: 1 | N61: Alta | O61: 3/11 | P61: 2021 | Q61: Alternativa aberta ao índice proprietário de segurança alimentar.
A62: 7. Segurança Alimentar e Saúde | B62: Prevalência de subalimentação | C62: Substituto | D62: SN.ITK.DEFC.ZS | E62: Prevalence of undernourishment (% of population) | F62: Banco Mundial/FAO | G62: https://data.worldbank.org/indicator/SN.ITK.DEFC.ZS?locations=AO | H62: % | I62: - | J62: 0 | K62: 60 | L62: 20 | M62: 1 | N62: Alta | O62: 9/11 | P62: 2023 | Q62: Série FAO comparável para segurança alimentar.
A63: 7. Segurança Alimentar e Saúde | B63: Atraso de crescimento infantil | C63: Complementar | D63: SH.STA.STNT.ZS | E63: Prevalence of stunting, height for age (% of children under 5) | F63: Banco Mundial/OMS/UNICEF | G63: https://data.worldbank.org/indicator/SH.STA.STNT.ZS?locations=AO | H63: % crianças <5 | I63: - | J63: 0 | K63: 60 | L63: 25 | M63: 1 | N63: Média | O63: 1/11 | P63: 2015 | Q63: Mede nutrição crónica infantil.
A64: 7. Segurança Alimentar e Saúde | B64: Emaciação infantil | C64: Complementar | D64: SH.STA.WAST.ZS | E64: Prevalence of wasting, weight for height (% of children under 5) | F64: Banco Mundial/OMS/UNICEF | G64: https://data.worldbank.org/indicator/SH.STA.WAST.ZS?locations=AO | H64: % crianças <5 | I64: - | J64: 0 | K64: 25 | L64: 5 | M64: 1 | N64: Média | O64: 1/11 | P64: 2015 | Q64: Mede nutrição aguda e choque alimentar/saúde.
A65: 7. Segurança Alimentar e Saúde | B65: Mortalidade de menores de 5 anos | C65: Complementar | D65: SH.DYN.MORT | E65: Mortality rate, under-5 (per 1,000 live births) | F65: Banco Mundial/UNICEF | G65: https://data.worldbank.org/indicator/SH.DYN.MORT?locations=AO | H65: por 1000 | I65: - | J65: 0 | K65: 200 | L65: 50 | M65: 1 | N65: Alta | O65: 10/11 | P65: 2024 | Q65: Mais abrangente que mortalidade infantil isolada.
A66: 7. Segurança Alimentar e Saúde | B66: Cobertura universal de saúde - UHC service coverage index | C66: Complementar | D66: SH.UHC.SRVS.CV.XD | E66: UHC service coverage index | F66: Banco Mundial/OMS | G66: https://data.worldbank.org/indicator/SH.UHC.SRVS.CV.XD?locations=AO | H66: 0-100 | I66: + | J66: 0 | K66: 100 | L66: 55 | M66: 1 | N66: Baixa | O66: 0/11 | Q66: Sintetiza cobertura efetiva de serviços essenciais. Usar como benchmark de qualidade; a cobertura anual para Angola é limitada.
A67: 7. Segurança Alimentar e Saúde | B67: Vacinação DPT | C67: Substituto/Complementar | D67: SH.IMM.IDPT | E67: Immunization, DPT (% of children ages 12-23 months) | F67: Banco Mundial/OMS/UNICEF | G67: https://data.worldbank.org/indicator/SH.IMM.IDPT?locations=AO | H67: % crianças 12-23m | I67: + | J67: 0 | K67: 100 | L67: 85 | M67: 1 | N67: Alta | O67: 10/11 | P67: 2024 | Q67: Pode complementar a cobertura vacinal geral com indicador padronizado.
A68: 7. Segurança Alimentar e Saúde | B68: Despesa corrente em saúde (% PIB) | C68: Substituto | D68: SH.XPD.CHEX.GD.ZS | E68: Current health expenditure (% of GDP) | F68: Banco Mundial/OMS | G68: https://data.worldbank.org/indicator/SH.XPD.CHEX.GD.ZS?locations=AO | H68: % | I68: + | J68: 0 | K68: 15 | L68: 5 | M68: 1 | N68: Alta | O68: 9/11 | P68: 2023 | Q68: Fonte internacional padronizada para a linha já existente.
A69: 7. Segurança Alimentar e Saúde | B69: Médicos por 1000 habitantes | C69: Complementar | D69: SH.MED.PHYS.ZS | E69: Physicians (per 1,000 people) | F69: Banco Mundial/OMS | G69: https://data.worldbank.org/indicator/SH.MED.PHYS.ZS?locations=AO | H69: por 1000 | I69: + | J69: 0 | K69: 5 | L69: 1 | M69: 1 | N69: Média | O69: 3/11 | P69: 2022 | Q69: Complementa camas hospitalares com capacidade humana do sistema.
A70: 7. Segurança Alimentar e Saúde | B70: Camas hospitalares por 1000 habitantes | C70: Substituto | D70: SH.MED.BEDS.ZS | E70: Hospital beds (per 1,000 people) | F70: Banco Mundial/OMS | G70: https://data.worldbank.org/indicator/SH.MED.BEDS.ZS?locations=AO | H70: por 1000 | I70: + | J70: 0 | K70: 10 | L70: 2 | M70: 1 | N70: Alta | O70: 1/11 | P70: 2019 | Q70: Fonte alternativa para preencher a série com baixa cobertura.
A71: 7. Segurança Alimentar e Saúde | B71: Índice de produção alimentar | C71: Complementar | D71: AG.PRD.FOOD.XD | E71: Food production index (2014-2016 = 100) | F71: Banco Mundial/FAO | G71: https://data.worldbank.org/indicator/AG.PRD.FOOD.XD?locations=AO | H71: 2014-2016=100 | I71: + | J71: 50 | K71: 150 | L71: 110 | M71: 1 | N71: Média | O71: 8/11 | P71: 2022 | Q71: Acompanha disponibilidade doméstica de alimentos.
A72: 7. Segurança Alimentar e Saúde | B72: Rendimento cerealífero | C72: Complementar | D72: AG.YLD.CREL.KG | E72: Cereal yield (kg per hectare) | F72: Banco Mundial/FAO | G72: https://data.worldbank.org/indicator/AG.YLD.CREL.KG?locations=AO | H72: kg/ha | I72: + | J72: 0 | K72: 6000 | L72: 2000 | M72: 1 | N72: Média | O72: 9/11 | P72: 2023 | Q72: Proxy de produtividade agrícola e segurança alimentar.

Sheet Base_Alargada
A1: Base alargada de indicadores IGDA-BDA
A2: Compila os indicadores atuais e os indicadores sugeridos. Valores automáticos foram recolhidos de fontes abertas estruturadas quando havia código/API; restantes ficam marcados para recolha manual.
A4: Dimensão | B4: Subíndice curto | C4: Indicador | D4: Tipo | E4: Código | F4: Nome oficial/API | G4: Fonte | H4: Fonte_URL | I4: Unidade | J4: Sentido | K4: Mínimo | L4: Máximo | M4: Meta 2027 | N4: Peso | O4: Prioridade | P4: Estado da série | Q4: Cobertura 2015-2025 | R4: 2015 | S4: 2016 | T4: 2017 | U4: 2018 | V4: 2019 | W4: 2020 | X4: 2021 | Y4: 2022 | Z4: 2023 | AA4: 2024 | AB4: 2025 | AC4: Racional / nota
A5: 1. Governança e Estado de Direito | B5: 1. Governança | C5: Índice de Percepção da Corrupção | D5: Atual no modelo | G5: Transparency Int. | H5: Angola - Corruption Perceptions Index 2023 | countryeconomy.com | I5: 0-100 | J5: + | K5: 0 | L5: 100 | M5: 35 | N5: 1 | O5: Em uso | P5: Série existente no Input_Dados | Q5: 10/11 | R5: 15 | S5: 18 | T5: 19 | U5: 19 | V5: 26 | W5: 27 | X5: 29 | Y5: 33 | Z5: 33 | AA5: 32 | AC5: Indicador já incluído no modelo original.
A6: 1. Governança e Estado de Direito | B6: 1. Governança | C6: WGI - Estado de Direito | D6: Atual no modelo | E6: RL.EST | G6: Banco Mundial | H6: Angola's Income Inequality (2018) – Trends & Historical Data | I6: -2.5 a 2.5 | J6: + | K6: -2.5 | L6: 2.5 | M6: 0 | N6: 1 | O6: Em uso | P6: Série existente no Input_Dados | Q6: 10/11 | R6: -1.3086297 | S6: -1.3287764 | T6: -1.3317055 | U6: -1.1105522 | V6: -1.0519682 | W6: -0.9475038 | X6: -1.0980135 | Y6: -1.1625439 | Z6: -1.1944432 | AA6: -1.1697408 | AC6: Indicador já incluído no modelo original.
A7: 1. Governança e Estado de Direito | B7: 1. Governança | C7: WGI - Eficiência do Governo | D7: Atual no modelo | E7: GE.EST | G7: Banco Mundial | I7: -2.5 a 2.5 | J7: + | K7: -2.5 | L7: 2.5 | M7: 0 | N7: 1 | O7: Em uso | P7: Série existente no Input_Dados | Q7: 10/11 | R7: -0.9378237 | S7: -0.9493847 | T7: -0.9681157 | U7: -0.9784602 | V7: -0.9116965 | W7: -1.0163604 | X7: -0.9347008 | Y7: -0.8325718 | Z7: -0.8287026 | AA7: -0.7851909 | AC7: Indicador já incluído no modelo original.
A8: 1. Governança e Estado de Direito | B8: 1. Governança | C8: Estabilidade Política (WGI) | D8: Atual no modelo | E8: PV.EST | G8: Banco Mundial | I8: -2.5 a 2.5 | J8: + | K8: -2.5 | L8: 2.5 | M8: 0 | N8: 1 | O8: Em uso | P8: Série existente no Input_Dados | Q8: 10/11 | R8: -0.5591026 | S8: -0.434628 | T8: -0.5372145 | U8: -0.4058117 | V8: -0.4207039 | W8: -0.6427634 | X8: -0.7936068 | Y8: -0.5414068 | Z8: -0.3131654 | AA8: -0.5735964 | AC8: Indicador já incluído no modelo original.
A9: 1. Governança e Estado de Direito | B9: 1. Governança | C9: Doing Business / Ease of Business | D9: Atual no modelo | G9: Banco Mundial | H9: Internet Users in Angola | 2025 Trends & Rankings | World View Data | I9: 0-100 | J9: + | K9: 0 | L9: 100 | M9: 55 | N9: 1 | O9: Em uso | P9: Série existente no Input_Dados | Q9: 6/11 | R9: 37.09 | S9: 38.46 | T9: 38.41 | U9: 41.49 | V9: 43.86 | W9: 41.9 | AC9: Indicador já incluído no modelo original.
A10: 1. Governança e Estado de Direito | B10: 1. Governança | C10: WGI - Controlo da Corrupção | D10: Substituto/Complementar | E10: CC.EST | F10: Control of Corruption: Estimate | G10: WGI/Banco Mundial | H10: https://datacatalog.worldbank.org/search/dataset/0038026/worldwide-governance-indicators | I10: -2.5 a 2.5 | J10: + | K10: -2.5 | L10: 2.5 | M10: 0 | N10: 1 | O10: Alta | P10: Preenchido via WGI 2025 oficial | Q10: 10/11 | R10: -1.4857649 | S10: -1.4881942 | T10: -1.4208093 | U10: -1.181782 | V10: -0.9647988 | W10: -0.8918323 | X10: -0.6416506 | Y10: -0.6031537 | Z10: -0.6242518 | AA10: -0.6225793 | AC10: Complementa o CPI com uma medida anual comparável e alinhada com os restantes WGI. Cobertura estimada pela periodicidade WGI; o endpoint WDI simples não devolve esta série.
A11: 1. Governança e Estado de Direito | B11: 1. Governança | C11: WGI - Qualidade Regulatória | D11: Substituto | E11: RQ.EST | F11: Regulatory Quality: Estimate | G11: WGI/Banco Mundial | H11: https://datacatalog.worldbank.org/search/dataset/0038026/worldwide-governance-indicators | I11: -2.5 a 2.5 | J11: + | K11: -2.5 | L11: 2.5 | M11: 0 | N11: 1 | O11: Alta | P11: Preenchido via WGI 2025 oficial | Q11: 10/11 | R11: -1.0904945 | S11: -1.1804235 | T11: -1.1799885 | U11: -1.0624393 | V11: -0.9960854 | W11: -1.0388818 | X11: -0.8486184 | Y11: -0.8618821 | Z11: -0.904342 | AA11: -0.77302 | AC11: Bom substituto para Doing Business, que foi descontinuado. Cobertura estimada pela periodicidade WGI; o endpoint WDI simples não devolve esta série.
A12: 1. Governança e Estado de Direito | B12: 1. Governança | C12: WGI - Voz e Responsabilização | D12: Complementar | E12: VA.EST | F12: Voice and Accountability: Estimate | G12: WGI/Banco Mundial | H12: https://datacatalog.worldbank.org/search/dataset/0038026/worldwide-governance-indicators | I12: -2.5 a 2.5 | J12: + | K12: -2.5 | L12: 2.5 | M12: 0 | N12: 1 | O12: Média | P12: Preenchido via WGI 2025 oficial | Q12: 10/11 | R12: -1.1542998 | S12: -1.19498 | T12: -1.131561 | U12: -1.005668 | V12: -0.9382176 | W12: -0.9376898 | X12: -0.9985085 | Y12: -1.0480912 | Z12: -1.020936 | AA12: -1.0588932 | AC12: Acrescenta dimensão de responsabilização pública e participação. Cobertura estimada pela periodicidade WGI; o endpoint WDI simples não devolve esta série.
A13: 1. Governança e Estado de Direito | B13: 1. Governança | C13: Índice Ibrahim - Governação Global | D13: Complementar | G13: Mo Ibrahim Foundation | H13: https://iiag.online/ | I13: 0-100 | J13: + | K13: 0 | L13: 100 | M13: 55 | N13: 1 | O13: Alta | P13: Sem código/API; recolha manual | Q13: 0/11 | AC13: Benchmark africano com várias dimensões institucionais.
A14: 1. Governança e Estado de Direito | B14: 1. Governança | C14: Índice Ibrahim - Segurança e Estado de Direito | D14: Complementar | G14: Mo Ibrahim Foundation | H14: https://iiag.online/ | I14: 0-100 | J14: + | K14: 0 | L14: 100 | M14: 55 | N14: 1 | O14: Média | P14: Sem código/API; recolha manual | Q14: 0/11 | AC14: Aproxima governança de segurança, justiça e direitos no contexto africano.
A15: 1. Governança e Estado de Direito | B15: 1. Governança | C15: Open Budget Index | D15: Complementar | G15: International Budget Partnership | H15: https://internationalbudget.org/open-budget-survey/ | I15: 0-100 | J15: + | K15: 0 | L15: 100 | M15: 50 | N15: 1 | O15: Média | P15: Sem código/API; recolha manual | Q15: 0/11 | AC15: Mede transparência orçamental, relevante para responsabilização fiscal.
A16: 1. Governança e Estado de Direito | B16: 1. Governança | C16: Empresas solicitadas a fazer pagamentos informais | D16: Complementar | G16: World Bank Enterprise Surveys | H16: https://www.enterprisesurveys.org/ | I16: % | J16: - | K16: 0 | L16: 100 | M16: 10 | N16: 1 | O16: Média | P16: Sem código/API; recolha manual | Q16: 0/11 | AC16: Capta corrupção administrativa sentida pelas empresas.
A17: 1. Governança e Estado de Direito | B17: 1. Governança | C17: Statistical Performance Index - score geral | D17: Complementar | E17: IQ.SPI.OVRL | F17: Statistical performance indicators (SPI): Overall score (scale 0-100) | G17: Banco Mundial | H17: https://data.worldbank.org/indicator/IQ.SPI.OVRL?locations=AO | I17: 0-100 | J17: + | K17: 0 | L17: 100 | M17: 65 | N17: 1 | O17: Média | P17: Preenchido via Banco Mundial API/CSV | Q17: 9/11 | S17: 47.395417 | T17: 48.359583 | U17: 54.572083 | V17: 57.9525 | W17: 59.17 | X17: 56.45625 | Y17: 54.967083 | Z17: 57.595833 | AA17: 58.152083 | AC17: Mede capacidade estatística, útil para qualidade de políticas públicas e monitorização.
A18: 2. Estabilidade Macroeconómica | B18: 2. Macroeconomia | C18: Taxa de Crescimento do PIB | D18: Atual no modelo | E18: NY.GDP.MKTP.KD.ZG | G18: INE/MEP | H18: Repositório de Conhecimento Aberto | I18: % | J18: + | K18: -10 | L18: 15 | M18: 5 | N18: 1 | O18: Em uso | P18: Série existente no Input_Dados | Q18: 10/11 | R18: 0.76317771 | S18: -1.7005304 | T18: -0.14939623 | U18: -0.59441123 | V18: -0.20468025 | W18: -4.0424472 | X18: 2.1027525 | Y18: 4.2160026 | Z18: 1.2633081 | AA18: 4.4239066 | AC18: Indicador já incluído no modelo original.
A19: 2. Estabilidade Macroeconómica | B19: 2. Macroeconomia | C19: PIB per Capita (USD) | D19: Atual no modelo | E19: NY.GDP.PCAP.CD | G19: INE/MEP | I19: USD | J19: + | K19: 500 | L19: 15000 | M19: 5000 | N19: 1 | O19: Em uso | P19: Série existente no Input_Dados | Q19: 10/11 | R19: 4400.1341 | S19: 4136.7763 | T19: 4955.1922 | U19: 3214.8018 | V19: 2397.7613 | W19: 1902.3184 | X19: 2990.8603 | Y19: 3935.501 | Z19: 2773.0062 | AA19: 3181.6243 | AC19: Indicador já incluído no modelo original.
A20: 2. Estabilidade Macroeconómica | B20: 2. Macroeconomia | C20: Inflação (IPC) | D20: Atual no modelo | E20: FP.CPI.TOTL.ZG | G20: INE/BNA | I20: % | J20: - | K20: 0 | L20: 50 | M20: 10 | N20: 1 | O20: Em uso | P20: Série existente no Input_Dados | Q20: 11/11 | R20: 12.094268 | S20: 41.121135 | T20: 23.66655 | U20: 18.601105 | V20: 16.897288 | W20: 25.09653 | X20: 27.029944 | Y20: 13.860475 | Z20: 20.00716 | AA20: 26.480339 | AB20: 15.69722 | AC20: Indicador já incluído no modelo original.
A21: 2. Estabilidade Macroeconómica | B21: 2. Macroeconomia | C21: Dívida Pública (% do PIB) | D21: Atual no modelo | E21: GC.DOD.TOTL.GD.ZS | G21: MINFIN | H21: PUBLIC DEBT STATISTICAL BULLETIN AS OF [] | I21: % | J21: - | K21: 0 | L21: 150 | M21: 60 | N21: 1 | O21: Em uso | P21: Série existente no Input_Dados | Q21: 11/11 | R21: 50 | S21: 67 | T21: 60 | U21: 83 | V21: 101 | W21: 119 | X21: 74 | Y21: 56 | Z21: 72 | AA21: 60 | AB21: 63 | AC21: Indicador já incluído no modelo original.
A22: 2. Estabilidade Macroeconómica | B22: 2. Macroeconomia | C22: Saldo Orçamental (% do PIB) | D22: Atual no modelo | E22: GC.BAL.CASH.GD.ZS | G22: MINFIN | I22: % | J22: + | K22: -15 | L22: 10 | M22: 0 | N22: 1 | O22: Em uso | P22: Série existente no Input_Dados | Q22: 11/11 | R22: -2 | S22: -3 | T22: 1.5 | U22: -0.5 | V22: 0.5 | W22: -5 | X22: 1.5 | Y22: 0.7 | Z22: -1.9 | AA22: -1.5 | AB22: -1.65 | AC22: Indicador já incluído no modelo original.
A23: 2. Estabilidade Macroeconómica | B23: 2. Macroeconomia | C23: IDE não-petrolífero (% PIB) | D23: Atual no modelo | G23: AIPEX/BNA | I23: % | J23: + | K23: 0 | L23: 10 | M23: 3 | N23: 1 | O23: Em uso | P23: Série existente no Input_Dados | Q23: 0/11 | AC23: Indicador já incluído no modelo original.
A24: 2. Estabilidade Macroeconómica | B24: 2. Macroeconomia | C24: Reservas Internacionais (meses) | D24: Atual no modelo | E24: FI.RES.TOTL.MO | G24: BNA | I24: Meses | J24: + | K24: 0 | L24: 12 | M24: 6 | N24: 1 | O24: Em uso | P24: Série existente no Input_Dados | Q24: 11/11 | R24: =+F47 | S24: =+G47 | T24: =+H47 | U24: =+I47 | V24: =+J47 | W24: =+K47 | X24: =+L47 | Y24: =+M47 | ... AB24: =+P47 | AC24: Indicador já incluído no modelo original.
A25: 2. Estabilidade Macroeconómica | B25: 2. Macroeconomia | C25: Saldo da conta corrente (% PIB) | D25: Complementar | E25: BN.CAB.XOKA.GD.ZS | F25: Current account balance (% of GDP) | G25: Banco Mundial/WDI | H25: https://data.worldbank.org/indicator/BN.CAB.XOKA.GD.ZS?locations=AO | I25: % | J25: + | K25: -30 | L25: 30 | M25: 0 | N25: 1 | O25: Alta | P25: Preenchido via Banco Mundial API/CSV | Q25: 10/11 | R25: -10.018075 | S25: -5.1524476 | T25: -0.75004756 | U25: 8.2698865 | V25: 6.363326 | W25: 1.4815318 | X25: 10.557441 | Y25: 8.9647752 | Z25: 3.905087 | AA25: 6.2474404 | AC25: Acrescenta sustentabilidade externa, ausente do subíndice atual.
A26: 2. Estabilidade Macroeconómica | B26: 2. Macroeconomia | C26: Receita fiscal (% PIB) | D26: Complementar | E26: GC.TAX.TOTL.GD.ZS | F26: Tax revenue (% of GDP) | G26: Banco Mundial/WDI | H26: https://data.worldbank.org/indicator/GC.TAX.TOTL.GD.ZS?locations=AO | I26: % | J26: + | K26: 0 | L26: 40 | M26: 18 | N26: 1 | O26: Alta | P26: Preenchido via Banco Mundial API/CSV | Q26: 10/11 | R26: 9.7095139 | S26: 8.5757867 | T26: 8.0555378 | U26: 9.9288802 | V26: 11.288852 | W26: 20.517608 | X26: 10.70333 | Y26: 12.731812 | Z26: 8.8691289 | AA26: 7.7443637 | AC26: Capta capacidade interna de financiamento do Estado.
A27: 2. Estabilidade Macroeconómica | B27: 2. Macroeconomia | C27: IDE líquido total (% PIB) | D27: Substituto | E27: BX.KLT.DINV.WD.GD.ZS | F27: Foreign direct investment, net inflows (% of GDP) | G27: Banco Mundial/WDI | H27: https://data.worldbank.org/indicator/BX.KLT.DINV.WD.GD.ZS?locations=AO | I27: % | J27: + | K27: -10 | L27: 20 | M27: 5 | N27: 1 | O27: Alta | P27: Preenchido via Banco Mundial API/CSV | Q27: 10/11 | R27: 9.7795155 | S27: -0.29980439 | T27: -8.7669638 | U27: -7.2124622 | V27: -5.0764944 | W27: -3.1714362 | X27: -5.4740341 | Y27: -5.0289929 | Z27: -1.9778639 | AA27: -1.0986881 | AC27: Substitui provisoriamente o IDE não-petrolífero quando a série setorial estiver vazia.
A28: 2. Estabilidade Macroeconómica | B28: 2. Macroeconomia | C28: Rendas petrolíferas (% PIB) | D28: Complementar | E28: NY.GDP.PETR.RT.ZS | F28: Oil rents (% of GDP) | G28: Banco Mundial/WDI | H28: https://data.worldbank.org/indicator/NY.GDP.PETR.RT.ZS?locations=AO | I28: % | J28: - | K28: 0 | L28: 60 | M28: 15 | N28: 1 | O28: Alta | P28: Preenchido via Banco Mundial API/CSV | Q28: 7/11 | R28: 12.71873 | S28: 19.748399 | T28: 24.711006 | U28: 30.730403 | V28: 27.504829 | W28: 18.57196 | X28: 28.27444 | AC28: Proxy de dependência petrolífera; menor dependência é melhor para diversificação.
A29: 2. Estabilidade Macroeconómica | B29: 2. Macroeconomia | C29: Exportações de bens e serviços (% PIB) | D29: Complementar | E29: NE.EXP.GNFS.ZS | F29: Exports of goods and services (% of GDP) | G29: Banco Mundial/WDI | H29: https://data.worldbank.org/indicator/NE.EXP.GNFS.ZS?locations=AO | I29: % | J29: + | K29: 0 | L29: 100 | M29: 40 | N29: 1 | O29: Média | P29: Preenchido via Banco Mundial API/CSV | Q29: 10/11 | R29: 26.148932 | S29: 24.659165 | T29: 25.457235 | U29: 36.245895 | V29: 37.160331 | W29: 31.575828 | X29: 39.449484 | Y29: 35.196053 | Z29: 32.326302 | AA29: 31.483523 | AC29: Acompanha abertura e capacidade exportadora, mas deve ser lido com composição setorial.
A30: 2. Estabilidade Macroeconómica | B30: 2. Macroeconomia | C30: Reservas internacionais em meses de importações | D30: Substituto | E30: FI.RES.TOTL.MO | F30: Total reserves in months of imports | G30: Banco Mundial/WDI | H30: https://data.worldbank.org/indicator/FI.RES.TOTL.MO?locations=AO | I30: Meses | J30: + | K30: 0 | L30: 12 | M30: 6 | N30: 1 | O30: Alta | P30: Preenchido via Banco Mundial API/CSV | Q30: 10/11 | R30: 6.4820457 | S30: 9.0838712 | T30: 5.8181869 | U30: 5.4126402 | V30: 6.4250943 | W30: 8.0261477 | X30: 6.9491541 | Y30: 4.3768329 | Z30: 5.0892711 | AA30: 5.5137491 | AC30: Pode substituir o cálculo manual atualmente colocado abaixo da tabela.
A31: 2. Estabilidade Macroeconómica | B31: 2. Macroeconomia | C31: Crédito doméstico ao setor privado (% PIB) | D31: Complementar | E31: FS.AST.PRVT.GD.ZS | F31: Domestic credit to private sector (% of GDP) | G31: Banco Mundial/WDI | H31: https://data.worldbank.org/indicator/FS.AST.PRVT.GD.ZS?locations=AO | I31: % | J31: + | K31: 0 | L31: 100 | M31: 35 | N31: 1 | O31: Média | P31: Preenchido via Banco Mundial API/CSV | Q31: 10/11 | R31: 22.274928 | S31: 18.590828 | T31: 14.847459 | U31: 13.256401 | V31: 13.471825 | W31: 11.310753 | X31: 8.7024964 | Y31: 6.8656074 | Z31: 7.5654438 | AA31: 7.3166804 | AC31: Acrescenta profundidade financeira e apoio ao investimento privado.
A32: 2. Estabilidade Macroeconómica | B32: 2. Macroeconomia | C32: Crescimento do PIB não petrolífero | D32: Complementar | G32: INE/MEP/BNA | H32: https://www.ine.gov.ao/ | I32: % | J32: + | K32: -10 | L32: 15 | M32: 5 | N32: 1 | O32: Alta | P32: Sem código/API; recolha manual | Q32: 0/11 | AC32: Mais alinhado com a diversificação económica do que o PIB total.
A33: 2. Estabilidade Macroeconómica | B33: 2. Macroeconomia | C33: Volatilidade da taxa de câmbio nominal | D33: Complementar | E33: PA.NUS.FCRF | F33: Official exchange rate, annual absolute variation calculated from PA.NUS.FCRF | G33: Banco Mundial/WDI ou BNA | H33: https://data.worldbank.org/indicator/PA.NUS.FCRF?locations=AO | I33: % variação anual | J33: - | K33: 0 | L33: 80 | M33: 10 | N33: 1 | O33: Média | P33: Calculado: variação absoluta anual de PA.NUS.FCRF | Q33: 10/11 | R33: 22.134028 | S33: 36.311409 | T33: 1.3806463 | U33: 52.399903 | V33: 44.282188 | W33: 58.502708 | X33: 9.1971237 | Y33: 27.06099 | Z33: 48.733947 | AA33: 26.981094 | AC33: Capta instabilidade cambial que afeta preços, dívida e importações.
A34: 3. Capital Humano | B34: 3. Capital Humano | C34: Índice de Desenvolvimento Humano | D34: Atual no modelo | G34: PNUD | H34: Relatório do Desenvolvimento Humano (RDH) 2023-2024 | United Nations Development Programme | I34: 0-1 | J34: + | K34: 0 | L34: 1 | M34: 0.6 | N34: 1 | O34: Em uso | P34: Série existente no Input_Dados | Q34: 9/11 | R34: 0.591 | S34: 0.595 | T34: 0.597 | U34: 0.598 | V34: 0.597 | W34: 0.594 | X34: 0.59 | Y34: 0.591 | Z34: 0.616 | AC34: Indicador já incluído no modelo original.
A35: 3. Capital Humano | B35: 3. Capital Humano | C35: Esperança Média de Vida | D35: Atual no modelo | E35: SP.DYN.LE00.IN | G35: INE/OMS | H35: Life Expectancy at Birth, Total for Angola (SPDYNLE00INAGO) | FRED | St. Louis Fed | I35: Anos | J35: + | K35: 40 | L35: 85 | M35: 65 | N35: 1 | O35: Em uso | P35: Série existente no Input_Dados | Q35: 11/11 | R35: 61.042 | S35: 61.619 | T35: 61.7 | U35: 61.7 | V35: 62.2 | W35: 62.48 | X35: 62.72 | Y35: 62.95 | Z35: 64.617 | AA35: 64 | AB35: 65 | AC35: Indicador já incluído no modelo original.
A36: 3. Capital Humano | B36: 3. Capital Humano | C36: Taxa de Alfabetização (+15 anos) | D36: Atual no modelo | E36: SE.ADT.LITR.ZS | G36: INE/MED | I36: % | J36: + | K36: 0 | L36: 100 | M36: 75 | N36: 1 | O36: Em uso | P36: Série existente no Input_Dados | Q36: 0/11 | AC36: Indicador já incluído no modelo original.
A37: 3. Capital Humano | B37: 3. Capital Humano | C37: Taxa de Matrícula (primário) | D37: Atual no modelo | E37: SE.PRM.NENR | G37: MED | I37: % | J37: + | K37: 0 | L37: 100 | M37: 95 | N37: 1 | O37: Em uso | P37: Série existente no Input_Dados | Q37: 0/11 | AC37: Indicador já incluído no modelo original.
A38: 3. Capital Humano | B38: 3. Capital Humano | C38: Anos Médios de Escolaridade | D38: Atual no modelo | G38: UNESCO | I38: Anos | J38: + | K38: 0 | L38: 15 | M38: 8 | N38: 1 | O38: Em uso | P38: Série existente no Input_Dados | Q38: 0/11 | AC38: Indicador já incluído no modelo original.
A39: 3. Capital Humano | B39: 3. Capital Humano | C39: Mortalidade Infantil (por 1000) | D39: Atual no modelo | E39: SP.DYN.IMRT.IN | G39: INE/MINSA | I39: ‰ | J39: - | K39: 0 | L39: 150 | M39: 40 | N39: 1 | O39: Em uso | P39: Série existente no Input_Dados | Q39: 6/11 | T39: 61.1 | U39: 60 | V39: 58.9 | W39: 57.8 | X39: 56.81 | Y39: 55.84 | AC39: Indicador já incluído no modelo original.
A40: 3. Capital Humano | B40: 3. Capital Humano | C40: Taxa de alfabetização adulta | D40: Substituto | E40: SE.ADT.LITR.ZS | F40: Literacy rate, adult total (% of people ages 15 and above) | G40: Banco Mundial/UNESCO | H40: https://data.worldbank.org/indicator/SE.ADT.LITR.ZS?locations=AO | I40: % | J40: + | K40: 0 | L40: 100 | M40: 75 | N40: 1 | O40: Alta | P40: Preenchido via Banco Mundial API/CSV | Q40: 2/11 | R40: 66.239998 | Z40: 68.18 | AC40: Preenche a linha existente com fonte internacional comparável.
A41: 3. Capital Humano | B41: 3. Capital Humano | C41: Taxa de conclusão do ensino primário | D41: Complementar | E41: SE.PRM.CMPT.ZS | F41: Primary completion rate, total (% of relevant age group) | G41: Banco Mundial/UNESCO | H41: https://data.worldbank.org/indicator/SE.PRM.CMPT.ZS?locations=AO | I41: % | J41: + | K41: 0 | L41: 100 | M41: 90 | N41: 1 | O41: Alta | P41: Preenchido via Banco Mundial API/CSV | Q41: 2/11 | X41: 60.025939 | Z41: 47.855679 | AC41: Mais robusta que matrícula para medir progressão efetiva.
A42: 3. Capital Humano | B42: 3. Capital Humano | C42: Matrícula no ensino secundário, bruta | D42: Complementar | E42: SE.SEC.ENRR | F42: School enrollment, secondary (% gross) | G42: Banco Mundial/UNESCO | H42: https://data.worldbank.org/indicator/SE.SEC.ENRR?locations=AO | I42: % | J42: + | K42: 0 | L42: 150 | M42: 80 | N42: 1 | O42: Alta | P42: Preenchido via Banco Mundial API/CSV | Q42: 3/11 | S42: 54.416799 | X42: 53.135154 | Z42: 51.483905 | AC42: Captura continuidade pós-primária.
A43: 3. Capital Humano | B43: 3. Capital Humano | C43: Matrícula no ensino terciário, bruta | D43: Complementar | E43: SE.TER.ENRR | F43: School enrollment, tertiary (% gross) | G43: Banco Mundial/UNESCO | H43: https://data.worldbank.org/indicator/SE.TER.ENRR?locations=AO | I43: % | J43: + | K43: 0 | L43: 100 | M43: 20 | N43: 1 | O43: Média | P43: Preenchido via Banco Mundial API/CSV | Q43: 4/11 | R43: 8.7832087 | S43: 9.782877 | Z43: 10.049358 | AA43: 9.9549066 | AC43: Ajuda a medir formação avançada e capacidade técnica.
A44: 3. Capital Humano | B44: 3. Capital Humano | C44: Despesa pública em educação (% PIB) | D44: Complementar | E44: SE.XPD.TOTL.GD.ZS | F44: Government expenditure on education, total (% of GDP) | G44: Banco Mundial/UNESCO | H44: https://data.worldbank.org/indicator/SE.XPD.TOTL.GD.ZS?locations=AO | I44: % | J44: + | K44: 0 | L44: 10 | M44: 5 | N44: 1 | O44: Média | P44: Preenchido via Banco Mundial API/CSV | Q44: 9/11 | R44: 3.4868958 | S44: 2.7549366 | T44: 2.4668788 | U44: 2.183513 | V44: 2.0730644 | W44: 2.6674473 | X44: 2.2971969 | Y44: 2.385359 | Z44: 2.5127366 | AC44: Input de política pública; deve ser combinado com resultados de aprendizagem.
A45: 3. Capital Humano | B45: 3. Capital Humano | C45: Learning poverty - crianças sem proficiência mínima de leitura | D45: Complementar | E45: SE.LPV.PRIM | F45: Learning poverty: Share of Children at the End-of-Primary age below minimum reading proficiency adjusted by Out-of-School Children (%) | G45: Banco Mundial/UNESCO | H45: https://data.worldbank.org/indicator/SE.LPV.PRIM?locations=AO | I45: % | J45: - | K45: 0 | L45: 100 | M45: 50 | N45: 1 | O45: Baixa | P45: Sem valores para Angola em 2014-2025 | Q45: 0/11 | AC45: Mede aprendizagem, não apenas acesso à escola. Usar como benchmark de qualidade; a cobertura anual para Angola é limitada.
A46: 3. Capital Humano | B46: 3. Capital Humano | C46: Rácio alunos/professor no primário | D46: Complementar | E46: SE.PRM.ENRL.TC.ZS | F46: Pupil-teacher ratio, primary | G46: Banco Mundial/UNESCO | H46: https://data.worldbank.org/indicator/SE.PRM.ENRL.TC.ZS?locations=AO | I46: Alunos por professor | J46: - | K46: 10 | L46: 80 | M46: 35 | N46: 1 | O46: Média | P46: Preenchido via Banco Mundial API/CSV | Q46: 1/11 | R46: 50.02951 | AC46: Proxy simples de pressão sobre qualidade de ensino.
A47: 3. Capital Humano | B47: 3. Capital Humano | C47: Índice de Capital Humano | D47: Complementar | E47: HD.HCI.OVRL | F47: Human Capital Index (HCI) (scale 0-1) | G47: Banco Mundial | H47: https://data.worldbank.org/indicator/HD.HCI.OVRL?locations=AO | I47: 0-1 | J47: + | K47: 0 | L47: 1 | M47: 0.5 | N47: 1 | O47: Baixa | P47: Preenchido via Banco Mundial API/CSV | Q47: 3/11 | T47: 0.361 | U47: 0.36019096 | W47: 0.36240539 | AC47: Útil como benchmark, mas menos anual do que os restantes indicadores.
A48: 3. Capital Humano | B48: 3. Capital Humano | C48: Anos esperados de escolaridade | D48: Substituto | G48: PNUD/HDR | H48: https://hdr.undp.org/data-center | I48: Anos | J48: + | K48: 0 | L48: 18 | M48: 12 | N48: 1 | O48: Alta | P48: Sem código/API; recolha manual | Q48: 0/11 | AC48: Substitui ou complementa anos médios de escolaridade quando a série nacional estiver vazia.
A49: 4. Inclusão Social e Protecção | B49: 4. Inclusão Social | C49: Taxa de Pobreza (< 2.15 USD/dia) | D49: Atual no modelo | E49: SI.POV.DDAY | G49: INE/BM | H49: UNdata | record view | Poverty headcount ratio at $2.15 a day (2017 PPP) (% of population) | I49: % | J49: - | K49: 0 | L49: 80 | M49: 30 | N49: 1 | O49: Em uso | P49: Série existente no Input_Dados | Q49: 1/11 | U49: 31.1 | AC49: Indicador já incluído no modelo original.
A50: 4. Inclusão Social e Protecção | B50: 4. Inclusão Social | C50: Índice de Gini | D50: Atual no modelo | E50: SI.POV.GINI | G50: INE/BM | H50: Gini index - Angola | Data | I50: 0-100 | J50: - | K50: 0 | L50: 70 | M50: 40 | N50: 1 | O50: Em uso | P50: Série existente no Input_Dados | Q50: 1/11 | U50: 51.3 | AC50: Indicador já incluído no modelo original.
A51: 4. Inclusão Social e Protecção | B51: 4. Inclusão Social | C51: Cobertura Protecção Social | D51: Atual no modelo | G51: INSS | I51: % | J51: + | K51: 0 | L51: 100 | M51: 40 | N51: 1 | O51: Em uso | P51: Série existente no Input_Dados | Q51: 0/11 | AC51: Indicador já incluído no modelo original.
A52: 4. Inclusão Social e Protecção | B52: 4. Inclusão Social | C52: Global Gender Gap Index | D52: Atual no modelo | G52: WEF | H52: Angola - Global Gender Gap Index 2024 | countryeconomy.com | I52: 0-1 | J52: + | K52: 0 | L52: 1 | M52: 0.7 | N52: 1 | O52: Em uso | P52: Série existente no Input_Dados | Q52: 10/11 | R52: 0.637 | S52: 0.643 | T52: 0.64 | U52: 0.633 | W52: 0.66 | X52: 0.657 | Y52: 0.638 | Z52: 0.656 | AA52: 0.668 | AB52: 0.668 | AC52: Indicador já incluído no modelo original.
A53: 4. Inclusão Social e Protecção | B53: 4. Inclusão Social | C53: RNB per Capita (USD) | D53: Atual no modelo | E53: NY.GNP.PCAP.CD | G53: INE | H53: GNI per capita, Atlas method (current US$) - Angola | Data | I53: USD | J53: + | K53: 500 | L53: 15000 | M53: 4500 | N53: 1 | O53: Em uso | P53: Série existente no Input_Dados | Q53: 11/11 | R53: 2350 | S53: 3100 | T53: 2850 | U53: 2450 | V53: 2300 | W53: 2250 | X53: 2300 | Y53: 2400 | Z53: 2500 | AA53: 2840 | AB53: 2900 | AC53: Indicador já incluído no modelo original.
A54: 4. Inclusão Social e Protecção | B54: 4. Inclusão Social | C54: Pobreza pela linha nacional | D54: Substituto | E54: SI.POV.NAHC | F54: Poverty headcount ratio at national poverty lines (% of population) | G54: Banco Mundial/PIP | H54: https://data.worldbank.org/indicator/SI.POV.NAHC?locations=AO | I54: % | J54: - | K54: 0 | L54: 80 | M54: 30 | N54: 1 | O54: Alta | P54: Preenchido via Banco Mundial API/CSV | Q54: 1/11 | U54: 32.3 | AC54: Mais diretamente ligada à linha oficial de pobreza do país.
A55: 4. Inclusão Social e Protecção | B55: 4. Inclusão Social | C55: Pobreza internacional a 3,00 USD/dia, PPP 2021 | D55: Substituto | E55: SI.POV.DDAY | F55: Poverty headcount ratio at $3.00 a day (2021 PPP) (% of population) | G55: Banco Mundial/PIP | H55: https://data.worldbank.org/indicator/SI.POV.DDAY?locations=AO | I55: % | J55: - | K55: 0 | L55: 90 | M55: 40 | N55: 1 | O55: Alta | P55: Preenchido via Banco Mundial API/CSV | Q55: 1/11 | U55: 39.3 | AC55: Atualiza a referência internacional que substituiu linhas PPP antigas.
A56: 4. Inclusão Social e Protecção | B56: 4. Inclusão Social | C56: Índice de Gini | D56: Substituto | E56: SI.POV.GINI | F56: Gini index | G56: Banco Mundial/PIP | H56: https://data.worldbank.org/indicator/SI.POV.GINI?locations=AO | I56: 0-100 | J56: - | K56: 0 | L56: 70 | M56: 40 | N56: 1 | O56: Alta | P56: Preenchido via Banco Mundial API/CSV | Q56: 1/11 | U56: 51.3 | AC56: Mantém comparabilidade internacional para desigualdade.
A57: 4. Inclusão Social e Protecção | B57: 4. Inclusão Social | C57: Quota de rendimento dos 20% mais pobres | D57: Complementar | E57: SI.DST.FRST.20 | F57: Income share held by lowest 20% | G57: Banco Mundial/PIP | H57: https://data.worldbank.org/indicator/SI.DST.FRST.20?locations=AO | I57: % | J57: + | K57: 0 | L57: 20 | M57: 7 | N57: 1 | O57: Média | P57: Preenchido via Banco Mundial API/CSV | Q57: 1/11 | U57: 3.8 | AC57: Lê inclusão distributiva de forma complementar ao Gini.
A58: 4. Inclusão Social e Protecção | B58: 4. Inclusão Social | C58: Cobertura de proteção social da população | D58: Substituto | G58: Banco Mundial ASPIRE/OIT | H58: https://www.worldbank.org/en/data/datatopics/aspire | I58: % | J58: + | K58: 0 | L58: 100 | M58: 40 | N58: 1 | O58: Alta | P58: Sem código/API; recolha manual | Q58: 0/11 | AC58: Preenche a lacuna existente de proteção social se houver série ASPIRE/OIT ou INSS.
A59: 4. Inclusão Social e Protecção | B59: 4. Inclusão Social | C59: Índice de Pobreza Multidimensional - incidência | D59: Complementar | G59: PNUD/OPHI | H59: https://hdr.undp.org/data-center/thematic-composite-indices | I59: % | J59: - | K59: 0 | L59: 80 | M59: 25 | N59: 1 | O59: Média | P59: Sem código/API; recolha manual | Q59: 0/11 | AC59: Capta privações simultâneas além de rendimento.
A60: 4. Inclusão Social e Protecção | B60: 4. Inclusão Social | C60: Jovens NEET | D60: Complementar | E60: SL.UEM.NEET.ZS | F60: Share of youth not in education, employment or training, total (% of youth population) | G60: Banco Mundial/OIT | H60: https://data.worldbank.org/indicator/SL.UEM.NEET.ZS?locations=AO | I60: % | J60: - | K60: 0 | L60: 70 | M60: 30 | N60: 1 | O60: Alta | P60: Preenchido via Banco Mundial API/CSV | Q60: 6/11 | V60: 22.922 | W60: 27.286 | X60: 28.126 | Y60: 24.766 | Z60: 21.383 | AA60: 24.564 | AC60: Forte indicador de exclusão de jovens.
A61: 4. Inclusão Social e Protecção | B61: 4. Inclusão Social | C61: Mulheres no parlamento | D61: Complementar | E61: SG.GEN.PARL.ZS | F61: Proportion of seats held by women in national parliaments (%) | G61: Banco Mundial/IPU | H61: https://data.worldbank.org/indicator/SG.GEN.PARL.ZS?locations=AO | I61: % | J61: + | K61: 0 | L61: 60 | M61: 35 | N61: 1 | O61: Média | P61: Preenchido via Banco Mundial API/CSV | Q61: 11/11 | R61: 36.818182 | S61: 36.818182 | T61: 30.454545 | U61: 30.454545 | V61: 30 | W61: 30 | X61: 29.545455 | Y61: 33.636364 | Z61: 33.636364 | AA61: 39.545455 | AB61: 39.090909 | AC61: Mede inclusão política de género.
A62: 4. Inclusão Social e Protecção | B62: 4. Inclusão Social | C62: Participação feminina na força de trabalho | D62: Complementar | E62: SL.TLF.CACT.FE.ZS | F62: Labor force participation rate, female (% of female population ages 15+) (modeled ILO estimate) | G62: Banco Mundial/OIT | H62: https://data.worldbank.org/indicator/SL.TLF.CACT.FE.ZS?locations=AO | I62: % | J62: + | K62: 0 | L62: 100 | M62: 65 | N62: 1 | O62: Média | P62: Preenchido via Banco Mundial API/CSV | Q62: 11/11 | R62: 73.933 | S62: 73.697 | T62: 73.461 | U62: 73.224 | V62: 72.985 | W62: 71.342 | X62: 74.695 | Y62: 74.018 | Z62: 72.318 | AA62: 72.359 | AB62: 72.224 | AC62: Complementa o Global Gender Gap com uma métrica económica anual.
A63: 4. Inclusão Social e Protecção | B63: 4. Inclusão Social | C63: Registo de nascimento completo | D63: Complementar | E63: SP.REG.BRTH.ZS | F63: Completeness of birth registration (%) | G63: Banco Mundial/UNICEF | H63: https://data.worldbank.org/indicator/SP.REG.BRTH.ZS?locations=AO | I63: % | J63: + | K63: 0 | L63: 100 | M63: 80 | N63: 1 | O63: Média | P63: Preenchido via Banco Mundial API/CSV | Q63: 1/11 | S63: 25 | AC63: Proxy de inclusão administrativa e acesso a direitos básicos.
A64: 5. Infraestruturas e Serviços | B64: 5. Infraestruturas | C64: Taxa de Electrificação | D64: Atual no modelo | E64: EG.ELC.ACCS.ZS | G64: MINEA | H64: Angola - Access To Electricity (% Of Population) - 2026 Data 2027 Forecast 1990-2023 Historical | I64: % | J64: + | K64: 0 | L64: 100 | M64: 60 | N64: 1 | O64: Em uso | P64: Série existente no Input_Dados | Q64: 9/11 | R64: 42 | S64: 41.8 | T64: 42.9 | U64: 45.3 | V64: 45.6 | W64: 47 | X64: 48.2 | Y64: 48.5 | Z64: 51.1 | AC64: Indicador já incluído no modelo original.
A65: 5. Infraestruturas e Serviços | B65: 5. Infraestruturas | C65: Acesso a Água Potável | D65: Atual no modelo | E65: SH.H2O.BASW.ZS | G65: MINEA/INE | H65: Access to Basic Drinking Water in Angola | 2025 Trends & Rankings | World View Data | I65: % | J65: + | K65: 0 | L65: 100 | M65: 70 | N65: 1 | O65: Em uso | P65: Série existente no Input_Dados | Q65: 8/11 | R65: 54.3 | S65: 55.1 | T65: 55.8 | U65: 56.6 | V65: 56.9 | W65: 57.2 | X65: 57.4 | Y65: 57.7 | AC65: Indicador já incluído no modelo original.
A66: 5. Infraestruturas e Serviços | B66: 5. Infraestruturas | C66: Acesso a Saneamento Básico | D66: Atual no modelo | E66: SH.STA.BASS.ZS | G66: MINEA/INE | H66: People using at least basic sanitation services (% of population) - Angola | Data | I66: % | J66: + | K66: 0 | L66: 100 | M66: 60 | N66: 1 | O66: Em uso | P66: Série existente no Input_Dados | Q66: 8/11 | R66: 47 | S66: 48 | T66: 48 | U66: 49 | V66: 50 | W66: 50 | X66: 50 | Y66: 50 | AC66: Indicador já incluído no modelo original.
A67: 5. Infraestruturas e Serviços | B67: 5. Infraestruturas | C67: Cobertura de Rede 4G | D67: Atual no modelo | G67: INACOM | H67: Não tem estatísticas anuais | I67: % | J67: + | K67: 0 | L67: 100 | M67: 70 | N67: 1 | O67: Em uso | P67: Série existente no Input_Dados | Q67: 0/11 | AC67: Indicador já incluído no modelo original.
A68: 5. Infraestruturas e Serviços | B68: 5. Infraestruturas | C68: Utilizadores de Internet (%) | D68: Atual no modelo | E68: IT.NET.USER.ZS | G68: INACOM | H68: Table Data - Internet users for Angola | FRED | St. Louis Fed | I68: % | J68: + | K68: 0 | L68: 100 | M68: 40 | N68: 1 | O68: Em uso | P68: Série existente no Input_Dados | Q68: 9/11 | R68: 22 | S68: 23.2 | T68: 26 | U68: 29 | V68: 32.1 | W68: 36.6 | X68: 39.3 | Y68: 42 | Z68: 44 | AC68: Indicador já incluído no modelo original.
A69: 5. Infraestruturas e Serviços | B69: 5. Infraestruturas | C69: Densidade Rodoviária (km/1000km²) | D69: Atual no modelo | E69: IS.ROD.DNST.K2 | G69: MINTRANS | H69: World Bank Document | I69: km | J69: + | K69: 0 | L69: 100 | M69: 30 | N69: 1 | O69: Em uso | P69: Série existente no Input_Dados | Q69: 10/11 | R69: 29 | S69: 29 | T69: 29 | U69: 29 | V69: 29 | W69: 30 | X69: 31 | Y69: 31 | Z69: 32 | AA69: 33 | AC69: Indicador já incluído no modelo original.
A70: 5. Infraestruturas e Serviços | B70: 5. Infraestruturas | C70: Acesso rural à eletricidade | D70: Complementar | E70: EG.ELC.ACCS.RU.ZS | F70: Access to electricity, rural (% of rural population) | G70: Banco Mundial/IEA | H70: https://data.worldbank.org/indicator/EG.ELC.ACCS.RU.ZS?locations=AO | I70: % | J70: + | K70: 0 | L70: 100 | M70: 50 | N70: 1 | O70: Alta | P70: Preenchido via Banco Mundial API/CSV | Q70: 2/11 | R70: 3.8 | U70: 7.3 | AC70: Evidencia desigualdade territorial no acesso à energia.
A71: 5. Infraestruturas e Serviços | B71: 5. Infraestruturas | C71: Acesso a energia limpa para cozinhar | D71: Complementar | E71: EG.CFT.ACCS.ZS | F71: Access to clean fuels and technologies for cooking (% of population) | G71: Banco Mundial/OMS | H71: https://data.worldbank.org/indicator/EG.CFT.ACCS.ZS?locations=AO | I71: % | J71: + | K71: 0 | L71: 100 | M71: 35 | N71: 1 | O71: Alta | P71: Preenchido via Banco Mundial API/CSV | Q71: 9/11 | R71: 47 | S71: 48 | T71: 48.2 | U71: 48.8 | V71: 49.2 | W71: 49.4 | X71: 49.8 | Y71: 50 | Z71: 50.2 | AC71: Indicador de infraestrutura doméstica com impacto ambiental e de saúde.
A72: 5. Infraestruturas e Serviços | B72: 5. Infraestruturas | C72: Perdas de transmissão e distribuição elétrica | D72: Complementar | E72: EG.ELC.LOSS.ZS | F72: Electric power transmission and distribution losses (% of output) | G72: Banco Mundial/IEA | H72: https://data.worldbank.org/indicator/EG.ELC.LOSS.ZS?locations=AO | I72: % | J72: - | K72: 0 | L72: 60 | M72: 15 | N72: 1 | O72: Média | P72: Preenchido via Banco Mundial API/CSV | Q72: 9/11 | R72: 11.27007 | S72: 11.26696 | T72: 11.258031 | U72: 11.264913 | V72: 11.262912 | W72: 11.266159 | X72: 11.262288 | Y72: 11.261682 | Z72: 11.266798 | AC72: Mede eficiência da rede elétrica, não apenas acesso.
A73: 5. Infraestruturas e Serviços | B73: 5. Infraestruturas | C73: Subscrições móveis por 100 habitantes | D73: Substituto/Complementar | E73: IT.CEL.SETS.P2 | F73: Mobile cellular subscriptions (per 100 people) | G73: Banco Mundial/ITU | H73: https://data.worldbank.org/indicator/IT.CEL.SETS.P2?locations=AO | I73: por 100 hab. | J73: + | K73: 0 | L73: 160 | M73: 100 | N73: 1 | O73: Alta | P73: Preenchido via Banco Mundial API/CSV | Q73: 10/11 | R73: 49.309722 | S73: 44.550227 | T73: 44.068209 | U73: 42.458878 | V73: 45.806531 | W73: 43.780432 | X73: 44.386869 | Y73: 66.600807 | Z73: 70.051959 | AA73: 69.703947 | AC73: Alternativa anual à cobertura 4G quando a série INACOM estiver incompleta.
A74: 5. Infraestruturas e Serviços | B74: 5. Infraestruturas | C74: Banda larga fixa por 100 habitantes | D74: Complementar | E74: IT.NET.BBND.P2 | F74: Fixed broadband subscriptions (per 100 people) | G74: Banco Mundial/ITU | H74: https://data.worldbank.org/indicator/IT.NET.BBND.P2?locations=AO | I74: por 100 hab. | J74: + | K74: 0 | L74: 50 | M74: 8 | N74: 1 | O74: Média | P74: Preenchido via Banco Mundial API/CSV | Q74: 10/11 | R74: 0.54539421 | S74: 0.29031901 | T74: 0.32055405 | U74: 0.35006696 | V74: 0.36777043 | W74: 0.36326424 | X74: 0.3909253 | Y74: 0.38669816 | Z74: 0.37366898 | AA74: 0.36284524 | AC74: Mede infraestrutura digital fixa, distinta do uso de internet.
A75: 5. Infraestruturas e Serviços | B75: 5. Infraestruturas | C75: Preço de cabaz móvel-banda larga (% RNB per capita) | D75: Complementar | G75: ITU DataHub | H75: https://datahub.itu.int/ | I75: % RNB per capita | J75: - | K75: 0 | L75: 30 | M75: 5 | N75: 1 | O75: Média | P75: Sem código/API; recolha manual | Q75: 0/11 | AC75: Capta acessibilidade económica da conectividade.
A76: 5. Infraestruturas e Serviços | B76: 5. Infraestruturas | C76: Água potável básica - população total | D76: Substituto | E76: SH.H2O.BASW.ZS | F76: People using at least basic drinking water services (% of population) | G76: Banco Mundial/JMP | H76: https://data.worldbank.org/indicator/SH.H2O.BASW.ZS?locations=AO | I76: % | J76: + | K76: 0 | L76: 100 | M76: 70 | N76: 1 | O76: Alta | P76: Preenchido via Banco Mundial API/CSV | Q76: 10/11 | R76: 58.619631 | S76: 60.192062 | T76: 61.773512 | U76: 63.362791 | V76: 64.159911 | W76: 64.944031 | X76: 65.716258 | Y76: 66.476327 | Z76: 67.224425 | AA76: 67.960742 | AC76: Fonte comparável para preencher/validar a linha de água potável.
A77: 5. Infraestruturas e Serviços | B77: 5. Infraestruturas | C77: Saneamento básico - população total | D77: Substituto | E77: SH.STA.BASS.ZS | F77: People using at least basic sanitation services (% of population) | G77: Banco Mundial/JMP | H77: https://data.worldbank.org/indicator/SH.STA.BASS.ZS?locations=AO | I77: % | J77: + | K77: 0 | L77: 100 | M77: 60 | N77: 1 | O77: Alta | P77: Preenchido via Banco Mundial API/CSV | Q77: 8/11 | R77: 46.683765 | S77: 47.555909 | T77: 48.423766 | U77: 49.286523 | V77: 49.547024 | W77: 49.801638 | X77: 50.051135 | Y77: 50.295136 | AC77: Fonte comparável para preencher/validar saneamento.
A78: 5. Infraestruturas e Serviços | B78: 5. Infraestruturas | C78: Estradas pavimentadas (% total) | D78: Complementar | E78: IS.ROD.PAVE.ZS | F78: Roads, paved (% of total roads) | G78: Banco Mundial/WDI | H78: https://data.worldbank.org/indicator/IS.ROD.PAVE.ZS?locations=AO | I78: % | J78: + | K78: 0 | L78: 100 | M78: 30 | N78: 1 | O78: Média | P78: Sem valores para Angola em 2014-2025 | Q78: 0/11 | AC78: Complementa densidade rodoviária com qualidade da rede.
A79: 5. Infraestruturas e Serviços | B79: 5. Infraestruturas | C79: Logistics Performance Index - geral | D79: Complementar | E79: LP.LPI.OVRL.XQ | F79: Logistics performance index: Overall (1=low to 5=high) | G79: Banco Mundial/LPI | H79: https://data.worldbank.org/indicator/LP.LPI.OVRL.XQ?locations=AO | I79: 1-5 | J79: + | K79: 1 | L79: 5 | M79: 3 | N79: 1 | O79: Baixa | P79: Preenchido via Banco Mundial API/CSV | Q79: 3/11 | S79: 2.241183 | U79: 2.05 | Y79: 2.1 | AC79: Indicador sintético de logística; útil, mas não anual.
A80: 6. Mercado de Trabalho | B80: 6. Mercado Trabalho | C80: Taxa de Emprego | D80: Atual no modelo | E80: SL.EMP.TOTL.SP.ZS | G80: INE | I80: % | J80: + | K80: 0 | L80: 100 | M80: 65 | N80: 1 | O80: Em uso | P80: Série existente no Input_Dados | Q80: 7/11 | V80: 61.190162 | W80: 60.774759 | X80: 61.491468 | Y80: 62.715613 | Z80: 60.653315 | AA80: 61.666148 | AB80: 64.441287 | AC80: Indicador já incluído no modelo original.
A81: 6. Mercado de Trabalho | B81: 6. Mercado Trabalho | C81: Taxa de Desemprego | D81: Atual no modelo | E81: SL.UEM.TOTL.ZS | G81: INE | I81: % | J81: - | K81: 0 | L81: 50 | M81: 20 | N81: 1 | O81: Em uso | P81: Série existente no Input_Dados | Q81: 7/11 | V81: 30.208847 | W81: 32.181087 | X81: 32.320726 | Y81: 30.155336 | Z81: 31.852861 | AA81: 31.466353 | AB81: 26.860611 | AC81: Indicador já incluído no modelo original.
A82: 6. Mercado de Trabalho | B82: 6. Mercado Trabalho | C82: Desemprego Juvenil (15-25) | D82: Atual no modelo | E82: SL.UEM.1524.ZS | G82: INE | I82: % | J82: - | N82: 1 | O82: Em uso | P82: Série existente no Input_Dados | Q82: 0/11 | AC82: Indicador já incluído no modelo original.
A83: 6. Mercado de Trabalho | B83: 6. Mercado Trabalho | C83: Emprego Informal (%) | D83: Atual no modelo | G83: INE | I83: % | J83: - | K83: 0 | L83: 100 | M83: 50 | N83: 1 | O83: Em uso | P83: Série existente no Input_Dados | Q83: 7/11 | V83: 74.541816 | W83: 80.353575 | X83: 80.447518 | Y83: 79.860137 | Z83: 80.488095 | AA83: 79.759923 | AB83: 77.120842 | AC83: Indicador já incluído no modelo original.
A84: 6. Mercado de Trabalho | B84: 6. Mercado Trabalho | C84: Taxa de Formalização | D84: Atual no modelo | G84: INSS | I84: % | J84: + | K84: 0 | L84: 100 | M84: 40 | N84: 1 | O84: Em uso | P84: Série existente no Input_Dados | Q84: 7/11 | V84: 25.458184 | W84: 19.646425 | X84: 19.552482 | Y84: 20.139863 | Z84: 19.511905 | AA84: 20.240077 | AB84: 22.879158 | AC84: Indicador já incluído no modelo original.
A85: 6. Mercado de Trabalho | B85: 6. Mercado Trabalho | C85: Crescimento da Produtividade | D85: Atual no modelo | G85: INE/MEP | I85: % | J85: + | K85: -5 | L85: 10 | M85: 3 | N85: 1 | O85: Em uso | P85: Série existente no Input_Dados | Q85: 0/11 | AC85: Indicador já incluído no modelo original.
A86: 6. Mercado de Trabalho | B86: 6. Mercado Trabalho | C86: Emprego/população 15+ | D86: Substituto | E86: SL.EMP.TOTL.SP.ZS | F86: Employment to population ratio, 15+, total (%) (modeled ILO estimate) | G86: Banco Mundial/OIT | H86: https://data.worldbank.org/indicator/SL.EMP.TOTL.SP.ZS?locations=AO | I86: % | J86: + | K86: 0 | L86: 100 | M86: 65 | N86: 1 | O86: Alta | P86: Preenchido via Banco Mundial API/CSV | Q86: 11/11 | R86: 63.638 | S86: 63.321 | T86: 63.045 | U86: 62.812 | V86: 62.644 | W86: 61.078 | X86: 64.306 | Y86: 64.619 | Z86: 64.369 | AA86: 64.383 | AB86: 64.236 | AC86: Série internacional para validar a taxa de emprego.
A87: 6. Mercado de Trabalho | B87: 6. Mercado Trabalho | C87: Desemprego total modelado OIT | D87: Substituto | E87: SL.UEM.TOTL.ZS | F87: Unemployment, total (% of total labor force) (modeled ILO estimate) | G87: Banco Mundial/OIT | H87: https://data.worldbank.org/indicator/SL.UEM.TOTL.ZS?locations=AO | I87: % | J87: - | K87: 0 | L87: 50 | M87: 15 | N87: 1 | O87: Alta | P87: Preenchido via Banco Mundial API/CSV | Q87: 11/11 | R87: 16.472 | S87: 16.572 | T87: 16.617 | U87: 16.602 | V87: 16.497 | W87: 16.696 | X87: 15.799 | Y87: 14.124 | Z87: 14.051 | AA87: 14.02 | AB87: 14.108 | AC87: Série anual comparável para anos sem inquérito nacional.
A88: 6. Mercado de Trabalho | B88: 6. Mercado Trabalho | C88: Desemprego juvenil 15-24 | D88: Substituto | E88: SL.UEM.1524.ZS | F88: Unemployment, youth total (% of total labor force ages 15-24) (modeled ILO estimate) | G88: Banco Mundial/OIT | H88: https://data.worldbank.org/indicator/SL.UEM.1524.ZS?locations=AO | I88: % | J88: - | K88: 0 | L88: 70 | M88: 30 | N88: 1 | O88: Alta | P88: Preenchido via Banco Mundial API/CSV | Q88: 11/11 | R88: 35.122 | S88: 34.483 | T88: 33.725 | U88: 32.855 | V88: 31.832 | W88: 33.076 | X88: 30.171 | Y88: 27.143 | Z88: 26.834 | AA88: 26.74 | AB88: 27.229 | AC88: Preenche a lacuna existente de desemprego juvenil.
A89: 6. Mercado de Trabalho | B89: 6. Mercado Trabalho | C89: Participação na força de trabalho | D89: Complementar | E89: SL.TLF.CACT.ZS | F89: Labor force participation rate, total (% of total population ages 15+) (modeled ILO estimate) | G89: Banco Mundial/OIT | H89: https://data.worldbank.org/indicator/SL.TLF.CACT.ZS?locations=AO | I89: % | J89: + | K89: 0 | L89: 100 | M89: 70 | N89: 1 | O89: Alta | P89: Preenchido via Banco Mundial API/CSV | Q89: 11/11 | R89: 76.187 | S89: 75.899 | T89: 75.609 | U89: 75.316 | V89: 75.021 | W89: 73.319 | X89: 76.372 | Y89: 75.247 | Z89: 74.892 | AA89: 74.881 | AB89: 74.786 | AC89: Ajuda a interpretar desemprego junto com atividade laboral.
A90: 6. Mercado de Trabalho | B90: 6. Mercado Trabalho | C90: Emprego vulnerável | D90: Complementar | E90: SL.EMP.VULN.ZS | F90: Vulnerable employment, total (% of total employment) (modeled ILO estimate) | G90: Banco Mundial/OIT | H90: https://data.worldbank.org/indicator/SL.EMP.VULN.ZS?locations=AO | I90: % | J90: - | K90: 0 | L90: 100 | M90: 50 | N90: 1 | O90: Alta | P90: Preenchido via Banco Mundial API/CSV | Q90: 11/11 | R90: 65.262784 | S90: 65.224798 | T90: 65.221118 | U90: 65.260189 | V90: 65.269002 | W90: 65.941091 | X90: 65.793082 | Y90: 66.312488 | Z90: 66.309574 | AA90: 66.233541 | AB90: 66.266595 | AC90: Qualidade do emprego; boa alternativa a informalidade quando esta estiver incompleta.
A91: 6. Mercado de Trabalho | B91: 6. Mercado Trabalho | C91: Trabalhadores assalariados | D91: Complementar | E91: SL.EMP.WORK.ZS | F91: Wage and salaried workers, total (% of total employment) (modeled ILO estimate) | G91: Banco Mundial/OIT | H91: https://data.worldbank.org/indicator/SL.EMP.WORK.ZS?locations=AO | I91: % emprego total | J91: + | K91: 0 | L91: 100 | M91: 50 | N91: 1 | O91: Alta | P91: Preenchido via Banco Mundial API/CSV | Q91: 11/11 | R91: 25.408997 | S91: 25.385663 | T91: 25.326996 | U91: 25.222143 | V91: 25.152635 | W91: 24.578103 | X91: 24.690895 | Y91: 24.154879 | Z91: 24.107087 | AA91: 24.142151 | AB91: 24.09504 | AC91: Proxy de formalização/estrutura moderna do emprego.
A92: 6. Mercado de Trabalho | B92: 6. Mercado Trabalho | C92: Emprego na agricultura | D92: Complementar | E92: SL.AGR.EMPL.ZS | F92: Employment in agriculture (% of total employment) (modeled ILO estimate) | G92: Banco Mundial/OIT | H92: https://data.worldbank.org/indicator/SL.AGR.EMPL.ZS?locations=AO | I92: % emprego total | J92: - | K92: 0 | L92: 100 | M92: 35 | N92: 1 | O92: Média | P92: Preenchido via Banco Mundial API/CSV | Q92: 11/11 | R92: 52.70021 | S92: 52.921321 | T92: 53.008943 | U92: 53.309141 | V92: 53.423323 | W92: 55.559734 | X92: 56.707509 | Y92: 52.484758 | Z92: 52.406629 | AA92: 52.154747 | AB92: 51.949389 | AC92: Proxy de transformação estrutural; deve ser lido com produtividade agrícola.
A93: 6. Mercado de Trabalho | B93: 6. Mercado Trabalho | C93: PIB por pessoa empregada | D93: Substituto | E93: SL.GDP.PCAP.EM.KD | F93: GDP per person employed (constant 2021 PPP $) | G93: Banco Mundial/OIT | H93: https://data.worldbank.org/indicator/SL.GDP.PCAP.EM.KD?locations=AO | I93: USD PPP constantes | J93: + | K93: 1000 | L93: 50000 | M93: 12000 | N93: 1 | O93: Alta | P93: Preenchido via Banco Mundial API/CSV | Q93: 10/11 | R93: 32713.473 | S93: 31187.472 | T93: 30171.658 | U93: 29053.335 | V93: 28059.953 | W93: 26682.793 | X93: 25015.856 | Y93: 25072.6 | Z93: 24631.965 | AA93: 24845.814 | AC93: Preenche crescimento de produtividade com uma medida de nível anual.
A94: 6. Mercado de Trabalho | B94: 6. Mercado Trabalho | C94: Jovens NEET | D94: Complementar | E94: SL.UEM.NEET.ZS | F94: Share of youth not in education, employment or training, total (% of youth population) | G94: Banco Mundial/OIT | H94: https://data.worldbank.org/indicator/SL.UEM.NEET.ZS?locations=AO | I94: % | J94: - | K94: 0 | L94: 70 | M94: 25 | N94: 1 | O94: Alta | P94: Preenchido via Banco Mundial API/CSV | Q94: 6/11 | V94: 22.922 | W94: 27.286 | X94: 28.126 | Y94: 24.766 | Z94: 21.383 | AA94: 24.564 | AC94: Indicador concorrente do desemprego juvenil porque inclui jovens fora da força de trabalho.
A95: 6. Mercado de Trabalho | B95: 6. Mercado Trabalho | C95: Emprego informal fora da agricultura | D95: Complementar | G95: INE/OIT ILOSTAT | H95: https://ilostat.ilo.org/data/ | I95: % emprego | J95: - | K95: 0 | L95: 100 | M95: 55 | N95: 1 | O95: Alta | P95: Sem código/API; recolha manual | Q95: 0/11 | AC95: Mantém a dimensão de informalidade, idealmente com microdados/inquéritos nacionais.
A96: 7. Segurança Alimentar e Saúde | B96: 7. Seg. Alimentar/Saúde | C96: Índice Global Seg. Alimentar | D96: Atual no modelo | G96: EIU | H96: Indicadores Segurança Alimentar | I96: 0-100 | J96: + | K96: 0 | L96: 100 | M96: 50 | N96: 1 | O96: Em uso | P96: Série existente no Input_Dados | Q96: 3/11 | R96: 35.1 | AA96: 26 | AB96: 29.7 | AC96: Indicador já incluído no modelo original.
A97: 7. Segurança Alimentar e Saúde | B97: 7. Seg. Alimentar/Saúde | C97: Prevalência de Desnutrição | D97: Atual no modelo | E97: SN.ITK.DEFC.ZS | G97: MINSA/FAO | H97: Angola Prevalence of undernourishment - data, chart | TheGlobalEconomy.com | I97: % | J97: - | K97: 0 | L97: 50 | M97: 15 | N97: 1 | O97: Em uso | P97: Série existente no Input_Dados | Q97: 8/11 | S97: 15.2 | T97: 15.4 | U97: 15.9 | V97: 18.2 | W97: 20.8 | X97: 22.6 | Y97: 23.1 | Z97: 22.5 | AC97: Indicador já incluído no modelo original.
A98: 7. Segurança Alimentar e Saúde | B98: 7. Seg. Alimentar/Saúde | C98: Mortalidade Materna (por 100k) | D98: Atual no modelo | E98: SH.STA.MMRT | G98: MINSA/OMS | H98: Lifetime risk of maternal death (%) - Angola | Data | I98: por 100k | J98: - | K98: 0 | L98: 1000 | M98: 300 | N98: 1 | O98: Em uso | P98: Série existente no Input_Dados | Q98: 11/11 | R98: 477 | S98: 442 | T98: 400 | U98: 370 | V98: 330 | W98: 300 | X98: 290 | Y98: 250 | Z98: 183 | AA98: 185 | AB98: 170 | AC98: Indicador já incluído no modelo original.
A99: 7. Segurança Alimentar e Saúde | B99: 7. Seg. Alimentar/Saúde | C99: Despesas Saúde (% PIB) | D99: Atual no modelo | E99: SH.XPD.CHEX.GD.ZS | G99: MINFIN/OMS | H99: Angola Health spending as percent of GDP - data, chart | TheGlobalEconomy.com | I99: % | J99: + | K99: 0 | L99: 15 | M99: 5 | N99: 1 | O99: Em uso | P99: Série existente no Input_Dados | Q99: 8/11 | R99: 2.61 | S99: 2.71 | T99: 2.79 | U99: 2.59 | V99: 2.48 | W99: 3.27 | X99: 3.09 | Y99: 2.93 | AC99: Indicador já incluído no modelo original.
A100: 7. Segurança Alimentar e Saúde | B100: 7. Seg. Alimentar/Saúde | C100: Camas Hospitalares (por 1000) | D100: Atual no modelo | E100: SH.MED.BEDS.ZS | G100: MINSA | I100: por 1000 | J100: + | K100: 0 | L100: 10 | M100: 2 | N100: 1 | O100: Em uso | P100: Série existente no Input_Dados | Q100: 2/11 | T100: 0.38 | Y100: 1.02 | AC100: Indicador já incluído no modelo original.
A101: 7. Segurança Alimentar e Saúde | B101: 7. Seg. Alimentar/Saúde | C101: Cobertura Vacinal (%) | D101: Atual no modelo | E101: SH.IMM.MEAS | G101: MINSA/OMS | H101: https://cdn.who.int/media/docs/default-source/country-profiles/immunization/2024-country-profiles/immunization-2024-ago.pdf?utm_source=chatgpt.co | I101: % | J101: + | K101: 0 | L101: 100 | M101: 80 | N101: 1 | O101: Em uso | P101: Série existente no Input_Dados | Q101: 9/11 | R101: 45 | S101: 42 | T101: 50 | U101: 51 | V101: 44 | W101: 36 | X101: 37 | Y101: 37 | Z101: 50 | AC101: Indicador já incluído no modelo original.
...

Sheet Compilacao_Sugeridos
A1: Compilação dos indicadores sugeridos
A2: Apenas indicadores sugeridos, com dados 2015-2025 quando disponíveis automaticamente.
A4: Dimensão | B4: Subíndice curto | C4: Indicador | D4: Tipo | E4: Código | F4: Nome oficial/API | G4: Fonte | H4: Fonte_URL | I4: Unidade | J4: Sentido | K4: Mínimo | L4: Máximo | M4: Meta 2027 | N4: Peso | O4: Prioridade | P4: Estado da série | Q4: Cobertura 2015-2025 | R4: 2015 | S4: 2016 | T4: 2017 | U4: 2018 | V4: 2019 | W4: 2020 | X4: 2021 | Y4: 2022 | Z4: 2023 | AA4: 2024 | AB4: 2025 | AC4: Racional / nota
A5: 1. Governança e Estado de Direito | B5: 1. Governança | C5: WGI - Controlo da Corrupção | D5: Substituto/Complementar | E5: CC.EST | F5: Control of Corruption: Estimate | G5: WGI/Banco Mundial | H5: https://datacatalog.worldbank.org/search/dataset/0038026/worldwide-governance-indicators | I5: -2.5 a 2.5 | J5: + | K5: -2.5 | L5: 2.5 | M5: 0 | N5: 1 | O5: Alta | P5: Preenchido via WGI 2025 oficial | Q5: 10/11 | R5: -1.4857649 | S5: -1.4881942 | T5: -1.4208093 | U5: -1.181782 | V5: -0.9647988 | W5: -0.8918323 | X5: -0.6416506 | Y5: -0.6031537 | Z5: -0.6242518 | AA5: -0.6225793 | AC5: Complementa o CPI com uma medida anual comparável e alinhada com os restantes WGI. Cobertura estimada pela periodicidade WGI; o endpoint WDI simples não devolve esta série.
A6: 1. Governança e Estado de Direito | B6: 1. Governança | C6: WGI - Qualidade Regulatória | D6: Substituto | E6: RQ.EST | F6: Regulatory Quality: Estimate | G6: WGI/Banco Mundial | H6: https://datacatalog.worldbank.org/search/dataset/0038026/worldwide-governance-indicators | I6: -2.5 a 2.5 | J6: + | K6: -2.5 | L6: 2.5 | M6: 0 | N6: 1 | O6: Alta | P6: Preenchido via WGI 2025 oficial | Q6: 10/11 | R6: -1.0904945 | S6: -1.1804235 | T6: -1.1799885 | U6: -1.0624393 | V6: -0.9960854 | W6: -1.0388818 | X6: -0.8486184 | Y6: -0.8618821 | Z6: -0.904342 | AA6: -0.77302 | AC6: Bom substituto para Doing Business, que foi descontinuado. Cobertura estimada pela periodicidade WGI; o endpoint WDI simples não devolve esta série.
A7: 1. Governança e Estado de Direito | B7: 1. Governança | C7: WGI - Voz e Responsabilização | D7: Complementar | E7: VA.EST | F7: Voice and Accountability: Estimate | G7: WGI/Banco Mundial | H7: https://datacatalog.worldbank.org/search/dataset/0038026/worldwide-governance-indicators | I7: -2.5 a 2.5 | J7: + | K7: -2.5 | L7: 2.5 | M7: 0 | N7: 1 | O7: Média | P7: Preenchido via WGI 2025 oficial | Q7: 10/11 | R7: -1.1542998 | S7: -1.19498 | T7: -1.131561 | U7: -1.005668 | V7: -0.9382176 | W7: -0.9376898 | X7: -0.9985085 | Y7: -1.0480912 | Z7: -1.020936 | AA7: -1.0588932 | AC7: Acrescenta dimensão de responsabilização pública e participação. Cobertura estimada pela periodicidade WGI; o endpoint WDI simples não devolve esta série.
A8: 1. Governança e Estado de Direito | B8: 1. Governança | C8: Índice Ibrahim - Governação Global | D8: Complementar | G8: Mo Ibrahim Foundation | H8: https://iiag.online/ | I8: 0-100 | J8: + | K8: 0 | L8: 100 | M8: 55 | N8: 1 | O8: Alta | P8: Sem código/API; recolha manual | Q8: 0/11 | AC8: Benchmark africano com várias dimensões institucionais.
A9: 1. Governança e Estado de Direito | B9: 1. Governança | C9: Índice Ibrahim - Segurança e Estado de Direito | D9: Complementar | G9: Mo Ibrahim Foundation | H9: https://iiag.online/ | I9: 0-100 | J9: + | K9: 0 | L9: 100 | M9: 55 | N9: 1 | O9: Média | P9: Sem código/API; recolha manual | Q9: 0/11 | AC9: Aproxima governança de segurança, justiça e direitos no contexto africano.
A10: 1. Governança e Estado de Direito | B10: 1. Governança | C10: Open Budget Index | D10: Complementar | G10: International Budget Partnership | H10: https://internationalbudget.org/open-budget-survey/ | I10: 0-100 | J10: + | K10: 0 | L10: 100 | M10: 50 | N10: 1 | O10: Média | P10: Sem código/API; recolha manual | Q10: 0/11 | AC10: Mede transparência orçamental, relevante para responsabilização fiscal.
A11: 1. Governança e Estado de Direito | B11: 1. Governança | C11: Empresas solicitadas a fazer pagamentos informais | D11: Complementar | G11: World Bank Enterprise Surveys | H11: https://www.enterprisesurveys.org/ | I11: % | J11: - | K11: 0 | L11: 100 | M11: 10 | N11: 1 | O11: Média | P11: Sem código/API; recolha manual | Q11: 0/11 | AC11: Capta corrupção administrativa sentida pelas empresas.
A12: 1. Governança e Estado de Direito | B12: 1. Governança | C12: Statistical Performance Index - score geral | D12: Complementar | E12: IQ.SPI.OVRL | F12: Statistical performance indicators (SPI): Overall score (scale 0-100) | G12: Banco Mundial | H12: https://data.worldbank.org/indicator/IQ.SPI.OVRL?locations=AO | I12: 0-100 | J12: + | K12: 0 | L12: 100 | M12: 65 | N12: 1 | O12: Média | P12: Preenchido via Banco Mundial API/CSV | Q12: 9/11 | S12: 47.395417 | T12: 48.359583 | U12: 54.572083 | V12: 57.9525 | W12: 59.17 | X12: 56.45625 | Y12: 54.967083 | Z12: 57.595833 | AA12: 58.152083 | AC12: Mede capacidade estatística, útil para qualidade de políticas públicas e monitorização.
A13: 2. Estabilidade Macroeconómica | B13: 2. Macroeconomia | C13: Saldo da conta corrente (% PIB) | D13: Complementar | E13: BN.CAB.XOKA.GD.ZS | F13: Current account balance (% of GDP) | G13: Banco Mundial/WDI | H13: https://data.worldbank.org/indicator/BN.CAB.XOKA.GD.ZS?locations=AO | I13: % | J13: + | K13: -30 | L13: 30 | M13: 0 | N13: 1 | O13: Alta | P13: Preenchido via Banco Mundial API/CSV | Q13: 10/11 | R13: -10.018075 | S13: -5.1524476 | T13: -0.75004756 | U13: 8.2698865 | V13: 6.363326 | W13: 1.4815318 | X13: 10.557441 | Y13: 8.9647752 | Z13: 3.905087 | AA13: 6.2474404 | AC13: Acrescenta sustentabilidade externa, ausente do subíndice atual.
A14: 2. Estabilidade Macroeconómica | B14: 2. Macroeconomia | C14: Receita fiscal (% PIB) | D14: Complementar | E14: GC.TAX.TOTL.GD.ZS | F14: Tax revenue (% of GDP) | G14: Banco Mundial/WDI | H14: https://data.worldbank.org/indicator/GC.TAX.TOTL.GD.ZS?locations=AO | I14: % | J14: + | K14: 0 | L14: 40 | M14: 18 | N14: 1 | O14: Alta | P14: Preenchido via Banco Mundial API/CSV | Q14: 10/11 | R14: 9.7095139 | S14: 8.5757867 | T14: 8.0555378 | U14: 9.9288802 | V14: 11.288852 | W14: 20.517608 | X14: 10.70333 | Y14: 12.731812 | Z14: 8.8691289 | AA14: 7.7443637 | AC14: Capta capacidade interna de financiamento do Estado.
A15: 2. Estabilidade Macroeconómica | B15: 2. Macroeconomia | C15: IDE líquido total (% PIB) | D15: Substituto | E15: BX.KLT.DINV.WD.GD.ZS | F15: Foreign direct investment, net inflows (% of GDP) | G15: Banco Mundial/WDI | H15: https://data.worldbank.org/indicator/BX.KLT.DINV.WD.GD.ZS?locations=AO | I15: % | J15: + | K15: -10 | L15: 20 | M15: 5 | N15: 1 | O15: Alta | P15: Preenchido via Banco Mundial API/CSV | Q15: 10/11 | R15: 9.7795155 | S15: -0.29980439 | T15: -8.7669638 | U15: -7.2124622 | V15: -5.0764944 | W15: -3.1714362 | X15: -5.4740341 | Y15: -5.0289929 | Z15: -1.9778639 | AA15: -1.0986881 | AC15: Substitui provisoriamente o IDE não-petrolífero quando a série setorial estiver vazia.
A16: 2. Estabilidade Macroeconómica | B16: 2. Macroeconomia | C16: Rendas petrolíferas (% PIB) | D16: Complementar | E16: NY.GDP.PETR.RT.ZS | F16: Oil rents (% of GDP) | G16: Banco Mundial/WDI | H16: https://data.worldbank.org/indicator/NY.GDP.PETR.RT.ZS?locations=AO | I16: % | J16: - | K16: 0 | L16: 60 | M16: 15 | N16: 1 | O16: Alta | P16: Preenchido via Banco Mundial API/CSV | Q16: 7/11 | R16: 12.71873 | S16: 19.748399 | T16: 24.711006 | U16: 30.730403 | V16: 27.504829 | W16: 18.57196 | X16: 28.27444 | AC16: Proxy de dependência petrolífera; menor dependência é melhor para diversificação.
A17: 2. Estabilidade Macroeconómica | B17: 2. Macroeconomia | C17: Exportações de bens e serviços (% PIB) | D17: Complementar | E17: NE.EXP.GNFS.ZS | F17: Exports of goods and services (% of GDP) | G17: Banco Mundial/WDI | H17: https://data.worldbank.org/indicator/NE.EXP.GNFS.ZS?locations=AO | I17: % | J17: + | K17: 0 | L17: 100 | M17: 40 | N17: 1 | O17: Média | P17: Preenchido via Banco Mundial API/CSV | Q17: 10/11 | R17: 26.148932 | S17: 24.659165 | T17: 25.457235 | U17: 36.245895 | V17: 37.160331 | W17: 31.575828 | X17: 39.449484 | Y17: 35.196053 | Z17: 32.326302 | AA17: 31.483523 | AC17: Acompanha abertura e capacidade exportadora, mas deve ser lido com composição setorial.
A18: 2. Estabilidade Macroeconómica | B18: 2. Macroeconomia | C18: Reservas internacionais em meses de importações | D18: Substituto | E18: FI.RES.TOTL.MO | F18: Total reserves in months of imports | G18: Banco Mundial/WDI | H18: https://data.worldbank.org/indicator/FI.RES.TOTL.MO?locations=AO | I18: Meses | J18: + | K18: 0 | L18: 12 | M18: 6 | N18: 1 | O18: Alta | P18: Preenchido via Banco Mundial API/CSV | Q18: 10/11 | R18: 6.4820457 | S18: 9.0838712 | T18: 5.8181869 | U18: 5.4126402 | V18: 6.4250943 | W18: 8.0261477 | X18: 6.9491541 | Y18: 4.3768329 | Z18: 5.0892711 | AA18: 5.5137491 | AC18: Pode substituir o cálculo manual atualmente colocado abaixo da tabela.
A19: 2. Estabilidade Macroeconómica | B19: 2. Macroeconomia | C19: Crédito doméstico ao setor privado (% PIB) | D19: Complementar | E19: FS.AST.PRVT.GD.ZS | F19: Domestic credit to private sector (% of GDP) | G19: Banco Mundial/WDI | H19: https://data.worldbank.org/indicator/FS.AST.PRVT.GD.ZS?locations=AO | I19: % | J19: + | K19: 0 | L19: 100 | M19: 35 | N19: 1 | O19: Média | P19: Preenchido via Banco Mundial API/CSV | Q19: 10/11 | R19: 22.274928 | S19: 18.590828 | T19: 14.847459 | U19: 13.256401 | V19: 13.471825 | W19: 11.310753 | X19: 8.7024964 | Y19: 6.8656074 | Z19: 7.5654438 | AA19: 7.3166804 | AC19: Acrescenta profundidade financeira e apoio ao investimento privado.
A20: 2. Estabilidade Macroeconómica | B20: 2. Macroeconomia | C20: Crescimento do PIB não petrolífero | D20: Complementar | G20: INE/MEP/BNA | H20: https://www.ine.gov.ao/ | I20: % | J20: + | K20: -10 | L20: 15 | M20: 5 | N20: 1 | O20: Alta | P20: Sem código/API; recolha manual | Q20: 0/11 | AC20: Mais alinhado com a diversificação económica do que o PIB total.
A21: 2. Estabilidade Macroeconómica | B21: 2. Macroeconomia | C21: Volatilidade da taxa de câmbio nominal | D21: Complementar | E21: PA.NUS.FCRF | F21: Official exchange rate, annual absolute variation calculated from PA.NUS.FCRF | G21: Banco Mundial/WDI ou BNA | H21: https://data.worldbank.org/indicator/PA.NUS.FCRF?locations=AO | I21: % variação anual | J21: - | K21: 0 | L21: 80 | M21: 10 | N21: 1 | O21: Média | P21: Calculado: variação absoluta anual de PA.NUS.FCRF | Q21: 10/11 | R21: 22.134028 | S21: 36.311409 | T21: 1.3806463 | U21: 52.399903 | V21: 44.282188 | W21: 58.502708 | X21: 9.1971237 | Y21: 27.06099 | Z21: 48.733947 | AA21: 26.981094 | AC21: Capta instabilidade cambial que afeta preços, dívida e importações.
A22: 3. Capital Humano | B22: 3. Capital Humano | C22: Taxa de alfabetização adulta | D22: Substituto | E22: SE.ADT.LITR.ZS | F22: Literacy rate, adult total (% of people ages 15 and above) | G22: Banco Mundial/UNESCO | H22: https://data.worldbank.org/indicator/SE.ADT.LITR.ZS?locations=AO | I22: % | J22: + | K22: 0 | L22: 100 | M22: 75 | N22: 1 | O22: Alta | P22: Preenchido via Banco Mundial API/CSV | Q22: 2/11 | R22: 66.239998 | Z22: 68.18 | AC22: Preenche a linha existente com fonte internacional comparável.
A23: 3. Capital Humano | B23: 3. Capital Humano | C23: Taxa de conclusão do ensino primário | D23: Complementar | E23: SE.PRM.CMPT.ZS | F23: Primary completion rate, total (% of relevant age group) | G23: Banco Mundial/UNESCO | H23: https://data.worldbank.org/indicator/SE.PRM.CMPT.ZS?locations=AO | I23: % | J23: + | K23: 0 | L23: 100 | M23: 90 | N23: 1 | O23: Alta | P23: Preenchido via Banco Mundial API/CSV | Q23: 2/11 | X23: 60.025939 | Z23: 47.855679 | AC23: Mais robusta que matrícula para medir progressão efetiva.
A24: 3. Capital Humano | B24: 3. Capital Humano | C24: Matrícula no ensino secundário, bruta | D24: Complementar | E24: SE.SEC.ENRR | F24: School enrollment, secondary (% gross) | G24: Banco Mundial/UNESCO | H24: https://data.worldbank.org/indicator/SE.SEC.ENRR?locations=AO | I24: % | J24: + | K24: 0 | L24: 150 | M24: 80 | N24: 1 | O24: Alta | P24: Preenchido via Banco Mundial API/CSV | Q24: 3/11 | S24: 54.416799 | X24: 53.135154 | Z24: 51.483905 | AC24: Captura continuidade pós-primária.
A25: 3. Capital Humano | B25: 3. Capital Humano | C25: Matrícula no ensino terciário, bruta | D25: Complementar | E25: SE.TER.ENRR | F25: School enrollment, tertiary (% gross) | G25: Banco Mundial/UNESCO | H25: https://data.worldbank.org/indicator/SE.TER.ENRR?locations=AO | I25: % | J25: + | K25: 0 | L25: 100 | M25: 20 | N25: 1 | O25: Média | P25: Preenchido via Banco Mundial API/CSV | Q25: 4/11 | R25: 8.7832087 | S25: 9.782877 | Z25: 10.049358 | AA25: 9.9549066 | AC25: Ajuda a medir formação avançada e capacidade técnica.
A26: 3. Capital Humano | B26: 3. Capital Humano | C26: Despesa pública em educação (% PIB) | D26: Complementar | E26: SE.XPD.TOTL.GD.ZS | F26: Government expenditure on education, total (% of GDP) | G26: Banco Mundial/UNESCO | H26: https://data.worldbank.org/indicator/SE.XPD.TOTL.GD.ZS?locations=AO | I26: % | J26: + | K26: 0 | L26: 10 | M26: 5 | N26: 1 | O26: Média | P26: Preenchido via Banco Mundial API/CSV | Q26: 9/11 | R26: 3.4868958 | S26: 2.7549366 | T26: 2.4668788 | U26: 2.183513 | V26: 2.0730644 | W26: 2.6674473 | X26: 2.2971969 | Y26: 2.385359 | Z26: 2.5127366 | AC26: Input de política pública; deve ser combinado com resultados de aprendizagem.
A27: 3. Capital Humano | B27: 3. Capital Humano | C27: Learning poverty - crianças sem proficiência mínima de leitura | D27: Complementar | E27: SE.LPV.PRIM | F27: Learning poverty: Share of Children at the End-of-Primary age below minimum reading proficiency adjusted by Out-of-School Children (%) | G27: Banco Mundial/UNESCO | H27: https://data.worldbank.org/indicator/SE.LPV.PRIM?locations=AO | I27: % | J27: - | K27: 0 | L27: 100 | M27: 50 | N27: 1 | O27: Baixa | P27: Sem valores para Angola em 2014-2025 | Q27: 0/11 | AC27: Mede aprendizagem, não apenas acesso à escola. Usar como benchmark de qualidade; a cobertura anual para Angola é limitada.
A28: 3. Capital Humano | B28: 3. Capital Humano | C28: Rácio alunos/professor no primário | D28: Complementar | E28: SE.PRM.ENRL.TC.ZS | F28: Pupil-teacher ratio, primary | G28: Banco Mundial/UNESCO | H28: https://data.worldbank.org/indicator/SE.PRM.ENRL.TC.ZS?locations=AO | I28: Alunos por professor | J28: - | K28: 10 | L28: 80 | M28: 35 | N28: 1 | O28: Média | P28: Preenchido via Banco Mundial API/CSV | Q28: 1/11 | R28: 50.02951 | AC28: Proxy simples de pressão sobre qualidade de ensino.
A29: 3. Capital Humano | B29: 3. Capital Humano | C29: Índice de Capital Humano | D29: Complementar | E29: HD.HCI.OVRL | F29: Human Capital Index (HCI) (scale 0-1) | G29: Banco Mundial | H29: https://data.worldbank.org/indicator/HD.HCI.OVRL?locations=AO | I29: 0-1 | J29: + | K29: 0 | L29: 1 | M29: 0.5 | N29: 1 | O29: Baixa | P29: Preenchido via Banco Mundial API/CSV | Q29: 3/11 | T29: 0.361 | U29: 0.36019096 | W29: 0.36240539 | AC29: Útil como benchmark, mas menos anual do que os restantes indicadores.
A30: 3. Capital Humano | B30: 3. Capital Humano | C30: Anos esperados de escolaridade | D30: Substituto | G30: PNUD/HDR | H30: https://hdr.undp.org/data-center | I30: Anos | J30: + | K30: 0 | L30: 18 | M30: 12 | N30: 1 | O30: Alta | P30: Sem código/API; recolha manual | Q30: 0/11 | AC30: Substitui ou complementa anos médios de escolaridade quando a série nacional estiver vazia.
A31: 4. Inclusão Social e Protecção | B31: 4. Inclusão Social | C31: Pobreza pela linha nacional | D31: Substituto | E31: SI.POV.NAHC | F31: Poverty headcount ratio at national poverty lines (% of population) | G31: Banco Mundial/PIP | H31: https://data.worldbank.org/indicator/SI.POV.NAHC?locations=AO | I31: % | J31: - | K31: 0 | L31: 80 | M31: 30 | N31: 1 | O31: Alta | P31: Preenchido via Banco Mundial API/CSV | Q31: 1/11 | U31: 32.3 | AC31: Mais diretamente ligada à linha oficial de pobreza do país.
A32: 4. Inclusão Social e Protecção | B32: 4. Inclusão Social | C32: Pobreza internacional a 3,00 USD/dia, PPP 2021 | D32: Substituto | E32: SI.POV.DDAY | F32: Poverty headcount ratio at $3.00 a day (2021 PPP) (% of population) | G32: Banco Mundial/PIP | H32: https://data.worldbank.org/indicator/SI.POV.DDAY?locations=AO | I32: % | J32: - | K32: 0 | L32: 90 | M32: 40 | N32: 1 | O32: Alta | P32: Preenchido via Banco Mundial API/CSV | Q32: 1/11 | U32: 39.3 | AC32: Atualiza a referência internacional que substituiu linhas PPP antigas.
A33: 4. Inclusão Social e Protecção | B33: 4. Inclusão Social | C33: Índice de Gini | D33: Substituto | E33: SI.POV.GINI | F33: Gini index | G33: Banco Mundial/PIP | H33: https://data.worldbank.org/indicator/SI.POV.GINI?locations=AO | I33: 0-100 | J33: - | K33: 0 | L33: 70 | M33: 40 | N33: 1 | O33: Alta | P33: Preenchido via Banco Mundial API/CSV | Q33: 1/11 | U33: 51.3 | AC33: Mantém comparabilidade internacional para desigualdade.
A34: 4. Inclusão Social e Protecção | B34: 4. Inclusão Social | C34: Quota de rendimento dos 20% mais pobres | D34: Complementar | E34: SI.DST.FRST.20 | F34: Income share held by lowest 20% | G34: Banco Mundial/PIP | H34: https://data.worldbank.org/indicator/SI.DST.FRST.20?locations=AO | I34: % | J34: + | K34: 0 | L34: 20 | M34: 7 | N34: 1 | O34: Média | P34: Preenchido via Banco Mundial API/CSV | Q34: 1/11 | U34: 3.8 | AC34: Lê inclusão distributiva de forma complementar ao Gini.
A35: 4. Inclusão Social e Protecção | B35: 4. Inclusão Social | C35: Cobertura de proteção social da população | D35: Substituto | G35: Banco Mundial ASPIRE/OIT | H35: https://www.worldbank.org/en/data/datatopics/aspire | I35: % | J35: + | K35: 0 | L35: 100 | M35: 40 | N35: 1 | O35: Alta | P35: Sem código/API; recolha manual | Q35: 0/11 | AC35: Preenche a lacuna existente de proteção social se houver série ASPIRE/OIT ou INSS.
A36: 4. Inclusão Social e Protecção | B36: 4. Inclusão Social | C36: Índice de Pobreza Multidimensional - incidência | D36: Complementar | G36: PNUD/OPHI | H36: https://hdr.undp.org/data-center/thematic-composite-indices | I36: % | J36: - | K36: 0 | L36: 80 | M36: 25 | N36: 1 | O36: Média | P36: Sem código/API; recolha manual | Q36: 0/11 | AC36: Capta privações simultâneas além de rendimento.
A37: 4. Inclusão Social e Protecção | B37: 4. Inclusão Social | C37: Jovens NEET | D37: Complementar | E37: SL.UEM.NEET.ZS | F37: Share of youth not in education, employment or training, total (% of youth population) | G37: Banco Mundial/OIT | H37: https://data.worldbank.org/indicator/SL.UEM.NEET.ZS?locations=AO | I37: % | J37: - | K37: 0 | L37: 70 | M37: 30 | N37: 1 | O37: Alta | P37: Preenchido via Banco Mundial API/CSV | Q37: 6/11 | V37: 22.922 | W37: 27.286 | X37: 28.126 | Y37: 24.766 | Z37: 21.383 | AA37: 24.564 | AC37: Forte indicador de exclusão de jovens.
A38: 4. Inclusão Social e Protecção | B38: 4. Inclusão Social | C38: Mulheres no parlamento | D38: Complementar | E38: SG.GEN.PARL.ZS | F38: Proportion of seats held by women in national parliaments (%) | G38: Banco Mundial/IPU | H38: https://data.worldbank.org/indicator/SG.GEN.PARL.ZS?locations=AO | I38: % | J38: + | K38: 0 | L38: 60 | M38: 35 | N38: 1 | O38: Média | P38: Preenchido via Banco Mundial API/CSV | Q38: 11/11 | R38: 36.818182 | S38: 36.818182 | T38: 30.454545 | U38: 30.454545 | V38: 30 | W38: 30 | X38: 29.545455 | Y38: 33.636364 | Z38: 33.636364 | AA38: 39.545455 | AB38: 39.090909 | AC38: Mede inclusão política de género.
A39: 4. Inclusão Social e Protecção | B39: 4. Inclusão Social | C39: Participação feminina na força de trabalho | D39: Complementar | E39: SL.TLF.CACT.FE.ZS | F39: Labor force participation rate, female (% of female population ages 15+) (modeled ILO estimate) | G39: Banco Mundial/OIT | H39: https://data.worldbank.org/indicator/SL.TLF.CACT.FE.ZS?locations=AO | I39: % | J39: + | K39: 0 | L39: 100 | M39: 65 | N39: 1 | O39: Média | P39: Preenchido via Banco Mundial API/CSV | Q39: 11/11 | R39: 73.933 | S39: 73.697 | T39: 73.461 | U39: 73.224 | V39: 72.985 | W39: 71.342 | X39: 74.695 | Y39: 74.018 | Z39: 72.318 | AA39: 72.359 | AB39: 72.224 | AC39: Complementa o Global Gender Gap com uma métrica económica anual.
A40: 4. Inclusão Social e Protecção | B40: 4. Inclusão Social | C40: Registo de nascimento completo | D40: Complementar | E40: SP.REG.BRTH.ZS | F40: Completeness of birth registration (%) | G40: Banco Mundial/UNICEF | H40: https://data.worldbank.org/indicator/SP.REG.BRTH.ZS?locations=AO | I40: % | J40: + | K40: 0 | L40: 100 | M40: 80 | N40: 1 | O40: Média | P40: Preenchido via Banco Mundial API/CSV | Q40: 1/11 | S40: 25 | AC40: Proxy de inclusão administrativa e acesso a direitos básicos.
A41: 5. Infraestruturas e Serviços | B41: 5. Infraestruturas | C41: Acesso rural à eletricidade | D41: Complementar | E41: EG.ELC.ACCS.RU.ZS | F41: Access to electricity, rural (% of rural population) | G41: Banco Mundial/IEA | H41: https://data.worldbank.org/indicator/EG.ELC.ACCS.RU.ZS?locations=AO | I41: % | J41: + | K41: 0 | L41: 100 | M41: 50 | N41: 1 | O41: Alta | P41: Preenchido via Banco Mundial API/CSV | Q41: 2/11 | R41: 3.8 | U41: 7.3 | AC41: Evidencia desigualdade territorial no acesso à energia.
A42: 5. Infraestruturas e Serviços | B42: 5. Infraestruturas | C42: Acesso a energia limpa para cozinhar | D42: Complementar | E42: EG.CFT.ACCS.ZS | F42: Access to clean fuels and technologies for cooking (% of population) | G42: Banco Mundial/OMS | H42: https://data.worldbank.org/indicator/EG.CFT.ACCS.ZS?locations=AO | I42: % | J42: + | K42: 0 | L42: 100 | M42: 35 | N42: 1 | O42: Alta | P42: Preenchido via Banco Mundial API/CSV | Q42: 9/11 | R42: 47 | S42: 48 | T42: 48.2 | U42: 48.8 | V42: 49.2 | W42: 49.4 | X42: 49.8 | Y42: 50 | Z42: 50.2 | AC42: Indicador de infraestrutura doméstica com impacto ambiental e de saúde.
A43: 5. Infraestruturas e Serviços | B43: 5. Infraestruturas | C43: Perdas de transmissão e distribuição elétrica | D43: Complementar | E43: EG.ELC.LOSS.ZS | F43: Electric power transmission and distribution losses (% of output) | G43: Banco Mundial/IEA | H43: https://data.worldbank.org/indicator/EG.ELC.LOSS.ZS?locations=AO | I43: % | J43: - | K43: 0 | L43: 60 | M43: 15 | N43: 1 | O43: Média | P43: Preenchido via Banco Mundial API/CSV | Q43: 9/11 | R43: 11.27007 | S43: 11.26696 | T43: 11.258031 | U43: 11.264913 | V43: 11.262912 | W43: 11.266159 | X43: 11.262288 | Y43: 11.261682 | Z43: 11.266798 | AC43: Mede eficiência da rede elétrica, não apenas acesso.
A44: 5. Infraestruturas e Serviços | B44: 5. Infraestruturas | C44: Subscrições móveis por 100 habitantes | D44: Substituto/Complementar | E44: IT.CEL.SETS.P2 | F44: Mobile cellular subscriptions (per 100 people) | G44: Banco Mundial/ITU | H44: https://data.worldbank.org/indicator/IT.CEL.SETS.P2?locations=AO | I44: por 100 hab. | J44: + | K44: 0 | L44: 160 | M44: 100 | N44: 1 | O44: Alta | P44: Preenchido via Banco Mundial API/CSV | Q44: 10/11 | R44: 49.309722 | S44: 44.550227 | T44: 44.068209 | U44: 42.458878 | V44: 45.806531 | W44: 43.780432 | X44: 44.386869 | Y44: 66.600807 | Z44: 70.051959 | AA44: 69.703947 | AC44: Alternativa anual à cobertura 4G quando a série INACOM estiver incompleta.
A45: 5. Infraestruturas e Serviços | B45: 5. Infraestruturas | C45: Banda larga fixa por 100 habitantes | D45: Complementar | E45: IT.NET.BBND.P2 | F45: Fixed broadband subscriptions (per 100 people) | G45: Banco Mundial/ITU | H45: https://data.worldbank.org/indicator/IT.NET.BBND.P2?locations=AO | I45: por 100 hab. | J45: + | K45: 0 | L45: 50 | M45: 8 | N45: 1 | O45: Média | P45: Preenchido via Banco Mundial API/CSV | Q45: 10/11 | R45: 0.54539421 | S45: 0.29031901 | T45: 0.32055405 | U45: 0.35006696 | V45: 0.36777043 | W45: 0.36326424 | X45: 0.3909253 | Y45: 0.38669816 | Z45: 0.37366898 | AA45: 0.36284524 | AC45: Mede infraestrutura digital fixa, distinta do uso de internet.
A46: 5. Infraestruturas e Serviços | B46: 5. Infraestruturas | C46: Preço de cabaz móvel-banda larga (% RNB per capita) | D46: Complementar | G46: ITU DataHub | H46: https://datahub.itu.int/ | I46: % RNB per capita | J46: - | K46: 0 | L46: 30 | M46: 5 | N46: 1 | O46: Média | P46: Sem código/API; recolha manual | Q46: 0/11 | AC46: Capta acessibilidade económica da conectividade.
A47: 5. Infraestruturas e Serviços | B47: 5. Infraestruturas | C47: Água potável básica - população total | D47: Substituto | E47: SH.H2O.BASW.ZS | F47: People using at least basic drinking water services (% of population) | G47: Banco Mundial/JMP | H47: https://data.worldbank.org/indicator/SH.H2O.BASW.ZS?locations=AO | I47: % | J47: + | K47: 0 | L47: 100 | M47: 70 | N47: 1 | O47: Alta | P47: Preenchido via Banco Mundial API/CSV | Q47: 10/11 | R47: 58.619631 | S47: 60.192062 | T47: 61.773512 | U47: 63.362791 | V47: 64.159911 | W47: 64.944031 | X47: 65.716258 | Y47: 66.476327 | Z47: 67.224425 | AA47: 67.960742 | AC47: Fonte comparável para preencher/validar a linha de água potável.
A48: 5. Infraestruturas e Serviços | B48: 5. Infraestruturas | C48: Saneamento básico - população total | D48: Substituto | E48: SH.STA.BASS.ZS | F48: People using at least basic sanitation services (% of population) | G48: Banco Mundial/JMP | H48: https://data.worldbank.org/indicator/SH.STA.BASS.ZS?locations=AO | I48: % | J48: + | K48: 0 | L48: 100 | M48: 60 | N48: 1 | O48: Alta | P48: Preenchido via Banco Mundial API/CSV | Q48: 8/11 | R48: 46.683765 | S48: 47.555909 | T48: 48.423766 | U48: 49.286523 | V48: 49.547024 | W48: 49.801638 | X48: 50.051135 | Y48: 50.295136 | AC48: Fonte comparável para preencher/validar saneamento.
A49: 5. Infraestruturas e Serviços | B49: 5. Infraestruturas | C49: Estradas pavimentadas (% total) | D49: Complementar | E49: IS.ROD.PAVE.ZS | F49: Roads, paved (% of total roads) | G49: Banco Mundial/WDI | H49: https://data.worldbank.org/indicator/IS.ROD.PAVE.ZS?locations=AO | I49: % | J49: + | K49: 0 | L49: 100 | M49: 30 | N49: 1 | O49: Média | P49: Sem valores para Angola em 2014-2025 | Q49: 0/11 | AC49: Complementa densidade rodoviária com qualidade da rede.
A50: 5. Infraestruturas e Serviços | B50: 5. Infraestruturas | C50: Logistics Performance Index - geral | D50: Complementar | E50: LP.LPI.OVRL.XQ | F50: Logistics performance index: Overall (1=low to 5=high) | G50: Banco Mundial/LPI | H50: https://data.worldbank.org/indicator/LP.LPI.OVRL.XQ?locations=AO | I50: 1-5 | J50: + | K50: 1 | L50: 5 | M50: 3 | N50: 1 | O50: Baixa | P50: Preenchido via Banco Mundial API/CSV | Q50: 3/11 | S50: 2.241183 | U50: 2.05 | Y50: 2.1 | AC50: Indicador sintético de logística; útil, mas não anual.
A51: 6. Mercado de Trabalho | B51: 6. Mercado Trabalho | C51: Emprego/população 15+ | D51: Substituto | E51: SL.EMP.TOTL.SP.ZS | F51: Employment to population ratio, 15+, total (%) (modeled ILO estimate) | G51: Banco Mundial/OIT | H51: https://data.worldbank.org/indicator/SL.EMP.TOTL.SP.ZS?locations=AO | I51: % | J51: + | K51: 0 | L51: 100 | M51: 65 | N51: 1 | O51: Alta | P51: Preenchido via Banco Mundial API/CSV | Q51: 11/11 | R51: 63.638 | S51: 63.321 | T51: 63.045 | U51: 62.812 | V51: 62.644 | W51: 61.078 | X51: 64.306 | Y51: 64.619 | Z51: 64.369 | AA51: 64.383 | AB51: 64.236 | AC51: Série internacional para validar a taxa de emprego.
A52: 6. Mercado de Trabalho | B52: 6. Mercado Trabalho | C52: Desemprego total modelado OIT | D52: Substituto | E52: SL.UEM.TOTL.ZS | F52: Unemployment, total (% of total labor force) (modeled ILO estimate) | G52: Banco Mundial/OIT | H52: https://data.worldbank.org/indicator/SL.UEM.TOTL.ZS?locations=AO | I52: % | J52: - | K52: 0 | L52: 50 | M52: 15 | N52: 1 | O52: Alta | P52: Preenchido via Banco Mundial API/CSV | Q52: 11/11 | R52: 16.472 | S52: 16.572 | T52: 16.617 | U52: 16.602 | V52: 16.497 | W52: 16.696 | X52: 15.799 | Y52: 14.124 | Z52: 14.051 | AA52: 14.02 | AB52: 14.108 | AC52: Série anual comparável para anos sem inquérito nacional.
A53: 6. Mercado de Trabalho | B53: 6. Mercado Trabalho | C53: Desemprego juvenil 15-24 | D53: Substituto | E53: SL.UEM.1524.ZS | F53: Unemployment, youth total (% of total labor force ages 15-24) (modeled ILO estimate) | G53: Banco Mundial/OIT | H53: https://data.worldbank.org/indicator/SL.UEM.1524.ZS?locations=AO | I53: % | J53: - | K53: 0 | L53: 70 | M53: 30 | N53: 1 | O53: Alta | P53: Preenchido via Banco Mundial API/CSV | Q53: 11/11 | R53: 35.122 | S53: 34.483 | T53: 33.725 | U53: 32.855 | V53: 31.832 | W53: 33.076 | X53: 30.171 | Y53: 27.143 | Z53: 26.834 | AA53: 26.74 | AB53: 27.229 | AC53: Preenche a lacuna existente de desemprego juvenil.
A54: 6. Mercado de Trabalho | B54: 6. Mercado Trabalho | C54: Participação na força de trabalho | D54: Complementar | E54: SL.TLF.CACT.ZS | F54: Labor force participation rate, total (% of total population ages 15+) (modeled ILO estimate) | G54: Banco Mundial/OIT | H54: https://data.worldbank.org/indicator/SL.TLF.CACT.ZS?locations=AO | I54: % | J54: + | K54: 0 | L54: 100 | M54: 70 | N54: 1 | O54: Alta | P54: Preenchido via Banco Mundial API/CSV | Q54: 11/11 | R54: 76.187 | S54: 75.899 | T54: 75.609 | U54: 75.316 | V54: 75.021 | W54: 73.319 | X54: 76.372 | Y54: 75.247 | Z54: 74.892 | AA54: 74.881 | AB54: 74.786 | AC54: Ajuda a interpretar desemprego junto com atividade laboral.
A55: 6. Mercado de Trabalho | B55: 6. Mercado Trabalho | C55: Emprego vulnerável | D55: Complementar | E55: SL.EMP.VULN.ZS | F55: Vulnerable employment, total (% of total employment) (modeled ILO estimate) | G55: Banco Mundial/OIT | H55: https://data.worldbank.org/indicator/SL.EMP.VULN.ZS?locations=AO | I55: % | J55: - | K55: 0 | L55: 100 | M55: 50 | N55: 1 | O55: Alta | P55: Preenchido via Banco Mundial API/CSV | Q55: 11/11 | R55: 65.262784 | S55: 65.224798 | T55: 65.221118 | U55: 65.260189 | V55: 65.269002 | W55: 65.941091 | X55: 65.793082 | Y55: 66.312488 | Z55: 66.309574 | AA55: 66.233541 | AB55: 66.266595 | AC55: Qualidade do emprego; boa alternativa a informalidade quando esta estiver incompleta.
A56: 6. Mercado de Trabalho | B56: 6. Mercado Trabalho | C56: Trabalhadores assalariados | D56: Complementar | E56: SL.EMP.WORK.ZS | F56: Wage and salaried workers, total (% of total employment) (modeled ILO estimate) | G56: Banco Mundial/OIT | H56: https://data.worldbank.org/indicator/SL.EMP.WORK.ZS?locations=AO | I56: % emprego total | J56: + | K56: 0 | L56: 100 | M56: 50 | N56: 1 | O56: Alta | P56: Preenchido via Banco Mundial API/CSV | Q56: 11/11 | R56: 25.408997 | S56: 25.385663 | T56: 25.326996 | U56: 25.222143 | V56: 25.152635 | W56: 24.578103 | X56: 24.690895 | Y56: 24.154879 | Z56: 24.107087 | AA56: 24.142151 | AB56: 24.09504 | AC56: Proxy de formalização/estrutura moderna do emprego.
A57: 6. Mercado de Trabalho | B57: 6. Mercado Trabalho | C57: Emprego na agricultura | D57: Complementar | E57: SL.AGR.EMPL.ZS | F57: Employment in agriculture (% of total employment) (modeled ILO estimate) | G57: Banco Mundial/OIT | H57: https://data.worldbank.org/indicator/SL.AGR.EMPL.ZS?locations=AO | I57: % emprego total | J57: - | K57: 0 | L57: 100 | M57: 35 | N57: 1 | O57: Média | P57: Preenchido via Banco Mundial API/CSV | Q57: 11/11 | R57: 52.70021 | S57: 52.921321 | T57: 53.008943 | U57: 53.309141 | V57: 53.423323 | W57: 55.559734 | X57: 56.707509 | Y57: 52.484758 | Z57: 52.406629 | AA57: 52.154747 | AB57: 51.949389 | AC57: Proxy de transformação estrutural; deve ser lido com produtividade agrícola.
