Workbook

Sheet Instruções
A1: ÍNDICE DE DESENVOLVIMENTO DE ANGOLA (IGDA-BDA)
A3: INSTRUÇÕES DE UTILIZAÇÃO
A5: 1. ESTRUTURA DO FICHEIRO
A6: Este ficheiro está organizado nas seguintes folhas:
A7: • Instruções - Esta folha com orientações de utilização
A8: • Input_Dados - Onde deve introduzir os valores dos indicadores (células azuis)
A9: • Parametros - Definição de pesos, mínimos e máximos para normalização
A10: • Normalizacao - Cálculo automático da normalização (0-100)
A11: • Subindices - Cálculo dos 7 subíndices temáticos
A12: • Indice_Global - Cálculo do IGDA-BDA e dashboard
A14: 2. COMO UTILIZAR
A15: a) Vá à folha 'Input_Dados' e introduza os valores dos indicadores (pode modificar os indicadores)
... A47: - Subíndices continuam a ser média aritmética ponderada dos indicadores (igual ao Output 1).

Sheet Input_Dados
A1: Subíndice | B1: Indicador | C1: Unidade | D1: Sentido | E1: Fonte | F1: 2015 | G1: 2016 | H1: 2017 | I1: 2018 | J1: 2019 | K1: 2020 | L1: 2021 | M1: 2022 | N1: 2023 | O1: 2024 | P1: 2025
A2: 1. Governança | B2: Índice de Percepção da Corrupção | C2: 0-100 | D2: + | E2: Transparency Int. | F2: 15 | G2: 18 | H2: 19 | I2: 19 | J2: 26 | K2: 27 | L2: 29 | M2: 33 | N2: 33 | O2: 32 | Q2: Angola - Corruption Perceptions Index 2023 | countryeconomy.com
A3: 1. Governança | B3: WGI - Estado de Direito | C3: -2.5 a 2.5 | D3: + | E3: Banco Mundial | F3: -1.3086297 | G3: -1.3287764 | H3: -1.3317055 | I3: -1.1105522 | J3: -1.0519682 | K3: -0.9475038 | L3: -1.0980135 | M3: -1.1625439 | N3: -1.1944432 | O3: -1.1697408 | Q3: Angola's Income Inequality (2018) – Trends & Historical Data
A4: 1. Governança | B4: WGI - Eficiência do Governo | C4: -2.5 a 2.5 | D4: + | E4: Banco Mundial | F4: -0.9378237 | G4: -0.9493847 | H4: -0.9681157 | I4: -0.9784602 | J4: -0.9116965 | K4: -1.0163604 | L4: -0.9347008 | M4: -0.8325718 | N4: -0.8287026 | O4: -0.7851909
A5: 1. Governança | B5: Estabilidade Política (WGI) | C5: -2.5 a 2.5 | D5: + | E5: Banco Mundial | F5: -0.5591026 | G5: -0.434628 | H5: -0.5372145 | I5: -0.4058117 | J5: -0.4207039 | K5: -0.6427634 | L5: -0.7936068 | M5: -0.5414068 | N5: -0.3131654 | O5: -0.5735964
A6: 1. Governança | B6: Doing Business / Ease of Business | C6: 0-100 | D6: + | E6: Banco Mundial | F6: 37.09 | G6: 38.46 | H6: 38.41 | I6: 41.49 | J6: 43.86 | K6: 41.9 | Q6: Internet Users in Angola | 2025 Trends & Rankings | World View Data
A7: 2. Macroeconomia | B7: Taxa de Crescimento do PIB | C7: % | D7: + | E7: INE/MEP | F7: 0.76317771 | G7: -1.7005304 | H7: -0.14939623 | I7: -0.59441123 | J7: -0.20468025 | K7: -4.0424472 | L7: 2.1027525 | M7: 4.2160026 | N7: 1.2633081 | O7: 4.4239066 | Q7: Repositório de Conhecimento Aberto
A8: 2. Macroeconomia | B8: PIB per Capita (USD) | C8: USD | D8: + | E8: INE/MEP | F8: 4400.1341 | G8: 4136.7763 | H8: 4955.1922 | I8: 3214.8018 | J8: 2397.7613 | K8: 1902.3184 | L8: 2990.8603 | M8: 3935.501 | N8: 2773.0062 | O8: 3181.6243
A9: 2. Macroeconomia | B9: Inflação (IPC) | C9: % | D9: - | E9: INE/BNA | F9: 12.094268 | G9: 41.121135 | H9: 23.66655 | I9: 18.601105 | J9: 16.897288 | K9: 25.09653 | L9: 27.029944 | M9: 13.860475 | N9: 20.00716 | O9: 26.480339 | P9: 15.69722
A10: 2. Macroeconomia | B10: Dívida Pública (% do PIB) | C10: % | D10: - | E10: MINFIN | F10: 50 | G10: 67 | H10: 60 | I10: 83 | J10: 101 | K10: 119 | L10: 74 | M10: 56 | N10: 72 | O10: 60 | P10: 63 | Q10: PUBLIC DEBT STATISTICAL BULLETIN AS OF []
A11: 2. Macroeconomia | B11: Saldo Orçamental (% do PIB) | C11: % | D11: + | E11: MINFIN | F11: -2 | G11: -3 | H11: 1.5 | I11: -0.5 | J11: 0.5 | K11: -5 | L11: 1.5 | M11: 0.7 | N11: -1.9 | O11: -1.5 | P11: -1.65
A12: 2. Macroeconomia | B12: IDE não-petrolífero (% PIB) | C12: % | D12: + | E12: AIPEX/BNA
A13: 2. Macroeconomia | B13: Reservas Internacionais (meses) | C13: Meses | D13: + | E13: BNA | F13: =+F47 -> 7.7177632 | G13: =+G47 -> 11.3895 | H13: =+H47 -> 7.7409714 | I13: =+I47 -> 7.4956646 | J13: =+J47 -> 9.2620705 | K13: =+K47 -> 11.788329 | L13: =+L47 -> 9.8750392 | M13: =+M47 -> 6.1590116 | ... P13: =+P47 -> 10.391305
A14: 3. Capital Humano | B14: Índice de Desenvolvimento Humano | C14: 0-1 | D14: + | E14: PNUD | F14: 0.591 | G14: 0.595 | H14: 0.597 | I14: 0.598 | J14: 0.597 | K14: 0.594 | L14: 0.59 | M14: 0.591 | N14: 0.616 | Q14: Relatório do Desenvolvimento Humano (RDH) 2023-2024 | United Nations Development Programme
A15: 3. Capital Humano | B15: Esperança Média de Vida | C15: Anos | D15: + | E15: INE/OMS | F15: 61.042 | G15: 61.619 | H15: 61.7 | I15: 61.7 | J15: 62.2 | K15: 62.48 | L15: 62.72 | M15: 62.95 | N15: 64.617 | O15: 64 | P15: 65 | Q15: Life Expectancy at Birth, Total for Angola (SPDYNLE00INAGO) | FRED | St. Louis Fed
A16: 3. Capital Humano | B16: Taxa de Alfabetização (+15 anos) | C16: % | D16: + | E16: INE/MED
A17: 3. Capital Humano | B17: Taxa de Matrícula (primário) | C17: % | D17: + | E17: MED
A18: 3. Capital Humano | B18: Anos Médios de Escolaridade | C18: Anos | D18: + | E18: UNESCO
A19: 3. Capital Humano | B19: Mortalidade Infantil (por 1000) | C19: ‰ | D19: - | E19: INE/MINSA | H19: 61.1 | I19: 60 | J19: 58.9 | K19: 57.8 | L19: 56.81 | M19: 55.84
A20: 4. Inclusão Social | B20: Taxa de Pobreza (< 2.15 USD/dia) | C20: % | D20: - | E20: INE/BM | I20: 31.1 | Q20: UNdata | record view | Poverty headcount ratio at $2.15 a day (2017 PPP) (% of population)
A21: 4. Inclusão Social | B21: Índice de Gini | C21: 0-100 | D21: - | E21: INE/BM | I21: 51.3 | Q21: Gini index - Angola | Data
A22: 4. Inclusão Social | B22: Cobertura Protecção Social | C22: % | D22: + | E22: INSS
A23: 4. Inclusão Social | B23: Global Gender Gap Index | C23: 0-1 | D23: + | E23: WEF | F23: 0.637 | G23: 0.643 | H23: 0.64 | I23: 0.633 | K23: 0.66 | L23: 0.657 | M23: 0.638 | N23: 0.656 | O23: 0.668 | P23: 0.668 | Q23: Angola - Global Gender Gap Index 2024 | countryeconomy.com
A24: 4. Inclusão Social | B24: RNB per Capita (USD) | C24: USD | D24: + | E24: INE | F24: 2350 | G24: 3100 | H24: 2850 | I24: 2450 | J24: 2300 | K24: 2250 | L24: 2300 | M24: 2400 | N24: 2500 | O24: 2840 | P24: 2900 | Q24: GNI per capita, Atlas method (current US$) - Angola | Data
A25: 5. Infraestruturas | B25: Taxa de Electrificação | C25: % | D25: + | E25: MINEA | F25: 42 | G25: 41.8 | H25: 42.9 | I25: 45.3 | J25: 45.6 | K25: 47 | L25: 48.2 | M25: 48.5 | N25: 51.1 | Q25: Angola - Access To Electricity (% Of Population) - 2026 Data 2027 Forecast 1990-2023 Historical
A26: 5. Infraestruturas | B26: Acesso a Água Potável | C26: % | D26: + | E26: MINEA/INE | F26: 54.3 | G26: 55.1 | H26: 55.8 | I26: 56.6 | J26: 56.9 | K26: 57.2 | L26: 57.4 | M26: 57.7 | Q26: Access to Basic Drinking Water in Angola | 2025 Trends & Rankings | World View Data
A27: 5. Infraestruturas | B27: Acesso a Saneamento Básico | C27: % | D27: + | E27: MINEA/INE | F27: 47 | G27: 48 | H27: 48 | I27: 49 | J27: 50 | K27: 50 | L27: 50 | M27: 50 | Q27: People using at least basic sanitation services (% of population) - Angola | Data
A28: 5. Infraestruturas | B28: Cobertura de Rede 4G | C28: % | D28: + | E28: INACOM | Q28: Não tem estatísticas anuais
A29: 5. Infraestruturas | B29: Utilizadores de Internet (%) | C29: % | D29: + | E29: INACOM | F29: 22 | G29: 23.2 | H29: 26 | I29: 29 | J29: 32.1 | K29: 36.6 | L29: 39.3 | M29: 42 | N29: 44 | Q29: Table Data - Internet users for Angola | FRED | St. Louis Fed
A30: 5. Infraestruturas | B30: Densidade Rodoviária (km/1000km²) | C30: km | D30: + | E30: MINTRANS | F30: 29 | G30: 29 | H30: 29 | I30: 29 | J30: 29 | K30: 30 | L30: 31 | M30: 31 | N30: 32 | O30: 33 | Q30: World Bank Document
A31: 6. Mercado Trabalho | B31: Taxa de Emprego | C31: % | D31: + | E31: INE | J31: 61.190162 | K31: 60.774759 | L31: 61.491468 | M31: 62.715613 | N31: 60.653315 | O31: 61.666148 | P31: 64.441287
A32: 6. Mercado Trabalho | B32: Taxa de Desemprego | C32: % | D32: - | E32: INE | J32: 30.208847 | K32: 32.181087 | L32: 32.320726 | M32: 30.155336 | N32: 31.852861 | O32: 31.466353 | P32: 26.860611
A33: 6. Mercado Trabalho | B33: Desemprego Juvenil (15-25) | C33: % | D33: - | E33: INE
A34: 6. Mercado Trabalho | B34: Emprego Informal (%) | C34: % | D34: - | E34: INE | J34: 74.541816 | K34: 80.353575 | L34: 80.447518 | M34: 79.860137 | N34: 80.488095 | O34: 79.759923 | P34: 77.120842
A35: 6. Mercado Trabalho | B35: Taxa de Formalização | C35: % | D35: + | E35: INSS | J35: 25.458184 | K35: 19.646425 | L35: 19.552482 | M35: 20.139863 | N35: 19.511905 | O35: 20.240077 | P35: 22.879158
A36: 6. Mercado Trabalho | B36: Crescimento da Produtividade | C36: % | D36: + | E36: INE/MEP
A37: 7. Seg. Alimentar/Saúde | B37: Índice Global Seg. Alimentar | C37: 0-100 | D37: + | E37: EIU | F37: 35.1 | O37: 26 | P37: 29.7 | Q37: Indicadores Segurança Alimentar
A38: 7. Seg. Alimentar/Saúde | B38: Prevalência de Desnutrição | C38: % | D38: - | E38: MINSA/FAO | G38: 15.2 | H38: 15.4 | I38: 15.9 | J38: 18.2 | K38: 20.8 | L38: 22.6 | M38: 23.1 | N38: 22.5 | Q38: Angola Prevalence of undernourishment - data, chart | TheGlobalEconomy.com
A39: 7. Seg. Alimentar/Saúde | B39: Mortalidade Materna (por 100k) | C39: por 100k | D39: - | E39: MINSA/OMS | F39: 477 | G39: 442 | H39: 400 | I39: 370 | J39: 330 | K39: 300 | L39: 290 | M39: 250 | N39: 183 | O39: 185 | P39: 170 | Q39: Lifetime risk of maternal death (%) - Angola | Data
A40: 7. Seg. Alimentar/Saúde | B40: Despesas Saúde (% PIB) | C40: % | D40: + | E40: MINFIN/OMS | F40: 2.61 | G40: 2.71 | H40: 2.79 | I40: 2.59 | J40: 2.48 | K40: 3.27 | L40: 3.09 | M40: 2.93 | Q40: Angola Health spending as percent of GDP - data, chart | TheGlobalEconomy.com
A41: 7. Seg. Alimentar/Saúde | B41: Camas Hospitalares (por 1000) | C41: por 1000 | D41: + | E41: MINSA | H41: 0.38 | M41: 1.02
A42: 7. Seg. Alimentar/Saúde | B42: Cobertura Vacinal (%) | C42: % | D42: + | E42: MINSA/OMS | F42: 45 | G42: 42 | H42: 50 | I42: 51 | J42: 44 | K42: 36 | L42: 37 | M42: 37 | N42: 50 | Q42: https://cdn.who.int/media/docs/default-source/country-profiles/immunization/2024-country-profiles/immunization-2024-ago.pdf?utm_source=chatgpt.co
F44: =+F1 -> 2015 | G44: =+G1 -> 2016 | H44: =+H1 -> 2017 | I44: =+I1 -> 2018 | J44: =+J1 -> 2019 | K44: =+K1 -> 2020 | L44: =+L1 -> 2021 | M44: =+M1 -> 2022 | ... P44: =+P1 -> 2025
E45: RIL USD | F45: 24419.495 | G45: 24352.542 | H45: 18227.754 | I45: 16170.244 | J45: 17211.496 | K45: 14878.529 | L45: 15508.1 | M45: 14660.603 | N45: 14726.574 | O45: 15767.562 | P45: 15236.539
E46: Importações | F46: 37968.765 | G46: 25657.887 | H46: 28256.537 | I46: 25887.356 | J46: 22299.329 | K46: 15145.687 | L46: 18845.212 | M46: 28564.199 | N46: 23687.832 | O46: 22682.525 | P46: 17595.332
E47: Meses de Importação | F47: =+(F45*12)/F46 -> 7.7177632 | G47: =+(G45*12)/G46 -> 11.3895 | H47: =+(H45*12)/H46 -> 7.7409714 | I47: =+(I45*12)/I46 -> 7.4956646 | J47: =+(J45*12)/J46 -> 9.2620705 | K47: =+(K45*12)/K46 -> 11.788329 | L47: =+(L45*12)/L46 -> 9.8750392 | M47: =+(M45*12)/M46 -> 6.1590116 | ... P47: =+(P45*12)/P46 -> 10.391305

Sheet Parametros
A1: PARÂMETROS DE NORMALIZAÇÃO E PONDERAÇÃO
A3: Indicador | B3: Mínimo Teórico | C3: Máximo Teórico | D3: Meta 2027 | E3: Peso no Subíndice
A4: Índice de Percepção da Corrupção | B4: 0 | C4: 100 | D4: 35 | E4: 1
A5: WGI - Estado de Direito | B5: -2.5 | C5: 2.5 | D5: 0 | E5: 1
A6: WGI - Eficiência do Governo | B6: -2.5 | C6: 2.5 | D6: 0 | E6: 1
A7: Estabilidade Política (WGI) | B7: -2.5 | C7: 2.5 | D7: 0 | E7: 1
A8: Doing Business / Ease of Business | B8: 0 | C8: 100 | D8: 55 | E8: 1
A9: Taxa de Crescimento do PIB | B9: -10 | C9: 15 | D9: 5 | E9: 1
A10: PIB per Capita (USD) | B10: 500 | C10: 15000 | D10: 5000 | E10: 1
A11: Inflação (IPC) | B11: 0 | C11: 50 | D11: 10 | E11: 1
A12: Dívida Pública (% do PIB) | B12: 0 | C12: 150 | D12: 60 | E12: 1
A13: Saldo Orçamental (% do PIB) | B13: -15 | C13: 10 | D13: 0 | E13: 1
A14: IDE não-petrolífero (% PIB) | B14: 0 | C14: 10 | D14: 3 | E14: 1
A15: Reservas Internacionais (meses) | B15: 0 | C15: 12 | D15: 6 | E15: 1
... A44: Cobertura Vacinal (%) | B44: 0 | C44: 100 | D44: 80 | E44: 1
A46: Limiar de Cobertura Mínima por Subíndice (fração 0-1) | B46: 0.5
A47: Nº Mínimo de Subíndices para calcular o IGDA (de 7) | B47: 4
A50: PESOS DOS SUBÍNDICES
A51: Subíndice | B51: Peso
A52: 1. Governança e Estado de Direito | B52: 1
A53: 2. Estabilidade Macroeconómica | B53: 1
A54: 3. Capital Humano | B54: 1
A55: 4. Inclusão Social | B55: 1
A56: 5. Infraestruturas | B56: 1
A57: 6. Mercado de Trabalho | B57: 1
A58: 7. Segurança Alimentar e Saúde | B58: 1

Sheet Normalizacao
A1: Indicador | B1: Sentido | C1: 2015 | D1: 2016 | E1: 2017 | F1: 2018 | G1: 2019 | H1: 2020 | I1: 2021 | J1: 2022 | K1: 2023 | L1: 2024 | M1: 2025
A2: Índice de Percepção da Corrupção | B2: + | C2: =IF(Input_Dados!F$2="","",MIN(100,MAX(0,(Input_Dados!F$2-Parametros!$B$4)/(Parametros!$C$4-Parametros!$B$4)*100))) -> 15 | D2: =IF(Input_Dados!G$2="","",MIN(100,MAX(0,(Input_Dados!G$2-Parametros!$B$4)/(Parametros!$C$4-Parametros!$B$4)*100))) -> 18 | E2: =IF(Input_Dados!H$2="","",MIN(100,MAX(0,(Input_Dados!H$2-Parametros!$B$4)/(Parametros!$C$4-Parametros!$B$4)*100))) -> 19 | F2: =IF(Input_Dados!I$2="","",MIN(100,MAX(0,(Input_Dados!I$2-Parametros!$B$4)/(Parametros!$C$4-Parametros!$B$4)*100))) -> 19 | G2: =IF(Input_Dados!J$2="","",MIN(100,MAX(0,(Input_Dados!J$2-Parametros!$B$4)/(Parametros!$C$4-Parametros!$B$4)*100))) -> 26 | H2: =IF(Input_Dados!K$2="","",MIN(100,MAX(0,(Input_Dados!K$2-Parametros!$B$4)/(Parametros!$C$4-Parametros!$B$4)*100))) -> 27 | I2: =IF(Input_Dados!L$2="","",MIN(100,MAX(0,(Input_Dados!L$2-Parametros!$B$4)/(Parametros!$C$4-Parametros!$B$4)*100))) -> 29 | J2: =IF(Input_Dados!M$2="","",MIN(100,MAX(0,(Input_Dados!M$2-Parametros!$B$4)/(Parametros!$C$4-Parametros!$B$4)*100))) -> 33 | ... M2: =IF(Input_Dados!P$2="","",MIN(100,MAX(0,(Input_Dados!P$2-Parametros!$B$4)/(Parametros!$C$4-Parametros!$B$4)*100)))
A3: WGI - Estado de Direito | B3: + | C3: =IF(Input_Dados!F$3="","",MIN(100,MAX(0,(Input_Dados!F$3-Parametros!$B$5)/(Parametros!$C$5-Parametros!$B$5)*100))) -> 23.827406 | D3: =IF(Input_Dados!G$3="","",MIN(100,MAX(0,(Input_Dados!G$3-Parametros!$B$5)/(Parametros!$C$5-Parametros!$B$5)*100))) -> 23.424472 | E3: =IF(Input_Dados!H$3="","",MIN(100,MAX(0,(Input_Dados!H$3-Parametros!$B$5)/(Parametros!$C$5-Parametros!$B$5)*100))) -> 23.36589 | F3: =IF(Input_Dados!I$3="","",MIN(100,MAX(0,(Input_Dados!I$3-Parametros!$B$5)/(Parametros!$C$5-Parametros!$B$5)*100))) -> 27.788956 | G3: =IF(Input_Dados!J$3="","",MIN(100,MAX(0,(Input_Dados!J$3-Parametros!$B$5)/(Parametros!$C$5-Parametros!$B$5)*100))) -> 28.960636 | H3: =IF(Input_Dados!K$3="","",MIN(100,MAX(0,(Input_Dados!K$3-Parametros!$B$5)/(Parametros!$C$5-Parametros!$B$5)*100))) -> 31.049924 | I3: =IF(Input_Dados!L$3="","",MIN(100,MAX(0,(Input_Dados!L$3-Parametros!$B$5)/(Parametros!$C$5-Parametros!$B$5)*100))) -> 28.03973 | J3: =IF(Input_Dados!M$3="","",MIN(100,MAX(0,(Input_Dados!M$3-Parametros!$B$5)/(Parametros!$C$5-Parametros!$B$5)*100))) -> 26.749122 | ... M3: =IF(Input_Dados!P$3="","",MIN(100,MAX(0,(Input_Dados!P$3-Parametros!$B$5)/(Parametros!$C$5-Parametros!$B$5)*100)))
A4: WGI - Eficiência do Governo | B4: + | C4: =IF(Input_Dados!F$4="","",MIN(100,MAX(0,(Input_Dados!F$4-Parametros!$B$6)/(Parametros!$C$6-Parametros!$B$6)*100))) -> 31.243526 | D4: =IF(Input_Dados!G$4="","",MIN(100,MAX(0,(Input_Dados!G$4-Parametros!$B$6)/(Parametros!$C$6-Parametros!$B$6)*100))) -> 31.012306 | E4: =IF(Input_Dados!H$4="","",MIN(100,MAX(0,(Input_Dados!H$4-Parametros!$B$6)/(Parametros!$C$6-Parametros!$B$6)*100))) -> 30.637686 | F4: =IF(Input_Dados!I$4="","",MIN(100,MAX(0,(Input_Dados!I$4-Parametros!$B$6)/(Parametros!$C$6-Parametros!$B$6)*100))) -> 30.430796 | G4: =IF(Input_Dados!J$4="","",MIN(100,MAX(0,(Input_Dados!J$4-Parametros!$B$6)/(Parametros!$C$6-Parametros!$B$6)*100))) -> 31.76607 | H4: =IF(Input_Dados!K$4="","",MIN(100,MAX(0,(Input_Dados!K$4-Parametros!$B$6)/(Parametros!$C$6-Parametros!$B$6)*100))) -> 29.672792 | I4: =IF(Input_Dados!L$4="","",MIN(100,MAX(0,(Input_Dados!L$4-Parametros!$B$6)/(Parametros!$C$6-Parametros!$B$6)*100))) -> 31.305984 | J4: =IF(Input_Dados!M$4="","",MIN(100,MAX(0,(Input_Dados!M$4-Parametros!$B$6)/(Parametros!$C$6-Parametros!$B$6)*100))) -> 33.348564 | ... M4: =IF(Input_Dados!P$4="","",MIN(100,MAX(0,(Input_Dados!P$4-Parametros!$B$6)/(Parametros!$C$6-Parametros!$B$6)*100)))
A5: Estabilidade Política (WGI) | B5: + | C5: =IF(Input_Dados!F$5="","",MIN(100,MAX(0,(Input_Dados!F$5-Parametros!$B$7)/(Parametros!$C$7-Parametros!$B$7)*100))) -> 38.817948 | D5: =IF(Input_Dados!G$5="","",MIN(100,MAX(0,(Input_Dados!G$5-Parametros!$B$7)/(Parametros!$C$7-Parametros!$B$7)*100))) -> 41.30744 | E5: =IF(Input_Dados!H$5="","",MIN(100,MAX(0,(Input_Dados!H$5-Parametros!$B$7)/(Parametros!$C$7-Parametros!$B$7)*100))) -> 39.25571 | F5: =IF(Input_Dados!I$5="","",MIN(100,MAX(0,(Input_Dados!I$5-Parametros!$B$7)/(Parametros!$C$7-Parametros!$B$7)*100))) -> 41.883766 | G5: =IF(Input_Dados!J$5="","",MIN(100,MAX(0,(Input_Dados!J$5-Parametros!$B$7)/(Parametros!$C$7-Parametros!$B$7)*100))) -> 41.585922 | H5: =IF(Input_Dados!K$5="","",MIN(100,MAX(0,(Input_Dados!K$5-Parametros!$B$7)/(Parametros!$C$7-Parametros!$B$7)*100))) -> 37.144732 | I5: =IF(Input_Dados!L$5="","",MIN(100,MAX(0,(Input_Dados!L$5-Parametros!$B$7)/(Parametros!$C$7-Parametros!$B$7)*100))) -> 34.127864 | J5: =IF(Input_Dados!M$5="","",MIN(100,MAX(0,(Input_Dados!M$5-Parametros!$B$7)/(Parametros!$C$7-Parametros!$B$7)*100))) -> 39.171864 | ... M5: =IF(Input_Dados!P$5="","",MIN(100,MAX(0,(Input_Dados!P$5-Parametros!$B$7)/(Parametros!$C$7-Parametros!$B$7)*100)))
A6: Doing Business / Ease of Business | B6: + | C6: =IF(Input_Dados!F$6="","",MIN(100,MAX(0,(Input_Dados!F$6-Parametros!$B$8)/(Parametros!$C$8-Parametros!$B$8)*100))) -> 37.09 | D6: =IF(Input_Dados!G$6="","",MIN(100,MAX(0,(Input_Dados!G$6-Parametros!$B$8)/(Parametros!$C$8-Parametros!$B$8)*100))) -> 38.46 | E6: =IF(Input_Dados!H$6="","",MIN(100,MAX(0,(Input_Dados!H$6-Parametros!$B$8)/(Parametros!$C$8-Parametros!$B$8)*100))) -> 38.41 | F6: =IF(Input_Dados!I$6="","",MIN(100,MAX(0,(Input_Dados!I$6-Parametros!$B$8)/(Parametros!$C$8-Parametros!$B$8)*100))) -> 41.49 | G6: =IF(Input_Dados!J$6="","",MIN(100,MAX(0,(Input_Dados!J$6-Parametros!$B$8)/(Parametros!$C$8-Parametros!$B$8)*100))) -> 43.86 | H6: =IF(Input_Dados!K$6="","",MIN(100,MAX(0,(Input_Dados!K$6-Parametros!$B$8)/(Parametros!$C$8-Parametros!$B$8)*100))) -> 41.9 | I6: =IF(Input_Dados!L$6="","",MIN(100,MAX(0,(Input_Dados!L$6-Parametros!$B$8)/(Parametros!$C$8-Parametros!$B$8)*100))) | J6: =IF(Input_Dados!M$6="","",MIN(100,MAX(0,(Input_Dados!M$6-Parametros!$B$8)/(Parametros!$C$8-Parametros!$B$8)*100))) | ... M6: =IF(Input_Dados!P$6="","",MIN(100,MAX(0,(Input_Dados!P$6-Parametros!$B$8)/(Parametros!$C$8-Parametros!$B$8)*100)))
A7: Taxa de Crescimento do PIB | B7: + | C7: =IF(Input_Dados!F$7="","",MIN(100,MAX(0,(Input_Dados!F$7-Parametros!$B$9)/(Parametros!$C$9-Parametros!$B$9)*100))) -> 43.052711 | D7: =IF(Input_Dados!G$7="","",MIN(100,MAX(0,(Input_Dados!G$7-Parametros!$B$9)/(Parametros!$C$9-Parametros!$B$9)*100))) -> 33.197879 | E7: =IF(Input_Dados!H$7="","",MIN(100,MAX(0,(Input_Dados!H$7-Parametros!$B$9)/(Parametros!$C$9-Parametros!$B$9)*100))) -> 39.402415 | F7: =IF(Input_Dados!I$7="","",MIN(100,MAX(0,(Input_Dados!I$7-Parametros!$B$9)/(Parametros!$C$9-Parametros!$B$9)*100))) -> 37.622355 | G7: =IF(Input_Dados!J$7="","",MIN(100,MAX(0,(Input_Dados!J$7-Parametros!$B$9)/(Parametros!$C$9-Parametros!$B$9)*100))) -> 39.181279 | H7: =IF(Input_Dados!K$7="","",MIN(100,MAX(0,(Input_Dados!K$7-Parametros!$B$9)/(Parametros!$C$9-Parametros!$B$9)*100))) -> 23.830211 | I7: =IF(Input_Dados!L$7="","",MIN(100,MAX(0,(Input_Dados!L$7-Parametros!$B$9)/(Parametros!$C$9-Parametros!$B$9)*100))) -> 48.41101 | J7: =IF(Input_Dados!M$7="","",MIN(100,MAX(0,(Input_Dados!M$7-Parametros!$B$9)/(Parametros!$C$9-Parametros!$B$9)*100))) -> 56.86401 | ... M7: =IF(Input_Dados!P$7="","",MIN(100,MAX(0,(Input_Dados!P$7-Parametros!$B$9)/(Parametros!$C$9-Parametros!$B$9)*100)))
A8: PIB per Capita (USD) | B8: + | C8: =IF(Input_Dados!F$8="","",MIN(100,MAX(0,(Input_Dados!F$8-Parametros!$B$10)/(Parametros!$C$10-Parametros!$B$10)*100))) -> 26.897476 | D8: =IF(Input_Dados!G$8="","",MIN(100,MAX(0,(Input_Dados!G$8-Parametros!$B$10)/(Parametros!$C$10-Parametros!$B$10)*100))) -> 25.081216 | E8: =IF(Input_Dados!H$8="","",MIN(100,MAX(0,(Input_Dados!H$8-Parametros!$B$10)/(Parametros!$C$10-Parametros!$B$10)*100))) -> 30.725463 | F8: =IF(Input_Dados!I$8="","",MIN(100,MAX(0,(Input_Dados!I$8-Parametros!$B$10)/(Parametros!$C$10-Parametros!$B$10)*100))) -> 18.722771 | G8: =IF(Input_Dados!J$8="","",MIN(100,MAX(0,(Input_Dados!J$8-Parametros!$B$10)/(Parametros!$C$10-Parametros!$B$10)*100))) -> 13.088009 | H8: =IF(Input_Dados!K$8="","",MIN(100,MAX(0,(Input_Dados!K$8-Parametros!$B$10)/(Parametros!$C$10-Parametros!$B$10)*100))) -> 9.6711614 | I8: =IF(Input_Dados!L$8="","",MIN(100,MAX(0,(Input_Dados!L$8-Parametros!$B$10)/(Parametros!$C$10-Parametros!$B$10)*100))) -> 17.178347 | J8: =IF(Input_Dados!M$8="","",MIN(100,MAX(0,(Input_Dados!M$8-Parametros!$B$10)/(Parametros!$C$10-Parametros!$B$10)*100))) -> 23.69311 | ... M8: =IF(Input_Dados!P$8="","",MIN(100,MAX(0,(Input_Dados!P$8-Parametros!$B$10)/(Parametros!$C$10-Parametros!$B$10)*100)))
A9: Inflação (IPC) | B9: - | C9: =IF(Input_Dados!F$9="","",MIN(100,MAX(0,(Parametros!$C$11-Input_Dados!F$9)/(Parametros!$C$11-Parametros!$B$11)*100))) -> 75.811463 | D9: =IF(Input_Dados!G$9="","",MIN(100,MAX(0,(Parametros!$C$11-Input_Dados!G$9)/(Parametros!$C$11-Parametros!$B$11)*100))) -> 17.75773 | E9: =IF(Input_Dados!H$9="","",MIN(100,MAX(0,(Parametros!$C$11-Input_Dados!H$9)/(Parametros!$C$11-Parametros!$B$11)*100))) -> 52.666901 | F9: =IF(Input_Dados!I$9="","",MIN(100,MAX(0,(Parametros!$C$11-Input_Dados!I$9)/(Parametros!$C$11-Parametros!$B$11)*100))) -> 62.797791 | G9: =IF(Input_Dados!J$9="","",MIN(100,MAX(0,(Parametros!$C$11-Input_Dados!J$9)/(Parametros!$C$11-Parametros!$B$11)*100))) -> 66.205424 | H9: =IF(Input_Dados!K$9="","",MIN(100,MAX(0,(Parametros!$C$11-Input_Dados!K$9)/(Parametros!$C$11-Parametros!$B$11)*100))) -> 49.80694 | I9: =IF(Input_Dados!L$9="","",MIN(100,MAX(0,(Parametros!$C$11-Input_Dados!L$9)/(Parametros!$C$11-Parametros!$B$11)*100))) -> 45.940112 | J9: =IF(Input_Dados!M$9="","",MIN(100,MAX(0,(Parametros!$C$11-Input_Dados!M$9)/(Parametros!$C$11-Parametros!$B$11)*100))) -> 72.279049 | ... M9: =IF(Input_Dados!P$9="","",MIN(100,MAX(0,(Parametros!$C$11-Input_Dados!P$9)/(Parametros!$C$11-Parametros!$B$11)*100))) -> 68.605559
A10: Dívida Pública (% do PIB) | B10: - | C10: =IF(Input_Dados!F$10="","",MIN(100,MAX(0,(Parametros!$C$12-Input_Dados!F$10)/(Parametros!$C$12-Parametros!$B$12)*100))) -> 66.666667 | D10: =IF(Input_Dados!G$10="","",MIN(100,MAX(0,(Parametros!$C$12-Input_Dados!G$10)/(Parametros!$C$12-Parametros!$B$12)*100))) -> 55.333333 | E10: =IF(Input_Dados!H$10="","",MIN(100,MAX(0,(Parametros!$C$12-Input_Dados!H$10)/(Parametros!$C$12-Parametros!$B$12)*100))) -> 60 | F10: =IF(Input_Dados!I$10="","",MIN(100,MAX(0,(Parametros!$C$12-Input_Dados!I$10)/(Parametros!$C$12-Parametros!$B$12)*100))) -> 44.666667 | G10: =IF(Input_Dados!J$10="","",MIN(100,MAX(0,(Parametros!$C$12-Input_Dados!J$10)/(Parametros!$C$12-Parametros!$B$12)*100))) -> 32.666667 | H10: =IF(Input_Dados!K$10="","",MIN(100,MAX(0,(Parametros!$C$12-Input_Dados!K$10)/(Parametros!$C$12-Parametros!$B$12)*100))) -> 20.666667 | I10: =IF(Input_Dados!L$10="","",MIN(100,MAX(0,(Parametros!$C$12-Input_Dados!L$10)/(Parametros!$C$12-Parametros!$B$12)*100))) -> 50.666667 | J10: =IF(Input_Dados!M$10="","",MIN(100,MAX(0,(Parametros!$C$12-Input_Dados!M$10)/(Parametros!$C$12-Parametros!$B$12)*100))) -> 62.666667 | ... M10: =IF(Input_Dados!P$10="","",MIN(100,MAX(0,(Parametros!$C$12-Input_Dados!P$10)/(Parametros!$C$12-Parametros!$B$12)*100))) -> 58
A11: Saldo Orçamental (% do PIB) | B11: + | C11: =IF(Input_Dados!F$11="","",MIN(100,MAX(0,(Input_Dados!F$11-Parametros!$B$13)/(Parametros!$C$13-Parametros!$B$13)*100))) -> 52 | D11: =IF(Input_Dados!G$11="","",MIN(100,MAX(0,(Input_Dados!G$11-Parametros!$B$13)/(Parametros!$C$13-Parametros!$B$13)*100))) -> 48 | E11: =IF(Input_Dados!H$11="","",MIN(100,MAX(0,(Input_Dados!H$11-Parametros!$B$13)/(Parametros!$C$13-Parametros!$B$13)*100))) -> 66 | F11: =IF(Input_Dados!I$11="","",MIN(100,MAX(0,(Input_Dados!I$11-Parametros!$B$13)/(Parametros!$C$13-Parametros!$B$13)*100))) -> 58 | G11: =IF(Input_Dados!J$11="","",MIN(100,MAX(0,(Input_Dados!J$11-Parametros!$B$13)/(Parametros!$C$13-Parametros!$B$13)*100))) -> 62 | H11: =IF(Input_Dados!K$11="","",MIN(100,MAX(0,(Input_Dados!K$11-Parametros!$B$13)/(Parametros!$C$13-Parametros!$B$13)*100))) -> 40 | I11: =IF(Input_Dados!L$11="","",MIN(100,MAX(0,(Input_Dados!L$11-Parametros!$B$13)/(Parametros!$C$13-Parametros!$B$13)*100))) -> 66 | J11: =IF(Input_Dados!M$11="","",MIN(100,MAX(0,(Input_Dados!M$11-Parametros!$B$13)/(Parametros!$C$13-Parametros!$B$13)*100))) -> 62.8 | ... M11: =IF(Input_Dados!P$11="","",MIN(100,MAX(0,(Input_Dados!P$11-Parametros!$B$13)/(Parametros!$C$13-Parametros!$B$13)*100))) -> 53.4
A12: IDE não-petrolífero (% PIB) | B12: + | C12: =IF(Input_Dados!F$12="","",MIN(100,MAX(0,(Input_Dados!F$12-Parametros!$B$14)/(Parametros!$C$14-Parametros!$B$14)*100))) | D12: =IF(Input_Dados!G$12="","",MIN(100,MAX(0,(Input_Dados!G$12-Parametros!$B$14)/(Parametros!$C$14-Parametros!$B$14)*100))) | E12: =IF(Input_Dados!H$12="","",MIN(100,MAX(0,(Input_Dados!H$12-Parametros!$B$14)/(Parametros!$C$14-Parametros!$B$14)*100))) | F12: =IF(Input_Dados!I$12="","",MIN(100,MAX(0,(Input_Dados!I$12-Parametros!$B$14)/(Parametros!$C$14-Parametros!$B$14)*100))) | G12: =IF(Input_Dados!J$12="","",MIN(100,MAX(0,(Input_Dados!J$12-Parametros!$B$14)/(Parametros!$C$14-Parametros!$B$14)*100))) | H12: =IF(Input_Dados!K$12="","",MIN(100,MAX(0,(Input_Dados!K$12-Parametros!$B$14)/(Parametros!$C$14-Parametros!$B$14)*100))) | I12: =IF(Input_Dados!L$12="","",MIN(100,MAX(0,(Input_Dados!L$12-Parametros!$B$14)/(Parametros!$C$14-Parametros!$B$14)*100))) | J12: =IF(Input_Dados!M$12="","",MIN(100,MAX(0,(Input_Dados!M$12-Parametros!$B$14)/(Parametros!$C$14-Parametros!$B$14)*100))) | ... M12: =IF(Input_Dados!P$12="","",MIN(100,MAX(0,(Input_Dados!P$12-Parametros!$B$14)/(Parametros!$C$14-Parametros!$B$14)*100)))
A13: Reservas Internacionais (meses) | B13: + | C13: =IF(Input_Dados!F$13="","",MIN(100,MAX(0,(Input_Dados!F$13-Parametros!$B$15)/(Parametros!$C$15-Parametros!$B$15)*100))) -> 64.314693 | D13: =IF(Input_Dados!G$13="","",MIN(100,MAX(0,(Input_Dados!G$13-Parametros!$B$15)/(Parametros!$C$15-Parametros!$B$15)*100))) -> 94.9125 | E13: =IF(Input_Dados!H$13="","",MIN(100,MAX(0,(Input_Dados!H$13-Parametros!$B$15)/(Parametros!$C$15-Parametros!$B$15)*100))) -> 64.508095 | F13: =IF(Input_Dados!I$13="","",MIN(100,MAX(0,(Input_Dados!I$13-Parametros!$B$15)/(Parametros!$C$15-Parametros!$B$15)*100))) -> 62.463871 | G13: =IF(Input_Dados!J$13="","",MIN(100,MAX(0,(Input_Dados!J$13-Parametros!$B$15)/(Parametros!$C$15-Parametros!$B$15)*100))) -> 77.183921 | H13: =IF(Input_Dados!K$13="","",MIN(100,MAX(0,(Input_Dados!K$13-Parametros!$B$15)/(Parametros!$C$15-Parametros!$B$15)*100))) -> 98.236076 | I13: =IF(Input_Dados!L$13="","",MIN(100,MAX(0,(Input_Dados!L$13-Parametros!$B$15)/(Parametros!$C$15-Parametros!$B$15)*100))) -> 82.291994 | J13: =IF(Input_Dados!M$13="","",MIN(100,MAX(0,(Input_Dados!M$13-Parametros!$B$15)/(Parametros!$C$15-Parametros!$B$15)*100))) -> 51.325097 | ... M13: =IF(Input_Dados!P$13="","",MIN(100,MAX(0,(Input_Dados!P$13-Parametros!$B$15)/(Parametros!$C$15-Parametros!$B$15)*100))) -> 86.594209
A14: Índice de Desenvolvimento Humano | B14: + | C14: =IF(Input_Dados!F$14="","",MIN(100,MAX(0,(Input_Dados!F$14-Parametros!$B$16)/(Parametros!$C$16-Parametros!$B$16)*100))) -> 59.1 | D14: =IF(Input_Dados!G$14="","",MIN(100,MAX(0,(Input_Dados!G$14-Parametros!$B$16)/(Parametros!$C$16-Parametros!$B$16)*100))) -> 59.5 | E14: =IF(Input_Dados!H$14="","",MIN(100,MAX(0,(Input_Dados!H$14-Parametros!$B$16)/(Parametros!$C$16-Parametros!$B$16)*100))) -> 59.7 | F14: =IF(Input_Dados!I$14="","",MIN(100,MAX(0,(Input_Dados!I$14-Parametros!$B$16)/(Parametros!$C$16-Parametros!$B$16)*100))) -> 59.8 | G14: =IF(Input_Dados!J$14="","",MIN(100,MAX(0,(Input_Dados!J$14-Parametros!$B$16)/(Parametros!$C$16-Parametros!$B$16)*100))) -> 59.7 | H14: =IF(Input_Dados!K$14="","",MIN(100,MAX(0,(Input_Dados!K$14-Parametros!$B$16)/(Parametros!$C$16-Parametros!$B$16)*100))) -> 59.4 | I14: =IF(Input_Dados!L$14="","",MIN(100,MAX(0,(Input_Dados!L$14-Parametros!$B$16)/(Parametros!$C$16-Parametros!$B$16)*100))) -> 59 | J14: =IF(Input_Dados!M$14="","",MIN(100,MAX(0,(Input_Dados!M$14-Parametros!$B$16)/(Parametros!$C$16-Parametros!$B$16)*100))) -> 59.1 | ... M14: =IF(Input_Dados!P$14="","",MIN(100,MAX(0,(Input_Dados!P$14-Parametros!$B$16)/(Parametros!$C$16-Parametros!$B$16)*100)))
A15: Esperança Média de Vida | B15: + | C15: =IF(Input_Dados!F$15="","",MIN(100,MAX(0,(Input_Dados!F$15-Parametros!$B$17)/(Parametros!$C$17-Parametros!$B$17)*100))) -> 46.76 | D15: =IF(Input_Dados!G$15="","",MIN(100,MAX(0,(Input_Dados!G$15-Parametros!$B$17)/(Parametros!$C$17-Parametros!$B$17)*100))) -> 48.042222 | E15: =IF(Input_Dados!H$15="","",MIN(100,MAX(0,(Input_Dados!H$15-Parametros!$B$17)/(Parametros!$C$17-Parametros!$B$17)*100))) -> 48.222222 | F15: =IF(Input_Dados!I$15="","",MIN(100,MAX(0,(Input_Dados!I$15-Parametros!$B$17)/(Parametros!$C$17-Parametros!$B$17)*100))) -> 48.222222 | G15: =IF(Input_Dados!J$15="","",MIN(100,MAX(0,(Input_Dados!J$15-Parametros!$B$17)/(Parametros!$C$17-Parametros!$B$17)*100))) -> 49.333333 | H15: =IF(Input_Dados!K$15="","",MIN(100,MAX(0,(Input_Dados!K$15-Parametros!$B$17)/(Parametros!$C$17-Parametros!$B$17)*100))) -> 49.955556 | I15: =IF(Input_Dados!L$15="","",MIN(100,MAX(0,(Input_Dados!L$15-Parametros!$B$17)/(Parametros!$C$17-Parametros!$B$17)*100))) -> 50.488889 | J15: =IF(Input_Dados!M$15="","",MIN(100,MAX(0,(Input_Dados!M$15-Parametros!$B$17)/(Parametros!$C$17-Parametros!$B$17)*100))) -> 51 | ... M15: =IF(Input_Dados!P$15="","",MIN(100,MAX(0,(Input_Dados!P$15-Parametros!$B$17)/(Parametros!$C$17-Parametros!$B$17)*100))) -> 55.555556
A16: Taxa de Alfabetização (+15 anos) | B16: + | C16: =IF(Input_Dados!F$16="","",MIN(100,MAX(0,(Input_Dados!F$16-Parametros!$B$18)/(Parametros!$C$18-Parametros!$B$18)*100))) | D16: =IF(Input_Dados!G$16="","",MIN(100,MAX(0,(Input_Dados!G$16-Parametros!$B$18)/(Parametros!$C$18-Parametros!$B$18)*100))) | E16: =IF(Input_Dados!H$16="","",MIN(100,MAX(0,(Input_Dados!H$16-Parametros!$B$18)/(Parametros!$C$18-Parametros!$B$18)*100))) | F16: =IF(Input_Dados!I$16="","",MIN(100,MAX(0,(Input_Dados!I$16-Parametros!$B$18)/(Parametros!$C$18-Parametros!$B$18)*100))) | G16: =IF(Input_Dados!J$16="","",MIN(100,MAX(0,(Input_Dados!J$16-Parametros!$B$18)/(Parametros!$C$18-Parametros!$B$18)*100))) | H16: =IF(Input_Dados!K$16="","",MIN(100,MAX(0,(Input_Dados!K$16-Parametros!$B$18)/(Parametros!$C$18-Parametros!$B$18)*100))) | I16: =IF(Input_Dados!L$16="","",MIN(100,MAX(0,(Input_Dados!L$16-Parametros!$B$18)/(Parametros!$C$18-Parametros!$B$18)*100))) | J16: =IF(Input_Dados!M$16="","",MIN(100,MAX(0,(Input_Dados!M$16-Parametros!$B$18)/(Parametros!$C$18-Parametros!$B$18)*100))) | ... M16: =IF(Input_Dados!P$16="","",MIN(100,MAX(0,(Input_Dados!P$16-Parametros!$B$18)/(Parametros!$C$18-Parametros!$B$18)*100)))
A17: Taxa de Matrícula (primário) | B17: + | C17: =IF(Input_Dados!F$17="","",MIN(100,MAX(0,(Input_Dados!F$17-Parametros!$B$19)/(Parametros!$C$19-Parametros!$B$19)*100))) | D17: =IF(Input_Dados!G$17="","",MIN(100,MAX(0,(Input_Dados!G$17-Parametros!$B$19)/(Parametros!$C$19-Parametros!$B$19)*100))) | E17: =IF(Input_Dados!H$17="","",MIN(100,MAX(0,(Input_Dados!H$17-Parametros!$B$19)/(Parametros!$C$19-Parametros!$B$19)*100))) | F17: =IF(Input_Dados!I$17="","",MIN(100,MAX(0,(Input_Dados!I$17-Parametros!$B$19)/(Parametros!$C$19-Parametros!$B$19)*100))) | G17: =IF(Input_Dados!J$17="","",MIN(100,MAX(0,(Input_Dados!J$17-Parametros!$B$19)/(Parametros!$C$19-Parametros!$B$19)*100))) | H17: =IF(Input_Dados!K$17="","",MIN(100,MAX(0,(Input_Dados!K$17-Parametros!$B$19)/(Parametros!$C$19-Parametros!$B$19)*100))) | I17: =IF(Input_Dados!L$17="","",MIN(100,MAX(0,(Input_Dados!L$17-Parametros!$B$19)/(Parametros!$C$19-Parametros!$B$19)*100))) | J17: =IF(Input_Dados!M$17="","",MIN(100,MAX(0,(Input_Dados!M$17-Parametros!$B$19)/(Parametros!$C$19-Parametros!$B$19)*100))) | ... M17: =IF(Input_Dados!P$17="","",MIN(100,MAX(0,(Input_Dados!P$17-Parametros!$B$19)/(Parametros!$C$19-Parametros!$B$19)*100)))
A18: Anos Médios de Escolaridade | B18: + | C18: =IF(Input_Dados!F$18="","",MIN(100,MAX(0,(Input_Dados!F$18-Parametros!$B$20)/(Parametros!$C$20-Parametros!$B$20)*100))) | D18: =IF(Input_Dados!G$18="","",MIN(100,MAX(0,(Input_Dados!G$18-Parametros!$B$20)/(Parametros!$C$20-Parametros!$B$20)*100))) | E18: =IF(Input_Dados!H$18="","",MIN(100,MAX(0,(Input_Dados!H$18-Parametros!$B$20)/(Parametros!$C$20-Parametros!$B$20)*100))) | F18: =IF(Input_Dados!I$18="","",MIN(100,MAX(0,(Input_Dados!I$18-Parametros!$B$20)/(Parametros!$C$20-Parametros!$B$20)*100))) | G18: =IF(Input_Dados!J$18="","",MIN(100,MAX(0,(Input_Dados!J$18-Parametros!$B$20)/(Parametros!$C$20-Parametros!$B$20)*100))) | H18: =IF(Input_Dados!K$18="","",MIN(100,MAX(0,(Input_Dados!K$18-Parametros!$B$20)/(Parametros!$C$20-Parametros!$B$20)*100))) | I18: =IF(Input_Dados!L$18="","",MIN(100,MAX(0,(Input_Dados!L$18-Parametros!$B$20)/(Parametros!$C$20-Parametros!$B$20)*100))) | J18: =IF(Input_Dados!M$18="","",MIN(100,MAX(0,(Input_Dados!M$18-Parametros!$B$20)/(Parametros!$C$20-Parametros!$B$20)*100))) | ... M18: =IF(Input_Dados!P$18="","",MIN(100,MAX(0,(Input_Dados!P$18-Parametros!$B$20)/(Parametros!$C$20-Parametros!$B$20)*100)))
A19: Mortalidade Infantil (por 1000) | B19: - | C19: =IF(Input_Dados!F$19="","",MIN(100,MAX(0,(Parametros!$C$21-Input_Dados!F$19)/(Parametros!$C$21-Parametros!$B$21)*100))) | D19: =IF(Input_Dados!G$19="","",MIN(100,MAX(0,(Parametros!$C$21-Input_Dados!G$19)/(Parametros!$C$21-Parametros!$B$21)*100))) | E19: =IF(Input_Dados!H$19="","",MIN(100,MAX(0,(Parametros!$C$21-Input_Dados!H$19)/(Parametros!$C$21-Parametros!$B$21)*100))) -> 59.266667 | F19: =IF(Input_Dados!I$19="","",MIN(100,MAX(0,(Parametros!$C$21-Input_Dados!I$19)/(Parametros!$C$21-Parametros!$B$21)*100))) -> 60 | G19: =IF(Input_Dados!J$19="","",MIN(100,MAX(0,(Parametros!$C$21-Input_Dados!J$19)/(Parametros!$C$21-Parametros!$B$21)*100))) -> 60.733333 | H19: =IF(Input_Dados!K$19="","",MIN(100,MAX(0,(Parametros!$C$21-Input_Dados!K$19)/(Parametros!$C$21-Parametros!$B$21)*100))) -> 61.466667 | I19: =IF(Input_Dados!L$19="","",MIN(100,MAX(0,(Parametros!$C$21-Input_Dados!L$19)/(Parametros!$C$21-Parametros!$B$21)*100))) -> 62.126667 | J19: =IF(Input_Dados!M$19="","",MIN(100,MAX(0,(Parametros!$C$21-Input_Dados!M$19)/(Parametros!$C$21-Parametros!$B$21)*100))) -> 62.773333 | ... M19: =IF(Input_Dados!P$19="","",MIN(100,MAX(0,(Parametros!$C$21-Input_Dados!P$19)/(Parametros!$C$21-Parametros!$B$21)*100)))
A20: Taxa de Pobreza (< 2.15 USD/dia) | B20: - | C20: =IF(Input_Dados!F$20="","",MIN(100,MAX(0,(Parametros!$C$22-Input_Dados!F$20)/(Parametros!$C$22-Parametros!$B$22)*100))) | D20: =IF(Input_Dados!G$20="","",MIN(100,MAX(0,(Parametros!$C$22-Input_Dados!G$20)/(Parametros!$C$22-Parametros!$B$22)*100))) | E20: =IF(Input_Dados!H$20="","",MIN(100,MAX(0,(Parametros!$C$22-Input_Dados!H$20)/(Parametros!$C$22-Parametros!$B$22)*100))) | F20: =IF(Input_Dados!I$20="","",MIN(100,MAX(0,(Parametros!$C$22-Input_Dados!I$20)/(Parametros!$C$22-Parametros!$B$22)*100))) -> 61.125 | G20: =IF(Input_Dados!J$20="","",MIN(100,MAX(0,(Parametros!$C$22-Input_Dados!J$20)/(Parametros!$C$22-Parametros!$B$22)*100))) | H20: =IF(Input_Dados!K$20="","",MIN(100,MAX(0,(Parametros!$C$22-Input_Dados!K$20)/(Parametros!$C$22-Parametros!$B$22)*100))) | I20: =IF(Input_Dados!L$20="","",MIN(100,MAX(0,(Parametros!$C$22-Input_Dados!L$20)/(Parametros!$C$22-Parametros!$B$22)*100))) | J20: =IF(Input_Dados!M$20="","",MIN(100,MAX(0,(Parametros!$C$22-Input_Dados!M$20)/(Parametros!$C$22-Parametros!$B$22)*100))) | ... M20: =IF(Input_Dados!P$20="","",MIN(100,MAX(0,(Parametros!$C$22-Input_Dados!P$20)/(Parametros!$C$22-Parametros!$B$22)*100)))
A21: Índice de Gini | B21: - | C21: =IF(Input_Dados!F$21="","",MIN(100,MAX(0,(Parametros!$C$23-Input_Dados!F$21)/(Parametros!$C$23-Parametros!$B$23)*100))) | D21: =IF(Input_Dados!G$21="","",MIN(100,MAX(0,(Parametros!$C$23-Input_Dados!G$21)/(Parametros!$C$23-Parametros!$B$23)*100))) | E21: =IF(Input_Dados!H$21="","",MIN(100,MAX(0,(Parametros!$C$23-Input_Dados!H$21)/(Parametros!$C$23-Parametros!$B$23)*100))) | F21: =IF(Input_Dados!I$21="","",MIN(100,MAX(0,(Parametros!$C$23-Input_Dados!I$21)/(Parametros!$C$23-Parametros!$B$23)*100))) -> 26.714286 | G21: =IF(Input_Dados!J$21="","",MIN(100,MAX(0,(Parametros!$C$23-Input_Dados!J$21)/(Parametros!$C$23-Parametros!$B$23)*100))) | H21: =IF(Input_Dados!K$21="","",MIN(100,MAX(0,(Parametros!$C$23-Input_Dados!K$21)/(Parametros!$C$23-Parametros!$B$23)*100))) | I21: =IF(Input_Dados!L$21="","",MIN(100,MAX(0,(Parametros!$C$23-Input_Dados!L$21)/(Parametros!$C$23-Parametros!$B$23)*100))) | J21: =IF(Input_Dados!M$21="","",MIN(100,MAX(0,(Parametros!$C$23-Input_Dados!M$21)/(Parametros!$C$23-Parametros!$B$23)*100))) | ... M21: =IF(Input_Dados!P$21="","",MIN(100,MAX(0,(Parametros!$C$23-Input_Dados!P$21)/(Parametros!$C$23-Parametros!$B$23)*100)))
A22: Cobertura Protecção Social | B22: + | C22: =IF(Input_Dados!F$22="","",MIN(100,MAX(0,(Input_Dados!F$22-Parametros!$B$24)/(Parametros!$C$24-Parametros!$B$24)*100))) | D22: =IF(Input_Dados!G$22="","",MIN(100,MAX(0,(Input_Dados!G$22-Parametros!$B$24)/(Parametros!$C$24-Parametros!$B$24)*100))) | E22: =IF(Input_Dados!H$22="","",MIN(100,MAX(0,(Input_Dados!H$22-Parametros!$B$24)/(Parametros!$C$24-Parametros!$B$24)*100))) | F22: =IF(Input_Dados!I$22="","",MIN(100,MAX(0,(Input_Dados!I$22-Parametros!$B$24)/(Parametros!$C$24-Parametros!$B$24)*100))) | G22: =IF(Input_Dados!J$22="","",MIN(100,MAX(0,(Input_Dados!J$22-Parametros!$B$24)/(Parametros!$C$24-Parametros!$B$24)*100))) | H22: =IF(Input_Dados!K$22="","",MIN(100,MAX(0,(Input_Dados!K$22-Parametros!$B$24)/(Parametros!$C$24-Parametros!$B$24)*100))) | I22: =IF(Input_Dados!L$22="","",MIN(100,MAX(0,(Input_Dados!L$22-Parametros!$B$24)/(Parametros!$C$24-Parametros!$B$24)*100))) | J22: =IF(Input_Dados!M$22="","",MIN(100,MAX(0,(Input_Dados!M$22-Parametros!$B$24)/(Parametros!$C$24-Parametros!$B$24)*100))) | ... M22: =IF(Input_Dados!P$22="","",MIN(100,MAX(0,(Input_Dados!P$22-Parametros!$B$24)/(Parametros!$C$24-Parametros!$B$24)*100)))
A23: Global Gender Gap Index | B23: + | C23: =IF(Input_Dados!F$23="","",MIN(100,MAX(0,(Input_Dados!F$23-Parametros!$B$25)/(Parametros!$C$25-Parametros!$B$25)*100))) -> 63.7 | D23: =IF(Input_Dados!G$23="","",MIN(100,MAX(0,(Input_Dados!G$23-Parametros!$B$25)/(Parametros!$C$25-Parametros!$B$25)*100))) -> 64.3 | E23: =IF(Input_Dados!H$23="","",MIN(100,MAX(0,(Input_Dados!H$23-Parametros!$B$25)/(Parametros!$C$25-Parametros!$B$25)*100))) -> 64 | F23: =IF(Input_Dados!I$23="","",MIN(100,MAX(0,(Input_Dados!I$23-Parametros!$B$25)/(Parametros!$C$25-Parametros!$B$25)*100))) -> 63.3 | G23: =IF(Input_Dados!J$23="","",MIN(100,MAX(0,(Input_Dados!J$23-Parametros!$B$25)/(Parametros!$C$25-Parametros!$B$25)*100))) | H23: =IF(Input_Dados!K$23="","",MIN(100,MAX(0,(Input_Dados!K$23-Parametros!$B$25)/(Parametros!$C$25-Parametros!$B$25)*100))) -> 66 | I23: =IF(Input_Dados!L$23="","",MIN(100,MAX(0,(Input_Dados!L$23-Parametros!$B$25)/(Parametros!$C$25-Parametros!$B$25)*100))) -> 65.7 | J23: =IF(Input_Dados!M$23="","",MIN(100,MAX(0,(Input_Dados!M$23-Parametros!$B$25)/(Parametros!$C$25-Parametros!$B$25)*100))) -> 63.8 | ... M23: =IF(Input_Dados!P$23="","",MIN(100,MAX(0,(Input_Dados!P$23-Parametros!$B$25)/(Parametros!$C$25-Parametros!$B$25)*100))) -> 66.8
A24: RNB per Capita (USD) | B24: + | C24: =IF(Input_Dados!F$24="","",MIN(100,MAX(0,(Input_Dados!F$24-Parametros!$B$26)/(Parametros!$C$26-Parametros!$B$26)*100))) -> 12.758621 | D24: =IF(Input_Dados!G$24="","",MIN(100,MAX(0,(Input_Dados!G$24-Parametros!$B$26)/(Parametros!$C$26-Parametros!$B$26)*100))) -> 17.931034 | E24: =IF(Input_Dados!H$24="","",MIN(100,MAX(0,(Input_Dados!H$24-Parametros!$B$26)/(Parametros!$C$26-Parametros!$B$26)*100))) -> 16.206897 | F24: =IF(Input_Dados!I$24="","",MIN(100,MAX(0,(Input_Dados!I$24-Parametros!$B$26)/(Parametros!$C$26-Parametros!$B$26)*100))) -> 13.448276 | G24: =IF(Input_Dados!J$24="","",MIN(100,MAX(0,(Input_Dados!J$24-Parametros!$B$26)/(Parametros!$C$26-Parametros!$B$26)*100))) -> 12.413793 | H24: =IF(Input_Dados!K$24="","",MIN(100,MAX(0,(Input_Dados!K$24-Parametros!$B$26)/(Parametros!$C$26-Parametros!$B$26)*100))) -> 12.068966 | I24: =IF(Input_Dados!L$24="","",MIN(100,MAX(0,(Input_Dados!L$24-Parametros!$B$26)/(Parametros!$C$26-Parametros!$B$26)*100))) -> 12.413793 | J24: =IF(Input_Dados!M$24="","",MIN(100,MAX(0,(Input_Dados!M$24-Parametros!$B$26)/(Parametros!$C$26-Parametros!$B$26)*100))) -> 13.103448 | ... M24: =IF(Input_Dados!P$24="","",MIN(100,MAX(0,(Input_Dados!P$24-Parametros!$B$26)/(Parametros!$C$26-Parametros!$B$26)*100))) -> 16.551724
A25: Taxa de Electrificação | B25: + | C25: =IF(Input_Dados!F$25="","",MIN(100,MAX(0,(Input_Dados!F$25-Parametros!$B$27)/(Parametros!$C$27-Parametros!$B$27)*100))) -> 42 | D25: =IF(Input_Dados!G$25="","",MIN(100,MAX(0,(Input_Dados!G$25-Parametros!$B$27)/(Parametros!$C$27-Parametros!$B$27)*100))) -> 41.8 | E25: =IF(Input_Dados!H$25="","",MIN(100,MAX(0,(Input_Dados!H$25-Parametros!$B$27)/(Parametros!$C$27-Parametros!$B$27)*100))) -> 42.9 | F25: =IF(Input_Dados!I$25="","",MIN(100,MAX(0,(Input_Dados!I$25-Parametros!$B$27)/(Parametros!$C$27-Parametros!$B$27)*100))) -> 45.3 | G25: =IF(Input_Dados!J$25="","",MIN(100,MAX(0,(Input_Dados!J$25-Parametros!$B$27)/(Parametros!$C$27-Parametros!$B$27)*100))) -> 45.6 | H25: =IF(Input_Dados!K$25="","",MIN(100,MAX(0,(Input_Dados!K$25-Parametros!$B$27)/(Parametros!$C$27-Parametros!$B$27)*100))) -> 47 | I25: =IF(Input_Dados!L$25="","",MIN(100,MAX(0,(Input_Dados!L$25-Parametros!$B$27)/(Parametros!$C$27-Parametros!$B$27)*100))) -> 48.2 | J25: =IF(Input_Dados!M$25="","",MIN(100,MAX(0,(Input_Dados!M$25-Parametros!$B$27)/(Parametros!$C$27-Parametros!$B$27)*100))) -> 48.5 | ... M25: =IF(Input_Dados!P$25="","",MIN(100,MAX(0,(Input_Dados!P$25-Parametros!$B$27)/(Parametros!$C$27-Parametros!$B$27)*100)))
A26: Acesso a Água Potável | B26: + | C26: =IF(Input_Dados!F$26="","",MIN(100,MAX(0,(Input_Dados!F$26-Parametros!$B$28)/(Parametros!$C$28-Parametros!$B$28)*100))) -> 54.3 | D26: =IF(Input_Dados!G$26="","",MIN(100,MAX(0,(Input_Dados!G$26-Parametros!$B$28)/(Parametros!$C$28-Parametros!$B$28)*100))) -> 55.1 | E26: =IF(Input_Dados!H$26="","",MIN(100,MAX(0,(Input_Dados!H$26-Parametros!$B$28)/(Parametros!$C$28-Parametros!$B$28)*100))) -> 55.8 | F26: =IF(Input_Dados!I$26="","",MIN(100,MAX(0,(Input_Dados!I$26-Parametros!$B$28)/(Parametros!$C$28-Parametros!$B$28)*100))) -> 56.6 | G26: =IF(Input_Dados!J$26="","",MIN(100,MAX(0,(Input_Dados!J$26-Parametros!$B$28)/(Parametros!$C$28-Parametros!$B$28)*100))) -> 56.9 | H26: =IF(Input_Dados!K$26="","",MIN(100,MAX(0,(Input_Dados!K$26-Parametros!$B$28)/(Parametros!$C$28-Parametros!$B$28)*100))) -> 57.2 | I26: =IF(Input_Dados!L$26="","",MIN(100,MAX(0,(Input_Dados!L$26-Parametros!$B$28)/(Parametros!$C$28-Parametros!$B$28)*100))) -> 57.4 | J26: =IF(Input_Dados!M$26="","",MIN(100,MAX(0,(Input_Dados!M$26-Parametros!$B$28)/(Parametros!$C$28-Parametros!$B$28)*100))) -> 57.7 | ... M26: =IF(Input_Dados!P$26="","",MIN(100,MAX(0,(Input_Dados!P$26-Parametros!$B$28)/(Parametros!$C$28-Parametros!$B$28)*100)))
A27: Acesso a Saneamento Básico | B27: + | C27: =IF(Input_Dados!F$27="","",MIN(100,MAX(0,(Input_Dados!F$27-Parametros!$B$29)/(Parametros!$C$29-Parametros!$B$29)*100))) -> 47 | D27: =IF(Input_Dados!G$27="","",MIN(100,MAX(0,(Input_Dados!G$27-Parametros!$B$29)/(Parametros!$C$29-Parametros!$B$29)*100))) -> 48 | E27: =IF(Input_Dados!H$27="","",MIN(100,MAX(0,(Input_Dados!H$27-Parametros!$B$29)/(Parametros!$C$29-Parametros!$B$29)*100))) -> 48 | F27: =IF(Input_Dados!I$27="","",MIN(100,MAX(0,(Input_Dados!I$27-Parametros!$B$29)/(Parametros!$C$29-Parametros!$B$29)*100))) -> 49 | G27: =IF(Input_Dados!J$27="","",MIN(100,MAX(0,(Input_Dados!J$27-Parametros!$B$29)/(Parametros!$C$29-Parametros!$B$29)*100))) -> 50 | H27: =IF(Input_Dados!K$27="","",MIN(100,MAX(0,(Input_Dados!K$27-Parametros!$B$29)/(Parametros!$C$29-Parametros!$B$29)*100))) -> 50 | I27: =IF(Input_Dados!L$27="","",MIN(100,MAX(0,(Input_Dados!L$27-Parametros!$B$29)/(Parametros!$C$29-Parametros!$B$29)*100))) -> 50 | J27: =IF(Input_Dados!M$27="","",MIN(100,MAX(0,(Input_Dados!M$27-Parametros!$B$29)/(Parametros!$C$29-Parametros!$B$29)*100))) -> 50 | ... M27: =IF(Input_Dados!P$27="","",MIN(100,MAX(0,(Input_Dados!P$27-Parametros!$B$29)/(Parametros!$C$29-Parametros!$B$29)*100)))
A28: Cobertura de Rede 4G | B28: + | C28: =IF(Input_Dados!F$28="","",MIN(100,MAX(0,(Input_Dados!F$28-Parametros!$B$30)/(Parametros!$C$30-Parametros!$B$30)*100))) | D28: =IF(Input_Dados!G$28="","",MIN(100,MAX(0,(Input_Dados!G$28-Parametros!$B$30)/(Parametros!$C$30-Parametros!$B$30)*100))) | E28: =IF(Input_Dados!H$28="","",MIN(100,MAX(0,(Input_Dados!H$28-Parametros!$B$30)/(Parametros!$C$30-Parametros!$B$30)*100))) | F28: =IF(Input_Dados!I$28="","",MIN(100,MAX(0,(Input_Dados!I$28-Parametros!$B$30)/(Parametros!$C$30-Parametros!$B$30)*100))) | G28: =IF(Input_Dados!J$28="","",MIN(100,MAX(0,(Input_Dados!J$28-Parametros!$B$30)/(Parametros!$C$30-Parametros!$B$30)*100))) | H28: =IF(Input_Dados!K$28="","",MIN(100,MAX(0,(Input_Dados!K$28-Parametros!$B$30)/(Parametros!$C$30-Parametros!$B$30)*100))) | I28: =IF(Input_Dados!L$28="","",MIN(100,MAX(0,(Input_Dados!L$28-Parametros!$B$30)/(Parametros!$C$30-Parametros!$B$30)*100))) | J28: =IF(Input_Dados!M$28="","",MIN(100,MAX(0,(Input_Dados!M$28-Parametros!$B$30)/(Parametros!$C$30-Parametros!$B$30)*100))) | ... M28: =IF(Input_Dados!P$28="","",MIN(100,MAX(0,(Input_Dados!P$28-Parametros!$B$30)/(Parametros!$C$30-Parametros!$B$30)*100)))
A29: Utilizadores de Internet (%) | B29: + | C29: =IF(Input_Dados!F$29="","",MIN(100,MAX(0,(Input_Dados!F$29-Parametros!$B$31)/(Parametros!$C$31-Parametros!$B$31)*100))) -> 22 | D29: =IF(Input_Dados!G$29="","",MIN(100,MAX(0,(Input_Dados!G$29-Parametros!$B$31)/(Parametros!$C$31-Parametros!$B$31)*100))) -> 23.2 | E29: =IF(Input_Dados!H$29="","",MIN(100,MAX(0,(Input_Dados!H$29-Parametros!$B$31)/(Parametros!$C$31-Parametros!$B$31)*100))) -> 26 | F29: =IF(Input_Dados!I$29="","",MIN(100,MAX(0,(Input_Dados!I$29-Parametros!$B$31)/(Parametros!$C$31-Parametros!$B$31)*100))) -> 29 | G29: =IF(Input_Dados!J$29="","",MIN(100,MAX(0,(Input_Dados!J$29-Parametros!$B$31)/(Parametros!$C$31-Parametros!$B$31)*100))) -> 32.1 | H29: =IF(Input_Dados!K$29="","",MIN(100,MAX(0,(Input_Dados!K$29-Parametros!$B$31)/(Parametros!$C$31-Parametros!$B$31)*100))) -> 36.6 | I29: =IF(Input_Dados!L$29="","",MIN(100,MAX(0,(Input_Dados!L$29-Parametros!$B$31)/(Parametros!$C$31-Parametros!$B$31)*100))) -> 39.3 | J29: =IF(Input_Dados!M$29="","",MIN(100,MAX(0,(Input_Dados!M$29-Parametros!$B$31)/(Parametros!$C$31-Parametros!$B$31)*100))) -> 42 | ... M29: =IF(Input_Dados!P$29="","",MIN(100,MAX(0,(Input_Dados!P$29-Parametros!$B$31)/(Parametros!$C$31-Parametros!$B$31)*100)))
A30: Densidade Rodoviária (km/1000km²) | B30: + | C30: =IF(Input_Dados!F$30="","",MIN(100,MAX(0,(Input_Dados!F$30-Parametros!$B$32)/(Parametros!$C$32-Parametros!$B$32)*100))) -> 29 | D30: =IF(Input_Dados!G$30="","",MIN(100,MAX(0,(Input_Dados!G$30-Parametros!$B$32)/(Parametros!$C$32-Parametros!$B$32)*100))) -> 29 | E30: =IF(Input_Dados!H$30="","",MIN(100,MAX(0,(Input_Dados!H$30-Parametros!$B$32)/(Parametros!$C$32-Parametros!$B$32)*100))) -> 29 | F30: =IF(Input_Dados!I$30="","",MIN(100,MAX(0,(Input_Dados!I$30-Parametros!$B$32)/(Parametros!$C$32-Parametros!$B$32)*100))) -> 29 | G30: =IF(Input_Dados!J$30="","",MIN(100,MAX(0,(Input_Dados!J$30-Parametros!$B$32)/(Parametros!$C$32-Parametros!$B$32)*100))) -> 29 | H30: =IF(Input_Dados!K$30="","",MIN(100,MAX(0,(Input_Dados!K$30-Parametros!$B$32)/(Parametros!$C$32-Parametros!$B$32)*100))) -> 30 | I30: =IF(Input_Dados!L$30="","",MIN(100,MAX(0,(Input_Dados!L$30-Parametros!$B$32)/(Parametros!$C$32-Parametros!$B$32)*100))) -> 31 | J30: =IF(Input_Dados!M$30="","",MIN(100,MAX(0,(Input_Dados!M$30-Parametros!$B$32)/(Parametros!$C$32-Parametros!$B$32)*100))) -> 31 | ... M30: =IF(Input_Dados!P$30="","",MIN(100,MAX(0,(Input_Dados!P$30-Parametros!$B$32)/(Parametros!$C$32-Parametros!$B$32)*100)))
A31: Taxa de Emprego | B31: + | C31: =IF(Input_Dados!F$31="","",MIN(100,MAX(0,(Input_Dados!F$31-Parametros!$B$33)/(Parametros!$C$33-Parametros!$B$33)*100))) | D31: =IF(Input_Dados!G$31="","",MIN(100,MAX(0,(Input_Dados!G$31-Parametros!$B$33)/(Parametros!$C$33-Parametros!$B$33)*100))) | E31: =IF(Input_Dados!H$31="","",MIN(100,MAX(0,(Input_Dados!H$31-Parametros!$B$33)/(Parametros!$C$33-Parametros!$B$33)*100))) | F31: =IF(Input_Dados!I$31="","",MIN(100,MAX(0,(Input_Dados!I$31-Parametros!$B$33)/(Parametros!$C$33-Parametros!$B$33)*100))) | G31: =IF(Input_Dados!J$31="","",MIN(100,MAX(0,(Input_Dados!J$31-Parametros!$B$33)/(Parametros!$C$33-Parametros!$B$33)*100))) -> 61.190162 | H31: =IF(Input_Dados!K$31="","",MIN(100,MAX(0,(Input_Dados!K$31-Parametros!$B$33)/(Parametros!$C$33-Parametros!$B$33)*100))) -> 60.774759 | I31: =IF(Input_Dados!L$31="","",MIN(100,MAX(0,(Input_Dados!L$31-Parametros!$B$33)/(Parametros!$C$33-Parametros!$B$33)*100))) -> 61.491468 | J31: =IF(Input_Dados!M$31="","",MIN(100,MAX(0,(Input_Dados!M$31-Parametros!$B$33)/(Parametros!$C$33-Parametros!$B$33)*100))) -> 62.715613 | ... M31: =IF(Input_Dados!P$31="","",MIN(100,MAX(0,(Input_Dados!P$31-Parametros!$B$33)/(Parametros!$C$33-Parametros!$B$33)*100))) -> 64.441287
A32: Taxa de Desemprego | B32: - | C32: =IF(Input_Dados!F$32="","",MIN(100,MAX(0,(Parametros!$C$34-Input_Dados!F$32)/(Parametros!$C$34-Parametros!$B$34)*100))) | D32: =IF(Input_Dados!G$32="","",MIN(100,MAX(0,(Parametros!$C$34-Input_Dados!G$32)/(Parametros!$C$34-Parametros!$B$34)*100))) | E32: =IF(Input_Dados!H$32="","",MIN(100,MAX(0,(Parametros!$C$34-Input_Dados!H$32)/(Parametros!$C$34-Parametros!$B$34)*100))) | F32: =IF(Input_Dados!I$32="","",MIN(100,MAX(0,(Parametros!$C$34-Input_Dados!I$32)/(Parametros!$C$34-Parametros!$B$34)*100))) | G32: =IF(Input_Dados!J$32="","",MIN(100,MAX(0,(Parametros!$C$34-Input_Dados!J$32)/(Parametros!$C$34-Parametros!$B$34)*100))) -> 39.582306 | H32: =IF(Input_Dados!K$32="","",MIN(100,MAX(0,(Parametros!$C$34-Input_Dados!K$32)/(Parametros!$C$34-Parametros!$B$34)*100))) -> 35.637826 | I32: =IF(Input_Dados!L$32="","",MIN(100,MAX(0,(Parametros!$C$34-Input_Dados!L$32)/(Parametros!$C$34-Parametros!$B$34)*100))) -> 35.358548 | J32: =IF(Input_Dados!M$32="","",MIN(100,MAX(0,(Parametros!$C$34-Input_Dados!M$32)/(Parametros!$C$34-Parametros!$B$34)*100))) -> 39.689327 | ... M32: =IF(Input_Dados!P$32="","",MIN(100,MAX(0,(Parametros!$C$34-Input_Dados!P$32)/(Parametros!$C$34-Parametros!$B$34)*100))) -> 46.278778
A33: Desemprego Juvenil | B33: - | C33: =IF(Input_Dados!F$33="","",MIN(100,MAX(0,(Parametros!$C$35-Input_Dados!F$33)/(Parametros!$C$35-Parametros!$B$35)*100))) | D33: =IF(Input_Dados!G$33="","",MIN(100,MAX(0,(Parametros!$C$35-Input_Dados!G$33)/(Parametros!$C$35-Parametros!$B$35)*100))) | E33: =IF(Input_Dados!H$33="","",MIN(100,MAX(0,(Parametros!$C$35-Input_Dados!H$33)/(Parametros!$C$35-Parametros!$B$35)*100))) | F33: =IF(Input_Dados!I$33="","",MIN(100,MAX(0,(Parametros!$C$35-Input_Dados!I$33)/(Parametros!$C$35-Parametros!$B$35)*100))) | G33: =IF(Input_Dados!J$33="","",MIN(100,MAX(0,(Parametros!$C$35-Input_Dados!J$33)/(Parametros!$C$35-Parametros!$B$35)*100))) | H33: =IF(Input_Dados!K$33="","",MIN(100,MAX(0,(Parametros!$C$35-Input_Dados!K$33)/(Parametros!$C$35-Parametros!$B$35)*100))) | I33: =IF(Input_Dados!L$33="","",MIN(100,MAX(0,(Parametros!$C$35-Input_Dados!L$33)/(Parametros!$C$35-Parametros!$B$35)*100))) | J33: =IF(Input_Dados!M$33="","",MIN(100,MAX(0,(Parametros!$C$35-Input_Dados!M$33)/(Parametros!$C$35-Parametros!$B$35)*100))) | ... M33: =IF(Input_Dados!P$33="","",MIN(100,MAX(0,(Parametros!$C$35-Input_Dados!P$33)/(Parametros!$C$35-Parametros!$B$35)*100)))
A34: Emprego Informal (%) | B34: - | C34: =IF(Input_Dados!F$34="","",MIN(100,MAX(0,(Parametros!$C$36-Input_Dados!F$34)/(Parametros!$C$36-Parametros!$B$36)*100))) | D34: =IF(Input_Dados!G$34="","",MIN(100,MAX(0,(Parametros!$C$36-Input_Dados!G$34)/(Parametros!$C$36-Parametros!$B$36)*100))) | E34: =IF(Input_Dados!H$34="","",MIN(100,MAX(0,(Parametros!$C$36-Input_Dados!H$34)/(Parametros!$C$36-Parametros!$B$36)*100))) | F34: =IF(Input_Dados!I$34="","",MIN(100,MAX(0,(Parametros!$C$36-Input_Dados!I$34)/(Parametros!$C$36-Parametros!$B$36)*100))) | G34: =IF(Input_Dados!J$34="","",MIN(100,MAX(0,(Parametros!$C$36-Input_Dados!J$34)/(Parametros!$C$36-Parametros!$B$36)*100))) -> 25.458184 | H34: =IF(Input_Dados!K$34="","",MIN(100,MAX(0,(Parametros!$C$36-Input_Dados!K$34)/(Parametros!$C$36-Parametros!$B$36)*100))) -> 19.646425 | I34: =IF(Input_Dados!L$34="","",MIN(100,MAX(0,(Parametros!$C$36-Input_Dados!L$34)/(Parametros!$C$36-Parametros!$B$36)*100))) -> 19.552482 | J34: =IF(Input_Dados!M$34="","",MIN(100,MAX(0,(Parametros!$C$36-Input_Dados!M$34)/(Parametros!$C$36-Parametros!$B$36)*100))) -> 20.139863 | ... M34: =IF(Input_Dados!P$34="","",MIN(100,MAX(0,(Parametros!$C$36-Input_Dados!P$34)/(Parametros!$C$36-Parametros!$B$36)*100))) -> 22.879158
A35: Taxa de Formalização | B35: + | C35: =IF(Input_Dados!F$35="","",MIN(100,MAX(0,(Input_Dados!F$35-Parametros!$B$37)/(Parametros!$C$37-Parametros!$B$37)*100))) | D35: =IF(Input_Dados!G$35="","",MIN(100,MAX(0,(Input_Dados!G$35-Parametros!$B$37)/(Parametros!$C$37-Parametros!$B$37)*100))) | E35: =IF(Input_Dados!H$35="","",MIN(100,MAX(0,(Input_Dados!H$35-Parametros!$B$37)/(Parametros!$C$37-Parametros!$B$37)*100))) | F35: =IF(Input_Dados!I$35="","",MIN(100,MAX(0,(Input_Dados!I$35-Parametros!$B$37)/(Parametros!$C$37-Parametros!$B$37)*100))) | G35: =IF(Input_Dados!J$35="","",MIN(100,MAX(0,(Input_Dados!J$35-Parametros!$B$37)/(Parametros!$C$37-Parametros!$B$37)*100))) -> 25.458184 | H35: =IF(Input_Dados!K$35="","",MIN(100,MAX(0,(Input_Dados!K$35-Parametros!$B$37)/(Parametros!$C$37-Parametros!$B$37)*100))) -> 19.646425 | I35: =IF(Input_Dados!L$35="","",MIN(100,MAX(0,(Input_Dados!L$35-Parametros!$B$37)/(Parametros!$C$37-Parametros!$B$37)*100))) -> 19.552482 | J35: =IF(Input_Dados!M$35="","",MIN(100,MAX(0,(Input_Dados!M$35-Parametros!$B$37)/(Parametros!$C$37-Parametros!$B$37)*100))) -> 20.139863 | ... M35: =IF(Input_Dados!P$35="","",MIN(100,MAX(0,(Input_Dados!P$35-Parametros!$B$37)/(Parametros!$C$37-Parametros!$B$37)*100))) -> 22.879158
A36: Crescimento da Produtividade | B36: + | C36: =IF(Input_Dados!F$36="","",MIN(100,MAX(0,(Input_Dados!F$36-Parametros!$B$38)/(Parametros!$C$38-Parametros!$B$38)*100))) | D36: =IF(Input_Dados!G$36="","",MIN(100,MAX(0,(Input_Dados!G$36-Parametros!$B$38)/(Parametros!$C$38-Parametros!$B$38)*100))) | E36: =IF(Input_Dados!H$36="","",MIN(100,MAX(0,(Input_Dados!H$36-Parametros!$B$38)/(Parametros!$C$38-Parametros!$B$38)*100))) | F36: =IF(Input_Dados!I$36="","",MIN(100,MAX(0,(Input_Dados!I$36-Parametros!$B$38)/(Parametros!$C$38-Parametros!$B$38)*100))) | G36: =IF(Input_Dados!J$36="","",MIN(100,MAX(0,(Input_Dados!J$36-Parametros!$B$38)/(Parametros!$C$38-Parametros!$B$38)*100))) | H36: =IF(Input_Dados!K$36="","",MIN(100,MAX(0,(Input_Dados!K$36-Parametros!$B$38)/(Parametros!$C$38-Parametros!$B$38)*100))) | I36: =IF(Input_Dados!L$36="","",MIN(100,MAX(0,(Input_Dados!L$36-Parametros!$B$38)/(Parametros!$C$38-Parametros!$B$38)*100))) | J36: =IF(Input_Dados!M$36="","",MIN(100,MAX(0,(Input_Dados!M$36-Parametros!$B$38)/(Parametros!$C$38-Parametros!$B$38)*100))) | ... M36: =IF(Input_Dados!P$36="","",MIN(100,MAX(0,(Input_Dados!P$36-Parametros!$B$38)/(Parametros!$C$38-Parametros!$B$38)*100)))
A37: Índice Global Seg. Alimentar | B37: + | C37: =IF(Input_Dados!F$37="","",MIN(100,MAX(0,(Input_Dados!F$37-Parametros!$B$39)/(Parametros!$C$39-Parametros!$B$39)*100))) -> 35.1 | D37: =IF(Input_Dados!G$37="","",MIN(100,MAX(0,(Input_Dados!G$37-Parametros!$B$39)/(Parametros!$C$39-Parametros!$B$39)*100))) | E37: =IF(Input_Dados!H$37="","",MIN(100,MAX(0,(Input_Dados!H$37-Parametros!$B$39)/(Parametros!$C$39-Parametros!$B$39)*100))) | F37: =IF(Input_Dados!I$37="","",MIN(100,MAX(0,(Input_Dados!I$37-Parametros!$B$39)/(Parametros!$C$39-Parametros!$B$39)*100))) | G37: =IF(Input_Dados!J$37="","",MIN(100,MAX(0,(Input_Dados!J$37-Parametros!$B$39)/(Parametros!$C$39-Parametros!$B$39)*100))) | H37: =IF(Input_Dados!K$37="","",MIN(100,MAX(0,(Input_Dados!K$37-Parametros!$B$39)/(Parametros!$C$39-Parametros!$B$39)*100))) | I37: =IF(Input_Dados!L$37="","",MIN(100,MAX(0,(Input_Dados!L$37-Parametros!$B$39)/(Parametros!$C$39-Parametros!$B$39)*100))) | J37: =IF(Input_Dados!M$37="","",MIN(100,MAX(0,(Input_Dados!M$37-Parametros!$B$39)/(Parametros!$C$39-Parametros!$B$39)*100))) | ... M37: =IF(Input_Dados!P$37="","",MIN(100,MAX(0,(Input_Dados!P$37-Parametros!$B$39)/(Parametros!$C$39-Parametros!$B$39)*100))) -> 29.7
A38: Prevalência de Desnutrição | B38: - | C38: =IF(Input_Dados!F$38="","",MIN(100,MAX(0,(Parametros!$C$40-Input_Dados!F$38)/(Parametros!$C$40-Parametros!$B$40)*100))) | D38: =IF(Input_Dados!G$38="","",MIN(100,MAX(0,(Parametros!$C$40-Input_Dados!G$38)/(Parametros!$C$40-Parametros!$B$40)*100))) -> 69.6 | E38: =IF(Input_Dados!H$38="","",MIN(100,MAX(0,(Parametros!$C$40-Input_Dados!H$38)/(Parametros!$C$40-Parametros!$B$40)*100))) -> 69.2 | F38: =IF(Input_Dados!I$38="","",MIN(100,MAX(0,(Parametros!$C$40-Input_Dados!I$38)/(Parametros!$C$40-Parametros!$B$40)*100))) -> 68.2 | G38: =IF(Input_Dados!J$38="","",MIN(100,MAX(0,(Parametros!$C$40-Input_Dados!J$38)/(Parametros!$C$40-Parametros!$B$40)*100))) -> 63.6 | H38: =IF(Input_Dados!K$38="","",MIN(100,MAX(0,(Parametros!$C$40-Input_Dados!K$38)/(Parametros!$C$40-Parametros!$B$40)*100))) -> 58.4 | I38: =IF(Input_Dados!L$38="","",MIN(100,MAX(0,(Parametros!$C$40-Input_Dados!L$38)/(Parametros!$C$40-Parametros!$B$40)*100))) -> 54.8 | J38: =IF(Input_Dados!M$38="","",MIN(100,MAX(0,(Parametros!$C$40-Input_Dados!M$38)/(Parametros!$C$40-Parametros!$B$40)*100))) -> 53.8 | ... M38: =IF(Input_Dados!P$38="","",MIN(100,MAX(0,(Parametros!$C$40-Input_Dados!P$38)/(Parametros!$C$40-Parametros!$B$40)*100)))
A39: Mortalidade Materna (por 100k) | B39: - | C39: =IF(Input_Dados!F$39="","",MIN(100,MAX(0,(Parametros!$C$41-Input_Dados!F$39)/(Parametros!$C$41-Parametros!$B$41)*100))) -> 52.3 | D39: =IF(Input_Dados!G$39="","",MIN(100,MAX(0,(Parametros!$C$41-Input_Dados!G$39)/(Parametros!$C$41-Parametros!$B$41)*100))) -> 55.8 | E39: =IF(Input_Dados!H$39="","",MIN(100,MAX(0,(Parametros!$C$41-Input_Dados!H$39)/(Parametros!$C$41-Parametros!$B$41)*100))) -> 60 | F39: =IF(Input_Dados!I$39="","",MIN(100,MAX(0,(Parametros!$C$41-Input_Dados!I$39)/(Parametros!$C$41-Parametros!$B$41)*100))) -> 63 | G39: =IF(Input_Dados!J$39="","",MIN(100,MAX(0,(Parametros!$C$41-Input_Dados!J$39)/(Parametros!$C$41-Parametros!$B$41)*100))) -> 67 | H39: =IF(Input_Dados!K$39="","",MIN(100,MAX(0,(Parametros!$C$41-Input_Dados!K$39)/(Parametros!$C$41-Parametros!$B$41)*100))) -> 70 | I39: =IF(Input_Dados!L$39="","",MIN(100,MAX(0,(Parametros!$C$41-Input_Dados!L$39)/(Parametros!$C$41-Parametros!$B$41)*100))) -> 71 | J39: =IF(Input_Dados!M$39="","",MIN(100,MAX(0,(Parametros!$C$41-Input_Dados!M$39)/(Parametros!$C$41-Parametros!$B$41)*100))) -> 75 | ... M39: =IF(Input_Dados!P$39="","",MIN(100,MAX(0,(Parametros!$C$41-Input_Dados!P$39)/(Parametros!$C$41-Parametros!$B$41)*100))) -> 83
A40: Despesas Saúde (% PIB) | B40: + | C40: =IF(Input_Dados!F$40="","",MIN(100,MAX(0,(Input_Dados!F$40-Parametros!$B$42)/(Parametros!$C$42-Parametros!$B$42)*100))) -> 17.4 | D40: =IF(Input_Dados!G$40="","",MIN(100,MAX(0,(Input_Dados!G$40-Parametros!$B$42)/(Parametros!$C$42-Parametros!$B$42)*100))) -> 18.066667 | E40: =IF(Input_Dados!H$40="","",MIN(100,MAX(0,(Input_Dados!H$40-Parametros!$B$42)/(Parametros!$C$42-Parametros!$B$42)*100))) -> 18.6 | F40: =IF(Input_Dados!I$40="","",MIN(100,MAX(0,(Input_Dados!I$40-Parametros!$B$42)/(Parametros!$C$42-Parametros!$B$42)*100))) -> 17.266667 | G40: =IF(Input_Dados!J$40="","",MIN(100,MAX(0,(Input_Dados!J$40-Parametros!$B$42)/(Parametros!$C$42-Parametros!$B$42)*100))) -> 16.533333 | H40: =IF(Input_Dados!K$40="","",MIN(100,MAX(0,(Input_Dados!K$40-Parametros!$B$42)/(Parametros!$C$42-Parametros!$B$42)*100))) -> 21.8 | I40: =IF(Input_Dados!L$40="","",MIN(100,MAX(0,(Input_Dados!L$40-Parametros!$B$42)/(Parametros!$C$42-Parametros!$B$42)*100))) -> 20.6 | J40: =IF(Input_Dados!M$40="","",MIN(100,MAX(0,(Input_Dados!M$40-Parametros!$B$42)/(Parametros!$C$42-Parametros!$B$42)*100))) -> 19.533333 | ... M40: =IF(Input_Dados!P$40="","",MIN(100,MAX(0,(Input_Dados!P$40-Parametros!$B$42)/(Parametros!$C$42-Parametros!$B$42)*100)))
A41: Camas Hospitalares (por 1000) | B41: + | C41: =IF(Input_Dados!F$41="","",MIN(100,MAX(0,(Input_Dados!F$41-Parametros!$B$43)/(Parametros!$C$43-Parametros!$B$43)*100))) | D41: =IF(Input_Dados!G$41="","",MIN(100,MAX(0,(Input_Dados!G$41-Parametros!$B$43)/(Parametros!$C$43-Parametros!$B$43)*100))) | E41: =IF(Input_Dados!H$41="","",MIN(100,MAX(0,(Input_Dados!H$41-Parametros!$B$43)/(Parametros!$C$43-Parametros!$B$43)*100))) -> 3.8 | F41: =IF(Input_Dados!I$41="","",MIN(100,MAX(0,(Input_Dados!I$41-Parametros!$B$43)/(Parametros!$C$43-Parametros!$B$43)*100))) | G41: =IF(Input_Dados!J$41="","",MIN(100,MAX(0,(Input_Dados!J$41-Parametros!$B$43)/(Parametros!$C$43-Parametros!$B$43)*100))) | H41: =IF(Input_Dados!K$41="","",MIN(100,MAX(0,(Input_Dados!K$41-Parametros!$B$43)/(Parametros!$C$43-Parametros!$B$43)*100))) | I41: =IF(Input_Dados!L$41="","",MIN(100,MAX(0,(Input_Dados!L$41-Parametros!$B$43)/(Parametros!$C$43-Parametros!$B$43)*100))) | J41: =IF(Input_Dados!M$41="","",MIN(100,MAX(0,(Input_Dados!M$41-Parametros!$B$43)/(Parametros!$C$43-Parametros!$B$43)*100))) -> 10.2 | ... M41: =IF(Input_Dados!P$41="","",MIN(100,MAX(0,(Input_Dados!P$41-Parametros!$B$43)/(Parametros!$C$43-Parametros!$B$43)*100)))
A42: Cobertura Vacinal (%) | B42: + | C42: =IF(Input_Dados!F$42="","",MIN(100,MAX(0,(Input_Dados!F$42-Parametros!$B$44)/(Parametros!$C$44-Parametros!$B$44)*100))) -> 45 | D42: =IF(Input_Dados!G$42="","",MIN(100,MAX(0,(Input_Dados!G$42-Parametros!$B$44)/(Parametros!$C$44-Parametros!$B$44)*100))) -> 42 | E42: =IF(Input_Dados!H$42="","",MIN(100,MAX(0,(Input_Dados!H$42-Parametros!$B$44)/(Parametros!$C$44-Parametros!$B$44)*100))) -> 50 | F42: =IF(Input_Dados!I$42="","",MIN(100,MAX(0,(Input_Dados!I$42-Parametros!$B$44)/(Parametros!$C$44-Parametros!$B$44)*100))) -> 51 | G42: =IF(Input_Dados!J$42="","",MIN(100,MAX(0,(Input_Dados!J$42-Parametros!$B$44)/(Parametros!$C$44-Parametros!$B$44)*100))) -> 44 | H42: =IF(Input_Dados!K$42="","",MIN(100,MAX(0,(Input_Dados!K$42-Parametros!$B$44)/(Parametros!$C$44-Parametros!$B$44)*100))) -> 36 | I42: =IF(Input_Dados!L$42="","",MIN(100,MAX(0,(Input_Dados!L$42-Parametros!$B$44)/(Parametros!$C$44-Parametros!$B$44)*100))) -> 37 | J42: =IF(Input_Dados!M$42="","",MIN(100,MAX(0,(Input_Dados!M$42-Parametros!$B$44)/(Parametros!$C$44-Parametros!$B$44)*100))) -> 37 | ... M42: =IF(Input_Dados!P$42="","",MIN(100,MAX(0,(Input_Dados!P$42-Parametros!$B$44)/(Parametros!$C$44-Parametros!$B$44)*100)))

Sheet Subindices
A1: Subíndice | B1: 2015 | C1: 2016 | D1: 2017 | E1: 2018 | F1: 2019 | G1: 2020 | H1: 2021 | I1: 2022 | J1: 2023 | K1: 2024 | L1: 2025
A2: 1. Governança e Estado de Direito | B2: =IF(SUMPRODUCT((Normalizacao!C$2:C$6<>"")*1)<Parametros!$B$46*5,"",SUMPRODUCT(IFERROR(Normalizacao!C$2:C$6*Parametros!$E$4:$E$8,0))/SUMPRODUCT((Normalizacao!C$2:C$6<>"")*Parametros!$E$4:$E$8)) -> 0 | C2: =IF(SUMPRODUCT((Normalizacao!D$2:D$6<>"")*1)<Parametros!$B$46*5,"",SUMPRODUCT(IFERROR(Normalizacao!D$2:D$6*Parametros!$E$4:$E$8,0))/SUMPRODUCT((Normalizacao!D$2:D$6<>"")*Parametros!$E$4:$E$8)) -> 0 | D2: =IF(SUMPRODUCT((Normalizacao!E$2:E$6<>"")*1)<Parametros!$B$46*5,"",SUMPRODUCT(IFERROR(Normalizacao!E$2:E$6*Parametros!$E$4:$E$8,0))/SUMPRODUCT((Normalizacao!E$2:E$6<>"")*Parametros!$E$4:$E$8)) -> 0 | E2: =IF(SUMPRODUCT((Normalizacao!F$2:F$6<>"")*1)<Parametros!$B$46*5,"",SUMPRODUCT(IFERROR(Normalizacao!F$2:F$6*Parametros!$E$4:$E$8,0))/SUMPRODUCT((Normalizacao!F$2:F$6<>"")*Parametros!$E$4:$E$8)) -> 0 | F2: =IF(SUMPRODUCT((Normalizacao!G$2:G$6<>"")*1)<Parametros!$B$46*5,"",SUMPRODUCT(IFERROR(Normalizacao!G$2:G$6*Parametros!$E$4:$E$8,0))/SUMPRODUCT((Normalizacao!G$2:G$6<>"")*Parametros!$E$4:$E$8)) -> 0 | G2: =IF(SUMPRODUCT((Normalizacao!H$2:H$6<>"")*1)<Parametros!$B$46*5,"",SUMPRODUCT(IFERROR(Normalizacao!H$2:H$6*Parametros!$E$4:$E$8,0))/SUMPRODUCT((Normalizacao!H$2:H$6<>"")*Parametros!$E$4:$E$8)) -> 0 | H2: =IF(SUMPRODUCT((Normalizacao!I$2:I$6<>"")*1)<Parametros!$B$46*5,"",SUMPRODUCT(IFERROR(Normalizacao!I$2:I$6*Parametros!$E$4:$E$8,0))/SUMPRODUCT((Normalizacao!I$2:I$6<>"")*Parametros!$E$4:$E$8)) -> 0 | I2: =IF(SUMPRODUCT((Normalizacao!J$2:J$6<>"")*1)<Parametros!$B$46*5,"",SUMPRODUCT(IFERROR(Normalizacao!J$2:J$6*Parametros!$E$4:$E$8,0))/SUMPRODUCT((Normalizacao!J$2:J$6<>"")*Parametros!$E$4:$E$8)) -> 0 | ... L2: =IF(SUMPRODUCT((Normalizacao!M$2:M$6<>"")*1)<Parametros!$B$46*5,"",SUMPRODUCT(IFERROR(Normalizacao!M$2:M$6*Parametros!$E$4:$E$8,0))/SUMPRODUCT((Normalizacao!M$2:M$6<>"")*Parametros!$E$4:$E$8))
A3: 2. Estabilidade Macroeconómica | B3: =IF(SUMPRODUCT((Normalizacao!C$7:C$13<>"")*1)<Parametros!$B$46*7,"",SUMPRODUCT(IFERROR(Normalizacao!C$7:C$13*Parametros!$E$9:$E$15,0))/SUMPRODUCT((Normalizacao!C$7:C$13<>"")*Parametros!$E$9:$E$15)) -> 0 | C3: =IF(SUMPRODUCT((Normalizacao!D$7:D$13<>"")*1)<Parametros!$B$46*7,"",SUMPRODUCT(IFERROR(Normalizacao!D$7:D$13*Parametros!$E$9:$E$15,0))/SUMPRODUCT((Normalizacao!D$7:D$13<>"")*Parametros!$E$9:$E$15)) -> 0 | D3: =IF(SUMPRODUCT((Normalizacao!E$7:E$13<>"")*1)<Parametros!$B$46*7,"",SUMPRODUCT(IFERROR(Normalizacao!E$7:E$13*Parametros!$E$9:$E$15,0))/SUMPRODUCT((Normalizacao!E$7:E$13<>"")*Parametros!$E$9:$E$15)) -> 0 | E3: =IF(SUMPRODUCT((Normalizacao!F$7:F$13<>"")*1)<Parametros!$B$46*7,"",SUMPRODUCT(IFERROR(Normalizacao!F$7:F$13*Parametros!$E$9:$E$15,0))/SUMPRODUCT((Normalizacao!F$7:F$13<>"")*Parametros!$E$9:$E$15)) -> 0 | F3: =IF(SUMPRODUCT((Normalizacao!G$7:G$13<>"")*1)<Parametros!$B$46*7,"",SUMPRODUCT(IFERROR(Normalizacao!G$7:G$13*Parametros!$E$9:$E$15,0))/SUMPRODUCT((Normalizacao!G$7:G$13<>"")*Parametros!$E$9:$E$15)) -> 0 | G3: =IF(SUMPRODUCT((Normalizacao!H$7:H$13<>"")*1)<Parametros!$B$46*7,"",SUMPRODUCT(IFERROR(Normalizacao!H$7:H$13*Parametros!$E$9:$E$15,0))/SUMPRODUCT((Normalizacao!H$7:H$13<>"")*Parametros!$E$9:$E$15)) -> 0 | H3: =IF(SUMPRODUCT((Normalizacao!I$7:I$13<>"")*1)<Parametros!$B$46*7,"",SUMPRODUCT(IFERROR(Normalizacao!I$7:I$13*Parametros!$E$9:$E$15,0))/SUMPRODUCT((Normalizacao!I$7:I$13<>"")*Parametros!$E$9:$E$15)) -> 0 | I3: =IF(SUMPRODUCT((Normalizacao!J$7:J$13<>"")*1)<Parametros!$B$46*7,"",SUMPRODUCT(IFERROR(Normalizacao!J$7:J$13*Parametros!$E$9:$E$15,0))/SUMPRODUCT((Normalizacao!J$7:J$13<>"")*Parametros!$E$9:$E$15)) -> 0 | ... L3: =IF(SUMPRODUCT((Normalizacao!M$7:M$13<>"")*1)<Parametros!$B$46*7,"",SUMPRODUCT(IFERROR(Normalizacao!M$7:M$13*Parametros!$E$9:$E$15,0))/SUMPRODUCT((Normalizacao!M$7:M$13<>"")*Parametros!$E$9:$E$15)) -> 0
A4: 3. Capital Humano | B4: =IF(SUMPRODUCT((Normalizacao!C$14:C$19<>"")*1)<Parametros!$B$46*6,"",SUMPRODUCT(IFERROR(Normalizacao!C$14:C$19*Parametros!$E$16:$E$21,0))/SUMPRODUCT((Normalizacao!C$14:C$19<>"")*Parametros!$E$16:$E$21)) | C4: =IF(SUMPRODUCT((Normalizacao!D$14:D$19<>"")*1)<Parametros!$B$46*6,"",SUMPRODUCT(IFERROR(Normalizacao!D$14:D$19*Parametros!$E$16:$E$21,0))/SUMPRODUCT((Normalizacao!D$14:D$19<>"")*Parametros!$E$16:$E$21)) | D4: =IF(SUMPRODUCT((Normalizacao!E$14:E$19<>"")*1)<Parametros!$B$46*6,"",SUMPRODUCT(IFERROR(Normalizacao!E$14:E$19*Parametros!$E$16:$E$21,0))/SUMPRODUCT((Normalizacao!E$14:E$19<>"")*Parametros!$E$16:$E$21)) -> 0 | E4: =IF(SUMPRODUCT((Normalizacao!F$14:F$19<>"")*1)<Parametros!$B$46*6,"",SUMPRODUCT(IFERROR(Normalizacao!F$14:F$19*Parametros!$E$16:$E$21,0))/SUMPRODUCT((Normalizacao!F$14:F$19<>"")*Parametros!$E$16:$E$21)) -> 0 | F4: =IF(SUMPRODUCT((Normalizacao!G$14:G$19<>"")*1)<Parametros!$B$46*6,"",SUMPRODUCT(IFERROR(Normalizacao!G$14:G$19*Parametros!$E$16:$E$21,0))/SUMPRODUCT((Normalizacao!G$14:G$19<>"")*Parametros!$E$16:$E$21)) -> 0 | G4: =IF(SUMPRODUCT((Normalizacao!H$14:H$19<>"")*1)<Parametros!$B$46*6,"",SUMPRODUCT(IFERROR(Normalizacao!H$14:H$19*Parametros!$E$16:$E$21,0))/SUMPRODUCT((Normalizacao!H$14:H$19<>"")*Parametros!$E$16:$E$21)) -> 0 | H4: =IF(SUMPRODUCT((Normalizacao!I$14:I$19<>"")*1)<Parametros!$B$46*6,"",SUMPRODUCT(IFERROR(Normalizacao!I$14:I$19*Parametros!$E$16:$E$21,0))/SUMPRODUCT((Normalizacao!I$14:I$19<>"")*Parametros!$E$16:$E$21)) -> 0 | I4: =IF(SUMPRODUCT((Normalizacao!J$14:J$19<>"")*1)<Parametros!$B$46*6,"",SUMPRODUCT(IFERROR(Normalizacao!J$14:J$19*Parametros!$E$16:$E$21,0))/SUMPRODUCT((Normalizacao!J$14:J$19<>"")*Parametros!$E$16:$E$21)) -> 0 | ... L4: =IF(SUMPRODUCT((Normalizacao!M$14:M$19<>"")*1)<Parametros!$B$46*6,"",SUMPRODUCT(IFERROR(Normalizacao!M$14:M$19*Parametros!$E$16:$E$21,0))/SUMPRODUCT((Normalizacao!M$14:M$19<>"")*Parametros!$E$16:$E$21))
A5: 4. Inclusão Social e Protecção | B5: =IF(SUMPRODUCT((Normalizacao!C$20:C$24<>"")*1)<Parametros!$B$46*5,"",SUMPRODUCT(IFERROR(Normalizacao!C$20:C$24*Parametros!$E$22:$E$26,0))/SUMPRODUCT((Normalizacao!C$20:C$24<>"")*Parametros!$E$22:$E$26)) | C5: =IF(SUMPRODUCT((Normalizacao!D$20:D$24<>"")*1)<Parametros!$B$46*5,"",SUMPRODUCT(IFERROR(Normalizacao!D$20:D$24*Parametros!$E$22:$E$26,0))/SUMPRODUCT((Normalizacao!D$20:D$24<>"")*Parametros!$E$22:$E$26)) | D5: =IF(SUMPRODUCT((Normalizacao!E$20:E$24<>"")*1)<Parametros!$B$46*5,"",SUMPRODUCT(IFERROR(Normalizacao!E$20:E$24*Parametros!$E$22:$E$26,0))/SUMPRODUCT((Normalizacao!E$20:E$24<>"")*Parametros!$E$22:$E$26)) | E5: =IF(SUMPRODUCT((Normalizacao!F$20:F$24<>"")*1)<Parametros!$B$46*5,"",SUMPRODUCT(IFERROR(Normalizacao!F$20:F$24*Parametros!$E$22:$E$26,0))/SUMPRODUCT((Normalizacao!F$20:F$24<>"")*Parametros!$E$22:$E$26)) -> 0 | F5: =IF(SUMPRODUCT((Normalizacao!G$20:G$24<>"")*1)<Parametros!$B$46*5,"",SUMPRODUCT(IFERROR(Normalizacao!G$20:G$24*Parametros!$E$22:$E$26,0))/SUMPRODUCT((Normalizacao!G$20:G$24<>"")*Parametros!$E$22:$E$26)) | G5: =IF(SUMPRODUCT((Normalizacao!H$20:H$24<>"")*1)<Parametros!$B$46*5,"",SUMPRODUCT(IFERROR(Normalizacao!H$20:H$24*Parametros!$E$22:$E$26,0))/SUMPRODUCT((Normalizacao!H$20:H$24<>"")*Parametros!$E$22:$E$26)) | H5: =IF(SUMPRODUCT((Normalizacao!I$20:I$24<>"")*1)<Parametros!$B$46*5,"",SUMPRODUCT(IFERROR(Normalizacao!I$20:I$24*Parametros!$E$22:$E$26,0))/SUMPRODUCT((Normalizacao!I$20:I$24<>"")*Parametros!$E$22:$E$26)) | I5: =IF(SUMPRODUCT((Normalizacao!J$20:J$24<>"")*1)<Parametros!$B$46*5,"",SUMPRODUCT(IFERROR(Normalizacao!J$20:J$24*Parametros!$E$22:$E$26,0))/SUMPRODUCT((Normalizacao!J$20:J$24<>"")*Parametros!$E$22:$E$26)) | ... L5: =IF(SUMPRODUCT((Normalizacao!M$20:M$24<>"")*1)<Parametros!$B$46*5,"",SUMPRODUCT(IFERROR(Normalizacao!M$20:M$24*Parametros!$E$22:$E$26,0))/SUMPRODUCT((Normalizacao!M$20:M$24<>"")*Parametros!$E$22:$E$26))
A6: 5. Infraestruturas e Serviços | B6: =IF(SUMPRODUCT((Normalizacao!C$25:C$30<>"")*1)<Parametros!$B$46*6,"",SUMPRODUCT(IFERROR(Normalizacao!C$25:C$30*Parametros!$E$27:$E$32,0))/SUMPRODUCT((Normalizacao!C$25:C$30<>"")*Parametros!$E$27:$E$32)) -> 0 | C6: =IF(SUMPRODUCT((Normalizacao!D$25:D$30<>"")*1)<Parametros!$B$46*6,"",SUMPRODUCT(IFERROR(Normalizacao!D$25:D$30*Parametros!$E$27:$E$32,0))/SUMPRODUCT((Normalizacao!D$25:D$30<>"")*Parametros!$E$27:$E$32)) -> 0 | D6: =IF(SUMPRODUCT((Normalizacao!E$25:E$30<>"")*1)<Parametros!$B$46*6,"",SUMPRODUCT(IFERROR(Normalizacao!E$25:E$30*Parametros!$E$27:$E$32,0))/SUMPRODUCT((Normalizacao!E$25:E$30<>"")*Parametros!$E$27:$E$32)) -> 0 | E6: =IF(SUMPRODUCT((Normalizacao!F$25:F$30<>"")*1)<Parametros!$B$46*6,"",SUMPRODUCT(IFERROR(Normalizacao!F$25:F$30*Parametros!$E$27:$E$32,0))/SUMPRODUCT((Normalizacao!F$25:F$30<>"")*Parametros!$E$27:$E$32)) -> 0 | F6: =IF(SUMPRODUCT((Normalizacao!G$25:G$30<>"")*1)<Parametros!$B$46*6,"",SUMPRODUCT(IFERROR(Normalizacao!G$25:G$30*Parametros!$E$27:$E$32,0))/SUMPRODUCT((Normalizacao!G$25:G$30<>"")*Parametros!$E$27:$E$32)) -> 0 | G6: =IF(SUMPRODUCT((Normalizacao!H$25:H$30<>"")*1)<Parametros!$B$46*6,"",SUMPRODUCT(IFERROR(Normalizacao!H$25:H$30*Parametros!$E$27:$E$32,0))/SUMPRODUCT((Normalizacao!H$25:H$30<>"")*Parametros!$E$27:$E$32)) -> 0 | H6: =IF(SUMPRODUCT((Normalizacao!I$25:I$30<>"")*1)<Parametros!$B$46*6,"",SUMPRODUCT(IFERROR(Normalizacao!I$25:I$30*Parametros!$E$27:$E$32,0))/SUMPRODUCT((Normalizacao!I$25:I$30<>"")*Parametros!$E$27:$E$32)) -> 0 | I6: =IF(SUMPRODUCT((Normalizacao!J$25:J$30<>"")*1)<Parametros!$B$46*6,"",SUMPRODUCT(IFERROR(Normalizacao!J$25:J$30*Parametros!$E$27:$E$32,0))/SUMPRODUCT((Normalizacao!J$25:J$30<>"")*Parametros!$E$27:$E$32)) -> 0 | ... L6: =IF(SUMPRODUCT((Normalizacao!M$25:M$30<>"")*1)<Parametros!$B$46*6,"",SUMPRODUCT(IFERROR(Normalizacao!M$25:M$30*Parametros!$E$27:$E$32,0))/SUMPRODUCT((Normalizacao!M$25:M$30<>"")*Parametros!$E$27:$E$32))
A7: 6. Mercado de Trabalho | B7: =IF(SUMPRODUCT((Normalizacao!C$31:C$36<>"")*1)<Parametros!$B$46*6,"",SUMPRODUCT(IFERROR(Normalizacao!C$31:C$36*Parametros!$E$33:$E$38,0))/SUMPRODUCT((Normalizacao!C$31:C$36<>"")*Parametros!$E$33:$E$38)) | C7: =IF(SUMPRODUCT((Normalizacao!D$31:D$36<>"")*1)<Parametros!$B$46*6,"",SUMPRODUCT(IFERROR(Normalizacao!D$31:D$36*Parametros!$E$33:$E$38,0))/SUMPRODUCT((Normalizacao!D$31:D$36<>"")*Parametros!$E$33:$E$38)) | D7: =IF(SUMPRODUCT((Normalizacao!E$31:E$36<>"")*1)<Parametros!$B$46*6,"",SUMPRODUCT(IFERROR(Normalizacao!E$31:E$36*Parametros!$E$33:$E$38,0))/SUMPRODUCT((Normalizacao!E$31:E$36<>"")*Parametros!$E$33:$E$38)) | E7: =IF(SUMPRODUCT((Normalizacao!F$31:F$36<>"")*1)<Parametros!$B$46*6,"",SUMPRODUCT(IFERROR(Normalizacao!F$31:F$36*Parametros!$E$33:$E$38,0))/SUMPRODUCT((Normalizacao!F$31:F$36<>"")*Parametros!$E$33:$E$38)) | F7: =IF(SUMPRODUCT((Normalizacao!G$31:G$36<>"")*1)<Parametros!$B$46*6,"",SUMPRODUCT(IFERROR(Normalizacao!G$31:G$36*Parametros!$E$33:$E$38,0))/SUMPRODUCT((Normalizacao!G$31:G$36<>"")*Parametros!$E$33:$E$38)) -> 0 | G7: =IF(SUMPRODUCT((Normalizacao!H$31:H$36<>"")*1)<Parametros!$B$46*6,"",SUMPRODUCT(IFERROR(Normalizacao!H$31:H$36*Parametros!$E$33:$E$38,0))/SUMPRODUCT((Normalizacao!H$31:H$36<>"")*Parametros!$E$33:$E$38)) -> 0 | H7: =IF(SUMPRODUCT((Normalizacao!I$31:I$36<>"")*1)<Parametros!$B$46*6,"",SUMPRODUCT(IFERROR(Normalizacao!I$31:I$36*Parametros!$E$33:$E$38,0))/SUMPRODUCT((Normalizacao!I$31:I$36<>"")*Parametros!$E$33:$E$38)) -> 0 | I7: =IF(SUMPRODUCT((Normalizacao!J$31:J$36<>"")*1)<Parametros!$B$46*6,"",SUMPRODUCT(IFERROR(Normalizacao!J$31:J$36*Parametros!$E$33:$E$38,0))/SUMPRODUCT((Normalizacao!J$31:J$36<>"")*Parametros!$E$33:$E$38)) -> 0 | ... L7: =IF(SUMPRODUCT((Normalizacao!M$31:M$36<>"")*1)<Parametros!$B$46*6,"",SUMPRODUCT(IFERROR(Normalizacao!M$31:M$36*Parametros!$E$33:$E$38,0))/SUMPRODUCT((Normalizacao!M$31:M$36<>"")*Parametros!$E$33:$E$38)) -> 0
A8: 7. Segurança Alimentar e Saúde | B8: =IF(SUMPRODUCT((Normalizacao!C$37:C$42<>"")*1)<Parametros!$B$46*6,"",SUMPRODUCT(IFERROR(Normalizacao!C$37:C$42*Parametros!$E$39:$E$44,0))/SUMPRODUCT((Normalizacao!C$37:C$42<>"")*Parametros!$E$39:$E$44)) -> 0 | C8: =IF(SUMPRODUCT((Normalizacao!D$37:D$42<>"")*1)<Parametros!$B$46*6,"",SUMPRODUCT(IFERROR(Normalizacao!D$37:D$42*Parametros!$E$39:$E$44,0))/SUMPRODUCT((Normalizacao!D$37:D$42<>"")*Parametros!$E$39:$E$44)) -> 0 | D8: =IF(SUMPRODUCT((Normalizacao!E$37:E$42<>"")*1)<Parametros!$B$46*6,"",SUMPRODUCT(IFERROR(Normalizacao!E$37:E$42*Parametros!$E$39:$E$44,0))/SUMPRODUCT((Normalizacao!E$37:E$42<>"")*Parametros!$E$39:$E$44)) -> 0 | E8: =IF(SUMPRODUCT((Normalizacao!F$37:F$42<>"")*1)<Parametros!$B$46*6,"",SUMPRODUCT(IFERROR(Normalizacao!F$37:F$42*Parametros!$E$39:$E$44,0))/SUMPRODUCT((Normalizacao!F$37:F$42<>"")*Parametros!$E$39:$E$44)) -> 0 | F8: =IF(SUMPRODUCT((Normalizacao!G$37:G$42<>"")*1)<Parametros!$B$46*6,"",SUMPRODUCT(IFERROR(Normalizacao!G$37:G$42*Parametros!$E$39:$E$44,0))/SUMPRODUCT((Normalizacao!G$37:G$42<>"")*Parametros!$E$39:$E$44)) -> 0 | G8: =IF(SUMPRODUCT((Normalizacao!H$37:H$42<>"")*1)<Parametros!$B$46*6,"",SUMPRODUCT(IFERROR(Normalizacao!H$37:H$42*Parametros!$E$39:$E$44,0))/SUMPRODUCT((Normalizacao!H$37:H$42<>"")*Parametros!$E$39:$E$44)) -> 0 | H8: =IF(SUMPRODUCT((Normalizacao!I$37:I$42<>"")*1)<Parametros!$B$46*6,"",SUMPRODUCT(IFERROR(Normalizacao!I$37:I$42*Parametros!$E$39:$E$44,0))/SUMPRODUCT((Normalizacao!I$37:I$42<>"")*Parametros!$E$39:$E$44)) -> 0 | I8: =IF(SUMPRODUCT((Normalizacao!J$37:J$42<>"")*1)<Parametros!$B$46*6,"",SUMPRODUCT(IFERROR(Normalizacao!J$37:J$42*Parametros!$E$39:$E$44,0))/SUMPRODUCT((Normalizacao!J$37:J$42<>"")*Parametros!$E$39:$E$44)) -> 0 | ... L8: =IF(SUMPRODUCT((Normalizacao!M$37:M$42<>"")*1)<Parametros!$B$46*6,"",SUMPRODUCT(IFERROR(Normalizacao!M$37:M$42*Parametros!$E$39:$E$44,0))/SUMPRODUCT((Normalizacao!M$37:M$42<>"")*Parametros!$E$39:$E$44))
A10: DIAGNÓSTICO DE COBERTURA (nº de indicadores com dados / total)
A11: Subíndice | B11: 2015 | C11: 2016 | D11: 2017 | E11: 2018 | F11: 2019 | G11: 2020 | H11: 2021 | I11: 2022 | J11: 2023 | K11: 2024 | L11: 2025
A12: 1. Governança e Estado de Direito | B12: =SUMPRODUCT((Normalizacao!C$2:C$6<>"")*1)&"/5" -> 5/5 | C12: =SUMPRODUCT((Normalizacao!D$2:D$6<>"")*1)&"/5" -> 5/5 | D12: =SUMPRODUCT((Normalizacao!E$2:E$6<>"")*1)&"/5" -> 5/5 | E12: =SUMPRODUCT((Normalizacao!F$2:F$6<>"")*1)&"/5" -> 5/5 | F12: =SUMPRODUCT((Normalizacao!G$2:G$6<>"")*1)&"/5" -> 5/5 | G12: =SUMPRODUCT((Normalizacao!H$2:H$6<>"")*1)&"/5" -> 5/5 | H12: =SUMPRODUCT((Normalizacao!I$2:I$6<>"")*1)&"/5" -> 4/5 | I12: =SUMPRODUCT((Normalizacao!J$2:J$6<>"")*1)&"/5" -> 4/5 | ... L12: =SUMPRODUCT((Normalizacao!M$2:M$6<>"")*1)&"/5" -> 0/5
A13: 2. Estabilidade Macroeconómica | B13: =SUMPRODUCT((Normalizacao!C$7:C$13<>"")*1)&"/7" -> 6/7 | C13: =SUMPRODUCT((Normalizacao!D$7:D$13<>"")*1)&"/7" -> 6/7 | D13: =SUMPRODUCT((Normalizacao!E$7:E$13<>"")*1)&"/7" -> 6/7 | E13: =SUMPRODUCT((Normalizacao!F$7:F$13<>"")*1)&"/7" -> 6/7 | F13: =SUMPRODUCT((Normalizacao!G$7:G$13<>"")*1)&"/7" -> 6/7 | G13: =SUMPRODUCT((Normalizacao!H$7:H$13<>"")*1)&"/7" -> 6/7 | H13: =SUMPRODUCT((Normalizacao!I$7:I$13<>"")*1)&"/7" -> 6/7 | I13: =SUMPRODUCT((Normalizacao!J$7:J$13<>"")*1)&"/7" -> 6/7 | ... L13: =SUMPRODUCT((Normalizacao!M$7:M$13<>"")*1)&"/7" -> 4/7
A14: 3. Capital Humano | B14: =SUMPRODUCT((Normalizacao!C$14:C$19<>"")*1)&"/6" -> 2/6 | C14: =SUMPRODUCT((Normalizacao!D$14:D$19<>"")*1)&"/6" -> 2/6 | D14: =SUMPRODUCT((Normalizacao!E$14:E$19<>"")*1)&"/6" -> 3/6 | E14: =SUMPRODUCT((Normalizacao!F$14:F$19<>"")*1)&"/6" -> 3/6 | F14: =SUMPRODUCT((Normalizacao!G$14:G$19<>"")*1)&"/6" -> 3/6 | G14: =SUMPRODUCT((Normalizacao!H$14:H$19<>"")*1)&"/6" -> 3/6 | H14: =SUMPRODUCT((Normalizacao!I$14:I$19<>"")*1)&"/6" -> 3/6 | I14: =SUMPRODUCT((Normalizacao!J$14:J$19<>"")*1)&"/6" -> 3/6 | ... L14: =SUMPRODUCT((Normalizacao!M$14:M$19<>"")*1)&"/6" -> 1/6
A15: 4. Inclusão Social e Protecção | B15: =SUMPRODUCT((Normalizacao!C$20:C$24<>"")*1)&"/5" -> 2/5 | C15: =SUMPRODUCT((Normalizacao!D$20:D$24<>"")*1)&"/5" -> 2/5 | D15: =SUMPRODUCT((Normalizacao!E$20:E$24<>"")*1)&"/5" -> 2/5 | E15: =SUMPRODUCT((Normalizacao!F$20:F$24<>"")*1)&"/5" -> 4/5 | F15: =SUMPRODUCT((Normalizacao!G$20:G$24<>"")*1)&"/5" -> 1/5 | G15: =SUMPRODUCT((Normalizacao!H$20:H$24<>"")*1)&"/5" -> 2/5 | H15: =SUMPRODUCT((Normalizacao!I$20:I$24<>"")*1)&"/5" -> 2/5 | I15: =SUMPRODUCT((Normalizacao!J$20:J$24<>"")*1)&"/5" -> 2/5 | ... L15: =SUMPRODUCT((Normalizacao!M$20:M$24<>"")*1)&"/5" -> 2/5
A16: 5. Infraestruturas e Serviços | B16: =SUMPRODUCT((Normalizacao!C$25:C$30<>"")*1)&"/6" -> 5/6 | C16: =SUMPRODUCT((Normalizacao!D$25:D$30<>"")*1)&"/6" -> 5/6 | D16: =SUMPRODUCT((Normalizacao!E$25:E$30<>"")*1)&"/6" -> 5/6 | E16: =SUMPRODUCT((Normalizacao!F$25:F$30<>"")*1)&"/6" -> 5/6 | F16: =SUMPRODUCT((Normalizacao!G$25:G$30<>"")*1)&"/6" -> 5/6 | G16: =SUMPRODUCT((Normalizacao!H$25:H$30<>"")*1)&"/6" -> 5/6 | H16: =SUMPRODUCT((Normalizacao!I$25:I$30<>"")*1)&"/6" -> 5/6 | I16: =SUMPRODUCT((Normalizacao!J$25:J$30<>"")*1)&"/6" -> 5/6 | ... L16: =SUMPRODUCT((Normalizacao!M$25:M$30<>"")*1)&"/6" -> 0/6
A17: 6. Mercado de Trabalho | B17: =SUMPRODUCT((Normalizacao!C$31:C$36<>"")*1)&"/6" -> 0/6 | C17: =SUMPRODUCT((Normalizacao!D$31:D$36<>"")*1)&"/6" -> 0/6 | D17: =SUMPRODUCT((Normalizacao!E$31:E$36<>"")*1)&"/6" -> 0/6 | E17: =SUMPRODUCT((Normalizacao!F$31:F$36<>"")*1)&"/6" -> 0/6 | F17: =SUMPRODUCT((Normalizacao!G$31:G$36<>"")*1)&"/6" -> 4/6 | G17: =SUMPRODUCT((Normalizacao!H$31:H$36<>"")*1)&"/6" -> 4/6 | H17: =SUMPRODUCT((Normalizacao!I$31:I$36<>"")*1)&"/6" -> 4/6 | I17: =SUMPRODUCT((Normalizacao!J$31:J$36<>"")*1)&"/6" -> 4/6 | ... L17: =SUMPRODUCT((Normalizacao!M$31:M$36<>"")*1)&"/6" -> 4/6
A18: 7. Segurança Alimentar e Saúde | B18: =SUMPRODUCT((Normalizacao!C$37:C$42<>"")*1)&"/6" -> 4/6 | C18: =SUMPRODUCT((Normalizacao!D$37:D$42<>"")*1)&"/6" -> 4/6 | D18: =SUMPRODUCT((Normalizacao!E$37:E$42<>"")*1)&"/6" -> 5/6 | E18: =SUMPRODUCT((Normalizacao!F$37:F$42<>"")*1)&"/6" -> 4/6 | F18: =SUMPRODUCT((Normalizacao!G$37:G$42<>"")*1)&"/6" -> 4/6 | G18: =SUMPRODUCT((Normalizacao!H$37:H$42<>"")*1)&"/6" -> 4/6 | H18: =SUMPRODUCT((Normalizacao!I$37:I$42<>"")*1)&"/6" -> 4/6 | I18: =SUMPRODUCT((Normalizacao!J$37:J$42<>"")*1)&"/6" -> 5/6 | ... L18: =SUMPRODUCT((Normalizacao!M$37:M$42<>"")*1)&"/6" -> 2/6
A20: Subíndices com dados (de 7) | B20: =SUMPRODUCT((B2:B8<>"")*1) -> 4 | C20: =SUMPRODUCT((C2:C8<>"")*1) -> 4 | D20: =SUMPRODUCT((D2:D8<>"")*1) -> 5 | E20: =SUMPRODUCT((E2:E8<>"")*1) -> 6 | F20: =SUMPRODUCT((F2:F8<>"")*1) -> 6 | G20: =SUMPRODUCT((G2:G8<>"")*1) -> 6 | H20: =SUMPRODUCT((H2:H8<>"")*1) -> 6 | I20: =SUMPRODUCT((I2:I8<>"")*1) -> 6 | ... L20: =SUMPRODUCT((L2:L8<>"")*1) -> 2

Sheet Indice_Global
C2: EVOLUÇÃO DO ÍNDICE DE DESENVOLVIMENTO DE ANGOLA (IGDA-BDA)
C4: Componente | D4: Peso | E4: 2015 | F4: 2016 | G4: 2017 | H4: 2018 | I4: 2019 | J4: 2020 | K4: 2021 | L4: 2022 | M4: 2023 | N4: 2024 | O4: 2025
C5: 1. Governança e Estado de Direito | D5: =Parametros!B52 -> 1 | E5: =Subindices!B$2 -> 0 | F5: =Subindices!C$2 -> 0 | G5: =Subindices!D$2 -> 0 | H5: =Subindices!E$2 -> 0 | I5: =Subindices!F$2 -> 0 | J5: =Subindices!G$2 -> 0 | K5: =Subindices!H$2 -> 0 | L5: =Subindices!I$2 -> 0 | ... O5: =Subindices!L$2
C6: 2. Estabilidade Macroeconómica | D6: =Parametros!B53 -> 1 | E6: =Subindices!B$3 -> 0 | F6: =Subindices!C$3 -> 0 | G6: =Subindices!D$3 -> 0 | H6: =Subindices!E$3 -> 0 | I6: =Subindices!F$3 -> 0 | J6: =Subindices!G$3 -> 0 | K6: =Subindices!H$3 -> 0 | L6: =Subindices!I$3 -> 0 | ... O6: =Subindices!L$3 -> 0
C7: 3. Capital Humano | D7: =Parametros!B54 -> 1 | E7: =Subindices!B$4 | F7: =Subindices!C$4 | G7: =Subindices!D$4 -> 0 | H7: =Subindices!E$4 -> 0 | I7: =Subindices!F$4 -> 0 | J7: =Subindices!G$4 -> 0 | K7: =Subindices!H$4 -> 0 | L7: =Subindices!I$4 -> 0 | ... O7: =Subindices!L$4
C8: 4. Inclusão Social e Protecção | D8: =Parametros!B55 -> 1 | E8: =Subindices!B$5 | F8: =Subindices!C$5 | G8: =Subindices!D$5 | H8: =Subindices!E$5 -> 0 | I8: =Subindices!F$5 | J8: =Subindices!G$5 | K8: =Subindices!H$5 | L8: =Subindices!I$5 | ... O8: =Subindices!L$5
C9: 5. Infraestruturas e Serviços | D9: =Parametros!B56 -> 1 | E9: =Subindices!B$6 -> 0 | F9: =Subindices!C$6 -> 0 | G9: =Subindices!D$6 -> 0 | H9: =Subindices!E$6 -> 0 | I9: =Subindices!F$6 -> 0 | J9: =Subindices!G$6 -> 0 | K9: =Subindices!H$6 -> 0 | L9: =Subindices!I$6 -> 0 | ... O9: =Subindices!L$6
C10: 6. Mercado de Trabalho | D10: =Parametros!B57 -> 1 | E10: =Subindices!B$7 | F10: =Subindices!C$7 | G10: =Subindices!D$7 | H10: =Subindices!E$7 | I10: =Subindices!F$7 -> 0 | J10: =Subindices!G$7 -> 0 | K10: =Subindices!H$7 -> 0 | L10: =Subindices!I$7 -> 0 | ... O10: =Subindices!L$7 -> 0
C11: 7. Segurança Alimentar e Saúde | D11: =Parametros!B58 -> 1 | E11: =Subindices!B$8 -> 0 | F11: =Subindices!C$8 -> 0 | G11: =Subindices!D$8 -> 0 | H11: =Subindices!E$8 -> 0 | I11: =Subindices!F$8 -> 0 | J11: =Subindices!G$8 -> 0 | K11: =Subindices!H$8 -> 0 | L11: =Subindices!I$8 -> 0 | ... O11: =Subindices!L$8
C13: EVOLUÇÃO DO IGDA-BDA (Índice Global) | E13: =IF(SUMPRODUCT((E5:E11<>"")*1)<Parametros!$B$47,"",IF(SUMPRODUCT((E5:E11<>"")*(E5:E11<=0))>0,0,EXP(SUMPRODUCT(IFERROR(LN(E5:E11)*$D$5:$D$11,0))/SUMPRODUCT((E5:E11<>"")*$D$5:$D$11)))) -> 0 | F13: =IF(SUMPRODUCT((F5:F11<>"")*1)<Parametros!$B$47,"",IF(SUMPRODUCT((F5:F11<>"")*(F5:F11<=0))>0,0,EXP(SUMPRODUCT(IFERROR(LN(F5:F11)*$D$5:$D$11,0))/SUMPRODUCT((F5:F11<>"")*$D$5:$D$11)))) -> 0 | G13: =IF(SUMPRODUCT((G5:G11<>"")*1)<Parametros!$B$47,"",IF(SUMPRODUCT((G5:G11<>"")*(G5:G11<=0))>0,0,EXP(SUMPRODUCT(IFERROR(LN(G5:G11)*$D$5:$D$11,0))/SUMPRODUCT((G5:G11<>"")*$D$5:$D$11)))) -> 0 | H13: =IF(SUMPRODUCT((H5:H11<>"")*1)<Parametros!$B$47,"",IF(SUMPRODUCT((H5:H11<>"")*(H5:H11<=0))>0,0,EXP(SUMPRODUCT(IFERROR(LN(H5:H11)*$D$5:$D$11,0))/SUMPRODUCT((H5:H11<>"")*$D$5:$D$11)))) -> 0 | I13: =IF(SUMPRODUCT((I5:I11<>"")*1)<Parametros!$B$47,"",IF(SUMPRODUCT((I5:I11<>"")*(I5:I11<=0))>0,0,EXP(SUMPRODUCT(IFERROR(LN(I5:I11)*$D$5:$D$11,0))/SUMPRODUCT((I5:I11<>"")*$D$5:$D$11)))) -> 0 | J13: =IF(SUMPRODUCT((J5:J11<>"")*1)<Parametros!$B$47,"",IF(SUMPRODUCT((J5:J11<>"")*(J5:J11<=0))>0,0,EXP(SUMPRODUCT(IFERROR(LN(J5:J11)*$D$5:$D$11,0))/SUMPRODUCT((J5:J11<>"")*$D$5:$D$11)))) -> 0 | K13: =IF(SUMPRODUCT((K5:K11<>"")*1)<Parametros!$B$47,"",IF(SUMPRODUCT((K5:K11<>"")*(K5:K11<=0))>0,0,EXP(SUMPRODUCT(IFERROR(LN(K5:K11)*$D$5:$D$11,0))/SUMPRODUCT((K5:K11<>"")*$D$5:$D$11)))) -> 0 | L13: =IF(SUMPRODUCT((L5:L11<>"")*1)<Parametros!$B$47,"",IF(SUMPRODUCT((L5:L11<>"")*(L5:L11<=0))>0,0,EXP(SUMPRODUCT(IFERROR(LN(L5:L11)*$D$5:$D$11,0))/SUMPRODUCT((L5:L11<>"")*$D$5:$D$11)))) -> 0 | ... O13: =IF(SUMPRODUCT((O5:O11<>"")*1)<Parametros!$B$47,"",IF(SUMPRODUCT((O5:O11<>"")*(O5:O11<=0))>0,0,EXP(SUMPRODUCT(IFERROR(LN(O5:O11)*$D$5:$D$11,0))/SUMPRODUCT((O5:O11<>"")*$D$5:$D$11))))
E14: =IF(E13="","",IF(E13>=70,"Bom",IF(E13>=50,"Moderado","Fraco"))) -> Fraco | F14: =IF(F13="","",IF(F13>=70,"Bom",IF(F13>=50,"Moderado","Fraco"))) -> Fraco | G14: =IF(G13="","",IF(G13>=70,"Bom",IF(G13>=50,"Moderado","Fraco"))) -> Fraco | H14: =IF(H13="","",IF(H13>=70,"Bom",IF(H13>=50,"Moderado","Fraco"))) -> Fraco | I14: =IF(I13="","",IF(I13>=70,"Bom",IF(I13>=50,"Moderado","Fraco"))) -> Fraco | J14: =IF(J13="","",IF(J13>=70,"Bom",IF(J13>=50,"Moderado","Fraco"))) -> Fraco | K14: =IF(K13="","",IF(K13>=70,"Bom",IF(K13>=50,"Moderado","Fraco"))) -> Fraco | L14: =IF(L13="","",IF(L13>=70,"Bom",IF(L13>=50,"Moderado","Fraco"))) -> Fraco | ... O14: =IF(O13="","",IF(O13>=70,"Bom",IF(O13>=50,"Moderado","Fraco")))
C15: Variação Anual (p.p.) | F15: =IF(OR(F13="",E13=""),"",F13-E13) -> 0 | G15: =IF(OR(G13="",F13=""),"",G13-F13) -> 0 | H15: =IF(OR(H13="",G13=""),"",H13-G13) -> 0 | I15: =IF(OR(I13="",H13=""),"",I13-H13) -> 0 | J15: =IF(OR(J13="",I13=""),"",J13-I13) -> 0 | K15: =IF(OR(K13="",J13=""),"",K13-J13) -> 0 | L15: =IF(OR(L13="",K13=""),"",L13-K13) -> 0 | M15: =IF(OR(M13="",L13=""),"",M13-L13) -> 0 | ... O15: =IF(OR(O13="",N13=""),"",O13-N13)
C16: SEMÁFORO DE DESEMPENHO
C17: ≥ 70: Bom | 50-70: Moderado | < 50: Fraco
B41: EVOLUÇÃO DOS SUB ÍNDICES

Sheet Diagnostico_Lacunas
A1: Diagnóstico de lacunas do IGDA-BDA
A2: Cobertura calculada apenas sobre as colunas 2015-2025 da folha Input_Dados. A coluna Q foi tratada como notas/fonte, não como série anual.
A4: Dimensão | B4: Nº indicadores atuais | C4: Indicadores sem dados 2015-2025 | D4: Indicadores com baixa cobertura (<6/11) | E4: Observação
A5: 1. Governança | B5: 5 | C5: Nenhum | D5: Nenhum | E5: Cobertura razoável; sugerem-se indicadores concorrentes para robustez metodológica.
A6: 2. Macroeconomia | B6: 7 | C6: IDE não-petrolífero (% PIB) | D6: Nenhum | E6: Reforçar com substitutos internacionais e/ou séries nacionais administrativas.
A7: 3. Capital Humano | B7: 6 | C7: Taxa de Alfabetização (+15 anos); Taxa de Matrícula (primário); Anos Médios de Escolaridade | D7: Nenhum | E7: Reforçar com substitutos internacionais e/ou séries nacionais administrativas.
A8: 4. Inclusão Social | B8: 5 | C8: Cobertura Protecção Social | D8: Taxa de Pobreza (< 2.15 USD/dia) (1/11); Índice de Gini (1/11) | E8: Reforçar com substitutos internacionais e/ou séries nacionais administrativas.
A9: 5. Infraestruturas | B9: 6 | C9: Cobertura de Rede 4G | D9: Nenhum | E9: Reforçar com substitutos internacionais e/ou séries nacionais administrativas.
A10: 6. Mercado Trabalho | B10: 6 | C10: Desemprego Juvenil (15-25); Crescimento da Produtividade | D10: Nenhum | E10: Reforçar com substitutos internacionais e/ou séries nacionais administrativas.
A11: 7. Seg. Alimentar/Saúde | B11: 6 | C11: Nenhum | D11: Índice Global Seg. Alimentar (3/11); Camas Hospitalares (por 1000) (2/11) | E11: Reforçar com substitutos internacionais e/ou séries nacionais administrativas.

Sheet Sugestoes_Indicadores
A1: Indicadores concorrentes/candidatos para reforçar o IGDA-BDA
A2: Estas linhas são sugestões metodológicas. Para entrarem no cálculo, devem ser copiadas para Input_Dados, Parametros e Normalizacao, ajustando os intervalos dos subíndices.
A3: Fontes priorizadas: Banco Mundial/WDI/WGI, PNUD/HDR, OIT/ILOSTAT, ITU, FAO/FAOSTAT, OMS/WHO, UNICEF/JMP, INE/BNA/MEP/MINFIN para séries nacionais.
A4: Dimensão | B4: Indicador sugerido | C4: Tipo | D4: Código | E4: Nome oficial/API | F4: Fonte | G4: Fonte_URL | H4: Unidade | I4: Sentido | J4: Mín. sugerido | K4: Máx. sugerido | L4: Meta 2027 sugerida | M4: Peso sugerido | N4: Prioridade | O4: Cobertura AGO 2015-2025 | P4: Último ano com dado | Q4: Racional / uso recomendado
A5: 1. Governança e Estado de Direito | B5: WGI - Controlo da Corrupção | C5: Substituto/Complementar | D5: CC.EST | E5: Control of Corruption: Estimate | F5: WGI/Banco Mundial | G5: https://datacatalog.worldbank.org/search/dataset/0038026/worldwide-governance-indicators | H5: -2.5 a 2.5 | I5: + | J5: -2.5 | K5: 2.5 | L5: 0 | M5: 1 | N5: Alta | O5: 10/11 (WGI 2015-2024) | P5: 2024 | Q5: Complementa o CPI com uma medida anual comparável e alinhada com os restantes WGI. Cobertura estimada pela periodicidade WGI; o endpoint WDI simples não devolve esta série.
A6: 1. Governança e Estado de Direito | B6: WGI - Qualidade Regulatória | C6: Substituto | D6: RQ.EST | E6: Regulatory Quality: Estimate | F6: WGI/Banco Mundial | G6: https://datacatalog.worldbank.org/search/dataset/0038026/worldwide-governance-indicators | H6: -2.5 a 2.5 | I6: + | J6: -2.5 | K6: 2.5 | L6: 0 | M6: 1 | N6: Alta | O6: 10/11 (WGI 2015-2024) | P6: 2024 | Q6: Bom substituto para Doing Business, que foi descontinuado. Cobertura estimada pela periodicidade WGI; o endpoint WDI simples não devolve esta série.
A7: 1. Governança e Estado de Direito | B7: WGI - Voz e Responsabilização | C7: Complementar | D7: VA.EST | E7: Voice and Accountability: Estimate | F7: WGI/Banco Mundial | G7: https://datacatalog.worldbank.org/search/dataset/0038026/worldwide-governance-indicators | H7: -2.5 a 2.5 | I7: + | J7: -2.5 | K7: 2.5 | L7: 0 | M7: 1 | N7: Média | O7: 10/11 (WGI 2015-2024) | P7: 2024 | Q7: Acrescenta dimensão de responsabilização pública e participação. Cobertura estimada pela periodicidade WGI; o endpoint WDI simples não devolve esta série.
A8: 1. Governança e Estado de Direito | B8: Índice Ibrahim - Governação Global | C8: Complementar | F8: Mo Ibrahim Foundation | G8: https://iiag.online/ | H8: 0-100 | I8: + | J8: 0 | K8: 100 | L8: 55 | M8: 1 | N8: Alta | Q8: Benchmark africano com várias dimensões institucionais.
A9: 1. Governança e Estado de Direito | B9: Índice Ibrahim - Segurança e Estado de Direito | C9: Complementar | F9: Mo Ibrahim Foundation | G9: https://iiag.online/ | H9: 0-100 | I9: + | J9: 0 | K9: 100 | L9: 55 | M9: 1 | N9: Média | Q9: Aproxima governança de segurança, justiça e direitos no contexto africano.
A10: 1. Governança e Estado de Direito | B10: Open Budget Index | C10: Complementar | F10: International Budget Partnership | G10: https://internationalbudget.org/open-budget-survey/ | H10: 0-100 | I10: + | J10: 0 | K10: 100 | L10: 50 | M10: 1 | N10: Média | Q10: Mede transparência orçamental, relevante para responsabilização fiscal.
A11: 1. Governança e Estado de Direito | B11: Empresas solicitadas a fazer pagamentos informais | C11: Complementar | F11: World Bank Enterprise Surveys | G11: https://www.enterprisesurveys.org/ | H11: % | I11: - | J11: 0 | K11: 100 | L11: 10 | M11: 1 | N11: Média | Q11: Capta corrupção administrativa sentida pelas empresas.
A12: 1. Governança e Estado de Direito | B12: Statistical Performance Index - score geral | C12: Complementar | D12: IQ.SPI.OVRL | E12: Statistical performance indicators (SPI): Overall score (scale 0-100) | F12: Banco Mundial | G12: https://data.worldbank.org/indicator/IQ.SPI.OVRL?locations=AO | H12: 0-100 | I12: + | J12: 0 | K12: 100 | L12: 65 | M12: 1 | N12: Média | O12: 9/11 | P12: 2024 | Q12: Mede capacidade estatística, útil para qualidade de políticas públicas e monitorização.
A13: 2. Estabilidade Macroeconómica | B13: Saldo da conta corrente (% PIB) | C13: Complementar | D13: BN.CAB.XOKA.GD.ZS | E13: Current account balance (% of GDP) | F13: Banco Mundial/WDI | G13: https://data.worldbank.org/indicator/BN.CAB.XOKA.GD.ZS?locations=AO | H13: % | I13: + | J13: -30 | K13: 30 | L13: 0 | M13: 1 | N13: Alta | O13: 10/11 | P13: 2024 | Q13: Acrescenta sustentabilidade externa, ausente do subíndice atual.
A14: 2. Estabilidade Macroeconómica | B14: Receita fiscal (% PIB) | C14: Complementar | D14: GC.TAX.TOTL.GD.ZS | E14: Tax revenue (% of GDP) | F14: Banco Mundial/WDI | G14: https://data.worldbank.org/indicator/GC.TAX.TOTL.GD.ZS?locations=AO | H14: % | I14: + | J14: 0 | K14: 40 | L14: 18 | M14: 1 | N14: Alta | O14: 10/11 | P14: 2024 | Q14: Capta capacidade interna de financiamento do Estado.
A15: 2. Estabilidade Macroeconómica | B15: IDE líquido total (% PIB) | C15: Substituto | D15: BX.KLT.DINV.WD.GD.ZS | E15: Foreign direct investment, net inflows (% of GDP) | F15: Banco Mundial/WDI | G15: https://data.worldbank.org/indicator/BX.KLT.DINV.WD.GD.ZS?locations=AO | H15: % | I15: + | J15: -10 | K15: 20 | L15: 5 | M15: 1 | N15: Alta | O15: 10/11 | P15: 2024 | Q15: Substitui provisoriamente o IDE não-petrolífero quando a série setorial estiver vazia.
A16: 2. Estabilidade Macroeconómica | B16: Rendas petrolíferas (% PIB) | C16: Complementar | D16: NY.GDP.PETR.RT.ZS | E16: Oil rents (% of GDP) | F16: Banco Mundial/WDI | G16: https://data.worldbank.org/indicator/NY.GDP.PETR.RT.ZS?locations=AO | H16: % | I16: - | J16: 0 | K16: 60 | L16: 15 | M16: 1 | N16: Alta | O16: 7/11 | P16: 2021 | Q16: Proxy de dependência petrolífera; menor dependência é melhor para diversificação.
A17: 2. Estabilidade Macroeconómica | B17: Exportações de bens e serviços (% PIB) | C17: Complementar | D17: NE.EXP.GNFS.ZS | E17: Exports of goods and services (% of GDP) | F17: Banco Mundial/WDI | G17: https://data.worldbank.org/indicator/NE.EXP.GNFS.ZS?locations=AO | H17: % | I17: + | J17: 0 | K17: 100 | L17: 40 | M17: 1 | N17: Média | O17: 10/11 | P17: 2024 | Q17: Acompanha abertura e capacidade exportadora, mas deve ser lido com composição setorial.
A18: 2. Estabilidade Macroeconómica | B18: Reservas internacionais em meses de importações | C18: Substituto | D18: FI.RES.TOTL.MO | E18: Total reserves in months of imports | F18: Banco Mundial/WDI | G18: https://data.worldbank.org/indicator/FI.RES.TOTL.MO?locations=AO | H18: Meses | I18: + | J18: 0 | K18: 12 | L18: 6 | M18: 1 | N18: Alta | O18: 10/11 | P18: 2024 | Q18: Pode substituir o cálculo manual atualmente colocado abaixo da tabela.
A19: 2. Estabilidade Macroeconómica | B19: Crédito doméstico ao setor privado (% PIB) | C19: Complementar | D19: FS.AST.PRVT.GD.ZS | E19: Domestic credit to private sector (% of GDP) | F19: Banco Mundial/WDI | G19: https://data.worldbank.org/indicator/FS.AST.PRVT.GD.ZS?locations=AO | H19: % | I19: + | J19: 0 | K19: 100 | L19: 35 | M19: 1 | N19: Média | O19: 10/11 | P19: 2024 | Q19: Acrescenta profundidade financeira e apoio ao investimento privado.
A20: 2. Estabilidade Macroeconómica | B20: Crescimento do PIB não petrolífero | C20: Complementar | F20: INE/MEP/BNA | G20: https://www.ine.gov.ao/ | H20: % | I20: + | J20: -10 | K20: 15 | L20: 5 | M20: 1 | N20: Alta | Q20: Mais alinhado com a diversificação económica do que o PIB total.
A21: 2. Estabilidade Macroeconómica | B21: Volatilidade da taxa de câmbio nominal | C21: Complementar | D21: PA.NUS.FCRF | E21: Official exchange rate (LCU per US$, period average) | F21: Banco Mundial/WDI ou BNA | G21: https://data.worldbank.org/indicator/PA.NUS.FCRF?locations=AO | H21: % variação anual | I21: - | J21: 0 | K21: 80 | L21: 10 | M21: 1 | N21: Média | O21: 10/11 | P21: 2024 | Q21: Capta instabilidade cambial que afeta preços, dívida e importações.
A22: 3. Capital Humano | B22: Taxa de alfabetização adulta | C22: Substituto | D22: SE.ADT.LITR.ZS | E22: Literacy rate, adult total (% of people ages 15 and above) | F22: Banco Mundial/UNESCO | G22: https://data.worldbank.org/indicator/SE.ADT.LITR.ZS?locations=AO | H22: % | I22: + | J22: 0 | K22: 100 | L22: 75 | M22: 1 | N22: Alta | O22: 2/11 | P22: 2023 | Q22: Preenche a linha existente com fonte internacional comparável.
A23: 3. Capital Humano | B23: Taxa de conclusão do ensino primário | C23: Complementar | D23: SE.PRM.CMPT.ZS | E23: Primary completion rate, total (% of relevant age group) | F23: Banco Mundial/UNESCO | G23: https://data.worldbank.org/indicator/SE.PRM.CMPT.ZS?locations=AO | H23: % | I23: + | J23: 0 | K23: 100 | L23: 90 | M23: 1 | N23: Alta | O23: 2/11 | P23: 2023 | Q23: Mais robusta que matrícula para medir progressão efetiva.
A24: 3. Capital Humano | B24: Matrícula no ensino secundário, bruta | C24: Complementar | D24: SE.SEC.ENRR | E24: School enrollment, secondary (% gross) | F24: Banco Mundial/UNESCO | G24: https://data.worldbank.org/indicator/SE.SEC.ENRR?locations=AO | H24: % | I24: + | J24: 0 | K24: 150 | L24: 80 | M24: 1 | N24: Alta | O24: 3/11 | P24: 2023 | Q24: Captura continuidade pós-primária.
A25: 3. Capital Humano | B25: Matrícula no ensino terciário, bruta | C25: Complementar | D25: SE.TER.ENRR | E25: School enrollment, tertiary (% gross) | F25: Banco Mundial/UNESCO | G25: https://data.worldbank.org/indicator/SE.TER.ENRR?locations=AO | H25: % | I25: + | J25: 0 | K25: 100 | L25: 20 | M25: 1 | N25: Média | O25: 4/11 | P25: 2024 | Q25: Ajuda a medir formação avançada e capacidade técnica.
A26: 3. Capital Humano | B26: Despesa pública em educação (% PIB) | C26: Complementar | D26: SE.XPD.TOTL.GD.ZS | E26: Government expenditure on education, total (% of GDP) | F26: Banco Mundial/UNESCO | G26: https://data.worldbank.org/indicator/SE.XPD.TOTL.GD.ZS?locations=AO | H26: % | I26: + | J26: 0 | K26: 10 | L26: 5 | M26: 1 | N26: Média | O26: 9/11 | P26: 2023 | Q26: Input de política pública; deve ser combinado com resultados de aprendizagem.
A27: 3. Capital Humano | B27: Learning poverty - crianças sem proficiência mínima de leitura | C27: Complementar | D27: SE.LPV.PRIM | E27: Learning poverty: Share of Children at the End-of-Primary age below minimum reading proficiency adjusted by Out-of-School Children (%) | F27: Banco Mundial/UNESCO | G27: https://data.worldbank.org/indicator/SE.LPV.PRIM?locations=AO | H27: % | I27: - | J27: 0 | K27: 100 | L27: 50 | M27: 1 | N27: Baixa | O27: 0/11 | Q27: Mede aprendizagem, não apenas acesso à escola. Usar como benchmark de qualidade; a cobertura anual para Angola é limitada.
A28: 3. Capital Humano | B28: Rácio alunos/professor no primário | C28: Complementar | D28: SE.PRM.ENRL.TC.ZS | E28: Pupil-teacher ratio, primary | F28: Banco Mundial/UNESCO | G28: https://data.worldbank.org/indicator/SE.PRM.ENRL.TC.ZS?locations=AO | H28: Alunos por professor | I28: - | J28: 10 | K28: 80 | L28: 35 | M28: 1 | N28: Média | O28: 1/11 | P28: 2015 | Q28: Proxy simples de pressão sobre qualidade de ensino.
A29: 3. Capital Humano | B29: Índice de Capital Humano | C29: Complementar | D29: HD.HCI.OVRL | E29: Human Capital Index (HCI) (scale 0-1) | F29: Banco Mundial | G29: https://data.worldbank.org/indicator/HD.HCI.OVRL?locations=AO | H29: 0-1 | I29: + | J29: 0 | K29: 1 | L29: 0.5 | M29: 1 | N29: Baixa | O29: 3/11 | P29: 2020 | Q29: Útil como benchmark, mas menos anual do que os restantes indicadores.
A30: 3. Capital Humano | B30: Anos esperados de escolaridade | C30: Substituto | F30: PNUD/HDR | G30: https://hdr.undp.org/data-center | H30: Anos | I30: + | J30: 0 | K30: 18 | L30: 12 | M30: 1 | N30: Alta | Q30: Substitui ou complementa anos médios de escolaridade quando a série nacional estiver vazia.
A31: 4. Inclusão Social e Protecção | B31: Pobreza pela linha nacional | C31: Substituto | D31: SI.POV.NAHC | E31: Poverty headcount ratio at national poverty lines (% of population) | F31: Banco Mundial/PIP | G31: https://data.worldbank.org/indicator/SI.POV.NAHC?locations=AO | H31: % | I31: - | J31: 0 | K31: 80 | L31: 30 | M31: 1 | N31: Alta | O31: 1/11 | P31: 2018 | Q31: Mais diretamente ligada à linha oficial de pobreza do país.
A32: 4. Inclusão Social e Protecção | B32: Pobreza internacional a 3,00 USD/dia, PPP 2021 | C32: Substituto | D32: SI.POV.DDAY | E32: Poverty headcount ratio at $3.00 a day (2021 PPP) (% of population) | F32: Banco Mundial/PIP | G32: https://data.worldbank.org/indicator/SI.POV.DDAY?locations=AO | H32: % | I32: - | J32: 0 | K32: 90 | L32: 40 | M32: 1 | N32: Alta | O32: 1/11 | P32: 2018 | Q32: Atualiza a referência internacional que substituiu linhas PPP antigas.
A33: 4. Inclusão Social e Protecção | B33: Índice de Gini | C33: Substituto | D33: SI.POV.GINI | E33: Gini index | F33: Banco Mundial/PIP | G33: https://data.worldbank.org/indicator/SI.POV.GINI?locations=AO | H33: 0-100 | I33: - | J33: 0 | K33: 70 | L33: 40 | M33: 1 | N33: Alta | O33: 1/11 | P33: 2018 | Q33: Mantém comparabilidade internacional para desigualdade.
A34: 4. Inclusão Social e Protecção | B34: Quota de rendimento dos 20% mais pobres | C34: Complementar | D34: SI.DST.FRST.20 | E34: Income share held by lowest 20% | F34: Banco Mundial/PIP | G34: https://data.worldbank.org/indicator/SI.DST.FRST.20?locations=AO | H34: % | I34: + | J34: 0 | K34: 20 | L34: 7 | M34: 1 | N34: Média | O34: 1/11 | P34: 2018 | Q34: Lê inclusão distributiva de forma complementar ao Gini.
A35: 4. Inclusão Social e Protecção | B35: Cobertura de proteção social da população | C35: Substituto | F35: Banco Mundial ASPIRE/OIT | G35: https://www.worldbank.org/en/data/datatopics/aspire | H35: % | I35: + | J35: 0 | K35: 100 | L35: 40 | M35: 1 | N35: Alta | Q35: Preenche a lacuna existente de proteção social se houver série ASPIRE/OIT ou INSS.
A36: 4. Inclusão Social e Protecção | B36: Índice de Pobreza Multidimensional - incidência | C36: Complementar | F36: PNUD/OPHI | G36: https://hdr.undp.org/data-center/thematic-composite-indices | H36: % | I36: - | J36: 0 | K36: 80 | L36: 25 | M36: 1 | N36: Média | Q36: Capta privações simultâneas além de rendimento.
A37: 4. Inclusão Social e Protecção | B37: Jovens NEET | C37: Complementar | D37: SL.UEM.NEET.ZS | E37: Share of youth not in education, employment or training, total (% of youth population) | F37: Banco Mundial/OIT | G37: https://data.worldbank.org/indicator/SL.UEM.NEET.ZS?locations=AO | H37: % | I37: - | J37: 0 | K37: 70 | L37: 30 | M37: 1 | N37: Alta | O37: 6/11 | P37: 2024 | Q37: Forte indicador de exclusão de jovens.
A38: 4. Inclusão Social e Protecção | B38: Mulheres no parlamento | C38: Complementar | D38: SG.GEN.PARL.ZS | E38: Proportion of seats held by women in national parliaments (%) | F38: Banco Mundial/IPU | G38: https://data.worldbank.org/indicator/SG.GEN.PARL.ZS?locations=AO | H38: % | I38: + | J38: 0 | K38: 60 | L38: 35 | M38: 1 | N38: Média | O38: 11/11 | P38: 2025 | Q38: Mede inclusão política de género.
A39: 4. Inclusão Social e Protecção | B39: Participação feminina na força de trabalho | C39: Complementar | D39: SL.TLF.CACT.FE.ZS | E39: Labor force participation rate, female (% of female population ages 15+) (modeled ILO estimate) | F39: Banco Mundial/OIT | G39: https://data.worldbank.org/indicator/SL.TLF.CACT.FE.ZS?locations=AO | H39: % | I39: + | J39: 0 | K39: 100 | L39: 65 | M39: 1 | N39: Média | O39: 11/11 | P39: 2025 | Q39: Complementa o Global Gender Gap com uma métrica económica anual.
A40: 4. Inclusão Social e Protecção | B40: Registo de nascimento completo | C40: Complementar | D40: SP.REG.BRTH.ZS | E40: Completeness of birth registration (%) | F40: Banco Mundial/UNICEF | G40: https://data.worldbank.org/indicator/SP.REG.BRTH.ZS?locations=AO | H40: % | I40: + | J40: 0 | K40: 100 | L40: 80 | M40: 1 | N40: Média | O40: 1/11 | P40: 2016 | Q40: Proxy de inclusão administrativa e acesso a direitos básicos.
A41: 5. Infraestruturas e Serviços | B41: Acesso rural à eletricidade | C41: Complementar | D41: EG.ELC.ACCS.RU.ZS | E41: Access to electricity, rural (% of rural population) | F41: Banco Mundial/IEA | G41: https://data.worldbank.org/indicator/EG.ELC.ACCS.RU.ZS?locations=AO | H41: % | I41: + | J41: 0 | K41: 100 | L41: 50 | M41: 1 | N41: Alta | O41: 2/11 | P41: 2018 | Q41: Evidencia desigualdade territorial no acesso à energia.
A42: 5. Infraestruturas e Serviços | B42: Acesso a energia limpa para cozinhar | C42: Complementar | D42: EG.CFT.ACCS.ZS | E42: Access to clean fuels and technologies for cooking (% of population) | F42: Banco Mundial/OMS | G42: https://data.worldbank.org/indicator/EG.CFT.ACCS.ZS?locations=AO | H42: % | I42: + | J42: 0 | K42: 100 | L42: 35 | M42: 1 | N42: Alta | O42: 9/11 | P42: 2023 | Q42: Indicador de infraestrutura doméstica com impacto ambiental e de saúde.
A43: 5. Infraestruturas e Serviços | B43: Perdas de transmissão e distribuição elétrica | C43: Complementar | D43: EG.ELC.LOSS.ZS | E43: Electric power transmission and distribution losses (% of output) | F43: Banco Mundial/IEA | G43: https://data.worldbank.org/indicator/EG.ELC.LOSS.ZS?locations=AO | H43: % | I43: - | J43: 0 | K43: 60 | L43: 15 | M43: 1 | N43: Média | O43: 9/11 | P43: 2023 | Q43: Mede eficiência da rede elétrica, não apenas acesso.
A44: 5. Infraestruturas e Serviços | B44: Subscrições móveis por 100 habitantes | C44: Substituto/Complementar | D44: IT.CEL.SETS.P2 | E44: Mobile cellular subscriptions (per 100 people) | F44: Banco Mundial/ITU | G44: https://data.worldbank.org/indicator/IT.CEL.SETS.P2?locations=AO | H44: por 100 hab. | I44: + | J44: 0 | K44: 160 | L44: 100 | M44: 1 | N44: Alta | O44: 10/11 | P44: 2024 | Q44: Alternativa anual à cobertura 4G quando a série INACOM estiver incompleta.
A45: 5. Infraestruturas e Serviços | B45: Banda larga fixa por 100 habitantes | C45: Complementar | D45: IT.NET.BBND.P2 | E45: Fixed broadband subscriptions (per 100 people) | F45: Banco Mundial/ITU | G45: https://data.worldbank.org/indicator/IT.NET.BBND.P2?locations=AO | H45: por 100 hab. | I45: + | J45: 0 | K45: 50 | L45: 8 | M45: 1 | N45: Média | O45: 10/11 | P45: 2024 | Q45: Mede infraestrutura digital fixa, distinta do uso de internet.
A46: 5. Infraestruturas e Serviços | B46: Preço de cabaz móvel-banda larga (% RNB per capita) | C46: Complementar | F46: ITU DataHub | G46: https://datahub.itu.int/ | H46: % RNB per capita | I46: - | J46: 0 | K46: 30 | L46: 5 | M46: 1 | N46: Média | Q46: Capta acessibilidade económica da conectividade.
A47: 5. Infraestruturas e Serviços | B47: Água potável básica - população total | C47: Substituto | D47: SH.H2O.BASW.ZS | E47: People using at least basic drinking water services (% of population) | F47: Banco Mundial/JMP | G47: https://data.worldbank.org/indicator/SH.H2O.BASW.ZS?locations=AO | H47: % | I47: + | J47: 0 | K47: 100 | L47: 70 | M47: 1 | N47: Alta | O47: 10/11 | P47: 2024 | Q47: Fonte comparável para preencher/validar a linha de água potável.
A48: 5. Infraestruturas e Serviços | B48: Saneamento básico - população total | C48: Substituto | D48: SH.STA.BASS.ZS | E48: People using at least basic sanitation services (% of population) | F48: Banco Mundial/JMP | G48: https://data.worldbank.org/indicator/SH.STA.BASS.ZS?locations=AO | H48: % | I48: + | J48: 0 | K48: 100 | L48: 60 | M48: 1 | N48: Alta | O48: 8/11 | P48: 2022 | Q48: Fonte comparável para preencher/validar saneamento.
A49: 5. Infraestruturas e Serviços | B49: Estradas pavimentadas (% total) | C49: Complementar | D49: IS.ROD.PAVE.ZS | E49: Roads, paved (% of total roads) | F49: Banco Mundial/WDI | G49: https://data.worldbank.org/indicator/IS.ROD.PAVE.ZS?locations=AO | H49: % | I49: + | J49: 0 | K49: 100 | L49: 30 | M49: 1 | N49: Média | O49: 3/11 | P49: 2001 | Q49: Complementa densidade rodoviária com qualidade da rede.
A50: 5. Infraestruturas e Serviços | B50: Logistics Performance Index - geral | C50: Complementar | D50: LP.LPI.OVRL.XQ | E50: Logistics performance index: Overall (1=low to 5=high) | F50: Banco Mundial/LPI | G50: https://data.worldbank.org/indicator/LP.LPI.OVRL.XQ?locations=AO | H50: 1-5 | I50: + | J50: 1 | K50: 5 | L50: 3 | M50: 1 | N50: Baixa | O50: 3/11 | P50: 2022 | Q50: Indicador sintético de logística; útil, mas não anual.
A51: 6. Mercado de Trabalho | B51: Emprego/população 15+ | C51: Substituto | D51: SL.EMP.TOTL.SP.ZS | E51: Employment to population ratio, 15+, total (%) (modeled ILO estimate) | F51: Banco Mundial/OIT | G51: https://data.worldbank.org/indicator/SL.EMP.TOTL.SP.ZS?locations=AO | H51: % | I51: + | J51: 0 | K51: 100 | L51: 65 | M51: 1 | N51: Alta | O51: 11/11 | P51: 2025 | Q51: Série internacional para validar a taxa de emprego.
A52: 6. Mercado de Trabalho | B52: Desemprego total modelado OIT | C52: Substituto | D52: SL.UEM.TOTL.ZS | E52: Unemployment, total (% of total labor force) (modeled ILO estimate) | F52: Banco Mundial/OIT | G52: https://data.worldbank.org/indicator/SL.UEM.TOTL.ZS?locations=AO | H52: % | I52: - | J52: 0 | K52: 50 | L52: 15 | M52: 1 | N52: Alta | O52: 11/11 | P52: 2025 | Q52: Série anual comparável para anos sem inquérito nacional.
A53: 6. Mercado de Trabalho | B53: Desemprego juvenil 15-24 | C53: Substituto | D53: SL.UEM.1524.ZS | E53: Unemployment, youth total (% of total labor force ages 15-24) (modeled ILO estimate) | F53: Banco Mundial/OIT | G53: https://data.worldbank.org/indicator/SL.UEM.1524.ZS?locations=AO | H53: % | I53: - | J53: 0 | K53: 70 | L53: 30 | M53: 1 | N53: Alta | O53: 11/11 | P53: 2025 | Q53: Preenche a lacuna existente de desemprego juvenil.
A54: 6. Mercado de Trabalho | B54: Participação na força de trabalho | C54: Complementar | D54: SL.TLF.CACT.ZS | E54: Labor force participation rate, total (% of total population ages 15+) (modeled ILO estimate) | F54: Banco Mundial/OIT | G54: https://data.worldbank.org/indicator/SL.TLF.CACT.ZS?locations=AO | H54: % | I54: + | J54: 0 | K54: 100 | L54: 70 | M54: 1 | N54: Alta | O54: 11/11 | P54: 2025 | Q54: Ajuda a interpretar desemprego junto com atividade laboral.
A55: 6. Mercado de Trabalho | B55: Emprego vulnerável | C55: Complementar | D55: SL.EMP.VULN.ZS | E55: Vulnerable employment, total (% of total employment) (modeled ILO estimate) | F55: Banco Mundial/OIT | G55: https://data.worldbank.org/indicator/SL.EMP.VULN.ZS?locations=AO | H55: % | I55: - | J55: 0 | K55: 100 | L55: 50 | M55: 1 | N55: Alta | O55: 11/11 | P55: 2025 | Q55: Qualidade do emprego; boa alternativa a informalidade quando esta estiver incompleta.
A56: 6. Mercado de Trabalho | B56: Trabalhadores assalariados | C56: Complementar | D56: SL.EMP.WORK.ZS | E56: Wage and salaried workers, total (% of total employment) (modeled ILO estimate) | F56: Banco Mundial/OIT | G56: https://data.worldbank.org/indicator/SL.EMP.WORK.ZS?locations=AO | H56: % emprego total | I56: + | J56: 0 | K56: 100 | L56: 50 | M56: 1 | N56: Alta | O56: 11/11 | P56: 2025 | Q56: Proxy de formalização/estrutura moderna do emprego.
A57: 6. Mercado de Trabalho | B57: Emprego na agricultura | C57: Complementar | D57: SL.AGR.EMPL.ZS | E57: Employment in agriculture (% of total employment) (modeled ILO estimate) | F57: Banco Mundial/OIT | G57: https://data.worldbank.org/indicator/SL.AGR.EMPL.ZS?locations=AO | H57: % emprego total | I57: - | J57: 0 | K57: 100 | L57: 35 | M57: 1 | N57: Média | O57: 11/11 | P57: 2025 | Q57: Proxy de transformação estrutural; deve ser lido com produtividade agrícola.
A58: 6. Mercado de Trabalho | B58: PIB por pessoa empregada | C58: Substituto | D58: SL.GDP.PCAP.EM.KD | E58: GDP per person employed (constant 2021 PPP $) | F58: Banco Mundial/OIT | G58: https://data.worldbank.org/indicator/SL.GDP.PCAP.EM.KD?locations=AO | H58: USD PPP constantes | I58: + | J58: 1000 | K58: 50000 | L58: 12000 | M58: 1 | N58: Alta | O58: 10/11 | P58: 2024 | Q58: Preenche crescimento de produtividade com uma medida de nível anual.
A59: 6. Mercado de Trabalho | B59: Jovens NEET | C59: Complementar | D59: SL.UEM.NEET.ZS | E59: Share of youth not in education, employment or training, total (% of youth population) | F59: Banco Mundial/OIT | G59: https://data.worldbank.org/indicator/SL.UEM.NEET.ZS?locations=AO | H59: % | I59: - | J59: 0 | K59: 70 | L59: 25 | M59: 1 | N59: Alta | O59: 6/11 | P59: 2024 | Q59: Indicador concorrente do desemprego juvenil porque inclui jovens fora da força de trabalho.
A60: 6. Mercado de Trabalho | B60: Emprego informal fora da agricultura | C60: Complementar | F60: INE/OIT ILOSTAT | G60: https://ilostat.ilo.org/data/ | H60: % emprego | I60: - | J60: 0 | K60: 100 | L60: 55 | M60: 1 | N60: Alta | Q60: Mantém a dimensão de informalidade, idealmente com microdados/inquéritos nacionais.
A61: 7. Segurança Alimentar e Saúde | B61: Insegurança alimentar moderada ou severa | C61: Substituto/Complementar | D61: SN.ITK.MSFI.ZS | E61: Prevalence of moderate or severe food insecurity in the population (%) | F61: Banco Mundial/FAO | G61: https://data.worldbank.org/indicator/SN.ITK.MSFI.ZS?locations=AO | H61: % | I61: - | J61: 0 | K61: 100 | L61: 45 | M61: 1 | N61: Alta | O61: 3/11 | P61: 2021 | Q61: Alternativa aberta ao índice proprietário de segurança alimentar.
A62: 7. Segurança Alimentar e Saúde | B62: Prevalência de subalimentação | C62: Substituto | D62: SN.ITK.DEFC.ZS | E62: Prevalence of undernourishment (% of population) | F62: Banco Mundial/FAO | G62: https://data.worldbank.org/indicator/SN.ITK.DEFC.ZS?locations=AO | H62: % | I62: - | J62: 0 | K62: 60 | L62: 20 | M62: 1 | N62: Alta | O62: 9/11 | P62: 2023 | Q62: Série FAO comparável para segurança alimentar.
A63: 7. Segurança Alimentar e Saúde | B63: Atraso de crescimento infantil | C63: Complementar | D63: SH.STA.STNT.ZS | E63: Prevalence of stunting, height for age (% of children under 5) | F63: Banco Mundial/OMS/UNICEF | G63: https://data.worldbank.org/indicator/SH.STA.STNT.ZS?locations=AO | H63: % crianças <5 | I63: - | J63: 0 | K63: 60 | L63: 25 | M63: 1 | N63: Média | O63: 1/11 | P63: 2015 | Q63: Mede nutrição crónica infantil.
A64: 7. Segurança Alimentar e Saúde | B64: Emaciação infantil | C64: Complementar | D64: SH.STA.WAST.ZS | E64: Prevalence of wasting, weight for height (% of children under 5) | F64: Banco Mundial/OMS/UNICEF | G64: https://data.worldbank.org/indicator/SH.STA.WAST.ZS?locations=AO | H64: % crianças <5 | I64: - | J64: 0 | K64: 25 | L64: 5 | M64: 1 | N64: Média | O64: 1/11 | P64: 2015 | Q64: Mede nutrição aguda e choque alimentar/saúde.
A65: 7. Segurança Alimentar e Saúde | B65: Mortalidade de menores de 5 anos | C65: Complementar | D65: SH.DYN.MORT | E65: Mortality rate, under-5 (per 1,000 live births) | F65: Banco Mundial/UNICEF | G65: https://data.worldbank.org/indicator/SH.DYN.MORT?locations=AO | H65: por 1000 | I65: - | J65: 0 | K65: 200 | L65: 50 | M65: 1 | N65: Alta | O65: 10/11 | P65: 2024 | Q65: Mais abrangente que mortalidade infantil isolada.
A66: 7. Segurança Alimentar e Saúde | B66: Cobertura universal de saúde - UHC service coverage index | C66: Complementar | D66: SH.UHC.SRVS.CV.XD | E66: UHC service coverage index | F66: Banco Mundial/OMS | G66: https://data.worldbank.org/indicator/SH.UHC.SRVS.CV.XD?locations=AO | H66: 0-100 | I66: + | J66: 0 | K66: 100 | L66: 55 | M66: 1 | N66: Baixa | O66: 0/11 | Q66: Sintetiza cobertura efetiva de serviços essenciais. Usar como benchmark de qualidade; a cobertura anual para Angola é limitada.
A67: 7. Segurança Alimentar e Saúde | B67: Vacinação DPT | C67: Substituto/Complementar | D67: SH.IMM.IDPT | E67: Immunization, DPT (% of children ages 12-23 months) | F67: Banco Mundial/OMS/UNICEF | G67: https://data.worldbank.org/indicator/SH.IMM.IDPT?locations=AO | H67: % crianças 12-23m | I67: + | J67: 0 | K67: 100 | L67: 85 | M67: 1 | N67: Alta | O67: 10/11 | P67: 2024 | Q67: Pode complementar a cobertura vacinal geral com indicador padronizado.
A68: 7. Segurança Alimentar e Saúde | B68: Despesa corrente em saúde (% PIB) | C68: Substituto | D68: SH.XPD.CHEX.GD.ZS | E68: Current health expenditure (% of GDP) | F68: Banco Mundial/OMS | G68: https://data.worldbank.org/indicator/SH.XPD.CHEX.GD.ZS?locations=AO | H68: % | I68: + | J68: 0 | K68: 15 | L68: 5 | M68: 1 | N68: Alta | O68: 9/11 | P68: 2023 | Q68: Fonte internacional padronizada para a linha já existente.
A69: 7. Segurança Alimentar e Saúde | B69: Médicos por 1000 habitantes | C69: Complementar | D69: SH.MED.PHYS.ZS | E69: Physicians (per 1,000 people) | F69: Banco Mundial/OMS | G69: https://data.worldbank.org/indicator/SH.MED.PHYS.ZS?locations=AO | H69: por 1000 | I69: + | J69: 0 | K69: 5 | L69: 1 | M69: 1 | N69: Média | O69: 3/11 | P69: 2022 | Q69: Complementa camas hospitalares com capacidade humana do sistema.
A70: 7. Segurança Alimentar e Saúde | B70: Camas hospitalares por 1000 habitantes | C70: Substituto | D70: SH.MED.BEDS.ZS | E70: Hospital beds (per 1,000 people) | F70: Banco Mundial/OMS | G70: https://data.worldbank.org/indicator/SH.MED.BEDS.ZS?locations=AO | H70: por 1000 | I70: + | J70: 0 | K70: 10 | L70: 2 | M70: 1 | N70: Alta | O70: 1/11 | P70: 2019 | Q70: Fonte alternativa para preencher a série com baixa cobertura.
A71: 7. Segurança Alimentar e Saúde | B71: Índice de produção alimentar | C71: Complementar | D71: AG.PRD.FOOD.XD | E71: Food production index (2014-2016 = 100) | F71: Banco Mundial/FAO | G71: https://data.worldbank.org/indicator/AG.PRD.FOOD.XD?locations=AO | H71: 2014-2016=100 | I71: + | J71: 50 | K71: 150 | L71: 110 | M71: 1 | N71: Média | O71: 8/11 | P71: 2022 | Q71: Acompanha disponibilidade doméstica de alimentos.
A72: 7. Segurança Alimentar e Saúde | B72: Rendimento cerealífero | C72: Complementar | D72: AG.YLD.CREL.KG | E72: Cereal yield (kg per hectare) | F72: Banco Mundial/FAO | G72: https://data.worldbank.org/indicator/AG.YLD.CREL.KG?locations=AO | H72: kg/ha | I72: + | J72: 0 | K72: 6000 | L72: 2000 | M72: 1 | N72: Média | O72: 9/11 | P72: 2023 | Q72: Proxy de produtividade agrícola e segurança alimentar.
