Workbook

Sheet Metodologia_v4
A1: IGDA-BDA v4 - metodologia linkada
A2: Seleciona os melhores indicadores disponíveis por dimensão, separa dados observados de dados ajustados, e identifica todos os anos não observados usados no cálculo.
A4: Parâmetros editáveis
A5: Parâmetro | B5: Valor | C5: Uso nas fórmulas
A6: Ano inicial | B6: 2015 | C6: Referenciado pelas folhas de dados ajustados, flags, normalização, subíndices e IGDA.
A7: Ano final | B7: 2025 | C7: Referenciado pelas folhas de dados ajustados, flags, normalização, subíndices e IGDA.
A8: Escala normalizada mínima | B8: 0 | C8: Referenciado pelas folhas de dados ajustados, flags, normalização, subíndices e IGDA.
A9: Escala normalizada máxima | B9: 100 | C9: Referenciado pelas folhas de dados ajustados, flags, normalização, subíndices e IGDA.
A10: Limiar mínimo de cobertura por subíndice | B10: 0.5 | C10: Referenciado pelas folhas de dados ajustados, flags, normalização, subíndices e IGDA.
A11: Nº mínimo de subíndices para IGDA global | B11: 4 | C11: Referenciado pelas folhas de dados ajustados, flags, normalização, subíndices e IGDA.
A12: Lacuna máxima para interpolação linear (nº de anos sem observação entre dois dados) | B12: 3 | C12: Referenciado pelas folhas de dados ajustados, flags, normalização, subíndices e IGDA.
A13: Carry-forward máximo no fim da série (anos) | B13: 2 | C13: Referenciado pelas folhas de dados ajustados, flags, normalização, subíndices e IGDA.
A14: Carry-backward máximo no início da série (anos) | B14: 1 | C14: Referenciado pelas folhas de dados ajustados, flags, normalização, subíndices e IGDA.
A15: Agregação dos indicadores no subíndice | B15: Média aritmética ponderada | C15: Referenciado pelas folhas de dados ajustados, flags, normalização, subíndices e IGDA.
A16: Agregação dos subíndices no IGDA | B16: Média geométrica ponderada | C16: Referenciado pelas folhas de dados ajustados, flags, normalização, subíndices e IGDA.
A19: Regras para anos não observáveis
A20: Flag | B20: Descrição
A21: OBS | B21: Valor observado diretamente na fonte usada.
A22: EST_INTERP_LINEAR | B22: Ano sem observação estimado por interpolação linear entre dois anos observados, se a lacuna for menor ou igual a B12.
A23: EST_CARRY_FORWARD | B23: Ano final sem observação preenchido com o último valor observado, até ao limite de B13.
A24: EST_CARRY_BACKWARD | B24: Ano inicial sem observação preenchido com o primeiro valor observado posterior, até ao limite de B14.
A25: SEM_DADO | B25: Sem observação e sem ajustamento permitido; o indicador é ignorado nesse ano.
A29: Fórmulas metodológicas
A30: Item | B30: Regra
A31: Normalização sentido positivo | B31: Score = MIN(100, MAX(0, (valor - mínimo) / (máximo - mínimo) * 100))
A32: Normalização sentido negativo | B32: Score = MIN(100, MAX(0, (máximo - valor) / (máximo - mínimo) * 100))
A33: Subíndice | B33: Média aritmética ponderada dos indicadores ativos com score disponível, se cumprir o limiar mínimo de cobertura.
A34: IGDA global | B34: Média geométrica ponderada dos sete subíndices, se houver pelo menos o nº mínimo de subíndices.

Sheet Indicadores_v4
A1: Indicadores finais selecionados para o IGDA-BDA v4
A2: Edite pesos, ativos, mínimos, máximos e metas nesta folha. As demais folhas referenciam estes parâmetros.
A4: ID | B4: Dimensão | C4: Indicador | D4: Unidade | E4: Sentido | F4: Mínimo | G4: Máximo | H4: Meta 2027 | I4: Peso indicador | J4: Ativo | K4: Fonte | L4: Código/API | M4: Fonte_URL | N4: Prioridade | O4: Justificação | P4: Regra anos em falta
A5: GOV01 | B5: 1. Governança e Estado de Direito | C5: Índice de Percepção da Corrupção | D5: 0-100 | E5: + | F5: 0 | G5: 100 | H5: 35 | I5: 1 | J5: 1 | K5: Transparency International / ficheiro base | M5: https://www.transparency.org/en/cpi | N5: Alta | O5: Referência internacional já usada no modelo original. | P5: Usa regra global definida em Metodologia_v4!B12:B14
A6: GOV02 | B6: 1. Governança e Estado de Direito | C6: WGI - Estado de Direito | D6: -2.5 a 2.5 | E6: + | F6: -2.5 | G6: 2.5 | H6: 0 | I6: 1 | J6: 1 | K6: Worldwide Governance Indicators | L6: RL.EST | M6: https://datacatalogfiles.worldbank.org/ddh-published/0038026/DR0095947/wgidataset_with_sourcedata-2025.xlsx | N6: Alta | O6: Estado de Direito e execução de regras. | P6: Usa regra global definida em Metodologia_v4!B12:B14
A7: GOV03 | B7: 1. Governança e Estado de Direito | C7: WGI - Eficiência do Governo | D7: -2.5 a 2.5 | E7: + | F7: -2.5 | G7: 2.5 | H7: 0 | I7: 1 | J7: 1 | K7: Worldwide Governance Indicators | L7: GE.EST | M7: https://datacatalogfiles.worldbank.org/ddh-published/0038026/DR0095947/wgidataset_with_sourcedata-2025.xlsx | N7: Alta | O7: Capacidade do Estado para executar políticas públicas. | P7: Usa regra global definida em Metodologia_v4!B12:B14
A8: GOV04 | B8: 1. Governança e Estado de Direito | C8: WGI - Estabilidade Política | D8: -2.5 a 2.5 | E8: + | F8: -2.5 | G8: 2.5 | H8: 0 | I8: 1 | J8: 1 | K8: Worldwide Governance Indicators | L8: PV.EST | M8: https://datacatalogfiles.worldbank.org/ddh-published/0038026/DR0095947/wgidataset_with_sourcedata-2025.xlsx | N8: Alta | O8: Risco político, violência e continuidade institucional. | P8: Usa regra global definida em Metodologia_v4!B12:B14
A9: GOV05 | B9: 1. Governança e Estado de Direito | C9: WGI - Qualidade Regulatória | D9: -2.5 a 2.5 | E9: + | F9: -2.5 | G9: 2.5 | H9: 0 | I9: 1 | J9: 1 | K9: Worldwide Governance Indicators | L9: RQ.EST | M9: https://datacatalogfiles.worldbank.org/ddh-published/0038026/DR0095947/wgidataset_with_sourcedata-2025.xlsx | N9: Alta | O9: Substituto robusto para Doing Business, descontinuado. | P9: Usa regra global definida em Metodologia_v4!B12:B14
A10: GOV06 | B10: 1. Governança e Estado de Direito | C10: WGI - Controlo da Corrupção | D10: -2.5 a 2.5 | E10: + | F10: -2.5 | G10: 2.5 | H10: 0 | I10: 1 | J10: 1 | K10: Worldwide Governance Indicators | L10: CC.EST | M10: https://datacatalogfiles.worldbank.org/ddh-published/0038026/DR0095947/wgidataset_with_sourcedata-2025.xlsx | N10: Alta | O10: Complementa o CPI com uma métrica WGI coerente. | P10: Usa regra global definida em Metodologia_v4!B12:B14
A11: MAC01 | B11: 2. Estabilidade Macroeconómica | C11: Crescimento real do PIB | D11: % | E11: + | F11: -10 | G11: 15 | H11: 5 | I11: 1 | J11: 1 | K11: Banco Mundial/WDI | L11: NY.GDP.MKTP.KD.ZG | M11: https://data.worldbank.org/indicator/NY.GDP.MKTP.KD.ZG?locations=AO | N11: Alta | O11: Dinamismo económico real. | P11: Usa regra global definida em Metodologia_v4!B12:B14
A12: MAC02 | B12: 2. Estabilidade Macroeconómica | C12: PIB per capita | D12: USD correntes | E12: + | F12: 500 | G12: 15000 | H12: 5000 | I12: 1 | J12: 1 | K12: Banco Mundial/WDI | L12: NY.GDP.PCAP.CD | M12: https://data.worldbank.org/indicator/NY.GDP.PCAP.CD?locations=AO | N12: Alta | O12: Nível médio de rendimento. | P12: Usa regra global definida em Metodologia_v4!B12:B14
A13: MAC03 | B13: 2. Estabilidade Macroeconómica | C13: Inflação, preços ao consumidor | D13: % | E13: - | F13: 0 | G13: 50 | H13: 10 | I13: 1 | J13: 1 | K13: Banco Mundial/WDI | L13: FP.CPI.TOTL.ZG | M13: https://data.worldbank.org/indicator/FP.CPI.TOTL.ZG?locations=AO | N13: Alta | O13: Estabilidade de preços. | P13: Usa regra global definida em Metodologia_v4!B12:B14
A14: MAC04 | B14: 2. Estabilidade Macroeconómica | C14: Dívida pública do governo central | D14: % PIB | E14: - | F14: 0 | G14: 150 | H14: 60 | I14: 1 | J14: 1 | K14: Banco Mundial/WDI | L14: GC.DOD.TOTL.GD.ZS | M14: https://data.worldbank.org/indicator/GC.DOD.TOTL.GD.ZS?locations=AO | N14: Alta | O14: Sustentabilidade fiscal. | P14: Usa regra global definida em Metodologia_v4!B12:B14
A15: MAC05 | B15: 2. Estabilidade Macroeconómica | C15: Saldo orçamental de caixa | D15: % PIB | E15: + | F15: -15 | G15: 10 | H15: 0 | I15: 1 | J15: 1 | K15: Banco Mundial/WDI | L15: GC.BAL.CASH.GD.ZS | M15: https://data.worldbank.org/indicator/GC.BAL.CASH.GD.ZS?locations=AO | N15: Alta | O15: Equilíbrio fiscal corrente. | P15: Usa regra global definida em Metodologia_v4!B12:B14
A16: MAC06 | B16: 2. Estabilidade Macroeconómica | C16: Saldo da conta corrente | D16: % PIB | E16: + | F16: -30 | G16: 30 | H16: 0 | I16: 1 | J16: 1 | K16: Banco Mundial/WDI | L16: BN.CAB.XOKA.GD.ZS | M16: https://data.worldbank.org/indicator/BN.CAB.XOKA.GD.ZS?locations=AO | N16: Alta | O16: Sustentabilidade externa. | P16: Usa regra global definida em Metodologia_v4!B12:B14
A17: MAC07 | B17: 2. Estabilidade Macroeconómica | C17: Reservas internacionais | D17: meses de importações | E17: + | F17: 0 | G17: 12 | H17: 6 | I17: 1 | J17: 1 | K17: Banco Mundial/WDI | L17: FI.RES.TOTL.MO | M17: https://data.worldbank.org/indicator/FI.RES.TOTL.MO?locations=AO | N17: Alta | O17: Almofada externa contra choques. | P17: Usa regra global definida em Metodologia_v4!B12:B14
A18: MAC08 | B18: 2. Estabilidade Macroeconómica | C18: Receita fiscal | D18: % PIB | E18: + | F18: 0 | G18: 40 | H18: 18 | I18: 1 | J18: 1 | K18: Banco Mundial/WDI | L18: GC.TAX.TOTL.GD.ZS | M18: https://data.worldbank.org/indicator/GC.TAX.TOTL.GD.ZS?locations=AO | N18: Alta | O18: Capacidade doméstica de financiamento público. | P18: Usa regra global definida em Metodologia_v4!B12:B14
A19: HUM01 | B19: 3. Capital Humano | C19: Índice de Desenvolvimento Humano | D19: 0-1 | E19: + | F19: 0 | G19: 1 | H19: 0.6 | I19: 1 | J19: 1 | K19: PNUD/HDR / ficheiro base | M19: https://hdr.undp.org/data-center | N19: Alta | O19: Indicador sintético de saúde, educação e rendimento. | P19: Usa regra global definida em Metodologia_v4!B12:B14
A20: HUM02 | B20: 3. Capital Humano | C20: Esperança de vida à nascença | D20: anos | E20: + | F20: 40 | G20: 85 | H20: 65 | I20: 1 | J20: 1 | K20: Banco Mundial/WDI | L20: SP.DYN.LE00.IN | M20: https://data.worldbank.org/indicator/SP.DYN.LE00.IN?locations=AO | N20: Alta | O20: Resultado central de saúde e bem-estar. | P20: Usa regra global definida em Metodologia_v4!B12:B14
A21: HUM03 | B21: 3. Capital Humano | C21: Alfabetização adulta | D21: % | E21: + | F21: 0 | G21: 100 | H21: 75 | I21: 1 | J21: 1 | K21: Banco Mundial/UNESCO | L21: SE.ADT.LITR.ZS | M21: https://data.worldbank.org/indicator/SE.ADT.LITR.ZS?locations=AO | N21: Média | O21: Competência básica acumulada. | P21: Usa regra global definida em Metodologia_v4!B12:B14
A22: HUM04 | B22: 3. Capital Humano | C22: Conclusão do ensino primário | D22: % | E22: + | F22: 0 | G22: 100 | H22: 90 | I22: 1 | J22: 1 | K22: Banco Mundial/UNESCO | L22: SE.PRM.CMPT.ZS | M22: https://data.worldbank.org/indicator/SE.PRM.CMPT.ZS?locations=AO | N22: Alta | O22: Resultado educacional mais robusto que matrícula simples. | P22: Usa regra global definida em Metodologia_v4!B12:B14
A23: HUM05 | B23: 3. Capital Humano | C23: Matrícula no ensino secundário | D23: % bruto | E23: + | F23: 0 | G23: 150 | H23: 80 | I23: 1 | J23: 1 | K23: Banco Mundial/UNESCO | L23: SE.SEC.ENRR | M23: https://data.worldbank.org/indicator/SE.SEC.ENRR?locations=AO | N23: Alta | O23: Continuidade escolar pós-primária. | P23: Usa regra global definida em Metodologia_v4!B12:B14
A24: HUM06 | B24: 3. Capital Humano | C24: Despesa pública em educação | D24: % PIB | E24: + | F24: 0 | G24: 10 | H24: 5 | I24: 1 | J24: 1 | K24: Banco Mundial/UNESCO | L24: SE.XPD.TOTL.GD.ZS | M24: https://data.worldbank.org/indicator/SE.XPD.TOTL.GD.ZS?locations=AO | N24: Média | O24: Esforço público em educação. | P24: Usa regra global definida em Metodologia_v4!B12:B14
A25: HUM07 | B25: 3. Capital Humano | C25: Mortalidade infantil | D25: por 1000 nados-vivos | E25: - | F25: 0 | G25: 150 | H25: 40 | I25: 1 | J25: 1 | K25: Banco Mundial/WDI | L25: SP.DYN.IMRT.IN | M25: https://data.worldbank.org/indicator/SP.DYN.IMRT.IN?locations=AO | N25: Alta | O25: Resultado de saúde infantil. | P25: Usa regra global definida em Metodologia_v4!B12:B14
A26: INC01 | B26: 4. Inclusão Social e Protecção | C26: Pobreza internacional | D26: % pop. abaixo de 3,00 USD/dia PPP 2021 | E26: - | F26: 0 | G26: 90 | H26: 40 | I26: 1 | J26: 1 | K26: Banco Mundial/PIP | L26: SI.POV.DDAY | M26: https://data.worldbank.org/indicator/SI.POV.DDAY?locations=AO | N26: Alta | O26: Pobreza monetária internacional atualizada. | P26: Usa regra global definida em Metodologia_v4!B12:B14
A27: INC02 | B27: 4. Inclusão Social e Protecção | C27: Índice de Gini | D27: 0-100 | E27: - | F27: 0 | G27: 70 | H27: 40 | I27: 1 | J27: 1 | K27: Banco Mundial/PIP | L27: SI.POV.GINI | M27: https://data.worldbank.org/indicator/SI.POV.GINI?locations=AO | N27: Alta | O27: Desigualdade de rendimento. | P27: Usa regra global definida em Metodologia_v4!B12:B14
A28: INC03 | B28: 4. Inclusão Social e Protecção | C28: Rendimento dos 20% mais pobres | D28: % rendimento total | E28: + | F28: 0 | G28: 20 | H28: 7 | I28: 1 | J28: 1 | K28: Banco Mundial/PIP | L28: SI.DST.FRST.20 | M28: https://data.worldbank.org/indicator/SI.DST.FRST.20?locations=AO | N28: Média | O28: Inclusão distributiva na base da distribuição. | P28: Usa regra global definida em Metodologia_v4!B12:B14
A29: INC04 | B29: 4. Inclusão Social e Protecção | C29: Global Gender Gap Index | D29: 0-1 | E29: + | F29: 0 | G29: 1 | H29: 0.7 | I29: 1 | J29: 1 | K29: WEF / ficheiro base | M29: https://www.weforum.org/publications/global-gender-gap-report-2025/ | N29: Alta | O29: Medida internacional de igualdade de género. | P29: Usa regra global definida em Metodologia_v4!B12:B14
A30: INC05 | B30: 4. Inclusão Social e Protecção | C30: Participação feminina na força de trabalho | D30: % | E30: + | F30: 0 | G30: 100 | H30: 65 | I30: 1 | J30: 1 | K30: Banco Mundial/OIT | L30: SL.TLF.CACT.FE.ZS | M30: https://data.worldbank.org/indicator/SL.TLF.CACT.FE.ZS?locations=AO | N30: Alta | O30: Inclusão económica das mulheres. | P30: Usa regra global definida em Metodologia_v4!B12:B14
A31: INC06 | B31: 4. Inclusão Social e Protecção | C31: Mulheres no parlamento | D31: % lugares | E31: + | F31: 0 | G31: 60 | H31: 35 | I31: 1 | J31: 1 | K31: Banco Mundial/IPU | L31: SG.GEN.PARL.ZS | M31: https://data.worldbank.org/indicator/SG.GEN.PARL.ZS?locations=AO | N31: Média | O31: Inclusão política de género. | P31: Usa regra global definida em Metodologia_v4!B12:B14
A32: INC07 | B32: 4. Inclusão Social e Protecção | C32: Jovens NEET | D32: % jovens | E32: - | F32: 0 | G32: 70 | H32: 30 | I32: 1 | J32: 1 | K32: Banco Mundial/OIT | L32: SL.UEM.NEET.ZS | M32: https://data.worldbank.org/indicator/SL.UEM.NEET.ZS?locations=AO | N32: Alta | O32: Jovens fora de educação, emprego e formação. | P32: Usa regra global definida em Metodologia_v4!B12:B14
A33: INC08 | B33: 4. Inclusão Social e Protecção | C33: RNB per capita | D33: USD correntes | E33: + | F33: 500 | G33: 15000 | H33: 4500 | I33: 1 | J33: 1 | K33: Banco Mundial/WDI | L33: NY.GNP.PCAP.CD | M33: https://data.worldbank.org/indicator/NY.GNP.PCAP.CD?locations=AO | N33: Média | O33: Rendimento nacional médio, já presente na lógica original. | P33: Usa regra global definida em Metodologia_v4!B12:B14
A34: INF01 | B34: 5. Infraestruturas e Serviços | C34: Acesso à eletricidade | D34: % população | E34: + | F34: 0 | G34: 100 | H34: 60 | I34: 1 | J34: 1 | K34: Banco Mundial/IEA | L34: EG.ELC.ACCS.ZS | M34: https://data.worldbank.org/indicator/EG.ELC.ACCS.ZS?locations=AO | N34: Alta | O34: Acesso básico a energia. | P34: Usa regra global definida em Metodologia_v4!B12:B14
A35: INF02 | B35: 5. Infraestruturas e Serviços | C35: Perdas na rede elétrica | D35: % produção | E35: - | F35: 0 | G35: 60 | H35: 15 | I35: 1 | J35: 1 | K35: Banco Mundial/IEA | L35: EG.ELC.LOSS.ZS | M35: https://data.worldbank.org/indicator/EG.ELC.LOSS.ZS?locations=AO | N35: Média | O35: Qualidade e eficiência da rede elétrica. | P35: Usa regra global definida em Metodologia_v4!B12:B14
A36: INF03 | B36: 5. Infraestruturas e Serviços | C36: Acesso a água potável básica | D36: % população | E36: + | F36: 0 | G36: 100 | H36: 70 | I36: 1 | J36: 1 | K36: Banco Mundial/JMP | L36: SH.H2O.BASW.ZS | M36: https://data.worldbank.org/indicator/SH.H2O.BASW.ZS?locations=AO | N36: Alta | O36: Serviço básico essencial. | P36: Usa regra global definida em Metodologia_v4!B12:B14
A37: INF04 | B37: 5. Infraestruturas e Serviços | C37: Acesso a saneamento básico | D37: % população | E37: + | F37: 0 | G37: 100 | H37: 60 | I37: 1 | J37: 1 | K37: Banco Mundial/JMP | L37: SH.STA.BASS.ZS | M37: https://data.worldbank.org/indicator/SH.STA.BASS.ZS?locations=AO | N37: Alta | O37: Serviço básico com impacto em saúde. | P37: Usa regra global definida em Metodologia_v4!B12:B14
A38: INF05 | B38: 5. Infraestruturas e Serviços | C38: Acesso a energia limpa para cozinhar | D38: % população | E38: + | F38: 0 | G38: 100 | H38: 35 | I38: 1 | J38: 1 | K38: Banco Mundial/OMS | L38: EG.CFT.ACCS.ZS | M38: https://data.worldbank.org/indicator/EG.CFT.ACCS.ZS?locations=AO | N38: Alta | O38: Infraestrutura doméstica com impacto em saúde e ambiente. | P38: Usa regra global definida em Metodologia_v4!B12:B14
A39: INF06 | B39: 5. Infraestruturas e Serviços | C39: Utilizadores de internet | D39: % população | E39: + | F39: 0 | G39: 100 | H39: 40 | I39: 1 | J39: 1 | K39: Banco Mundial/ITU | L39: IT.NET.USER.ZS | M39: https://data.worldbank.org/indicator/IT.NET.USER.ZS?locations=AO | N39: Alta | O39: Acesso digital efetivo. | P39: Usa regra global definida em Metodologia_v4!B12:B14
A40: INF07 | B40: 5. Infraestruturas e Serviços | C40: Subscrições móveis | D40: por 100 habitantes | E40: + | F40: 0 | G40: 160 | H40: 100 | I40: 1 | J40: 1 | K40: Banco Mundial/ITU | L40: IT.CEL.SETS.P2 | M40: https://data.worldbank.org/indicator/IT.CEL.SETS.P2?locations=AO | N40: Alta | O40: Infraestrutura e penetração móvel. | P40: Usa regra global definida em Metodologia_v4!B12:B14
A41: INF08 | B41: 5. Infraestruturas e Serviços | C41: Banda larga fixa | D41: por 100 habitantes | E41: + | F41: 0 | G41: 50 | H41: 8 | I41: 1 | J41: 1 | K41: Banco Mundial/ITU | L41: IT.NET.BBND.P2 | M41: https://data.worldbank.org/indicator/IT.NET.BBND.P2?locations=AO | N41: Média | O41: Infraestrutura digital fixa. | P41: Usa regra global definida em Metodologia_v4!B12:B14
A42: INF09 | B42: 5. Infraestruturas e Serviços | C42: Densidade rodoviária | D42: km/1000 km2 | E42: + | F42: 0 | G42: 100 | H42: 30 | I42: 1 | J42: 1 | K42: MINTRANS / ficheiro base | N42: Média | O42: Conectividade física territorial. | P42: Usa regra global definida em Metodologia_v4!B12:B14
A43: LAB01 | B43: 6. Mercado de Trabalho | C43: Taxa de emprego | D43: % | E43: + | F43: 0 | G43: 100 | H43: 65 | I43: 1 | J43: 1 | K43: Banco Mundial/OIT | L43: SL.EMP.TOTL.SP.ZS | M43: https://data.worldbank.org/indicator/SL.EMP.TOTL.SP.ZS?locations=AO | N43: Alta | O43: Emprego face à população em idade ativa. | P43: Usa regra global definida em Metodologia_v4!B12:B14
A44: LAB02 | B44: 6. Mercado de Trabalho | C44: Taxa de desemprego | D44: % | E44: - | F44: 0 | G44: 50 | H44: 20 | I44: 1 | J44: 1 | K44: Banco Mundial/OIT | L44: SL.UEM.TOTL.ZS | M44: https://data.worldbank.org/indicator/SL.UEM.TOTL.ZS?locations=AO | N44: Alta | O44: Subutilização laboral aberta. | P44: Usa regra global definida em Metodologia_v4!B12:B14
A45: LAB03 | B45: 6. Mercado de Trabalho | C45: Desemprego juvenil | D45: % | E45: - | F45: 0 | G45: 70 | H45: 30 | I45: 1 | J45: 1 | K45: Banco Mundial/OIT | L45: SL.UEM.1524.ZS | M45: https://data.worldbank.org/indicator/SL.UEM.1524.ZS?locations=AO | N45: Alta | O45: Risco laboral dos jovens. | P45: Usa regra global definida em Metodologia_v4!B12:B14
A46: LAB04 | B46: 6. Mercado de Trabalho | C46: Participação na força de trabalho | D46: % | E46: + | F46: 0 | G46: 100 | H46: 70 | I46: 1 | J46: 1 | K46: Banco Mundial/OIT | L46: SL.TLF.CACT.ZS | M46: https://data.worldbank.org/indicator/SL.TLF.CACT.ZS?locations=AO | N46: Alta | O46: Oferta laboral ativa. | P46: Usa regra global definida em Metodologia_v4!B12:B14
A47: LAB05 | B47: 6. Mercado de Trabalho | C47: Emprego vulnerável | D47: % emprego total | E47: - | F47: 0 | G47: 100 | H47: 50 | I47: 1 | J47: 1 | K47: Banco Mundial/OIT | L47: SL.EMP.VULN.ZS | M47: https://data.worldbank.org/indicator/SL.EMP.VULN.ZS?locations=AO | N47: Alta | O47: Qualidade e precariedade do emprego. | P47: Usa regra global definida em Metodologia_v4!B12:B14
A48: LAB06 | B48: 6. Mercado de Trabalho | C48: Trabalhadores assalariados | D48: % emprego total | E48: + | F48: 0 | G48: 100 | H48: 50 | I48: 1 | J48: 1 | K48: Banco Mundial/OIT | L48: SL.EMP.WORK.ZS | M48: https://data.worldbank.org/indicator/SL.EMP.WORK.ZS?locations=AO | N48: Alta | O48: Proxy de emprego mais formal e protegido. | P48: Usa regra global definida em Metodologia_v4!B12:B14
A49: LAB07 | B49: 6. Mercado de Trabalho | C49: PIB por pessoa empregada | D49: USD PPP constantes | E49: + | F49: 1000 | G49: 50000 | H49: 12000 | I49: 1 | J49: 1 | K49: Banco Mundial/OIT | L49: SL.GDP.PCAP.EM.KD | M49: https://data.worldbank.org/indicator/SL.GDP.PCAP.EM.KD?locations=AO | N49: Alta | O49: Nível de produtividade laboral. | P49: Usa regra global definida em Metodologia_v4!B12:B14
A50: LAB08 | B50: 6. Mercado de Trabalho | C50: Emprego informal | D50: % emprego | E50: - | F50: 0 | G50: 100 | H50: 50 | I50: 1 | J50: 1 | K50: INE / ficheiro base | N50: Alta | O50: Qualidade institucional do mercado de trabalho. | P50: Usa regra global definida em Metodologia_v4!B12:B14
A51: LAB09 | B51: 6. Mercado de Trabalho | C51: Taxa de formalização | D51: % | E51: + | F51: 0 | G51: 100 | H51: 40 | I51: 1 | J51: 1 | K51: INSS / ficheiro base | N51: Média | O51: Cobertura formal e contributiva. | P51: Usa regra global definida em Metodologia_v4!B12:B14
A52: SAU01 | B52: 7. Segurança Alimentar e Saúde | C52: Prevalência de subalimentação | D52: % população | E52: - | F52: 0 | G52: 60 | H52: 20 | I52: 1 | J52: 1 | K52: Banco Mundial/FAO | L52: SN.ITK.DEFC.ZS | M52: https://data.worldbank.org/indicator/SN.ITK.DEFC.ZS?locations=AO | N52: Alta | O52: Privação alimentar estrutural. | P52: Usa regra global definida em Metodologia_v4!B12:B14
A53: SAU02 | B53: 7. Segurança Alimentar e Saúde | C53: Insegurança alimentar moderada ou severa | D53: % população | E53: - | F53: 0 | G53: 100 | H53: 45 | I53: 1 | J53: 1 | K53: Banco Mundial/FAO | L53: SN.ITK.MSFI.ZS | M53: https://data.worldbank.org/indicator/SN.ITK.MSFI.ZS?locations=AO | N53: Alta | O53: Acesso alimentar insuficiente. | P53: Usa regra global definida em Metodologia_v4!B12:B14
A54: SAU03 | B54: 7. Segurança Alimentar e Saúde | C54: Mortalidade materna | D54: por 100 mil nados-vivos | E54: - | F54: 0 | G54: 1000 | H54: 300 | I54: 1 | J54: 1 | K54: Banco Mundial/OMS | L54: SH.STA.MMRT | M54: https://data.worldbank.org/indicator/SH.STA.MMRT?locations=AO | N54: Alta | O54: Capacidade do sistema de saúde materna. | P54: Usa regra global definida em Metodologia_v4!B12:B14
A55: SAU04 | B55: 7. Segurança Alimentar e Saúde | C55: Mortalidade de menores de 5 anos | D55: por 1000 nados-vivos | E55: - | F55: 0 | G55: 200 | H55: 50 | I55: 1 | J55: 1 | K55: Banco Mundial/UNICEF | L55: SH.DYN.MORT | M55: https://data.worldbank.org/indicator/SH.DYN.MORT?locations=AO | N55: Alta | O55: Resultado amplo de saúde infantil. | P55: Usa regra global definida em Metodologia_v4!B12:B14
A56: SAU05 | B56: 7. Segurança Alimentar e Saúde | C56: Despesa corrente em saúde | D56: % PIB | E56: + | F56: 0 | G56: 15 | H56: 5 | I56: 1 | J56: 1 | K56: Banco Mundial/OMS | L56: SH.XPD.CHEX.GD.ZS | M56: https://data.worldbank.org/indicator/SH.XPD.CHEX.GD.ZS?locations=AO | N56: Média | O56: Esforço económico no sistema de saúde. | P56: Usa regra global definida em Metodologia_v4!B12:B14
A57: SAU06 | B57: 7. Segurança Alimentar e Saúde | C57: Vacinação DPT | D57: % crianças 12-23 meses | E57: + | F57: 0 | G57: 100 | H57: 85 | I57: 1 | J57: 1 | K57: Banco Mundial/OMS/UNICEF | L57: SH.IMM.IDPT | M57: https://data.worldbank.org/indicator/SH.IMM.IDPT?locations=AO | N57: Alta | O57: Cobertura básica de imunização. | P57: Usa regra global definida em Metodologia_v4!B12:B14
A58: SAU07 | B58: 7. Segurança Alimentar e Saúde | C58: Médicos | D58: por 1000 habitantes | E58: + | F58: 0 | G58: 5 | H58: 1 | I58: 1 | J58: 1 | K58: Banco Mundial/OMS | L58: SH.MED.PHYS.ZS | M58: https://data.worldbank.org/indicator/SH.MED.PHYS.ZS?locations=AO | N58: Média | O58: Capacidade humana do sistema de saúde. | P58: Usa regra global definida em Metodologia_v4!B12:B14
A59: SAU08 | B59: 7. Segurança Alimentar e Saúde | C59: Camas hospitalares | D59: por 1000 habitantes | E59: + | F59: 0 | G59: 10 | H59: 2 | I59: 1 | J59: 1 | K59: Banco Mundial/OMS | L59: SH.MED.BEDS.ZS | M59: https://data.worldbank.org/indicator/SH.MED.BEDS.ZS?locations=AO | N59: Média | O59: Capacidade física hospitalar. | P59: Usa regra global definida em Metodologia_v4!B12:B14
A60: SAU09 | B60: 7. Segurança Alimentar e Saúde | C60: Índice de produção alimentar | D60: 2014-2016=100 | E60: + | F60: 50 | G60: 150 | H60: 110 | I60: 1 | J60: 1 | K60: Banco Mundial/FAO | L60: AG.PRD.FOOD.XD | M60: https://data.worldbank.org/indicator/AG.PRD.FOOD.XD?locations=AO | N60: Média | O60: Disponibilidade doméstica de alimentos. | P60: Usa regra global definida em Metodologia_v4!B12:B14

Sheet Dados_Observados_v4
A1: Dados observados por indicador
A2: Apenas valores diretamente observados nas fontes. Não contém estimativas.
A4: ID | B4: Dimensão | C4: Indicador | D4: Fonte | E4: Código/API | F4: Estado dados | G4: Cobertura observada | H4: Último ano obs. | I4: Nota | J4: 2015 | K4: 2016 | L4: 2017 | M4: 2018 | N4: 2019 | O4: 2020 | P4: 2021 | Q4: 2022 | R4: 2023 | S4: 2024 | T4: 2025
A5: GOV01 | B5: 1. Governança e Estado de Direito | C5: Índice de Percepção da Corrupção | D5: Transparency International / ficheiro base | F5: Série observada do ficheiro base | G5: 10/11 | H5: 2024 | J5: 15 | K5: 18 | L5: 19 | M5: 19 | N5: 26 | O5: 27 | P5: 29 | Q5: 33 | R5: 33 | S5: 32
A6: GOV02 | B6: 1. Governança e Estado de Direito | C6: WGI - Estado de Direito | D6: Worldwide Governance Indicators | E6: RL.EST | F6: Fonte oficial WGI 2025 | G6: 10/11 | H6: 2024 | I6: Rule of Law: Governance estimate | J6: -1.3086297 | K6: -1.3287764 | L6: -1.3317055 | M6: -1.1105522 | N6: -1.0519682 | O6: -0.9475038 | P6: -1.0980135 | Q6: -1.1625439 | R6: -1.1944432 | S6: -1.1697408
A7: GOV03 | B7: 1. Governança e Estado de Direito | C7: WGI - Eficiência do Governo | D7: Worldwide Governance Indicators | E7: GE.EST | F7: Fonte oficial WGI 2025 | G7: 10/11 | H7: 2024 | I7: Government Effectiveness: Governance estimate | J7: -0.9378237 | K7: -0.9493847 | L7: -0.9681157 | M7: -0.9784602 | N7: -0.9116965 | O7: -1.0163604 | P7: -0.9347008 | Q7: -0.8325718 | R7: -0.8287026 | S7: -0.7851909
A8: GOV04 | B8: 1. Governança e Estado de Direito | C8: WGI - Estabilidade Política | D8: Worldwide Governance Indicators | E8: PV.EST | F8: Fonte oficial WGI 2025 | G8: 10/11 | H8: 2024 | I8: Political Stability and Absence of Violence/Terrorism: Governance estimate | J8: -0.5591026 | K8: -0.434628 | L8: -0.5372145 | M8: -0.4058117 | N8: -0.4207039 | O8: -0.6427634 | P8: -0.7936068 | Q8: -0.5414068 | R8: -0.3131654 | S8: -0.5735964
A9: GOV05 | B9: 1. Governança e Estado de Direito | C9: WGI - Qualidade Regulatória | D9: Worldwide Governance Indicators | E9: RQ.EST | F9: Fonte oficial WGI 2025 | G9: 10/11 | H9: 2024 | I9: Regulatory Quality: Governance estimate | J9: -1.0904945 | K9: -1.1804235 | L9: -1.1799885 | M9: -1.0624393 | N9: -0.9960854 | O9: -1.0388818 | P9: -0.8486184 | Q9: -0.8618821 | R9: -0.904342 | S9: -0.77302
A10: GOV06 | B10: 1. Governança e Estado de Direito | C10: WGI - Controlo da Corrupção | D10: Worldwide Governance Indicators | E10: CC.EST | F10: Fonte oficial WGI 2025 | G10: 10/11 | H10: 2024 | I10: Control of Corruption: Governance estimate | J10: -1.4857649 | K10: -1.4881942 | L10: -1.4208093 | M10: -1.181782 | N10: -0.9647988 | O10: -0.8918323 | P10: -0.6416506 | Q10: -0.6031537 | R10: -0.6242518 | S10: -0.6225793
A11: MAC01 | B11: 2. Estabilidade Macroeconómica | C11: Crescimento real do PIB | D11: Banco Mundial/WDI | E11: NY.GDP.MKTP.KD.ZG | F11: Fonte Banco Mundial API/CSV | G11: 10/11 | H11: 2024 | I11: GDP growth (annual %) | J11: 0.76317771 | K11: -1.7005304 | L11: -0.14939623 | M11: -0.59441123 | N11: -0.20468025 | O11: -4.0424472 | P11: 2.1027525 | Q11: 4.2160026 | R11: 1.2633081 | S11: 4.4239066
A12: MAC02 | B12: 2. Estabilidade Macroeconómica | C12: PIB per capita | D12: Banco Mundial/WDI | E12: NY.GDP.PCAP.CD | F12: Fonte Banco Mundial API/CSV | G12: 10/11 | H12: 2024 | I12: GDP per capita (current US$) | J12: 3641.7289 | K12: 2051.8146 | L12: 2790.7189 | M12: 2860.0936 | N12: 2493.6788 | O12: 1759.3562 | P12: 2303.9081 | Q12: 3682.1132 | R12: 2916.1366 | S12: 2665.8744
A13: MAC03 | B13: 2. Estabilidade Macroeconómica | C13: Inflação, preços ao consumidor | D13: Banco Mundial/WDI | E13: FP.CPI.TOTL.ZG | F13: Fonte Banco Mundial API/CSV | G13: 10/11 | H13: 2024 | I13: Inflation, consumer prices (annual %) | J13: 9.3559722 | K13: 30.694415 | L13: 29.84448 | M13: 19.628938 | N13: 17.080954 | O13: 22.271539 | P13: 25.754295 | Q13: 21.35529 | R13: 13.644102 | S13: 28.240495
A14: MAC04 | B14: 2. Estabilidade Macroeconómica | C14: Dívida pública do governo central | D14: Banco Mundial/WDI | E14: GC.DOD.TOTL.GD.ZS | F14: Sem valores Angola no período; fallback para série do ficheiro base | G14: 11/11 | H14: 2025 | I14: Central government debt, total (% of GDP) | J14: 50 | K14: 67 | L14: 60 | M14: 83 | N14: 101 | O14: 119 | P14: 74 | Q14: 56 | R14: 72 | S14: 60 | T14: 63
A15: MAC05 | B15: 2. Estabilidade Macroeconómica | C15: Saldo orçamental de caixa | D15: Banco Mundial/WDI | E15: GC.BAL.CASH.GD.ZS | F15: Sem valores Angola no período; fallback para série do ficheiro base | G15: 11/11 | H15: 2025 | I15: Cash surplus/deficit (% of GDP) | J15: -2 | K15: -3 | L15: 1.5 | M15: -0.5 | N15: 0.5 | O15: -5 | P15: 1.5 | Q15: 0.7 | R15: -1.9 | S15: -1.5 | T15: -1.65
A16: MAC06 | B16: 2. Estabilidade Macroeconómica | C16: Saldo da conta corrente | D16: Banco Mundial/WDI | E16: BN.CAB.XOKA.GD.ZS | F16: Fonte Banco Mundial API/CSV | G16: 10/11 | H16: 2024 | I16: Current account balance (% of GDP) | J16: -10.018075 | K16: -5.1524476 | L16: -0.75004756 | M16: 8.2698865 | N16: 6.363326 | O16: 1.4815318 | P16: 10.557441 | Q16: 8.9647752 | R16: 3.905087 | S16: 6.2474404
A17: MAC07 | B17: 2. Estabilidade Macroeconómica | C17: Reservas internacionais | D17: Banco Mundial/WDI | E17: FI.RES.TOTL.MO | F17: Fonte Banco Mundial API/CSV | G17: 10/11 | H17: 2024 | I17: Total reserves in months of imports | J17: 6.4820457 | K17: 9.0838712 | L17: 5.8181869 | M17: 5.4126402 | N17: 6.4250943 | O17: 8.0261477 | P17: 6.9491541 | Q17: 4.3768329 | R17: 5.0892711 | S17: 5.5137491
A18: MAC08 | B18: 2. Estabilidade Macroeconómica | C18: Receita fiscal | D18: Banco Mundial/WDI | E18: GC.TAX.TOTL.GD.ZS | F18: Fonte Banco Mundial API/CSV | G18: 10/11 | H18: 2024 | I18: Tax revenue (% of GDP) | J18: 9.7095139 | K18: 8.5757867 | L18: 8.0555378 | M18: 9.9288802 | N18: 11.288852 | O18: 20.517608 | P18: 10.70333 | Q18: 12.731812 | R18: 8.8691289 | S18: 7.7443637
A19: HUM01 | B19: 3. Capital Humano | C19: Índice de Desenvolvimento Humano | D19: PNUD/HDR / ficheiro base | F19: Série observada do ficheiro base | G19: 9/11 | H19: 2023 | J19: 0.591 | K19: 0.595 | L19: 0.597 | M19: 0.598 | N19: 0.597 | O19: 0.594 | P19: 0.59 | Q19: 0.591 | R19: 0.616
A20: HUM02 | B20: 3. Capital Humano | C20: Esperança de vida à nascença | D20: Banco Mundial/WDI | E20: SP.DYN.LE00.IN | F20: Fonte Banco Mundial API/CSV | G20: 10/11 | H20: 2024 | I20: Life expectancy at birth, total (years) | J20: 61.042 | K20: 61.619 | L20: 62.122 | M20: 62.622 | N20: 63.051 | O20: 63.116 | P20: 62.958 | Q20: 64.246 | R20: 64.617 | S20: 64.805
A21: HUM03 | B21: 3. Capital Humano | C21: Alfabetização adulta | D21: Banco Mundial/UNESCO | E21: SE.ADT.LITR.ZS | F21: Fonte Banco Mundial API/CSV | G21: 2/11 | H21: 2023 | I21: Literacy rate, adult total (% of people ages 15 and above) | J21: 66.239998 | R21: 68.18
A22: HUM04 | B22: 3. Capital Humano | C22: Conclusão do ensino primário | D22: Banco Mundial/UNESCO | E22: SE.PRM.CMPT.ZS | F22: Fonte Banco Mundial API/CSV | G22: 2/11 | H22: 2023 | I22: Primary completion rate, total (% of relevant age group) | P22: 60.025939 | R22: 47.855679
A23: HUM05 | B23: 3. Capital Humano | C23: Matrícula no ensino secundário | D23: Banco Mundial/UNESCO | E23: SE.SEC.ENRR | F23: Fonte Banco Mundial API/CSV | G23: 3/11 | H23: 2023 | I23: School enrollment, secondary (% gross) | K23: 54.416799 | P23: 53.135154 | R23: 51.483905
A24: HUM06 | B24: 3. Capital Humano | C24: Despesa pública em educação | D24: Banco Mundial/UNESCO | E24: SE.XPD.TOTL.GD.ZS | F24: Fonte Banco Mundial API/CSV | G24: 9/11 | H24: 2023 | I24: Government expenditure on education, total (% of GDP) | J24: 3.4868958 | K24: 2.7549366 | L24: 2.4668788 | M24: 2.183513 | N24: 2.0730644 | O24: 2.6674473 | P24: 2.2971969 | Q24: 2.385359 | R24: 2.5127366
A25: HUM07 | B25: 3. Capital Humano | C25: Mortalidade infantil | D25: Banco Mundial/WDI | E25: SP.DYN.IMRT.IN | F25: Fonte Banco Mundial API/CSV | G25: 10/11 | H25: 2024 | I25: Mortality rate, infant (per 1,000 live births) | J25: 38.8 | K25: 37.6 | L25: 36.7 | M25: 36 | N25: 35.5 | O25: 34.9 | P25: 34.4 | Q25: 33.7 | R25: 33 | S25: 32.1
A26: INC01 | B26: 4. Inclusão Social e Protecção | C26: Pobreza internacional | D26: Banco Mundial/PIP | E26: SI.POV.DDAY | F26: Fonte Banco Mundial API/CSV | G26: 1/11 | H26: 2018 | I26: Poverty headcount ratio at $3.00 a day (2021 PPP) (% of population) | M26: 39.3
A27: INC02 | B27: 4. Inclusão Social e Protecção | C27: Índice de Gini | D27: Banco Mundial/PIP | E27: SI.POV.GINI | F27: Fonte Banco Mundial API/CSV | G27: 1/11 | H27: 2018 | I27: Gini index | M27: 51.3
A28: INC03 | B28: 4. Inclusão Social e Protecção | C28: Rendimento dos 20% mais pobres | D28: Banco Mundial/PIP | E28: SI.DST.FRST.20 | F28: Fonte Banco Mundial API/CSV | G28: 1/11 | H28: 2018 | I28: Income share held by lowest 20% | M28: 3.8
A29: INC04 | B29: 4. Inclusão Social e Protecção | C29: Global Gender Gap Index | D29: WEF / ficheiro base | F29: Série observada do ficheiro base | G29: 10/11 | H29: 2025 | J29: 0.637 | K29: 0.643 | L29: 0.64 | M29: 0.633 | O29: 0.66 | P29: 0.657 | Q29: 0.638 | R29: 0.656 | S29: 0.668 | T29: 0.668
A30: INC05 | B30: 4. Inclusão Social e Protecção | C30: Participação feminina na força de trabalho | D30: Banco Mundial/OIT | E30: SL.TLF.CACT.FE.ZS | F30: Fonte Banco Mundial API/CSV | G30: 11/11 | H30: 2025 | I30: Labor force participation rate, female (% of female population ages 15+) (modeled ILO estimate) | J30: 73.933 | K30: 73.697 | L30: 73.461 | M30: 73.224 | N30: 72.985 | O30: 71.342 | P30: 74.695 | Q30: 74.018 | R30: 72.318 | S30: 72.359 | T30: 72.224
A31: INC06 | B31: 4. Inclusão Social e Protecção | C31: Mulheres no parlamento | D31: Banco Mundial/IPU | E31: SG.GEN.PARL.ZS | F31: Fonte Banco Mundial API/CSV | G31: 11/11 | H31: 2025 | I31: Proportion of seats held by women in national parliaments (%) | J31: 36.818182 | K31: 36.818182 | L31: 30.454545 | M31: 30.454545 | N31: 30 | O31: 30 | P31: 29.545455 | Q31: 33.636364 | R31: 33.636364 | S31: 39.545455 | T31: 39.090909
A32: INC07 | B32: 4. Inclusão Social e Protecção | C32: Jovens NEET | D32: Banco Mundial/OIT | E32: SL.UEM.NEET.ZS | F32: Fonte Banco Mundial API/CSV | G32: 6/11 | H32: 2024 | I32: Share of youth not in education, employment or training, total (% of youth population) | N32: 22.922 | O32: 27.286 | P32: 28.126 | Q32: 24.766 | R32: 21.383 | S32: 24.564
A33: INC08 | B33: 4. Inclusão Social e Protecção | C33: RNB per capita | D33: Banco Mundial/WDI | E33: NY.GNP.PCAP.CD | F33: Fonte Banco Mundial API/CSV | G33: 10/11 | H33: 2024 | I33: GNI per capita, Atlas method (current US$) | J33: 4450 | K33: 2910 | L33: 2400 | M33: 2270 | N33: 2440 | O33: 2020 | P33: 1990 | Q33: 2340 | R33: 2700 | S33: 2840
A34: INF01 | B34: 5. Infraestruturas e Serviços | C34: Acesso à eletricidade | D34: Banco Mundial/IEA | E34: EG.ELC.ACCS.ZS | F34: Fonte Banco Mundial API/CSV | G34: 9/11 | H34: 2023 | I34: Access to electricity (% of population) | J34: 42 | K34: 41.8 | L34: 42.9 | M34: 45.3 | N34: 45.6 | O34: 47 | P34: 48.2 | Q34: 48.5 | R34: 51.1
A35: INF02 | B35: 5. Infraestruturas e Serviços | C35: Perdas na rede elétrica | D35: Banco Mundial/IEA | E35: EG.ELC.LOSS.ZS | F35: Fonte Banco Mundial API/CSV | G35: 9/11 | H35: 2023 | I35: Electric power transmission and distribution losses (% of output) | J35: 11.27007 | K35: 11.26696 | L35: 11.258031 | M35: 11.264913 | N35: 11.262912 | O35: 11.266159 | P35: 11.262288 | Q35: 11.261682 | R35: 11.266798
A36: INF03 | B36: 5. Infraestruturas e Serviços | C36: Acesso a água potável básica | D36: Banco Mundial/JMP | E36: SH.H2O.BASW.ZS | F36: Fonte Banco Mundial API/CSV | G36: 10/11 | H36: 2024 | I36: People using at least basic drinking water services (% of population) | J36: 58.619631 | K36: 60.192062 | L36: 61.773512 | M36: 63.362791 | N36: 64.159911 | O36: 64.944031 | P36: 65.716258 | Q36: 66.476327 | R36: 67.224425 | S36: 67.960742
A37: INF04 | B37: 5. Infraestruturas e Serviços | C37: Acesso a saneamento básico | D37: Banco Mundial/JMP | E37: SH.STA.BASS.ZS | F37: Fonte Banco Mundial API/CSV | G37: 8/11 | H37: 2022 | I37: People using at least basic sanitation services (% of population) | J37: 46.683765 | K37: 47.555909 | L37: 48.423766 | M37: 49.286523 | N37: 49.547024 | O37: 49.801638 | P37: 50.051135 | Q37: 50.295136
A38: INF05 | B38: 5. Infraestruturas e Serviços | C38: Acesso a energia limpa para cozinhar | D38: Banco Mundial/OMS | E38: EG.CFT.ACCS.ZS | F38: Fonte Banco Mundial API/CSV | G38: 9/11 | H38: 2023 | I38: Access to clean fuels and technologies for cooking (% of population) | J38: 47 | K38: 48 | L38: 48.2 | M38: 48.8 | N38: 49.2 | O38: 49.4 | P38: 49.8 | Q38: 50 | R38: 50.2
A39: INF06 | B39: 5. Infraestruturas e Serviços | C39: Utilizadores de internet | D39: Banco Mundial/ITU | E39: IT.NET.USER.ZS | F39: Fonte Banco Mundial API/CSV | G39: 10/11 | H39: 2024 | I39: Individuals using the Internet (% of population) | J39: 22 | K39: 23.200001 | L39: 26 | M39: 29 | N39: 32.129398 | O39: 33.3209 | P39: 34.556499 | Q39: 35.838001 | R39: 37.885899 | S39: 40.7048
A40: INF07 | B40: 5. Infraestruturas e Serviços | C40: Subscrições móveis | D40: Banco Mundial/ITU | E40: IT.CEL.SETS.P2 | F40: Fonte Banco Mundial API/CSV | G40: 10/11 | H40: 2024 | I40: Mobile cellular subscriptions (per 100 people) | J40: 49.309722 | K40: 44.550227 | L40: 44.068209 | M40: 42.458878 | N40: 45.806531 | O40: 43.780432 | P40: 44.386869 | Q40: 66.600807 | R40: 70.051959 | S40: 69.703947
A41: INF08 | B41: 5. Infraestruturas e Serviços | C41: Banda larga fixa | D41: Banco Mundial/ITU | E41: IT.NET.BBND.P2 | F41: Fonte Banco Mundial API/CSV | G41: 10/11 | H41: 2024 | I41: Fixed broadband subscriptions (per 100 people) | J41: 0.54539421 | K41: 0.29031901 | L41: 0.32055405 | M41: 0.35006696 | N41: 0.36777043 | O41: 0.36326424 | P41: 0.3909253 | Q41: 0.38669816 | R41: 0.37366898 | S41: 0.36284524
A42: INF09 | B42: 5. Infraestruturas e Serviços | C42: Densidade rodoviária | D42: MINTRANS / ficheiro base | F42: Série observada do ficheiro base | G42: 10/11 | H42: 2024 | J42: 29 | K42: 29 | L42: 29 | M42: 29 | N42: 29 | O42: 30 | P42: 31 | Q42: 31 | R42: 32 | S42: 33
A43: LAB01 | B43: 6. Mercado de Trabalho | C43: Taxa de emprego | D43: Banco Mundial/OIT | E43: SL.EMP.TOTL.SP.ZS | F43: Fonte Banco Mundial API/CSV | G43: 11/11 | H43: 2025 | I43: Employment to population ratio, 15+, total (%) (modeled ILO estimate) | J43: 63.638 | K43: 63.321 | L43: 63.045 | M43: 62.812 | N43: 62.644 | O43: 61.078 | P43: 64.306 | Q43: 64.619 | R43: 64.369 | S43: 64.383 | T43: 64.236
A44: LAB02 | B44: 6. Mercado de Trabalho | C44: Taxa de desemprego | D44: Banco Mundial/OIT | E44: SL.UEM.TOTL.ZS | F44: Fonte Banco Mundial API/CSV | G44: 11/11 | H44: 2025 | I44: Unemployment, total (% of total labor force) (modeled ILO estimate) | J44: 16.472 | K44: 16.572 | L44: 16.617 | M44: 16.602 | N44: 16.497 | O44: 16.696 | P44: 15.799 | Q44: 14.124 | R44: 14.051 | S44: 14.02 | T44: 14.108
A45: LAB03 | B45: 6. Mercado de Trabalho | C45: Desemprego juvenil | D45: Banco Mundial/OIT | E45: SL.UEM.1524.ZS | F45: Fonte Banco Mundial API/CSV | G45: 11/11 | H45: 2025 | I45: Unemployment, youth total (% of total labor force ages 15-24) (modeled ILO estimate) | J45: 35.122 | K45: 34.483 | L45: 33.725 | M45: 32.855 | N45: 31.832 | O45: 33.076 | P45: 30.171 | Q45: 27.143 | R45: 26.834 | S45: 26.74 | T45: 27.229
A46: LAB04 | B46: 6. Mercado de Trabalho | C46: Participação na força de trabalho | D46: Banco Mundial/OIT | E46: SL.TLF.CACT.ZS | F46: Fonte Banco Mundial API/CSV | G46: 11/11 | H46: 2025 | I46: Labor force participation rate, total (% of total population ages 15+) (modeled ILO estimate) | J46: 76.187 | K46: 75.899 | L46: 75.609 | M46: 75.316 | N46: 75.021 | O46: 73.319 | P46: 76.372 | Q46: 75.247 | R46: 74.892 | S46: 74.881 | T46: 74.786
A47: LAB05 | B47: 6. Mercado de Trabalho | C47: Emprego vulnerável | D47: Banco Mundial/OIT | E47: SL.EMP.VULN.ZS | F47: Fonte Banco Mundial API/CSV | G47: 11/11 | H47: 2025 | I47: Vulnerable employment, total (% of total employment) (modeled ILO estimate) | J47: 65.262784 | K47: 65.224798 | L47: 65.221118 | M47: 65.260189 | N47: 65.269002 | O47: 65.941091 | P47: 65.793082 | Q47: 66.312488 | R47: 66.309574 | S47: 66.233541 | T47: 66.266595
A48: LAB06 | B48: 6. Mercado de Trabalho | C48: Trabalhadores assalariados | D48: Banco Mundial/OIT | E48: SL.EMP.WORK.ZS | F48: Fonte Banco Mundial API/CSV | G48: 11/11 | H48: 2025 | I48: Wage and salaried workers, total (% of total employment) (modeled ILO estimate) | J48: 25.408997 | K48: 25.385663 | L48: 25.326996 | M48: 25.222143 | N48: 25.152635 | O48: 24.578103 | P48: 24.690895 | Q48: 24.154879 | R48: 24.107087 | S48: 24.142151 | T48: 24.09504
A49: LAB07 | B49: 6. Mercado de Trabalho | C49: PIB por pessoa empregada | D49: Banco Mundial/OIT | E49: SL.GDP.PCAP.EM.KD | F49: Fonte Banco Mundial API/CSV | G49: 10/11 | H49: 2024 | I49: GDP per person employed (constant 2021 PPP $) | J49: 32713.473 | K49: 31187.472 | L49: 30171.658 | M49: 29053.335 | N49: 28059.953 | O49: 26682.793 | P49: 25015.856 | Q49: 25072.6 | R49: 24631.965 | S49: 24845.814
A50: LAB08 | B50: 6. Mercado de Trabalho | C50: Emprego informal | D50: INE / ficheiro base | F50: Série observada do ficheiro base | G50: 7/11 | H50: 2025 | N50: 74.541816 | O50: 80.353575 | P50: 80.447518 | Q50: 79.860137 | R50: 80.488095 | S50: 79.759923 | T50: 77.120842
A51: LAB09 | B51: 6. Mercado de Trabalho | C51: Taxa de formalização | D51: INSS / ficheiro base | F51: Série observada do ficheiro base | G51: 7/11 | H51: 2025 | N51: 25.458184 | O51: 19.646425 | P51: 19.552482 | Q51: 20.139863 | R51: 19.511905 | S51: 20.240077 | T51: 22.879158
A52: SAU01 | B52: 7. Segurança Alimentar e Saúde | C52: Prevalência de subalimentação | D52: Banco Mundial/FAO | E52: SN.ITK.DEFC.ZS | F52: Fonte Banco Mundial API/CSV | G52: 9/11 | H52: 2023 | I52: Prevalence of undernourishment (% of population) | J52: 14.2 | K52: 15.2 | L52: 15.4 | M52: 15.9 | N52: 18.2 | O52: 20.8 | P52: 22.6 | Q52: 23.1 | R52: 22.5
A53: SAU02 | B53: 7. Segurança Alimentar e Saúde | C53: Insegurança alimentar moderada ou severa | D53: Banco Mundial/FAO | E53: SN.ITK.MSFI.ZS | F53: Fonte Banco Mundial API/CSV | G53: 3/11 | H53: 2021 | I53: Prevalence of moderate or severe food insecurity in the population (%) | N53: 73.5 | O53: 77.7 | P53: 78.5
A54: SAU03 | B54: 7. Segurança Alimentar e Saúde | C54: Mortalidade materna | D54: Banco Mundial/OMS | E54: SH.STA.MMRT | F54: Fonte Banco Mundial API/CSV | G54: 9/11 | H54: 2023 | I54: Maternal mortality ratio (modeled estimate, per 100,000 live births) | J54: 249 | K54: 236 | L54: 220 | M54: 208 | N54: 202 | O54: 195 | P54: 211 | Q54: 185 | R54: 183
A55: SAU04 | B55: 7. Segurança Alimentar e Saúde | C55: Mortalidade de menores de 5 anos | D55: Banco Mundial/UNICEF | E55: SH.DYN.MORT | F55: Fonte Banco Mundial API/CSV | G55: 10/11 | H55: 2024 | I55: Mortality rate, under-5 (per 1,000 live births) | J55: 61.8 | K55: 59.6 | L55: 57.9 | M55: 56.5 | N55: 55.3 | O55: 54.2 | P55: 53.2 | Q55: 51.9 | R55: 50.5 | S55: 49
A56: SAU05 | B56: 7. Segurança Alimentar e Saúde | C56: Despesa corrente em saúde | D56: Banco Mundial/OMS | E56: SH.XPD.CHEX.GD.ZS | F56: Fonte Banco Mundial API/CSV | G56: 9/11 | H56: 2023 | I56: Current health expenditure (% of GDP) | J56: 2.2996688 | K56: 2.3906872 | L56: 2.4379425 | M56: 2.2988749 | N56: 2.2039428 | O56: 2.816889 | P56: 2.739871 | Q56: 2.6004105 | R56: 2.5469286
A57: SAU06 | B57: 7. Segurança Alimentar e Saúde | C57: Vacinação DPT | D57: Banco Mundial/OMS/UNICEF | E57: SH.IMM.IDPT | F57: Fonte Banco Mundial API/CSV | G57: 10/11 | H57: 2024 | I57: Immunization, DPT (% of children ages 12-23 months) | J57: 57 | K57: 59 | L57: 58 | M57: 67 | N57: 64 | O57: 59 | P57: 55 | Q57: 54 | R57: 66 | S57: 64
A58: SAU07 | B58: 7. Segurança Alimentar e Saúde | C58: Médicos | D58: Banco Mundial/OMS | E58: SH.MED.PHYS.ZS | F58: Fonte Banco Mundial API/CSV | G58: 3/11 | H58: 2022 | I58: Physicians (per 1,000 people) | L58: 0.212 | M58: 0.211 | Q58: 0.244
A59: SAU08 | B59: 7. Segurança Alimentar e Saúde | C59: Camas hospitalares | D59: Banco Mundial/OMS | E59: SH.MED.BEDS.ZS | F59: Fonte Banco Mundial API/CSV | G59: 1/11 | H59: 2019 | I59: Hospital beds (per 1,000 people) | N59: 0.75
A60: SAU09 | B60: 7. Segurança Alimentar e Saúde | C60: Índice de produção alimentar | D60: Banco Mundial/FAO | E60: AG.PRD.FOOD.XD | F60: Fonte Banco Mundial API/CSV | G60: 8/11 | H60: 2022 | I60: Food production index (2014-2016 = 100) | J60: 100.7 | K60: 104.88 | L60: 105.13 | M60: 107.35 | N60: 110.28 | O60: 114.88 | P60: 117.5 | Q60: 124.09

Sheet Dados_Ajustados_v4
A1: Dados ajustados usados no cálculo
A2: Valores observados + estimativas permitidas pela metodologia. As fórmulas estão ligadas a Metodologia_v4!B12:B14.
A4: ID | B4: Dimensão | C4: Indicador | D4: Fonte | E4: Código/API | F4: Estado dados | G4: Cobertura observada | H4: Último ano obs. | I4: Nota | J4: 2015 | K4: 2016 | L4: 2017 | M4: 2018 | N4: 2019 | O4: 2020 | P4: 2021 | Q4: 2022 | R4: 2023 | S4: 2024 | T4: 2025
A5: GOV01 | B5: 1. Governança e Estado de Direito | C5: Índice de Percepção da Corrupção | D5: Transparency International / ficheiro base | F5: Série observada do ficheiro base | G5: 10/11 | H5: 2024 | I5: Referenciado pelas regras de Metodologia_v4 | J5: =IF(Dados_Observados_v4!J5<>"",Dados_Observados_v4!J5,IF(AND(Dados_Observados_v4!K5<>"",(2016-2015)<=Metodologia_v4!$B$14),Dados_Observados_v4!K5,"")) | K5: =IF(Dados_Observados_v4!K5<>"",Dados_Observados_v4!K5,IF(AND(Dados_Observados_v4!J5<>"",Dados_Observados_v4!L5<>"",(2017-2015-1)<=Metodologia_v4!$B$12),Dados_Observados_v4!J5+(Dados_Observados_v4!L5-Dados_Observados_v4!J5)*(2016-2015)/(2017-2015),IF(AND(Dados_Observados_v4!J5<>"",(2016-2015)<=Metodologia_v4!$B$13),Dados_Observados_v4!J5,IF(AND(Dados_Observados_v4!L5<>"",(2017-2016)<=Metodologia_v4!$B$14),Dados_Observados_v4!L5,"")))) | L5: =IF(Dados_Observados_v4!L5<>"",Dados_Observados_v4!L5,IF(AND(Dados_Observados_v4!K5<>"",Dados_Observados_v4!M5<>"",(2018-2016-1)<=Metodologia_v4!$B$12),Dados_Observados_v4!K5+(Dados_Observados_v4!M5-Dados_Observados_v4!K5)*(2017-2016)/(2018-2016),IF(AND(Dados_Observados_v4!K5<>"",(2017-2016)<=Metodologia_v4!$B$13),Dados_Observados_v4!K5,IF(AND(Dados_Observados_v4!M5<>"",(2018-2017)<=Metodologia_v4!$B$14),Dados_Observados_v4!M5,"")))) | M5: =IF(Dados_Observados_v4!M5<>"",Dados_Observados_v4!M5,IF(AND(Dados_Observados_v4!L5<>"",Dados_Observados_v4!N5<>"",(2019-2017-1)<=Metodologia_v4!$B$12),Dados_Observados_v4!L5+(Dados_Observados_v4!N5-Dados_Observados_v4!L5)*(2018-2017)/(2019-2017),IF(AND(Dados_Observados_v4!L5<>"",(2018-2017)<=Metodologia_v4!$B$13),Dados_Observados_v4!L5,IF(AND(Dados_Observados_v4!N5<>"",(2019-2018)<=Metodologia_v4!$B$14),Dados_Observados_v4!N5,"")))) | N5: =IF(Dados_Observados_v4!N5<>"",Dados_Observados_v4!N5,IF(AND(Dados_Observados_v4!M5<>"",Dados_Observados_v4!O5<>"",(2020-2018-1)<=Metodologia_v4!$B$12),Dados_Observados_v4!M5+(Dados_Observados_v4!O5-Dados_Observados_v4!M5)*(2019-2018)/(2020-2018),IF(AND(Dados_Observados_v4!M5<>"",(2019-2018)<=Metodologia_v4!$B$13),Dados_Observados_v4!M5,IF(AND(Dados_Observados_v4!O5<>"",(2020-2019)<=Metodologia_v4!$B$14),Dados_Observados_v4!O5,"")))) | O5: =IF(Dados_Observados_v4!O5<>"",Dados_Observados_v4!O5,IF(AND(Dados_Observados_v4!N5<>"",Dados_Observados_v4!P5<>"",(2021-2019-1)<=Metodologia_v4!$B$12),Dados_Observados_v4!N5+(Dados_Observados_v4!P5-Dados_Observados_v4!N5)*(2020-2019)/(2021-2019),IF(AND(Dados_Observados_v4!N5<>"",(2020-2019)<=Metodologia_v4!$B$13),Dados_Observados_v4!N5,IF(AND(Dados_Observados_v4!P5<>"",(2021-2020)<=Metodologia_v4!$B$14),Dados_Observados_v4!P5,"")))) | P5: =IF(Dados_Observados_v4!P5<>"",Dados_Observados_v4!P5,IF(AND(Dados_Observados_v4!O5<>"",Dados_Observados_v4!Q5<>"",(2022-2020-1)<=Metodologia_v4!$B$12),Dados_Observados_v4!O5+(Dados_Observados_v4!Q5-Dados_Observados_v4!O5)*(2021-2020)/(2022-2020),IF(AND(Dados_Observados_v4!O5<>"",(2021-2020)<=Metodologia_v4!$B$13),Dados_Observados_v4!O5,IF(AND(Dados_Observados_v4!Q5<>"",(2022-2021)<=Metodologia_v4!$B$14),Dados_Observados_v4!Q5,"")))) | Q5: =IF(Dados_Observados_v4!Q5<>"",Dados_Observados_v4!Q5,IF(AND(Dados_Observados_v4!P5<>"",Dados_Observados_v4!R5<>"",(2023-2021-1)<=Metodologia_v4!$B$12),Dados_Observados_v4!P5+(Dados_Observados_v4!R5-Dados_Observados_v4!P5)*(2022-2021)/(2023-2021),IF(AND(Dados_Observados_v4!P5<>"",(2022-2021)<=Metodologia_v4!$B$13),Dados_Observados_v4!P5,IF(AND(Dados_Observados_v4!R5<>"",(2023-2022)<=Metodologia_v4!$B$14),Dados_Observados_v4!R5,"")))) | R5: =IF(Dados_Observados_v4!R5<>"",Dados_Observados_v4!R5,IF(AND(Dados_Observados_v4!Q5<>"",Dados_Observados_v4!S5<>"",(2024-2022-1)<=Metodologia_v4!$B$12),Dados_Observados_v4!Q5+(Dados_Observados_v4!S5-Dados_Observados_v4!Q5)*(2023-2022)/(2024-2022),IF(AND(Dados_Observados_v4!Q5<>"",(2023-2022)<=Metodologia_v4!$B$13),Dados_Observados_v4!Q5,IF(AND(Dados_Observados_v4!S5<>"",(2024-2023)<=Metodologia_v4!$B$14),Dados_Observados_v4!S5,"")))) | S5: =IF(Dados_Observados_v4!S5<>"",Dados_Observados_v4!S5,IF(AND(Dados_Observados_v4!R5<>"",(2024-2023)<=Metodologia_v4!$B$13),Dados_Observados_v4!R5,"")) | T5: =IF(Dados_Observados_v4!T5<>"",Dados_Observados_v4!T5,IF(AND(Dados_Observados_v4!S5<>"",(2025-2024)<=Metodologia_v4!$B$13),Dados_Observados_v4!S5,""))
A6: GOV02 | B6: 1. Governança e Estado de Direito | C6: WGI - Estado de Direito | D6: Worldwide Governance Indicators | E6: RL.EST | F6: Fonte oficial WGI 2025 | G6: 10/11 | H6: 2024 | I6: Referenciado pelas regras de Metodologia_v4 | J6: =IF(Dados_Observados_v4!J6<>"",Dados_Observados_v4!J6,IF(AND(Dados_Observados_v4!K6<>"",(2016-2015)<=Metodologia_v4!$B$14),Dados_Observados_v4!K6,"")) | K6: =IF(Dados_Observados_v4!K6<>"",Dados_Observados_v4!K6,IF(AND(Dados_Observados_v4!J6<>"",Dados_Observados_v4!L6<>"",(2017-2015-1)<=Metodologia_v4!$B$12),Dados_Observados_v4!J6+(Dados_Observados_v4!L6-Dados_Observados_v4!J6)*(2016-2015)/(2017-2015),IF(AND(Dados_Observados_v4!J6<>"",(2016-2015)<=Metodologia_v4!$B$13),Dados_Observados_v4!J6,IF(AND(Dados_Observados_v4!L6<>"",(2017-2016)<=Metodologia_v4!$B$14),Dados_Observados_v4!L6,"")))) | L6: =IF(Dados_Observados_v4!L6<>"",Dados_Observados_v4!L6,IF(AND(Dados_Observados_v4!K6<>"",Dados_Observados_v4!M6<>"",(2018-2016-1)<=Metodologia_v4!$B$12),Dados_Observados_v4!K6+(Dados_Observados_v4!M6-Dados_Observados_v4!K6)*(2017-2016)/(2018-2016),IF(AND(Dados_Observados_v4!K6<>"",(2017-2016)<=Metodologia_v4!$B$13),Dados_Observados_v4!K6,IF(AND(Dados_Observados_v4!M6<>"",(2018-2017)<=Metodologia_v4!$B$14),Dados_Observados_v4!M6,"")))) | M6: =IF(Dados_Observados_v4!M6<>"",Dados_Observados_v4!M6,IF(AND(Dados_Observados_v4!L6<>"",Dados_Observados_v4!N6<>"",(2019-2017-1)<=Metodologia_v4!$B$12),Dados_Observados_v4!L6+(Dados_Observados_v4!N6-Dados_Observados_v4!L6)*(2018-2017)/(2019-2017),IF(AND(Dados_Observados_v4!L6<>"",(2018-2017)<=Metodologia_v4!$B$13),Dados_Observados_v4!L6,IF(AND(Dados_Observados_v4!N6<>"",(2019-2018)<=Metodologia_v4!$B$14),Dados_Observados_v4!N6,"")))) | N6: =IF(Dados_Observados_v4!N6<>"",Dados_Observados_v4!N6,IF(AND(Dados_Observados_v4!M6<>"",Dados_Observados_v4!O6<>"",(2020-2018-1)<=Metodologia_v4!$B$12),Dados_Observados_v4!M6+(Dados_Observados_v4!O6-Dados_Observados_v4!M6)*(2019-2018)/(2020-2018),IF(AND(Dados_Observados_v4!M6<>"",(2019-2018)<=Metodologia_v4!$B$13),Dados_Observados_v4!M6,IF(AND(Dados_Observados_v4!O6<>"",(2020-2019)<=Metodologia_v4!$B$14),Dados_Observados_v4!O6,"")))) | O6: =IF(Dados_Observados_v4!O6<>"",Dados_Observados_v4!O6,IF(AND(Dados_Observados_v4!N6<>"",Dados_Observados_v4!P6<>"",(2021-2019-1)<=Metodologia_v4!$B$12),Dados_Observados_v4!N6+(Dados_Observados_v4!P6-Dados_Observados_v4!N6)*(2020-2019)/(2021-2019),IF(AND(Dados_Observados_v4!N6<>"",(2020-2019)<=Metodologia_v4!$B$13),Dados_Observados_v4!N6,IF(AND(Dados_Observados_v4!P6<>"",(2021-2020)<=Metodologia_v4!$B$14),Dados_Observados_v4!P6,"")))) | P6: =IF(Dados_Observados_v4!P6<>"",Dados_Observados_v4!P6,IF(AND(Dados_Observados_v4!O6<>"",Dados_Observados_v4!Q6<>"",(2022-2020-1)<=Metodologia_v4!$B$12),Dados_Observados_v4!O6+(Dados_Observados_v4!Q6-Dados_Observados_v4!O6)*(2021-2020)/(2022-2020),IF(AND(Dados_Observados_v4!O6<>"",(2021-2020)<=Metodologia_v4!$B$13),Dados_Observados_v4!O6,IF(AND(Dados_Observados_v4!Q6<>"",(2022-2021)<=Metodologia_v4!$B$14),Dados_Observados_v4!Q6,"")))) | Q6: =IF(Dados_Observados_v4!Q6<>"",Dados_Observados_v4!Q6,IF(AND(Dados_Observados_v4!P6<>"",Dados_Observados_v4!R6<>"",(2023-2021-1)<=Metodologia_v4!$B$12),Dados_Observados_v4!P6+(Dados_Observados_v4!R6-Dados_Observados_v4!P6)*(2022-2021)/(2023-2021),IF(AND(Dados_Observados_v4!P6<>"",(2022-2021)<=Metodologia_v4!$B$13),Dados_Observados_v4!P6,IF(AND(Dados_Observados_v4!R6<>"",(2023-2022)<=Metodologia_v4!$B$14),Dados_Observados_v4!R6,"")))) | R6: =IF(Dados_Observados_v4!R6<>"",Dados_Observados_v4!R6,IF(AND(Dados_Observados_v4!Q6<>"",Dados_Observados_v4!S6<>"",(2024-2022-1)<=Metodologia_v4!$B$12),Dados_Observados_v4!Q6+(Dados_Observados_v4!S6-Dados_Observados_v4!Q6)*(2023-2022)/(2024-2022),IF(AND(Dados_Observados_v4!Q6<>"",(2023-2022)<=Metodologia_v4!$B$13),Dados_Observados_v4!Q6,IF(AND(Dados_Observados_v4!S6<>"",(2024-2023)<=Metodologia_v4!$B$14),Dados_Observados_v4!S6,"")))) | S6: =IF(Dados_Observados_v4!S6<>"",Dados_Observados_v4!S6,IF(AND(Dados_Observados_v4!R6<>"",(2024-2023)<=Metodologia_v4!$B$13),Dados_Observados_v4!R6,"")) | T6: =IF(Dados_Observados_v4!T6<>"",Dados_Observados_v4!T6,IF(AND(Dados_Observados_v4!S6<>"",(2025-2024)<=Metodologia_v4!$B$13),Dados_Observados_v4!S6,""))
A7: GOV03 | B7: 1. Governança e Estado de Direito | C7: WGI - Eficiência do Governo | D7: Worldwide Governance Indicators | E7: GE.EST | F7: Fonte oficial WGI 2025 | G7: 10/11 | H7: 2024 | I7: Referenciado pelas regras de Metodologia_v4 | J7: =IF(Dados_Observados_v4!J7<>"",Dados_Observados_v4!J7,IF(AND(Dados_Observados_v4!K7<>"",(2016-2015)<=Metodologia_v4!$B$14),Dados_Observados_v4!K7,"")) | K7: =IF(Dados_Observados_v4!K7<>"",Dados_Observados_v4!K7,IF(AND(Dados_Observados_v4!J7<>"",Dados_Observados_v4!L7<>"",(2017-2015-1)<=Metodologia_v4!$B$12),Dados_Observados_v4!J7+(Dados_Observados_v4!L7-Dados_Observados_v4!J7)*(2016-2015)/(2017-2015),IF(AND(Dados_Observados_v4!J7<>"",(2016-2015)<=Metodologia_v4!$B$13),Dados_Observados_v4!J7,IF(AND(Dados_Observados_v4!L7<>"",(2017-2016)<=Metodologia_v4!$B$14),Dados_Observados_v4!L7,"")))) | L7: =IF(Dados_Observados_v4!L7<>"",Dados_Observados_v4!L7,IF(AND(Dados_Observados_v4!K7<>"",Dados_Observados_v4!M7<>"",(2018-2016-1)<=Metodologia_v4!$B$12),Dados_Observados_v4!K7+(Dados_Observados_v4!M7-Dados_Observados_v4!K7)*(2017-2016)/(2018-2016),IF(AND(Dados_Observados_v4!K7<>"",(2017-2016)<=Metodologia_v4!$B$13),Dados_Observados_v4!K7,IF(AND(Dados_Observados_v4!M7<>"",(2018-2017)<=Metodologia_v4!$B$14),Dados_Observados_v4!M7,"")))) | M7: =IF(Dados_Observados_v4!M7<>"",Dados_Observados_v4!M7,IF(AND(Dados_Observados_v4!L7<>"",Dados_Observados_v4!N7<>"",(2019-2017-1)<=Metodologia_v4!$B$12),Dados_Observados_v4!L7+(Dados_Observados_v4!N7-Dados_Observados_v4!L7)*(2018-2017)/(2019-2017),IF(AND(Dados_Observados_v4!L7<>"",(2018-2017)<=Metodologia_v4!$B$13),Dados_Observados_v4!L7,IF(AND(Dados_Observados_v4!N7<>"",(2019-2018)<=Metodologia_v4!$B$14),Dados_Observados_v4!N7,"")))) | N7: =IF(Dados_Observados_v4!N7<>"",Dados_Observados_v4!N7,IF(AND(Dados_Observados_v4!M7<>"",Dados_Observados_v4!O7<>"",(2020-2018-1)<=Metodologia_v4!$B$12),Dados_Observados_v4!M7+(Dados_Observados_v4!O7-Dados_Observados_v4!M7)*(2019-2018)/(2020-2018),IF(AND(Dados_Observados_v4!M7<>"",(2019-2018)<=Metodologia_v4!$B$13),Dados_Observados_v4!M7,IF(AND(Dados_Observados_v4!O7<>"",(2020-2019)<=Metodologia_v4!$B$14),Dados_Observados_v4!O7,"")))) | O7: =IF(Dados_Observados_v4!O7<>"",Dados_Observados_v4!O7,IF(AND(Dados_Observados_v4!N7<>"",Dados_Observados_v4!P7<>"",(2021-2019-1)<=Metodologia_v4!$B$12),Dados_Observados_v4!N7+(Dados_Observados_v4!P7-Dados_Observados_v4!N7)*(2020-2019)/(2021-2019),IF(AND(Dados_Observados_v4!N7<>"",(2020-2019)<=Metodologia_v4!$B$13),Dados_Observados_v4!N7,IF(AND(Dados_Observados_v4!P7<>"",(2021-2020)<=Metodologia_v4!$B$14),Dados_Observados_v4!P7,"")))) | P7: =IF(Dados_Observados_v4!P7<>"",Dados_Observados_v4!P7,IF(AND(Dados_Observados_v4!O7<>"",Dados_Observados_v4!Q7<>"",(2022-2020-1)<=Metodologia_v4!$B$12),Dados_Observados_v4!O7+(Dados_Observados_v4!Q7-Dados_Observados_v4!O7)*(2021-2020)/(2022-2020),IF(AND(Dados_Observados_v4!O7<>"",(2021-2020)<=Metodologia_v4!$B$13),Dados_Observados_v4!O7,IF(AND(Dados_Observados_v4!Q7<>"",(2022-2021)<=Metodologia_v4!$B$14),Dados_Observados_v4!Q7,"")))) | Q7: =IF(Dados_Observados_v4!Q7<>"",Dados_Observados_v4!Q7,IF(AND(Dados_Observados_v4!P7<>"",Dados_Observados_v4!R7<>"",(2023-2021-1)<=Metodologia_v4!$B$12),Dados_Observados_v4!P7+(Dados_Observados_v4!R7-Dados_Observados_v4!P7)*(2022-2021)/(2023-2021),IF(AND(Dados_Observados_v4!P7<>"",(2022-2021)<=Metodologia_v4!$B$13),Dados_Observados_v4!P7,IF(AND(Dados_Observados_v4!R7<>"",(2023-2022)<=Metodologia_v4!$B$14),Dados_Observados_v4!R7,"")))) | R7: =IF(Dados_Observados_v4!R7<>"",Dados_Observados_v4!R7,IF(AND(Dados_Observados_v4!Q7<>"",Dados_Observados_v4!S7<>"",(2024-2022-1)<=Metodologia_v4!$B$12),Dados_Observados_v4!Q7+(Dados_Observados_v4!S7-Dados_Observados_v4!Q7)*(2023-2022)/(2024-2022),IF(AND(Dados_Observados_v4!Q7<>"",(2023-2022)<=Metodologia_v4!$B$13),Dados_Observados_v4!Q7,IF(AND(Dados_Observados_v4!S7<>"",(2024-2023)<=Metodologia_v4!$B$14),Dados_Observados_v4!S7,"")))) | S7: =IF(Dados_Observados_v4!S7<>"",Dados_Observados_v4!S7,IF(AND(Dados_Observados_v4!R7<>"",(2024-2023)<=Metodologia_v4!$B$13),Dados_Observados_v4!R7,"")) | T7: =IF(Dados_Observados_v4!T7<>"",Dados_Observados_v4!T7,IF(AND(Dados_Observados_v4!S7<>"",(2025-2024)<=Metodologia_v4!$B$13),Dados_Observados_v4!S7,""))
A8: GOV04 | B8: 1. Governança e Estado de Direito | C8: WGI - Estabilidade Política | D8: Worldwide Governance Indicators | E8: PV.EST | F8: Fonte oficial WGI 2025 | G8: 10/11 | H8: 2024 | I8: Referenciado pelas regras de Metodologia_v4 | J8: =IF(Dados_Observados_v4!J8<>"",Dados_Observados_v4!J8,IF(AND(Dados_Observados_v4!K8<>"",(2016-2015)<=Metodologia_v4!$B$14),Dados_Observados_v4!K8,"")) | K8: =IF(Dados_Observados_v4!K8<>"",Dados_Observados_v4!K8,IF(AND(Dados_Observados_v4!J8<>"",Dados_Observados_v4!L8<>"",(2017-2015-1)<=Metodologia_v4!$B$12),Dados_Observados_v4!J8+(Dados_Observados_v4!L8-Dados_Observados_v4!J8)*(2016-2015)/(2017-2015),IF(AND(Dados_Observados_v4!J8<>"",(2016-2015)<=Metodologia_v4!$B$13),Dados_Observados_v4!J8,IF(AND(Dados_Observados_v4!L8<>"",(2017-2016)<=Metodologia_v4!$B$14),Dados_Observados_v4!L8,"")))) | L8: =IF(Dados_Observados_v4!L8<>"",Dados_Observados_v4!L8,IF(AND(Dados_Observados_v4!K8<>"",Dados_Observados_v4!M8<>"",(2018-2016-1)<=Metodologia_v4!$B$12),Dados_Observados_v4!K8+(Dados_Observados_v4!M8-Dados_Observados_v4!K8)*(2017-2016)/(2018-2016),IF(AND(Dados_Observados_v4!K8<>"",(2017-2016)<=Metodologia_v4!$B$13),Dados_Observados_v4!K8,IF(AND(Dados_Observados_v4!M8<>"",(2018-2017)<=Metodologia_v4!$B$14),Dados_Observados_v4!M8,"")))) | M8: =IF(Dados_Observados_v4!M8<>"",Dados_Observados_v4!M8,IF(AND(Dados_Observados_v4!L8<>"",Dados_Observados_v4!N8<>"",(2019-2017-1)<=Metodologia_v4!$B$12),Dados_Observados_v4!L8+(Dados_Observados_v4!N8-Dados_Observados_v4!L8)*(2018-2017)/(2019-2017),IF(AND(Dados_Observados_v4!L8<>"",(2018-2017)<=Metodologia_v4!$B$13),Dados_Observados_v4!L8,IF(AND(Dados_Observados_v4!N8<>"",(2019-2018)<=Metodologia_v4!$B$14),Dados_Observados_v4!N8,"")))) | N8: =IF(Dados_Observados_v4!N8<>"",Dados_Observados_v4!N8,IF(AND(Dados_Observados_v4!M8<>"",Dados_Observados_v4!O8<>"",(2020-2018-1)<=Metodologia_v4!$B$12),Dados_Observados_v4!M8+(Dados_Observados_v4!O8-Dados_Observados_v4!M8)*(2019-2018)/(2020-2018),IF(AND(Dados_Observados_v4!M8<>"",(2019-2018)<=Metodologia_v4!$B$13),Dados_Observados_v4!M8,IF(AND(Dados_Observados_v4!O8<>"",(2020-2019)<=Metodologia_v4!$B$14),Dados_Observados_v4!O8,"")))) | O8: =IF(Dados_Observados_v4!O8<>"",Dados_Observados_v4!O8,IF(AND(Dados_Observados_v4!N8<>"",Dados_Observados_v4!P8<>"",(2021-2019-1)<=Metodologia_v4!$B$12),Dados_Observados_v4!N8+(Dados_Observados_v4!P8-Dados_Observados_v4!N8)*(2020-2019)/(2021-2019),IF(AND(Dados_Observados_v4!N8<>"",(2020-2019)<=Metodologia_v4!$B$13),Dados_Observados_v4!N8,IF(AND(Dados_Observados_v4!P8<>"",(2021-2020)<=Metodologia_v4!$B$14),Dados_Observados_v4!P8,"")))) | P8: =IF(Dados_Observados_v4!P8<>"",Dados_Observados_v4!P8,IF(AND(Dados_Observados_v4!O8<>"",Dados_Observados_v4!Q8<>"",(2022-2020-1)<=Metodologia_v4!$B$12),Dados_Observados_v4!O8+(Dados_Observados_v4!Q8-Dados_Observados_v4!O8)*(2021-2020)/(2022-2020),IF(AND(Dados_Observados_v4!O8<>"",(2021-2020)<=Metodologia_v4!$B$13),Dados_Observados_v4!O8,IF(AND(Dados_Observados_v4!Q8<>"",(2022-2021)<=Metodologia_v4!$B$14),Dados_Observados_v4!Q8,"")))) | Q8: =IF(Dados_Observados_v4!Q8<>"",Dados_Observados_v4!Q8,IF(AND(Dados_Observados_v4!P8<>"",Dados_Observados_v4!R8<>"",(2023-2021-1)<=Metodologia_v4!$B$12),Dados_Observados_v4!P8+(Dados_Observados_v4!R8-Dados_Observados_v4!P8)*(2022-2021)/(2023-2021),IF(AND(Dados_Observados_v4!P8<>"",(2022-2021)<=Metodologia_v4!$B$13),Dados_Observados_v4!P8,IF(AND(Dados_Observados_v4!R8<>"",(2023-2022)<=Metodologia_v4!$B$14),Dados_Observados_v4!R8,"")))) | R8: =IF(Dados_Observados_v4!R8<>"",Dados_Observados_v4!R8,IF(AND(Dados_Observados_v4!Q8<>"",Dados_Observados_v4!S8<>"",(2024-2022-1)<=Metodologia_v4!$B$12),Dados_Observados_v4!Q8+(Dados_Observados_v4!S8-Dados_Observados_v4!Q8)*(2023-2022)/(2024-2022),IF(AND(Dados_Observados_v4!Q8<>"",(2023-2022)<=Metodologia_v4!$B$13),Dados_Observados_v4!Q8,IF(AND(Dados_Observados_v4!S8<>"",(2024-2023)<=Metodologia_v4!$B$14),Dados_Observados_v4!S8,"")))) | S8: =IF(Dados_Observados_v4!S8<>"",Dados_Observados_v4!S8,IF(AND(Dados_Observados_v4!R8<>"",(2024-2023)<=Metodologia_v4!$B$13),Dados_Observados_v4!R8,"")) | T8: =IF(Dados_Observados_v4!T8<>"",Dados_Observados_v4!T8,IF(AND(Dados_Observados_v4!S8<>"",(2025-2024)<=Metodologia_v4!$B$13),Dados_Observados_v4!S8,""))
A9: GOV05 | B9: 1. Governança e Estado de Direito | C9: WGI - Qualidade Regulatória | D9: Worldwide Governance Indicators | E9: RQ.EST | F9: Fonte oficial WGI 2025 | G9: 10/11 | H9: 2024 | I9: Referenciado pelas regras de Metodologia_v4 | J9: =IF(Dados_Observados_v4!J9<>"",Dados_Observados_v4!J9,IF(AND(Dados_Observados_v4!K9<>"",(2016-2015)<=Metodologia_v4!$B$14),Dados_Observados_v4!K9,"")) | K9: =IF(Dados_Observados_v4!K9<>"",Dados_Observados_v4!K9,IF(AND(Dados_Observados_v4!J9<>"",Dados_Observados_v4!L9<>"",(2017-2015-1)<=Metodologia_v4!$B$12),Dados_Observados_v4!J9+(Dados_Observados_v4!L9-Dados_Observados_v4!J9)*(2016-2015)/(2017-2015),IF(AND(Dados_Observados_v4!J9<>"",(2016-2015)<=Metodologia_v4!$B$13),Dados_Observados_v4!J9,IF(AND(Dados_Observados_v4!L9<>"",(2017-2016)<=Metodologia_v4!$B$14),Dados_Observados_v4!L9,"")))) | L9: =IF(Dados_Observados_v4!L9<>"",Dados_Observados_v4!L9,IF(AND(Dados_Observados_v4!K9<>"",Dados_Observados_v4!M9<>"",(2018-2016-1)<=Metodologia_v4!$B$12),Dados_Observados_v4!K9+(Dados_Observados_v4!M9-Dados_Observados_v4!K9)*(2017-2016)/(2018-2016),IF(AND(Dados_Observados_v4!K9<>"",(2017-2016)<=Metodologia_v4!$B$13),Dados_Observados_v4!K9,IF(AND(Dados_Observados_v4!M9<>"",(2018-2017)<=Metodologia_v4!$B$14),Dados_Observados_v4!M9,"")))) | M9: =IF(Dados_Observados_v4!M9<>"",Dados_Observados_v4!M9,IF(AND(Dados_Observados_v4!L9<>"",Dados_Observados_v4!N9<>"",(2019-2017-1)<=Metodologia_v4!$B$12),Dados_Observados_v4!L9+(Dados_Observados_v4!N9-Dados_Observados_v4!L9)*(2018-2017)/(2019-2017),IF(AND(Dados_Observados_v4!L9<>"",(2018-2017)<=Metodologia_v4!$B$13),Dados_Observados_v4!L9,IF(AND(Dados_Observados_v4!N9<>"",(2019-2018)<=Metodologia_v4!$B$14),Dados_Observados_v4!N9,"")))) | N9: =IF(Dados_Observados_v4!N9<>"",Dados_Observados_v4!N9,IF(AND(Dados_Observados_v4!M9<>"",Dados_Observados_v4!O9<>"",(2020-2018-1)<=Metodologia_v4!$B$12),Dados_Observados_v4!M9+(Dados_Observados_v4!O9-Dados_Observados_v4!M9)*(2019-2018)/(2020-2018),IF(AND(Dados_Observados_v4!M9<>"",(2019-2018)<=Metodologia_v4!$B$13),Dados_Observados_v4!M9,IF(AND(Dados_Observados_v4!O9<>"",(2020-2019)<=Metodologia_v4!$B$14),Dados_Observados_v4!O9,"")))) | O9: =IF(Dados_Observados_v4!O9<>"",Dados_Observados_v4!O9,IF(AND(Dados_Observados_v4!N9<>"",Dados_Observados_v4!P9<>"",(2021-2019-1)<=Metodologia_v4!$B$12),Dados_Observados_v4!N9+(Dados_Observados_v4!P9-Dados_Observados_v4!N9)*(2020-2019)/(2021-2019),IF(AND(Dados_Observados_v4!N9<>"",(2020-2019)<=Metodologia_v4!$B$13),Dados_Observados_v4!N9,IF(AND(Dados_Observados_v4!P9<>"",(2021-2020)<=Metodologia_v4!$B$14),Dados_Observados_v4!P9,"")))) | P9: =IF(Dados_Observados_v4!P9<>"",Dados_Observados_v4!P9,IF(AND(Dados_Observados_v4!O9<>"",Dados_Observados_v4!Q9<>"",(2022-2020-1)<=Metodologia_v4!$B$12),Dados_Observados_v4!O9+(Dados_Observados_v4!Q9-Dados_Observados_v4!O9)*(2021-2020)/(2022-2020),IF(AND(Dados_Observados_v4!O9<>"",(2021-2020)<=Metodologia_v4!$B$13),Dados_Observados_v4!O9,IF(AND(Dados_Observados_v4!Q9<>"",(2022-2021)<=Metodologia_v4!$B$14),Dados_Observados_v4!Q9,"")))) | Q9: =IF(Dados_Observados_v4!Q9<>"",Dados_Observados_v4!Q9,IF(AND(Dados_Observados_v4!P9<>"",Dados_Observados_v4!R9<>"",(2023-2021-1)<=Metodologia_v4!$B$12),Dados_Observados_v4!P9+(Dados_Observados_v4!R9-Dados_Observados_v4!P9)*(2022-2021)/(2023-2021),IF(AND(Dados_Observados_v4!P9<>"",(2022-2021)<=Metodologia_v4!$B$13),Dados_Observados_v4!P9,IF(AND(Dados_Observados_v4!R9<>"",(2023-2022)<=Metodologia_v4!$B$14),Dados_Observados_v4!R9,"")))) | R9: =IF(Dados_Observados_v4!R9<>"",Dados_Observados_v4!R9,IF(AND(Dados_Observados_v4!Q9<>"",Dados_Observados_v4!S9<>"",(2024-2022-1)<=Metodologia_v4!$B$12),Dados_Observados_v4!Q9+(Dados_Observados_v4!S9-Dados_Observados_v4!Q9)*(2023-2022)/(2024-2022),IF(AND(Dados_Observados_v4!Q9<>"",(2023-2022)<=Metodologia_v4!$B$13),Dados_Observados_v4!Q9,IF(AND(Dados_Observados_v4!S9<>"",(2024-2023)<=Metodologia_v4!$B$14),Dados_Observados_v4!S9,"")))) | S9: =IF(Dados_Observados_v4!S9<>"",Dados_Observados_v4!S9,IF(AND(Dados_Observados_v4!R9<>"",(2024-2023)<=Metodologia_v4!$B$13),Dados_Observados_v4!R9,"")) | T9: =IF(Dados_Observados_v4!T9<>"",Dados_Observados_v4!T9,IF(AND(Dados_Observados_v4!S9<>"",(2025-2024)<=Metodologia_v4!$B$13),Dados_Observados_v4!S9,""))
A10: GOV06 | B10: 1. Governança e Estado de Direito | C10: WGI - Controlo da Corrupção | D10: Worldwide Governance Indicators | E10: CC.EST | F10: Fonte oficial WGI 2025 | G10: 10/11 | H10: 2024 | I10: Referenciado pelas regras de Metodologia_v4 | J10: =IF(Dados_Observados_v4!J10<>"",Dados_Observados_v4!J10,IF(AND(Dados_Observados_v4!K10<>"",(2016-2015)<=Metodologia_v4!$B$14),Dados_Observados_v4!K10,"")) | K10: =IF(Dados_Observados_v4!K10<>"",Dados_Observados_v4!K10,IF(AND(Dados_Observados_v4!J10<>"",Dados_Observados_v4!L10<>"",(2017-2015-1)<=Metodologia_v4!$B$12),Dados_Observados_v4!J10+(Dados_Observados_v4!L10-Dados_Observados_v4!J10)*(2016-2015)/(2017-2015),IF(AND(Dados_Observados_v4!J10<>"",(2016-2015)<=Metodologia_v4!$B$13),Dados_Observados_v4!J10,IF(AND(Dados_Observados_v4!L10<>"",(2017-2016)<=Metodologia_v4!$B$14),Dados_Observados_v4!L10,"")))) | L10: =IF(Dados_Observados_v4!L10<>"",Dados_Observados_v4!L10,IF(AND(Dados_Observados_v4!K10<>"",Dados_Observados_v4!M10<>"",(2018-2016-1)<=Metodologia_v4!$B$12),Dados_Observados_v4!K10+(Dados_Observados_v4!M10-Dados_Observados_v4!K10)*(2017-2016)/(2018-2016),IF(AND(Dados_Observados_v4!K10<>"",(2017-2016)<=Metodologia_v4!$B$13),Dados_Observados_v4!K10,IF(AND(Dados_Observados_v4!M10<>"",(2018-2017)<=Metodologia_v4!$B$14),Dados_Observados_v4!M10,"")))) | M10: =IF(Dados_Observados_v4!M10<>"",Dados_Observados_v4!M10,IF(AND(Dados_Observados_v4!L10<>"",Dados_Observados_v4!N10<>"",(2019-2017-1)<=Metodologia_v4!$B$12),Dados_Observados_v4!L10+(Dados_Observados_v4!N10-Dados_Observados_v4!L10)*(2018-2017)/(2019-2017),IF(AND(Dados_Observados_v4!L10<>"",(2018-2017)<=Metodologia_v4!$B$13),Dados_Observados_v4!L10,IF(AND(Dados_Observados_v4!N10<>"",(2019-2018)<=Metodologia_v4!$B$14),Dados_Observados_v4!N10,"")))) | N10: =IF(Dados_Observados_v4!N10<>"",Dados_Observados_v4!N10,IF(AND(Dados_Observados_v4!M10<>"",Dados_Observados_v4!O10<>"",(2020-2018-1)<=Metodologia_v4!$B$12),Dados_Observados_v4!M10+(Dados_Observados_v4!O10-Dados_Observados_v4!M10)*(2019-2018)/(2020-2018),IF(AND(Dados_Observados_v4!M10<>"",(2019-2018)<=Metodologia_v4!$B$13),Dados_Observados_v4!M10,IF(AND(Dados_Observados_v4!O10<>"",(2020-2019)<=Metodologia_v4!$B$14),Dados_Observados_v4!O10,"")))) | O10: =IF(Dados_Observados_v4!O10<>"",Dados_Observados_v4!O10,IF(AND(Dados_Observados_v4!N10<>"",Dados_Observados_v4!P10<>"",(2021-2019-1)<=Metodologia_v4!$B$12),Dados_Observados_v4!N10+(Dados_Observados_v4!P10-Dados_Observados_v4!N10)*(2020-2019)/(2021-2019),IF(AND(Dados_Observados_v4!N10<>"",(2020-2019)<=Metodologia_v4!$B$13),Dados_Observados_v4!N10,IF(AND(Dados_Observados_v4!P10<>"",(2021-2020)<=Metodologia_v4!$B$14),Dados_Observados_v4!P10,"")))) | P10: =IF(Dados_Observados_v4!P10<>"",Dados_Observados_v4!P10,IF(AND(Dados_Observados_v4!O10<>"",Dados_Observados_v4!Q10<>"",(2022-2020-1)<=Metodologia_v4!$B$12),Dados_Observados_v4!O10+(Dados_Observados_v4!Q10-Dados_Observados_v4!O10)*(2021-2020)/(2022-2020),IF(AND(Dados_Observados_v4!O10<>"",(2021-2020)<=Metodologia_v4!$B$13),Dados_Observados_v4!O10,IF(AND(Dados_Observados_v4!Q10<>"",(2022-2021)<=Metodologia_v4!$B$14),Dados_Observados_v4!Q10,"")))) | Q10: =IF(Dados_Observados_v4!Q10<>"",Dados_Observados_v4!Q10,IF(AND(Dados_Observados_v4!P10<>"",Dados_Observados_v4!R10<>"",(2023-2021-1)<=Metodologia_v4!$B$12),Dados_Observados_v4!P10+(Dados_Observados_v4!R10-Dados_Observados_v4!P10)*(2022-2021)/(2023-2021),IF(AND(Dados_Observados_v4!P10<>"",(2022-2021)<=Metodologia_v4!$B$13),Dados_Observados_v4!P10,IF(AND(Dados_Observados_v4!R10<>"",(2023-2022)<=Metodologia_v4!$B$14),Dados_Observados_v4!R10,"")))) | R10: =IF(Dados_Observados_v4!R10<>"",Dados_Observados_v4!R10,IF(AND(Dados_Observados_v4!Q10<>"",Dados_Observados_v4!S10<>"",(2024-2022-1)<=Metodologia_v4!$B$12),Dados_Observados_v4!Q10+(Dados_Observados_v4!S10-Dados_Observados_v4!Q10)*(2023-2022)/(2024-2022),IF(AND(Dados_Observados_v4!Q10<>"",(2023-2022)<=Metodologia_v4!$B$13),Dados_Observados_v4!Q10,IF(AND(Dados_Observados_v4!S10<>"",(2024-2023)<=Metodologia_v4!$B$14),Dados_Observados_v4!S10,"")))) | S10: =IF(Dados_Observados_v4!S10<>"",Dados_Observados_v4!S10,IF(AND(Dados_Observados_v4!R10<>"",(2024-2023)<=Metodologia_v4!$B$13),Dados_Observados_v4!R10,"")) | T10: =IF(Dados_Observados_v4!T10<>"",Dados_Observados_v4!T10,IF(AND(Dados_Observados_v4!S10<>"",(2025-2024)<=Metodologia_v4!$B$13),Dados_Observados_v4!S10,""))
A11: MAC01 | B11: 2. Estabilidade Macroeconómica | C11: Crescimento real do PIB | D11: Banco Mundial/WDI | E11: NY.GDP.MKTP.KD.ZG | F11: Fonte Banco Mundial API/CSV | G11: 10/11 | H11: 2024 | I11: Referenciado pelas regras de Metodologia_v4 | J11: =IF(Dados_Observados_v4!J11<>"",Dados_Observados_v4!J11,IF(AND(Dados_Observados_v4!K11<>"",(2016-2015)<=Metodologia_v4!$B$14),Dados_Observados_v4!K11,"")) | K11: =IF(Dados_Observados_v4!K11<>"",Dados_Observados_v4!K11,IF(AND(Dados_Observados_v4!J11<>"",Dados_Observados_v4!L11<>"",(2017-2015-1)<=Metodologia_v4!$B$12),Dados_Observados_v4!J11+(Dados_Observados_v4!L11-Dados_Observados_v4!J11)*(2016-2015)/(2017-2015),IF(AND(Dados_Observados_v4!J11<>"",(2016-2015)<=Metodologia_v4!$B$13),Dados_Observados_v4!J11,IF(AND(Dados_Observados_v4!L11<>"",(2017-2016)<=Metodologia_v4!$B$14),Dados_Observados_v4!L11,"")))) | L11: =IF(Dados_Observados_v4!L11<>"",Dados_Observados_v4!L11,IF(AND(Dados_Observados_v4!K11<>"",Dados_Observados_v4!M11<>"",(2018-2016-1)<=Metodologia_v4!$B$12),Dados_Observados_v4!K11+(Dados_Observados_v4!M11-Dados_Observados_v4!K11)*(2017-2016)/(2018-2016),IF(AND(Dados_Observados_v4!K11<>"",(2017-2016)<=Metodologia_v4!$B$13),Dados_Observados_v4!K11,IF(AND(Dados_Observados_v4!M11<>"",(2018-2017)<=Metodologia_v4!$B$14),Dados_Observados_v4!M11,"")))) | M11: =IF(Dados_Observados_v4!M11<>"",Dados_Observados_v4!M11,IF(AND(Dados_Observados_v4!L11<>"",Dados_Observados_v4!N11<>"",(2019-2017-1)<=Metodologia_v4!$B$12),Dados_Observados_v4!L11+(Dados_Observados_v4!N11-Dados_Observados_v4!L11)*(2018-2017)/(2019-2017),IF(AND(Dados_Observados_v4!L11<>"",(2018-2017)<=Metodologia_v4!$B$13),Dados_Observados_v4!L11,IF(AND(Dados_Observados_v4!N11<>"",(2019-2018)<=Metodologia_v4!$B$14),Dados_Observados_v4!N11,"")))) | N11: =IF(Dados_Observados_v4!N11<>"",Dados_Observados_v4!N11,IF(AND(Dados_Observados_v4!M11<>"",Dados_Observados_v4!O11<>"",(2020-2018-1)<=Metodologia_v4!$B$12),Dados_Observados_v4!M11+(Dados_Observados_v4!O11-Dados_Observados_v4!M11)*(2019-2018)/(2020-2018),IF(AND(Dados_Observados_v4!M11<>"",(2019-2018)<=Metodologia_v4!$B$13),Dados_Observados_v4!M11,IF(AND(Dados_Observados_v4!O11<>"",(2020-2019)<=Metodologia_v4!$B$14),Dados_Observados_v4!O11,"")))) | O11: =IF(Dados_Observados_v4!O11<>"",Dados_Observados_v4!O11,IF(AND(Dados_Observados_v4!N11<>"",Dados_Observados_v4!P11<>"",(2021-2019-1)<=Metodologia_v4!$B$12),Dados_Observados_v4!N11+(Dados_Observados_v4!P11-Dados_Observados_v4!N11)*(2020-2019)/(2021-2019),IF(AND(Dados_Observados_v4!N11<>"",(2020-2019)<=Metodologia_v4!$B$13),Dados_Observados_v4!N11,IF(AND(Dados_Observados_v4!P11<>"",(2021-2020)<=Metodologia_v4!$B$14),Dados_Observados_v4!P11,"")))) | P11: =IF(Dados_Observados_v4!P11<>"",Dados_Observados_v4!P11,IF(AND(Dados_Observados_v4!O11<>"",Dados_Observados_v4!Q11<>"",(2022-2020-1)<=Metodologia_v4!$B$12),Dados_Observados_v4!O11+(Dados_Observados_v4!Q11-Dados_Observados_v4!O11)*(2021-2020)/(2022-2020),IF(AND(Dados_Observados_v4!O11<>"",(2021-2020)<=Metodologia_v4!$B$13),Dados_Observados_v4!O11,IF(AND(Dados_Observados_v4!Q11<>"",(2022-2021)<=Metodologia_v4!$B$14),Dados_Observados_v4!Q11,"")))) | Q11: =IF(Dados_Observados_v4!Q11<>"",Dados_Observados_v4!Q11,IF(AND(Dados_Observados_v4!P11<>"",Dados_Observados_v4!R11<>"",(2023-2021-1)<=Metodologia_v4!$B$12),Dados_Observados_v4!P11+(Dados_Observados_v4!R11-Dados_Observados_v4!P11)*(2022-2021)/(2023-2021),IF(AND(Dados_Observados_v4!P11<>"",(2022-2021)<=Metodologia_v4!$B$13),Dados_Observados_v4!P11,IF(AND(Dados_Observados_v4!R11<>"",(2023-2022)<=Metodologia_v4!$B$14),Dados_Observados_v4!R11,"")))) | R11: =IF(Dados_Observados_v4!R11<>"",Dados_Observados_v4!R11,IF(AND(Dados_Observados_v4!Q11<>"",Dados_Observados_v4!S11<>"",(2024-2022-1)<=Metodologia_v4!$B$12),Dados_Observados_v4!Q11+(Dados_Observados_v4!S11-Dados_Observados_v4!Q11)*(2023-2022)/(2024-2022),IF(AND(Dados_Observados_v4!Q11<>"",(2023-2022)<=Metodologia_v4!$B$13),Dados_Observados_v4!Q11,IF(AND(Dados_Observados_v4!S11<>"",(2024-2023)<=Metodologia_v4!$B$14),Dados_Observados_v4!S11,"")))) | S11: =IF(Dados_Observados_v4!S11<>"",Dados_Observados_v4!S11,IF(AND(Dados_Observados_v4!R11<>"",(2024-2023)<=Metodologia_v4!$B$13),Dados_Observados_v4!R11,"")) | T11: =IF(Dados_Observados_v4!T11<>"",Dados_Observados_v4!T11,IF(AND(Dados_Observados_v4!S11<>"",(2025-2024)<=Metodologia_v4!$B$13),Dados_Observados_v4!S11,""))
A12: MAC02 | B12: 2. Estabilidade Macroeconómica | C12: PIB per capita | D12: Banco Mundial/WDI | E12: NY.GDP.PCAP.CD | F12: Fonte Banco Mundial API/CSV | G12: 10/11 | H12: 2024 | I12: Referenciado pelas regras de Metodologia_v4 | J12: =IF(Dados_Observados_v4!J12<>"",Dados_Observados_v4!J12,IF(AND(Dados_Observados_v4!K12<>"",(2016-2015)<=Metodologia_v4!$B$14),Dados_Observados_v4!K12,"")) | K12: =IF(Dados_Observados_v4!K12<>"",Dados_Observados_v4!K12,IF(AND(Dados_Observados_v4!J12<>"",Dados_Observados_v4!L12<>"",(2017-2015-1)<=Metodologia_v4!$B$12),Dados_Observados_v4!J12+(Dados_Observados_v4!L12-Dados_Observados_v4!J12)*(2016-2015)/(2017-2015),IF(AND(Dados_Observados_v4!J12<>"",(2016-2015)<=Metodologia_v4!$B$13),Dados_Observados_v4!J12,IF(AND(Dados_Observados_v4!L12<>"",(2017-2016)<=Metodologia_v4!$B$14),Dados_Observados_v4!L12,"")))) | L12: =IF(Dados_Observados_v4!L12<>"",Dados_Observados_v4!L12,IF(AND(Dados_Observados_v4!K12<>"",Dados_Observados_v4!M12<>"",(2018-2016-1)<=Metodologia_v4!$B$12),Dados_Observados_v4!K12+(Dados_Observados_v4!M12-Dados_Observados_v4!K12)*(2017-2016)/(2018-2016),IF(AND(Dados_Observados_v4!K12<>"",(2017-2016)<=Metodologia_v4!$B$13),Dados_Observados_v4!K12,IF(AND(Dados_Observados_v4!M12<>"",(2018-2017)<=Metodologia_v4!$B$14),Dados_Observados_v4!M12,"")))) | M12: =IF(Dados_Observados_v4!M12<>"",Dados_Observados_v4!M12,IF(AND(Dados_Observados_v4!L12<>"",Dados_Observados_v4!N12<>"",(2019-2017-1)<=Metodologia_v4!$B$12),Dados_Observados_v4!L12+(Dados_Observados_v4!N12-Dados_Observados_v4!L12)*(2018-2017)/(2019-2017),IF(AND(Dados_Observados_v4!L12<>"",(2018-2017)<=Metodologia_v4!$B$13),Dados_Observados_v4!L12,IF(AND(Dados_Observados_v4!N12<>"",(2019-2018)<=Metodologia_v4!$B$14),Dados_Observados_v4!N12,"")))) | N12: =IF(Dados_Observados_v4!N12<>"",Dados_Observados_v4!N12,IF(AND(Dados_Observados_v4!M12<>"",Dados_Observados_v4!O12<>"",(2020-2018-1)<=Metodologia_v4!$B$12),Dados_Observados_v4!M12+(Dados_Observados_v4!O12-Dados_Observados_v4!M12)*(2019-2018)/(2020-2018),IF(AND(Dados_Observados_v4!M12<>"",(2019-2018)<=Metodologia_v4!$B$13),Dados_Observados_v4!M12,IF(AND(Dados_Observados_v4!O12<>"",(2020-2019)<=Metodologia_v4!$B$14),Dados_Observados_v4!O12,"")))) | O12: =IF(Dados_Observados_v4!O12<>"",Dados_Observados_v4!O12,IF(AND(Dados_Observados_v4!N12<>"",Dados_Observados_v4!P12<>"",(2021-2019-1)<=Metodologia_v4!$B$12),Dados_Observados_v4!N12+(Dados_Observados_v4!P12-Dados_Observados_v4!N12)*(2020-2019)/(2021-2019),IF(AND(Dados_Observados_v4!N12<>"",(2020-2019)<=Metodologia_v4!$B$13),Dados_Observados_v4!N12,IF(AND(Dados_Observados_v4!P12<>"",(2021-2020)<=Metodologia_v4!$B$14),Dados_Observados_v4!P12,"")))) | P12: =IF(Dados_Observados_v4!P12<>"",Dados_Observados_v4!P12,IF(AND(Dados_Observados_v4!O12<>"",Dados_Observados_v4!Q12<>"",(2022-2020-1)<=Metodologia_v4!$B$12),Dados_Observados_v4!O12+(Dados_Observados_v4!Q12-Dados_Observados_v4!O12)*(2021-2020)/(2022-2020),IF(AND(Dados_Observados_v4!O12<>"",(2021-2020)<=Metodologia_v4!$B$13),Dados_Observados_v4!O12,IF(AND(Dados_Observados_v4!Q12<>"",(2022-2021)<=Metodologia_v4!$B$14),Dados_Observados_v4!Q12,"")))) | Q12: =IF(Dados_Observados_v4!Q12<>"",Dados_Observados_v4!Q12,IF(AND(Dados_Observados_v4!P12<>"",Dados_Observados_v4!R12<>"",(2023-2021-1)<=Metodologia_v4!$B$12),Dados_Observados_v4!P12+(Dados_Observados_v4!R12-Dados_Observados_v4!P12)*(2022-2021)/(2023-2021),IF(AND(Dados_Observados_v4!P12<>"",(2022-2021)<=Metodologia_v4!$B$13),Dados_Observados_v4!P12,IF(AND(Dados_Observados_v4!R12<>"",(2023-2022)<=Metodologia_v4!$B$14),Dados_Observados_v4!R12,"")))) | R12: =IF(Dados_Observados_v4!R12<>"",Dados_Observados_v4!R12,IF(AND(Dados_Observados_v4!Q12<>"",Dados_Observados_v4!S12<>"",(2024-2022-1)<=Metodologia_v4!$B$12),Dados_Observados_v4!Q12+(Dados_Observados_v4!S12-Dados_Observados_v4!Q12)*(2023-2022)/(2024-2022),IF(AND(Dados_Observados_v4!Q12<>"",(2023-2022)<=Metodologia_v4!$B$13),Dados_Observados_v4!Q12,IF(AND(Dados_Observados_v4!S12<>"",(2024-2023)<=Metodologia_v4!$B$14),Dados_Observados_v4!S12,"")))) | S12: =IF(Dados_Observados_v4!S12<>"",Dados_Observados_v4!S12,IF(AND(Dados_Observados_v4!R12<>"",(2024-2023)<=Metodologia_v4!$B$13),Dados_Observados_v4!R12,"")) | T12: =IF(Dados_Observados_v4!T12<>"",Dados_Observados_v4!T12,IF(AND(Dados_Observados_v4!S12<>"",(2025-2024)<=Metodologia_v4!$B$13),Dados_Observados_v4!S12,""))
A13: MAC03 | B13: 2. Estabilidade Macroeconómica | C13: Inflação, preços ao consumidor | D13: Banco Mundial/WDI | E13: FP.CPI.TOTL.ZG | F13: Fonte Banco Mundial API/CSV | G13: 10/11 | H13: 2024 | I13: Referenciado pelas regras de Metodologia_v4 | J13: =IF(Dados_Observados_v4!J13<>"",Dados_Observados_v4!J13,IF(AND(Dados_Observados_v4!K13<>"",(2016-2015)<=Metodologia_v4!$B$14),Dados_Observados_v4!K13,"")) | K13: =IF(Dados_Observados_v4!K13<>"",Dados_Observados_v4!K13,IF(AND(Dados_Observados_v4!J13<>"",Dados_Observados_v4!L13<>"",(2017-2015-1)<=Metodologia_v4!$B$12),Dados_Observados_v4!J13+(Dados_Observados_v4!L13-Dados_Observados_v4!J13)*(2016-2015)/(2017-2015),IF(AND(Dados_Observados_v4!J13<>"",(2016-2015)<=Metodologia_v4!$B$13),Dados_Observados_v4!J13,IF(AND(Dados_Observados_v4!L13<>"",(2017-2016)<=Metodologia_v4!$B$14),Dados_Observados_v4!L13,"")))) | L13: =IF(Dados_Observados_v4!L13<>"",Dados_Observados_v4!L13,IF(AND(Dados_Observados_v4!K13<>"",Dados_Observados_v4!M13<>"",(2018-2016-1)<=Metodologia_v4!$B$12),Dados_Observados_v4!K13+(Dados_Observados_v4!M13-Dados_Observados_v4!K13)*(2017-2016)/(2018-2016),IF(AND(Dados_Observados_v4!K13<>"",(2017-2016)<=Metodologia_v4!$B$13),Dados_Observados_v4!K13,IF(AND(Dados_Observados_v4!M13<>"",(2018-2017)<=Metodologia_v4!$B$14),Dados_Observados_v4!M13,"")))) | M13: =IF(Dados_Observados_v4!M13<>"",Dados_Observados_v4!M13,IF(AND(Dados_Observados_v4!L13<>"",Dados_Observados_v4!N13<>"",(2019-2017-1)<=Metodologia_v4!$B$12),Dados_Observados_v4!L13+(Dados_Observados_v4!N13-Dados_Observados_v4!L13)*(2018-2017)/(2019-2017),IF(AND(Dados_Observados_v4!L13<>"",(2018-2017)<=Metodologia_v4!$B$13),Dados_Observados_v4!L13,IF(AND(Dados_Observados_v4!N13<>"",(2019-2018)<=Metodologia_v4!$B$14),Dados_Observados_v4!N13,"")))) | N13: =IF(Dados_Observados_v4!N13<>"",Dados_Observados_v4!N13,IF(AND(Dados_Observados_v4!M13<>"",Dados_Observados_v4!O13<>"",(2020-2018-1)<=Metodologia_v4!$B$12),Dados_Observados_v4!M13+(Dados_Observados_v4!O13-Dados_Observados_v4!M13)*(2019-2018)/(2020-2018),IF(AND(Dados_Observados_v4!M13<>"",(2019-2018)<=Metodologia_v4!$B$13),Dados_Observados_v4!M13,IF(AND(Dados_Observados_v4!O13<>"",(2020-2019)<=Metodologia_v4!$B$14),Dados_Observados_v4!O13,"")))) | O13: =IF(Dados_Observados_v4!O13<>"",Dados_Observados_v4!O13,IF(AND(Dados_Observados_v4!N13<>"",Dados_Observados_v4!P13<>"",(2021-2019-1)<=Metodologia_v4!$B$12),Dados_Observados_v4!N13+(Dados_Observados_v4!P13-Dados_Observados_v4!N13)*(2020-2019)/(2021-2019),IF(AND(Dados_Observados_v4!N13<>"",(2020-2019)<=Metodologia_v4!$B$13),Dados_Observados_v4!N13,IF(AND(Dados_Observados_v4!P13<>"",(2021-2020)<=Metodologia_v4!$B$14),Dados_Observados_v4!P13,"")))) | P13: =IF(Dados_Observados_v4!P13<>"",Dados_Observados_v4!P13,IF(AND(Dados_Observados_v4!O13<>"",Dados_Observados_v4!Q13<>"",(2022-2020-1)<=Metodologia_v4!$B$12),Dados_Observados_v4!O13+(Dados_Observados_v4!Q13-Dados_Observados_v4!O13)*(2021-2020)/(2022-2020),IF(AND(Dados_Observados_v4!O13<>"",(2021-2020)<=Metodologia_v4!$B$13),Dados_Observados_v4!O13,IF(AND(Dados_Observados_v4!Q13<>"",(2022-2021)<=Metodologia_v4!$B$14),Dados_Observados_v4!Q13,"")))) | Q13: =IF(Dados_Observados_v4!Q13<>"",Dados_Observados_v4!Q13,IF(AND(Dados_Observados_v4!P13<>"",Dados_Observados_v4!R13<>"",(2023-2021-1)<=Metodologia_v4!$B$12),Dados_Observados_v4!P13+(Dados_Observados_v4!R13-Dados_Observados_v4!P13)*(2022-2021)/(2023-2021),IF(AND(Dados_Observados_v4!P13<>"",(2022-2021)<=Metodologia_v4!$B$13),Dados_Observados_v4!P13,IF(AND(Dados_Observados_v4!R13<>"",(2023-2022)<=Metodologia_v4!$B$14),Dados_Observados_v4!R13,"")))) | R13: =IF(Dados_Observados_v4!R13<>"",Dados_Observados_v4!R13,IF(AND(Dados_Observados_v4!Q13<>"",Dados_Observados_v4!S13<>"",(2024-2022-1)<=Metodologia_v4!$B$12),Dados_Observados_v4!Q13+(Dados_Observados_v4!S13-Dados_Observados_v4!Q13)*(2023-2022)/(2024-2022),IF(AND(Dados_Observados_v4!Q13<>"",(2023-2022)<=Metodologia_v4!$B$13),Dados_Observados_v4!Q13,IF(AND(Dados_Observados_v4!S13<>"",(2024-2023)<=Metodologia_v4!$B$14),Dados_Observados_v4!S13,"")))) | S13: =IF(Dados_Observados_v4!S13<>"",Dados_Observados_v4!S13,IF(AND(Dados_Observados_v4!R13<>"",(2024-2023)<=Metodologia_v4!$B$13),Dados_Observados_v4!R13,"")) | T13: =IF(Dados_Observados_v4!T13<>"",Dados_Observados_v4!T13,IF(AND(Dados_Observados_v4!S13<>"",(2025-2024)<=Metodologia_v4!$B$13),Dados_Observados_v4!S13,""))
A14: MAC04 | B14: 2. Estabilidade Macroeconómica | C14: Dívida pública do governo central | D14: Banco Mundial/WDI | E14: GC.DOD.TOTL.GD.ZS | F14: Sem valores Angola no período; fallback para série do ficheiro base | G14: 11/11 | H14: 2025 | I14: Referenciado pelas regras de Metodologia_v4 | J14: =IF(Dados_Observados_v4!J14<>"",Dados_Observados_v4!J14,IF(AND(Dados_Observados_v4!K14<>"",(2016-2015)<=Metodologia_v4!$B$14),Dados_Observados_v4!K14,"")) | K14: =IF(Dados_Observados_v4!K14<>"",Dados_Observados_v4!K14,IF(AND(Dados_Observados_v4!J14<>"",Dados_Observados_v4!L14<>"",(2017-2015-1)<=Metodologia_v4!$B$12),Dados_Observados_v4!J14+(Dados_Observados_v4!L14-Dados_Observados_v4!J14)*(2016-2015)/(2017-2015),IF(AND(Dados_Observados_v4!J14<>"",(2016-2015)<=Metodologia_v4!$B$13),Dados_Observados_v4!J14,IF(AND(Dados_Observados_v4!L14<>"",(2017-2016)<=Metodologia_v4!$B$14),Dados_Observados_v4!L14,"")))) | L14: =IF(Dados_Observados_v4!L14<>"",Dados_Observados_v4!L14,IF(AND(Dados_Observados_v4!K14<>"",Dados_Observados_v4!M14<>"",(2018-2016-1)<=Metodologia_v4!$B$12),Dados_Observados_v4!K14+(Dados_Observados_v4!M14-Dados_Observados_v4!K14)*(2017-2016)/(2018-2016),IF(AND(Dados_Observados_v4!K14<>"",(2017-2016)<=Metodologia_v4!$B$13),Dados_Observados_v4!K14,IF(AND(Dados_Observados_v4!M14<>"",(2018-2017)<=Metodologia_v4!$B$14),Dados_Observados_v4!M14,"")))) | M14: =IF(Dados_Observados_v4!M14<>"",Dados_Observados_v4!M14,IF(AND(Dados_Observados_v4!L14<>"",Dados_Observados_v4!N14<>"",(2019-2017-1)<=Metodologia_v4!$B$12),Dados_Observados_v4!L14+(Dados_Observados_v4!N14-Dados_Observados_v4!L14)*(2018-2017)/(2019-2017),IF(AND(Dados_Observados_v4!L14<>"",(2018-2017)<=Metodologia_v4!$B$13),Dados_Observados_v4!L14,IF(AND(Dados_Observados_v4!N14<>"",(2019-2018)<=Metodologia_v4!$B$14),Dados_Observados_v4!N14,"")))) | N14: =IF(Dados_Observados_v4!N14<>"",Dados_Observados_v4!N14,IF(AND(Dados_Observados_v4!M14<>"",Dados_Observados_v4!O14<>"",(2020-2018-1)<=Metodologia_v4!$B$12),Dados_Observados_v4!M14+(Dados_Observados_v4!O14-Dados_Observados_v4!M14)*(2019-2018)/(2020-2018),IF(AND(Dados_Observados_v4!M14<>"",(2019-2018)<=Metodologia_v4!$B$13),Dados_Observados_v4!M14,IF(AND(Dados_Observados_v4!O14<>"",(2020-2019)<=Metodologia_v4!$B$14),Dados_Observados_v4!O14,"")))) | O14: =IF(Dados_Observados_v4!O14<>"",Dados_Observados_v4!O14,IF(AND(Dados_Observados_v4!N14<>"",Dados_Observados_v4!P14<>"",(2021-2019-1)<=Metodologia_v4!$B$12),Dados_Observados_v4!N14+(Dados_Observados_v4!P14-Dados_Observados_v4!N14)*(2020-2019)/(2021-2019),IF(AND(Dados_Observados_v4!N14<>"",(2020-2019)<=Metodologia_v4!$B$13),Dados_Observados_v4!N14,IF(AND(Dados_Observados_v4!P14<>"",(2021-2020)<=Metodologia_v4!$B$14),Dados_Observados_v4!P14,"")))) | P14: =IF(Dados_Observados_v4!P14<>"",Dados_Observados_v4!P14,IF(AND(Dados_Observados_v4!O14<>"",Dados_Observados_v4!Q14<>"",(2022-2020-1)<=Metodologia_v4!$B$12),Dados_Observados_v4!O14+(Dados_Observados_v4!Q14-Dados_Observados_v4!O14)*(2021-2020)/(2022-2020),IF(AND(Dados_Observados_v4!O14<>"",(2021-2020)<=Metodologia_v4!$B$13),Dados_Observados_v4!O14,IF(AND(Dados_Observados_v4!Q14<>"",(2022-2021)<=Metodologia_v4!$B$14),Dados_Observados_v4!Q14,"")))) | Q14: =IF(Dados_Observados_v4!Q14<>"",Dados_Observados_v4!Q14,IF(AND(Dados_Observados_v4!P14<>"",Dados_Observados_v4!R14<>"",(2023-2021-1)<=Metodologia_v4!$B$12),Dados_Observados_v4!P14+(Dados_Observados_v4!R14-Dados_Observados_v4!P14)*(2022-2021)/(2023-2021),IF(AND(Dados_Observados_v4!P14<>"",(2022-2021)<=Metodologia_v4!$B$13),Dados_Observados_v4!P14,IF(AND(Dados_Observados_v4!R14<>"",(2023-2022)<=Metodologia_v4!$B$14),Dados_Observados_v4!R14,"")))) | R14: =IF(Dados_Observados_v4!R14<>"",Dados_Observados_v4!R14,IF(AND(Dados_Observados_v4!Q14<>"",Dados_Observados_v4!S14<>"",(2024-2022-1)<=Metodologia_v4!$B$12),Dados_Observados_v4!Q14+(Dados_Observados_v4!S14-Dados_Observados_v4!Q14)*(2023-2022)/(2024-2022),IF(AND(Dados_Observados_v4!Q14<>"",(2023-2022)<=Metodologia_v4!$B$13),Dados_Observados_v4!Q14,IF(AND(Dados_Observados_v4!S14<>"",(2024-2023)<=Metodologia_v4!$B$14),Dados_Observados_v4!S14,"")))) | S14: =IF(Dados_Observados_v4!S14<>"",Dados_Observados_v4!S14,IF(AND(Dados_Observados_v4!R14<>"",Dados_Observados_v4!T14<>"",(2025-2023-1)<=Metodologia_v4!$B$12),Dados_Observados_v4!R14+(Dados_Observados_v4!T14-Dados_Observados_v4!R14)*(2024-2023)/(2025-2023),IF(AND(Dados_Observados_v4!R14<>"",(2024-2023)<=Metodologia_v4!$B$13),Dados_Observados_v4!R14,IF(AND(Dados_Observados_v4!T14<>"",(2025-2024)<=Metodologia_v4!$B$14),Dados_Observados_v4!T14,"")))) | T14: =IF(Dados_Observados_v4!T14<>"",Dados_Observados_v4!T14,IF(AND(Dados_Observados_v4!S14<>"",(2025-2024)<=Metodologia_v4!$B$13),Dados_Observados_v4!S14,""))
A15: MAC05 | B15: 2. Estabilidade Macroeconómica | C15: Saldo orçamental de caixa | D15: Banco Mundial/WDI | E15: GC.BAL.CASH.GD.ZS | F15: Sem valores Angola no período; fallback para série do ficheiro base | G15: 11/11 | H15: 2025 | I15: Referenciado pelas regras de Metodologia_v4 | J15: =IF(Dados_Observados_v4!J15<>"",Dados_Observados_v4!J15,IF(AND(Dados_Observados_v4!K15<>"",(2016-2015)<=Metodologia_v4!$B$14),Dados_Observados_v4!K15,"")) | K15: =IF(Dados_Observados_v4!K15<>"",Dados_Observados_v4!K15,IF(AND(Dados_Observados_v4!J15<>"",Dados_Observados_v4!L15<>"",(2017-2015-1)<=Metodologia_v4!$B$12),Dados_Observados_v4!J15+(Dados_Observados_v4!L15-Dados_Observados_v4!J15)*(2016-2015)/(2017-2015),IF(AND(Dados_Observados_v4!J15<>"",(2016-2015)<=Metodologia_v4!$B$13),Dados_Observados_v4!J15,IF(AND(Dados_Observados_v4!L15<>"",(2017-2016)<=Metodologia_v4!$B$14),Dados_Observados_v4!L15,"")))) | L15: =IF(Dados_Observados_v4!L15<>"",Dados_Observados_v4!L15,IF(AND(Dados_Observados_v4!K15<>"",Dados_Observados_v4!M15<>"",(2018-2016-1)<=Metodologia_v4!$B$12),Dados_Observados_v4!K15+(Dados_Observados_v4!M15-Dados_Observados_v4!K15)*(2017-2016)/(2018-2016),IF(AND(Dados_Observados_v4!K15<>"",(2017-2016)<=Metodologia_v4!$B$13),Dados_Observados_v4!K15,IF(AND(Dados_Observados_v4!M15<>"",(2018-2017)<=Metodologia_v4!$B$14),Dados_Observados_v4!M15,"")))) | M15: =IF(Dados_Observados_v4!M15<>"",Dados_Observados_v4!M15,IF(AND(Dados_Observados_v4!L15<>"",Dados_Observados_v4!N15<>"",(2019-2017-1)<=Metodologia_v4!$B$12),Dados_Observados_v4!L15+(Dados_Observados_v4!N15-Dados_Observados_v4!L15)*(2018-2017)/(2019-2017),IF(AND(Dados_Observados_v4!L15<>"",(2018-2017)<=Metodologia_v4!$B$13),Dados_Observados_v4!L15,IF(AND(Dados_Observados_v4!N15<>"",(2019-2018)<=Metodologia_v4!$B$14),Dados_Observados_v4!N15,"")))) | N15: =IF(Dados_Observados_v4!N15<>"",Dados_Observados_v4!N15,IF(AND(Dados_Observados_v4!M15<>"",Dados_Observados_v4!O15<>"",(2020-2018-1)<=Metodologia_v4!$B$12),Dados_Observados_v4!M15+(Dados_Observados_v4!O15-Dados_Observados_v4!M15)*(2019-2018)/(2020-2018),IF(AND(Dados_Observados_v4!M15<>"",(2019-2018)<=Metodologia_v4!$B$13),Dados_Observados_v4!M15,IF(AND(Dados_Observados_v4!O15<>"",(2020-2019)<=Metodologia_v4!$B$14),Dados_Observados_v4!O15,"")))) | O15: =IF(Dados_Observados_v4!O15<>"",Dados_Observados_v4!O15,IF(AND(Dados_Observados_v4!N15<>"",Dados_Observados_v4!P15<>"",(2021-2019-1)<=Metodologia_v4!$B$12),Dados_Observados_v4!N15+(Dados_Observados_v4!P15-Dados_Observados_v4!N15)*(2020-2019)/(2021-2019),IF(AND(Dados_Observados_v4!N15<>"",(2020-2019)<=Metodologia_v4!$B$13),Dados_Observados_v4!N15,IF(AND(Dados_Observados_v4!P15<>"",(2021-2020)<=Metodologia_v4!$B$14),Dados_Observados_v4!P15,"")))) | P15: =IF(Dados_Observados_v4!P15<>"",Dados_Observados_v4!P15,IF(AND(Dados_Observados_v4!O15<>"",Dados_Observados_v4!Q15<>"",(2022-2020-1)<=Metodologia_v4!$B$12),Dados_Observados_v4!O15+(Dados_Observados_v4!Q15-Dados_Observados_v4!O15)*(2021-2020)/(2022-2020),IF(AND(Dados_Observados_v4!O15<>"",(2021-2020)<=Metodologia_v4!$B$13),Dados_Observados_v4!O15,IF(AND(Dados_Observados_v4!Q15<>"",(2022-2021)<=Metodologia_v4!$B$14),Dados_Observados_v4!Q15,"")))) | Q15: =IF(Dados_Observados_v4!Q15<>"",Dados_Observados_v4!Q15,IF(AND(Dados_Observados_v4!P15<>"",Dados_Observados_v4!R15<>"",(2023-2021-1)<=Metodologia_v4!$B$12),Dados_Observados_v4!P15+(Dados_Observados_v4!R15-Dados_Observados_v4!P15)*(2022-2021)/(2023-2021),IF(AND(Dados_Observados_v4!P15<>"",(2022-2021)<=Metodologia_v4!$B$13),Dados_Observados_v4!P15,IF(AND(Dados_Observados_v4!R15<>"",(2023-2022)<=Metodologia_v4!$B$14),Dados_Observados_v4!R15,"")))) | R15: =IF(Dados_Observados_v4!R15<>"",Dados_Observados_v4!R15,IF(AND(Dados_Observados_v4!Q15<>"",Dados_Observados_v4!S15<>"",(2024-2022-1)<=Metodologia_v4!$B$12),Dados_Observados_v4!Q15+(Dados_Observados_v4!S15-Dados_Observados_v4!Q15)*(2023-2022)/(2024-2022),IF(AND(Dados_Observados_v4!Q15<>"",(2023-2022)<=Metodologia_v4!$B$13),Dados_Observados_v4!Q15,IF(AND(Dados_Observados_v4!S15<>"",(2024-2023)<=Metodologia_v4!$B$14),Dados_Observados_v4!S15,"")))) | S15: =IF(Dados_Observados_v4!S15<>"",Dados_Observados_v4!S15,IF(AND(Dados_Observados_v4!R15<>"",Dados_Observados_v4!T15<>"",(2025-2023-1)<=Metodologia_v4!$B$12),Dados_Observados_v4!R15+(Dados_Observados_v4!T15-Dados_Observados_v4!R15)*(2024-2023)/(2025-2023),IF(AND(Dados_Observados_v4!R15<>"",(2024-2023)<=Metodologia_v4!$B$13),Dados_Observados_v4!R15,IF(AND(Dados_Observados_v4!T15<>"",(2025-2024)<=Metodologia_v4!$B$14),Dados_Observados_v4!T15,"")))) | T15: =IF(Dados_Observados_v4!T15<>"",Dados_Observados_v4!T15,IF(AND(Dados_Observados_v4!S15<>"",(2025-2024)<=Metodologia_v4!$B$13),Dados_Observados_v4!S15,""))
A16: MAC06 | B16: 2. Estabilidade Macroeconómica | C16: Saldo da conta corrente | D16: Banco Mundial/WDI | E16: BN.CAB.XOKA.GD.ZS | F16: Fonte Banco Mundial API/CSV | G16: 10/11 | H16: 2024 | I16: Referenciado pelas regras de Metodologia_v4 | J16: =IF(Dados_Observados_v4!J16<>"",Dados_Observados_v4!J16,IF(AND(Dados_Observados_v4!K16<>"",(2016-2015)<=Metodologia_v4!$B$14),Dados_Observados_v4!K16,"")) | K16: =IF(Dados_Observados_v4!K16<>"",Dados_Observados_v4!K16,IF(AND(Dados_Observados_v4!J16<>"",Dados_Observados_v4!L16<>"",(2017-2015-1)<=Metodologia_v4!$B$12),Dados_Observados_v4!J16+(Dados_Observados_v4!L16-Dados_Observados_v4!J16)*(2016-2015)/(2017-2015),IF(AND(Dados_Observados_v4!J16<>"",(2016-2015)<=Metodologia_v4!$B$13),Dados_Observados_v4!J16,IF(AND(Dados_Observados_v4!L16<>"",(2017-2016)<=Metodologia_v4!$B$14),Dados_Observados_v4!L16,"")))) | L16: =IF(Dados_Observados_v4!L16<>"",Dados_Observados_v4!L16,IF(AND(Dados_Observados_v4!K16<>"",Dados_Observados_v4!M16<>"",(2018-2016-1)<=Metodologia_v4!$B$12),Dados_Observados_v4!K16+(Dados_Observados_v4!M16-Dados_Observados_v4!K16)*(2017-2016)/(2018-2016),IF(AND(Dados_Observados_v4!K16<>"",(2017-2016)<=Metodologia_v4!$B$13),Dados_Observados_v4!K16,IF(AND(Dados_Observados_v4!M16<>"",(2018-2017)<=Metodologia_v4!$B$14),Dados_Observados_v4!M16,"")))) | M16: =IF(Dados_Observados_v4!M16<>"",Dados_Observados_v4!M16,IF(AND(Dados_Observados_v4!L16<>"",Dados_Observados_v4!N16<>"",(2019-2017-1)<=Metodologia_v4!$B$12),Dados_Observados_v4!L16+(Dados_Observados_v4!N16-Dados_Observados_v4!L16)*(2018-2017)/(2019-2017),IF(AND(Dados_Observados_v4!L16<>"",(2018-2017)<=Metodologia_v4!$B$13),Dados_Observados_v4!L16,IF(AND(Dados_Observados_v4!N16<>"",(2019-2018)<=Metodologia_v4!$B$14),Dados_Observados_v4!N16,"")))) | N16: =IF(Dados_Observados_v4!N16<>"",Dados_Observados_v4!N16,IF(AND(Dados_Observados_v4!M16<>"",Dados_Observados_v4!O16<>"",(2020-2018-1)<=Metodologia_v4!$B$12),Dados_Observados_v4!M16+(Dados_Observados_v4!O16-Dados_Observados_v4!M16)*(2019-2018)/(2020-2018),IF(AND(Dados_Observados_v4!M16<>"",(2019-2018)<=Metodologia_v4!$B$13),Dados_Observados_v4!M16,IF(AND(Dados_Observados_v4!O16<>"",(2020-2019)<=Metodologia_v4!$B$14),Dados_Observados_v4!O16,"")))) | O16: =IF(Dados_Observados_v4!O16<>"",Dados_Observados_v4!O16,IF(AND(Dados_Observados_v4!N16<>"",Dados_Observados_v4!P16<>"",(2021-2019-1)<=Metodologia_v4!$B$12),Dados_Observados_v4!N16+(Dados_Observados_v4!P16-Dados_Observados_v4!N16)*(2020-2019)/(2021-2019),IF(AND(Dados_Observados_v4!N16<>"",(2020-2019)<=Metodologia_v4!$B$13),Dados_Observados_v4!N16,IF(AND(Dados_Observados_v4!P16<>"",(2021-2020)<=Metodologia_v4!$B$14),Dados_Observados_v4!P16,"")))) | P16: =IF(Dados_Observados_v4!P16<>"",Dados_Observados_v4!P16,IF(AND(Dados_Observados_v4!O16<>"",Dados_Observados_v4!Q16<>"",(2022-2020-1)<=Metodologia_v4!$B$12),Dados_Observados_v4!O16+(Dados_Observados_v4!Q16-Dados_Observados_v4!O16)*(2021-2020)/(2022-2020),IF(AND(Dados_Observados_v4!O16<>"",(2021-2020)<=Metodologia_v4!$B$13),Dados_Observados_v4!O16,IF(AND(Dados_Observados_v4!Q16<>"",(2022-2021)<=Metodologia_v4!$B$14),Dados_Observados_v4!Q16,"")))) | Q16: =IF(Dados_Observados_v4!Q16<>"",Dados_Observados_v4!Q16,IF(AND(Dados_Observados_v4!P16<>"",Dados_Observados_v4!R16<>"",(2023-2021-1)<=Metodologia_v4!$B$12),Dados_Observados_v4!P16+(Dados_Observados_v4!R16-Dados_Observados_v4!P16)*(2022-2021)/(2023-2021),IF(AND(Dados_Observados_v4!P16<>"",(2022-2021)<=Metodologia_v4!$B$13),Dados_Observados_v4!P16,IF(AND(Dados_Observados_v4!R16<>"",(2023-2022)<=Metodologia_v4!$B$14),Dados_Observados_v4!R16,"")))) | R16: =IF(Dados_Observados_v4!R16<>"",Dados_Observados_v4!R16,IF(AND(Dados_Observados_v4!Q16<>"",Dados_Observados_v4!S16<>"",(2024-2022-1)<=Metodologia_v4!$B$12),Dados_Observados_v4!Q16+(Dados_Observados_v4!S16-Dados_Observados_v4!Q16)*(2023-2022)/(2024-2022),IF(AND(Dados_Observados_v4!Q16<>"",(2023-2022)<=Metodologia_v4!$B$13),Dados_Observados_v4!Q16,IF(AND(Dados_Observados_v4!S16<>"",(2024-2023)<=Metodologia_v4!$B$14),Dados_Observados_v4!S16,"")))) | S16: =IF(Dados_Observados_v4!S16<>"",Dados_Observados_v4!S16,IF(AND(Dados_Observados_v4!R16<>"",(2024-2023)<=Metodologia_v4!$B$13),Dados_Observados_v4!R16,"")) | T16: =IF(Dados_Observados_v4!T16<>"",Dados_Observados_v4!T16,IF(AND(Dados_Observados_v4!S16<>"",(2025-2024)<=Metodologia_v4!$B$13),Dados_Observados_v4!S16,""))
A17: MAC07 | B17: 2. Estabilidade Macroeconómica | C17: Reservas internacionais | D17: Banco Mundial/WDI | E17: FI.RES.TOTL.MO | F17: Fonte Banco Mundial API/CSV | G17: 10/11 | H17: 2024 | I17: Referenciado pelas regras de Metodologia_v4 | J17: =IF(Dados_Observados_v4!J17<>"",Dados_Observados_v4!J17,IF(AND(Dados_Observados_v4!K17<>"",(2016-2015)<=Metodologia_v4!$B$14),Dados_Observados_v4!K17,"")) | K17: =IF(Dados_Observados_v4!K17<>"",Dados_Observados_v4!K17,IF(AND(Dados_Observados_v4!J17<>"",Dados_Observados_v4!L17<>"",(2017-2015-1)<=Metodologia_v4!$B$12),Dados_Observados_v4!J17+(Dados_Observados_v4!L17-Dados_Observados_v4!J17)*(2016-2015)/(2017-2015),IF(AND(Dados_Observados_v4!J17<>"",(2016-2015)<=Metodologia_v4!$B$13),Dados_Observados_v4!J17,IF(AND(Dados_Observados_v4!L17<>"",(2017-2016)<=Metodologia_v4!$B$14),Dados_Observados_v4!L17,"")))) | L17: =IF(Dados_Observados_v4!L17<>"",Dados_Observados_v4!L17,IF(AND(Dados_Observados_v4!K17<>"",Dados_Observados_v4!M17<>"",(2018-2016-1)<=Metodologia_v4!$B$12),Dados_Observados_v4!K17+(Dados_Observados_v4!M17-Dados_Observados_v4!K17)*(2017-2016)/(2018-2016),IF(AND(Dados_Observados_v4!K17<>"",(2017-2016)<=Metodologia_v4!$B$13),Dados_Observados_v4!K17,IF(AND(Dados_Observados_v4!M17<>"",(2018-2017)<=Metodologia_v4!$B$14),Dados_Observados_v4!M17,"")))) | M17: =IF(Dados_Observados_v4!M17<>"",Dados_Observados_v4!M17,IF(AND(Dados_Observados_v4!L17<>"",Dados_Observados_v4!N17<>"",(2019-2017-1)<=Metodologia_v4!$B$12),Dados_Observados_v4!L17+(Dados_Observados_v4!N17-Dados_Observados_v4!L17)*(2018-2017)/(2019-2017),IF(AND(Dados_Observados_v4!L17<>"",(2018-2017)<=Metodologia_v4!$B$13),Dados_Observados_v4!L17,IF(AND(Dados_Observados_v4!N17<>"",(2019-2018)<=Metodologia_v4!$B$14),Dados_Observados_v4!N17,"")))) | N17: =IF(Dados_Observados_v4!N17<>"",Dados_Observados_v4!N17,IF(AND(Dados_Observados_v4!M17<>"",Dados_Observados_v4!O17<>"",(2020-2018-1)<=Metodologia_v4!$B$12),Dados_Observados_v4!M17+(Dados_Observados_v4!O17-Dados_Observados_v4!M17)*(2019-2018)/(2020-2018),IF(AND(Dados_Observados_v4!M17<>"",(2019-2018)<=Metodologia_v4!$B$13),Dados_Observados_v4!M17,IF(AND(Dados_Observados_v4!O17<>"",(2020-2019)<=Metodologia_v4!$B$14),Dados_Observados_v4!O17,"")))) | O17: =IF(Dados_Observados_v4!O17<>"",Dados_Observados_v4!O17,IF(AND(Dados_Observados_v4!N17<>"",Dados_Observados_v4!P17<>"",(2021-2019-1)<=Metodologia_v4!$B$12),Dados_Observados_v4!N17+(Dados_Observados_v4!P17-Dados_Observados_v4!N17)*(2020-2019)/(2021-2019),IF(AND(Dados_Observados_v4!N17<>"",(2020-2019)<=Metodologia_v4!$B$13),Dados_Observados_v4!N17,IF(AND(Dados_Observados_v4!P17<>"",(2021-2020)<=Metodologia_v4!$B$14),Dados_Observados_v4!P17,"")))) | P17: =IF(Dados_Observados_v4!P17<>"",Dados_Observados_v4!P17,IF(AND(Dados_Observados_v4!O17<>"",Dados_Observados_v4!Q17<>"",(2022-2020-1)<=Metodologia_v4!$B$12),Dados_Observados_v4!O17+(Dados_Observados_v4!Q17-Dados_Observados_v4!O17)*(2021-2020)/(2022-2020),IF(AND(Dados_Observados_v4!O17<>"",(2021-2020)<=Metodologia_v4!$B$13),Dados_Observados_v4!O17,IF(AND(Dados_Observados_v4!Q17<>"",(2022-2021)<=Metodologia_v4!$B$14),Dados_Observados_v4!Q17,"")))) | Q17: =IF(Dados_Observados_v4!Q17<>"",Dados_Observados_v4!Q17,IF(AND(Dados_Observados_v4!P17<>"",Dados_Observados_v4!R17<>"",(2023-2021-1)<=Metodologia_v4!$B$12),Dados_Observados_v4!P17+(Dados_Observados_v4!R17-Dados_Observados_v4!P17)*(2022-2021)/(2023-2021),IF(AND(Dados_Observados_v4!P17<>"",(2022-2021)<=Metodologia_v4!$B$13),Dados_Observados_v4!P17,IF(AND(Dados_Observados_v4!R17<>"",(2023-2022)<=Metodologia_v4!$B$14),Dados_Observados_v4!R17,"")))) | R17: =IF(Dados_Observados_v4!R17<>"",Dados_Observados_v4!R17,IF(AND(Dados_Observados_v4!Q17<>"",Dados_Observados_v4!S17<>"",(2024-2022-1)<=Metodologia_v4!$B$12),Dados_Observados_v4!Q17+(Dados_Observados_v4!S17-Dados_Observados_v4!Q17)*(2023-2022)/(2024-2022),IF(AND(Dados_Observados_v4!Q17<>"",(2023-2022)<=Metodologia_v4!$B$13),Dados_Observados_v4!Q17,IF(AND(Dados_Observados_v4!S17<>"",(2024-2023)<=Metodologia_v4!$B$14),Dados_Observados_v4!S17,"")))) | S17: =IF(Dados_Observados_v4!S17<>"",Dados_Observados_v4!S17,IF(AND(Dados_Observados_v4!R17<>"",(2024-2023)<=Metodologia_v4!$B$13),Dados_Observados_v4!R17,"")) | T17: =IF(Dados_Observados_v4!T17<>"",Dados_Observados_v4!T17,IF(AND(Dados_Observados_v4!S17<>"",(2025-2024)<=Metodologia_v4!$B$13),Dados_Observados_v4!S17,""))
A18: MAC08 | B18: 2. Estabilidade Macroeconómica | C18: Receita fiscal | D18: Banco Mundial/WDI | E18: GC.TAX.TOTL.GD.ZS | F18: Fonte Banco Mundial API/CSV | G18: 10/11 | H18: 2024 | I18: Referenciado pelas regras de Metodologia_v4 | J18: =IF(Dados_Observados_v4!J18<>"",Dados_Observados_v4!J18,IF(AND(Dados_Observados_v4!K18<>"",(2016-2015)<=Metodologia_v4!$B$14),Dados_Observados_v4!K18,"")) | K18: =IF(Dados_Observados_v4!K18<>"",Dados_Observados_v4!K18,IF(AND(Dados_Observados_v4!J18<>"",Dados_Observados_v4!L18<>"",(2017-2015-1)<=Metodologia_v4!$B$12),Dados_Observados_v4!J18+(Dados_Observados_v4!L18-Dados_Observados_v4!J18)*(2016-2015)/(2017-2015),IF(AND(Dados_Observados_v4!J18<>"",(2016-2015)<=Metodologia_v4!$B$13),Dados_Observados_v4!J18,IF(AND(Dados_Observados_v4!L18<>"",(2017-2016)<=Metodologia_v4!$B$14),Dados_Observados_v4!L18,"")))) | L18: =IF(Dados_Observados_v4!L18<>"",Dados_Observados_v4!L18,IF(AND(Dados_Observados_v4!K18<>"",Dados_Observados_v4!M18<>"",(2018-2016-1)<=Metodologia_v4!$B$12),Dados_Observados_v4!K18+(Dados_Observados_v4!M18-Dados_Observados_v4!K18)*(2017-2016)/(2018-2016),IF(AND(Dados_Observados_v4!K18<>"",(2017-2016)<=Metodologia_v4!$B$13),Dados_Observados_v4!K18,IF(AND(Dados_Observados_v4!M18<>"",(2018-2017)<=Metodologia_v4!$B$14),Dados_Observados_v4!M18,"")))) | M18: =IF(Dados_Observados_v4!M18<>"",Dados_Observados_v4!M18,IF(AND(Dados_Observados_v4!L18<>"",Dados_Observados_v4!N18<>"",(2019-2017-1)<=Metodologia_v4!$B$12),Dados_Observados_v4!L18+(Dados_Observados_v4!N18-Dados_Observados_v4!L18)*(2018-2017)/(2019-2017),IF(AND(Dados_Observados_v4!L18<>"",(2018-2017)<=Metodologia_v4!$B$13),Dados_Observados_v4!L18,IF(AND(Dados_Observados_v4!N18<>"",(2019-2018)<=Metodologia_v4!$B$14),Dados_Observados_v4!N18,"")))) | N18: =IF(Dados_Observados_v4!N18<>"",Dados_Observados_v4!N18,IF(AND(Dados_Observados_v4!M18<>"",Dados_Observados_v4!O18<>"",(2020-2018-1)<=Metodologia_v4!$B$12),Dados_Observados_v4!M18+(Dados_Observados_v4!O18-Dados_Observados_v4!M18)*(2019-2018)/(2020-2018),IF(AND(Dados_Observados_v4!M18<>"",(2019-2018)<=Metodologia_v4!$B$13),Dados_Observados_v4!M18,IF(AND(Dados_Observados_v4!O18<>"",(2020-2019)<=Metodologia_v4!$B$14),Dados_Observados_v4!O18,"")))) | O18: =IF(Dados_Observados_v4!O18<>"",Dados_Observados_v4!O18,IF(AND(Dados_Observados_v4!N18<>"",Dados_Observados_v4!P18<>"",(2021-2019-1)<=Metodologia_v4!$B$12),Dados_Observados_v4!N18+(Dados_Observados_v4!P18-Dados_Observados_v4!N18)*(2020-2019)/(2021-2019),IF(AND(Dados_Observados_v4!N18<>"",(2020-2019)<=Metodologia_v4!$B$13),Dados_Observados_v4!N18,IF(AND(Dados_Observados_v4!P18<>"",(2021-2020)<=Metodologia_v4!$B$14),Dados_Observados_v4!P18,"")))) | P18: =IF(Dados_Observados_v4!P18<>"",Dados_Observados_v4!P18,IF(AND(Dados_Observados_v4!O18<>"",Dados_Observados_v4!Q18<>"",(2022-2020-1)<=Metodologia_v4!$B$12),Dados_Observados_v4!O18+(Dados_Observados_v4!Q18-Dados_Observados_v4!O18)*(2021-2020)/(2022-2020),IF(AND(Dados_Observados_v4!O18<>"",(2021-2020)<=Metodologia_v4!$B$13),Dados_Observados_v4!O18,IF(AND(Dados_Observados_v4!Q18<>"",(2022-2021)<=Metodologia_v4!$B$14),Dados_Observados_v4!Q18,"")))) | Q18: =IF(Dados_Observados_v4!Q18<>"",Dados_Observados_v4!Q18,IF(AND(Dados_Observados_v4!P18<>"",Dados_Observados_v4!R18<>"",(2023-2021-1)<=Metodologia_v4!$B$12),Dados_Observados_v4!P18+(Dados_Observados_v4!R18-Dados_Observados_v4!P18)*(2022-2021)/(2023-2021),IF(AND(Dados_Observados_v4!P18<>"",(2022-2021)<=Metodologia_v4!$B$13),Dados_Observados_v4!P18,IF(AND(Dados_Observados_v4!R18<>"",(2023-2022)<=Metodologia_v4!$B$14),Dados_Observados_v4!R18,"")))) | R18: =IF(Dados_Observados_v4!R18<>"",Dados_Observados_v4!R18,IF(AND(Dados_Observados_v4!Q18<>"",Dados_Observados_v4!S18<>"",(2024-2022-1)<=Metodologia_v4!$B$12),Dados_Observados_v4!Q18+(Dados_Observados_v4!S18-Dados_Observados_v4!Q18)*(2023-2022)/(2024-2022),IF(AND(Dados_Observados_v4!Q18<>"",(2023-2022)<=Metodologia_v4!$B$13),Dados_Observados_v4!Q18,IF(AND(Dados_Observados_v4!S18<>"",(2024-2023)<=Metodologia_v4!$B$14),Dados_Observados_v4!S18,"")))) | S18: =IF(Dados_Observados_v4!S18<>"",Dados_Observados_v4!S18,IF(AND(Dados_Observados_v4!R18<>"",(2024-2023)<=Metodologia_v4!$B$13),Dados_Observados_v4!R18,"")) | T18: =IF(Dados_Observados_v4!T18<>"",Dados_Observados_v4!T18,IF(AND(Dados_Observados_v4!S18<>"",(2025-2024)<=Metodologia_v4!$B$13),Dados_Observados_v4!S18,""))
A19: HUM01 | B19: 3. Capital Humano | C19: Índice de Desenvolvimento Humano | D19: PNUD/HDR / ficheiro base | F19: Série observada do ficheiro base | G19: 9/11 | H19: 2023 | I19: Referenciado pelas regras de Metodologia_v4 | J19: =IF(Dados_Observados_v4!J19<>"",Dados_Observados_v4!J19,IF(AND(Dados_Observados_v4!K19<>"",(2016-2015)<=Metodologia_v4!$B$14),Dados_Observados_v4!K19,"")) | K19: =IF(Dados_Observados_v4!K19<>"",Dados_Observados_v4!K19,IF(AND(Dados_Observados_v4!J19<>"",Dados_Observados_v4!L19<>"",(2017-2015-1)<=Metodologia_v4!$B$12),Dados_Observados_v4!J19+(Dados_Observados_v4!L19-Dados_Observados_v4!J19)*(2016-2015)/(2017-2015),IF(AND(Dados_Observados_v4!J19<>"",(2016-2015)<=Metodologia_v4!$B$13),Dados_Observados_v4!J19,IF(AND(Dados_Observados_v4!L19<>"",(2017-2016)<=Metodologia_v4!$B$14),Dados_Observados_v4!L19,"")))) | L19: =IF(Dados_Observados_v4!L19<>"",Dados_Observados_v4!L19,IF(AND(Dados_Observados_v4!K19<>"",Dados_Observados_v4!M19<>"",(2018-2016-1)<=Metodologia_v4!$B$12),Dados_Observados_v4!K19+(Dados_Observados_v4!M19-Dados_Observados_v4!K19)*(2017-2016)/(2018-2016),IF(AND(Dados_Observados_v4!K19<>"",(2017-2016)<=Metodologia_v4!$B$13),Dados_Observados_v4!K19,IF(AND(Dados_Observados_v4!M19<>"",(2018-2017)<=Metodologia_v4!$B$14),Dados_Observados_v4!M19,"")))) | M19: =IF(Dados_Observados_v4!M19<>"",Dados_Observados_v4!M19,IF(AND(Dados_Observados_v4!L19<>"",Dados_Observados_v4!N19<>"",(2019-2017-1)<=Metodologia_v4!$B$12),Dados_Observados_v4!L19+(Dados_Observados_v4!N19-Dados_Observados_v4!L19)*(2018-2017)/(2019-2017),IF(AND(Dados_Observados_v4!L19<>"",(2018-2017)<=Metodologia_v4!$B$13),Dados_Observados_v4!L19,IF(AND(Dados_Observados_v4!N19<>"",(2019-2018)<=Metodologia_v4!$B$14),Dados_Observados_v4!N19,"")))) | N19: =IF(Dados_Observados_v4!N19<>"",Dados_Observados_v4!N19,IF(AND(Dados_Observados_v4!M19<>"",Dados_Observados_v4!O19<>"",(2020-2018-1)<=Metodologia_v4!$B$12),Dados_Observados_v4!M19+(Dados_Observados_v4!O19-Dados_Observados_v4!M19)*(2019-2018)/(2020-2018),IF(AND(Dados_Observados_v4!M19<>"",(2019-2018)<=Metodologia_v4!$B$13),Dados_Observados_v4!M19,IF(AND(Dados_Observados_v4!O19<>"",(2020-2019)<=Metodologia_v4!$B$14),Dados_Observados_v4!O19,"")))) | O19: =IF(Dados_Observados_v4!O19<>"",Dados_Observados_v4!O19,IF(AND(Dados_Observados_v4!N19<>"",Dados_Observados_v4!P19<>"",(2021-2019-1)<=Metodologia_v4!$B$12),Dados_Observados_v4!N19+(Dados_Observados_v4!P19-Dados_Observados_v4!N19)*(2020-2019)/(2021-2019),IF(AND(Dados_Observados_v4!N19<>"",(2020-2019)<=Metodologia_v4!$B$13),Dados_Observados_v4!N19,IF(AND(Dados_Observados_v4!P19<>"",(2021-2020)<=Metodologia_v4!$B$14),Dados_Observados_v4!P19,"")))) | P19: =IF(Dados_Observados_v4!P19<>"",Dados_Observados_v4!P19,IF(AND(Dados_Observados_v4!O19<>"",Dados_Observados_v4!Q19<>"",(2022-2020-1)<=Metodologia_v4!$B$12),Dados_Observados_v4!O19+(Dados_Observados_v4!Q19-Dados_Observados_v4!O19)*(2021-2020)/(2022-2020),IF(AND(Dados_Observados_v4!O19<>"",(2021-2020)<=Metodologia_v4!$B$13),Dados_Observados_v4!O19,IF(AND(Dados_Observados_v4!Q19<>"",(2022-2021)<=Metodologia_v4!$B$14),Dados_Observados_v4!Q19,"")))) | Q19: =IF(Dados_Observados_v4!Q19<>"",Dados_Observados_v4!Q19,IF(AND(Dados_Observados_v4!P19<>"",Dados_Observados_v4!R19<>"",(2023-2021-1)<=Metodologia_v4!$B$12),Dados_Observados_v4!P19+(Dados_Observados_v4!R19-Dados_Observados_v4!P19)*(2022-2021)/(2023-2021),IF(AND(Dados_Observados_v4!P19<>"",(2022-2021)<=Metodologia_v4!$B$13),Dados_Observados_v4!P19,IF(AND(Dados_Observados_v4!R19<>"",(2023-2022)<=Metodologia_v4!$B$14),Dados_Observados_v4!R19,"")))) | R19: =IF(Dados_Observados_v4!R19<>"",Dados_Observados_v4!R19,IF(AND(Dados_Observados_v4!Q19<>"",(2023-2022)<=Metodologia_v4!$B$13),Dados_Observados_v4!Q19,"")) | S19: =IF(Dados_Observados_v4!S19<>"",Dados_Observados_v4!S19,IF(AND(Dados_Observados_v4!R19<>"",(2024-2023)<=Metodologia_v4!$B$13),Dados_Observados_v4!R19,"")) | T19: =IF(Dados_Observados_v4!T19<>"",Dados_Observados_v4!T19,IF(AND(Dados_Observados_v4!R19<>"",(2025-2023)<=Metodologia_v4!$B$13),Dados_Observados_v4!R19,""))
A20: HUM02 | B20: 3. Capital Humano | C20: Esperança de vida à nascença | D20: Banco Mundial/WDI | E20: SP.DYN.LE00.IN | F20: Fonte Banco Mundial API/CSV | G20: 10/11 | H20: 2024 | I20: Referenciado pelas regras de Metodologia_v4 | J20: =IF(Dados_Observados_v4!J20<>"",Dados_Observados_v4!J20,IF(AND(Dados_Observados_v4!K20<>"",(2016-2015)<=Metodologia_v4!$B$14),Dados_Observados_v4!K20,"")) | K20: =IF(Dados_Observados_v4!K20<>"",Dados_Observados_v4!K20,IF(AND(Dados_Observados_v4!J20<>"",Dados_Observados_v4!L20<>"",(2017-2015-1)<=Metodologia_v4!$B$12),Dados_Observados_v4!J20+(Dados_Observados_v4!L20-Dados_Observados_v4!J20)*(2016-2015)/(2017-2015),IF(AND(Dados_Observados_v4!J20<>"",(2016-2015)<=Metodologia_v4!$B$13),Dados_Observados_v4!J20,IF(AND(Dados_Observados_v4!L20<>"",(2017-2016)<=Metodologia_v4!$B$14),Dados_Observados_v4!L20,"")))) | L20: =IF(Dados_Observados_v4!L20<>"",Dados_Observados_v4!L20,IF(AND(Dados_Observados_v4!K20<>"",Dados_Observados_v4!M20<>"",(2018-2016-1)<=Metodologia_v4!$B$12),Dados_Observados_v4!K20+(Dados_Observados_v4!M20-Dados_Observados_v4!K20)*(2017-2016)/(2018-2016),IF(AND(Dados_Observados_v4!K20<>"",(2017-2016)<=Metodologia_v4!$B$13),Dados_Observados_v4!K20,IF(AND(Dados_Observados_v4!M20<>"",(2018-2017)<=Metodologia_v4!$B$14),Dados_Observados_v4!M20,"")))) | M20: =IF(Dados_Observados_v4!M20<>"",Dados_Observados_v4!M20,IF(AND(Dados_Observados_v4!L20<>"",Dados_Observados_v4!N20<>"",(2019-2017-1)<=Metodologia_v4!$B$12),Dados_Observados_v4!L20+(Dados_Observados_v4!N20-Dados_Observados_v4!L20)*(2018-2017)/(2019-2017),IF(AND(Dados_Observados_v4!L20<>"",(2018-2017)<=Metodologia_v4!$B$13),Dados_Observados_v4!L20,IF(AND(Dados_Observados_v4!N20<>"",(2019-2018)<=Metodologia_v4!$B$14),Dados_Observados_v4!N20,"")))) | N20: =IF(Dados_Observados_v4!N20<>"",Dados_Observados_v4!N20,IF(AND(Dados_Observados_v4!M20<>"",Dados_Observados_v4!O20<>"",(2020-2018-1)<=Metodologia_v4!$B$12),Dados_Observados_v4!M20+(Dados_Observados_v4!O20-Dados_Observados_v4!M20)*(2019-2018)/(2020-2018),IF(AND(Dados_Observados_v4!M20<>"",(2019-2018)<=Metodologia_v4!$B$13),Dados_Observados_v4!M20,IF(AND(Dados_Observados_v4!O20<>"",(2020-2019)<=Metodologia_v4!$B$14),Dados_Observados_v4!O20,"")))) | O20: =IF(Dados_Observados_v4!O20<>"",Dados_Observados_v4!O20,IF(AND(Dados_Observados_v4!N20<>"",Dados_Observados_v4!P20<>"",(2021-2019-1)<=Metodologia_v4!$B$12),Dados_Observados_v4!N20+(Dados_Observados_v4!P20-Dados_Observados_v4!N20)*(2020-2019)/(2021-2019),IF(AND(Dados_Observados_v4!N20<>"",(2020-2019)<=Metodologia_v4!$B$13),Dados_Observados_v4!N20,IF(AND(Dados_Observados_v4!P20<>"",(2021-2020)<=Metodologia_v4!$B$14),Dados_Observados_v4!P20,"")))) | P20: =IF(Dados_Observados_v4!P20<>"",Dados_Observados_v4!P20,IF(AND(Dados_Observados_v4!O20<>"",Dados_Observados_v4!Q20<>"",(2022-2020-1)<=Metodologia_v4!$B$12),Dados_Observados_v4!O20+(Dados_Observados_v4!Q20-Dados_Observados_v4!O20)*(2021-2020)/(2022-2020),IF(AND(Dados_Observados_v4!O20<>"",(2021-2020)<=Metodologia_v4!$B$13),Dados_Observados_v4!O20,IF(AND(Dados_Observados_v4!Q20<>"",(2022-2021)<=Metodologia_v4!$B$14),Dados_Observados_v4!Q20,"")))) | Q20: =IF(Dados_Observados_v4!Q20<>"",Dados_Observados_v4!Q20,IF(AND(Dados_Observados_v4!P20<>"",Dados_Observados_v4!R20<>"",(2023-2021-1)<=Metodologia_v4!$B$12),Dados_Observados_v4!P20+(Dados_Observados_v4!R20-Dados_Observados_v4!P20)*(2022-2021)/(2023-2021),IF(AND(Dados_Observados_v4!P20<>"",(2022-2021)<=Metodologia_v4!$B$13),Dados_Observados_v4!P20,IF(AND(Dados_Observados_v4!R20<>"",(2023-2022)<=Metodologia_v4!$B$14),Dados_Observados_v4!R20,"")))) | R20: =IF(Dados_Observados_v4!R20<>"",Dados_Observados_v4!R20,IF(AND(Dados_Observados_v4!Q20<>"",Dados_Observados_v4!S20<>"",(2024-2022-1)<=Metodologia_v4!$B$12),Dados_Observados_v4!Q20+(Dados_Observados_v4!S20-Dados_Observados_v4!Q20)*(2023-2022)/(2024-2022),IF(AND(Dados_Observados_v4!Q20<>"",(2023-2022)<=Metodologia_v4!$B$13),Dados_Observados_v4!Q20,IF(AND(Dados_Observados_v4!S20<>"",(2024-2023)<=Metodologia_v4!$B$14),Dados_Observados_v4!S20,"")))) | S20: =IF(Dados_Observados_v4!S20<>"",Dados_Observados_v4!S20,IF(AND(Dados_Observados_v4!R20<>"",(2024-2023)<=Metodologia_v4!$B$13),Dados_Observados_v4!R20,"")) | T20: =IF(Dados_Observados_v4!T20<>"",Dados_Observados_v4!T20,IF(AND(Dados_Observados_v4!S20<>"",(2025-2024)<=Metodologia_v4!$B$13),Dados_Observados_v4!S20,""))
A21: HUM03 | B21: 3. Capital Humano | C21: Alfabetização adulta | D21: Banco Mundial/UNESCO | E21: SE.ADT.LITR.ZS | F21: Fonte Banco Mundial API/CSV | G21: 2/11 | H21: 2023 | I21: Referenciado pelas regras de Metodologia_v4 | J21: =IF(Dados_Observados_v4!J21<>"",Dados_Observados_v4!J21,IF(AND(Dados_Observados_v4!R21<>"",(2023-2015)<=Metodologia_v4!$B$14),Dados_Observados_v4!R21,"")) | K21: =IF(Dados_Observados_v4!K21<>"",Dados_Observados_v4!K21,IF(AND(Dados_Observados_v4!J21<>"",Dados_Observados_v4!R21<>"",(2023-2015-1)<=Metodologia_v4!$B$12),Dados_Observados_v4!J21+(Dados_Observados_v4!R21-Dados_Observados_v4!J21)*(2016-2015)/(2023-2015),IF(AND(Dados_Observados_v4!J21<>"",(2016-2015)<=Metodologia_v4!$B$13),Dados_Observados_v4!J21,IF(AND(Dados_Observados_v4!R21<>"",(2023-2016)<=Metodologia_v4!$B$14),Dados_Observados_v4!R21,"")))) | L21: =IF(Dados_Observados_v4!L21<>"",Dados_Observados_v4!L21,IF(AND(Dados_Observados_v4!J21<>"",Dados_Observados_v4!R21<>"",(2023-2015-1)<=Metodologia_v4!$B$12),Dados_Observados_v4!J21+(Dados_Observados_v4!R21-Dados_Observados_v4!J21)*(2017-2015)/(2023-2015),IF(AND(Dados_Observados_v4!J21<>"",(2017-2015)<=Metodologia_v4!$B$13),Dados_Observados_v4!J21,IF(AND(Dados_Observados_v4!R21<>"",(2023-2017)<=Metodologia_v4!$B$14),Dados_Observados_v4!R21,"")))) | M21: =IF(Dados_Observados_v4!M21<>"",Dados_Observados_v4!M21,IF(AND(Dados_Observados_v4!J21<>"",Dados_Observados_v4!R21<>"",(2023-2015-1)<=Metodologia_v4!$B$12),Dados_Observados_v4!J21+(Dados_Observados_v4!R21-Dados_Observados_v4!J21)*(2018-2015)/(2023-2015),IF(AND(Dados_Observados_v4!J21<>"",(2018-2015)<=Metodologia_v4!$B$13),Dados_Observados_v4!J21,IF(AND(Dados_Observados_v4!R21<>"",(2023-2018)<=Metodologia_v4!$B$14),Dados_Observados_v4!R21,"")))) | N21: =IF(Dados_Observados_v4!N21<>"",Dados_Observados_v4!N21,IF(AND(Dados_Observados_v4!J21<>"",Dados_Observados_v4!R21<>"",(2023-2015-1)<=Metodologia_v4!$B$12),Dados_Observados_v4!J21+(Dados_Observados_v4!R21-Dados_Observados_v4!J21)*(2019-2015)/(2023-2015),IF(AND(Dados_Observados_v4!J21<>"",(2019-2015)<=Metodologia_v4!$B$13),Dados_Observados_v4!J21,IF(AND(Dados_Observados_v4!R21<>"",(2023-2019)<=Metodologia_v4!$B$14),Dados_Observados_v4!R21,"")))) | O21: =IF(Dados_Observados_v4!O21<>"",Dados_Observados_v4!O21,IF(AND(Dados_Observados_v4!J21<>"",Dados_Observados_v4!R21<>"",(2023-2015-1)<=Metodologia_v4!$B$12),Dados_Observados_v4!J21+(Dados_Observados_v4!R21-Dados_Observados_v4!J21)*(2020-2015)/(2023-2015),IF(AND(Dados_Observados_v4!J21<>"",(2020-2015)<=Metodologia_v4!$B$13),Dados_Observados_v4!J21,IF(AND(Dados_Observados_v4!R21<>"",(2023-2020)<=Metodologia_v4!$B$14),Dados_Observados_v4!R21,"")))) | P21: =IF(Dados_Observados_v4!P21<>"",Dados_Observados_v4!P21,IF(AND(Dados_Observados_v4!J21<>"",Dados_Observados_v4!R21<>"",(2023-2015-1)<=Metodologia_v4!$B$12),Dados_Observados_v4!J21+(Dados_Observados_v4!R21-Dados_Observados_v4!J21)*(2021-2015)/(2023-2015),IF(AND(Dados_Observados_v4!J21<>"",(2021-2015)<=Metodologia_v4!$B$13),Dados_Observados_v4!J21,IF(AND(Dados_Observados_v4!R21<>"",(2023-2021)<=Metodologia_v4!$B$14),Dados_Observados_v4!R21,"")))) | Q21: =IF(Dados_Observados_v4!Q21<>"",Dados_Observados_v4!Q21,IF(AND(Dados_Observados_v4!J21<>"",Dados_Observados_v4!R21<>"",(2023-2015-1)<=Metodologia_v4!$B$12),Dados_Observados_v4!J21+(Dados_Observados_v4!R21-Dados_Observados_v4!J21)*(2022-2015)/(2023-2015),IF(AND(Dados_Observados_v4!J21<>"",(2022-2015)<=Metodologia_v4!$B$13),Dados_Observados_v4!J21,IF(AND(Dados_Observados_v4!R21<>"",(2023-2022)<=Metodologia_v4!$B$14),Dados_Observados_v4!R21,"")))) | R21: =IF(Dados_Observados_v4!R21<>"",Dados_Observados_v4!R21,IF(AND(Dados_Observados_v4!J21<>"",(2023-2015)<=Metodologia_v4!$B$13),Dados_Observados_v4!J21,"")) | S21: =IF(Dados_Observados_v4!S21<>"",Dados_Observados_v4!S21,IF(AND(Dados_Observados_v4!R21<>"",(2024-2023)<=Metodologia_v4!$B$13),Dados_Observados_v4!R21,"")) | T21: =IF(Dados_Observados_v4!T21<>"",Dados_Observados_v4!T21,IF(AND(Dados_Observados_v4!R21<>"",(2025-2023)<=Metodologia_v4!$B$13),Dados_Observados_v4!R21,""))
A22: HUM04 | B22: 3. Capital Humano | C22: Conclusão do ensino primário | D22: Banco Mundial/UNESCO | E22: SE.PRM.CMPT.ZS | F22: Fonte Banco Mundial API/CSV | G22: 2/11 | H22: 2023 | I22: Referenciado pelas regras de Metodologia_v4 | J22: =IF(Dados_Observados_v4!J22<>"",Dados_Observados_v4!J22,IF(AND(Dados_Observados_v4!P22<>"",(2021-2015)<=Metodologia_v4!$B$14),Dados_Observados_v4!P22,"")) | K22: =IF(Dados_Observados_v4!K22<>"",Dados_Observados_v4!K22,IF(AND(Dados_Observados_v4!P22<>"",(2021-2016)<=Metodologia_v4!$B$14),Dados_Observados_v4!P22,"")) | L22: =IF(Dados_Observados_v4!L22<>"",Dados_Observados_v4!L22,IF(AND(Dados_Observados_v4!P22<>"",(2021-2017)<=Metodologia_v4!$B$14),Dados_Observados_v4!P22,"")) | M22: =IF(Dados_Observados_v4!M22<>"",Dados_Observados_v4!M22,IF(AND(Dados_Observados_v4!P22<>"",(2021-2018)<=Metodologia_v4!$B$14),Dados_Observados_v4!P22,"")) | N22: =IF(Dados_Observados_v4!N22<>"",Dados_Observados_v4!N22,IF(AND(Dados_Observados_v4!P22<>"",(2021-2019)<=Metodologia_v4!$B$14),Dados_Observados_v4!P22,"")) | O22: =IF(Dados_Observados_v4!O22<>"",Dados_Observados_v4!O22,IF(AND(Dados_Observados_v4!P22<>"",(2021-2020)<=Metodologia_v4!$B$14),Dados_Observados_v4!P22,"")) | P22: =IF(Dados_Observados_v4!P22<>"",Dados_Observados_v4!P22,IF(AND(Dados_Observados_v4!R22<>"",(2023-2021)<=Metodologia_v4!$B$14),Dados_Observados_v4!R22,"")) | Q22: =IF(Dados_Observados_v4!Q22<>"",Dados_Observados_v4!Q22,IF(AND(Dados_Observados_v4!P22<>"",Dados_Observados_v4!R22<>"",(2023-2021-1)<=Metodologia_v4!$B$12),Dados_Observados_v4!P22+(Dados_Observados_v4!R22-Dados_Observados_v4!P22)*(2022-2021)/(2023-2021),IF(AND(Dados_Observados_v4!P22<>"",(2022-2021)<=Metodologia_v4!$B$13),Dados_Observados_v4!P22,IF(AND(Dados_Observados_v4!R22<>"",(2023-2022)<=Metodologia_v4!$B$14),Dados_Observados_v4!R22,"")))) | R22: =IF(Dados_Observados_v4!R22<>"",Dados_Observados_v4!R22,IF(AND(Dados_Observados_v4!P22<>"",(2023-2021)<=Metodologia_v4!$B$13),Dados_Observados_v4!P22,"")) | S22: =IF(Dados_Observados_v4!S22<>"",Dados_Observados_v4!S22,IF(AND(Dados_Observados_v4!R22<>"",(2024-2023)<=Metodologia_v4!$B$13),Dados_Observados_v4!R22,"")) | T22: =IF(Dados_Observados_v4!T22<>"",Dados_Observados_v4!T22,IF(AND(Dados_Observados_v4!R22<>"",(2025-2023)<=Metodologia_v4!$B$13),Dados_Observados_v4!R22,""))
A23: HUM05 | B23: 3. Capital Humano | C23: Matrícula no ensino secundário | D23: Banco Mundial/UNESCO | E23: SE.SEC.ENRR | F23: Fonte Banco Mundial API/CSV | G23: 3/11 | H23: 2023 | I23: Referenciado pelas regras de Metodologia_v4 | J23: =IF(Dados_Observados_v4!J23<>"",Dados_Observados_v4!J23,IF(AND(Dados_Observados_v4!K23<>"",(2016-2015)<=Metodologia_v4!$B$14),Dados_Observados_v4!K23,"")) | K23: =IF(Dados_Observados_v4!K23<>"",Dados_Observados_v4!K23,IF(AND(Dados_Observados_v4!P23<>"",(2021-2016)<=Metodologia_v4!$B$14),Dados_Observados_v4!P23,"")) | L23: =IF(Dados_Observados_v4!L23<>"",Dados_Observados_v4!L23,IF(AND(Dados_Observados_v4!K23<>"",Dados_Observados_v4!P23<>"",(2021-2016-1)<=Metodologia_v4!$B$12),Dados_Observados_v4!K23+(Dados_Observados_v4!P23-Dados_Observados_v4!K23)*(2017-2016)/(2021-2016),IF(AND(Dados_Observados_v4!K23<>"",(2017-2016)<=Metodologia_v4!$B$13),Dados_Observados_v4!K23,IF(AND(Dados_Observados_v4!P23<>"",(2021-2017)<=Metodologia_v4!$B$14),Dados_Observados_v4!P23,"")))) | M23: =IF(Dados_Observados_v4!M23<>"",Dados_Observados_v4!M23,IF(AND(Dados_Observados_v4!K23<>"",Dados_Observados_v4!P23<>"",(2021-2016-1)<=Metodologia_v4!$B$12),Dados_Observados_v4!K23+(Dados_Observados_v4!P23-Dados_Observados_v4!K23)*(2018-2016)/(2021-2016),IF(AND(Dados_Observados_v4!K23<>"",(2018-2016)<=Metodologia_v4!$B$13),Dados_Observados_v4!K23,IF(AND(Dados_Observados_v4!P23<>"",(2021-2018)<=Metodologia_v4!$B$14),Dados_Observados_v4!P23,"")))) | N23: =IF(Dados_Observados_v4!N23<>"",Dados_Observados_v4!N23,IF(AND(Dados_Observados_v4!K23<>"",Dados_Observados_v4!P23<>"",(2021-2016-1)<=Metodologia_v4!$B$12),Dados_Observados_v4!K23+(Dados_Observados_v4!P23-Dados_Observados_v4!K23)*(2019-2016)/(2021-2016),IF(AND(Dados_Observados_v4!K23<>"",(2019-2016)<=Metodologia_v4!$B$13),Dados_Observados_v4!K23,IF(AND(Dados_Observados_v4!P23<>"",(2021-2019)<=Metodologia_v4!$B$14),Dados_Observados_v4!P23,"")))) | O23: =IF(Dados_Observados_v4!O23<>"",Dados_Observados_v4!O23,IF(AND(Dados_Observados_v4!K23<>"",Dados_Observados_v4!P23<>"",(2021-2016-1)<=Metodologia_v4!$B$12),Dados_Observados_v4!K23+(Dados_Observados_v4!P23-Dados_Observados_v4!K23)*(2020-2016)/(2021-2016),IF(AND(Dados_Observados_v4!K23<>"",(2020-2016)<=Metodologia_v4!$B$13),Dados_Observados_v4!K23,IF(AND(Dados_Observados_v4!P23<>"",(2021-2020)<=Metodologia_v4!$B$14),Dados_Observados_v4!P23,"")))) | P23: =IF(Dados_Observados_v4!P23<>"",Dados_Observados_v4!P23,IF(AND(Dados_Observados_v4!K23<>"",Dados_Observados_v4!R23<>"",(2023-2016-1)<=Metodologia_v4!$B$12),Dados_Observados_v4!K23+(Dados_Observados_v4!R23-Dados_Observados_v4!K23)*(2021-2016)/(2023-2016),IF(AND(Dados_Observados_v4!K23<>"",(2021-2016)<=Metodologia_v4!$B$13),Dados_Observados_v4!K23,IF(AND(Dados_Observados_v4!R23<>"",(2023-2021)<=Metodologia_v4!$B$14),Dados_Observados_v4!R23,"")))) | Q23: =IF(Dados_Observados_v4!Q23<>"",Dados_Observados_v4!Q23,IF(AND(Dados_Observados_v4!P23<>"",Dados_Observados_v4!R23<>"",(2023-2021-1)<=Metodologia_v4!$B$12),Dados_Observados_v4!P23+(Dados_Observados_v4!R23-Dados_Observados_v4!P23)*(2022-2021)/(2023-2021),IF(AND(Dados_Observados_v4!P23<>"",(2022-2021)<=Metodologia_v4!$B$13),Dados_Observados_v4!P23,IF(AND(Dados_Observados_v4!R23<>"",(2023-2022)<=Metodologia_v4!$B$14),Dados_Observados_v4!R23,"")))) | R23: =IF(Dados_Observados_v4!R23<>"",Dados_Observados_v4!R23,IF(AND(Dados_Observados_v4!P23<>"",(2023-2021)<=Metodologia_v4!$B$13),Dados_Observados_v4!P23,"")) | S23: =IF(Dados_Observados_v4!S23<>"",Dados_Observados_v4!S23,IF(AND(Dados_Observados_v4!R23<>"",(2024-2023)<=Metodologia_v4!$B$13),Dados_Observados_v4!R23,"")) | T23: =IF(Dados_Observados_v4!T23<>"",Dados_Observados_v4!T23,IF(AND(Dados_Observados_v4!R23<>"",(2025-2023)<=Metodologia_v4!$B$13),Dados_Observados_v4!R23,""))
A24: HUM06 | B24: 3. Capital Humano | C24: Despesa pública em educação | D24: Banco Mundial/UNESCO | E24: SE.XPD.TOTL.GD.ZS | F24: Fonte Banco Mundial API/CSV | G24: 9/11 | H24: 2023 | I24: Referenciado pelas regras de Metodologia_v4 | J24: =IF(Dados_Observados_v4!J24<>"",Dados_Observados_v4!J24,IF(AND(Dados_Observados_v4!K24<>"",(2016-2015)<=Metodologia_v4!$B$14),Dados_Observados_v4!K24,"")) | K24: =IF(Dados_Observados_v4!K24<>"",Dados_Observados_v4!K24,IF(AND(Dados_Observados_v4!J24<>"",Dados_Observados_v4!L24<>"",(2017-2015-1)<=Metodologia_v4!$B$12),Dados_Observados_v4!J24+(Dados_Observados_v4!L24-Dados_Observados_v4!J24)*(2016-2015)/(2017-2015),IF(AND(Dados_Observados_v4!J24<>"",(2016-2015)<=Metodologia_v4!$B$13),Dados_Observados_v4!J24,IF(AND(Dados_Observados_v4!L24<>"",(2017-2016)<=Metodologia_v4!$B$14),Dados_Observados_v4!L24,"")))) | L24: =IF(Dados_Observados_v4!L24<>"",Dados_Observados_v4!L24,IF(AND(Dados_Observados_v4!K24<>"",Dados_Observados_v4!M24<>"",(2018-2016-1)<=Metodologia_v4!$B$12),Dados_Observados_v4!K24+(Dados_Observados_v4!M24-Dados_Observados_v4!K24)*(2017-2016)/(2018-2016),IF(AND(Dados_Observados_v4!K24<>"",(2017-2016)<=Metodologia_v4!$B$13),Dados_Observados_v4!K24,IF(AND(Dados_Observados_v4!M24<>"",(2018-2017)<=Metodologia_v4!$B$14),Dados_Observados_v4!M24,"")))) | M24: =IF(Dados_Observados_v4!M24<>"",Dados_Observados_v4!M24,IF(AND(Dados_Observados_v4!L24<>"",Dados_Observados_v4!N24<>"",(2019-2017-1)<=Metodologia_v4!$B$12),Dados_Observados_v4!L24+(Dados_Observados_v4!N24-Dados_Observados_v4!L24)*(2018-2017)/(2019-2017),IF(AND(Dados_Observados_v4!L24<>"",(2018-2017)<=Metodologia_v4!$B$13),Dados_Observados_v4!L24,IF(AND(Dados_Observados_v4!N24<>"",(2019-2018)<=Metodologia_v4!$B$14),Dados_Observados_v4!N24,"")))) | N24: =IF(Dados_Observados_v4!N24<>"",Dados_Observados_v4!N24,IF(AND(Dados_Observados_v4!M24<>"",Dados_Observados_v4!O24<>"",(2020-2018-1)<=Metodologia_v4!$B$12),Dados_Observados_v4!M24+(Dados_Observados_v4!O24-Dados_Observados_v4!M24)*(2019-2018)/(2020-2018),IF(AND(Dados_Observados_v4!M24<>"",(2019-2018)<=Metodologia_v4!$B$13),Dados_Observados_v4!M24,IF(AND(Dados_Observados_v4!O24<>"",(2020-2019)<=Metodologia_v4!$B$14),Dados_Observados_v4!O24,"")))) | O24: =IF(Dados_Observados_v4!O24<>"",Dados_Observados_v4!O24,IF(AND(Dados_Observados_v4!N24<>"",Dados_Observados_v4!P24<>"",(2021-2019-1)<=Metodologia_v4!$B$12),Dados_Observados_v4!N24+(Dados_Observados_v4!P24-Dados_Observados_v4!N24)*(2020-2019)/(2021-2019),IF(AND(Dados_Observados_v4!N24<>"",(2020-2019)<=Metodologia_v4!$B$13),Dados_Observados_v4!N24,IF(AND(Dados_Observados_v4!P24<>"",(2021-2020)<=Metodologia_v4!$B$14),Dados_Observados_v4!P24,"")))) | P24: =IF(Dados_Observados_v4!P24<>"",Dados_Observados_v4!P24,IF(AND(Dados_Observados_v4!O24<>"",Dados_Observados_v4!Q24<>"",(2022-2020-1)<=Metodologia_v4!$B$12),Dados_Observados_v4!O24+(Dados_Observados_v4!Q24-Dados_Observados_v4!O24)*(2021-2020)/(2022-2020),IF(AND(Dados_Observados_v4!O24<>"",(2021-2020)<=Metodologia_v4!$B$13),Dados_Observados_v4!O24,IF(AND(Dados_Observados_v4!Q24<>"",(2022-2021)<=Metodologia_v4!$B$14),Dados_Observados_v4!Q24,"")))) | Q24: =IF(Dados_Observados_v4!Q24<>"",Dados_Observados_v4!Q24,IF(AND(Dados_Observados_v4!P24<>"",Dados_Observados_v4!R24<>"",(2023-2021-1)<=Metodologia_v4!$B$12),Dados_Observados_v4!P24+(Dados_Observados_v4!R24-Dados_Observados_v4!P24)*(2022-2021)/(2023-2021),IF(AND(Dados_Observados_v4!P24<>"",(2022-2021)<=Metodologia_v4!$B$13),Dados_Observados_v4!P24,IF(AND(Dados_Observados_v4!R24<>"",(2023-2022)<=Metodologia_v4!$B$14),Dados_Observados_v4!R24,"")))) | R24: =IF(Dados_Observados_v4!R24<>"",Dados_Observados_v4!R24,IF(AND(Dados_Observados_v4!Q24<>"",(2023-2022)<=Metodologia_v4!$B$13),Dados_Observados_v4!Q24,"")) | S24: =IF(Dados_Observados_v4!S24<>"",Dados_Observados_v4!S24,IF(AND(Dados_Observados_v4!R24<>"",(2024-2023)<=Metodologia_v4!$B$13),Dados_Observados_v4!R24,"")) | T24: =IF(Dados_Observados_v4!T24<>"",Dados_Observados_v4!T24,IF(AND(Dados_Observados_v4!R24<>"",(2025-2023)<=Metodologia_v4!$B$13),Dados_Observados_v4!R24,""))
A25: HUM07 | B25: 3. Capital Humano | C25: Mortalidade infantil | D25: Banco Mundial/WDI | E25: SP.DYN.IMRT.IN | F25: Fonte Banco Mundial API/CSV | G25: 10/11 | H25: 2024 | I25: Referenciado pelas regras de Metodologia_v4 | J25: =IF(Dados_Observados_v4!J25<>"",Dados_Observados_v4!J25,IF(AND(Dados_Observados_v4!K25<>"",(2016-2015)<=Metodologia_v4!$B$14),Dados_Observados_v4!K25,"")) | K25: =IF(Dados_Observados_v4!K25<>"",Dados_Observados_v4!K25,IF(AND(Dados_Observados_v4!J25<>"",Dados_Observados_v4!L25<>"",(2017-2015-1)<=Metodologia_v4!$B$12),Dados_Observados_v4!J25+(Dados_Observados_v4!L25-Dados_Observados_v4!J25)*(2016-2015)/(2017-2015),IF(AND(Dados_Observados_v4!J25<>"",(2016-2015)<=Metodologia_v4!$B$13),Dados_Observados_v4!J25,IF(AND(Dados_Observados_v4!L25<>"",(2017-2016)<=Metodologia_v4!$B$14),Dados_Observados_v4!L25,"")))) | L25: =IF(Dados_Observados_v4!L25<>"",Dados_Observados_v4!L25,IF(AND(Dados_Observados_v4!K25<>"",Dados_Observados_v4!M25<>"",(2018-2016-1)<=Metodologia_v4!$B$12),Dados_Observados_v4!K25+(Dados_Observados_v4!M25-Dados_Observados_v4!K25)*(2017-2016)/(2018-2016),IF(AND(Dados_Observados_v4!K25<>"",(2017-2016)<=Metodologia_v4!$B$13),Dados_Observados_v4!K25,IF(AND(Dados_Observados_v4!M25<>"",(2018-2017)<=Metodologia_v4!$B$14),Dados_Observados_v4!M25,"")))) | M25: =IF(Dados_Observados_v4!M25<>"",Dados_Observados_v4!M25,IF(AND(Dados_Observados_v4!L25<>"",Dados_Observados_v4!N25<>"",(2019-2017-1)<=Metodologia_v4!$B$12),Dados_Observados_v4!L25+(Dados_Observados_v4!N25-Dados_Observados_v4!L25)*(2018-2017)/(2019-2017),IF(AND(Dados_Observados_v4!L25<>"",(2018-2017)<=Metodologia_v4!$B$13),Dados_Observados_v4!L25,IF(AND(Dados_Observados_v4!N25<>"",(2019-2018)<=Metodologia_v4!$B$14),Dados_Observados_v4!N25,"")))) | N25: =IF(Dados_Observados_v4!N25<>"",Dados_Observados_v4!N25,IF(AND(Dados_Observados_v4!M25<>"",Dados_Observados_v4!O25<>"",(2020-2018-1)<=Metodologia_v4!$B$12),Dados_Observados_v4!M25+(Dados_Observados_v4!O25-Dados_Observados_v4!M25)*(2019-2018)/(2020-2018),IF(AND(Dados_Observados_v4!M25<>"",(2019-2018)<=Metodologia_v4!$B$13),Dados_Observados_v4!M25,IF(AND(Dados_Observados_v4!O25<>"",(2020-2019)<=Metodologia_v4!$B$14),Dados_Observados_v4!O25,"")))) | O25: =IF(Dados_Observados_v4!O25<>"",Dados_Observados_v4!O25,IF(AND(Dados_Observados_v4!N25<>"",Dados_Observados_v4!P25<>"",(2021-2019-1)<=Metodologia_v4!$B$12),Dados_Observados_v4!N25+(Dados_Observados_v4!P25-Dados_Observados_v4!N25)*(2020-2019)/(2021-2019),IF(AND(Dados_Observados_v4!N25<>"",(2020-2019)<=Metodologia_v4!$B$13),Dados_Observados_v4!N25,IF(AND(Dados_Observados_v4!P25<>"",(2021-2020)<=Metodologia_v4!$B$14),Dados_Observados_v4!P25,"")))) | P25: =IF(Dados_Observados_v4!P25<>"",Dados_Observados_v4!P25,IF(AND(Dados_Observados_v4!O25<>"",Dados_Observados_v4!Q25<>"",(2022-2020-1)<=Metodologia_v4!$B$12),Dados_Observados_v4!O25+(Dados_Observados_v4!Q25-Dados_Observados_v4!O25)*(2021-2020)/(2022-2020),IF(AND(Dados_Observados_v4!O25<>"",(2021-2020)<=Metodologia_v4!$B$13),Dados_Observados_v4!O25,IF(AND(Dados_Observados_v4!Q25<>"",(2022-2021)<=Metodologia_v4!$B$14),Dados_Observados_v4!Q25,"")))) | Q25: =IF(Dados_Observados_v4!Q25<>"",Dados_Observados_v4!Q25,IF(AND(Dados_Observados_v4!P25<>"",Dados_Observados_v4!R25<>"",(2023-2021-1)<=Metodologia_v4!$B$12),Dados_Observados_v4!P25+(Dados_Observados_v4!R25-Dados_Observados_v4!P25)*(2022-2021)/(2023-2021),IF(AND(Dados_Observados_v4!P25<>"",(2022-2021)<=Metodologia_v4!$B$13),Dados_Observados_v4!P25,IF(AND(Dados_Observados_v4!R25<>"",(2023-2022)<=Metodologia_v4!$B$14),Dados_Observados_v4!R25,"")))) | R25: =IF(Dados_Observados_v4!R25<>"",Dados_Observados_v4!R25,IF(AND(Dados_Observados_v4!Q25<>"",Dados_Observados_v4!S25<>"",(2024-2022-1)<=Metodologia_v4!$B$12),Dados_Observados_v4!Q25+(Dados_Observados_v4!S25-Dados_Observados_v4!Q25)*(2023-2022)/(2024-2022),IF(AND(Dados_Observados_v4!Q25<>"",(2023-2022)<=Metodologia_v4!$B$13),Dados_Observados_v4!Q25,IF(AND(Dados_Observados_v4!S25<>"",(2024-2023)<=Metodologia_v4!$B$14),Dados_Observados_v4!S25,"")))) | S25: =IF(Dados_Observados_v4!S25<>"",Dados_Observados_v4!S25,IF(AND(Dados_Observados_v4!R25<>"",(2024-2023)<=Metodologia_v4!$B$13),Dados_Observados_v4!R25,"")) | T25: =IF(Dados_Observados_v4!T25<>"",Dados_Observados_v4!T25,IF(AND(Dados_Observados_v4!S25<>"",(2025-2024)<=Metodologia_v4!$B$13),Dados_Observados_v4!S25,""))
A26: INC01 | B26: 4. Inclusão Social e Protecção | C26: Pobreza internacional | D26: Banco Mundial/PIP | E26: SI.POV.DDAY | F26: Fonte Banco Mundial API/CSV | G26: 1/11 | H26: 2018 | I26: Referenciado pelas regras de Metodologia_v4 | J26: =IF(Dados_Observados_v4!J26<>"",Dados_Observados_v4!J26,IF(AND(Dados_Observados_v4!M26<>"",(2018-2015)<=Metodologia_v4!$B$14),Dados_Observados_v4!M26,"")) | K26: =IF(Dados_Observados_v4!K26<>"",Dados_Observados_v4!K26,IF(AND(Dados_Observados_v4!M26<>"",(2018-2016)<=Metodologia_v4!$B$14),Dados_Observados_v4!M26,"")) | L26: =IF(Dados_Observados_v4!L26<>"",Dados_Observados_v4!L26,IF(AND(Dados_Observados_v4!M26<>"",(2018-2017)<=Metodologia_v4!$B$14),Dados_Observados_v4!M26,"")) | M26: =IF(Dados_Observados_v4!M26<>"",Dados_Observados_v4!M26,"") | N26: =IF(Dados_Observados_v4!N26<>"",Dados_Observados_v4!N26,IF(AND(Dados_Observados_v4!M26<>"",(2019-2018)<=Metodologia_v4!$B$13),Dados_Observados_v4!M26,"")) | O26: =IF(Dados_Observados_v4!O26<>"",Dados_Observados_v4!O26,IF(AND(Dados_Observados_v4!M26<>"",(2020-2018)<=Metodologia_v4!$B$13),Dados_Observados_v4!M26,"")) | P26: =IF(Dados_Observados_v4!P26<>"",Dados_Observados_v4!P26,IF(AND(Dados_Observados_v4!M26<>"",(2021-2018)<=Metodologia_v4!$B$13),Dados_Observados_v4!M26,"")) | Q26: =IF(Dados_Observados_v4!Q26<>"",Dados_Observados_v4!Q26,IF(AND(Dados_Observados_v4!M26<>"",(2022-2018)<=Metodologia_v4!$B$13),Dados_Observados_v4!M26,"")) | R26: =IF(Dados_Observados_v4!R26<>"",Dados_Observados_v4!R26,IF(AND(Dados_Observados_v4!M26<>"",(2023-2018)<=Metodologia_v4!$B$13),Dados_Observados_v4!M26,"")) | S26: =IF(Dados_Observados_v4!S26<>"",Dados_Observados_v4!S26,IF(AND(Dados_Observados_v4!M26<>"",(2024-2018)<=Metodologia_v4!$B$13),Dados_Observados_v4!M26,"")) | T26: =IF(Dados_Observados_v4!T26<>"",Dados_Observados_v4!T26,IF(AND(Dados_Observados_v4!M26<>"",(2025-2018)<=Metodologia_v4!$B$13),Dados_Observados_v4!M26,""))
A27: INC02 | B27: 4. Inclusão Social e Protecção | C27: Índice de Gini | D27: Banco Mundial/PIP | E27: SI.POV.GINI | F27: Fonte Banco Mundial API/CSV | G27: 1/11 | H27: 2018 | I27: Referenciado pelas regras de Metodologia_v4 | J27: =IF(Dados_Observados_v4!J27<>"",Dados_Observados_v4!J27,IF(AND(Dados_Observados_v4!M27<>"",(2018-2015)<=Metodologia_v4!$B$14),Dados_Observados_v4!M27,"")) | K27: =IF(Dados_Observados_v4!K27<>"",Dados_Observados_v4!K27,IF(AND(Dados_Observados_v4!M27<>"",(2018-2016)<=Metodologia_v4!$B$14),Dados_Observados_v4!M27,"")) | L27: =IF(Dados_Observados_v4!L27<>"",Dados_Observados_v4!L27,IF(AND(Dados_Observados_v4!M27<>"",(2018-2017)<=Metodologia_v4!$B$14),Dados_Observados_v4!M27,"")) | M27: =IF(Dados_Observados_v4!M27<>"",Dados_Observados_v4!M27,"") | N27: =IF(Dados_Observados_v4!N27<>"",Dados_Observados_v4!N27,IF(AND(Dados_Observados_v4!M27<>"",(2019-2018)<=Metodologia_v4!$B$13),Dados_Observados_v4!M27,"")) | O27: =IF(Dados_Observados_v4!O27<>"",Dados_Observados_v4!O27,IF(AND(Dados_Observados_v4!M27<>"",(2020-2018)<=Metodologia_v4!$B$13),Dados_Observados_v4!M27,"")) | P27: =IF(Dados_Observados_v4!P27<>"",Dados_Observados_v4!P27,IF(AND(Dados_Observados_v4!M27<>"",(2021-2018)<=Metodologia_v4!$B$13),Dados_Observados_v4!M27,"")) | Q27: =IF(Dados_Observados_v4!Q27<>"",Dados_Observados_v4!Q27,IF(AND(Dados_Observados_v4!M27<>"",(2022-2018)<=Metodologia_v4!$B$13),Dados_Observados_v4!M27,"")) | R27: =IF(Dados_Observados_v4!R27<>"",Dados_Observados_v4!R27,IF(AND(Dados_Observados_v4!M27<>"",(2023-2018)<=Metodologia_v4!$B$13),Dados_Observados_v4!M27,"")) | S27: =IF(Dados_Observados_v4!S27<>"",Dados_Observados_v4!S27,IF(AND(Dados_Observados_v4!M27<>"",(2024-2018)<=Metodologia_v4!$B$13),Dados_Observados_v4!M27,"")) | T27: =IF(Dados_Observados_v4!T27<>"",Dados_Observados_v4!T27,IF(AND(Dados_Observados_v4!M27<>"",(2025-2018)<=Metodologia_v4!$B$13),Dados_Observados_v4!M27,""))
A28: INC03 | B28: 4. Inclusão Social e Protecção | C28: Rendimento dos 20% mais pobres | D28: Banco Mundial/PIP | E28: SI.DST.FRST.20 | F28: Fonte Banco Mundial API/CSV | G28: 1/11 | H28: 2018 | I28: Referenciado pelas regras de Metodologia_v4 | J28: =IF(Dados_Observados_v4!J28<>"",Dados_Observados_v4!J28,IF(AND(Dados_Observados_v4!M28<>"",(2018-2015)<=Metodologia_v4!$B$14),Dados_Observados_v4!M28,"")) | K28: =IF(Dados_Observados_v4!K28<>"",Dados_Observados_v4!K28,IF(AND(Dados_Observados_v4!M28<>"",(2018-2016)<=Metodologia_v4!$B$14),Dados_Observados_v4!M28,"")) | L28: =IF(Dados_Observados_v4!L28<>"",Dados_Observados_v4!L28,IF(AND(Dados_Observados_v4!M28<>"",(2018-2017)<=Metodologia_v4!$B$14),Dados_Observados_v4!M28,"")) | M28: =IF(Dados_Observados_v4!M28<>"",Dados_Observados_v4!M28,"") | N28: =IF(Dados_Observados_v4!N28<>"",Dados_Observados_v4!N28,IF(AND(Dados_Observados_v4!M28<>"",(2019-2018)<=Metodologia_v4!$B$13),Dados_Observados_v4!M28,"")) | O28: =IF(Dados_Observados_v4!O28<>"",Dados_Observados_v4!O28,IF(AND(Dados_Observados_v4!M28<>"",(2020-2018)<=Metodologia_v4!$B$13),Dados_Observados_v4!M28,"")) | P28: =IF(Dados_Observados_v4!P28<>"",Dados_Observados_v4!P28,IF(AND(Dados_Observados_v4!M28<>"",(2021-2018)<=Metodologia_v4!$B$13),Dados_Observados_v4!M28,"")) | Q28: =IF(Dados_Observados_v4!Q28<>"",Dados_Observados_v4!Q28,IF(AND(Dados_Observados_v4!M28<>"",(2022-2018)<=Metodologia_v4!$B$13),Dados_Observados_v4!M28,"")) | R28: =IF(Dados_Observados_v4!R28<>"",Dados_Observados_v4!R28,IF(AND(Dados_Observados_v4!M28<>"",(2023-2018)<=Metodologia_v4!$B$13),Dados_Observados_v4!M28,"")) | S28: =IF(Dados_Observados_v4!S28<>"",Dados_Observados_v4!S28,IF(AND(Dados_Observados_v4!M28<>"",(2024-2018)<=Metodologia_v4!$B$13),Dados_Observados_v4!M28,"")) | T28: =IF(Dados_Observados_v4!T28<>"",Dados_Observados_v4!T28,IF(AND(Dados_Observados_v4!M28<>"",(2025-2018)<=Metodologia_v4!$B$13),Dados_Observados_v4!M28,""))
A29: INC04 | B29: 4. Inclusão Social e Protecção | C29: Global Gender Gap Index | D29: WEF / ficheiro base | F29: Série observada do ficheiro base | G29: 10/11 | H29: 2025 | I29: Referenciado pelas regras de Metodologia_v4 | J29: =IF(Dados_Observados_v4!J29<>"",Dados_Observados_v4!J29,IF(AND(Dados_Observados_v4!K29<>"",(2016-2015)<=Metodologia_v4!$B$14),Dados_Observados_v4!K29,"")) | K29: =IF(Dados_Observados_v4!K29<>"",Dados_Observados_v4!K29,IF(AND(Dados_Observados_v4!J29<>"",Dados_Observados_v4!L29<>"",(2017-2015-1)<=Metodologia_v4!$B$12),Dados_Observados_v4!J29+(Dados_Observados_v4!L29-Dados_Observados_v4!J29)*(2016-2015)/(2017-2015),IF(AND(Dados_Observados_v4!J29<>"",(2016-2015)<=Metodologia_v4!$B$13),Dados_Observados_v4!J29,IF(AND(Dados_Observados_v4!L29<>"",(2017-2016)<=Metodologia_v4!$B$14),Dados_Observados_v4!L29,"")))) | L29: =IF(Dados_Observados_v4!L29<>"",Dados_Observados_v4!L29,IF(AND(Dados_Observados_v4!K29<>"",Dados_Observados_v4!M29<>"",(2018-2016-1)<=Metodologia_v4!$B$12),Dados_Observados_v4!K29+(Dados_Observados_v4!M29-Dados_Observados_v4!K29)*(2017-2016)/(2018-2016),IF(AND(Dados_Observados_v4!K29<>"",(2017-2016)<=Metodologia_v4!$B$13),Dados_Observados_v4!K29,IF(AND(Dados_Observados_v4!M29<>"",(2018-2017)<=Metodologia_v4!$B$14),Dados_Observados_v4!M29,"")))) | M29: =IF(Dados_Observados_v4!M29<>"",Dados_Observados_v4!M29,IF(AND(Dados_Observados_v4!L29<>"",Dados_Observados_v4!O29<>"",(2020-2017-1)<=Metodologia_v4!$B$12),Dados_Observados_v4!L29+(Dados_Observados_v4!O29-Dados_Observados_v4!L29)*(2018-2017)/(2020-2017),IF(AND(Dados_Observados_v4!L29<>"",(2018-2017)<=Metodologia_v4!$B$13),Dados_Observados_v4!L29,IF(AND(Dados_Observados_v4!O29<>"",(2020-2018)<=Metodologia_v4!$B$14),Dados_Observados_v4!O29,"")))) | N29: =IF(Dados_Observados_v4!N29<>"",Dados_Observados_v4!N29,IF(AND(Dados_Observados_v4!M29<>"",Dados_Observados_v4!O29<>"",(2020-2018-1)<=Metodologia_v4!$B$12),Dados_Observados_v4!M29+(Dados_Observados_v4!O29-Dados_Observados_v4!M29)*(2019-2018)/(2020-2018),IF(AND(Dados_Observados_v4!M29<>"",(2019-2018)<=Metodologia_v4!$B$13),Dados_Observados_v4!M29,IF(AND(Dados_Observados_v4!O29<>"",(2020-2019)<=Metodologia_v4!$B$14),Dados_Observados_v4!O29,"")))) | O29: =IF(Dados_Observados_v4!O29<>"",Dados_Observados_v4!O29,IF(AND(Dados_Observados_v4!M29<>"",Dados_Observados_v4!P29<>"",(2021-2018-1)<=Metodologia_v4!$B$12),Dados_Observados_v4!M29+(Dados_Observados_v4!P29-Dados_Observados_v4!M29)*(2020-2018)/(2021-2018),IF(AND(Dados_Observados_v4!M29<>"",(2020-2018)<=Metodologia_v4!$B$13),Dados_Observados_v4!M29,IF(AND(Dados_Observados_v4!P29<>"",(2021-2020)<=Metodologia_v4!$B$14),Dados_Observados_v4!P29,"")))) | P29: =IF(Dados_Observados_v4!P29<>"",Dados_Observados_v4!P29,IF(AND(Dados_Observados_v4!O29<>"",Dados_Observados_v4!Q29<>"",(2022-2020-1)<=Metodologia_v4!$B$12),Dados_Observados_v4!O29+(Dados_Observados_v4!Q29-Dados_Observados_v4!O29)*(2021-2020)/(2022-2020),IF(AND(Dados_Observados_v4!O29<>"",(2021-2020)<=Metodologia_v4!$B$13),Dados_Observados_v4!O29,IF(AND(Dados_Observados_v4!Q29<>"",(2022-2021)<=Metodologia_v4!$B$14),Dados_Observados_v4!Q29,"")))) | Q29: =IF(Dados_Observados_v4!Q29<>"",Dados_Observados_v4!Q29,IF(AND(Dados_Observados_v4!P29<>"",Dados_Observados_v4!R29<>"",(2023-2021-1)<=Metodologia_v4!$B$12),Dados_Observados_v4!P29+(Dados_Observados_v4!R29-Dados_Observados_v4!P29)*(2022-2021)/(2023-2021),IF(AND(Dados_Observados_v4!P29<>"",(2022-2021)<=Metodologia_v4!$B$13),Dados_Observados_v4!P29,IF(AND(Dados_Observados_v4!R29<>"",(2023-2022)<=Metodologia_v4!$B$14),Dados_Observados_v4!R29,"")))) | R29: =IF(Dados_Observados_v4!R29<>"",Dados_Observados_v4!R29,IF(AND(Dados_Observados_v4!Q29<>"",Dados_Observados_v4!S29<>"",(2024-2022-1)<=Metodologia_v4!$B$12),Dados_Observados_v4!Q29+(Dados_Observados_v4!S29-Dados_Observados_v4!Q29)*(2023-2022)/(2024-2022),IF(AND(Dados_Observados_v4!Q29<>"",(2023-2022)<=Metodologia_v4!$B$13),Dados_Observados_v4!Q29,IF(AND(Dados_Observados_v4!S29<>"",(2024-2023)<=Metodologia_v4!$B$14),Dados_Observados_v4!S29,"")))) | S29: =IF(Dados_Observados_v4!S29<>"",Dados_Observados_v4!S29,IF(AND(Dados_Observados_v4!R29<>"",Dados_Observados_v4!T29<>"",(2025-2023-1)<=Metodologia_v4!$B$12),Dados_Observados_v4!R29+(Dados_Observados_v4!T29-Dados_Observados_v4!R29)*(2024-2023)/(2025-2023),IF(AND(Dados_Observados_v4!R29<>"",(2024-2023)<=Metodologia_v4!$B$13),Dados_Observados_v4!R29,IF(AND(Dados_Observados_v4!T29<>"",(2025-2024)<=Metodologia_v4!$B$14),Dados_Observados_v4!T29,"")))) | T29: =IF(Dados_Observados_v4!T29<>"",Dados_Observados_v4!T29,IF(AND(Dados_Observados_v4!S29<>"",(2025-2024)<=Metodologia_v4!$B$13),Dados_Observados_v4!S29,""))
A30: INC05 | B30: 4. Inclusão Social e Protecção | C30: Participação feminina na força de trabalho | D30: Banco Mundial/OIT | E30: SL.TLF.CACT.FE.ZS | F30: Fonte Banco Mundial API/CSV | G30: 11/11 | H30: 2025 | I30: Referenciado pelas regras de Metodologia_v4 | J30: =IF(Dados_Observados_v4!J30<>"",Dados_Observados_v4!J30,IF(AND(Dados_Observados_v4!K30<>"",(2016-2015)<=Metodologia_v4!$B$14),Dados_Observados_v4!K30,"")) | K30: =IF(Dados_Observados_v4!K30<>"",Dados_Observados_v4!K30,IF(AND(Dados_Observados_v4!J30<>"",Dados_Observados_v4!L30<>"",(2017-2015-1)<=Metodologia_v4!$B$12),Dados_Observados_v4!J30+(Dados_Observados_v4!L30-Dados_Observados_v4!J30)*(2016-2015)/(2017-2015),IF(AND(Dados_Observados_v4!J30<>"",(2016-2015)<=Metodologia_v4!$B$13),Dados_Observados_v4!J30,IF(AND(Dados_Observados_v4!L30<>"",(2017-2016)<=Metodologia_v4!$B$14),Dados_Observados_v4!L30,"")))) | L30: =IF(Dados_Observados_v4!L30<>"",Dados_Observados_v4!L30,IF(AND(Dados_Observados_v4!K30<>"",Dados_Observados_v4!M30<>"",(2018-2016-1)<=Metodologia_v4!$B$12),Dados_Observados_v4!K30+(Dados_Observados_v4!M30-Dados_Observados_v4!K30)*(2017-2016)/(2018-2016),IF(AND(Dados_Observados_v4!K30<>"",(2017-2016)<=Metodologia_v4!$B$13),Dados_Observados_v4!K30,IF(AND(Dados_Observados_v4!M30<>"",(2018-2017)<=Metodologia_v4!$B$14),Dados_Observados_v4!M30,"")))) | M30: =IF(Dados_Observados_v4!M30<>"",Dados_Observados_v4!M30,IF(AND(Dados_Observados_v4!L30<>"",Dados_Observados_v4!N30<>"",(2019-2017-1)<=Metodologia_v4!$B$12),Dados_Observados_v4!L30+(Dados_Observados_v4!N30-Dados_Observados_v4!L30)*(2018-2017)/(2019-2017),IF(AND(Dados_Observados_v4!L30<>"",(2018-2017)<=Metodologia_v4!$B$13),Dados_Observados_v4!L30,IF(AND(Dados_Observados_v4!N30<>"",(2019-2018)<=Metodologia_v4!$B$14),Dados_Observados_v4!N30,"")))) | N30: =IF(Dados_Observados_v4!N30<>"",Dados_Observados_v4!N30,IF(AND(Dados_Observados_v4!M30<>"",Dados_Observados_v4!O30<>"",(2020-2018-1)<=Metodologia_v4!$B$12),Dados_Observados_v4!M30+(Dados_Observados_v4!O30-Dados_Observados_v4!M30)*(2019-2018)/(2020-2018),IF(AND(Dados_Observados_v4!M30<>"",(2019-2018)<=Metodologia_v4!$B$13),Dados_Observados_v4!M30,IF(AND(Dados_Observados_v4!O30<>"",(2020-2019)<=Metodologia_v4!$B$14),Dados_Observados_v4!O30,"")))) | O30: =IF(Dados_Observados_v4!O30<>"",Dados_Observados_v4!O30,IF(AND(Dados_Observados_v4!N30<>"",Dados_Observados_v4!P30<>"",(2021-2019-1)<=Metodologia_v4!$B$12),Dados_Observados_v4!N30+(Dados_Observados_v4!P30-Dados_Observados_v4!N30)*(2020-2019)/(2021-2019),IF(AND(Dados_Observados_v4!N30<>"",(2020-2019)<=Metodologia_v4!$B$13),Dados_Observados_v4!N30,IF(AND(Dados_Observados_v4!P30<>"",(2021-2020)<=Metodologia_v4!$B$14),Dados_Observados_v4!P30,"")))) | P30: =IF(Dados_Observados_v4!P30<>"",Dados_Observados_v4!P30,IF(AND(Dados_Observados_v4!O30<>"",Dados_Observados_v4!Q30<>"",(2022-2020-1)<=Metodologia_v4!$B$12),Dados_Observados_v4!O30+(Dados_Observados_v4!Q30-Dados_Observados_v4!O30)*(2021-2020)/(2022-2020),IF(AND(Dados_Observados_v4!O30<>"",(2021-2020)<=Metodologia_v4!$B$13),Dados_Observados_v4!O30,IF(AND(Dados_Observados_v4!Q30<>"",(2022-2021)<=Metodologia_v4!$B$14),Dados_Observados_v4!Q30,"")))) | Q30: =IF(Dados_Observados_v4!Q30<>"",Dados_Observados_v4!Q30,IF(AND(Dados_Observados_v4!P30<>"",Dados_Observados_v4!R30<>"",(2023-2021-1)<=Metodologia_v4!$B$12),Dados_Observados_v4!P30+(Dados_Observados_v4!R30-Dados_Observados_v4!P30)*(2022-2021)/(2023-2021),IF(AND(Dados_Observados_v4!P30<>"",(2022-2021)<=Metodologia_v4!$B$13),Dados_Observados_v4!P30,IF(AND(Dados_Observados_v4!R30<>"",(2023-2022)<=Metodologia_v4!$B$14),Dados_Observados_v4!R30,"")))) | R30: =IF(Dados_Observados_v4!R30<>"",Dados_Observados_v4!R30,IF(AND(Dados_Observados_v4!Q30<>"",Dados_Observados_v4!S30<>"",(2024-2022-1)<=Metodologia_v4!$B$12),Dados_Observados_v4!Q30+(Dados_Observados_v4!S30-Dados_Observados_v4!Q30)*(2023-2022)/(2024-2022),IF(AND(Dados_Observados_v4!Q30<>"",(2023-2022)<=Metodologia_v4!$B$13),Dados_Observados_v4!Q30,IF(AND(Dados_Observados_v4!S30<>"",(2024-2023)<=Metodologia_v4!$B$14),Dados_Observados_v4!S30,"")))) | S30: =IF(Dados_Observados_v4!S30<>"",Dados_Observados_v4!S30,IF(AND(Dados_Observados_v4!R30<>"",Dados_Observados_v4!T30<>"",(2025-2023-1)<=Metodologia_v4!$B$12),Dados_Observados_v4!R30+(Dados_Observados_v4!T30-Dados_Observados_v4!R30)*(2024-2023)/(2025-2023),IF(AND(Dados_Observados_v4!R30<>"",(2024-2023)<=Metodologia_v4!$B$13),Dados_Observados_v4!R30,IF(AND(Dados_Observados_v4!T30<>"",(2025-2024)<=Metodologia_v4!$B$14),Dados_Observados_v4!T30,"")))) | T30: =IF(Dados_Observados_v4!T30<>"",Dados_Observados_v4!T30,IF(AND(Dados_Observados_v4!S30<>"",(2025-2024)<=Metodologia_v4!$B$13),Dados_Observados_v4!S30,""))
A31: INC06 | B31: 4. Inclusão Social e Protecção | C31: Mulheres no parlamento | D31: Banco Mundial/IPU | E31: SG.GEN.PARL.ZS | F31: Fonte Banco Mundial API/CSV | G31: 11/11 | H31: 2025 | I31: Referenciado pelas regras de Metodologia_v4 | J31: =IF(Dados_Observados_v4!J31<>"",Dados_Observados_v4!J31,IF(AND(Dados_Observados_v4!K31<>"",(2016-2015)<=Metodologia_v4!$B$14),Dados_Observados_v4!K31,"")) | K31: =IF(Dados_Observados_v4!K31<>"",Dados_Observados_v4!K31,IF(AND(Dados_Observados_v4!J31<>"",Dados_Observados_v4!L31<>"",(2017-2015-1)<=Metodologia_v4!$B$12),Dados_Observados_v4!J31+(Dados_Observados_v4!L31-Dados_Observados_v4!J31)*(2016-2015)/(2017-2015),IF(AND(Dados_Observados_v4!J31<>"",(2016-2015)<=Metodologia_v4!$B$13),Dados_Observados_v4!J31,IF(AND(Dados_Observados_v4!L31<>"",(2017-2016)<=Metodologia_v4!$B$14),Dados_Observados_v4!L31,"")))) | L31: =IF(Dados_Observados_v4!L31<>"",Dados_Observados_v4!L31,IF(AND(Dados_Observados_v4!K31<>"",Dados_Observados_v4!M31<>"",(2018-2016-1)<=Metodologia_v4!$B$12),Dados_Observados_v4!K31+(Dados_Observados_v4!M31-Dados_Observados_v4!K31)*(2017-2016)/(2018-2016),IF(AND(Dados_Observados_v4!K31<>"",(2017-2016)<=Metodologia_v4!$B$13),Dados_Observados_v4!K31,IF(AND(Dados_Observados_v4!M31<>"",(2018-2017)<=Metodologia_v4!$B$14),Dados_Observados_v4!M31,"")))) | M31: =IF(Dados_Observados_v4!M31<>"",Dados_Observados_v4!M31,IF(AND(Dados_Observados_v4!L31<>"",Dados_Observados_v4!N31<>"",(2019-2017-1)<=Metodologia_v4!$B$12),Dados_Observados_v4!L31+(Dados_Observados_v4!N31-Dados_Observados_v4!L31)*(2018-2017)/(2019-2017),IF(AND(Dados_Observados_v4!L31<>"",(2018-2017)<=Metodologia_v4!$B$13),Dados_Observados_v4!L31,IF(AND(Dados_Observados_v4!N31<>"",(2019-2018)<=Metodologia_v4!$B$14),Dados_Observados_v4!N31,"")))) | N31: =IF(Dados_Observados_v4!N31<>"",Dados_Observados_v4!N31,IF(AND(Dados_Observados_v4!M31<>"",Dados_Observados_v4!O31<>"",(2020-2018-1)<=Metodologia_v4!$B$12),Dados_Observados_v4!M31+(Dados_Observados_v4!O31-Dados_Observados_v4!M31)*(2019-2018)/(2020-2018),IF(AND(Dados_Observados_v4!M31<>"",(2019-2018)<=Metodologia_v4!$B$13),Dados_Observados_v4!M31,IF(AND(Dados_Observados_v4!O31<>"",(2020-2019)<=Metodologia_v4!$B$14),Dados_Observados_v4!O31,"")))) | O31: =IF(Dados_Observados_v4!O31<>"",Dados_Observados_v4!O31,IF(AND(Dados_Observados_v4!N31<>"",Dados_Observados_v4!P31<>"",(2021-2019-1)<=Metodologia_v4!$B$12),Dados_Observados_v4!N31+(Dados_Observados_v4!P31-Dados_Observados_v4!N31)*(2020-2019)/(2021-2019),IF(AND(Dados_Observados_v4!N31<>"",(2020-2019)<=Metodologia_v4!$B$13),Dados_Observados_v4!N31,IF(AND(Dados_Observados_v4!P31<>"",(2021-2020)<=Metodologia_v4!$B$14),Dados_Observados_v4!P31,"")))) | P31: =IF(Dados_Observados_v4!P31<>"",Dados_Observados_v4!P31,IF(AND(Dados_Observados_v4!O31<>"",Dados_Observados_v4!Q31<>"",(2022-2020-1)<=Metodologia_v4!$B$12),Dados_Observados_v4!O31+(Dados_Observados_v4!Q31-Dados_Observados_v4!O31)*(2021-2020)/(2022-2020),IF(AND(Dados_Observados_v4!O31<>"",(2021-2020)<=Metodologia_v4!$B$13),Dados_Observados_v4!O31,IF(AND(Dados_Observados_v4!Q31<>"",(2022-2021)<=Metodologia_v4!$B$14),Dados_Observados_v4!Q31,"")))) | Q31: =IF(Dados_Observados_v4!Q31<>"",Dados_Observados_v4!Q31,IF(AND(Dados_Observados_v4!P31<>"",Dados_Observados_v4!R31<>"",(2023-2021-1)<=Metodologia_v4!$B$12),Dados_Observados_v4!P31+(Dados_Observados_v4!R31-Dados_Observados_v4!P31)*(2022-2021)/(2023-2021),IF(AND(Dados_Observados_v4!P31<>"",(2022-2021)<=Metodologia_v4!$B$13),Dados_Observados_v4!P31,IF(AND(Dados_Observados_v4!R31<>"",(2023-2022)<=Metodologia_v4!$B$14),Dados_Observados_v4!R31,"")))) | R31: =IF(Dados_Observados_v4!R31<>"",Dados_Observados_v4!R31,IF(AND(Dados_Observados_v4!Q31<>"",Dados_Observados_v4!S31<>"",(2024-2022-1)<=Metodologia_v4!$B$12),Dados_Observados_v4!Q31+(Dados_Observados_v4!S31-Dados_Observados_v4!Q31)*(2023-2022)/(2024-2022),IF(AND(Dados_Observados_v4!Q31<>"",(2023-2022)<=Metodologia_v4!$B$13),Dados_Observados_v4!Q31,IF(AND(Dados_Observados_v4!S31<>"",(2024-2023)<=Metodologia_v4!$B$14),Dados_Observados_v4!S31,"")))) | S31: =IF(Dados_Observados_v4!S31<>"",Dados_Observados_v4!S31,IF(AND(Dados_Observados_v4!R31<>"",Dados_Observados_v4!T31<>"",(2025-2023-1)<=Metodologia_v4!$B$12),Dados_Observados_v4!R31+(Dados_Observados_v4!T31-Dados_Observados_v4!R31)*(2024-2023)/(2025-2023),IF(AND(Dados_Observados_v4!R31<>"",(2024-2023)<=Metodologia_v4!$B$13),Dados_Observados_v4!R31,IF(AND(Dados_Observados_v4!T31<>"",(2025-2024)<=Metodologia_v4!$B$14),Dados_Observados_v4!T31,"")))) | T31: =IF(Dados_Observados_v4!T31<>"",Dados_Observados_v4!T31,IF(AND(Dados_Observados_v4!S31<>"",(2025-2024)<=Metodologia_v4!$B$13),Dados_Observados_v4!S31,""))
A32: INC07 | B32: 4. Inclusão Social e Protecção | C32: Jovens NEET | D32: Banco Mundial/OIT | E32: SL.UEM.NEET.ZS | F32: Fonte Banco Mundial API/CSV | G32: 6/11 | H32: 2024 | I32: Referenciado pelas regras de Metodologia_v4 | J32: =IF(Dados_Observados_v4!J32<>"",Dados_Observados_v4!J32,IF(AND(Dados_Observados_v4!N32<>"",(2019-2015)<=Metodologia_v4!$B$14),Dados_Observados_v4!N32,"")) | K32: =IF(Dados_Observados_v4!K32<>"",Dados_Observados_v4!K32,IF(AND(Dados_Observados_v4!N32<>"",(2019-2016)<=Metodologia_v4!$B$14),Dados_Observados_v4!N32,"")) | L32: =IF(Dados_Observados_v4!L32<>"",Dados_Observados_v4!L32,IF(AND(Dados_Observados_v4!N32<>"",(2019-2017)<=Metodologia_v4!$B$14),Dados_Observados_v4!N32,"")) | M32: =IF(Dados_Observados_v4!M32<>"",Dados_Observados_v4!M32,IF(AND(Dados_Observados_v4!N32<>"",(2019-2018)<=Metodologia_v4!$B$14),Dados_Observados_v4!N32,"")) | N32: =IF(Dados_Observados_v4!N32<>"",Dados_Observados_v4!N32,IF(AND(Dados_Observados_v4!O32<>"",(2020-2019)<=Metodologia_v4!$B$14),Dados_Observados_v4!O32,"")) | O32: =IF(Dados_Observados_v4!O32<>"",Dados_Observados_v4!O32,IF(AND(Dados_Observados_v4!N32<>"",Dados_Observados_v4!P32<>"",(2021-2019-1)<=Metodologia_v4!$B$12),Dados_Observados_v4!N32+(Dados_Observados_v4!P32-Dados_Observados_v4!N32)*(2020-2019)/(2021-2019),IF(AND(Dados_Observados_v4!N32<>"",(2020-2019)<=Metodologia_v4!$B$13),Dados_Observados_v4!N32,IF(AND(Dados_Observados_v4!P32<>"",(2021-2020)<=Metodologia_v4!$B$14),Dados_Observados_v4!P32,"")))) | P32: =IF(Dados_Observados_v4!P32<>"",Dados_Observados_v4!P32,IF(AND(Dados_Observados_v4!O32<>"",Dados_Observados_v4!Q32<>"",(2022-2020-1)<=Metodologia_v4!$B$12),Dados_Observados_v4!O32+(Dados_Observados_v4!Q32-Dados_Observados_v4!O32)*(2021-2020)/(2022-2020),IF(AND(Dados_Observados_v4!O32<>"",(2021-2020)<=Metodologia_v4!$B$13),Dados_Observados_v4!O32,IF(AND(Dados_Observados_v4!Q32<>"",(2022-2021)<=Metodologia_v4!$B$14),Dados_Observados_v4!Q32,"")))) | Q32: =IF(Dados_Observados_v4!Q32<>"",Dados_Observados_v4!Q32,IF(AND(Dados_Observados_v4!P32<>"",Dados_Observados_v4!R32<>"",(2023-2021-1)<=Metodologia_v4!$B$12),Dados_Observados_v4!P32+(Dados_Observados_v4!R32-Dados_Observados_v4!P32)*(2022-2021)/(2023-2021),IF(AND(Dados_Observados_v4!P32<>"",(2022-2021)<=Metodologia_v4!$B$13),Dados_Observados_v4!P32,IF(AND(Dados_Observados_v4!R32<>"",(2023-2022)<=Metodologia_v4!$B$14),Dados_Observados_v4!R32,"")))) | R32: =IF(Dados_Observados_v4!R32<>"",Dados_Observados_v4!R32,IF(AND(Dados_Observados_v4!Q32<>"",Dados_Observados_v4!S32<>"",(2024-2022-1)<=Metodologia_v4!$B$12),Dados_Observados_v4!Q32+(Dados_Observados_v4!S32-Dados_Observados_v4!Q32)*(2023-2022)/(2024-2022),IF(AND(Dados_Observados_v4!Q32<>"",(2023-2022)<=Metodologia_v4!$B$13),Dados_Observados_v4!Q32,IF(AND(Dados_Observados_v4!S32<>"",(2024-2023)<=Metodologia_v4!$B$14),Dados_Observados_v4!S32,"")))) | S32: =IF(Dados_Observados_v4!S32<>"",Dados_Observados_v4!S32,IF(AND(Dados_Observados_v4!R32<>"",(2024-2023)<=Metodologia_v4!$B$13),Dados_Observados_v4!R32,"")) | T32: =IF(Dados_Observados_v4!T32<>"",Dados_Observados_v4!T32,IF(AND(Dados_Observados_v4!S32<>"",(2025-2024)<=Metodologia_v4!$B$13),Dados_Observados_v4!S32,""))
A33: INC08 | B33: 4. Inclusão Social e Protecção | C33: RNB per capita | D33: Banco Mundial/WDI | E33: NY.GNP.PCAP.CD | F33: Fonte Banco Mundial API/CSV | G33: 10/11 | H33: 2024 | I33: Referenciado pelas regras de Metodologia_v4 | J33: =IF(Dados_Observados_v4!J33<>"",Dados_Observados_v4!J33,IF(AND(Dados_Observados_v4!K33<>"",(2016-2015)<=Metodologia_v4!$B$14),Dados_Observados_v4!K33,"")) | K33: =IF(Dados_Observados_v4!K33<>"",Dados_Observados_v4!K33,IF(AND(Dados_Observados_v4!J33<>"",Dados_Observados_v4!L33<>"",(2017-2015-1)<=Metodologia_v4!$B$12),Dados_Observados_v4!J33+(Dados_Observados_v4!L33-Dados_Observados_v4!J33)*(2016-2015)/(2017-2015),IF(AND(Dados_Observados_v4!J33<>"",(2016-2015)<=Metodologia_v4!$B$13),Dados_Observados_v4!J33,IF(AND(Dados_Observados_v4!L33<>"",(2017-2016)<=Metodologia_v4!$B$14),Dados_Observados_v4!L33,"")))) | L33: =IF(Dados_Observados_v4!L33<>"",Dados_Observados_v4!L33,IF(AND(Dados_Observados_v4!K33<>"",Dados_Observados_v4!M33<>"",(2018-2016-1)<=Metodologia_v4!$B$12),Dados_Observados_v4!K33+(Dados_Observados_v4!M33-Dados_Observados_v4!K33)*(2017-2016)/(2018-2016),IF(AND(Dados_Observados_v4!K33<>"",(2017-2016)<=Metodologia_v4!$B$13),Dados_Observados_v4!K33,IF(AND(Dados_Observados_v4!M33<>"",(2018-2017)<=Metodologia_v4!$B$14),Dados_Observados_v4!M33,"")))) | M33: =IF(Dados_Observados_v4!M33<>"",Dados_Observados_v4!M33,IF(AND(Dados_Observados_v4!L33<>"",Dados_Observados_v4!N33<>"",(2019-2017-1)<=Metodologia_v4!$B$12),Dados_Observados_v4!L33+(Dados_Observados_v4!N33-Dados_Observados_v4!L33)*(2018-2017)/(2019-2017),IF(AND(Dados_Observados_v4!L33<>"",(2018-2017)<=Metodologia_v4!$B$13),Dados_Observados_v4!L33,IF(AND(Dados_Observados_v4!N33<>"",(2019-2018)<=Metodologia_v4!$B$14),Dados_Observados_v4!N33,"")))) | N33: =IF(Dados_Observados_v4!N33<>"",Dados_Observados_v4!N33,IF(AND(Dados_Observados_v4!M33<>"",Dados_Observados_v4!O33<>"",(2020-2018-1)<=Metodologia_v4!$B$12),Dados_Observados_v4!M33+(Dados_Observados_v4!O33-Dados_Observados_v4!M33)*(2019-2018)/(2020-2018),IF(AND(Dados_Observados_v4!M33<>"",(2019-2018)<=Metodologia_v4!$B$13),Dados_Observados_v4!M33,IF(AND(Dados_Observados_v4!O33<>"",(2020-2019)<=Metodologia_v4!$B$14),Dados_Observados_v4!O33,"")))) | O33: =IF(Dados_Observados_v4!O33<>"",Dados_Observados_v4!O33,IF(AND(Dados_Observados_v4!N33<>"",Dados_Observados_v4!P33<>"",(2021-2019-1)<=Metodologia_v4!$B$12),Dados_Observados_v4!N33+(Dados_Observados_v4!P33-Dados_Observados_v4!N33)*(2020-2019)/(2021-2019),IF(AND(Dados_Observados_v4!N33<>"",(2020-2019)<=Metodologia_v4!$B$13),Dados_Observados_v4!N33,IF(AND(Dados_Observados_v4!P33<>"",(2021-2020)<=Metodologia_v4!$B$14),Dados_Observados_v4!P33,"")))) | P33: =IF(Dados_Observados_v4!P33<>"",Dados_Observados_v4!P33,IF(AND(Dados_Observados_v4!O33<>"",Dados_Observados_v4!Q33<>"",(2022-2020-1)<=Metodologia_v4!$B$12),Dados_Observados_v4!O33+(Dados_Observados_v4!Q33-Dados_Observados_v4!O33)*(2021-2020)/(2022-2020),IF(AND(Dados_Observados_v4!O33<>"",(2021-2020)<=Metodologia_v4!$B$13),Dados_Observados_v4!O33,IF(AND(Dados_Observados_v4!Q33<>"",(2022-2021)<=Metodologia_v4!$B$14),Dados_Observados_v4!Q33,"")))) | Q33: =IF(Dados_Observados_v4!Q33<>"",Dados_Observados_v4!Q33,IF(AND(Dados_Observados_v4!P33<>"",Dados_Observados_v4!R33<>"",(2023-2021-1)<=Metodologia_v4!$B$12),Dados_Observados_v4!P33+(Dados_Observados_v4!R33-Dados_Observados_v4!P33)*(2022-2021)/(2023-2021),IF(AND(Dados_Observados_v4!P33<>"",(2022-2021)<=Metodologia_v4!$B$13),Dados_Observados_v4!P33,IF(AND(Dados_Observados_v4!R33<>"",(2023-2022)<=Metodologia_v4!$B$14),Dados_Observados_v4!R33,"")))) | R33: =IF(Dados_Observados_v4!R33<>"",Dados_Observados_v4!R33,IF(AND(Dados_Observados_v4!Q33<>"",Dados_Observados_v4!S33<>"",(2024-2022-1)<=Metodologia_v4!$B$12),Dados_Observados_v4!Q33+(Dados_Observados_v4!S33-Dados_Observados_v4!Q33)*(2023-2022)/(2024-2022),IF(AND(Dados_Observados_v4!Q33<>"",(2023-2022)<=Metodologia_v4!$B$13),Dados_Observados_v4!Q33,IF(AND(Dados_Observados_v4!S33<>"",(2024-2023)<=Metodologia_v4!$B$14),Dados_Observados_v4!S33,"")))) | S33: =IF(Dados_Observados_v4!S33<>"",Dados_Observados_v4!S33,IF(AND(Dados_Observados_v4!R33<>"",(2024-2023)<=Metodologia_v4!$B$13),Dados_Observados_v4!R33,"")) | T33: =IF(Dados_Observados_v4!T33<>"",Dados_Observados_v4!T33,IF(AND(Dados_Observados_v4!S33<>"",(2025-2024)<=Metodologia_v4!$B$13),Dados_Observados_v4!S33,""))
A34: INF01 | B34: 5. Infraestruturas e Serviços | C34: Acesso à eletricidade | D34: Banco Mundial/IEA | E34: EG.ELC.ACCS.ZS | F34: Fonte Banco Mundial API/CSV | G34: 9/11 | H34: 2023 | I34: Referenciado pelas regras de Metodologia_v4 | J34: =IF(Dados_Observados_v4!J34<>"",Dados_Observados_v4!J34,IF(AND(Dados_Observados_v4!K34<>"",(2016-2015)<=Metodologia_v4!$B$14),Dados_Observados_v4!K34,"")) | K34: =IF(Dados_Observados_v4!K34<>"",Dados_Observados_v4!K34,IF(AND(Dados_Observados_v4!J34<>"",Dados_Observados_v4!L34<>"",(2017-2015-1)<=Metodologia_v4!$B$12),Dados_Observados_v4!J34+(Dados_Observados_v4!L34-Dados_Observados_v4!J34)*(2016-2015)/(2017-2015),IF(AND(Dados_Observados_v4!J34<>"",(2016-2015)<=Metodologia_v4!$B$13),Dados_Observados_v4!J34,IF(AND(Dados_Observados_v4!L34<>"",(2017-2016)<=Metodologia_v4!$B$14),Dados_Observados_v4!L34,"")))) | L34: =IF(Dados_Observados_v4!L34<>"",Dados_Observados_v4!L34,IF(AND(Dados_Observados_v4!K34<>"",Dados_Observados_v4!M34<>"",(2018-2016-1)<=Metodologia_v4!$B$12),Dados_Observados_v4!K34+(Dados_Observados_v4!M34-Dados_Observados_v4!K34)*(2017-2016)/(2018-2016),IF(AND(Dados_Observados_v4!K34<>"",(2017-2016)<=Metodologia_v4!$B$13),Dados_Observados_v4!K34,IF(AND(Dados_Observados_v4!M34<>"",(2018-2017)<=Metodologia_v4!$B$14),Dados_Observados_v4!M34,"")))) | M34: =IF(Dados_Observados_v4!M34<>"",Dados_Observados_v4!M34,IF(AND(Dados_Observados_v4!L34<>"",Dados_Observados_v4!N34<>"",(2019-2017-1)<=Metodologia_v4!$B$12),Dados_Observados_v4!L34+(Dados_Observados_v4!N34-Dados_Observados_v4!L34)*(2018-2017)/(2019-2017),IF(AND(Dados_Observados_v4!L34<>"",(2018-2017)<=Metodologia_v4!$B$13),Dados_Observados_v4!L34,IF(AND(Dados_Observados_v4!N34<>"",(2019-2018)<=Metodologia_v4!$B$14),Dados_Observados_v4!N34,"")))) | N34: =IF(Dados_Observados_v4!N34<>"",Dados_Observados_v4!N34,IF(AND(Dados_Observados_v4!M34<>"",Dados_Observados_v4!O34<>"",(2020-2018-1)<=Metodologia_v4!$B$12),Dados_Observados_v4!M34+(Dados_Observados_v4!O34-Dados_Observados_v4!M34)*(2019-2018)/(2020-2018),IF(AND(Dados_Observados_v4!M34<>"",(2019-2018)<=Metodologia_v4!$B$13),Dados_Observados_v4!M34,IF(AND(Dados_Observados_v4!O34<>"",(2020-2019)<=Metodologia_v4!$B$14),Dados_Observados_v4!O34,"")))) | O34: =IF(Dados_Observados_v4!O34<>"",Dados_Observados_v4!O34,IF(AND(Dados_Observados_v4!N34<>"",Dados_Observados_v4!P34<>"",(2021-2019-1)<=Metodologia_v4!$B$12),Dados_Observados_v4!N34+(Dados_Observados_v4!P34-Dados_Observados_v4!N34)*(2020-2019)/(2021-2019),IF(AND(Dados_Observados_v4!N34<>"",(2020-2019)<=Metodologia_v4!$B$13),Dados_Observados_v4!N34,IF(AND(Dados_Observados_v4!P34<>"",(2021-2020)<=Metodologia_v4!$B$14),Dados_Observados_v4!P34,"")))) | P34: =IF(Dados_Observados_v4!P34<>"",Dados_Observados_v4!P34,IF(AND(Dados_Observados_v4!O34<>"",Dados_Observados_v4!Q34<>"",(2022-2020-1)<=Metodologia_v4!$B$12),Dados_Observados_v4!O34+(Dados_Observados_v4!Q34-Dados_Observados_v4!O34)*(2021-2020)/(2022-2020),IF(AND(Dados_Observados_v4!O34<>"",(2021-2020)<=Metodologia_v4!$B$13),Dados_Observados_v4!O34,IF(AND(Dados_Observados_v4!Q34<>"",(2022-2021)<=Metodologia_v4!$B$14),Dados_Observados_v4!Q34,"")))) | Q34: =IF(Dados_Observados_v4!Q34<>"",Dados_Observados_v4!Q34,IF(AND(Dados_Observados_v4!P34<>"",Dados_Observados_v4!R34<>"",(2023-2021-1)<=Metodologia_v4!$B$12),Dados_Observados_v4!P34+(Dados_Observados_v4!R34-Dados_Observados_v4!P34)*(2022-2021)/(2023-2021),IF(AND(Dados_Observados_v4!P34<>"",(2022-2021)<=Metodologia_v4!$B$13),Dados_Observados_v4!P34,IF(AND(Dados_Observados_v4!R34<>"",(2023-2022)<=Metodologia_v4!$B$14),Dados_Observados_v4!R34,"")))) | R34: =IF(Dados_Observados_v4!R34<>"",Dados_Observados_v4!R34,IF(AND(Dados_Observados_v4!Q34<>"",(2023-2022)<=Metodologia_v4!$B$13),Dados_Observados_v4!Q34,"")) | S34: =IF(Dados_Observados_v4!S34<>"",Dados_Observados_v4!S34,IF(AND(Dados_Observados_v4!R34<>"",(2024-2023)<=Metodologia_v4!$B$13),Dados_Observados_v4!R34,"")) | T34: =IF(Dados_Observados_v4!T34<>"",Dados_Observados_v4!T34,IF(AND(Dados_Observados_v4!R34<>"",(2025-2023)<=Metodologia_v4!$B$13),Dados_Observados_v4!R34,""))
A35: INF02 | B35: 5. Infraestruturas e Serviços | C35: Perdas na rede elétrica | D35: Banco Mundial/IEA | E35: EG.ELC.LOSS.ZS | F35: Fonte Banco Mundial API/CSV | G35: 9/11 | H35: 2023 | I35: Referenciado pelas regras de Metodologia_v4 | J35: =IF(Dados_Observados_v4!J35<>"",Dados_Observados_v4!J35,IF(AND(Dados_Observados_v4!K35<>"",(2016-2015)<=Metodologia_v4!$B$14),Dados_Observados_v4!K35,"")) | K35: =IF(Dados_Observados_v4!K35<>"",Dados_Observados_v4!K35,IF(AND(Dados_Observados_v4!J35<>"",Dados_Observados_v4!L35<>"",(2017-2015-1)<=Metodologia_v4!$B$12),Dados_Observados_v4!J35+(Dados_Observados_v4!L35-Dados_Observados_v4!J35)*(2016-2015)/(2017-2015),IF(AND(Dados_Observados_v4!J35<>"",(2016-2015)<=Metodologia_v4!$B$13),Dados_Observados_v4!J35,IF(AND(Dados_Observados_v4!L35<>"",(2017-2016)<=Metodologia_v4!$B$14),Dados_Observados_v4!L35,"")))) | L35: =IF(Dados_Observados_v4!L35<>"",Dados_Observados_v4!L35,IF(AND(Dados_Observados_v4!K35<>"",Dados_Observados_v4!M35<>"",(2018-2016-1)<=Metodologia_v4!$B$12),Dados_Observados_v4!K35+(Dados_Observados_v4!M35-Dados_Observados_v4!K35)*(2017-2016)/(2018-2016),IF(AND(Dados_Observados_v4!K35<>"",(2017-2016)<=Metodologia_v4!$B$13),Dados_Observados_v4!K35,IF(AND(Dados_Observados_v4!M35<>"",(2018-2017)<=Metodologia_v4!$B$14),Dados_Observados_v4!M35,"")))) | M35: =IF(Dados_Observados_v4!M35<>"",Dados_Observados_v4!M35,IF(AND(Dados_Observados_v4!L35<>"",Dados_Observados_v4!N35<>"",(2019-2017-1)<=Metodologia_v4!$B$12),Dados_Observados_v4!L35+(Dados_Observados_v4!N35-Dados_Observados_v4!L35)*(2018-2017)/(2019-2017),IF(AND(Dados_Observados_v4!L35<>"",(2018-2017)<=Metodologia_v4!$B$13),Dados_Observados_v4!L35,IF(AND(Dados_Observados_v4!N35<>"",(2019-2018)<=Metodologia_v4!$B$14),Dados_Observados_v4!N35,"")))) | N35: =IF(Dados_Observados_v4!N35<>"",Dados_Observados_v4!N35,IF(AND(Dados_Observados_v4!M35<>"",Dados_Observados_v4!O35<>"",(2020-2018-1)<=Metodologia_v4!$B$12),Dados_Observados_v4!M35+(Dados_Observados_v4!O35-Dados_Observados_v4!M35)*(2019-2018)/(2020-2018),IF(AND(Dados_Observados_v4!M35<>"",(2019-2018)<=Metodologia_v4!$B$13),Dados_Observados_v4!M35,IF(AND(Dados_Observados_v4!O35<>"",(2020-2019)<=Metodologia_v4!$B$14),Dados_Observados_v4!O35,"")))) | O35: =IF(Dados_Observados_v4!O35<>"",Dados_Observados_v4!O35,IF(AND(Dados_Observados_v4!N35<>"",Dados_Observados_v4!P35<>"",(2021-2019-1)<=Metodologia_v4!$B$12),Dados_Observados_v4!N35+(Dados_Observados_v4!P35-Dados_Observados_v4!N35)*(2020-2019)/(2021-2019),IF(AND(Dados_Observados_v4!N35<>"",(2020-2019)<=Metodologia_v4!$B$13),Dados_Observados_v4!N35,IF(AND(Dados_Observados_v4!P35<>"",(2021-2020)<=Metodologia_v4!$B$14),Dados_Observados_v4!P35,"")))) | P35: =IF(Dados_Observados_v4!P35<>"",Dados_Observados_v4!P35,IF(AND(Dados_Observados_v4!O35<>"",Dados_Observados_v4!Q35<>"",(2022-2020-1)<=Metodologia_v4!$B$12),Dados_Observados_v4!O35+(Dados_Observados_v4!Q35-Dados_Observados_v4!O35)*(2021-2020)/(2022-2020),IF(AND(Dados_Observados_v4!O35<>"",(2021-2020)<=Metodologia_v4!$B$13),Dados_Observados_v4!O35,IF(AND(Dados_Observados_v4!Q35<>"",(2022-2021)<=Metodologia_v4!$B$14),Dados_Observados_v4!Q35,"")))) | Q35: =IF(Dados_Observados_v4!Q35<>"",Dados_Observados_v4!Q35,IF(AND(Dados_Observados_v4!P35<>"",Dados_Observados_v4!R35<>"",(2023-2021-1)<=Metodologia_v4!$B$12),Dados_Observados_v4!P35+(Dados_Observados_v4!R35-Dados_Observados_v4!P35)*(2022-2021)/(2023-2021),IF(AND(Dados_Observados_v4!P35<>"",(2022-2021)<=Metodologia_v4!$B$13),Dados_Observados_v4!P35,IF(AND(Dados_Observados_v4!R35<>"",(2023-2022)<=Metodologia_v4!$B$14),Dados_Observados_v4!R35,"")))) | R35: =IF(Dados_Observados_v4!R35<>"",Dados_Observados_v4!R35,IF(AND(Dados_Observados_v4!Q35<>"",(2023-2022)<=Metodologia_v4!$B$13),Dados_Observados_v4!Q35,"")) | S35: =IF(Dados_Observados_v4!S35<>"",Dados_Observados_v4!S35,IF(AND(Dados_Observados_v4!R35<>"",(2024-2023)<=Metodologia_v4!$B$13),Dados_Observados_v4!R35,"")) | T35: =IF(Dados_Observados_v4!T35<>"",Dados_Observados_v4!T35,IF(AND(Dados_Observados_v4!R35<>"",(2025-2023)<=Metodologia_v4!$B$13),Dados_Observados_v4!R35,""))
A36: INF03 | B36: 5. Infraestruturas e Serviços | C36: Acesso a água potável básica | D36: Banco Mundial/JMP | E36: SH.H2O.BASW.ZS | F36: Fonte Banco Mundial API/CSV | G36: 10/11 | H36: 2024 | I36: Referenciado pelas regras de Metodologia_v4 | J36: =IF(Dados_Observados_v4!J36<>"",Dados_Observados_v4!J36,IF(AND(Dados_Observados_v4!K36<>"",(2016-2015)<=Metodologia_v4!$B$14),Dados_Observados_v4!K36,"")) | K36: =IF(Dados_Observados_v4!K36<>"",Dados_Observados_v4!K36,IF(AND(Dados_Observados_v4!J36<>"",Dados_Observados_v4!L36<>"",(2017-2015-1)<=Metodologia_v4!$B$12),Dados_Observados_v4!J36+(Dados_Observados_v4!L36-Dados_Observados_v4!J36)*(2016-2015)/(2017-2015),IF(AND(Dados_Observados_v4!J36<>"",(2016-2015)<=Metodologia_v4!$B$13),Dados_Observados_v4!J36,IF(AND(Dados_Observados_v4!L36<>"",(2017-2016)<=Metodologia_v4!$B$14),Dados_Observados_v4!L36,"")))) | L36: =IF(Dados_Observados_v4!L36<>"",Dados_Observados_v4!L36,IF(AND(Dados_Observados_v4!K36<>"",Dados_Observados_v4!M36<>"",(2018-2016-1)<=Metodologia_v4!$B$12),Dados_Observados_v4!K36+(Dados_Observados_v4!M36-Dados_Observados_v4!K36)*(2017-2016)/(2018-2016),IF(AND(Dados_Observados_v4!K36<>"",(2017-2016)<=Metodologia_v4!$B$13),Dados_Observados_v4!K36,IF(AND(Dados_Observados_v4!M36<>"",(2018-2017)<=Metodologia_v4!$B$14),Dados_Observados_v4!M36,"")))) | M36: =IF(Dados_Observados_v4!M36<>"",Dados_Observados_v4!M36,IF(AND(Dados_Observados_v4!L36<>"",Dados_Observados_v4!N36<>"",(2019-2017-1)<=Metodologia_v4!$B$12),Dados_Observados_v4!L36+(Dados_Observados_v4!N36-Dados_Observados_v4!L36)*(2018-2017)/(2019-2017),IF(AND(Dados_Observados_v4!L36<>"",(2018-2017)<=Metodologia_v4!$B$13),Dados_Observados_v4!L36,IF(AND(Dados_Observados_v4!N36<>"",(2019-2018)<=Metodologia_v4!$B$14),Dados_Observados_v4!N36,"")))) | N36: =IF(Dados_Observados_v4!N36<>"",Dados_Observados_v4!N36,IF(AND(Dados_Observados_v4!M36<>"",Dados_Observados_v4!O36<>"",(2020-2018-1)<=Metodologia_v4!$B$12),Dados_Observados_v4!M36+(Dados_Observados_v4!O36-Dados_Observados_v4!M36)*(2019-2018)/(2020-2018),IF(AND(Dados_Observados_v4!M36<>"",(2019-2018)<=Metodologia_v4!$B$13),Dados_Observados_v4!M36,IF(AND(Dados_Observados_v4!O36<>"",(2020-2019)<=Metodologia_v4!$B$14),Dados_Observados_v4!O36,"")))) | O36: =IF(Dados_Observados_v4!O36<>"",Dados_Observados_v4!O36,IF(AND(Dados_Observados_v4!N36<>"",Dados_Observados_v4!P36<>"",(2021-2019-1)<=Metodologia_v4!$B$12),Dados_Observados_v4!N36+(Dados_Observados_v4!P36-Dados_Observados_v4!N36)*(2020-2019)/(2021-2019),IF(AND(Dados_Observados_v4!N36<>"",(2020-2019)<=Metodologia_v4!$B$13),Dados_Observados_v4!N36,IF(AND(Dados_Observados_v4!P36<>"",(2021-2020)<=Metodologia_v4!$B$14),Dados_Observados_v4!P36,"")))) | P36: =IF(Dados_Observados_v4!P36<>"",Dados_Observados_v4!P36,IF(AND(Dados_Observados_v4!O36<>"",Dados_Observados_v4!Q36<>"",(2022-2020-1)<=Metodologia_v4!$B$12),Dados_Observados_v4!O36+(Dados_Observados_v4!Q36-Dados_Observados_v4!O36)*(2021-2020)/(2022-2020),IF(AND(Dados_Observados_v4!O36<>"",(2021-2020)<=Metodologia_v4!$B$13),Dados_Observados_v4!O36,IF(AND(Dados_Observados_v4!Q36<>"",(2022-2021)<=Metodologia_v4!$B$14),Dados_Observados_v4!Q36,"")))) | Q36: =IF(Dados_Observados_v4!Q36<>"",Dados_Observados_v4!Q36,IF(AND(Dados_Observados_v4!P36<>"",Dados_Observados_v4!R36<>"",(2023-2021-1)<=Metodologia_v4!$B$12),Dados_Observados_v4!P36+(Dados_Observados_v4!R36-Dados_Observados_v4!P36)*(2022-2021)/(2023-2021),IF(AND(Dados_Observados_v4!P36<>"",(2022-2021)<=Metodologia_v4!$B$13),Dados_Observados_v4!P36,IF(AND(Dados_Observados_v4!R36<>"",(2023-2022)<=Metodologia_v4!$B$14),Dados_Observados_v4!R36,"")))) | R36: =IF(Dados_Observados_v4!R36<>"",Dados_Observados_v4!R36,IF(AND(Dados_Observados_v4!Q36<>"",Dados_Observados_v4!S36<>"",(2024-2022-1)<=Metodologia_v4!$B$12),Dados_Observados_v4!Q36+(Dados_Observados_v4!S36-Dados_Observados_v4!Q36)*(2023-2022)/(2024-2022),IF(AND(Dados_Observados_v4!Q36<>"",(2023-2022)<=Metodologia_v4!$B$13),Dados_Observados_v4!Q36,IF(AND(Dados_Observados_v4!S36<>"",(2024-2023)<=Metodologia_v4!$B$14),Dados_Observados_v4!S36,"")))) | S36: =IF(Dados_Observados_v4!S36<>"",Dados_Observados_v4!S36,IF(AND(Dados_Observados_v4!R36<>"",(2024-2023)<=Metodologia_v4!$B$13),Dados_Observados_v4!R36,"")) | T36: =IF(Dados_Observados_v4!T36<>"",Dados_Observados_v4!T36,IF(AND(Dados_Observados_v4!S36<>"",(2025-2024)<=Metodologia_v4!$B$13),Dados_Observados_v4!S36,""))
A37: INF04 | B37: 5. Infraestruturas e Serviços | C37: Acesso a saneamento básico | D37: Banco Mundial/JMP | E37: SH.STA.BASS.ZS | F37: Fonte Banco Mundial API/CSV | G37: 8/11 | H37: 2022 | I37: Referenciado pelas regras de Metodologia_v4 | J37: =IF(Dados_Observados_v4!J37<>"",Dados_Observados_v4!J37,IF(AND(Dados_Observados_v4!K37<>"",(2016-2015)<=Metodologia_v4!$B$14),Dados_Observados_v4!K37,"")) | K37: =IF(Dados_Observados_v4!K37<>"",Dados_Observados_v4!K37,IF(AND(Dados_Observados_v4!J37<>"",Dados_Observados_v4!L37<>"",(2017-2015-1)<=Metodologia_v4!$B$12),Dados_Observados_v4!J37+(Dados_Observados_v4!L37-Dados_Observados_v4!J37)*(2016-2015)/(2017-2015),IF(AND(Dados_Observados_v4!J37<>"",(2016-2015)<=Metodologia_v4!$B$13),Dados_Observados_v4!J37,IF(AND(Dados_Observados_v4!L37<>"",(2017-2016)<=Metodologia_v4!$B$14),Dados_Observados_v4!L37,"")))) | L37: =IF(Dados_Observados_v4!L37<>"",Dados_Observados_v4!L37,IF(AND(Dados_Observados_v4!K37<>"",Dados_Observados_v4!M37<>"",(2018-2016-1)<=Metodologia_v4!$B$12),Dados_Observados_v4!K37+(Dados_Observados_v4!M37-Dados_Observados_v4!K37)*(2017-2016)/(2018-2016),IF(AND(Dados_Observados_v4!K37<>"",(2017-2016)<=Metodologia_v4!$B$13),Dados_Observados_v4!K37,IF(AND(Dados_Observados_v4!M37<>"",(2018-2017)<=Metodologia_v4!$B$14),Dados_Observados_v4!M37,"")))) | M37: =IF(Dados_Observados_v4!M37<>"",Dados_Observados_v4!M37,IF(AND(Dados_Observados_v4!L37<>"",Dados_Observados_v4!N37<>"",(2019-2017-1)<=Metodologia_v4!$B$12),Dados_Observados_v4!L37+(Dados_Observados_v4!N37-Dados_Observados_v4!L37)*(2018-2017)/(2019-2017),IF(AND(Dados_Observados_v4!L37<>"",(2018-2017)<=Metodologia_v4!$B$13),Dados_Observados_v4!L37,IF(AND(Dados_Observados_v4!N37<>"",(2019-2018)<=Metodologia_v4!$B$14),Dados_Observados_v4!N37,"")))) | N37: =IF(Dados_Observados_v4!N37<>"",Dados_Observados_v4!N37,IF(AND(Dados_Observados_v4!M37<>"",Dados_Observados_v4!O37<>"",(2020-2018-1)<=Metodologia_v4!$B$12),Dados_Observados_v4!M37+(Dados_Observados_v4!O37-Dados_Observados_v4!M37)*(2019-2018)/(2020-2018),IF(AND(Dados_Observados_v4!M37<>"",(2019-2018)<=Metodologia_v4!$B$13),Dados_Observados_v4!M37,IF(AND(Dados_Observados_v4!O37<>"",(2020-2019)<=Metodologia_v4!$B$14),Dados_Observados_v4!O37,"")))) | O37: =IF(Dados_Observados_v4!O37<>"",Dados_Observados_v4!O37,IF(AND(Dados_Observados_v4!N37<>"",Dados_Observados_v4!P37<>"",(2021-2019-1)<=Metodologia_v4!$B$12),Dados_Observados_v4!N37+(Dados_Observados_v4!P37-Dados_Observados_v4!N37)*(2020-2019)/(2021-2019),IF(AND(Dados_Observados_v4!N37<>"",(2020-2019)<=Metodologia_v4!$B$13),Dados_Observados_v4!N37,IF(AND(Dados_Observados_v4!P37<>"",(2021-2020)<=Metodologia_v4!$B$14),Dados_Observados_v4!P37,"")))) | P37: =IF(Dados_Observados_v4!P37<>"",Dados_Observados_v4!P37,IF(AND(Dados_Observados_v4!O37<>"",Dados_Observados_v4!Q37<>"",(2022-2020-1)<=Metodologia_v4!$B$12),Dados_Observados_v4!O37+(Dados_Observados_v4!Q37-Dados_Observados_v4!O37)*(2021-2020)/(2022-2020),IF(AND(Dados_Observados_v4!O37<>"",(2021-2020)<=Metodologia_v4!$B$13),Dados_Observados_v4!O37,IF(AND(Dados_Observados_v4!Q37<>"",(2022-2021)<=Metodologia_v4!$B$14),Dados_Observados_v4!Q37,"")))) | Q37: =IF(Dados_Observados_v4!Q37<>"",Dados_Observados_v4!Q37,IF(AND(Dados_Observados_v4!P37<>"",(2022-2021)<=Metodologia_v4!$B$13),Dados_Observados_v4!P37,"")) | R37: =IF(Dados_Observados_v4!R37<>"",Dados_Observados_v4!R37,IF(AND(Dados_Observados_v4!Q37<>"",(2023-2022)<=Metodologia_v4!$B$13),Dados_Observados_v4!Q37,"")) | S37: =IF(Dados_Observados_v4!S37<>"",Dados_Observados_v4!S37,IF(AND(Dados_Observados_v4!Q37<>"",(2024-2022)<=Metodologia_v4!$B$13),Dados_Observados_v4!Q37,"")) | T37: =IF(Dados_Observados_v4!T37<>"",Dados_Observados_v4!T37,IF(AND(Dados_Observados_v4!Q37<>"",(2025-2022)<=Metodologia_v4!$B$13),Dados_Observados_v4!Q37,""))
A38: INF05 | B38: 5. Infraestruturas e Serviços | C38: Acesso a energia limpa para cozinhar | D38: Banco Mundial/OMS | E38: EG.CFT.ACCS.ZS | F38: Fonte Banco Mundial API/CSV | G38: 9/11 | H38: 2023 | I38: Referenciado pelas regras de Metodologia_v4 | J38: =IF(Dados_Observados_v4!J38<>"",Dados_Observados_v4!J38,IF(AND(Dados_Observados_v4!K38<>"",(2016-2015)<=Metodologia_v4!$B$14),Dados_Observados_v4!K38,"")) | K38: =IF(Dados_Observados_v4!K38<>"",Dados_Observados_v4!K38,IF(AND(Dados_Observados_v4!J38<>"",Dados_Observados_v4!L38<>"",(2017-2015-1)<=Metodologia_v4!$B$12),Dados_Observados_v4!J38+(Dados_Observados_v4!L38-Dados_Observados_v4!J38)*(2016-2015)/(2017-2015),IF(AND(Dados_Observados_v4!J38<>"",(2016-2015)<=Metodologia_v4!$B$13),Dados_Observados_v4!J38,IF(AND(Dados_Observados_v4!L38<>"",(2017-2016)<=Metodologia_v4!$B$14),Dados_Observados_v4!L38,"")))) | L38: =IF(Dados_Observados_v4!L38<>"",Dados_Observados_v4!L38,IF(AND(Dados_Observados_v4!K38<>"",Dados_Observados_v4!M38<>"",(2018-2016-1)<=Metodologia_v4!$B$12),Dados_Observados_v4!K38+(Dados_Observados_v4!M38-Dados_Observados_v4!K38)*(2017-2016)/(2018-2016),IF(AND(Dados_Observados_v4!K38<>"",(2017-2016)<=Metodologia_v4!$B$13),Dados_Observados_v4!K38,IF(AND(Dados_Observados_v4!M38<>"",(2018-2017)<=Metodologia_v4!$B$14),Dados_Observados_v4!M38,"")))) | M38: =IF(Dados_Observados_v4!M38<>"",Dados_Observados_v4!M38,IF(AND(Dados_Observados_v4!L38<>"",Dados_Observados_v4!N38<>"",(2019-2017-1)<=Metodologia_v4!$B$12),Dados_Observados_v4!L38+(Dados_Observados_v4!N38-Dados_Observados_v4!L38)*(2018-2017)/(2019-2017),IF(AND(Dados_Observados_v4!L38<>"",(2018-2017)<=Metodologia_v4!$B$13),Dados_Observados_v4!L38,IF(AND(Dados_Observados_v4!N38<>"",(2019-2018)<=Metodologia_v4!$B$14),Dados_Observados_v4!N38,"")))) | N38: =IF(Dados_Observados_v4!N38<>"",Dados_Observados_v4!N38,IF(AND(Dados_Observados_v4!M38<>"",Dados_Observados_v4!O38<>"",(2020-2018-1)<=Metodologia_v4!$B$12),Dados_Observados_v4!M38+(Dados_Observados_v4!O38-Dados_Observados_v4!M38)*(2019-2018)/(2020-2018),IF(AND(Dados_Observados_v4!M38<>"",(2019-2018)<=Metodologia_v4!$B$13),Dados_Observados_v4!M38,IF(AND(Dados_Observados_v4!O38<>"",(2020-2019)<=Metodologia_v4!$B$14),Dados_Observados_v4!O38,"")))) | O38: =IF(Dados_Observados_v4!O38<>"",Dados_Observados_v4!O38,IF(AND(Dados_Observados_v4!N38<>"",Dados_Observados_v4!P38<>"",(2021-2019-1)<=Metodologia_v4!$B$12),Dados_Observados_v4!N38+(Dados_Observados_v4!P38-Dados_Observados_v4!N38)*(2020-2019)/(2021-2019),IF(AND(Dados_Observados_v4!N38<>"",(2020-2019)<=Metodologia_v4!$B$13),Dados_Observados_v4!N38,IF(AND(Dados_Observados_v4!P38<>"",(2021-2020)<=Metodologia_v4!$B$14),Dados_Observados_v4!P38,"")))) | P38: =IF(Dados_Observados_v4!P38<>"",Dados_Observados_v4!P38,IF(AND(Dados_Observados_v4!O38<>"",Dados_Observados_v4!Q38<>"",(2022-2020-1)<=Metodologia_v4!$B$12),Dados_Observados_v4!O38+(Dados_Observados_v4!Q38-Dados_Observados_v4!O38)*(2021-2020)/(2022-2020),IF(AND(Dados_Observados_v4!O38<>"",(2021-2020)<=Metodologia_v4!$B$13),Dados_Observados_v4!O38,IF(AND(Dados_Observados_v4!Q38<>"",(2022-2021)<=Metodologia_v4!$B$14),Dados_Observados_v4!Q38,"")))) | Q38: =IF(Dados_Observados_v4!Q38<>"",Dados_Observados_v4!Q38,IF(AND(Dados_Observados_v4!P38<>"",Dados_Observados_v4!R38<>"",(2023-2021-1)<=Metodologia_v4!$B$12),Dados_Observados_v4!P38+(Dados_Observados_v4!R38-Dados_Observados_v4!P38)*(2022-2021)/(2023-2021),IF(AND(Dados_Observados_v4!P38<>"",(2022-2021)<=Metodologia_v4!$B$13),Dados_Observados_v4!P38,IF(AND(Dados_Observados_v4!R38<>"",(2023-2022)<=Metodologia_v4!$B$14),Dados_Observados_v4!R38,"")))) | R38: =IF(Dados_Observados_v4!R38<>"",Dados_Observados_v4!R38,IF(AND(Dados_Observados_v4!Q38<>"",(2023-2022)<=Metodologia_v4!$B$13),Dados_Observados_v4!Q38,"")) | S38: =IF(Dados_Observados_v4!S38<>"",Dados_Observados_v4!S38,IF(AND(Dados_Observados_v4!R38<>"",(2024-2023)<=Metodologia_v4!$B$13),Dados_Observados_v4!R38,"")) | T38: =IF(Dados_Observados_v4!T38<>"",Dados_Observados_v4!T38,IF(AND(Dados_Observados_v4!R38<>"",(2025-2023)<=Metodologia_v4!$B$13),Dados_Observados_v4!R38,""))
A39: INF06 | B39: 5. Infraestruturas e Serviços | C39: Utilizadores de internet | D39: Banco Mundial/ITU | E39: IT.NET.USER.ZS | F39: Fonte Banco Mundial API/CSV | G39: 10/11 | H39: 2024 | I39: Referenciado pelas regras de Metodologia_v4 | J39: =IF(Dados_Observados_v4!J39<>"",Dados_Observados_v4!J39,IF(AND(Dados_Observados_v4!K39<>"",(2016-2015)<=Metodologia_v4!$B$14),Dados_Observados_v4!K39,"")) | K39: =IF(Dados_Observados_v4!K39<>"",Dados_Observados_v4!K39,IF(AND(Dados_Observados_v4!J39<>"",Dados_Observados_v4!L39<>"",(2017-2015-1)<=Metodologia_v4!$B$12),Dados_Observados_v4!J39+(Dados_Observados_v4!L39-Dados_Observados_v4!J39)*(2016-2015)/(2017-2015),IF(AND(Dados_Observados_v4!J39<>"",(2016-2015)<=Metodologia_v4!$B$13),Dados_Observados_v4!J39,IF(AND(Dados_Observados_v4!L39<>"",(2017-2016)<=Metodologia_v4!$B$14),Dados_Observados_v4!L39,"")))) | L39: =IF(Dados_Observados_v4!L39<>"",Dados_Observados_v4!L39,IF(AND(Dados_Observados_v4!K39<>"",Dados_Observados_v4!M39<>"",(2018-2016-1)<=Metodologia_v4!$B$12),Dados_Observados_v4!K39+(Dados_Observados_v4!M39-Dados_Observados_v4!K39)*(2017-2016)/(2018-2016),IF(AND(Dados_Observados_v4!K39<>"",(2017-2016)<=Metodologia_v4!$B$13),Dados_Observados_v4!K39,IF(AND(Dados_Observados_v4!M39<>"",(2018-2017)<=Metodologia_v4!$B$14),Dados_Observados_v4!M39,"")))) | M39: =IF(Dados_Observados_v4!M39<>"",Dados_Observados_v4!M39,IF(AND(Dados_Observados_v4!L39<>"",Dados_Observados_v4!N39<>"",(2019-2017-1)<=Metodologia_v4!$B$12),Dados_Observados_v4!L39+(Dados_Observados_v4!N39-Dados_Observados_v4!L39)*(2018-2017)/(2019-2017),IF(AND(Dados_Observados_v4!L39<>"",(2018-2017)<=Metodologia_v4!$B$13),Dados_Observados_v4!L39,IF(AND(Dados_Observados_v4!N39<>"",(2019-2018)<=Metodologia_v4!$B$14),Dados_Observados_v4!N39,"")))) | N39: =IF(Dados_Observados_v4!N39<>"",Dados_Observados_v4!N39,IF(AND(Dados_Observados_v4!M39<>"",Dados_Observados_v4!O39<>"",(2020-2018-1)<=Metodologia_v4!$B$12),Dados_Observados_v4!M39+(Dados_Observados_v4!O39-Dados_Observados_v4!M39)*(2019-2018)/(2020-2018),IF(AND(Dados_Observados_v4!M39<>"",(2019-2018)<=Metodologia_v4!$B$13),Dados_Observados_v4!M39,IF(AND(Dados_Observados_v4!O39<>"",(2020-2019)<=Metodologia_v4!$B$14),Dados_Observados_v4!O39,"")))) | O39: =IF(Dados_Observados_v4!O39<>"",Dados_Observados_v4!O39,IF(AND(Dados_Observados_v4!N39<>"",Dados_Observados_v4!P39<>"",(2021-2019-1)<=Metodologia_v4!$B$12),Dados_Observados_v4!N39+(Dados_Observados_v4!P39-Dados_Observados_v4!N39)*(2020-2019)/(2021-2019),IF(AND(Dados_Observados_v4!N39<>"",(2020-2019)<=Metodologia_v4!$B$13),Dados_Observados_v4!N39,IF(AND(Dados_Observados_v4!P39<>"",(2021-2020)<=Metodologia_v4!$B$14),Dados_Observados_v4!P39,"")))) | P39: =IF(Dados_Observados_v4!P39<>"",Dados_Observados_v4!P39,IF(AND(Dados_Observados_v4!O39<>"",Dados_Observados_v4!Q39<>"",(2022-2020-1)<=Metodologia_v4!$B$12),Dados_Observados_v4!O39+(Dados_Observados_v4!Q39-Dados_Observados_v4!O39)*(2021-2020)/(2022-2020),IF(AND(Dados_Observados_v4!O39<>"",(2021-2020)<=Metodologia_v4!$B$13),Dados_Observados_v4!O39,IF(AND(Dados_Observados_v4!Q39<>"",(2022-2021)<=Metodologia_v4!$B$14),Dados_Observados_v4!Q39,"")))) | Q39: =IF(Dados_Observados_v4!Q39<>"",Dados_Observados_v4!Q39,IF(AND(Dados_Observados_v4!P39<>"",Dados_Observados_v4!R39<>"",(2023-2021-1)<=Metodologia_v4!$B$12),Dados_Observados_v4!P39+(Dados_Observados_v4!R39-Dados_Observados_v4!P39)*(2022-2021)/(2023-2021),IF(AND(Dados_Observados_v4!P39<>"",(2022-2021)<=Metodologia_v4!$B$13),Dados_Observados_v4!P39,IF(AND(Dados_Observados_v4!R39<>"",(2023-2022)<=Metodologia_v4!$B$14),Dados_Observados_v4!R39,"")))) | R39: =IF(Dados_Observados_v4!R39<>"",Dados_Observados_v4!R39,IF(AND(Dados_Observados_v4!Q39<>"",Dados_Observados_v4!S39<>"",(2024-2022-1)<=Metodologia_v4!$B$12),Dados_Observados_v4!Q39+(Dados_Observados_v4!S39-Dados_Observados_v4!Q39)*(2023-2022)/(2024-2022),IF(AND(Dados_Observados_v4!Q39<>"",(2023-2022)<=Metodologia_v4!$B$13),Dados_Observados_v4!Q39,IF(AND(Dados_Observados_v4!S39<>"",(2024-2023)<=Metodologia_v4!$B$14),Dados_Observados_v4!S39,"")))) | S39: =IF(Dados_Observados_v4!S39<>"",Dados_Observados_v4!S39,IF(AND(Dados_Observados_v4!R39<>"",(2024-2023)<=Metodologia_v4!$B$13),Dados_Observados_v4!R39,"")) | T39: =IF(Dados_Observados_v4!T39<>"",Dados_Observados_v4!T39,IF(AND(Dados_Observados_v4!S39<>"",(2025-2024)<=Metodologia_v4!$B$13),Dados_Observados_v4!S39,""))
A40: INF07 | B40: 5. Infraestruturas e Serviços | C40: Subscrições móveis | D40: Banco Mundial/ITU | E40: IT.CEL.SETS.P2 | F40: Fonte Banco Mundial API/CSV | G40: 10/11 | H40: 2024 | I40: Referenciado pelas regras de Metodologia_v4 | J40: =IF(Dados_Observados_v4!J40<>"",Dados_Observados_v4!J40,IF(AND(Dados_Observados_v4!K40<>"",(2016-2015)<=Metodologia_v4!$B$14),Dados_Observados_v4!K40,"")) | K40: =IF(Dados_Observados_v4!K40<>"",Dados_Observados_v4!K40,IF(AND(Dados_Observados_v4!J40<>"",Dados_Observados_v4!L40<>"",(2017-2015-1)<=Metodologia_v4!$B$12),Dados_Observados_v4!J40+(Dados_Observados_v4!L40-Dados_Observados_v4!J40)*(2016-2015)/(2017-2015),IF(AND(Dados_Observados_v4!J40<>"",(2016-2015)<=Metodologia_v4!$B$13),Dados_Observados_v4!J40,IF(AND(Dados_Observados_v4!L40<>"",(2017-2016)<=Metodologia_v4!$B$14),Dados_Observados_v4!L40,"")))) | L40: =IF(Dados_Observados_v4!L40<>"",Dados_Observados_v4!L40,IF(AND(Dados_Observados_v4!K40<>"",Dados_Observados_v4!M40<>"",(2018-2016-1)<=Metodologia_v4!$B$12),Dados_Observados_v4!K40+(Dados_Observados_v4!M40-Dados_Observados_v4!K40)*(2017-2016)/(2018-2016),IF(AND(Dados_Observados_v4!K40<>"",(2017-2016)<=Metodologia_v4!$B$13),Dados_Observados_v4!K40,IF(AND(Dados_Observados_v4!M40<>"",(2018-2017)<=Metodologia_v4!$B$14),Dados_Observados_v4!M40,"")))) | M40: =IF(Dados_Observados_v4!M40<>"",Dados_Observados_v4!M40,IF(AND(Dados_Observados_v4!L40<>"",Dados_Observados_v4!N40<>"",(2019-2017-1)<=Metodologia_v4!$B$12),Dados_Observados_v4!L40+(Dados_Observados_v4!N40-Dados_Observados_v4!L40)*(2018-2017)/(2019-2017),IF(AND(Dados_Observados_v4!L40<>"",(2018-2017)<=Metodologia_v4!$B$13),Dados_Observados_v4!L40,IF(AND(Dados_Observados_v4!N40<>"",(2019-2018)<=Metodologia_v4!$B$14),Dados_Observados_v4!N40,"")))) | N40: =IF(Dados_Observados_v4!N40<>"",Dados_Observados_v4!N40,IF(AND(Dados_Observados_v4!M40<>"",Dados_Observados_v4!O40<>"",(2020-2018-1)<=Metodologia_v4!$B$12),Dados_Observados_v4!M40+(Dados_Observados_v4!O40-Dados_Observados_v4!M40)*(2019-2018)/(2020-2018),IF(AND(Dados_Observados_v4!M40<>"",(2019-2018)<=Metodologia_v4!$B$13),Dados_Observados_v4!M40,IF(AND(Dados_Observados_v4!O40<>"",(2020-2019)<=Metodologia_v4!$B$14),Dados_Observados_v4!O40,"")))) | O40: =IF(Dados_Observados_v4!O40<>"",Dados_Observados_v4!O40,IF(AND(Dados_Observados_v4!N40<>"",Dados_Observados_v4!P40<>"",(2021-2019-1)<=Metodologia_v4!$B$12),Dados_Observados_v4!N40+(Dados_Observados_v4!P40-Dados_Observados_v4!N40)*(2020-2019)/(2021-2019),IF(AND(Dados_Observados_v4!N40<>"",(2020-2019)<=Metodologia_v4!$B$13),Dados_Observados_v4!N40,IF(AND(Dados_Observados_v4!P40<>"",(2021-2020)<=Metodologia_v4!$B$14),Dados_Observados_v4!P40,"")))) | P40: =IF(Dados_Observados_v4!P40<>"",Dados_Observados_v4!P40,IF(AND(Dados_Observados_v4!O40<>"",Dados_Observados_v4!Q40<>"",(2022-2020-1)<=Metodologia_v4!$B$12),Dados_Observados_v4!O40+(Dados_Observados_v4!Q40-Dados_Observados_v4!O40)*(2021-2020)/(2022-2020),IF(AND(Dados_Observados_v4!O40<>"",(2021-2020)<=Metodologia_v4!$B$13),Dados_Observados_v4!O40,IF(AND(Dados_Observados_v4!Q40<>"",(2022-2021)<=Metodologia_v4!$B$14),Dados_Observados_v4!Q40,"")))) | Q40: =IF(Dados_Observados_v4!Q40<>"",Dados_Observados_v4!Q40,IF(AND(Dados_Observados_v4!P40<>"",Dados_Observados_v4!R40<>"",(2023-2021-1)<=Metodologia_v4!$B$12),Dados_Observados_v4!P40+(Dados_Observados_v4!R40-Dados_Observados_v4!P40)*(2022-2021)/(2023-2021),IF(AND(Dados_Observados_v4!P40<>"",(2022-2021)<=Metodologia_v4!$B$13),Dados_Observados_v4!P40,IF(AND(Dados_Observados_v4!R40<>"",(2023-2022)<=Metodologia_v4!$B$14),Dados_Observados_v4!R40,"")))) | R40: =IF(Dados_Observados_v4!R40<>"",Dados_Observados_v4!R40,IF(AND(Dados_Observados_v4!Q40<>"",Dados_Observados_v4!S40<>"",(2024-2022-1)<=Metodologia_v4!$B$12),Dados_Observados_v4!Q40+(Dados_Observados_v4!S40-Dados_Observados_v4!Q40)*(2023-2022)/(2024-2022),IF(AND(Dados_Observados_v4!Q40<>"",(2023-2022)<=Metodologia_v4!$B$13),Dados_Observados_v4!Q40,IF(AND(Dados_Observados_v4!S40<>"",(2024-2023)<=Metodologia_v4!$B$14),Dados_Observados_v4!S40,"")))) | S40: =IF(Dados_Observados_v4!S40<>"",Dados_Observados_v4!S40,IF(AND(Dados_Observados_v4!R40<>"",(2024-2023)<=Metodologia_v4!$B$13),Dados_Observados_v4!R40,"")) | T40: =IF(Dados_Observados_v4!T40<>"",Dados_Observados_v4!T40,IF(AND(Dados_Observados_v4!S40<>"",(2025-2024)<=Metodologia_v4!$B$13),Dados_Observados_v4!S40,""))
A41: INF08 | B41: 5. Infraestruturas e Serviços | C41: Banda larga fixa | D41: Banco Mundial/ITU | E41: IT.NET.BBND.P2 | F41: Fonte Banco Mundial API/CSV | G41: 10/11 | H41: 2024 | I41: Referenciado pelas regras de Metodologia_v4 | J41: =IF(Dados_Observados_v4!J41<>"",Dados_Observados_v4!J41,IF(AND(Dados_Observados_v4!K41<>"",(2016-2015)<=Metodologia_v4!$B$14),Dados_Observados_v4!K41,"")) | K41: =IF(Dados_Observados_v4!K41<>"",Dados_Observados_v4!K41,IF(AND(Dados_Observados_v4!J41<>"",Dados_Observados_v4!L41<>"",(2017-2015-1)<=Metodologia_v4!$B$12),Dados_Observados_v4!J41+(Dados_Observados_v4!L41-Dados_Observados_v4!J41)*(2016-2015)/(2017-2015),IF(AND(Dados_Observados_v4!J41<>"",(2016-2015)<=Metodologia_v4!$B$13),Dados_Observados_v4!J41,IF(AND(Dados_Observados_v4!L41<>"",(2017-2016)<=Metodologia_v4!$B$14),Dados_Observados_v4!L41,"")))) | L41: =IF(Dados_Observados_v4!L41<>"",Dados_Observados_v4!L41,IF(AND(Dados_Observados_v4!K41<>"",Dados_Observados_v4!M41<>"",(2018-2016-1)<=Metodologia_v4!$B$12),Dados_Observados_v4!K41+(Dados_Observados_v4!M41-Dados_Observados_v4!K41)*(2017-2016)/(2018-2016),IF(AND(Dados_Observados_v4!K41<>"",(2017-2016)<=Metodologia_v4!$B$13),Dados_Observados_v4!K41,IF(AND(Dados_Observados_v4!M41<>"",(2018-2017)<=Metodologia_v4!$B$14),Dados_Observados_v4!M41,"")))) | M41: =IF(Dados_Observados_v4!M41<>"",Dados_Observados_v4!M41,IF(AND(Dados_Observados_v4!L41<>"",Dados_Observados_v4!N41<>"",(2019-2017-1)<=Metodologia_v4!$B$12),Dados_Observados_v4!L41+(Dados_Observados_v4!N41-Dados_Observados_v4!L41)*(2018-2017)/(2019-2017),IF(AND(Dados_Observados_v4!L41<>"",(2018-2017)<=Metodologia_v4!$B$13),Dados_Observados_v4!L41,IF(AND(Dados_Observados_v4!N41<>"",(2019-2018)<=Metodologia_v4!$B$14),Dados_Observados_v4!N41,"")))) | N41: =IF(Dados_Observados_v4!N41<>"",Dados_Observados_v4!N41,IF(AND(Dados_Observados_v4!M41<>"",Dados_Observados_v4!O41<>"",(2020-2018-1)<=Metodologia_v4!$B$12),Dados_Observados_v4!M41+(Dados_Observados_v4!O41-Dados_Observados_v4!M41)*(2019-2018)/(2020-2018),IF(AND(Dados_Observados_v4!M41<>"",(2019-2018)<=Metodologia_v4!$B$13),Dados_Observados_v4!M41,IF(AND(Dados_Observados_v4!O41<>"",(2020-2019)<=Metodologia_v4!$B$14),Dados_Observados_v4!O41,"")))) | O41: =IF(Dados_Observados_v4!O41<>"",Dados_Observados_v4!O41,IF(AND(Dados_Observados_v4!N41<>"",Dados_Observados_v4!P41<>"",(2021-2019-1)<=Metodologia_v4!$B$12),Dados_Observados_v4!N41+(Dados_Observados_v4!P41-Dados_Observados_v4!N41)*(2020-2019)/(2021-2019),IF(AND(Dados_Observados_v4!N41<>"",(2020-2019)<=Metodologia_v4!$B$13),Dados_Observados_v4!N41,IF(AND(Dados_Observados_v4!P41<>"",(2021-2020)<=Metodologia_v4!$B$14),Dados_Observados_v4!P41,"")))) | P41: =IF(Dados_Observados_v4!P41<>"",Dados_Observados_v4!P41,IF(AND(Dados_Observados_v4!O41<>"",Dados_Observados_v4!Q41<>"",(2022-2020-1)<=Metodologia_v4!$B$12),Dados_Observados_v4!O41+(Dados_Observados_v4!Q41-Dados_Observados_v4!O41)*(2021-2020)/(2022-2020),IF(AND(Dados_Observados_v4!O41<>"",(2021-2020)<=Metodologia_v4!$B$13),Dados_Observados_v4!O41,IF(AND(Dados_Observados_v4!Q41<>"",(2022-2021)<=Metodologia_v4!$B$14),Dados_Observados_v4!Q41,"")))) | Q41: =IF(Dados_Observados_v4!Q41<>"",Dados_Observados_v4!Q41,IF(AND(Dados_Observados_v4!P41<>"",Dados_Observados_v4!R41<>"",(2023-2021-1)<=Metodologia_v4!$B$12),Dados_Observados_v4!P41+(Dados_Observados_v4!R41-Dados_Observados_v4!P41)*(2022-2021)/(2023-2021),IF(AND(Dados_Observados_v4!P41<>"",(2022-2021)<=Metodologia_v4!$B$13),Dados_Observados_v4!P41,IF(AND(Dados_Observados_v4!R41<>"",(2023-2022)<=Metodologia_v4!$B$14),Dados_Observados_v4!R41,"")))) | R41: =IF(Dados_Observados_v4!R41<>"",Dados_Observados_v4!R41,IF(AND(Dados_Observados_v4!Q41<>"",Dados_Observados_v4!S41<>"",(2024-2022-1)<=Metodologia_v4!$B$12),Dados_Observados_v4!Q41+(Dados_Observados_v4!S41-Dados_Observados_v4!Q41)*(2023-2022)/(2024-2022),IF(AND(Dados_Observados_v4!Q41<>"",(2023-2022)<=Metodologia_v4!$B$13),Dados_Observados_v4!Q41,IF(AND(Dados_Observados_v4!S41<>"",(2024-2023)<=Metodologia_v4!$B$14),Dados_Observados_v4!S41,"")))) | S41: =IF(Dados_Observados_v4!S41<>"",Dados_Observados_v4!S41,IF(AND(Dados_Observados_v4!R41<>"",(2024-2023)<=Metodologia_v4!$B$13),Dados_Observados_v4!R41,"")) | T41: =IF(Dados_Observados_v4!T41<>"",Dados_Observados_v4!T41,IF(AND(Dados_Observados_v4!S41<>"",(2025-2024)<=Metodologia_v4!$B$13),Dados_Observados_v4!S41,""))
A42: INF09 | B42: 5. Infraestruturas e Serviços | C42: Densidade rodoviária | D42: MINTRANS / ficheiro base | F42: Série observada do ficheiro base | G42: 10/11 | H42: 2024 | I42: Referenciado pelas regras de Metodologia_v4 | J42: =IF(Dados_Observados_v4!J42<>"",Dados_Observados_v4!J42,IF(AND(Dados_Observados_v4!K42<>"",(2016-2015)<=Metodologia_v4!$B$14),Dados_Observados_v4!K42,"")) | K42: =IF(Dados_Observados_v4!K42<>"",Dados_Observados_v4!K42,IF(AND(Dados_Observados_v4!J42<>"",Dados_Observados_v4!L42<>"",(2017-2015-1)<=Metodologia_v4!$B$12),Dados_Observados_v4!J42+(Dados_Observados_v4!L42-Dados_Observados_v4!J42)*(2016-2015)/(2017-2015),IF(AND(Dados_Observados_v4!J42<>"",(2016-2015)<=Metodologia_v4!$B$13),Dados_Observados_v4!J42,IF(AND(Dados_Observados_v4!L42<>"",(2017-2016)<=Metodologia_v4!$B$14),Dados_Observados_v4!L42,"")))) | L42: =IF(Dados_Observados_v4!L42<>"",Dados_Observados_v4!L42,IF(AND(Dados_Observados_v4!K42<>"",Dados_Observados_v4!M42<>"",(2018-2016-1)<=Metodologia_v4!$B$12),Dados_Observados_v4!K42+(Dados_Observados_v4!M42-Dados_Observados_v4!K42)*(2017-2016)/(2018-2016),IF(AND(Dados_Observados_v4!K42<>"",(2017-2016)<=Metodologia_v4!$B$13),Dados_Observados_v4!K42,IF(AND(Dados_Observados_v4!M42<>"",(2018-2017)<=Metodologia_v4!$B$14),Dados_Observados_v4!M42,"")))) | M42: =IF(Dados_Observados_v4!M42<>"",Dados_Observados_v4!M42,IF(AND(Dados_Observados_v4!L42<>"",Dados_Observados_v4!N42<>"",(2019-2017-1)<=Metodologia_v4!$B$12),Dados_Observados_v4!L42+(Dados_Observados_v4!N42-Dados_Observados_v4!L42)*(2018-2017)/(2019-2017),IF(AND(Dados_Observados_v4!L42<>"",(2018-2017)<=Metodologia_v4!$B$13),Dados_Observados_v4!L42,IF(AND(Dados_Observados_v4!N42<>"",(2019-2018)<=Metodologia_v4!$B$14),Dados_Observados_v4!N42,"")))) | N42: =IF(Dados_Observados_v4!N42<>"",Dados_Observados_v4!N42,IF(AND(Dados_Observados_v4!M42<>"",Dados_Observados_v4!O42<>"",(2020-2018-1)<=Metodologia_v4!$B$12),Dados_Observados_v4!M42+(Dados_Observados_v4!O42-Dados_Observados_v4!M42)*(2019-2018)/(2020-2018),IF(AND(Dados_Observados_v4!M42<>"",(2019-2018)<=Metodologia_v4!$B$13),Dados_Observados_v4!M42,IF(AND(Dados_Observados_v4!O42<>"",(2020-2019)<=Metodologia_v4!$B$14),Dados_Observados_v4!O42,"")))) | O42: =IF(Dados_Observados_v4!O42<>"",Dados_Observados_v4!O42,IF(AND(Dados_Observados_v4!N42<>"",Dados_Observados_v4!P42<>"",(2021-2019-1)<=Metodologia_v4!$B$12),Dados_Observados_v4!N42+(Dados_Observados_v4!P42-Dados_Observados_v4!N42)*(2020-2019)/(2021-2019),IF(AND(Dados_Observados_v4!N42<>"",(2020-2019)<=Metodologia_v4!$B$13),Dados_Observados_v4!N42,IF(AND(Dados_Observados_v4!P42<>"",(2021-2020)<=Metodologia_v4!$B$14),Dados_Observados_v4!P42,"")))) | P42: =IF(Dados_Observados_v4!P42<>"",Dados_Observados_v4!P42,IF(AND(Dados_Observados_v4!O42<>"",Dados_Observados_v4!Q42<>"",(2022-2020-1)<=Metodologia_v4!$B$12),Dados_Observados_v4!O42+(Dados_Observados_v4!Q42-Dados_Observados_v4!O42)*(2021-2020)/(2022-2020),IF(AND(Dados_Observados_v4!O42<>"",(2021-2020)<=Metodologia_v4!$B$13),Dados_Observados_v4!O42,IF(AND(Dados_Observados_v4!Q42<>"",(2022-2021)<=Metodologia_v4!$B$14),Dados_Observados_v4!Q42,"")))) | Q42: =IF(Dados_Observados_v4!Q42<>"",Dados_Observados_v4!Q42,IF(AND(Dados_Observados_v4!P42<>"",Dados_Observados_v4!R42<>"",(2023-2021-1)<=Metodologia_v4!$B$12),Dados_Observados_v4!P42+(Dados_Observados_v4!R42-Dados_Observados_v4!P42)*(2022-2021)/(2023-2021),IF(AND(Dados_Observados_v4!P42<>"",(2022-2021)<=Metodologia_v4!$B$13),Dados_Observados_v4!P42,IF(AND(Dados_Observados_v4!R42<>"",(2023-2022)<=Metodologia_v4!$B$14),Dados_Observados_v4!R42,"")))) | R42: =IF(Dados_Observados_v4!R42<>"",Dados_Observados_v4!R42,IF(AND(Dados_Observados_v4!Q42<>"",Dados_Observados_v4!S42<>"",(2024-2022-1)<=Metodologia_v4!$B$12),Dados_Observados_v4!Q42+(Dados_Observados_v4!S42-Dados_Observados_v4!Q42)*(2023-2022)/(2024-2022),IF(AND(Dados_Observados_v4!Q42<>"",(2023-2022)<=Metodologia_v4!$B$13),Dados_Observados_v4!Q42,IF(AND(Dados_Observados_v4!S42<>"",(2024-2023)<=Metodologia_v4!$B$14),Dados_Observados_v4!S42,"")))) | S42: =IF(Dados_Observados_v4!S42<>"",Dados_Observados_v4!S42,IF(AND(Dados_Observados_v4!R42<>"",(2024-2023)<=Metodologia_v4!$B$13),Dados_Observados_v4!R42,"")) | T42: =IF(Dados_Observados_v4!T42<>"",Dados_Observados_v4!T42,IF(AND(Dados_Observados_v4!S42<>"",(2025-2024)<=Metodologia_v4!$B$13),Dados_Observados_v4!S42,""))
