Workbook

Sheet 00_Painel
B2: ÍNDICE GLOBAL DE DESENVOLVIMENTO DE ANGOLA (IGDA-BDA) — Selecção Final
B3: ="Período 2015–2025 · "&TEXT(SUMPRODUCT(('01_Criterios'!$C$26:$C$36=1)*1),"0")&" dimensões activas · "&TEXT(SUM('01_Criterios'!$H$26:$H$36),"0")&" indicadores seleccionados · selecção "&LOWER('01_Criterios'!$C$18) -> Período 2015–2025 · 8 dimensões activas · 41 indicadores seleccionados · selecção automática
B5: INDICADORES-CHAVE
B7: =IFERROR(LOOKUP(9.99E+307,'07_Subindices'!F18:P18),"–") -> 46.432549 | E7: =IFERROR(INDEX('07_Subindices'!F18:P18,MATCH(TRUE,INDEX(ISNUMBER('07_Subindices'!F18:P18),0),0)),"–") -> 43.248684 | H7: =IF('07_Subindices'!S18="","–",'07_Subindices'!S18) -> 3.1838649 | K7: =IFERROR(INDEX('07_Subindices'!$A$5:$A$15,MATCH(MAX('07_Subindices'!$T$5:$T$15),'07_Subindices'!$T$5:$T$15,0)),"–") -> Mercado Trabalho | N7: =IFERROR(INDEX('07_Subindices'!$A$5:$A$15,MATCH(MIN('07_Subindices'!$T$5:$T$15),'07_Subindices'!$T$5:$T$15,0)),"–") -> Diversificação
B9: ="IGDA "&IFERROR(LOOKUP(2,1/ISNUMBER('07_Subindices'!F18:P18),'07_Subindices'!$F$4:$P$4),"")&" (último ano)" -> IGDA 2025 (último ano) | E9: ="IGDA "&IFERROR(INDEX('07_Subindices'!$F$4:$P$4,MATCH(TRUE,INDEX(ISNUMBER('07_Subindices'!F18:P18),0),0)),"")&" (primeiro ano)" -> IGDA 2015 (primeiro ano) | H9: ="Variação no período (p.p.)" -> Variação no período (p.p.) | K9: ="Melhor dimensão (último ano)" -> Melhor dimensão (último ano) | N9: ="Pior dimensão (último ano)" -> Pior dimensão (último ano)
B11: =SUMPRODUCT(('01_Criterios'!$C$26:$C$36=1)*1)&" / 11" -> 8 / 11 | E11: =SUM('01_Criterios'!$H$26:$H$36) -> 41 | H11: =IFERROR(SUM('05_Flags_Qualidade'!$W$5:$W$114)/(SUM('05_Flags_Qualidade'!$V$5:$V$114)+SUM('05_Flags_Qualidade'!$W$5:$W$114)),0) -> 0.057649667 | K11: =IFERROR(LOOKUP(2,1/('07_Subindices'!F19:P19<>""),'07_Subindices'!F19:P19),"–") -> Médio
B12: ="Dimensões activas" -> Dimensões activas | E12: ="Indicadores no índice" -> Indicadores no índice | H12: ="Células estimadas (imputação)" -> Células estimadas (imputação) | K12: ="Classificação (último ano)" -> Classificação (último ano)
B14: NAVEGAÇÃO
B15: → 01 · Critérios de selecção | E15: Parâmetros, dimensões a incluir, nº de indicadores e modo automático/manual
B16: → 02 · Base potencial | E16: Catálogo completo de candidatos com dados de origem, scores e ranking
B17: → 03 · Base do índice | E17: Indicadores seleccionados (dados observados usados no índice)
B18: → 04 · Dados ajustados | E18: Séries completadas por interpolação/carry com limites controlados
B19: → 05 · Flags de qualidade | E19: Origem de cada célula: observada, estimada ou sem dado
B20: → 06 · Normalização | E20: Scores 0–100 com sentido direccional
B21: → 07 · Subíndices | E21: Subíndices por dimensão, IGDA global e diagnóstico de cobertura
B22: → 08 · Visualizações | E22: Mapa de calor, radar e variação entre anos
B23: → 09 · Metodologia | E23: Nota metodológica completa e instruções de utilização
B24: → 10 · Fontes | E24: Fontes e ligações de todos os indicadores
B26: EVOLUÇÃO DOS SUBÍNDICES
B27: Dimensão | C27: 2015 | D27: 2016 | E27: 2017 | F27: 2018 | G27: 2019 | H27: 2020 | I27: 2021 | J27: 2022 | K27: 2023 | L27: 2024 | M27: 2025
B28: ='07_Subindices'!A5 -> Governança | C28: =IF('07_Subindices'!F5="","",'07_Subindices'!F5) -> 27.415798 | D28: =IF('07_Subindices'!G5="","",'07_Subindices'!G5) -> 28.02715 | E28: =IF('07_Subindices'!H5="","",'07_Subindices'!H5) -> 27.731903 | F28: =IF('07_Subindices'!I5="","",'07_Subindices'!I5) -> 29.570946 | G28: =IF('07_Subindices'!J5="","",'07_Subindices'!J5) -> 31.678184 | H28: =IF('07_Subindices'!K5="","",'07_Subindices'!K5) -> 30.817962 | I28: =IF('07_Subindices'!L5="","",'07_Subindices'!L5) -> 31.100242 | J28: =IF('07_Subindices'!M5="","",'07_Subindices'!M5) -> 33.006382 | ... M28: =IF('07_Subindices'!P5="","",'07_Subindices'!P5) -> 33.193808
B29: ='07_Subindices'!A6 -> Macroeconomia | C29: =IF('07_Subindices'!F6="","",'07_Subindices'!F6) -> 49.133768 | D29: =IF('07_Subindices'!G6="","",'07_Subindices'!G6) -> 44.476292 | E29: =IF('07_Subindices'!H6="","",'07_Subindices'!H6) -> 46.557339 | F29: =IF('07_Subindices'!I6="","",'07_Subindices'!I6) -> 45.108331 | G29: =IF('07_Subindices'!J6="","",'07_Subindices'!J6) -> 44.095034 | H29: =IF('07_Subindices'!K6="","",'07_Subindices'!K6) -> 33.062574 | I29: =IF('07_Subindices'!L6="","",'07_Subindices'!L6) -> 48.695603 | J29: =IF('07_Subindices'!M6="","",'07_Subindices'!M6) -> 49.63024 | ... M29: =IF('07_Subindices'!P6="","",'07_Subindices'!P6) -> 49.659758
B30: ='07_Subindices'!A7 -> Capital Humano | C30: =IF('07_Subindices'!F7="","",'07_Subindices'!F7) -> 50.479034 | D30: =IF('07_Subindices'!G7="","",'07_Subindices'!G7) -> 56.862 | E30: =IF('07_Subindices'!H7="","",'07_Subindices'!H7) -> 56.5713 | F30: =IF('07_Subindices'!I7="","",'07_Subindices'!I7) -> 56.257329 | G30: =IF('07_Subindices'!J7="","",'07_Subindices'!J7) -> 56.302875 | H30: =IF('07_Subindices'!K7="","",'07_Subindices'!K7) -> 57.924943 | I30: =IF('07_Subindices'!L7="","",'07_Subindices'!L7) -> 56.994873 | J30: =IF('07_Subindices'!M7="","",'07_Subindices'!M7) -> 58.0475 | ... M30: =IF('07_Subindices'!P7="","",'07_Subindices'!P7) -> 59.0515
B31: ='07_Subindices'!A8 -> Inclusão Social | C31: =IF('07_Subindices'!F8="","",'07_Subindices'!F8) -> 50.768339 | D31: =IF('07_Subindices'!G8="","",'07_Subindices'!G8) -> 47.543051 | E31: =IF('07_Subindices'!H8="","",'07_Subindices'!H8) -> 42.712295 | F31: =IF('07_Subindices'!I8="","",'07_Subindices'!I8) -> 42.157123 | G31: =IF('07_Subindices'!J8="","",'07_Subindices'!J8) -> 42.722414 | H31: =IF('07_Subindices'!K8="","",'07_Subindices'!K8) -> 42.114943 | I31: =IF('07_Subindices'!L8="","",'07_Subindices'!L8) -> 41.670463 | J31: =IF('07_Subindices'!M8="","",'07_Subindices'!M8) -> 44.068478 | ... M31: =IF('07_Subindices'!P8="","",'07_Subindices'!P8) -> 49.409126
B32: ='07_Subindices'!A9 -> Infraestruturas | C32: =IF('07_Subindices'!F9="","",'07_Subindices'!F9) -> 45.989556 | D32: =IF('07_Subindices'!G9="","",'07_Subindices'!G9) -> 39.273909 | E32: =IF('07_Subindices'!H9="","",'07_Subindices'!H9) -> 44.683769 | F32: =IF('07_Subindices'!I9="","",'07_Subindices'!I9) -> 42.12924 | G32: =IF('07_Subindices'!J9="","",'07_Subindices'!J9) -> 44.854886 | H32: =IF('07_Subindices'!K9="","",'07_Subindices'!K9) -> 42.272599 | I32: =IF('07_Subindices'!L9="","",'07_Subindices'!L9) -> 44.079489 | J32: =IF('07_Subindices'!M9="","",'07_Subindices'!M9) -> 45.81254 | ... M32: =IF('07_Subindices'!P9="","",'07_Subindices'!P9) -> 47.984623
B33: ='07_Subindices'!A10 -> Mercado Trabalho | C33: =IF('07_Subindices'!F10="","",'07_Subindices'!F10) -> 65.104271 | D33: =IF('07_Subindices'!G10="","",'07_Subindices'!G10) -> 63.743466 | E33: =IF('07_Subindices'!H10="","",'07_Subindices'!H10) -> 63.451158 | F33: =IF('07_Subindices'!I10="","",'07_Subindices'!I10) -> 62.984662 | G33: =IF('07_Subindices'!J10="","",'07_Subindices'!J10) -> 62.98275 | H33: =IF('07_Subindices'!K10="","",'07_Subindices'!K10) -> 59.20706 | I33: =IF('07_Subindices'!L10="","",'07_Subindices'!L10) -> 62.696663 | J33: =IF('07_Subindices'!M10="","",'07_Subindices'!M10) -> 67.141387 | ... M33: =IF('07_Subindices'!P10="","",'07_Subindices'!P10) -> 66.04686
B34: ='07_Subindices'!A11 -> Saúde/Alimentar | C34: =IF('07_Subindices'!F11="","",'07_Subindices'!F11) -> 59.244851 | D34: =IF('07_Subindices'!G11="","",'07_Subindices'!G11) -> 58.281855 | E34: =IF('07_Subindices'!H11="","",'07_Subindices'!H11) -> 57.759991 | F34: =IF('07_Subindices'!I11="","",'07_Subindices'!I11) -> 58.248643 | G34: =IF('07_Subindices'!J11="","",'07_Subindices'!J11) -> 58.239981 | H34: =IF('07_Subindices'!K11="","",'07_Subindices'!K11) -> 58.150154 | I34: =IF('07_Subindices'!L11="","",'07_Subindices'!L11) -> 56.503793 | J34: =IF('07_Subindices'!M11="","",'07_Subindices'!M11) -> 56.375636 | ... M34: =IF('07_Subindices'!P11="","",'07_Subindices'!P11) -> 57.021835
B35: ='07_Subindices'!A12 -> Diversificação | C35: =IF('07_Subindices'!F12="","",'07_Subindices'!F12) -> 19.988441 | D35: =IF('07_Subindices'!G12="","",'07_Subindices'!G12) -> 23.478583 | E35: =IF('07_Subindices'!H12="","",'07_Subindices'!H12) -> 24.641194 | F35: =IF('07_Subindices'!I12="","",'07_Subindices'!I12) -> 23.183337 | G35: =IF('07_Subindices'!J12="","",'07_Subindices'!J12) -> 21.835223 | H35: =IF('07_Subindices'!K12="","",'07_Subindices'!K12) -> 17.201785 | I35: =IF('07_Subindices'!L12="","",'07_Subindices'!L12) -> 24.551909 | J35: =IF('07_Subindices'!M12="","",'07_Subindices'!M12) -> 22.852556 | ... M35: =IF('07_Subindices'!P12="","",'07_Subindices'!P12) -> 24.859076
B36: ='07_Subindices'!A13 -> Ambiente | C36: =IF('07_Subindices'!F13="","",'07_Subindices'!F13) | D36: =IF('07_Subindices'!G13="","",'07_Subindices'!G13) | E36: =IF('07_Subindices'!H13="","",'07_Subindices'!H13) | F36: =IF('07_Subindices'!I13="","",'07_Subindices'!I13) | G36: =IF('07_Subindices'!J13="","",'07_Subindices'!J13) | H36: =IF('07_Subindices'!K13="","",'07_Subindices'!K13) | I36: =IF('07_Subindices'!L13="","",'07_Subindices'!L13) | J36: =IF('07_Subindices'!M13="","",'07_Subindices'!M13) | ... M36: =IF('07_Subindices'!P13="","",'07_Subindices'!P13)
B37: ='07_Subindices'!A14 -> Demografia | C37: =IF('07_Subindices'!F14="","",'07_Subindices'!F14) | D37: =IF('07_Subindices'!G14="","",'07_Subindices'!G14) | E37: =IF('07_Subindices'!H14="","",'07_Subindices'!H14) | F37: =IF('07_Subindices'!I14="","",'07_Subindices'!I14) | G37: =IF('07_Subindices'!J14="","",'07_Subindices'!J14) | H37: =IF('07_Subindices'!K14="","",'07_Subindices'!K14) | I37: =IF('07_Subindices'!L14="","",'07_Subindices'!L14) | J37: =IF('07_Subindices'!M14="","",'07_Subindices'!M14) | ... M37: =IF('07_Subindices'!P14="","",'07_Subindices'!P14)
B38: ='07_Subindices'!A15 -> Digital/Inovação | C38: =IF('07_Subindices'!F15="","",'07_Subindices'!F15) | D38: =IF('07_Subindices'!G15="","",'07_Subindices'!G15) | E38: =IF('07_Subindices'!H15="","",'07_Subindices'!H15) | F38: =IF('07_Subindices'!I15="","",'07_Subindices'!I15) | G38: =IF('07_Subindices'!J15="","",'07_Subindices'!J15) | H38: =IF('07_Subindices'!K15="","",'07_Subindices'!K15) | I38: =IF('07_Subindices'!L15="","",'07_Subindices'!L15) | J38: =IF('07_Subindices'!M15="","",'07_Subindices'!M15) | ... M38: =IF('07_Subindices'!P15="","",'07_Subindices'!P15)
B39: IGDA GLOBAL | C39: =IF('07_Subindices'!F18="","",'07_Subindices'!F18) -> 43.248684 | D39: =IF('07_Subindices'!G18="","",'07_Subindices'!G18) -> 42.933393 | E39: =IF('07_Subindices'!H18="","",'07_Subindices'!H18) -> 43.400965 | F39: =IF('07_Subindices'!I18="","",'07_Subindices'!I18) -> 42.835765 | G39: =IF('07_Subindices'!J18="","",'07_Subindices'!J18) -> 43.173605 | H39: =IF('07_Subindices'!K18="","",'07_Subindices'!K18) -> 39.742017 | I39: =IF('07_Subindices'!L18="","",'07_Subindices'!L18) -> 43.898046 | J39: =IF('07_Subindices'!M18="","",'07_Subindices'!M18) -> 44.929553 | ... M39: =IF('07_Subindices'!P18="","",'07_Subindices'!P18) -> 46.432549
B42: DESTAQUES AUTOMÁTICOS
B43: ="• IGDA no último ano com dados: "&IFERROR(FIXED(LOOKUP(9.99E+307,'07_Subindices'!F18:P18),1),"–")&" ("&IFERROR(LOOKUP(2,1/ISNUMBER('07_Subindices'!F18:P18),'07_Subindices'!$F$4:$P$4),"–")&") — classificação "&IFERROR(LOOKUP(2,1/('07_Subindices'!F19:P19<>""),'07_Subindices'!F19:P19),"–") -> • IGDA no último ano com dados: 46,4 (2025) — classificação Médio
B44: ="• Variação no período: "&IF('07_Subindices'!S18="","–",FIXED('07_Subindices'!S18,1))&" p.p. desde "&IFERROR(INDEX('07_Subindices'!$F$4:$P$4,MATCH(TRUE,INDEX(ISNUMBER('07_Subindices'!F18:P18),0),0)),"–") -> • Variação no período: 3,2 p.p. desde 2015
B45: ="• Dimensão mais forte: "&IFERROR(INDEX('07_Subindices'!$A$5:$A$15,MATCH(MAX('07_Subindices'!$T$5:$T$15),'07_Subindices'!$T$5:$T$15,0))&" ("&FIXED(MAX('07_Subindices'!$T$5:$T$15),1)&")","–") -> • Dimensão mais forte: Mercado Trabalho (66,0)
B46: ="• Dimensão mais fraca: "&IFERROR(INDEX('07_Subindices'!$A$5:$A$15,MATCH(MIN('07_Subindices'!$T$5:$T$15),'07_Subindices'!$T$5:$T$15,0))&" ("&FIXED(MIN('07_Subindices'!$T$5:$T$15),1)&")","–") -> • Dimensão mais fraca: Diversificação (24,9)
B47: ="• Maior progresso no período: "&IFERROR(INDEX('07_Subindices'!$A$5:$A$15,MATCH(MAX('07_Subindices'!$U$5:$U$15),'07_Subindices'!$U$5:$U$15,0))&" ("&FIXED(MAX('07_Subindices'!$U$5:$U$15),1)&" p.p.)","–") -> • Maior progresso no período: Capital Humano (8,6 p.p.)
B48: ="• Maior retrocesso no período: "&IFERROR(INDEX('07_Subindices'!$A$5:$A$15,MATCH(MIN('07_Subindices'!$U$5:$U$15),'07_Subindices'!$U$5:$U$15,0))&" ("&FIXED(MIN('07_Subindices'!$U$5:$U$15),1)&" p.p.)","–") -> • Maior retrocesso no período: Saúde/Alimentar (-2,2 p.p.)

Sheet 01_Criterios
A1: ← Painel
B2: CRITÉRIOS DE SELECÇÃO E PARÂMETROS DO ÍNDICE
B3: Células amarelas são editáveis. Tudo o resto recalcula automaticamente (selecção de indicadores, imputação, normalização, subíndices e IGDA).
B5: A. Parâmetros gerais
B6: Parâmetro | C6: Valor | D6: Explicação
B7: Ano inicial do período | C7: 2015 | D7: Período fixo desta versão (colunas 2015–2025).
B8: Ano final do período | C8: 2025 | D8: Usado no cálculo da recência dos indicadores.
B9: Escala normalizada mínima | C9: 0 | D9: Limite inferior dos scores normalizados.
B10: Escala normalizada máxima | C10: 100 | D10: Limite superior dos scores normalizados.
B11: Cobertura mínima do indicador (% de anos observados) | C11: 0.8 | D11: Indicadores abaixo deste limiar ficam inelegíveis (demasiado incompletos).
B12: Último ano observado mínimo (recência) | C12: 2023 | D12: Indicadores sem observações desde este ano são ignorados (desactualizados).
B13: Lacuna máxima para interpolação linear (anos) | C13: 2 | D13: Lacunas internas até este nº de anos são interpoladas linearmente.
B14: Carry-forward máximo no fim da série (anos) | C14: 2 | D14: Propagação do último valor observado, no máximo este nº de anos.
B15: Carry-backward máximo no início da série (anos) | C15: 2 | D15: Propagação retroactiva do primeiro valor observado.
B16: Cobertura mínima por subíndice (fracção de indicadores com score) | C16: 0.75 | D16: Num dado ano, o subíndice só é calculado se houver scores suficientes.
B17: Nº mínimo de subíndices para calcular o IGDA | C17: 4 | D17: Abaixo deste número o IGDA global não é calculado.
B18: Modo de selecção (Automática / Manual) | C18: Automática | D18: Automática: top-N por score + ajustes manuais. Manual: só entram os "Incluir".
B19: Peso do critério Relevância | C19: 0.4 | D19: Prioridade do indicador no catálogo.
B20: Peso do critério Completude | C20: 0.35 | D20: % de anos do período com observação.
B21: Peso do critério Consistência | C21: 0.25 | D21: Continuidade da série e recência.
B22: Bónus fonte nacional (pontos) | C22: 12 | D22: Acresce ao score de indicadores com fonte nacional (BNA/INE/IIMS).
B24: B. Dimensões do índice
B25: Dimensão | C25: Incluir? (1/0) | D25: Peso | E25: Indicadores alvo | F25: Candidatos | G25: Elegíveis | H25: Seleccionados | I25: Cobertura média (sel.) | J25: Score médio (sel.)
B26: 1. Governança e Estado de Direito | C26: 1 | D26: 1 | E26: 5 | F26: =COUNTIF('02_Base_Potencial'!$B$5:$B$335,$B26) -> 28 | G26: =SUMPRODUCT(('02_Base_Potencial'!$B$5:$B$335=$B26)*('02_Base_Potencial'!$AL$5:$AL$335=1)) -> 8 | H26: =SUMPRODUCT(('02_Base_Potencial'!$B$5:$B$335=$B26)*('02_Base_Potencial'!$AQ$5:$AQ$335=1)) -> 5 | I26: =IFERROR(SUMPRODUCT(('02_Base_Potencial'!$B$5:$B$335=$B26)*('02_Base_Potencial'!$AQ$5:$AQ$335=1),'02_Base_Potencial'!$AC$5:$AC$335)/$H26,"") -> 0.92727273 | J26: =IFERROR(SUMPRODUCT(('02_Base_Potencial'!$B$5:$B$335=$B26)*('02_Base_Potencial'!$AQ$5:$AQ$335=1),'02_Base_Potencial'!$AK$5:$AK$335)/$H26,"") -> 94.24
B27: 2. Estabilidade Macroeconómica | C27: 1 | D27: 1 | E27: 7 | F27: =COUNTIF('02_Base_Potencial'!$B$5:$B$335,$B27) -> 57 | G27: =SUMPRODUCT(('02_Base_Potencial'!$B$5:$B$335=$B27)*('02_Base_Potencial'!$AL$5:$AL$335=1)) -> 48 | H27: =SUMPRODUCT(('02_Base_Potencial'!$B$5:$B$335=$B27)*('02_Base_Potencial'!$AQ$5:$AQ$335=1)) -> 7 | I27: =IFERROR(SUMPRODUCT(('02_Base_Potencial'!$B$5:$B$335=$B27)*('02_Base_Potencial'!$AQ$5:$AQ$335=1),'02_Base_Potencial'!$AC$5:$AC$335)/$H27,"") -> 1 | J27: =IFERROR(SUMPRODUCT(('02_Base_Potencial'!$B$5:$B$335=$B27)*('02_Base_Potencial'!$AQ$5:$AQ$335=1),'02_Base_Potencial'!$AK$5:$AK$335)/$H27,"") -> 111.14286
B28: 3. Capital Humano | C28: 1 | D28: 1 | E28: 5 | F28: =COUNTIF('02_Base_Potencial'!$B$5:$B$335,$B28) -> 30 | G28: =SUMPRODUCT(('02_Base_Potencial'!$B$5:$B$335=$B28)*('02_Base_Potencial'!$AL$5:$AL$335=1)) -> 6 | H28: =SUMPRODUCT(('02_Base_Potencial'!$B$5:$B$335=$B28)*('02_Base_Potencial'!$AQ$5:$AQ$335=1)) -> 4 | I28: =IFERROR(SUMPRODUCT(('02_Base_Potencial'!$B$5:$B$335=$B28)*('02_Base_Potencial'!$AQ$5:$AQ$335=1),'02_Base_Potencial'!$AC$5:$AC$335)/$H28,"") -> 0.93181818 | J28: =IFERROR(SUMPRODUCT(('02_Base_Potencial'!$B$5:$B$335=$B28)*('02_Base_Potencial'!$AQ$5:$AQ$335=1),'02_Base_Potencial'!$AK$5:$AK$335)/$H28,"") -> 90.225
B29: 4. Inclusão Social e Protecção | C29: 1 | D29: 1 | E29: 5 | F29: =COUNTIF('02_Base_Potencial'!$B$5:$B$335,$B29) -> 30 | G29: =SUMPRODUCT(('02_Base_Potencial'!$B$5:$B$335=$B29)*('02_Base_Potencial'!$AL$5:$AL$335=1)) -> 5 | H29: =SUMPRODUCT(('02_Base_Potencial'!$B$5:$B$335=$B29)*('02_Base_Potencial'!$AQ$5:$AQ$335=1)) -> 3 | I29: =IFERROR(SUMPRODUCT(('02_Base_Potencial'!$B$5:$B$335=$B29)*('02_Base_Potencial'!$AQ$5:$AQ$335=1),'02_Base_Potencial'!$AC$5:$AC$335)/$H29,"") -> 0.96969697 | J29: =IFERROR(SUMPRODUCT(('02_Base_Potencial'!$B$5:$B$335=$B29)*('02_Base_Potencial'!$AQ$5:$AQ$335=1),'02_Base_Potencial'!$AK$5:$AK$335)/$H29,"") -> 96.166667
B30: 5. Infraestruturas e Serviços | C30: 1 | D30: 1 | E30: 5 | F30: =COUNTIF('02_Base_Potencial'!$B$5:$B$335,$B30) -> 33 | G30: =SUMPRODUCT(('02_Base_Potencial'!$B$5:$B$335=$B30)*('02_Base_Potencial'!$AL$5:$AL$335=1)) -> 17 | H30: =SUMPRODUCT(('02_Base_Potencial'!$B$5:$B$335=$B30)*('02_Base_Potencial'!$AQ$5:$AQ$335=1)) -> 5 | I30: =IFERROR(SUMPRODUCT(('02_Base_Potencial'!$B$5:$B$335=$B30)*('02_Base_Potencial'!$AQ$5:$AQ$335=1),'02_Base_Potencial'!$AC$5:$AC$335)/$H30,"") -> 0.87272727 | J30: =IFERROR(SUMPRODUCT(('02_Base_Potencial'!$B$5:$B$335=$B30)*('02_Base_Potencial'!$AQ$5:$AQ$335=1),'02_Base_Potencial'!$AK$5:$AK$335)/$H30,"") -> 89.62
B31: 6. Mercado de Trabalho | C31: 1 | D31: 1 | E31: 5 | F31: =COUNTIF('02_Base_Potencial'!$B$5:$B$335,$B31) -> 27 | G31: =SUMPRODUCT(('02_Base_Potencial'!$B$5:$B$335=$B31)*('02_Base_Potencial'!$AL$5:$AL$335=1)) -> 19 | H31: =SUMPRODUCT(('02_Base_Potencial'!$B$5:$B$335=$B31)*('02_Base_Potencial'!$AQ$5:$AQ$335=1)) -> 5 | I31: =IFERROR(SUMPRODUCT(('02_Base_Potencial'!$B$5:$B$335=$B31)*('02_Base_Potencial'!$AQ$5:$AQ$335=1),'02_Base_Potencial'!$AC$5:$AC$335)/$H31,"") -> 1 | J31: =IFERROR(SUMPRODUCT(('02_Base_Potencial'!$B$5:$B$335=$B31)*('02_Base_Potencial'!$AQ$5:$AQ$335=1),'02_Base_Potencial'!$AK$5:$AK$335)/$H31,"") -> 104.8
B32: 7. Segurança Alimentar e Saúde | C32: 1 | D32: 1 | E32: 7 | F32: =COUNTIF('02_Base_Potencial'!$B$5:$B$335,$B32) -> 37 | G32: =SUMPRODUCT(('02_Base_Potencial'!$B$5:$B$335=$B32)*('02_Base_Potencial'!$AL$5:$AL$335=1)) -> 17 | H32: =SUMPRODUCT(('02_Base_Potencial'!$B$5:$B$335=$B32)*('02_Base_Potencial'!$AQ$5:$AQ$335=1)) -> 7 | I32: =IFERROR(SUMPRODUCT(('02_Base_Potencial'!$B$5:$B$335=$B32)*('02_Base_Potencial'!$AQ$5:$AQ$335=1),'02_Base_Potencial'!$AC$5:$AC$335)/$H32,"") -> 0.88311688 | J32: =IFERROR(SUMPRODUCT(('02_Base_Potencial'!$B$5:$B$335=$B32)*('02_Base_Potencial'!$AQ$5:$AQ$335=1),'02_Base_Potencial'!$AK$5:$AK$335)/$H32,"") -> 96.957143
B33: 8. Diversificação Produtiva e Setor Privado | C33: 1 | D33: 1 | E33: 5 | F33: =COUNTIF('02_Base_Potencial'!$B$5:$B$335,$B33) -> 20 | G33: =SUMPRODUCT(('02_Base_Potencial'!$B$5:$B$335=$B33)*('02_Base_Potencial'!$AL$5:$AL$335=1)) -> 15 | H33: =SUMPRODUCT(('02_Base_Potencial'!$B$5:$B$335=$B33)*('02_Base_Potencial'!$AQ$5:$AQ$335=1)) -> 5 | I33: =IFERROR(SUMPRODUCT(('02_Base_Potencial'!$B$5:$B$335=$B33)*('02_Base_Potencial'!$AQ$5:$AQ$335=1),'02_Base_Potencial'!$AC$5:$AC$335)/$H33,"") -> 0.96363636 | J33: =IFERROR(SUMPRODUCT(('02_Base_Potencial'!$B$5:$B$335=$B33)*('02_Base_Potencial'!$AQ$5:$AQ$335=1),'02_Base_Potencial'!$AK$5:$AK$335)/$H33,"") -> 94.12
B34: 9. Ambiente, Clima e Resiliência | C34: 0 | D34: 1 | E34: 7 | F34: =COUNTIF('02_Base_Potencial'!$B$5:$B$335,$B34) -> 23 | G34: =SUMPRODUCT(('02_Base_Potencial'!$B$5:$B$335=$B34)*('02_Base_Potencial'!$AL$5:$AL$335=1)) -> 10 | H34: =SUMPRODUCT(('02_Base_Potencial'!$B$5:$B$335=$B34)*('02_Base_Potencial'!$AQ$5:$AQ$335=1)) -> 0 | I34: =IFERROR(SUMPRODUCT(('02_Base_Potencial'!$B$5:$B$335=$B34)*('02_Base_Potencial'!$AQ$5:$AQ$335=1),'02_Base_Potencial'!$AC$5:$AC$335)/$H34,"") | J34: =IFERROR(SUMPRODUCT(('02_Base_Potencial'!$B$5:$B$335=$B34)*('02_Base_Potencial'!$AQ$5:$AQ$335=1),'02_Base_Potencial'!$AK$5:$AK$335)/$H34,"")
B35: 10. Demografia, Território e Urbanização | C35: 0 | D35: 1 | E35: 7 | F35: =COUNTIF('02_Base_Potencial'!$B$5:$B$335,$B35) -> 23 | G35: =SUMPRODUCT(('02_Base_Potencial'!$B$5:$B$335=$B35)*('02_Base_Potencial'!$AL$5:$AL$335=1)) -> 7 | H35: =SUMPRODUCT(('02_Base_Potencial'!$B$5:$B$335=$B35)*('02_Base_Potencial'!$AQ$5:$AQ$335=1)) -> 0 | I35: =IFERROR(SUMPRODUCT(('02_Base_Potencial'!$B$5:$B$335=$B35)*('02_Base_Potencial'!$AQ$5:$AQ$335=1),'02_Base_Potencial'!$AC$5:$AC$335)/$H35,"") | J35: =IFERROR(SUMPRODUCT(('02_Base_Potencial'!$B$5:$B$335=$B35)*('02_Base_Potencial'!$AQ$5:$AQ$335=1),'02_Base_Potencial'!$AK$5:$AK$335)/$H35,"")
B36: 11. Transformação Digital e Inovação | C36: 0 | D36: 1 | E36: 7 | F36: =COUNTIF('02_Base_Potencial'!$B$5:$B$335,$B36) -> 23 | G36: =SUMPRODUCT(('02_Base_Potencial'!$B$5:$B$335=$B36)*('02_Base_Potencial'!$AL$5:$AL$335=1)) -> 9 | H36: =SUMPRODUCT(('02_Base_Potencial'!$B$5:$B$335=$B36)*('02_Base_Potencial'!$AQ$5:$AQ$335=1)) -> 0 | I36: =IFERROR(SUMPRODUCT(('02_Base_Potencial'!$B$5:$B$335=$B36)*('02_Base_Potencial'!$AQ$5:$AQ$335=1),'02_Base_Potencial'!$AC$5:$AC$335)/$H36,"") | J36: =IFERROR(SUMPRODUCT(('02_Base_Potencial'!$B$5:$B$335=$B36)*('02_Base_Potencial'!$AQ$5:$AQ$335=1),'02_Base_Potencial'!$AK$5:$AK$335)/$H36,"")
B38: Como funciona: no modo "Automática", entram os melhores N indicadores por dimensão (N = "Indicadores alvo"), por ordem do Score Total da Base_Potencial; a coluna "Ajuste manual" dessa folha permite forçar ("Incluir") ou bloquear ("Excluir") qualquer candidato. No modo "Manual" só entram os marcados como "Incluir". Máximo de 10 indicadores por dimensão.

Sheet 02_Base_Potencial
A1: ← Painel
B2: BASE DE INDICADORES POTENCIAIS (CATÁLOGO POR DIMENSÃO)
B3: 331 indicadores candidatos, valores anuais como extraídos das fontes de origem (BNA, INE, IIMS, Banco Mundial/WDI, FMI/WEO, benchmarks internacionais). Colunas de avaliação e selecção calculadas por fórmulas. Editável: Peso (J) e Ajuste manual (AP).
A4: ID | B4: Dimensão | C4: Subtema | D4: Indicador | E4: Unidade | F4: Sentido | G4: Mínimo | H4: Máximo | I4: Meta 2027 | J4: Peso | K4: Fonte | L4: Código/API | M4: Origem | N4: Fonte nacional | O4: Grupo (anti-duplicação) | P4: Prioridade | Q4: 2015 | R4: 2016 | S4: 2017 | T4: 2018 | U4: 2019 | V4: 2020 | W4: 2021 | X4: 2022 | Y4: 2023 | Z4: 2024 | AA4: 2025 | AB4: Nº obs. | AC4: Cobertura | AD4: Primeiro ano | AE4: Último ano | AF4: Continuidade | AG4: Recência (anos) | AH4: Score Relevância | AI4: Score Completude | AJ4: Score Consistência | AK4: SCORE TOTAL | AL4: Elegível | AM4: Motivo de exclusão | AN4: Melhor do grupo | AO4: Rank na dimensão | AP4: Ajuste manual | AQ4: SELECCIONADO | AR4: Slot | AS4: Nota
A5: GOV004 | B5: 1. Governança e Estado de Direito | C5: 1. Governança | D5: Estabilidade Política (WGI) | E5: -2.5 a 2.5 | F5: + | G5: -2.5 | H5: 2.5 | I5: 0 | J5: 1 | K5: Banco Mundial | L5: PV.EST | M5: Compilação interna BDA | N5: 0 | O5: GOV004 | P5: Em uso | Q5: -0.5591026 | R5: -0.434628 | S5: -0.5372145 | T5: -0.4058117 | U5: -0.4207039 | V5: -0.6427634 | W5: -0.7936068 | X5: -0.5414068 | Y5: -0.3131654 | Z5: -0.5735964 | AB5: =COUNT(Q5:AA5) -> 10 | AC5: =AB5/11 -> 0.90909091 | AD5: =IFERROR(INDEX($Q$4:$AA$4,MATCH(TRUE,INDEX(ISNUMBER(Q5:AA5),0),0)),"") -> 2015 | AE5: =IFERROR(LOOKUP(2,1/ISNUMBER(Q5:AA5),$Q$4:$AA$4),"") -> 2024 | AF5: =IF(AB5=0,"",AB5/(AE5-AD5+1)) -> 1 | AG5: =IF(AB5=0,"",'01_Criterios'!$C$8-AE5) -> 1 | AH5: =IF(P5="Em uso",100,IF(P5="Alta",85,IF(P5="Média",55,30))) -> 100 | AI5: =ROUND(100*AC5,1) -> 90.9 | AJ5: =IF(AB5=0,0,ROUND(MAX(0,100*AF5-10*AG5),1)) -> 90 | AK5: =ROUND(('01_Criterios'!$C$19*AH5+'01_Criterios'!$C$20*AI5+'01_Criterios'!$C$21*AJ5)/('01_Criterios'!$C$19+'01_Criterios'!$C$20+'01_Criterios'!$C$21)+N5*'01_Criterios'!$C$22,1) -> 94.3 | AL5: =IF(AND(AB5>=3,AC5>='01_Criterios'!$C$11,N(AE5)>='01_Criterios'!$C$12,OR(F5="+",F5="-"),ISNUMBER(G5),ISNUMBER(H5)),1,0) -> 1 | AM5: =IF(AL5=1,"",TRIM(IF(AB5=0,"sem dados no período; ",IF(AB5<3,"série demasiado curta; ",""))&IF(AND(AB5>0,AC5<'01_Criterios'!$C$11),"cobertura insuficiente; ","")&IF(AND(AB5>0,N(AE5)<'01_Criterios'!$C$12),"desactualizado; ","")&IF(AND(F5<>"+",F5<>"-"),"sentido ambíguo; ","")&IF(OR(NOT(ISNUMBER(G5)),NOT(ISNUMBER(H5))),"sem limites min/max; ",""))) | AN5: =IF(OR(AL5=0,$AP5="Excluir"),0,IF(SUMPRODUCT(($O$5:$O$335=$O5)*($AL$5:$AL$335=1)*($AP$5:$AP$335<>"Excluir")*(($AK$5:$AK$335>$AK5)+(($AK$5:$AK$335=$AK5)*(ROW($O$5:$O$335)<ROW()))))=0,1,0)) -> 1 | AO5: =IF(AN5=0,"",1+SUMPRODUCT(($B$5:$B$335=$B5)*($AN$5:$AN$335=1)*(($AK$5:$AK$335>$AK5)+(($AK$5:$AK$335=$AK5)*(ROW($B$5:$B$335)<ROW()))))) -> 2 | AP5: Auto | AQ5: =IF(INDEX('01_Criterios'!$C$26:$C$36,MATCH($B5,'01_Criterios'!$B$26:$B$36,0))<>1,0,IF($AP5="Excluir",0,IF($AP5="Incluir",IF(AND(OR($F5="+",$F5="-"),ISNUMBER($G5),ISNUMBER($H5),COUNT($Q5:$AA5)>0),1,0),IF('01_Criterios'!$C$18="Automática",IF(AND($AN5=1,$AO5<>"",$AO5<=INDEX('01_Criterios'!$E$26:$E$36,MATCH($B5,'01_Criterios'!$B$26:$B$36,0))),1,0),0)))) -> 1 | AR5: =IF(AQ5=0,"",IF($AO5<>"",1+SUMPRODUCT(($B$5:$B$335=$B5)*($AQ$5:$AQ$335=1)*($AO$5:$AO$335<$AO5)),1+SUMPRODUCT(($B$5:$B$335=$B5)*($AQ$5:$AQ$335=1)*ISNUMBER($AO$5:$AO$335))+SUMPRODUCT(($B$5:$B$335=$B5)*($AQ$5:$AQ$335=1)*($AO$5:$AO$335="")*(ROW($AO$5:$AO$335)<ROW())))) -> 2 | AS5: Indicador já incluído no modelo original.
A6: GOV005 | B6: 1. Governança e Estado de Direito | C6: 1. Governança | D6: Doing Business / Ease of Business | E6: 0-100 | F6: + | G6: 0 | H6: 100 | I6: 55 | J6: 1 | K6: Banco Mundial | M6: Compilação interna BDA | N6: 0 | O6: GOV005 | P6: Em uso | Q6: 37.09 | R6: 38.46 | S6: 38.41 | T6: 41.49 | U6: 43.86 | V6: 41.9 | AB6: =COUNT(Q6:AA6) -> 6 | AC6: =AB6/11 -> 0.54545455 | AD6: =IFERROR(INDEX($Q$4:$AA$4,MATCH(TRUE,INDEX(ISNUMBER(Q6:AA6),0),0)),"") -> 2015 | AE6: =IFERROR(LOOKUP(2,1/ISNUMBER(Q6:AA6),$Q$4:$AA$4),"") -> 2020 | AF6: =IF(AB6=0,"",AB6/(AE6-AD6+1)) -> 1 | AG6: =IF(AB6=0,"",'01_Criterios'!$C$8-AE6) -> 5 | AH6: =IF(P6="Em uso",100,IF(P6="Alta",85,IF(P6="Média",55,30))) -> 100 | AI6: =ROUND(100*AC6,1) -> 54.5 | AJ6: =IF(AB6=0,0,ROUND(MAX(0,100*AF6-10*AG6),1)) -> 50 | AK6: =ROUND(('01_Criterios'!$C$19*AH6+'01_Criterios'!$C$20*AI6+'01_Criterios'!$C$21*AJ6)/('01_Criterios'!$C$19+'01_Criterios'!$C$20+'01_Criterios'!$C$21)+N6*'01_Criterios'!$C$22,1) -> 71.6 | AL6: =IF(AND(AB6>=3,AC6>='01_Criterios'!$C$11,N(AE6)>='01_Criterios'!$C$12,OR(F6="+",F6="-"),ISNUMBER(G6),ISNUMBER(H6)),1,0) -> 0 | AM6: =IF(AL6=1,"",TRIM(IF(AB6=0,"sem dados no período; ",IF(AB6<3,"série demasiado curta; ",""))&IF(AND(AB6>0,AC6<'01_Criterios'!$C$11),"cobertura insuficiente; ","")&IF(AND(AB6>0,N(AE6)<'01_Criterios'!$C$12),"desactualizado; ","")&IF(AND(F6<>"+",F6<>"-"),"sentido ambíguo; ","")&IF(OR(NOT(ISNUMBER(G6)),NOT(ISNUMBER(H6))),"sem limites min/max; ",""))) -> cobertura insuficiente; desactualizado; | AN6: =IF(OR(AL6=0,$AP6="Excluir"),0,IF(SUMPRODUCT(($O$5:$O$335=$O6)*($AL$5:$AL$335=1)*($AP$5:$AP$335<>"Excluir")*(($AK$5:$AK$335>$AK6)+(($AK$5:$AK$335=$AK6)*(ROW($O$5:$O$335)<ROW()))))=0,1,0)) -> 0 | AO6: =IF(AN6=0,"",1+SUMPRODUCT(($B$5:$B$335=$B6)*($AN$5:$AN$335=1)*(($AK$5:$AK$335>$AK6)+(($AK$5:$AK$335=$AK6)*(ROW($B$5:$B$335)<ROW()))))) | AP6: Auto | AQ6: =IF(INDEX('01_Criterios'!$C$26:$C$36,MATCH($B6,'01_Criterios'!$B$26:$B$36,0))<>1,0,IF($AP6="Excluir",0,IF($AP6="Incluir",IF(AND(OR($F6="+",$F6="-"),ISNUMBER($G6),ISNUMBER($H6),COUNT($Q6:$AA6)>0),1,0),IF('01_Criterios'!$C$18="Automática",IF(AND($AN6=1,$AO6<>"",$AO6<=INDEX('01_Criterios'!$E$26:$E$36,MATCH($B6,'01_Criterios'!$B$26:$B$36,0))),1,0),0)))) -> 0 | AR6: =IF(AQ6=0,"",IF($AO6<>"",1+SUMPRODUCT(($B$5:$B$335=$B6)*($AQ$5:$AQ$335=1)*($AO$5:$AO$335<$AO6)),1+SUMPRODUCT(($B$5:$B$335=$B6)*($AQ$5:$AQ$335=1)*ISNUMBER($AO$5:$AO$335))+SUMPRODUCT(($B$5:$B$335=$B6)*($AQ$5:$AQ$335=1)*($AO$5:$AO$335="")*(ROW($AO$5:$AO$335)<ROW())))) | AS6: Indicador já incluído no modelo original.
A7: GOV01 | B7: 1. Governança e Estado de Direito | C7: 1. Governança | D7: Índice de Percepção da Corrupção | E7: 0-100 | F7: + | G7: 0 | H7: 100 | I7: 35 | J7: 1 | K7: Transparency Int. | L7: TI_CPI_SCORE | M7: Transparency International — CPI | N7: 0 | O7: GOV01 | P7: Em uso | Q7: 15 | R7: 18 | S7: 19 | T7: 19 | U7: 26 | V7: 27 | W7: 29 | X7: 33 | Y7: 33 | Z7: 32 | AA7: 32 | AB7: =COUNT(Q7:AA7) -> 11 | AC7: =AB7/11 -> 1 | AD7: =IFERROR(INDEX($Q$4:$AA$4,MATCH(TRUE,INDEX(ISNUMBER(Q7:AA7),0),0)),"") -> 2015 | AE7: =IFERROR(LOOKUP(2,1/ISNUMBER(Q7:AA7),$Q$4:$AA$4),"") -> 2025 | AF7: =IF(AB7=0,"",AB7/(AE7-AD7+1)) -> 1 | AG7: =IF(AB7=0,"",'01_Criterios'!$C$8-AE7) -> 0 | AH7: =IF(P7="Em uso",100,IF(P7="Alta",85,IF(P7="Média",55,30))) -> 100 | AI7: =ROUND(100*AC7,1) -> 100 | AJ7: =IF(AB7=0,0,ROUND(MAX(0,100*AF7-10*AG7),1)) -> 100 | AK7: =ROUND(('01_Criterios'!$C$19*AH7+'01_Criterios'!$C$20*AI7+'01_Criterios'!$C$21*AJ7)/('01_Criterios'!$C$19+'01_Criterios'!$C$20+'01_Criterios'!$C$21)+N7*'01_Criterios'!$C$22,1) -> 100 | AL7: =IF(AND(AB7>=3,AC7>='01_Criterios'!$C$11,N(AE7)>='01_Criterios'!$C$12,OR(F7="+",F7="-"),ISNUMBER(G7),ISNUMBER(H7)),1,0) -> 1 | AM7: =IF(AL7=1,"",TRIM(IF(AB7=0,"sem dados no período; ",IF(AB7<3,"série demasiado curta; ",""))&IF(AND(AB7>0,AC7<'01_Criterios'!$C$11),"cobertura insuficiente; ","")&IF(AND(AB7>0,N(AE7)<'01_Criterios'!$C$12),"desactualizado; ","")&IF(AND(F7<>"+",F7<>"-"),"sentido ambíguo; ","")&IF(OR(NOT(ISNUMBER(G7)),NOT(ISNUMBER(H7))),"sem limites min/max; ",""))) | AN7: =IF(OR(AL7=0,$AP7="Excluir"),0,IF(SUMPRODUCT(($O$5:$O$335=$O7)*($AL$5:$AL$335=1)*($AP$5:$AP$335<>"Excluir")*(($AK$5:$AK$335>$AK7)+(($AK$5:$AK$335=$AK7)*(ROW($O$5:$O$335)<ROW()))))=0,1,0)) -> 1 | AO7: =IF(AN7=0,"",1+SUMPRODUCT(($B$5:$B$335=$B7)*($AN$5:$AN$335=1)*(($AK$5:$AK$335>$AK7)+(($AK$5:$AK$335=$AK7)*(ROW($B$5:$B$335)<ROW()))))) -> 1 | AP7: Auto | AQ7: =IF(INDEX('01_Criterios'!$C$26:$C$36,MATCH($B7,'01_Criterios'!$B$26:$B$36,0))<>1,0,IF($AP7="Excluir",0,IF($AP7="Incluir",IF(AND(OR($F7="+",$F7="-"),ISNUMBER($G7),ISNUMBER($H7),COUNT($Q7:$AA7)>0),1,0),IF('01_Criterios'!$C$18="Automática",IF(AND($AN7=1,$AO7<>"",$AO7<=INDEX('01_Criterios'!$E$26:$E$36,MATCH($B7,'01_Criterios'!$B$26:$B$36,0))),1,0),0)))) -> 1 | AR7: =IF(AQ7=0,"",IF($AO7<>"",1+SUMPRODUCT(($B$5:$B$335=$B7)*($AQ$5:$AQ$335=1)*($AO$5:$AO$335<$AO7)),1+SUMPRODUCT(($B$5:$B$335=$B7)*($AQ$5:$AQ$335=1)*ISNUMBER($AO$5:$AO$335))+SUMPRODUCT(($B$5:$B$335=$B7)*($AQ$5:$AQ$335=1)*($AO$5:$AO$335="")*(ROW($AO$5:$AO$335)<ROW())))) -> 1 | AS7: Nome local/API: Corruption Perceptions Index — score (0=highly corrupt, 100=clean) | 2025 preenchido a partir da página oficial Transparency International Angola/CPI 2025.
A8: GOV02 | B8: 1. Governança e Estado de Direito | C8: 1. Governança | D8: WGI - Estado de Direito | E8: -2.5 a 2.5 | F8: + | G8: -2.5 | H8: 2.5 | I8: 0 | J8: 1 | K8: Banco Mundial | L8: RL.EST | M8: Compilação interna BDA | N8: 0 | O8: GOV02 | P8: Em uso | Q8: -1.3086297 | R8: -1.3287764 | S8: -1.3317055 | T8: -1.1105522 | U8: -1.0519682 | V8: -0.9475038 | W8: -1.0980135 | X8: -1.1625439 | Y8: -1.1944432 | Z8: -1.1697408 | AB8: =COUNT(Q8:AA8) -> 10 | AC8: =AB8/11 -> 0.90909091 | AD8: =IFERROR(INDEX($Q$4:$AA$4,MATCH(TRUE,INDEX(ISNUMBER(Q8:AA8),0),0)),"") -> 2015 | AE8: =IFERROR(LOOKUP(2,1/ISNUMBER(Q8:AA8),$Q$4:$AA$4),"") -> 2024 | AF8: =IF(AB8=0,"",AB8/(AE8-AD8+1)) -> 1 | AG8: =IF(AB8=0,"",'01_Criterios'!$C$8-AE8) -> 1 | AH8: =IF(P8="Em uso",100,IF(P8="Alta",85,IF(P8="Média",55,30))) -> 100 | AI8: =ROUND(100*AC8,1) -> 90.9 | AJ8: =IF(AB8=0,0,ROUND(MAX(0,100*AF8-10*AG8),1)) -> 90 | AK8: =ROUND(('01_Criterios'!$C$19*AH8+'01_Criterios'!$C$20*AI8+'01_Criterios'!$C$21*AJ8)/('01_Criterios'!$C$19+'01_Criterios'!$C$20+'01_Criterios'!$C$21)+N8*'01_Criterios'!$C$22,1) -> 94.3 | AL8: =IF(AND(AB8>=3,AC8>='01_Criterios'!$C$11,N(AE8)>='01_Criterios'!$C$12,OR(F8="+",F8="-"),ISNUMBER(G8),ISNUMBER(H8)),1,0) -> 1 | AM8: =IF(AL8=1,"",TRIM(IF(AB8=0,"sem dados no período; ",IF(AB8<3,"série demasiado curta; ",""))&IF(AND(AB8>0,AC8<'01_Criterios'!$C$11),"cobertura insuficiente; ","")&IF(AND(AB8>0,N(AE8)<'01_Criterios'!$C$12),"desactualizado; ","")&IF(AND(F8<>"+",F8<>"-"),"sentido ambíguo; ","")&IF(OR(NOT(ISNUMBER(G8)),NOT(ISNUMBER(H8))),"sem limites min/max; ",""))) | AN8: =IF(OR(AL8=0,$AP8="Excluir"),0,IF(SUMPRODUCT(($O$5:$O$335=$O8)*($AL$5:$AL$335=1)*($AP$5:$AP$335<>"Excluir")*(($AK$5:$AK$335>$AK8)+(($AK$5:$AK$335=$AK8)*(ROW($O$5:$O$335)<ROW()))))=0,1,0)) -> 1 | AO8: =IF(AN8=0,"",1+SUMPRODUCT(($B$5:$B$335=$B8)*($AN$5:$AN$335=1)*(($AK$5:$AK$335>$AK8)+(($AK$5:$AK$335=$AK8)*(ROW($B$5:$B$335)<ROW()))))) -> 3 | AP8: Auto | AQ8: =IF(INDEX('01_Criterios'!$C$26:$C$36,MATCH($B8,'01_Criterios'!$B$26:$B$36,0))<>1,0,IF($AP8="Excluir",0,IF($AP8="Incluir",IF(AND(OR($F8="+",$F8="-"),ISNUMBER($G8),ISNUMBER($H8),COUNT($Q8:$AA8)>0),1,0),IF('01_Criterios'!$C$18="Automática",IF(AND($AN8=1,$AO8<>"",$AO8<=INDEX('01_Criterios'!$E$26:$E$36,MATCH($B8,'01_Criterios'!$B$26:$B$36,0))),1,0),0)))) -> 1 | AR8: =IF(AQ8=0,"",IF($AO8<>"",1+SUMPRODUCT(($B$5:$B$335=$B8)*($AQ$5:$AQ$335=1)*($AO$5:$AO$335<$AO8)),1+SUMPRODUCT(($B$5:$B$335=$B8)*($AQ$5:$AQ$335=1)*ISNUMBER($AO$5:$AO$335))+SUMPRODUCT(($B$5:$B$335=$B8)*($AQ$5:$AQ$335=1)*($AO$5:$AO$335="")*(ROW($AO$5:$AO$335)<ROW())))) -> 3 | AS8: Indicador já incluído no modelo original.
A9: GOV03 | B9: 1. Governança e Estado de Direito | C9: 1. Governança | D9: WGI - Eficiência do Governo | E9: -2.5 a 2.5 | F9: + | G9: -2.5 | H9: 2.5 | I9: 0 | J9: 1 | K9: Banco Mundial | L9: GE.EST | M9: Compilação interna BDA | N9: 0 | O9: GOV03 | P9: Em uso | Q9: -0.9378237 | R9: -0.9493847 | S9: -0.9681157 | T9: -0.9784602 | U9: -0.9116965 | V9: -1.0163604 | W9: -0.9347008 | X9: -0.8325718 | Y9: -0.8287026 | Z9: -0.7851909 | AB9: =COUNT(Q9:AA9) -> 10 | AC9: =AB9/11 -> 0.90909091 | AD9: =IFERROR(INDEX($Q$4:$AA$4,MATCH(TRUE,INDEX(ISNUMBER(Q9:AA9),0),0)),"") -> 2015 | AE9: =IFERROR(LOOKUP(2,1/ISNUMBER(Q9:AA9),$Q$4:$AA$4),"") -> 2024 | AF9: =IF(AB9=0,"",AB9/(AE9-AD9+1)) -> 1 | AG9: =IF(AB9=0,"",'01_Criterios'!$C$8-AE9) -> 1 | AH9: =IF(P9="Em uso",100,IF(P9="Alta",85,IF(P9="Média",55,30))) -> 100 | AI9: =ROUND(100*AC9,1) -> 90.9 | AJ9: =IF(AB9=0,0,ROUND(MAX(0,100*AF9-10*AG9),1)) -> 90 | AK9: =ROUND(('01_Criterios'!$C$19*AH9+'01_Criterios'!$C$20*AI9+'01_Criterios'!$C$21*AJ9)/('01_Criterios'!$C$19+'01_Criterios'!$C$20+'01_Criterios'!$C$21)+N9*'01_Criterios'!$C$22,1) -> 94.3 | AL9: =IF(AND(AB9>=3,AC9>='01_Criterios'!$C$11,N(AE9)>='01_Criterios'!$C$12,OR(F9="+",F9="-"),ISNUMBER(G9),ISNUMBER(H9)),1,0) -> 1 | AM9: =IF(AL9=1,"",TRIM(IF(AB9=0,"sem dados no período; ",IF(AB9<3,"série demasiado curta; ",""))&IF(AND(AB9>0,AC9<'01_Criterios'!$C$11),"cobertura insuficiente; ","")&IF(AND(AB9>0,N(AE9)<'01_Criterios'!$C$12),"desactualizado; ","")&IF(AND(F9<>"+",F9<>"-"),"sentido ambíguo; ","")&IF(OR(NOT(ISNUMBER(G9)),NOT(ISNUMBER(H9))),"sem limites min/max; ",""))) | AN9: =IF(OR(AL9=0,$AP9="Excluir"),0,IF(SUMPRODUCT(($O$5:$O$335=$O9)*($AL$5:$AL$335=1)*($AP$5:$AP$335<>"Excluir")*(($AK$5:$AK$335>$AK9)+(($AK$5:$AK$335=$AK9)*(ROW($O$5:$O$335)<ROW()))))=0,1,0)) -> 1 | AO9: =IF(AN9=0,"",1+SUMPRODUCT(($B$5:$B$335=$B9)*($AN$5:$AN$335=1)*(($AK$5:$AK$335>$AK9)+(($AK$5:$AK$335=$AK9)*(ROW($B$5:$B$335)<ROW()))))) -> 4 | AP9: Auto | AQ9: =IF(INDEX('01_Criterios'!$C$26:$C$36,MATCH($B9,'01_Criterios'!$B$26:$B$36,0))<>1,0,IF($AP9="Excluir",0,IF($AP9="Incluir",IF(AND(OR($F9="+",$F9="-"),ISNUMBER($G9),ISNUMBER($H9),COUNT($Q9:$AA9)>0),1,0),IF('01_Criterios'!$C$18="Automática",IF(AND($AN9=1,$AO9<>"",$AO9<=INDEX('01_Criterios'!$E$26:$E$36,MATCH($B9,'01_Criterios'!$B$26:$B$36,0))),1,0),0)))) -> 1 | AR9: =IF(AQ9=0,"",IF($AO9<>"",1+SUMPRODUCT(($B$5:$B$335=$B9)*($AQ$5:$AQ$335=1)*($AO$5:$AO$335<$AO9)),1+SUMPRODUCT(($B$5:$B$335=$B9)*($AQ$5:$AQ$335=1)*ISNUMBER($AO$5:$AO$335))+SUMPRODUCT(($B$5:$B$335=$B9)*($AQ$5:$AQ$335=1)*($AO$5:$AO$335="")*(ROW($AO$5:$AO$335)<ROW())))) -> 4 | AS9: Indicador já incluído no modelo original.
A10: GOV009 | B10: 1. Governança e Estado de Direito | C10: 1. Governança | D10: Índice Ibrahim - Governação Global | E10: 0-100 | F10: + | G10: 0 | H10: 100 | I10: 55 | J10: 1 | K10: Mo Ibrahim Foundation | L10: IIAG_OVERALL | M10: Mo Ibrahim Foundation | N10: 0 | O10: GOV009 | P10: Alta | Y10: 43.8 | AB10: =COUNT(Q10:AA10) -> 1 | AC10: =AB10/11 -> 0.090909091 | AD10: =IFERROR(INDEX($Q$4:$AA$4,MATCH(TRUE,INDEX(ISNUMBER(Q10:AA10),0),0)),"") -> 2023 | AE10: =IFERROR(LOOKUP(2,1/ISNUMBER(Q10:AA10),$Q$4:$AA$4),"") -> 2023 | AF10: =IF(AB10=0,"",AB10/(AE10-AD10+1)) -> 1 | AG10: =IF(AB10=0,"",'01_Criterios'!$C$8-AE10) -> 2 | AH10: =IF(P10="Em uso",100,IF(P10="Alta",85,IF(P10="Média",55,30))) -> 85 | AI10: =ROUND(100*AC10,1) -> 9.1 | AJ10: =IF(AB10=0,0,ROUND(MAX(0,100*AF10-10*AG10),1)) -> 80 | AK10: =ROUND(('01_Criterios'!$C$19*AH10+'01_Criterios'!$C$20*AI10+'01_Criterios'!$C$21*AJ10)/('01_Criterios'!$C$19+'01_Criterios'!$C$20+'01_Criterios'!$C$21)+N10*'01_Criterios'!$C$22,1) -> 57.2 | AL10: =IF(AND(AB10>=3,AC10>='01_Criterios'!$C$11,N(AE10)>='01_Criterios'!$C$12,OR(F10="+",F10="-"),ISNUMBER(G10),ISNUMBER(H10)),1,0) -> 0 | AM10: =IF(AL10=1,"",TRIM(IF(AB10=0,"sem dados no período; ",IF(AB10<3,"série demasiado curta; ",""))&IF(AND(AB10>0,AC10<'01_Criterios'!$C$11),"cobertura insuficiente; ","")&IF(AND(AB10>0,N(AE10)<'01_Criterios'!$C$12),"desactualizado; ","")&IF(AND(F10<>"+",F10<>"-"),"sentido ambíguo; ","")&IF(OR(NOT(ISNUMBER(G10)),NOT(ISNUMBER(H10))),"sem limites min/max; ",""))) -> série demasiado curta; cobertura insuficiente; | AN10: =IF(OR(AL10=0,$AP10="Excluir"),0,IF(SUMPRODUCT(($O$5:$O$335=$O10)*($AL$5:$AL$335=1)*($AP$5:$AP$335<>"Excluir")*(($AK$5:$AK$335>$AK10)+(($AK$5:$AK$335=$AK10)*(ROW($O$5:$O$335)<ROW()))))=0,1,0)) -> 0 | AO10: =IF(AN10=0,"",1+SUMPRODUCT(($B$5:$B$335=$B10)*($AN$5:$AN$335=1)*(($AK$5:$AK$335>$AK10)+(($AK$5:$AK$335=$AK10)*(ROW($B$5:$B$335)<ROW()))))) | AP10: Auto | AQ10: =IF(INDEX('01_Criterios'!$C$26:$C$36,MATCH($B10,'01_Criterios'!$B$26:$B$36,0))<>1,0,IF($AP10="Excluir",0,IF($AP10="Incluir",IF(AND(OR($F10="+",$F10="-"),ISNUMBER($G10),ISNUMBER($H10),COUNT($Q10:$AA10)>0),1,0),IF('01_Criterios'!$C$18="Automática",IF(AND($AN10=1,$AO10<>"",$AO10<=INDEX('01_Criterios'!$E$26:$E$36,MATCH($B10,'01_Criterios'!$B$26:$B$36,0))),1,0),0)))) -> 0 | AR10: =IF(AQ10=0,"",IF($AO10<>"",1+SUMPRODUCT(($B$5:$B$335=$B10)*($AQ$5:$AQ$335=1)*($AO$5:$AO$335<$AO10)),1+SUMPRODUCT(($B$5:$B$335=$B10)*($AQ$5:$AQ$335=1)*ISNUMBER($AO$5:$AO$335))+SUMPRODUCT(($B$5:$B$335=$B10)*($AQ$5:$AQ$335=1)*($AO$5:$AO$335="")*(ROW($AO$5:$AO$335)<ROW())))) | AS10: Benchmark africano com várias dimensões institucionais. | IIAG 2024: scorecard (2023) e perfil de país (2014). Dataset cobre 2014-2023; anos intermédios não rotulados numericamente.
A11: GOV020 | B11: 1. Governança e Estado de Direito | C11: Corrupção empresarial | D11: Incidência de subornos em empresas | E11: % | F11: - | G11: 0 | H11: 100 | I11: 10 | J11: 1 | K11: Banco Mundial/Enterprise Surveys | L11: IC.FRM.BRIB.ZS | M11: Banco Mundial — WDI | N11: 0 | O11: GOV020 | P11: Alta | Z11: 21.507504 | AB11: =COUNT(Q11:AA11) -> 1 | AC11: =AB11/11 -> 0.090909091 | AD11: =IFERROR(INDEX($Q$4:$AA$4,MATCH(TRUE,INDEX(ISNUMBER(Q11:AA11),0),0)),"") -> 2024 | AE11: =IFERROR(LOOKUP(2,1/ISNUMBER(Q11:AA11),$Q$4:$AA$4),"") -> 2024 | AF11: =IF(AB11=0,"",AB11/(AE11-AD11+1)) -> 1 | AG11: =IF(AB11=0,"",'01_Criterios'!$C$8-AE11) -> 1 | AH11: =IF(P11="Em uso",100,IF(P11="Alta",85,IF(P11="Média",55,30))) -> 85 | AI11: =ROUND(100*AC11,1) -> 9.1 | AJ11: =IF(AB11=0,0,ROUND(MAX(0,100*AF11-10*AG11),1)) -> 90 | AK11: =ROUND(('01_Criterios'!$C$19*AH11+'01_Criterios'!$C$20*AI11+'01_Criterios'!$C$21*AJ11)/('01_Criterios'!$C$19+'01_Criterios'!$C$20+'01_Criterios'!$C$21)+N11*'01_Criterios'!$C$22,1) -> 59.7 | AL11: =IF(AND(AB11>=3,AC11>='01_Criterios'!$C$11,N(AE11)>='01_Criterios'!$C$12,OR(F11="+",F11="-"),ISNUMBER(G11),ISNUMBER(H11)),1,0) -> 0 | AM11: =IF(AL11=1,"",TRIM(IF(AB11=0,"sem dados no período; ",IF(AB11<3,"série demasiado curta; ",""))&IF(AND(AB11>0,AC11<'01_Criterios'!$C$11),"cobertura insuficiente; ","")&IF(AND(AB11>0,N(AE11)<'01_Criterios'!$C$12),"desactualizado; ","")&IF(AND(F11<>"+",F11<>"-"),"sentido ambíguo; ","")&IF(OR(NOT(ISNUMBER(G11)),NOT(ISNUMBER(H11))),"sem limites min/max; ",""))) -> série demasiado curta; cobertura insuficiente; | AN11: =IF(OR(AL11=0,$AP11="Excluir"),0,IF(SUMPRODUCT(($O$5:$O$335=$O11)*($AL$5:$AL$335=1)*($AP$5:$AP$335<>"Excluir")*(($AK$5:$AK$335>$AK11)+(($AK$5:$AK$335=$AK11)*(ROW($O$5:$O$335)<ROW()))))=0,1,0)) -> 0 | AO11: =IF(AN11=0,"",1+SUMPRODUCT(($B$5:$B$335=$B11)*($AN$5:$AN$335=1)*(($AK$5:$AK$335>$AK11)+(($AK$5:$AK$335=$AK11)*(ROW($B$5:$B$335)<ROW()))))) | AP11: Auto | AQ11: =IF(INDEX('01_Criterios'!$C$26:$C$36,MATCH($B11,'01_Criterios'!$B$26:$B$36,0))<>1,0,IF($AP11="Excluir",0,IF($AP11="Incluir",IF(AND(OR($F11="+",$F11="-"),ISNUMBER($G11),ISNUMBER($H11),COUNT($Q11:$AA11)>0),1,0),IF('01_Criterios'!$C$18="Automática",IF(AND($AN11=1,$AO11<>"",$AO11<=INDEX('01_Criterios'!$E$26:$E$36,MATCH($B11,'01_Criterios'!$B$26:$B$36,0))),1,0),0)))) -> 0 | AR11: =IF(AQ11=0,"",IF($AO11<>"",1+SUMPRODUCT(($B$5:$B$335=$B11)*($AQ$5:$AQ$335=1)*($AO$5:$AO$335<$AO11)),1+SUMPRODUCT(($B$5:$B$335=$B11)*($AQ$5:$AQ$335=1)*ISNUMBER($AO$5:$AO$335))+SUMPRODUCT(($B$5:$B$335=$B11)*($AQ$5:$AQ$335=1)*($AO$5:$AO$335="")*(ROW($AO$5:$AO$335)<ROW())))) | AS11: Capta corrupção sentida pelas empresas, complementar ao CPI/WGI. | Nome local/API: Bribery incidence (% of firms experiencing at least one bribe payment request)
A12: GOV021 | B12: 1. Governança e Estado de Direito | C12: Corrupção empresarial | D12: Pagamentos informais a funcionários públicos | E12: % | F12: - | G12: 0 | H12: 100 | I12: 10 | J12: 1 | K12: Banco Mundial/Enterprise Surveys | L12: IC.FRM.CORR.ZS | M12: Banco Mundial — WDI | N12: 0 | O12: GOV021 | P12: Alta | Z12: 19.121405 | AB12: =COUNT(Q12:AA12) -> 1 | AC12: =AB12/11 -> 0.090909091 | AD12: =IFERROR(INDEX($Q$4:$AA$4,MATCH(TRUE,INDEX(ISNUMBER(Q12:AA12),0),0)),"") -> 2024 | AE12: =IFERROR(LOOKUP(2,1/ISNUMBER(Q12:AA12),$Q$4:$AA$4),"") -> 2024 | AF12: =IF(AB12=0,"",AB12/(AE12-AD12+1)) -> 1 | AG12: =IF(AB12=0,"",'01_Criterios'!$C$8-AE12) -> 1 | AH12: =IF(P12="Em uso",100,IF(P12="Alta",85,IF(P12="Média",55,30))) -> 85 | AI12: =ROUND(100*AC12,1) -> 9.1 | AJ12: =IF(AB12=0,0,ROUND(MAX(0,100*AF12-10*AG12),1)) -> 90 | AK12: =ROUND(('01_Criterios'!$C$19*AH12+'01_Criterios'!$C$20*AI12+'01_Criterios'!$C$21*AJ12)/('01_Criterios'!$C$19+'01_Criterios'!$C$20+'01_Criterios'!$C$21)+N12*'01_Criterios'!$C$22,1) -> 59.7 | AL12: =IF(AND(AB12>=3,AC12>='01_Criterios'!$C$11,N(AE12)>='01_Criterios'!$C$12,OR(F12="+",F12="-"),ISNUMBER(G12),ISNUMBER(H12)),1,0) -> 0 | AM12: =IF(AL12=1,"",TRIM(IF(AB12=0,"sem dados no período; ",IF(AB12<3,"série demasiado curta; ",""))&IF(AND(AB12>0,AC12<'01_Criterios'!$C$11),"cobertura insuficiente; ","")&IF(AND(AB12>0,N(AE12)<'01_Criterios'!$C$12),"desactualizado; ","")&IF(AND(F12<>"+",F12<>"-"),"sentido ambíguo; ","")&IF(OR(NOT(ISNUMBER(G12)),NOT(ISNUMBER(H12))),"sem limites min/max; ",""))) -> série demasiado curta; cobertura insuficiente; | AN12: =IF(OR(AL12=0,$AP12="Excluir"),0,IF(SUMPRODUCT(($O$5:$O$335=$O12)*($AL$5:$AL$335=1)*($AP$5:$AP$335<>"Excluir")*(($AK$5:$AK$335>$AK12)+(($AK$5:$AK$335=$AK12)*(ROW($O$5:$O$335)<ROW()))))=0,1,0)) -> 0 | AO12: =IF(AN12=0,"",1+SUMPRODUCT(($B$5:$B$335=$B12)*($AN$5:$AN$335=1)*(($AK$5:$AK$335>$AK12)+(($AK$5:$AK$335=$AK12)*(ROW($B$5:$B$335)<ROW()))))) | AP12: Auto | AQ12: =IF(INDEX('01_Criterios'!$C$26:$C$36,MATCH($B12,'01_Criterios'!$B$26:$B$36,0))<>1,0,IF($AP12="Excluir",0,IF($AP12="Incluir",IF(AND(OR($F12="+",$F12="-"),ISNUMBER($G12),ISNUMBER($H12),COUNT($Q12:$AA12)>0),1,0),IF('01_Criterios'!$C$18="Automática",IF(AND($AN12=1,$AO12<>"",$AO12<=INDEX('01_Criterios'!$E$26:$E$36,MATCH($B12,'01_Criterios'!$B$26:$B$36,0))),1,0),0)))) -> 0 | AR12: =IF(AQ12=0,"",IF($AO12<>"",1+SUMPRODUCT(($B$5:$B$335=$B12)*($AQ$5:$AQ$335=1)*($AO$5:$AO$335<$AO12)),1+SUMPRODUCT(($B$5:$B$335=$B12)*($AQ$5:$AQ$335=1)*ISNUMBER($AO$5:$AO$335))+SUMPRODUCT(($B$5:$B$335=$B12)*($AQ$5:$AQ$335=1)*($AO$5:$AO$335="")*(ROW($AO$5:$AO$335)<ROW())))) | AS12: Indicador empresarial direto de informalidade/corrupção administrativa. | Nome local/API: Informal payments to public officials (% of firms)
A13: GOV05 | B13: 1. Governança e Estado de Direito | C13: 1. Governança | D13: WGI - Qualidade Regulatória | E13: -2.5 a 2.5 | F13: + | G13: -2.5 | H13: 2.5 | I13: 0 | J13: 1 | K13: WGI/Banco Mundial | L13: RQ.EST | M13: Compilação interna BDA | N13: 0 | O13: GOV05 | P13: Alta | Q13: -1.0904945 | R13: -1.1804235 | S13: -1.1799885 | T13: -1.0624393 | U13: -0.9960854 | V13: -1.0388818 | W13: -0.8486184 | X13: -0.8618821 | Y13: -0.904342 | Z13: -0.77302 | AB13: =COUNT(Q13:AA13) -> 10 | AC13: =AB13/11 -> 0.90909091 | AD13: =IFERROR(INDEX($Q$4:$AA$4,MATCH(TRUE,INDEX(ISNUMBER(Q13:AA13),0),0)),"") -> 2015 | AE13: =IFERROR(LOOKUP(2,1/ISNUMBER(Q13:AA13),$Q$4:$AA$4),"") -> 2024 | AF13: =IF(AB13=0,"",AB13/(AE13-AD13+1)) -> 1 | AG13: =IF(AB13=0,"",'01_Criterios'!$C$8-AE13) -> 1 | AH13: =IF(P13="Em uso",100,IF(P13="Alta",85,IF(P13="Média",55,30))) -> 85 | AI13: =ROUND(100*AC13,1) -> 90.9 | AJ13: =IF(AB13=0,0,ROUND(MAX(0,100*AF13-10*AG13),1)) -> 90 | AK13: =ROUND(('01_Criterios'!$C$19*AH13+'01_Criterios'!$C$20*AI13+'01_Criterios'!$C$21*AJ13)/('01_Criterios'!$C$19+'01_Criterios'!$C$20+'01_Criterios'!$C$21)+N13*'01_Criterios'!$C$22,1) -> 88.3 | AL13: =IF(AND(AB13>=3,AC13>='01_Criterios'!$C$11,N(AE13)>='01_Criterios'!$C$12,OR(F13="+",F13="-"),ISNUMBER(G13),ISNUMBER(H13)),1,0) -> 1 | AM13: =IF(AL13=1,"",TRIM(IF(AB13=0,"sem dados no período; ",IF(AB13<3,"série demasiado curta; ",""))&IF(AND(AB13>0,AC13<'01_Criterios'!$C$11),"cobertura insuficiente; ","")&IF(AND(AB13>0,N(AE13)<'01_Criterios'!$C$12),"desactualizado; ","")&IF(AND(F13<>"+",F13<>"-"),"sentido ambíguo; ","")&IF(OR(NOT(ISNUMBER(G13)),NOT(ISNUMBER(H13))),"sem limites min/max; ",""))) | AN13: =IF(OR(AL13=0,$AP13="Excluir"),0,IF(SUMPRODUCT(($O$5:$O$335=$O13)*($AL$5:$AL$335=1)*($AP$5:$AP$335<>"Excluir")*(($AK$5:$AK$335>$AK13)+(($AK$5:$AK$335=$AK13)*(ROW($O$5:$O$335)<ROW()))))=0,1,0)) -> 1 | AO13: =IF(AN13=0,"",1+SUMPRODUCT(($B$5:$B$335=$B13)*($AN$5:$AN$335=1)*(($AK$5:$AK$335>$AK13)+(($AK$5:$AK$335=$AK13)*(ROW($B$5:$B$335)<ROW()))))) -> 5 | AP13: Auto | AQ13: =IF(INDEX('01_Criterios'!$C$26:$C$36,MATCH($B13,'01_Criterios'!$B$26:$B$36,0))<>1,0,IF($AP13="Excluir",0,IF($AP13="Incluir",IF(AND(OR($F13="+",$F13="-"),ISNUMBER($G13),ISNUMBER($H13),COUNT($Q13:$AA13)>0),1,0),IF('01_Criterios'!$C$18="Automática",IF(AND($AN13=1,$AO13<>"",$AO13<=INDEX('01_Criterios'!$E$26:$E$36,MATCH($B13,'01_Criterios'!$B$26:$B$36,0))),1,0),0)))) -> 1 | AR13: =IF(AQ13=0,"",IF($AO13<>"",1+SUMPRODUCT(($B$5:$B$335=$B13)*($AQ$5:$AQ$335=1)*($AO$5:$AO$335<$AO13)),1+SUMPRODUCT(($B$5:$B$335=$B13)*($AQ$5:$AQ$335=1)*ISNUMBER($AO$5:$AO$335))+SUMPRODUCT(($B$5:$B$335=$B13)*($AQ$5:$AQ$335=1)*($AO$5:$AO$335="")*(ROW($AO$5:$AO$335)<ROW())))) -> 5 | AS13: Bom substituto para Doing Business, que foi descontinuado. Cobertura estimada pela periodicidade WGI; o endpoint WDI simples não devolve esta série.
A14: GOV06 | B14: 1. Governança e Estado de Direito | C14: 1. Governança | D14: WGI - Controlo da Corrupção | E14: -2.5 a 2.5 | F14: + | G14: -2.5 | H14: 2.5 | I14: 0 | J14: 1 | K14: WGI/Banco Mundial | L14: CC.EST | M14: Compilação interna BDA | N14: 0 | O14: GOV06 | P14: Alta | Q14: -1.4857649 | R14: -1.4881942 | S14: -1.4208093 | T14: -1.181782 | U14: -0.9647988 | V14: -0.8918323 | W14: -0.6416506 | X14: -0.6031537 | Y14: -0.6242518 | Z14: -0.6225793 | AB14: =COUNT(Q14:AA14) -> 10 | AC14: =AB14/11 -> 0.90909091 | AD14: =IFERROR(INDEX($Q$4:$AA$4,MATCH(TRUE,INDEX(ISNUMBER(Q14:AA14),0),0)),"") -> 2015 | AE14: =IFERROR(LOOKUP(2,1/ISNUMBER(Q14:AA14),$Q$4:$AA$4),"") -> 2024 | AF14: =IF(AB14=0,"",AB14/(AE14-AD14+1)) -> 1 | AG14: =IF(AB14=0,"",'01_Criterios'!$C$8-AE14) -> 1 | AH14: =IF(P14="Em uso",100,IF(P14="Alta",85,IF(P14="Média",55,30))) -> 85 | AI14: =ROUND(100*AC14,1) -> 90.9 | AJ14: =IF(AB14=0,0,ROUND(MAX(0,100*AF14-10*AG14),1)) -> 90 | AK14: =ROUND(('01_Criterios'!$C$19*AH14+'01_Criterios'!$C$20*AI14+'01_Criterios'!$C$21*AJ14)/('01_Criterios'!$C$19+'01_Criterios'!$C$20+'01_Criterios'!$C$21)+N14*'01_Criterios'!$C$22,1) -> 88.3 | AL14: =IF(AND(AB14>=3,AC14>='01_Criterios'!$C$11,N(AE14)>='01_Criterios'!$C$12,OR(F14="+",F14="-"),ISNUMBER(G14),ISNUMBER(H14)),1,0) -> 1 | AM14: =IF(AL14=1,"",TRIM(IF(AB14=0,"sem dados no período; ",IF(AB14<3,"série demasiado curta; ",""))&IF(AND(AB14>0,AC14<'01_Criterios'!$C$11),"cobertura insuficiente; ","")&IF(AND(AB14>0,N(AE14)<'01_Criterios'!$C$12),"desactualizado; ","")&IF(AND(F14<>"+",F14<>"-"),"sentido ambíguo; ","")&IF(OR(NOT(ISNUMBER(G14)),NOT(ISNUMBER(H14))),"sem limites min/max; ",""))) | AN14: =IF(OR(AL14=0,$AP14="Excluir"),0,IF(SUMPRODUCT(($O$5:$O$335=$O14)*($AL$5:$AL$335=1)*($AP$5:$AP$335<>"Excluir")*(($AK$5:$AK$335>$AK14)+(($AK$5:$AK$335=$AK14)*(ROW($O$5:$O$335)<ROW()))))=0,1,0)) -> 0 | AO14: =IF(AN14=0,"",1+SUMPRODUCT(($B$5:$B$335=$B14)*($AN$5:$AN$335=1)*(($AK$5:$AK$335>$AK14)+(($AK$5:$AK$335=$AK14)*(ROW($B$5:$B$335)<ROW()))))) | AP14: Excluir | AQ14: =IF(INDEX('01_Criterios'!$C$26:$C$36,MATCH($B14,'01_Criterios'!$B$26:$B$36,0))<>1,0,IF($AP14="Excluir",0,IF($AP14="Incluir",IF(AND(OR($F14="+",$F14="-"),ISNUMBER($G14),ISNUMBER($H14),COUNT($Q14:$AA14)>0),1,0),IF('01_Criterios'!$C$18="Automática",IF(AND($AN14=1,$AO14<>"",$AO14<=INDEX('01_Criterios'!$E$26:$E$36,MATCH($B14,'01_Criterios'!$B$26:$B$36,0))),1,0),0)))) -> 0 | AR14: =IF(AQ14=0,"",IF($AO14<>"",1+SUMPRODUCT(($B$5:$B$335=$B14)*($AQ$5:$AQ$335=1)*($AO$5:$AO$335<$AO14)),1+SUMPRODUCT(($B$5:$B$335=$B14)*($AQ$5:$AQ$335=1)*ISNUMBER($AO$5:$AO$335))+SUMPRODUCT(($B$5:$B$335=$B14)*($AQ$5:$AQ$335=1)*($AO$5:$AO$335="")*(ROW($AO$5:$AO$335)<ROW())))) | AS14: Excluído por anti-duplicação (conceito já representado).
A15: GOV008 | B15: 1. Governança e Estado de Direito | C15: 1. Governança | D15: WGI - Voz e Responsabilização | E15: -2.5 a 2.5 | F15: + | G15: -2.5 | H15: 2.5 | I15: 0 | J15: 1 | K15: WGI/Banco Mundial | L15: VA.EST | M15: Compilação interna BDA | N15: 0 | O15: GOV008 | P15: Média | Q15: -1.1542998 | R15: -1.19498 | S15: -1.131561 | T15: -1.005668 | U15: -0.9382176 | V15: -0.9376898 | W15: -0.9985085 | X15: -1.0480912 | Y15: -1.020936 | Z15: -1.0588932 | AB15: =COUNT(Q15:AA15) -> 10 | AC15: =AB15/11 -> 0.90909091 | AD15: =IFERROR(INDEX($Q$4:$AA$4,MATCH(TRUE,INDEX(ISNUMBER(Q15:AA15),0),0)),"") -> 2015 | AE15: =IFERROR(LOOKUP(2,1/ISNUMBER(Q15:AA15),$Q$4:$AA$4),"") -> 2024 | AF15: =IF(AB15=0,"",AB15/(AE15-AD15+1)) -> 1 | AG15: =IF(AB15=0,"",'01_Criterios'!$C$8-AE15) -> 1 | AH15: =IF(P15="Em uso",100,IF(P15="Alta",85,IF(P15="Média",55,30))) -> 55 | AI15: =ROUND(100*AC15,1) -> 90.9 | AJ15: =IF(AB15=0,0,ROUND(MAX(0,100*AF15-10*AG15),1)) -> 90 | AK15: =ROUND(('01_Criterios'!$C$19*AH15+'01_Criterios'!$C$20*AI15+'01_Criterios'!$C$21*AJ15)/('01_Criterios'!$C$19+'01_Criterios'!$C$20+'01_Criterios'!$C$21)+N15*'01_Criterios'!$C$22,1) -> 76.3 | AL15: =IF(AND(AB15>=3,AC15>='01_Criterios'!$C$11,N(AE15)>='01_Criterios'!$C$12,OR(F15="+",F15="-"),ISNUMBER(G15),ISNUMBER(H15)),1,0) -> 1 | AM15: =IF(AL15=1,"",TRIM(IF(AB15=0,"sem dados no período; ",IF(AB15<3,"série demasiado curta; ",""))&IF(AND(AB15>0,AC15<'01_Criterios'!$C$11),"cobertura insuficiente; ","")&IF(AND(AB15>0,N(AE15)<'01_Criterios'!$C$12),"desactualizado; ","")&IF(AND(F15<>"+",F15<>"-"),"sentido ambíguo; ","")&IF(OR(NOT(ISNUMBER(G15)),NOT(ISNUMBER(H15))),"sem limites min/max; ",""))) | AN15: =IF(OR(AL15=0,$AP15="Excluir"),0,IF(SUMPRODUCT(($O$5:$O$335=$O15)*($AL$5:$AL$335=1)*($AP$5:$AP$335<>"Excluir")*(($AK$5:$AK$335>$AK15)+(($AK$5:$AK$335=$AK15)*(ROW($O$5:$O$335)<ROW()))))=0,1,0)) -> 1 | AO15: =IF(AN15=0,"",1+SUMPRODUCT(($B$5:$B$335=$B15)*($AN$5:$AN$335=1)*(($AK$5:$AK$335>$AK15)+(($AK$5:$AK$335=$AK15)*(ROW($B$5:$B$335)<ROW()))))) -> 6 | AP15: Auto | AQ15: =IF(INDEX('01_Criterios'!$C$26:$C$36,MATCH($B15,'01_Criterios'!$B$26:$B$36,0))<>1,0,IF($AP15="Excluir",0,IF($AP15="Incluir",IF(AND(OR($F15="+",$F15="-"),ISNUMBER($G15),ISNUMBER($H15),COUNT($Q15:$AA15)>0),1,0),IF('01_Criterios'!$C$18="Automática",IF(AND($AN15=1,$AO15<>"",$AO15<=INDEX('01_Criterios'!$E$26:$E$36,MATCH($B15,'01_Criterios'!$B$26:$B$36,0))),1,0),0)))) -> 0 | AR15: =IF(AQ15=0,"",IF($AO15<>"",1+SUMPRODUCT(($B$5:$B$335=$B15)*($AQ$5:$AQ$335=1)*($AO$5:$AO$335<$AO15)),1+SUMPRODUCT(($B$5:$B$335=$B15)*($AQ$5:$AQ$335=1)*ISNUMBER($AO$5:$AO$335))+SUMPRODUCT(($B$5:$B$335=$B15)*($AQ$5:$AQ$335=1)*($AO$5:$AO$335="")*(ROW($AO$5:$AO$335)<ROW())))) | AS15: Acrescenta dimensão de responsabilização pública e participação. Cobertura estimada pela periodicidade WGI; o endpoint WDI simples não devolve esta série.
A16: GOV010 | B16: 1. Governança e Estado de Direito | C16: 1. Governança | D16: Índice Ibrahim - Segurança e Estado de Direito | E16: 0-100 | F16: + | G16: 0 | H16: 100 | I16: 55 | J16: 1 | K16: Mo Ibrahim Foundation | L16: IIAG_SECRULE | M16: Mo Ibrahim Foundation | N16: 0 | O16: G_IIAG_SECRULE | P16: Média | Y16: 44.2 | AB16: =COUNT(Q16:AA16) -> 1 | AC16: =AB16/11 -> 0.090909091 | AD16: =IFERROR(INDEX($Q$4:$AA$4,MATCH(TRUE,INDEX(ISNUMBER(Q16:AA16),0),0)),"") -> 2023 | AE16: =IFERROR(LOOKUP(2,1/ISNUMBER(Q16:AA16),$Q$4:$AA$4),"") -> 2023 | AF16: =IF(AB16=0,"",AB16/(AE16-AD16+1)) -> 1 | AG16: =IF(AB16=0,"",'01_Criterios'!$C$8-AE16) -> 2 | AH16: =IF(P16="Em uso",100,IF(P16="Alta",85,IF(P16="Média",55,30))) -> 55 | AI16: =ROUND(100*AC16,1) -> 9.1 | AJ16: =IF(AB16=0,0,ROUND(MAX(0,100*AF16-10*AG16),1)) -> 80 | AK16: =ROUND(('01_Criterios'!$C$19*AH16+'01_Criterios'!$C$20*AI16+'01_Criterios'!$C$21*AJ16)/('01_Criterios'!$C$19+'01_Criterios'!$C$20+'01_Criterios'!$C$21)+N16*'01_Criterios'!$C$22,1) -> 45.2 | AL16: =IF(AND(AB16>=3,AC16>='01_Criterios'!$C$11,N(AE16)>='01_Criterios'!$C$12,OR(F16="+",F16="-"),ISNUMBER(G16),ISNUMBER(H16)),1,0) -> 0 | AM16: =IF(AL16=1,"",TRIM(IF(AB16=0,"sem dados no período; ",IF(AB16<3,"série demasiado curta; ",""))&IF(AND(AB16>0,AC16<'01_Criterios'!$C$11),"cobertura insuficiente; ","")&IF(AND(AB16>0,N(AE16)<'01_Criterios'!$C$12),"desactualizado; ","")&IF(AND(F16<>"+",F16<>"-"),"sentido ambíguo; ","")&IF(OR(NOT(ISNUMBER(G16)),NOT(ISNUMBER(H16))),"sem limites min/max; ",""))) -> série demasiado curta; cobertura insuficiente; | AN16: =IF(OR(AL16=0,$AP16="Excluir"),0,IF(SUMPRODUCT(($O$5:$O$335=$O16)*($AL$5:$AL$335=1)*($AP$5:$AP$335<>"Excluir")*(($AK$5:$AK$335>$AK16)+(($AK$5:$AK$335=$AK16)*(ROW($O$5:$O$335)<ROW()))))=0,1,0)) -> 0 | AO16: =IF(AN16=0,"",1+SUMPRODUCT(($B$5:$B$335=$B16)*($AN$5:$AN$335=1)*(($AK$5:$AK$335>$AK16)+(($AK$5:$AK$335=$AK16)*(ROW($B$5:$B$335)<ROW()))))) | AP16: Auto | AQ16: =IF(INDEX('01_Criterios'!$C$26:$C$36,MATCH($B16,'01_Criterios'!$B$26:$B$36,0))<>1,0,IF($AP16="Excluir",0,IF($AP16="Incluir",IF(AND(OR($F16="+",$F16="-"),ISNUMBER($G16),ISNUMBER($H16),COUNT($Q16:$AA16)>0),1,0),IF('01_Criterios'!$C$18="Automática",IF(AND($AN16=1,$AO16<>"",$AO16<=INDEX('01_Criterios'!$E$26:$E$36,MATCH($B16,'01_Criterios'!$B$26:$B$36,0))),1,0),0)))) -> 0 | AR16: =IF(AQ16=0,"",IF($AO16<>"",1+SUMPRODUCT(($B$5:$B$335=$B16)*($AQ$5:$AQ$335=1)*($AO$5:$AO$335<$AO16)),1+SUMPRODUCT(($B$5:$B$335=$B16)*($AQ$5:$AQ$335=1)*ISNUMBER($AO$5:$AO$335))+SUMPRODUCT(($B$5:$B$335=$B16)*($AQ$5:$AQ$335=1)*($AO$5:$AO$335="")*(ROW($AO$5:$AO$335)<ROW())))) | AS16: Aproxima governança de segurança, justiça e direitos no contexto africano. | IIAG 2024 scorecard/perfil; categoria Security & Rule of Law.
A17: GOV011 | B17: 1. Governança e Estado de Direito | C17: 1. Governança | D17: Open Budget Index | E17: 0-100 | F17: + | G17: 0 | H17: 100 | I17: 50 | J17: 1 | K17: International Budget Partnership | L17: OBI | M17: International Budget Partnership | N17: 0 | O17: GOV011 | P17: Média | Q17: 26 | S17: 25 | U17: 36 | W17: 30 | Y17: 26 | AB17: =COUNT(Q17:AA17) -> 5 | AC17: =AB17/11 -> 0.45454545 | AD17: =IFERROR(INDEX($Q$4:$AA$4,MATCH(TRUE,INDEX(ISNUMBER(Q17:AA17),0),0)),"") -> 2015 | AE17: =IFERROR(LOOKUP(2,1/ISNUMBER(Q17:AA17),$Q$4:$AA$4),"") -> 2023 | AF17: =IF(AB17=0,"",AB17/(AE17-AD17+1)) -> 0.55555556 | AG17: =IF(AB17=0,"",'01_Criterios'!$C$8-AE17) -> 2 | AH17: =IF(P17="Em uso",100,IF(P17="Alta",85,IF(P17="Média",55,30))) -> 55 | AI17: =ROUND(100*AC17,1) -> 45.5 | AJ17: =IF(AB17=0,0,ROUND(MAX(0,100*AF17-10*AG17),1)) -> 35.6 | AK17: =ROUND(('01_Criterios'!$C$19*AH17+'01_Criterios'!$C$20*AI17+'01_Criterios'!$C$21*AJ17)/('01_Criterios'!$C$19+'01_Criterios'!$C$20+'01_Criterios'!$C$21)+N17*'01_Criterios'!$C$22,1) -> 46.8 | AL17: =IF(AND(AB17>=3,AC17>='01_Criterios'!$C$11,N(AE17)>='01_Criterios'!$C$12,OR(F17="+",F17="-"),ISNUMBER(G17),ISNUMBER(H17)),1,0) -> 0 | AM17: =IF(AL17=1,"",TRIM(IF(AB17=0,"sem dados no período; ",IF(AB17<3,"série demasiado curta; ",""))&IF(AND(AB17>0,AC17<'01_Criterios'!$C$11),"cobertura insuficiente; ","")&IF(AND(AB17>0,N(AE17)<'01_Criterios'!$C$12),"desactualizado; ","")&IF(AND(F17<>"+",F17<>"-"),"sentido ambíguo; ","")&IF(OR(NOT(ISNUMBER(G17)),NOT(ISNUMBER(H17))),"sem limites min/max; ",""))) -> cobertura insuficiente; | AN17: =IF(OR(AL17=0,$AP17="Excluir"),0,IF(SUMPRODUCT(($O$5:$O$335=$O17)*($AL$5:$AL$335=1)*($AP$5:$AP$335<>"Excluir")*(($AK$5:$AK$335>$AK17)+(($AK$5:$AK$335=$AK17)*(ROW($O$5:$O$335)<ROW()))))=0,1,0)) -> 0 | AO17: =IF(AN17=0,"",1+SUMPRODUCT(($B$5:$B$335=$B17)*($AN$5:$AN$335=1)*(($AK$5:$AK$335>$AK17)+(($AK$5:$AK$335=$AK17)*(ROW($B$5:$B$335)<ROW()))))) | AP17: Auto | AQ17: =IF(INDEX('01_Criterios'!$C$26:$C$36,MATCH($B17,'01_Criterios'!$B$26:$B$36,0))<>1,0,IF($AP17="Excluir",0,IF($AP17="Incluir",IF(AND(OR($F17="+",$F17="-"),ISNUMBER($G17),ISNUMBER($H17),COUNT($Q17:$AA17)>0),1,0),IF('01_Criterios'!$C$18="Automática",IF(AND($AN17=1,$AO17<>"",$AO17<=INDEX('01_Criterios'!$E$26:$E$36,MATCH($B17,'01_Criterios'!$B$26:$B$36,0))),1,0),0)))) -> 0 | AR17: =IF(AQ17=0,"",IF($AO17<>"",1+SUMPRODUCT(($B$5:$B$335=$B17)*($AQ$5:$AQ$335=1)*($AO$5:$AO$335<$AO17)),1+SUMPRODUCT(($B$5:$B$335=$B17)*($AQ$5:$AQ$335=1)*ISNUMBER($AO$5:$AO$335))+SUMPRODUCT(($B$5:$B$335=$B17)*($AQ$5:$AQ$335=1)*($AO$5:$AO$335="")*(ROW($AO$5:$AO$335)<ROW())))) | AS17: Mede transparência orçamental, relevante para responsabilização fiscal. | IBP Open Budget Survey 2012-2023 (página de resultados de Angola 2023).
A18: GOV012 | B18: 1. Governança e Estado de Direito | C18: 1. Governança | D18: Empresas solicitadas a fazer pagamentos informais | E18: % | F18: - | G18: 0 | H18: 100 | I18: 10 | J18: 1 | K18: World Bank Enterprise Surveys | M18: Compilação interna BDA | N18: 0 | O18: GOV012 | P18: Média | AB18: =COUNT(Q18:AA18) -> 0 | AC18: =AB18/11 -> 0 | AD18: =IFERROR(INDEX($Q$4:$AA$4,MATCH(TRUE,INDEX(ISNUMBER(Q18:AA18),0),0)),"") | AE18: =IFERROR(LOOKUP(2,1/ISNUMBER(Q18:AA18),$Q$4:$AA$4),"") | AF18: =IF(AB18=0,"",AB18/(AE18-AD18+1)) | AG18: =IF(AB18=0,"",'01_Criterios'!$C$8-AE18) | AH18: =IF(P18="Em uso",100,IF(P18="Alta",85,IF(P18="Média",55,30))) -> 55 | AI18: =ROUND(100*AC18,1) -> 0 | AJ18: =IF(AB18=0,0,ROUND(MAX(0,100*AF18-10*AG18),1)) -> 0 | AK18: =ROUND(('01_Criterios'!$C$19*AH18+'01_Criterios'!$C$20*AI18+'01_Criterios'!$C$21*AJ18)/('01_Criterios'!$C$19+'01_Criterios'!$C$20+'01_Criterios'!$C$21)+N18*'01_Criterios'!$C$22,1) -> 22 | AL18: =IF(AND(AB18>=3,AC18>='01_Criterios'!$C$11,N(AE18)>='01_Criterios'!$C$12,OR(F18="+",F18="-"),ISNUMBER(G18),ISNUMBER(H18)),1,0) -> 0 | AM18: =IF(AL18=1,"",TRIM(IF(AB18=0,"sem dados no período; ",IF(AB18<3,"série demasiado curta; ",""))&IF(AND(AB18>0,AC18<'01_Criterios'!$C$11),"cobertura insuficiente; ","")&IF(AND(AB18>0,N(AE18)<'01_Criterios'!$C$12),"desactualizado; ","")&IF(AND(F18<>"+",F18<>"-"),"sentido ambíguo; ","")&IF(OR(NOT(ISNUMBER(G18)),NOT(ISNUMBER(H18))),"sem limites min/max; ",""))) -> sem dados no período; | AN18: =IF(OR(AL18=0,$AP18="Excluir"),0,IF(SUMPRODUCT(($O$5:$O$335=$O18)*($AL$5:$AL$335=1)*($AP$5:$AP$335<>"Excluir")*(($AK$5:$AK$335>$AK18)+(($AK$5:$AK$335=$AK18)*(ROW($O$5:$O$335)<ROW()))))=0,1,0)) -> 0 | AO18: =IF(AN18=0,"",1+SUMPRODUCT(($B$5:$B$335=$B18)*($AN$5:$AN$335=1)*(($AK$5:$AK$335>$AK18)+(($AK$5:$AK$335=$AK18)*(ROW($B$5:$B$335)<ROW()))))) | AP18: Auto | AQ18: =IF(INDEX('01_Criterios'!$C$26:$C$36,MATCH($B18,'01_Criterios'!$B$26:$B$36,0))<>1,0,IF($AP18="Excluir",0,IF($AP18="Incluir",IF(AND(OR($F18="+",$F18="-"),ISNUMBER($G18),ISNUMBER($H18),COUNT($Q18:$AA18)>0),1,0),IF('01_Criterios'!$C$18="Automática",IF(AND($AN18=1,$AO18<>"",$AO18<=INDEX('01_Criterios'!$E$26:$E$36,MATCH($B18,'01_Criterios'!$B$26:$B$36,0))),1,0),0)))) -> 0 | AR18: =IF(AQ18=0,"",IF($AO18<>"",1+SUMPRODUCT(($B$5:$B$335=$B18)*($AQ$5:$AQ$335=1)*($AO$5:$AO$335<$AO18)),1+SUMPRODUCT(($B$5:$B$335=$B18)*($AQ$5:$AQ$335=1)*ISNUMBER($AO$5:$AO$335))+SUMPRODUCT(($B$5:$B$335=$B18)*($AQ$5:$AQ$335=1)*($AO$5:$AO$335="")*(ROW($AO$5:$AO$335)<ROW())))) | AS18: Capta corrupção administrativa sentida pelas empresas.
A19: GOV013 | B19: 1. Governança e Estado de Direito | C19: 1. Governança | D19: Statistical Performance Index - score geral | E19: 0-100 | F19: + | G19: 0 | H19: 100 | I19: 65 | J19: 1 | K19: Banco Mundial | L19: IQ.SPI.OVRL | M19: Banco Mundial — WDI | N19: 0 | O19: GOV013 | P19: Média | R19: 47.395417 | S19: 48.359583 | T19: 54.572083 | U19: 57.9525 | V19: 59.17 | W19: 56.45625 | X19: 54.967083 | Y19: 57.595833 | Z19: 58.152083 | AB19: =COUNT(Q19:AA19) -> 9 | AC19: =AB19/11 -> 0.81818182 | AD19: =IFERROR(INDEX($Q$4:$AA$4,MATCH(TRUE,INDEX(ISNUMBER(Q19:AA19),0),0)),"") -> 2016 | AE19: =IFERROR(LOOKUP(2,1/ISNUMBER(Q19:AA19),$Q$4:$AA$4),"") -> 2024 | AF19: =IF(AB19=0,"",AB19/(AE19-AD19+1)) -> 1 | AG19: =IF(AB19=0,"",'01_Criterios'!$C$8-AE19) -> 1 | AH19: =IF(P19="Em uso",100,IF(P19="Alta",85,IF(P19="Média",55,30))) -> 55 | AI19: =ROUND(100*AC19,1) -> 81.8 | AJ19: =IF(AB19=0,0,ROUND(MAX(0,100*AF19-10*AG19),1)) -> 90 | AK19: =ROUND(('01_Criterios'!$C$19*AH19+'01_Criterios'!$C$20*AI19+'01_Criterios'!$C$21*AJ19)/('01_Criterios'!$C$19+'01_Criterios'!$C$20+'01_Criterios'!$C$21)+N19*'01_Criterios'!$C$22,1) -> 73.1 | AL19: =IF(AND(AB19>=3,AC19>='01_Criterios'!$C$11,N(AE19)>='01_Criterios'!$C$12,OR(F19="+",F19="-"),ISNUMBER(G19),ISNUMBER(H19)),1,0) -> 1 | AM19: =IF(AL19=1,"",TRIM(IF(AB19=0,"sem dados no período; ",IF(AB19<3,"série demasiado curta; ",""))&IF(AND(AB19>0,AC19<'01_Criterios'!$C$11),"cobertura insuficiente; ","")&IF(AND(AB19>0,N(AE19)<'01_Criterios'!$C$12),"desactualizado; ","")&IF(AND(F19<>"+",F19<>"-"),"sentido ambíguo; ","")&IF(OR(NOT(ISNUMBER(G19)),NOT(ISNUMBER(H19))),"sem limites min/max; ",""))) | AN19: =IF(OR(AL19=0,$AP19="Excluir"),0,IF(SUMPRODUCT(($O$5:$O$335=$O19)*($AL$5:$AL$335=1)*($AP$5:$AP$335<>"Excluir")*(($AK$5:$AK$335>$AK19)+(($AK$5:$AK$335=$AK19)*(ROW($O$5:$O$335)<ROW()))))=0,1,0)) -> 1 | AO19: =IF(AN19=0,"",1+SUMPRODUCT(($B$5:$B$335=$B19)*($AN$5:$AN$335=1)*(($AK$5:$AK$335>$AK19)+(($AK$5:$AK$335=$AK19)*(ROW($B$5:$B$335)<ROW()))))) -> 7 | AP19: Auto | AQ19: =IF(INDEX('01_Criterios'!$C$26:$C$36,MATCH($B19,'01_Criterios'!$B$26:$B$36,0))<>1,0,IF($AP19="Excluir",0,IF($AP19="Incluir",IF(AND(OR($F19="+",$F19="-"),ISNUMBER($G19),ISNUMBER($H19),COUNT($Q19:$AA19)>0),1,0),IF('01_Criterios'!$C$18="Automática",IF(AND($AN19=1,$AO19<>"",$AO19<=INDEX('01_Criterios'!$E$26:$E$36,MATCH($B19,'01_Criterios'!$B$26:$B$36,0))),1,0),0)))) -> 0 | AR19: =IF(AQ19=0,"",IF($AO19<>"",1+SUMPRODUCT(($B$5:$B$335=$B19)*($AQ$5:$AQ$335=1)*($AO$5:$AO$335<$AO19)),1+SUMPRODUCT(($B$5:$B$335=$B19)*($AQ$5:$AQ$335=1)*ISNUMBER($AO$5:$AO$335))+SUMPRODUCT(($B$5:$B$335=$B19)*($AQ$5:$AQ$335=1)*($AO$5:$AO$335="")*(ROW($AO$5:$AO$335)<ROW())))) | AS19: Mede capacidade estatística, útil para qualidade de políticas públicas e monitorização. | Nome local/API: Statistical performance indicators (SPI): Overall score (scale 0-100)
A20: GOV014 | B20: 1. Governança e Estado de Direito | C20: Instituições públicas | D20: CPIA - direitos de propriedade e governação baseada em regras | E20: 1-6 | F20: + | G20: 1 | H20: 6 | I20: 4 | J20: 1 | K20: Banco Mundial/WDI | L20: IQ.CPA.PROP.XQ | M20: Banco Mundial — WDI | N20: 0 | O20: GOV014 | P20: Média | AB20: =COUNT(Q20:AA20) -> 0 | AC20: =AB20/11 -> 0 | AD20: =IFERROR(INDEX($Q$4:$AA$4,MATCH(TRUE,INDEX(ISNUMBER(Q20:AA20),0),0)),"") | AE20: =IFERROR(LOOKUP(2,1/ISNUMBER(Q20:AA20),$Q$4:$AA$4),"") | AF20: =IF(AB20=0,"",AB20/(AE20-AD20+1)) | AG20: =IF(AB20=0,"",'01_Criterios'!$C$8-AE20) | AH20: =IF(P20="Em uso",100,IF(P20="Alta",85,IF(P20="Média",55,30))) -> 55 | AI20: =ROUND(100*AC20,1) -> 0 | AJ20: =IF(AB20=0,0,ROUND(MAX(0,100*AF20-10*AG20),1)) -> 0 | AK20: =ROUND(('01_Criterios'!$C$19*AH20+'01_Criterios'!$C$20*AI20+'01_Criterios'!$C$21*AJ20)/('01_Criterios'!$C$19+'01_Criterios'!$C$20+'01_Criterios'!$C$21)+N20*'01_Criterios'!$C$22,1) -> 22 | AL20: =IF(AND(AB20>=3,AC20>='01_Criterios'!$C$11,N(AE20)>='01_Criterios'!$C$12,OR(F20="+",F20="-"),ISNUMBER(G20),ISNUMBER(H20)),1,0) -> 0 | AM20: =IF(AL20=1,"",TRIM(IF(AB20=0,"sem dados no período; ",IF(AB20<3,"série demasiado curta; ",""))&IF(AND(AB20>0,AC20<'01_Criterios'!$C$11),"cobertura insuficiente; ","")&IF(AND(AB20>0,N(AE20)<'01_Criterios'!$C$12),"desactualizado; ","")&IF(AND(F20<>"+",F20<>"-"),"sentido ambíguo; ","")&IF(OR(NOT(ISNUMBER(G20)),NOT(ISNUMBER(H20))),"sem limites min/max; ",""))) -> sem dados no período; | AN20: =IF(OR(AL20=0,$AP20="Excluir"),0,IF(SUMPRODUCT(($O$5:$O$335=$O20)*($AL$5:$AL$335=1)*($AP$5:$AP$335<>"Excluir")*(($AK$5:$AK$335>$AK20)+(($AK$5:$AK$335=$AK20)*(ROW($O$5:$O$335)<ROW()))))=0,1,0)) -> 0 | AO20: =IF(AN20=0,"",1+SUMPRODUCT(($B$5:$B$335=$B20)*($AN$5:$AN$335=1)*(($AK$5:$AK$335>$AK20)+(($AK$5:$AK$335=$AK20)*(ROW($B$5:$B$335)<ROW()))))) | AP20: Auto | AQ20: =IF(INDEX('01_Criterios'!$C$26:$C$36,MATCH($B20,'01_Criterios'!$B$26:$B$36,0))<>1,0,IF($AP20="Excluir",0,IF($AP20="Incluir",IF(AND(OR($F20="+",$F20="-"),ISNUMBER($G20),ISNUMBER($H20),COUNT($Q20:$AA20)>0),1,0),IF('01_Criterios'!$C$18="Automática",IF(AND($AN20=1,$AO20<>"",$AO20<=INDEX('01_Criterios'!$E$26:$E$36,MATCH($B20,'01_Criterios'!$B$26:$B$36,0))),1,0),0)))) -> 0 | AR20: =IF(AQ20=0,"",IF($AO20<>"",1+SUMPRODUCT(($B$5:$B$335=$B20)*($AQ$5:$AQ$335=1)*($AO$5:$AO$335<$AO20)),1+SUMPRODUCT(($B$5:$B$335=$B20)*($AQ$5:$AQ$335=1)*ISNUMBER($AO$5:$AO$335))+SUMPRODUCT(($B$5:$B$335=$B20)*($AQ$5:$AQ$335=1)*($AO$5:$AO$335="")*(ROW($AO$5:$AO$335)<ROW())))) | AS20: Complementa WGI em qualidade institucional para países elegíveis IDA. | Nome local/API: CPIA property rights and rule-based governance rating (1=low to 6=high)
A21: GOV015 | B21: 1. Governança e Estado de Direito | C21: Instituições públicas | D21: CPIA - transparência, responsabilização e corrupção no setor público | E21: 1-6 | F21: + | G21: 1 | H21: 6 | I21: 4 | J21: 1 | K21: Banco Mundial/WDI | L21: IQ.CPA.TRAN.XQ | M21: Banco Mundial — WDI | N21: 0 | O21: GOV015 | P21: Média | AB21: =COUNT(Q21:AA21) -> 0 | AC21: =AB21/11 -> 0 | AD21: =IFERROR(INDEX($Q$4:$AA$4,MATCH(TRUE,INDEX(ISNUMBER(Q21:AA21),0),0)),"") | AE21: =IFERROR(LOOKUP(2,1/ISNUMBER(Q21:AA21),$Q$4:$AA$4),"") | AF21: =IF(AB21=0,"",AB21/(AE21-AD21+1)) | AG21: =IF(AB21=0,"",'01_Criterios'!$C$8-AE21) | AH21: =IF(P21="Em uso",100,IF(P21="Alta",85,IF(P21="Média",55,30))) -> 55 | AI21: =ROUND(100*AC21,1) -> 0 | AJ21: =IF(AB21=0,0,ROUND(MAX(0,100*AF21-10*AG21),1)) -> 0 | AK21: =ROUND(('01_Criterios'!$C$19*AH21+'01_Criterios'!$C$20*AI21+'01_Criterios'!$C$21*AJ21)/('01_Criterios'!$C$19+'01_Criterios'!$C$20+'01_Criterios'!$C$21)+N21*'01_Criterios'!$C$22,1) -> 22 | AL21: =IF(AND(AB21>=3,AC21>='01_Criterios'!$C$11,N(AE21)>='01_Criterios'!$C$12,OR(F21="+",F21="-"),ISNUMBER(G21),ISNUMBER(H21)),1,0) -> 0 | AM21: =IF(AL21=1,"",TRIM(IF(AB21=0,"sem dados no período; ",IF(AB21<3,"série demasiado curta; ",""))&IF(AND(AB21>0,AC21<'01_Criterios'!$C$11),"cobertura insuficiente; ","")&IF(AND(AB21>0,N(AE21)<'01_Criterios'!$C$12),"desactualizado; ","")&IF(AND(F21<>"+",F21<>"-"),"sentido ambíguo; ","")&IF(OR(NOT(ISNUMBER(G21)),NOT(ISNUMBER(H21))),"sem limites min/max; ",""))) -> sem dados no período; | AN21: =IF(OR(AL21=0,$AP21="Excluir"),0,IF(SUMPRODUCT(($O$5:$O$335=$O21)*($AL$5:$AL$335=1)*($AP$5:$AP$335<>"Excluir")*(($AK$5:$AK$335>$AK21)+(($AK$5:$AK$335=$AK21)*(ROW($O$5:$O$335)<ROW()))))=0,1,0)) -> 0 | AO21: =IF(AN21=0,"",1+SUMPRODUCT(($B$5:$B$335=$B21)*($AN$5:$AN$335=1)*(($AK$5:$AK$335>$AK21)+(($AK$5:$AK$335=$AK21)*(ROW($B$5:$B$335)<ROW()))))) | AP21: Auto | AQ21: =IF(INDEX('01_Criterios'!$C$26:$C$36,MATCH($B21,'01_Criterios'!$B$26:$B$36,0))<>1,0,IF($AP21="Excluir",0,IF($AP21="Incluir",IF(AND(OR($F21="+",$F21="-"),ISNUMBER($G21),ISNUMBER($H21),COUNT($Q21:$AA21)>0),1,0),IF('01_Criterios'!$C$18="Automática",IF(AND($AN21=1,$AO21<>"",$AO21<=INDEX('01_Criterios'!$E$26:$E$36,MATCH($B21,'01_Criterios'!$B$26:$B$36,0))),1,0),0)))) -> 0 | AR21: =IF(AQ21=0,"",IF($AO21<>"",1+SUMPRODUCT(($B$5:$B$335=$B21)*($AQ$5:$AQ$335=1)*($AO$5:$AO$335<$AO21)),1+SUMPRODUCT(($B$5:$B$335=$B21)*($AQ$5:$AQ$335=1)*ISNUMBER($AO$5:$AO$335))+SUMPRODUCT(($B$5:$B$335=$B21)*($AQ$5:$AQ$335=1)*($AO$5:$AO$335="")*(ROW($AO$5:$AO$335)<ROW())))) | AS21: Complementa CPI/WGI com avaliação institucional operacional. | Nome local/API: CPIA transparency, accountability, and corruption in the public sector rating (1=low to 6=high)
A22: GOV016 | B22: 1. Governança e Estado de Direito | C22: Instituições públicas | D22: CPIA - gestão do setor público e instituições | E22: 1-6 | F22: + | G22: 1 | H22: 6 | I22: 4 | J22: 1 | K22: Banco Mundial/WDI | L22: IQ.CPA.PUBS.XQ | M22: Banco Mundial — WDI | N22: 0 | O22: GOV016 | P22: Média | AB22: =COUNT(Q22:AA22) -> 0 | AC22: =AB22/11 -> 0 | AD22: =IFERROR(INDEX($Q$4:$AA$4,MATCH(TRUE,INDEX(ISNUMBER(Q22:AA22),0),0)),"") | AE22: =IFERROR(LOOKUP(2,1/ISNUMBER(Q22:AA22),$Q$4:$AA$4),"") | AF22: =IF(AB22=0,"",AB22/(AE22-AD22+1)) | AG22: =IF(AB22=0,"",'01_Criterios'!$C$8-AE22) | AH22: =IF(P22="Em uso",100,IF(P22="Alta",85,IF(P22="Média",55,30))) -> 55 | AI22: =ROUND(100*AC22,1) -> 0 | AJ22: =IF(AB22=0,0,ROUND(MAX(0,100*AF22-10*AG22),1)) -> 0 | AK22: =ROUND(('01_Criterios'!$C$19*AH22+'01_Criterios'!$C$20*AI22+'01_Criterios'!$C$21*AJ22)/('01_Criterios'!$C$19+'01_Criterios'!$C$20+'01_Criterios'!$C$21)+N22*'01_Criterios'!$C$22,1) -> 22 | AL22: =IF(AND(AB22>=3,AC22>='01_Criterios'!$C$11,N(AE22)>='01_Criterios'!$C$12,OR(F22="+",F22="-"),ISNUMBER(G22),ISNUMBER(H22)),1,0) -> 0 | AM22: =IF(AL22=1,"",TRIM(IF(AB22=0,"sem dados no período; ",IF(AB22<3,"série demasiado curta; ",""))&IF(AND(AB22>0,AC22<'01_Criterios'!$C$11),"cobertura insuficiente; ","")&IF(AND(AB22>0,N(AE22)<'01_Criterios'!$C$12),"desactualizado; ","")&IF(AND(F22<>"+",F22<>"-"),"sentido ambíguo; ","")&IF(OR(NOT(ISNUMBER(G22)),NOT(ISNUMBER(H22))),"sem limites min/max; ",""))) -> sem dados no período; | AN22: =IF(OR(AL22=0,$AP22="Excluir"),0,IF(SUMPRODUCT(($O$5:$O$335=$O22)*($AL$5:$AL$335=1)*($AP$5:$AP$335<>"Excluir")*(($AK$5:$AK$335>$AK22)+(($AK$5:$AK$335=$AK22)*(ROW($O$5:$O$335)<ROW()))))=0,1,0)) -> 0 | AO22: =IF(AN22=0,"",1+SUMPRODUCT(($B$5:$B$335=$B22)*($AN$5:$AN$335=1)*(($AK$5:$AK$335>$AK22)+(($AK$5:$AK$335=$AK22)*(ROW($B$5:$B$335)<ROW()))))) | AP22: Auto | AQ22: =IF(INDEX('01_Criterios'!$C$26:$C$36,MATCH($B22,'01_Criterios'!$B$26:$B$36,0))<>1,0,IF($AP22="Excluir",0,IF($AP22="Incluir",IF(AND(OR($F22="+",$F22="-"),ISNUMBER($G22),ISNUMBER($H22),COUNT($Q22:$AA22)>0),1,0),IF('01_Criterios'!$C$18="Automática",IF(AND($AN22=1,$AO22<>"",$AO22<=INDEX('01_Criterios'!$E$26:$E$36,MATCH($B22,'01_Criterios'!$B$26:$B$36,0))),1,0),0)))) -> 0 | AR22: =IF(AQ22=0,"",IF($AO22<>"",1+SUMPRODUCT(($B$5:$B$335=$B22)*($AQ$5:$AQ$335=1)*($AO$5:$AO$335<$AO22)),1+SUMPRODUCT(($B$5:$B$335=$B22)*($AQ$5:$AQ$335=1)*ISNUMBER($AO$5:$AO$335))+SUMPRODUCT(($B$5:$B$335=$B22)*($AQ$5:$AQ$335=1)*($AO$5:$AO$335="")*(ROW($AO$5:$AO$335)<ROW())))) | AS22: Cluster institucional útil para robustez do capítulo de governação. | Nome local/API: CPIA public sector management and institutions cluster average (1=low to 6=high)
A23: GOV017 | B23: 1. Governança e Estado de Direito | C23: Instituições públicas | D23: CPIA - qualidade da administração pública | E23: 1-6 | F23: + | G23: 1 | H23: 6 | I23: 4 | J23: 1 | K23: Banco Mundial/WDI | L23: IQ.CPA.PADM.XQ | M23: Banco Mundial — WDI | N23: 0 | O23: GOV017 | P23: Média | AB23: =COUNT(Q23:AA23) -> 0 | AC23: =AB23/11 -> 0 | AD23: =IFERROR(INDEX($Q$4:$AA$4,MATCH(TRUE,INDEX(ISNUMBER(Q23:AA23),0),0)),"") | AE23: =IFERROR(LOOKUP(2,1/ISNUMBER(Q23:AA23),$Q$4:$AA$4),"") | AF23: =IF(AB23=0,"",AB23/(AE23-AD23+1)) | AG23: =IF(AB23=0,"",'01_Criterios'!$C$8-AE23) | AH23: =IF(P23="Em uso",100,IF(P23="Alta",85,IF(P23="Média",55,30))) -> 55 | AI23: =ROUND(100*AC23,1) -> 0 | AJ23: =IF(AB23=0,0,ROUND(MAX(0,100*AF23-10*AG23),1)) -> 0 | AK23: =ROUND(('01_Criterios'!$C$19*AH23+'01_Criterios'!$C$20*AI23+'01_Criterios'!$C$21*AJ23)/('01_Criterios'!$C$19+'01_Criterios'!$C$20+'01_Criterios'!$C$21)+N23*'01_Criterios'!$C$22,1) -> 22 | AL23: =IF(AND(AB23>=3,AC23>='01_Criterios'!$C$11,N(AE23)>='01_Criterios'!$C$12,OR(F23="+",F23="-"),ISNUMBER(G23),ISNUMBER(H23)),1,0) -> 0 | AM23: =IF(AL23=1,"",TRIM(IF(AB23=0,"sem dados no período; ",IF(AB23<3,"série demasiado curta; ",""))&IF(AND(AB23>0,AC23<'01_Criterios'!$C$11),"cobertura insuficiente; ","")&IF(AND(AB23>0,N(AE23)<'01_Criterios'!$C$12),"desactualizado; ","")&IF(AND(F23<>"+",F23<>"-"),"sentido ambíguo; ","")&IF(OR(NOT(ISNUMBER(G23)),NOT(ISNUMBER(H23))),"sem limites min/max; ",""))) -> sem dados no período; | AN23: =IF(OR(AL23=0,$AP23="Excluir"),0,IF(SUMPRODUCT(($O$5:$O$335=$O23)*($AL$5:$AL$335=1)*($AP$5:$AP$335<>"Excluir")*(($AK$5:$AK$335>$AK23)+(($AK$5:$AK$335=$AK23)*(ROW($O$5:$O$335)<ROW()))))=0,1,0)) -> 0 | AO23: =IF(AN23=0,"",1+SUMPRODUCT(($B$5:$B$335=$B23)*($AN$5:$AN$335=1)*(($AK$5:$AK$335>$AK23)+(($AK$5:$AK$335=$AK23)*(ROW($B$5:$B$335)<ROW()))))) | AP23: Auto | AQ23: =IF(INDEX('01_Criterios'!$C$26:$C$36,MATCH($B23,'01_Criterios'!$B$26:$B$36,0))<>1,0,IF($AP23="Excluir",0,IF($AP23="Incluir",IF(AND(OR($F23="+",$F23="-"),ISNUMBER($G23),ISNUMBER($H23),COUNT($Q23:$AA23)>0),1,0),IF('01_Criterios'!$C$18="Automática",IF(AND($AN23=1,$AO23<>"",$AO23<=INDEX('01_Criterios'!$E$26:$E$36,MATCH($B23,'01_Criterios'!$B$26:$B$36,0))),1,0),0)))) -> 0 | AR23: =IF(AQ23=0,"",IF($AO23<>"",1+SUMPRODUCT(($B$5:$B$335=$B23)*($AQ$5:$AQ$335=1)*($AO$5:$AO$335<$AO23)),1+SUMPRODUCT(($B$5:$B$335=$B23)*($AQ$5:$AQ$335=1)*ISNUMBER($AO$5:$AO$335))+SUMPRODUCT(($B$5:$B$335=$B23)*($AQ$5:$AQ$335=1)*($AO$5:$AO$335="")*(ROW($AO$5:$AO$335)<ROW())))) | AS23: Capta capacidade administrativa do Estado. | Nome local/API: CPIA quality of public administration rating (1=low to 6=high)
A24: GOV018 | B24: 1. Governança e Estado de Direito | C24: Finanças públicas | D24: CPIA - qualidade da gestão orçamental e financeira | E24: 1-6 | F24: + | G24: 1 | H24: 6 | I24: 4 | J24: 1 | K24: Banco Mundial/WDI | L24: IQ.CPA.FINQ.XQ | M24: Banco Mundial — WDI | N24: 0 | O24: GOV018 | P24: Média | AB24: =COUNT(Q24:AA24) -> 0 | AC24: =AB24/11 -> 0 | AD24: =IFERROR(INDEX($Q$4:$AA$4,MATCH(TRUE,INDEX(ISNUMBER(Q24:AA24),0),0)),"") | AE24: =IFERROR(LOOKUP(2,1/ISNUMBER(Q24:AA24),$Q$4:$AA$4),"") | AF24: =IF(AB24=0,"",AB24/(AE24-AD24+1)) | AG24: =IF(AB24=0,"",'01_Criterios'!$C$8-AE24) | AH24: =IF(P24="Em uso",100,IF(P24="Alta",85,IF(P24="Média",55,30))) -> 55 | AI24: =ROUND(100*AC24,1) -> 0 | AJ24: =IF(AB24=0,0,ROUND(MAX(0,100*AF24-10*AG24),1)) -> 0 | AK24: =ROUND(('01_Criterios'!$C$19*AH24+'01_Criterios'!$C$20*AI24+'01_Criterios'!$C$21*AJ24)/('01_Criterios'!$C$19+'01_Criterios'!$C$20+'01_Criterios'!$C$21)+N24*'01_Criterios'!$C$22,1) -> 22 | AL24: =IF(AND(AB24>=3,AC24>='01_Criterios'!$C$11,N(AE24)>='01_Criterios'!$C$12,OR(F24="+",F24="-"),ISNUMBER(G24),ISNUMBER(H24)),1,0) -> 0 | AM24: =IF(AL24=1,"",TRIM(IF(AB24=0,"sem dados no período; ",IF(AB24<3,"série demasiado curta; ",""))&IF(AND(AB24>0,AC24<'01_Criterios'!$C$11),"cobertura insuficiente; ","")&IF(AND(AB24>0,N(AE24)<'01_Criterios'!$C$12),"desactualizado; ","")&IF(AND(F24<>"+",F24<>"-"),"sentido ambíguo; ","")&IF(OR(NOT(ISNUMBER(G24)),NOT(ISNUMBER(H24))),"sem limites min/max; ",""))) -> sem dados no período; | AN24: =IF(OR(AL24=0,$AP24="Excluir"),0,IF(SUMPRODUCT(($O$5:$O$335=$O24)*($AL$5:$AL$335=1)*($AP$5:$AP$335<>"Excluir")*(($AK$5:$AK$335>$AK24)+(($AK$5:$AK$335=$AK24)*(ROW($O$5:$O$335)<ROW()))))=0,1,0)) -> 0 | AO24: =IF(AN24=0,"",1+SUMPRODUCT(($B$5:$B$335=$B24)*($AN$5:$AN$335=1)*(($AK$5:$AK$335>$AK24)+(($AK$5:$AK$335=$AK24)*(ROW($B$5:$B$335)<ROW()))))) | AP24: Auto | AQ24: =IF(INDEX('01_Criterios'!$C$26:$C$36,MATCH($B24,'01_Criterios'!$B$26:$B$36,0))<>1,0,IF($AP24="Excluir",0,IF($AP24="Incluir",IF(AND(OR($F24="+",$F24="-"),ISNUMBER($G24),ISNUMBER($H24),COUNT($Q24:$AA24)>0),1,0),IF('01_Criterios'!$C$18="Automática",IF(AND($AN24=1,$AO24<>"",$AO24<=INDEX('01_Criterios'!$E$26:$E$36,MATCH($B24,'01_Criterios'!$B$26:$B$36,0))),1,0),0)))) -> 0 | AR24: =IF(AQ24=0,"",IF($AO24<>"",1+SUMPRODUCT(($B$5:$B$335=$B24)*($AQ$5:$AQ$335=1)*($AO$5:$AO$335<$AO24)),1+SUMPRODUCT(($B$5:$B$335=$B24)*($AQ$5:$AQ$335=1)*ISNUMBER($AO$5:$AO$335))+SUMPRODUCT(($B$5:$B$335=$B24)*($AQ$5:$AQ$335=1)*($AO$5:$AO$335="")*(ROW($AO$5:$AO$335)<ROW())))) | AS24: Complementa transparência e execução orçamental. | Nome local/API: CPIA quality of budgetary and financial management rating (1=low to 6=high)
A25: GOV019 | B25: 1. Governança e Estado de Direito | C25: Mobilização de receita | D25: CPIA - eficiência da mobilização de receita | E25: 1-6 | F25: + | G25: 1 | H25: 6 | I25: 4 | J25: 1 | K25: Banco Mundial/WDI | L25: IQ.CPA.REVN.XQ | M25: Banco Mundial — WDI | N25: 0 | O25: GOV019 | P25: Média | AB25: =COUNT(Q25:AA25) -> 0 | AC25: =AB25/11 -> 0 | AD25: =IFERROR(INDEX($Q$4:$AA$4,MATCH(TRUE,INDEX(ISNUMBER(Q25:AA25),0),0)),"") | AE25: =IFERROR(LOOKUP(2,1/ISNUMBER(Q25:AA25),$Q$4:$AA$4),"") | AF25: =IF(AB25=0,"",AB25/(AE25-AD25+1)) | AG25: =IF(AB25=0,"",'01_Criterios'!$C$8-AE25) | AH25: =IF(P25="Em uso",100,IF(P25="Alta",85,IF(P25="Média",55,30))) -> 55 | AI25: =ROUND(100*AC25,1) -> 0 | AJ25: =IF(AB25=0,0,ROUND(MAX(0,100*AF25-10*AG25),1)) -> 0 | AK25: =ROUND(('01_Criterios'!$C$19*AH25+'01_Criterios'!$C$20*AI25+'01_Criterios'!$C$21*AJ25)/('01_Criterios'!$C$19+'01_Criterios'!$C$20+'01_Criterios'!$C$21)+N25*'01_Criterios'!$C$22,1) -> 22 | AL25: =IF(AND(AB25>=3,AC25>='01_Criterios'!$C$11,N(AE25)>='01_Criterios'!$C$12,OR(F25="+",F25="-"),ISNUMBER(G25),ISNUMBER(H25)),1,0) -> 0 | AM25: =IF(AL25=1,"",TRIM(IF(AB25=0,"sem dados no período; ",IF(AB25<3,"série demasiado curta; ",""))&IF(AND(AB25>0,AC25<'01_Criterios'!$C$11),"cobertura insuficiente; ","")&IF(AND(AB25>0,N(AE25)<'01_Criterios'!$C$12),"desactualizado; ","")&IF(AND(F25<>"+",F25<>"-"),"sentido ambíguo; ","")&IF(OR(NOT(ISNUMBER(G25)),NOT(ISNUMBER(H25))),"sem limites min/max; ",""))) -> sem dados no período; | AN25: =IF(OR(AL25=0,$AP25="Excluir"),0,IF(SUMPRODUCT(($O$5:$O$335=$O25)*($AL$5:$AL$335=1)*($AP$5:$AP$335<>"Excluir")*(($AK$5:$AK$335>$AK25)+(($AK$5:$AK$335=$AK25)*(ROW($O$5:$O$335)<ROW()))))=0,1,0)) -> 0 | AO25: =IF(AN25=0,"",1+SUMPRODUCT(($B$5:$B$335=$B25)*($AN$5:$AN$335=1)*(($AK$5:$AK$335>$AK25)+(($AK$5:$AK$335=$AK25)*(ROW($B$5:$B$335)<ROW()))))) | AP25: Auto | AQ25: =IF(INDEX('01_Criterios'!$C$26:$C$36,MATCH($B25,'01_Criterios'!$B$26:$B$36,0))<>1,0,IF($AP25="Excluir",0,IF($AP25="Incluir",IF(AND(OR($F25="+",$F25="-"),ISNUMBER($G25),ISNUMBER($H25),COUNT($Q25:$AA25)>0),1,0),IF('01_Criterios'!$C$18="Automática",IF(AND($AN25=1,$AO25<>"",$AO25<=INDEX('01_Criterios'!$E$26:$E$36,MATCH($B25,'01_Criterios'!$B$26:$B$36,0))),1,0),0)))) -> 0 | AR25: =IF(AQ25=0,"",IF($AO25<>"",1+SUMPRODUCT(($B$5:$B$335=$B25)*($AQ$5:$AQ$335=1)*($AO$5:$AO$335<$AO25)),1+SUMPRODUCT(($B$5:$B$335=$B25)*($AQ$5:$AQ$335=1)*ISNUMBER($AO$5:$AO$335))+SUMPRODUCT(($B$5:$B$335=$B25)*($AQ$5:$AQ$335=1)*($AO$5:$AO$335="")*(ROW($AO$5:$AO$335)<ROW())))) | AS25: Relevante para sustentabilidade do Estado. | Nome local/API: CPIA efficiency of revenue mobilization rating (1=low to 6=high)
A26: GOV022 | B26: 1. Governança e Estado de Direito | C26: Segurança e paz | D26: Homicídios intencionais | E26: por 100.000 hab. | F26: - | G26: 0 | H26: 50 | I26: 5 | J26: 1 | K26: Banco Mundial/WDI | L26: VC.IHR.PSRC.P5 | M26: Banco Mundial — WDI | N26: 0 | O26: GOV022 | P26: Média | Q26: 4.4534732 | R26: 4.0982666 | AB26: =COUNT(Q26:AA26) -> 2 | AC26: =AB26/11 -> 0.18181818 | AD26: =IFERROR(INDEX($Q$4:$AA$4,MATCH(TRUE,INDEX(ISNUMBER(Q26:AA26),0),0)),"") -> 2015 | AE26: =IFERROR(LOOKUP(2,1/ISNUMBER(Q26:AA26),$Q$4:$AA$4),"") -> 2016 | AF26: =IF(AB26=0,"",AB26/(AE26-AD26+1)) -> 1 | AG26: =IF(AB26=0,"",'01_Criterios'!$C$8-AE26) -> 9 | AH26: =IF(P26="Em uso",100,IF(P26="Alta",85,IF(P26="Média",55,30))) -> 55 | AI26: =ROUND(100*AC26,1) -> 18.2 | AJ26: =IF(AB26=0,0,ROUND(MAX(0,100*AF26-10*AG26),1)) -> 10 | AK26: =ROUND(('01_Criterios'!$C$19*AH26+'01_Criterios'!$C$20*AI26+'01_Criterios'!$C$21*AJ26)/('01_Criterios'!$C$19+'01_Criterios'!$C$20+'01_Criterios'!$C$21)+N26*'01_Criterios'!$C$22,1) -> 30.9 | AL26: =IF(AND(AB26>=3,AC26>='01_Criterios'!$C$11,N(AE26)>='01_Criterios'!$C$12,OR(F26="+",F26="-"),ISNUMBER(G26),ISNUMBER(H26)),1,0) -> 0 | AM26: =IF(AL26=1,"",TRIM(IF(AB26=0,"sem dados no período; ",IF(AB26<3,"série demasiado curta; ",""))&IF(AND(AB26>0,AC26<'01_Criterios'!$C$11),"cobertura insuficiente; ","")&IF(AND(AB26>0,N(AE26)<'01_Criterios'!$C$12),"desactualizado; ","")&IF(AND(F26<>"+",F26<>"-"),"sentido ambíguo; ","")&IF(OR(NOT(ISNUMBER(G26)),NOT(ISNUMBER(H26))),"sem limites min/max; ",""))) -> série demasiado curta; cobertura insuficiente; desactualizado; | AN26: =IF(OR(AL26=0,$AP26="Excluir"),0,IF(SUMPRODUCT(($O$5:$O$335=$O26)*($AL$5:$AL$335=1)*($AP$5:$AP$335<>"Excluir")*(($AK$5:$AK$335>$AK26)+(($AK$5:$AK$335=$AK26)*(ROW($O$5:$O$335)<ROW()))))=0,1,0)) -> 0 | AO26: =IF(AN26=0,"",1+SUMPRODUCT(($B$5:$B$335=$B26)*($AN$5:$AN$335=1)*(($AK$5:$AK$335>$AK26)+(($AK$5:$AK$335=$AK26)*(ROW($B$5:$B$335)<ROW()))))) | AP26: Auto | AQ26: =IF(INDEX('01_Criterios'!$C$26:$C$36,MATCH($B26,'01_Criterios'!$B$26:$B$36,0))<>1,0,IF($AP26="Excluir",0,IF($AP26="Incluir",IF(AND(OR($F26="+",$F26="-"),ISNUMBER($G26),ISNUMBER($H26),COUNT($Q26:$AA26)>0),1,0),IF('01_Criterios'!$C$18="Automática",IF(AND($AN26=1,$AO26<>"",$AO26<=INDEX('01_Criterios'!$E$26:$E$36,MATCH($B26,'01_Criterios'!$B$26:$B$36,0))),1,0),0)))) -> 0 | AR26: =IF(AQ26=0,"",IF($AO26<>"",1+SUMPRODUCT(($B$5:$B$335=$B26)*($AQ$5:$AQ$335=1)*($AO$5:$AO$335<$AO26)),1+SUMPRODUCT(($B$5:$B$335=$B26)*($AQ$5:$AQ$335=1)*ISNUMBER($AO$5:$AO$335))+SUMPRODUCT(($B$5:$B$335=$B26)*($AQ$5:$AQ$335=1)*($AO$5:$AO$335="")*(ROW($AO$5:$AO$335)<ROW())))) | AS26: Aproxima segurança pública; deve ser lido com qualidade do registo criminal. | Nome local/API: Intentional homicides (per 100,000 people)
A27: GOV023 | B27: 1. Governança e Estado de Direito | C27: Segurança e paz | D27: Mortes relacionadas com conflito armado | E27: número | F27: - | G27: 0 | H27: 5000 | I27: 0 | J27: 1 | K27: Banco Mundial/WDI | L27: VC.BTL.DETH | M27: Banco Mundial — WDI | N27: 0 | O27: GOV023 | P27: Média | R27: 25 | S27: 25 | U27: 25 | V27: 21 | X27: 20 | Z27: 25 | AB27: =COUNT(Q27:AA27) -> 6 | AC27: =AB27/11 -> 0.54545455 | AD27: =IFERROR(INDEX($Q$4:$AA$4,MATCH(TRUE,INDEX(ISNUMBER(Q27:AA27),0),0)),"") -> 2016 | AE27: =IFERROR(LOOKUP(2,1/ISNUMBER(Q27:AA27),$Q$4:$AA$4),"") -> 2024 | AF27: =IF(AB27=0,"",AB27/(AE27-AD27+1)) -> 0.66666667 | AG27: =IF(AB27=0,"",'01_Criterios'!$C$8-AE27) -> 1 | AH27: =IF(P27="Em uso",100,IF(P27="Alta",85,IF(P27="Média",55,30))) -> 55 | AI27: =ROUND(100*AC27,1) -> 54.5 | AJ27: =IF(AB27=0,0,ROUND(MAX(0,100*AF27-10*AG27),1)) -> 56.7 | AK27: =ROUND(('01_Criterios'!$C$19*AH27+'01_Criterios'!$C$20*AI27+'01_Criterios'!$C$21*AJ27)/('01_Criterios'!$C$19+'01_Criterios'!$C$20+'01_Criterios'!$C$21)+N27*'01_Criterios'!$C$22,1) -> 55.3 | AL27: =IF(AND(AB27>=3,AC27>='01_Criterios'!$C$11,N(AE27)>='01_Criterios'!$C$12,OR(F27="+",F27="-"),ISNUMBER(G27),ISNUMBER(H27)),1,0) -> 0 | AM27: =IF(AL27=1,"",TRIM(IF(AB27=0,"sem dados no período; ",IF(AB27<3,"série demasiado curta; ",""))&IF(AND(AB27>0,AC27<'01_Criterios'!$C$11),"cobertura insuficiente; ","")&IF(AND(AB27>0,N(AE27)<'01_Criterios'!$C$12),"desactualizado; ","")&IF(AND(F27<>"+",F27<>"-"),"sentido ambíguo; ","")&IF(OR(NOT(ISNUMBER(G27)),NOT(ISNUMBER(H27))),"sem limites min/max; ",""))) -> cobertura insuficiente; | AN27: =IF(OR(AL27=0,$AP27="Excluir"),0,IF(SUMPRODUCT(($O$5:$O$335=$O27)*($AL$5:$AL$335=1)*($AP$5:$AP$335<>"Excluir")*(($AK$5:$AK$335>$AK27)+(($AK$5:$AK$335=$AK27)*(ROW($O$5:$O$335)<ROW()))))=0,1,0)) -> 0 | AO27: =IF(AN27=0,"",1+SUMPRODUCT(($B$5:$B$335=$B27)*($AN$5:$AN$335=1)*(($AK$5:$AK$335>$AK27)+(($AK$5:$AK$335=$AK27)*(ROW($B$5:$B$335)<ROW()))))) | AP27: Auto | AQ27: =IF(INDEX('01_Criterios'!$C$26:$C$36,MATCH($B27,'01_Criterios'!$B$26:$B$36,0))<>1,0,IF($AP27="Excluir",0,IF($AP27="Incluir",IF(AND(OR($F27="+",$F27="-"),ISNUMBER($G27),ISNUMBER($H27),COUNT($Q27:$AA27)>0),1,0),IF('01_Criterios'!$C$18="Automática",IF(AND($AN27=1,$AO27<>"",$AO27<=INDEX('01_Criterios'!$E$26:$E$36,MATCH($B27,'01_Criterios'!$B$26:$B$36,0))),1,0),0)))) -> 0 | AR27: =IF(AQ27=0,"",IF($AO27<>"",1+SUMPRODUCT(($B$5:$B$335=$B27)*($AQ$5:$AQ$335=1)*($AO$5:$AO$335<$AO27)),1+SUMPRODUCT(($B$5:$B$335=$B27)*($AQ$5:$AQ$335=1)*ISNUMBER($AO$5:$AO$335))+SUMPRODUCT(($B$5:$B$335=$B27)*($AQ$5:$AQ$335=1)*($AO$5:$AO$335="")*(ROW($AO$5:$AO$335)<ROW())))) | AS27: Inclui risco de estabilidade e segurança humana. | Nome local/API: Battle-related deaths (number of people)
A28: GOV024 | B28: 1. Governança e Estado de Direito | C28: Governança africana | D28: IIAG - Accountability and Transparency | E28: 0-100 | F28: + | G28: 0 | H28: 100 | I28: 60 | J28: 1 | K28: Mo Ibrahim Foundation | L28: IIAG_PARTIC | M28: Mo Ibrahim Foundation | N28: 0 | O28: GOV024 | P28: Média | Y28: 45.8 | AB28: =COUNT(Q28:AA28) -> 1 | AC28: =AB28/11 -> 0.090909091 | AD28: =IFERROR(INDEX($Q$4:$AA$4,MATCH(TRUE,INDEX(ISNUMBER(Q28:AA28),0),0)),"") -> 2023 | AE28: =IFERROR(LOOKUP(2,1/ISNUMBER(Q28:AA28),$Q$4:$AA$4),"") -> 2023 | AF28: =IF(AB28=0,"",AB28/(AE28-AD28+1)) -> 1 | AG28: =IF(AB28=0,"",'01_Criterios'!$C$8-AE28) -> 2 | AH28: =IF(P28="Em uso",100,IF(P28="Alta",85,IF(P28="Média",55,30))) -> 55 | AI28: =ROUND(100*AC28,1) -> 9.1 | AJ28: =IF(AB28=0,0,ROUND(MAX(0,100*AF28-10*AG28),1)) -> 80 | AK28: =ROUND(('01_Criterios'!$C$19*AH28+'01_Criterios'!$C$20*AI28+'01_Criterios'!$C$21*AJ28)/('01_Criterios'!$C$19+'01_Criterios'!$C$20+'01_Criterios'!$C$21)+N28*'01_Criterios'!$C$22,1) -> 45.2 | AL28: =IF(AND(AB28>=3,AC28>='01_Criterios'!$C$11,N(AE28)>='01_Criterios'!$C$12,OR(F28="+",F28="-"),ISNUMBER(G28),ISNUMBER(H28)),1,0) -> 0 | AM28: =IF(AL28=1,"",TRIM(IF(AB28=0,"sem dados no período; ",IF(AB28<3,"série demasiado curta; ",""))&IF(AND(AB28>0,AC28<'01_Criterios'!$C$11),"cobertura insuficiente; ","")&IF(AND(AB28>0,N(AE28)<'01_Criterios'!$C$12),"desactualizado; ","")&IF(AND(F28<>"+",F28<>"-"),"sentido ambíguo; ","")&IF(OR(NOT(ISNUMBER(G28)),NOT(ISNUMBER(H28))),"sem limites min/max; ",""))) -> série demasiado curta; cobertura insuficiente; | AN28: =IF(OR(AL28=0,$AP28="Excluir"),0,IF(SUMPRODUCT(($O$5:$O$335=$O28)*($AL$5:$AL$335=1)*($AP$5:$AP$335<>"Excluir")*(($AK$5:$AK$335>$AK28)+(($AK$5:$AK$335=$AK28)*(ROW($O$5:$O$335)<ROW()))))=0,1,0)) -> 0 | AO28: =IF(AN28=0,"",1+SUMPRODUCT(($B$5:$B$335=$B28)*($AN$5:$AN$335=1)*(($AK$5:$AK$335>$AK28)+(($AK$5:$AK$335=$AK28)*(ROW($B$5:$B$335)<ROW()))))) | AP28: Auto | AQ28: =IF(INDEX('01_Criterios'!$C$26:$C$36,MATCH($B28,'01_Criterios'!$B$26:$B$36,0))<>1,0,IF($AP28="Excluir",0,IF($AP28="Incluir",IF(AND(OR($F28="+",$F28="-"),ISNUMBER($G28),ISNUMBER($H28),COUNT($Q28:$AA28)>0),1,0),IF('01_Criterios'!$C$18="Automática",IF(AND($AN28=1,$AO28<>"",$AO28<=INDEX('01_Criterios'!$E$26:$E$36,MATCH($B28,'01_Criterios'!$B$26:$B$36,0))),1,0),0)))) -> 0 | AR28: =IF(AQ28=0,"",IF($AO28<>"",1+SUMPRODUCT(($B$5:$B$335=$B28)*($AQ$5:$AQ$335=1)*($AO$5:$AO$335<$AO28)),1+SUMPRODUCT(($B$5:$B$335=$B28)*($AQ$5:$AQ$335=1)*ISNUMBER($AO$5:$AO$335))+SUMPRODUCT(($B$5:$B$335=$B28)*($AQ$5:$AQ$335=1)*($AO$5:$AO$335="")*(ROW($AO$5:$AO$335)<ROW())))) | AS28: Benchmark africano para validação regional do capítulo de governação. | IIAG 2024 scorecard/perfil; categoria Participation, Rights & Inclusion (proxy de Accountability & Transparency = 31,6 em 2023).
A29: GOV025 | B29: 1. Governança e Estado de Direito | C29: Governança africana | D29: IIAG - Security and Rule of Law | E29: 0-100 | F29: + | G29: 0 | H29: 100 | I29: 60 | J29: 1 | K29: Mo Ibrahim Foundation | L29: IIAG_SECRULE | M29: Mo Ibrahim Foundation | N29: 0 | O29: G_IIAG_SECRULE | P29: Média | Y29: 44.2 | AB29: =COUNT(Q29:AA29) -> 1 | AC29: =AB29/11 -> 0.090909091 | AD29: =IFERROR(INDEX($Q$4:$AA$4,MATCH(TRUE,INDEX(ISNUMBER(Q29:AA29),0),0)),"") -> 2023 | AE29: =IFERROR(LOOKUP(2,1/ISNUMBER(Q29:AA29),$Q$4:$AA$4),"") -> 2023 | AF29: =IF(AB29=0,"",AB29/(AE29-AD29+1)) -> 1 | AG29: =IF(AB29=0,"",'01_Criterios'!$C$8-AE29) -> 2 | AH29: =IF(P29="Em uso",100,IF(P29="Alta",85,IF(P29="Média",55,30))) -> 55 | AI29: =ROUND(100*AC29,1) -> 9.1 | AJ29: =IF(AB29=0,0,ROUND(MAX(0,100*AF29-10*AG29),1)) -> 80 | AK29: =ROUND(('01_Criterios'!$C$19*AH29+'01_Criterios'!$C$20*AI29+'01_Criterios'!$C$21*AJ29)/('01_Criterios'!$C$19+'01_Criterios'!$C$20+'01_Criterios'!$C$21)+N29*'01_Criterios'!$C$22,1) -> 45.2 | AL29: =IF(AND(AB29>=3,AC29>='01_Criterios'!$C$11,N(AE29)>='01_Criterios'!$C$12,OR(F29="+",F29="-"),ISNUMBER(G29),ISNUMBER(H29)),1,0) -> 0 | AM29: =IF(AL29=1,"",TRIM(IF(AB29=0,"sem dados no período; ",IF(AB29<3,"série demasiado curta; ",""))&IF(AND(AB29>0,AC29<'01_Criterios'!$C$11),"cobertura insuficiente; ","")&IF(AND(AB29>0,N(AE29)<'01_Criterios'!$C$12),"desactualizado; ","")&IF(AND(F29<>"+",F29<>"-"),"sentido ambíguo; ","")&IF(OR(NOT(ISNUMBER(G29)),NOT(ISNUMBER(H29))),"sem limites min/max; ",""))) -> série demasiado curta; cobertura insuficiente; | AN29: =IF(OR(AL29=0,$AP29="Excluir"),0,IF(SUMPRODUCT(($O$5:$O$335=$O29)*($AL$5:$AL$335=1)*($AP$5:$AP$335<>"Excluir")*(($AK$5:$AK$335>$AK29)+(($AK$5:$AK$335=$AK29)*(ROW($O$5:$O$335)<ROW()))))=0,1,0)) -> 0 | AO29: =IF(AN29=0,"",1+SUMPRODUCT(($B$5:$B$335=$B29)*($AN$5:$AN$335=1)*(($AK$5:$AK$335>$AK29)+(($AK$5:$AK$335=$AK29)*(ROW($B$5:$B$335)<ROW()))))) | AP29: Auto | AQ29: =IF(INDEX('01_Criterios'!$C$26:$C$36,MATCH($B29,'01_Criterios'!$B$26:$B$36,0))<>1,0,IF($AP29="Excluir",0,IF($AP29="Incluir",IF(AND(OR($F29="+",$F29="-"),ISNUMBER($G29),ISNUMBER($H29),COUNT($Q29:$AA29)>0),1,0),IF('01_Criterios'!$C$18="Automática",IF(AND($AN29=1,$AO29<>"",$AO29<=INDEX('01_Criterios'!$E$26:$E$36,MATCH($B29,'01_Criterios'!$B$26:$B$36,0))),1,0),0)))) -> 0 | AR29: =IF(AQ29=0,"",IF($AO29<>"",1+SUMPRODUCT(($B$5:$B$335=$B29)*($AQ$5:$AQ$335=1)*($AO$5:$AO$335<$AO29)),1+SUMPRODUCT(($B$5:$B$335=$B29)*($AQ$5:$AQ$335=1)*ISNUMBER($AO$5:$AO$335))+SUMPRODUCT(($B$5:$B$335=$B29)*($AQ$5:$AQ$335=1)*($AO$5:$AO$335="")*(ROW($AO$5:$AO$335)<ROW())))) | AS29: Benchmark africano alinhado com estado de direito e segurança. | IIAG 2024 scorecard/perfil; categoria Security & Rule of Law.
A30: GOV026 | B30: 1. Governança e Estado de Direito | C30: Estabilidade do Estado | D30: Fragile States Index - total | E30: 0-120 | F30: - | G30: 0 | H30: 120 | I30: 70 | J30: 1 | K30: Fund for Peace | L30: FSI | M30: Pesquisa externa (web) | N30: 0 | O30: GOV026 | P30: Média | V30: 90.7 | W30: 89 | X30: 88.1 | Y30: 86.9 | Z30: 85.6 | AB30: =COUNT(Q30:AA30) -> 5 | AC30: =AB30/11 -> 0.45454545 | AD30: =IFERROR(INDEX($Q$4:$AA$4,MATCH(TRUE,INDEX(ISNUMBER(Q30:AA30),0),0)),"") -> 2020 | AE30: =IFERROR(LOOKUP(2,1/ISNUMBER(Q30:AA30),$Q$4:$AA$4),"") -> 2024 | AF30: =IF(AB30=0,"",AB30/(AE30-AD30+1)) -> 1 | AG30: =IF(AB30=0,"",'01_Criterios'!$C$8-AE30) -> 1 | AH30: =IF(P30="Em uso",100,IF(P30="Alta",85,IF(P30="Média",55,30))) -> 55 | AI30: =ROUND(100*AC30,1) -> 45.5 | AJ30: =IF(AB30=0,0,ROUND(MAX(0,100*AF30-10*AG30),1)) -> 90 | AK30: =ROUND(('01_Criterios'!$C$19*AH30+'01_Criterios'!$C$20*AI30+'01_Criterios'!$C$21*AJ30)/('01_Criterios'!$C$19+'01_Criterios'!$C$20+'01_Criterios'!$C$21)+N30*'01_Criterios'!$C$22,1) -> 60.4 | AL30: =IF(AND(AB30>=3,AC30>='01_Criterios'!$C$11,N(AE30)>='01_Criterios'!$C$12,OR(F30="+",F30="-"),ISNUMBER(G30),ISNUMBER(H30)),1,0) -> 0 | AM30: =IF(AL30=1,"",TRIM(IF(AB30=0,"sem dados no período; ",IF(AB30<3,"série demasiado curta; ",""))&IF(AND(AB30>0,AC30<'01_Criterios'!$C$11),"cobertura insuficiente; ","")&IF(AND(AB30>0,N(AE30)<'01_Criterios'!$C$12),"desactualizado; ","")&IF(AND(F30<>"+",F30<>"-"),"sentido ambíguo; ","")&IF(OR(NOT(ISNUMBER(G30)),NOT(ISNUMBER(H30))),"sem limites min/max; ",""))) -> cobertura insuficiente; | AN30: =IF(OR(AL30=0,$AP30="Excluir"),0,IF(SUMPRODUCT(($O$5:$O$335=$O30)*($AL$5:$AL$335=1)*($AP$5:$AP$335<>"Excluir")*(($AK$5:$AK$335>$AK30)+(($AK$5:$AK$335=$AK30)*(ROW($O$5:$O$335)<ROW()))))=0,1,0)) -> 0 | AO30: =IF(AN30=0,"",1+SUMPRODUCT(($B$5:$B$335=$B30)*($AN$5:$AN$335=1)*(($AK$5:$AK$335>$AK30)+(($AK$5:$AK$335=$AK30)*(ROW($B$5:$B$335)<ROW()))))) | AP30: Auto | AQ30: =IF(INDEX('01_Criterios'!$C$26:$C$36,MATCH($B30,'01_Criterios'!$B$26:$B$36,0))<>1,0,IF($AP30="Excluir",0,IF($AP30="Incluir",IF(AND(OR($F30="+",$F30="-"),ISNUMBER($G30),ISNUMBER($H30),COUNT($Q30:$AA30)>0),1,0),IF('01_Criterios'!$C$18="Automática",IF(AND($AN30=1,$AO30<>"",$AO30<=INDEX('01_Criterios'!$E$26:$E$36,MATCH($B30,'01_Criterios'!$B$26:$B$36,0))),1,0),0)))) -> 0 | AR30: =IF(AQ30=0,"",IF($AO30<>"",1+SUMPRODUCT(($B$5:$B$335=$B30)*($AQ$5:$AQ$335=1)*($AO$5:$AO$335<$AO30)),1+SUMPRODUCT(($B$5:$B$335=$B30)*($AQ$5:$AQ$335=1)*ISNUMBER($AO$5:$AO$335))+SUMPRODUCT(($B$5:$B$335=$B30)*($AQ$5:$AQ$335=1)*($AO$5:$AO$335="")*(ROW($AO$5:$AO$335)<ROW())))) | AS30: Fund for Peace FSI 2020-2024 (total; menor=mais estável).
A31: GOV027 | B31: 1. Governança e Estado de Direito | C31: Liberdade e direitos | D31: World Press Freedom Index (RSF) | E31: 0-100 (maior=mais livre) | F31: + | G31: 0 | H31: 100 | I31: 65 | J31: 1 | K31: Repórteres Sem Fronteiras | L31: RSF | M31: Pesquisa externa (web) | N31: 0 | O31: GOV027 | P31: Média | X31: 57.17 | Y31: 48.3 | Z31: 52.44 | AB31: =COUNT(Q31:AA31) -> 3 | AC31: =AB31/11 -> 0.27272727 | AD31: =IFERROR(INDEX($Q$4:$AA$4,MATCH(TRUE,INDEX(ISNUMBER(Q31:AA31),0),0)),"") -> 2022 | AE31: =IFERROR(LOOKUP(2,1/ISNUMBER(Q31:AA31),$Q$4:$AA$4),"") -> 2024 | AF31: =IF(AB31=0,"",AB31/(AE31-AD31+1)) -> 1 | AG31: =IF(AB31=0,"",'01_Criterios'!$C$8-AE31) -> 1 | AH31: =IF(P31="Em uso",100,IF(P31="Alta",85,IF(P31="Média",55,30))) -> 55 | AI31: =ROUND(100*AC31,1) -> 27.3 | AJ31: =IF(AB31=0,0,ROUND(MAX(0,100*AF31-10*AG31),1)) -> 90 | AK31: =ROUND(('01_Criterios'!$C$19*AH31+'01_Criterios'!$C$20*AI31+'01_Criterios'!$C$21*AJ31)/('01_Criterios'!$C$19+'01_Criterios'!$C$20+'01_Criterios'!$C$21)+N31*'01_Criterios'!$C$22,1) -> 54.1 | AL31: =IF(AND(AB31>=3,AC31>='01_Criterios'!$C$11,N(AE31)>='01_Criterios'!$C$12,OR(F31="+",F31="-"),ISNUMBER(G31),ISNUMBER(H31)),1,0) -> 0 | AM31: =IF(AL31=1,"",TRIM(IF(AB31=0,"sem dados no período; ",IF(AB31<3,"série demasiado curta; ",""))&IF(AND(AB31>0,AC31<'01_Criterios'!$C$11),"cobertura insuficiente; ","")&IF(AND(AB31>0,N(AE31)<'01_Criterios'!$C$12),"desactualizado; ","")&IF(AND(F31<>"+",F31<>"-"),"sentido ambíguo; ","")&IF(OR(NOT(ISNUMBER(G31)),NOT(ISNUMBER(H31))),"sem limites min/max; ",""))) -> cobertura insuficiente; | AN31: =IF(OR(AL31=0,$AP31="Excluir"),0,IF(SUMPRODUCT(($O$5:$O$335=$O31)*($AL$5:$AL$335=1)*($AP$5:$AP$335<>"Excluir")*(($AK$5:$AK$335>$AK31)+(($AK$5:$AK$335=$AK31)*(ROW($O$5:$O$335)<ROW()))))=0,1,0)) -> 0 | AO31: =IF(AN31=0,"",1+SUMPRODUCT(($B$5:$B$335=$B31)*($AN$5:$AN$335=1)*(($AK$5:$AK$335>$AK31)+(($AK$5:$AK$335=$AK31)*(ROW($B$5:$B$335)<ROW()))))) | AP31: Auto | AQ31: =IF(INDEX('01_Criterios'!$C$26:$C$36,MATCH($B31,'01_Criterios'!$B$26:$B$36,0))<>1,0,IF($AP31="Excluir",0,IF($AP31="Incluir",IF(AND(OR($F31="+",$F31="-"),ISNUMBER($G31),ISNUMBER($H31),COUNT($Q31:$AA31)>0),1,0),IF('01_Criterios'!$C$18="Automática",IF(AND($AN31=1,$AO31<>"",$AO31<=INDEX('01_Criterios'!$E$26:$E$36,MATCH($B31,'01_Criterios'!$B$26:$B$36,0))),1,0),0)))) -> 0 | AR31: =IF(AQ31=0,"",IF($AO31<>"",1+SUMPRODUCT(($B$5:$B$335=$B31)*($AQ$5:$AQ$335=1)*($AO$5:$AO$335<$AO31)),1+SUMPRODUCT(($B$5:$B$335=$B31)*($AQ$5:$AQ$335=1)*ISNUMBER($AO$5:$AO$335))+SUMPRODUCT(($B$5:$B$335=$B31)*($AQ$5:$AQ$335=1)*($AO$5:$AO$335="")*(ROW($AO$5:$AO$335)<ROW())))) | AS31: RSF 2022-2024 (escala 0-100 maior=mais livre; metodologia mudou em 2022).
A32: GOV028 | B32: 1. Governança e Estado de Direito | C32: Benchmark de prosperidade | D32: Legatum Prosperity Index - score | E32: 0-100 | F32: + | G32: 0 | H32: 100 | I32: 50 | J32: 1 | K32: Legatum Institute | L32: LEGATUM_SCORE | M32: Pesquisa externa (web) | N32: 0 | O32: GOV028 | P32: Baixa | Y32: 40.5 | AB32: =COUNT(Q32:AA32) -> 1 | AC32: =AB32/11 -> 0.090909091 | AD32: =IFERROR(INDEX($Q$4:$AA$4,MATCH(TRUE,INDEX(ISNUMBER(Q32:AA32),0),0)),"") -> 2023 | AE32: =IFERROR(LOOKUP(2,1/ISNUMBER(Q32:AA32),$Q$4:$AA$4),"") -> 2023 | AF32: =IF(AB32=0,"",AB32/(AE32-AD32+1)) -> 1 | AG32: =IF(AB32=0,"",'01_Criterios'!$C$8-AE32) -> 2 | AH32: =IF(P32="Em uso",100,IF(P32="Alta",85,IF(P32="Média",55,30))) -> 30 | AI32: =ROUND(100*AC32,1) -> 9.1 | AJ32: =IF(AB32=0,0,ROUND(MAX(0,100*AF32-10*AG32),1)) -> 80 | AK32: =ROUND(('01_Criterios'!$C$19*AH32+'01_Criterios'!$C$20*AI32+'01_Criterios'!$C$21*AJ32)/('01_Criterios'!$C$19+'01_Criterios'!$C$20+'01_Criterios'!$C$21)+N32*'01_Criterios'!$C$22,1) -> 35.2 | AL32: =IF(AND(AB32>=3,AC32>='01_Criterios'!$C$11,N(AE32)>='01_Criterios'!$C$12,OR(F32="+",F32="-"),ISNUMBER(G32),ISNUMBER(H32)),1,0) -> 0 | AM32: =IF(AL32=1,"",TRIM(IF(AB32=0,"sem dados no período; ",IF(AB32<3,"série demasiado curta; ",""))&IF(AND(AB32>0,AC32<'01_Criterios'!$C$11),"cobertura insuficiente; ","")&IF(AND(AB32>0,N(AE32)<'01_Criterios'!$C$12),"desactualizado; ","")&IF(AND(F32<>"+",F32<>"-"),"sentido ambíguo; ","")&IF(OR(NOT(ISNUMBER(G32)),NOT(ISNUMBER(H32))),"sem limites min/max; ",""))) -> série demasiado curta; cobertura insuficiente; | AN32: =IF(OR(AL32=0,$AP32="Excluir"),0,IF(SUMPRODUCT(($O$5:$O$335=$O32)*($AL$5:$AL$335=1)*($AP$5:$AP$335<>"Excluir")*(($AK$5:$AK$335>$AK32)+(($AK$5:$AK$335=$AK32)*(ROW($O$5:$O$335)<ROW()))))=0,1,0)) -> 0 | AO32: =IF(AN32=0,"",1+SUMPRODUCT(($B$5:$B$335=$B32)*($AN$5:$AN$335=1)*(($AK$5:$AK$335>$AK32)+(($AK$5:$AK$335=$AK32)*(ROW($B$5:$B$335)<ROW()))))) | AP32: Auto | AQ32: =IF(INDEX('01_Criterios'!$C$26:$C$36,MATCH($B32,'01_Criterios'!$B$26:$B$36,0))<>1,0,IF($AP32="Excluir",0,IF($AP32="Incluir",IF(AND(OR($F32="+",$F32="-"),ISNUMBER($G32),ISNUMBER($H32),COUNT($Q32:$AA32)>0),1,0),IF('01_Criterios'!$C$18="Automática",IF(AND($AN32=1,$AO32<>"",$AO32<=INDEX('01_Criterios'!$E$26:$E$36,MATCH($B32,'01_Criterios'!$B$26:$B$36,0))),1,0),0)))) -> 0 | AR32: =IF(AQ32=0,"",IF($AO32<>"",1+SUMPRODUCT(($B$5:$B$335=$B32)*($AQ$5:$AQ$335=1)*($AO$5:$AO$335<$AO32)),1+SUMPRODUCT(($B$5:$B$335=$B32)*($AQ$5:$AQ$335=1)*ISNUMBER($AO$5:$AO$335))+SUMPRODUCT(($B$5:$B$335=$B32)*($AQ$5:$AQ$335=1)*($AO$5:$AO$335="")*(ROW($AO$5:$AO$335)<ROW())))) | AS32: Perfil oficial Legatum 2023 (score 40,5; 2013 = 40,3).
A33: MAC001 | B33: 2. Estabilidade Macroeconómica | C33: 2. Macroeconomia | D33: Taxa de Crescimento do PIB | E33: % | F33: + | G33: -10 | H33: 15 | I33: 5 | J33: 1 | K33: INE/MEP | L33: NY.GDP.MKTP.KD.ZG | M33: Banco Mundial — WDI | N33: 1 | O33: G_PIB_CRESC | P33: Em uso | Q33: 0.76317771 | R33: -0.23307695 | S33: -0.16468866 | T33: -0.50669754 | U33: -1.0552341 | V33: -5.2734913 | W33: 1.0905837 | X33: 3.5574921 | Y33: 1.3201659 | Z33: 4.9526786 | AA33: 3.1335354 | AB33: =COUNT(Q33:AA33) -> 11 | AC33: =AB33/11 -> 1 | AD33: =IFERROR(INDEX($Q$4:$AA$4,MATCH(TRUE,INDEX(ISNUMBER(Q33:AA33),0),0)),"") -> 2015 | AE33: =IFERROR(LOOKUP(2,1/ISNUMBER(Q33:AA33),$Q$4:$AA$4),"") -> 2025 | AF33: =IF(AB33=0,"",AB33/(AE33-AD33+1)) -> 1 | AG33: =IF(AB33=0,"",'01_Criterios'!$C$8-AE33) -> 0 | AH33: =IF(P33="Em uso",100,IF(P33="Alta",85,IF(P33="Média",55,30))) -> 100 | AI33: =ROUND(100*AC33,1) -> 100 | AJ33: =IF(AB33=0,0,ROUND(MAX(0,100*AF33-10*AG33),1)) -> 100 | AK33: =ROUND(('01_Criterios'!$C$19*AH33+'01_Criterios'!$C$20*AI33+'01_Criterios'!$C$21*AJ33)/('01_Criterios'!$C$19+'01_Criterios'!$C$20+'01_Criterios'!$C$21)+N33*'01_Criterios'!$C$22,1) -> 112 | AL33: =IF(AND(AB33>=3,AC33>='01_Criterios'!$C$11,N(AE33)>='01_Criterios'!$C$12,OR(F33="+",F33="-"),ISNUMBER(G33),ISNUMBER(H33)),1,0) -> 1 | AM33: =IF(AL33=1,"",TRIM(IF(AB33=0,"sem dados no período; ",IF(AB33<3,"série demasiado curta; ",""))&IF(AND(AB33>0,AC33<'01_Criterios'!$C$11),"cobertura insuficiente; ","")&IF(AND(AB33>0,N(AE33)<'01_Criterios'!$C$12),"desactualizado; ","")&IF(AND(F33<>"+",F33<>"-"),"sentido ambíguo; ","")&IF(OR(NOT(ISNUMBER(G33)),NOT(ISNUMBER(H33))),"sem limites min/max; ",""))) | AN33: =IF(OR(AL33=0,$AP33="Excluir"),0,IF(SUMPRODUCT(($O$5:$O$335=$O33)*($AL$5:$AL$335=1)*($AP$5:$AP$335<>"Excluir")*(($AK$5:$AK$335>$AK33)+(($AK$5:$AK$335=$AK33)*(ROW($O$5:$O$335)<ROW()))))=0,1,0)) -> 1 | AO33: =IF(AN33=0,"",1+SUMPRODUCT(($B$5:$B$335=$B33)*($AN$5:$AN$335=1)*(($AK$5:$AK$335>$AK33)+(($AK$5:$AK$335=$AK33)*(ROW($B$5:$B$335)<ROW()))))) -> 1 | AP33: Auto | AQ33: =IF(INDEX('01_Criterios'!$C$26:$C$36,MATCH($B33,'01_Criterios'!$B$26:$B$36,0))<>1,0,IF($AP33="Excluir",0,IF($AP33="Incluir",IF(AND(OR($F33="+",$F33="-"),ISNUMBER($G33),ISNUMBER($H33),COUNT($Q33:$AA33)>0),1,0),IF('01_Criterios'!$C$18="Automática",IF(AND($AN33=1,$AO33<>"",$AO33<=INDEX('01_Criterios'!$E$26:$E$36,MATCH($B33,'01_Criterios'!$B$26:$B$36,0))),1,0),0)))) -> 1 | AR33: =IF(AQ33=0,"",IF($AO33<>"",1+SUMPRODUCT(($B$5:$B$335=$B33)*($AQ$5:$AQ$335=1)*($AO$5:$AO$335<$AO33)),1+SUMPRODUCT(($B$5:$B$335=$B33)*($AQ$5:$AQ$335=1)*ISNUMBER($AO$5:$AO$335))+SUMPRODUCT(($B$5:$B$335=$B33)*($AQ$5:$AQ$335=1)*($AO$5:$AO$335="")*(ROW($AO$5:$AO$335)<ROW())))) -> 1 | AS33: Nome local/API: GDP growth (annual %) | 2025 revisto pelo WDI bulk 2026-06-30; valor INE CNT local usado como validação próxima (3,1299%).
A34: MAC002 | B34: 2. Estabilidade Macroeconómica | C34: 2. Macroeconomia | D34: PIB per Capita (USD) | E34: USD | F34: + | G34: 500 | H34: 15000 | I34: 5000 | J34: 1 | K34: INE/MEP | L34: NY.GDP.PCAP.CD | M34: Banco Mundial — WDI | N34: 1 | O34: G_PIBPC | P34: Em uso | Q34: 3641.7289 | R34: 2082.3734 | S34: 2832.15 | T34: 2891.8303 | U34: 2507.8681 | V34: 1749.1795 | W34: 2266.9683 | X34: 3598.5367 | Y34: 2885.5135 | Z34: 2720.819 | AA34: 3129.4766 | AB34: =COUNT(Q34:AA34) -> 11 | AC34: =AB34/11 -> 1 | AD34: =IFERROR(INDEX($Q$4:$AA$4,MATCH(TRUE,INDEX(ISNUMBER(Q34:AA34),0),0)),"") -> 2015 | AE34: =IFERROR(LOOKUP(2,1/ISNUMBER(Q34:AA34),$Q$4:$AA$4),"") -> 2025 | AF34: =IF(AB34=0,"",AB34/(AE34-AD34+1)) -> 1 | AG34: =IF(AB34=0,"",'01_Criterios'!$C$8-AE34) -> 0 | AH34: =IF(P34="Em uso",100,IF(P34="Alta",85,IF(P34="Média",55,30))) -> 100 | AI34: =ROUND(100*AC34,1) -> 100 | AJ34: =IF(AB34=0,0,ROUND(MAX(0,100*AF34-10*AG34),1)) -> 100 | AK34: =ROUND(('01_Criterios'!$C$19*AH34+'01_Criterios'!$C$20*AI34+'01_Criterios'!$C$21*AJ34)/('01_Criterios'!$C$19+'01_Criterios'!$C$20+'01_Criterios'!$C$21)+N34*'01_Criterios'!$C$22,1) -> 112 | AL34: =IF(AND(AB34>=3,AC34>='01_Criterios'!$C$11,N(AE34)>='01_Criterios'!$C$12,OR(F34="+",F34="-"),ISNUMBER(G34),ISNUMBER(H34)),1,0) -> 1 | AM34: =IF(AL34=1,"",TRIM(IF(AB34=0,"sem dados no período; ",IF(AB34<3,"série demasiado curta; ",""))&IF(AND(AB34>0,AC34<'01_Criterios'!$C$11),"cobertura insuficiente; ","")&IF(AND(AB34>0,N(AE34)<'01_Criterios'!$C$12),"desactualizado; ","")&IF(AND(F34<>"+",F34<>"-"),"sentido ambíguo; ","")&IF(OR(NOT(ISNUMBER(G34)),NOT(ISNUMBER(H34))),"sem limites min/max; ",""))) | AN34: =IF(OR(AL34=0,$AP34="Excluir"),0,IF(SUMPRODUCT(($O$5:$O$335=$O34)*($AL$5:$AL$335=1)*($AP$5:$AP$335<>"Excluir")*(($AK$5:$AK$335>$AK34)+(($AK$5:$AK$335=$AK34)*(ROW($O$5:$O$335)<ROW()))))=0,1,0)) -> 1 | AO34: =IF(AN34=0,"",1+SUMPRODUCT(($B$5:$B$335=$B34)*($AN$5:$AN$335=1)*(($AK$5:$AK$335>$AK34)+(($AK$5:$AK$335=$AK34)*(ROW($B$5:$B$335)<ROW()))))) -> 2 | AP34: Auto | AQ34: =IF(INDEX('01_Criterios'!$C$26:$C$36,MATCH($B34,'01_Criterios'!$B$26:$B$36,0))<>1,0,IF($AP34="Excluir",0,IF($AP34="Incluir",IF(AND(OR($F34="+",$F34="-"),ISNUMBER($G34),ISNUMBER($H34),COUNT($Q34:$AA34)>0),1,0),IF('01_Criterios'!$C$18="Automática",IF(AND($AN34=1,$AO34<>"",$AO34<=INDEX('01_Criterios'!$E$26:$E$36,MATCH($B34,'01_Criterios'!$B$26:$B$36,0))),1,0),0)))) -> 1 | AR34: =IF(AQ34=0,"",IF($AO34<>"",1+SUMPRODUCT(($B$5:$B$335=$B34)*($AQ$5:$AQ$335=1)*($AO$5:$AO$335<$AO34)),1+SUMPRODUCT(($B$5:$B$335=$B34)*($AQ$5:$AQ$335=1)*ISNUMBER($AO$5:$AO$335))+SUMPRODUCT(($B$5:$B$335=$B34)*($AQ$5:$AQ$335=1)*($AO$5:$AO$335="")*(ROW($AO$5:$AO$335)<ROW())))) -> 2 | AS34: Nome local/API: GDP per capita (current US$)
A35: MAC003 | B35: 2. Estabilidade Macroeconómica | C35: 2. Macroeconomia | D35: Inflação (IPC) | E35: % | F35: - | G35: 0 | H35: 50 | I35: 10 | J35: 1 | K35: INE/BNA | L35: FP.CPI.TOTL.ZG | M35: Banco Mundial — WDI | N35: 1 | O35: G_INFLACAO | P35: Em uso | Q35: 9.3559722 | R35: 30.694415 | S35: 29.84448 | T35: 19.628938 | U35: 17.080954 | V35: 22.271539 | W35: 25.754295 | X35: 21.35529 | Y35: 13.644102 | Z35: 28.240495 | AA35: 20.16202 | AB35: =COUNT(Q35:AA35) -> 11 | AC35: =AB35/11 -> 1 | AD35: =IFERROR(INDEX($Q$4:$AA$4,MATCH(TRUE,INDEX(ISNUMBER(Q35:AA35),0),0)),"") -> 2015 | AE35: =IFERROR(LOOKUP(2,1/ISNUMBER(Q35:AA35),$Q$4:$AA$4),"") -> 2025 | AF35: =IF(AB35=0,"",AB35/(AE35-AD35+1)) -> 1 | AG35: =IF(AB35=0,"",'01_Criterios'!$C$8-AE35) -> 0 | AH35: =IF(P35="Em uso",100,IF(P35="Alta",85,IF(P35="Média",55,30))) -> 100 | AI35: =ROUND(100*AC35,1) -> 100 | AJ35: =IF(AB35=0,0,ROUND(MAX(0,100*AF35-10*AG35),1)) -> 100 | AK35: =ROUND(('01_Criterios'!$C$19*AH35+'01_Criterios'!$C$20*AI35+'01_Criterios'!$C$21*AJ35)/('01_Criterios'!$C$19+'01_Criterios'!$C$20+'01_Criterios'!$C$21)+N35*'01_Criterios'!$C$22,1) -> 112 | AL35: =IF(AND(AB35>=3,AC35>='01_Criterios'!$C$11,N(AE35)>='01_Criterios'!$C$12,OR(F35="+",F35="-"),ISNUMBER(G35),ISNUMBER(H35)),1,0) -> 1 | AM35: =IF(AL35=1,"",TRIM(IF(AB35=0,"sem dados no período; ",IF(AB35<3,"série demasiado curta; ",""))&IF(AND(AB35>0,AC35<'01_Criterios'!$C$11),"cobertura insuficiente; ","")&IF(AND(AB35>0,N(AE35)<'01_Criterios'!$C$12),"desactualizado; ","")&IF(AND(F35<>"+",F35<>"-"),"sentido ambíguo; ","")&IF(OR(NOT(ISNUMBER(G35)),NOT(ISNUMBER(H35))),"sem limites min/max; ",""))) | AN35: =IF(OR(AL35=0,$AP35="Excluir"),0,IF(SUMPRODUCT(($O$5:$O$335=$O35)*($AL$5:$AL$335=1)*($AP$5:$AP$335<>"Excluir")*(($AK$5:$AK$335>$AK35)+(($AK$5:$AK$335=$AK35)*(ROW($O$5:$O$335)<ROW()))))=0,1,0)) -> 1 | AO35: =IF(AN35=0,"",1+SUMPRODUCT(($B$5:$B$335=$B35)*($AN$5:$AN$335=1)*(($AK$5:$AK$335>$AK35)+(($AK$5:$AK$335=$AK35)*(ROW($B$5:$B$335)<ROW()))))) -> 3 | AP35: Auto | AQ35: =IF(INDEX('01_Criterios'!$C$26:$C$36,MATCH($B35,'01_Criterios'!$B$26:$B$36,0))<>1,0,IF($AP35="Excluir",0,IF($AP35="Incluir",IF(AND(OR($F35="+",$F35="-"),ISNUMBER($G35),ISNUMBER($H35),COUNT($Q35:$AA35)>0),1,0),IF('01_Criterios'!$C$18="Automática",IF(AND($AN35=1,$AO35<>"",$AO35<=INDEX('01_Criterios'!$E$26:$E$36,MATCH($B35,'01_Criterios'!$B$26:$B$36,0))),1,0),0)))) -> 1 | AR35: =IF(AQ35=0,"",IF($AO35<>"",1+SUMPRODUCT(($B$5:$B$335=$B35)*($AQ$5:$AQ$335=1)*($AO$5:$AO$335<$AO35)),1+SUMPRODUCT(($B$5:$B$335=$B35)*($AQ$5:$AQ$335=1)*ISNUMBER($AO$5:$AO$335))+SUMPRODUCT(($B$5:$B$335=$B35)*($AQ$5:$AQ$335=1)*($AO$5:$AO$335="")*(ROW($AO$5:$AO$335)<ROW())))) -> 3 | AS35: Nome local/API: Inflation, consumer prices (annual %)
A36: MAC004 | B36: 2. Estabilidade Macroeconómica | C36: 2. Macroeconomia | D36: Dívida Pública (% do PIB) | E36: % | F36: - | G36: 0 | H36: 150 | I36: 60 | J36: 1 | K36: MINFIN | L36: GC.DOD.TOTL.GD.ZS | M36: Compilação interna BDA | N36: 1 | O36: G_DIVIDA_PUB | P36: Em uso | Q36: 50 | R36: 67 | S36: 60 | T36: 83 | U36: 101 | V36: 119 | W36: 74 | X36: 56 | Y36: 72 | Z36: 60 | AA36: 63 | AB36: =COUNT(Q36:AA36) -> 11 | AC36: =AB36/11 -> 1 | AD36: =IFERROR(INDEX($Q$4:$AA$4,MATCH(TRUE,INDEX(ISNUMBER(Q36:AA36),0),0)),"") -> 2015 | AE36: =IFERROR(LOOKUP(2,1/ISNUMBER(Q36:AA36),$Q$4:$AA$4),"") -> 2025 | AF36: =IF(AB36=0,"",AB36/(AE36-AD36+1)) -> 1 | AG36: =IF(AB36=0,"",'01_Criterios'!$C$8-AE36) -> 0 | AH36: =IF(P36="Em uso",100,IF(P36="Alta",85,IF(P36="Média",55,30))) -> 100 | AI36: =ROUND(100*AC36,1) -> 100 | AJ36: =IF(AB36=0,0,ROUND(MAX(0,100*AF36-10*AG36),1)) -> 100 | AK36: =ROUND(('01_Criterios'!$C$19*AH36+'01_Criterios'!$C$20*AI36+'01_Criterios'!$C$21*AJ36)/('01_Criterios'!$C$19+'01_Criterios'!$C$20+'01_Criterios'!$C$21)+N36*'01_Criterios'!$C$22,1) -> 112 | AL36: =IF(AND(AB36>=3,AC36>='01_Criterios'!$C$11,N(AE36)>='01_Criterios'!$C$12,OR(F36="+",F36="-"),ISNUMBER(G36),ISNUMBER(H36)),1,0) -> 1 | AM36: =IF(AL36=1,"",TRIM(IF(AB36=0,"sem dados no período; ",IF(AB36<3,"série demasiado curta; ",""))&IF(AND(AB36>0,AC36<'01_Criterios'!$C$11),"cobertura insuficiente; ","")&IF(AND(AB36>0,N(AE36)<'01_Criterios'!$C$12),"desactualizado; ","")&IF(AND(F36<>"+",F36<>"-"),"sentido ambíguo; ","")&IF(OR(NOT(ISNUMBER(G36)),NOT(ISNUMBER(H36))),"sem limites min/max; ",""))) | AN36: =IF(OR(AL36=0,$AP36="Excluir"),0,IF(SUMPRODUCT(($O$5:$O$335=$O36)*($AL$5:$AL$335=1)*($AP$5:$AP$335<>"Excluir")*(($AK$5:$AK$335>$AK36)+(($AK$5:$AK$335=$AK36)*(ROW($O$5:$O$335)<ROW()))))=0,1,0)) -> 1 | AO36: =IF(AN36=0,"",1+SUMPRODUCT(($B$5:$B$335=$B36)*($AN$5:$AN$335=1)*(($AK$5:$AK$335>$AK36)+(($AK$5:$AK$335=$AK36)*(ROW($B$5:$B$335)<ROW()))))) -> 4 | AP36: Auto | AQ36: =IF(INDEX('01_Criterios'!$C$26:$C$36,MATCH($B36,'01_Criterios'!$B$26:$B$36,0))<>1,0,IF($AP36="Excluir",0,IF($AP36="Incluir",IF(AND(OR($F36="+",$F36="-"),ISNUMBER($G36),ISNUMBER($H36),COUNT($Q36:$AA36)>0),1,0),IF('01_Criterios'!$C$18="Automática",IF(AND($AN36=1,$AO36<>"",$AO36<=INDEX('01_Criterios'!$E$26:$E$36,MATCH($B36,'01_Criterios'!$B$26:$B$36,0))),1,0),0)))) -> 1 | AR36: =IF(AQ36=0,"",IF($AO36<>"",1+SUMPRODUCT(($B$5:$B$335=$B36)*($AQ$5:$AQ$335=1)*($AO$5:$AO$335<$AO36)),1+SUMPRODUCT(($B$5:$B$335=$B36)*($AQ$5:$AQ$335=1)*ISNUMBER($AO$5:$AO$335))+SUMPRODUCT(($B$5:$B$335=$B36)*($AQ$5:$AQ$335=1)*($AO$5:$AO$335="")*(ROW($AO$5:$AO$335)<ROW())))) -> 4 | AS36: Indicador já incluído no modelo original.
A37: MAC005 | B37: 2. Estabilidade Macroeconómica | C37: 2. Macroeconomia | D37: Saldo Orçamental (% do PIB) | E37: % | F37: + | G37: -15 | H37: 10 | I37: 0 | J37: 1 | K37: MINFIN | L37: GC.BAL.CASH.GD.ZS | M37: Compilação interna BDA | N37: 1 | O37: G_SALDO_ORC | P37: Em uso | Q37: -2 | R37: -3 | S37: 1.5 | T37: -0.5 | U37: 0.5 | V37: -5 | W37: 1.5 | X37: 0.7 | Y37: -1.9 | Z37: -1.5 | AA37: -1.65 | AB37: =COUNT(Q37:AA37) -> 11 | AC37: =AB37/11 -> 1 | AD37: =IFERROR(INDEX($Q$4:$AA$4,MATCH(TRUE,INDEX(ISNUMBER(Q37:AA37),0),0)),"") -> 2015 | AE37: =IFERROR(LOOKUP(2,1/ISNUMBER(Q37:AA37),$Q$4:$AA$4),"") -> 2025 | AF37: =IF(AB37=0,"",AB37/(AE37-AD37+1)) -> 1 | AG37: =IF(AB37=0,"",'01_Criterios'!$C$8-AE37) -> 0 | AH37: =IF(P37="Em uso",100,IF(P37="Alta",85,IF(P37="Média",55,30))) -> 100 | AI37: =ROUND(100*AC37,1) -> 100 | AJ37: =IF(AB37=0,0,ROUND(MAX(0,100*AF37-10*AG37),1)) -> 100 | AK37: =ROUND(('01_Criterios'!$C$19*AH37+'01_Criterios'!$C$20*AI37+'01_Criterios'!$C$21*AJ37)/('01_Criterios'!$C$19+'01_Criterios'!$C$20+'01_Criterios'!$C$21)+N37*'01_Criterios'!$C$22,1) -> 112 | AL37: =IF(AND(AB37>=3,AC37>='01_Criterios'!$C$11,N(AE37)>='01_Criterios'!$C$12,OR(F37="+",F37="-"),ISNUMBER(G37),ISNUMBER(H37)),1,0) -> 1 | AM37: =IF(AL37=1,"",TRIM(IF(AB37=0,"sem dados no período; ",IF(AB37<3,"série demasiado curta; ",""))&IF(AND(AB37>0,AC37<'01_Criterios'!$C$11),"cobertura insuficiente; ","")&IF(AND(AB37>0,N(AE37)<'01_Criterios'!$C$12),"desactualizado; ","")&IF(AND(F37<>"+",F37<>"-"),"sentido ambíguo; ","")&IF(OR(NOT(ISNUMBER(G37)),NOT(ISNUMBER(H37))),"sem limites min/max; ",""))) | AN37: =IF(OR(AL37=0,$AP37="Excluir"),0,IF(SUMPRODUCT(($O$5:$O$335=$O37)*($AL$5:$AL$335=1)*($AP$5:$AP$335<>"Excluir")*(($AK$5:$AK$335>$AK37)+(($AK$5:$AK$335=$AK37)*(ROW($O$5:$O$335)<ROW()))))=0,1,0)) -> 1 | AO37: =IF(AN37=0,"",1+SUMPRODUCT(($B$5:$B$335=$B37)*($AN$5:$AN$335=1)*(($AK$5:$AK$335>$AK37)+(($AK$5:$AK$335=$AK37)*(ROW($B$5:$B$335)<ROW()))))) -> 5 | AP37: Auto | AQ37: =IF(INDEX('01_Criterios'!$C$26:$C$36,MATCH($B37,'01_Criterios'!$B$26:$B$36,0))<>1,0,IF($AP37="Excluir",0,IF($AP37="Incluir",IF(AND(OR($F37="+",$F37="-"),ISNUMBER($G37),ISNUMBER($H37),COUNT($Q37:$AA37)>0),1,0),IF('01_Criterios'!$C$18="Automática",IF(AND($AN37=1,$AO37<>"",$AO37<=INDEX('01_Criterios'!$E$26:$E$36,MATCH($B37,'01_Criterios'!$B$26:$B$36,0))),1,0),0)))) -> 1 | AR37: =IF(AQ37=0,"",IF($AO37<>"",1+SUMPRODUCT(($B$5:$B$335=$B37)*($AQ$5:$AQ$335=1)*($AO$5:$AO$335<$AO37)),1+SUMPRODUCT(($B$5:$B$335=$B37)*($AQ$5:$AQ$335=1)*ISNUMBER($AO$5:$AO$335))+SUMPRODUCT(($B$5:$B$335=$B37)*($AQ$5:$AQ$335=1)*($AO$5:$AO$335="")*(ROW($AO$5:$AO$335)<ROW())))) -> 5 | AS37: Indicador já incluído no modelo original.
A38: MAC006 | B38: 2. Estabilidade Macroeconómica | C38: 2. Macroeconomia | D38: IDE não-petrolífero (% PIB) | E38: % | F38: + | G38: 0 | H38: 10 | I38: 3 | J38: 1 | K38: AIPEX/BNA | M38: Compilação interna BDA | N38: 1 | O38: MAC006 | P38: Em uso | AB38: =COUNT(Q38:AA38) -> 0 | AC38: =AB38/11 -> 0 | AD38: =IFERROR(INDEX($Q$4:$AA$4,MATCH(TRUE,INDEX(ISNUMBER(Q38:AA38),0),0)),"") | AE38: =IFERROR(LOOKUP(2,1/ISNUMBER(Q38:AA38),$Q$4:$AA$4),"") | AF38: =IF(AB38=0,"",AB38/(AE38-AD38+1)) | AG38: =IF(AB38=0,"",'01_Criterios'!$C$8-AE38) | AH38: =IF(P38="Em uso",100,IF(P38="Alta",85,IF(P38="Média",55,30))) -> 100 | AI38: =ROUND(100*AC38,1) -> 0 | AJ38: =IF(AB38=0,0,ROUND(MAX(0,100*AF38-10*AG38),1)) -> 0 | AK38: =ROUND(('01_Criterios'!$C$19*AH38+'01_Criterios'!$C$20*AI38+'01_Criterios'!$C$21*AJ38)/('01_Criterios'!$C$19+'01_Criterios'!$C$20+'01_Criterios'!$C$21)+N38*'01_Criterios'!$C$22,1) -> 52 | AL38: =IF(AND(AB38>=3,AC38>='01_Criterios'!$C$11,N(AE38)>='01_Criterios'!$C$12,OR(F38="+",F38="-"),ISNUMBER(G38),ISNUMBER(H38)),1,0) -> 0 | AM38: =IF(AL38=1,"",TRIM(IF(AB38=0,"sem dados no período; ",IF(AB38<3,"série demasiado curta; ",""))&IF(AND(AB38>0,AC38<'01_Criterios'!$C$11),"cobertura insuficiente; ","")&IF(AND(AB38>0,N(AE38)<'01_Criterios'!$C$12),"desactualizado; ","")&IF(AND(F38<>"+",F38<>"-"),"sentido ambíguo; ","")&IF(OR(NOT(ISNUMBER(G38)),NOT(ISNUMBER(H38))),"sem limites min/max; ",""))) -> sem dados no período; | AN38: =IF(OR(AL38=0,$AP38="Excluir"),0,IF(SUMPRODUCT(($O$5:$O$335=$O38)*($AL$5:$AL$335=1)*($AP$5:$AP$335<>"Excluir")*(($AK$5:$AK$335>$AK38)+(($AK$5:$AK$335=$AK38)*(ROW($O$5:$O$335)<ROW()))))=0,1,0)) -> 0 | AO38: =IF(AN38=0,"",1+SUMPRODUCT(($B$5:$B$335=$B38)*($AN$5:$AN$335=1)*(($AK$5:$AK$335>$AK38)+(($AK$5:$AK$335=$AK38)*(ROW($B$5:$B$335)<ROW()))))) | AP38: Auto | AQ38: =IF(INDEX('01_Criterios'!$C$26:$C$36,MATCH($B38,'01_Criterios'!$B$26:$B$36,0))<>1,0,IF($AP38="Excluir",0,IF($AP38="Incluir",IF(AND(OR($F38="+",$F38="-"),ISNUMBER($G38),ISNUMBER($H38),COUNT($Q38:$AA38)>0),1,0),IF('01_Criterios'!$C$18="Automática",IF(AND($AN38=1,$AO38<>"",$AO38<=INDEX('01_Criterios'!$E$26:$E$36,MATCH($B38,'01_Criterios'!$B$26:$B$36,0))),1,0),0)))) -> 0 | AR38: =IF(AQ38=0,"",IF($AO38<>"",1+SUMPRODUCT(($B$5:$B$335=$B38)*($AQ$5:$AQ$335=1)*($AO$5:$AO$335<$AO38)),1+SUMPRODUCT(($B$5:$B$335=$B38)*($AQ$5:$AQ$335=1)*ISNUMBER($AO$5:$AO$335))+SUMPRODUCT(($B$5:$B$335=$B38)*($AQ$5:$AQ$335=1)*($AO$5:$AO$335="")*(ROW($AO$5:$AO$335)<ROW())))) | AS38: Indicador já incluído no modelo original.
A39: MAC007 | B39: 2. Estabilidade Macroeconómica | C39: 2. Macroeconomia | D39: Reservas Internacionais (meses) | E39: Meses | F39: + | G39: 0 | H39: 12 | I39: 6 | J39: 1 | K39: BNA | L39: FI.RES.TOTL.MO | M39: Banco Mundial — WDI | N39: 1 | O39: G_RESERVAS_MESES | P39: Em uso | Q39: 6.4820457 | R39: 9.0838712 | S39: 5.8181869 | T39: 5.4126402 | U39: 6.4250943 | V39: 8.0261477 | W39: 6.9491541 | X39: 4.3768329 | Y39: 5.0892711 | Z39: 5.5137491 | AA39: 5.3228023 | AB39: =COUNT(Q39:AA39) -> 11 | AC39: =AB39/11 -> 1 | AD39: =IFERROR(INDEX($Q$4:$AA$4,MATCH(TRUE,INDEX(ISNUMBER(Q39:AA39),0),0)),"") -> 2015 | AE39: =IFERROR(LOOKUP(2,1/ISNUMBER(Q39:AA39),$Q$4:$AA$4),"") -> 2025 | AF39: =IF(AB39=0,"",AB39/(AE39-AD39+1)) -> 1 | AG39: =IF(AB39=0,"",'01_Criterios'!$C$8-AE39) -> 0 | AH39: =IF(P39="Em uso",100,IF(P39="Alta",85,IF(P39="Média",55,30))) -> 100 | AI39: =ROUND(100*AC39,1) -> 100 | AJ39: =IF(AB39=0,0,ROUND(MAX(0,100*AF39-10*AG39),1)) -> 100 | AK39: =ROUND(('01_Criterios'!$C$19*AH39+'01_Criterios'!$C$20*AI39+'01_Criterios'!$C$21*AJ39)/('01_Criterios'!$C$19+'01_Criterios'!$C$20+'01_Criterios'!$C$21)+N39*'01_Criterios'!$C$22,1) -> 112 | AL39: =IF(AND(AB39>=3,AC39>='01_Criterios'!$C$11,N(AE39)>='01_Criterios'!$C$12,OR(F39="+",F39="-"),ISNUMBER(G39),ISNUMBER(H39)),1,0) -> 1 | AM39: =IF(AL39=1,"",TRIM(IF(AB39=0,"sem dados no período; ",IF(AB39<3,"série demasiado curta; ",""))&IF(AND(AB39>0,AC39<'01_Criterios'!$C$11),"cobertura insuficiente; ","")&IF(AND(AB39>0,N(AE39)<'01_Criterios'!$C$12),"desactualizado; ","")&IF(AND(F39<>"+",F39<>"-"),"sentido ambíguo; ","")&IF(OR(NOT(ISNUMBER(G39)),NOT(ISNUMBER(H39))),"sem limites min/max; ",""))) | AN39: =IF(OR(AL39=0,$AP39="Excluir"),0,IF(SUMPRODUCT(($O$5:$O$335=$O39)*($AL$5:$AL$335=1)*($AP$5:$AP$335<>"Excluir")*(($AK$5:$AK$335>$AK39)+(($AK$5:$AK$335=$AK39)*(ROW($O$5:$O$335)<ROW()))))=0,1,0)) -> 1 | AO39: =IF(AN39=0,"",1+SUMPRODUCT(($B$5:$B$335=$B39)*($AN$5:$AN$335=1)*(($AK$5:$AK$335>$AK39)+(($AK$5:$AK$335=$AK39)*(ROW($B$5:$B$335)<ROW()))))) -> 6 | AP39: Auto | AQ39: =IF(INDEX('01_Criterios'!$C$26:$C$36,MATCH($B39,'01_Criterios'!$B$26:$B$36,0))<>1,0,IF($AP39="Excluir",0,IF($AP39="Incluir",IF(AND(OR($F39="+",$F39="-"),ISNUMBER($G39),ISNUMBER($H39),COUNT($Q39:$AA39)>0),1,0),IF('01_Criterios'!$C$18="Automática",IF(AND($AN39=1,$AO39<>"",$AO39<=INDEX('01_Criterios'!$E$26:$E$36,MATCH($B39,'01_Criterios'!$B$26:$B$36,0))),1,0),0)))) -> 1 | AR39: =IF(AQ39=0,"",IF($AO39<>"",1+SUMPRODUCT(($B$5:$B$335=$B39)*($AQ$5:$AQ$335=1)*($AO$5:$AO$335<$AO39)),1+SUMPRODUCT(($B$5:$B$335=$B39)*($AQ$5:$AQ$335=1)*ISNUMBER($AO$5:$AO$335))+SUMPRODUCT(($B$5:$B$335=$B39)*($AQ$5:$AQ$335=1)*($AO$5:$AO$335="")*(ROW($AO$5:$AO$335)<ROW())))) -> 6 | AS39: Nome local/API: Total reserves in months of imports
A40: MAC014 | B40: 2. Estabilidade Macroeconómica | C40: 2. Macroeconomia | D40: Crescimento do PIB não petrolífero | E40: % | F40: + | G40: -10 | H40: 15 | I40: 5 | J40: 1 | K40: INE - Contas Nacionais Trimestrais | L40: INE_CNT_NONOIL_GROWTH | M40: Compilação interna BDA | N40: 1 | O40: MAC014 | P40: Alta | Q40: -3.6888 | R40: 0.9275 | S40: 3.9201 | T40: 3.1939 | U40: 1.2479 | V40: -4.7728 | W40: 5.3133 | X40: 3.1457 | Y40: 2.3972 | Z40: 5.3951 | AA40: 5.3793 | AB40: =COUNT(Q40:AA40) -> 11 | AC40: =AB40/11 -> 1 | AD40: =IFERROR(INDEX($Q$4:$AA$4,MATCH(TRUE,INDEX(ISNUMBER(Q40:AA40),0),0)),"") -> 2015 | AE40: =IFERROR(LOOKUP(2,1/ISNUMBER(Q40:AA40),$Q$4:$AA$4),"") -> 2025 | AF40: =IF(AB40=0,"",AB40/(AE40-AD40+1)) -> 1 | AG40: =IF(AB40=0,"",'01_Criterios'!$C$8-AE40) -> 0 | AH40: =IF(P40="Em uso",100,IF(P40="Alta",85,IF(P40="Média",55,30))) -> 85 | AI40: =ROUND(100*AC40,1) -> 100 | AJ40: =IF(AB40=0,0,ROUND(MAX(0,100*AF40-10*AG40),1)) -> 100 | AK40: =ROUND(('01_Criterios'!$C$19*AH40+'01_Criterios'!$C$20*AI40+'01_Criterios'!$C$21*AJ40)/('01_Criterios'!$C$19+'01_Criterios'!$C$20+'01_Criterios'!$C$21)+N40*'01_Criterios'!$C$22,1) -> 106 | AL40: =IF(AND(AB40>=3,AC40>='01_Criterios'!$C$11,N(AE40)>='01_Criterios'!$C$12,OR(F40="+",F40="-"),ISNUMBER(G40),ISNUMBER(H40)),1,0) -> 1 | AM40: =IF(AL40=1,"",TRIM(IF(AB40=0,"sem dados no período; ",IF(AB40<3,"série demasiado curta; ",""))&IF(AND(AB40>0,AC40<'01_Criterios'!$C$11),"cobertura insuficiente; ","")&IF(AND(AB40>0,N(AE40)<'01_Criterios'!$C$12),"desactualizado; ","")&IF(AND(F40<>"+",F40<>"-"),"sentido ambíguo; ","")&IF(OR(NOT(ISNUMBER(G40)),NOT(ISNUMBER(H40))),"sem limites min/max; ",""))) | AN40: =IF(OR(AL40=0,$AP40="Excluir"),0,IF(SUMPRODUCT(($O$5:$O$335=$O40)*($AL$5:$AL$335=1)*($AP$5:$AP$335<>"Excluir")*(($AK$5:$AK$335>$AK40)+(($AK$5:$AK$335=$AK40)*(ROW($O$5:$O$335)<ROW()))))=0,1,0)) -> 1 | AO40: =IF(AN40=0,"",1+SUMPRODUCT(($B$5:$B$335=$B40)*($AN$5:$AN$335=1)*(($AK$5:$AK$335>$AK40)+(($AK$5:$AK$335=$AK40)*(ROW($B$5:$B$335)<ROW()))))) -> 7 | AP40: Auto | AQ40: =IF(INDEX('01_Criterios'!$C$26:$C$36,MATCH($B40,'01_Criterios'!$B$26:$B$36,0))<>1,0,IF($AP40="Excluir",0,IF($AP40="Incluir",IF(AND(OR($F40="+",$F40="-"),ISNUMBER($G40),ISNUMBER($H40),COUNT($Q40:$AA40)>0),1,0),IF('01_Criterios'!$C$18="Automática",IF(AND($AN40=1,$AO40<>"",$AO40<=INDEX('01_Criterios'!$E$26:$E$36,MATCH($B40,'01_Criterios'!$B$26:$B$36,0))),1,0),0)))) -> 1 | AR40: =IF(AQ40=0,"",IF($AO40<>"",1+SUMPRODUCT(($B$5:$B$335=$B40)*($AQ$5:$AQ$335=1)*($AO$5:$AO$335<$AO40)),1+SUMPRODUCT(($B$5:$B$335=$B40)*($AQ$5:$AQ$335=1)*ISNUMBER($AO$5:$AO$335))+SUMPRODUCT(($B$5:$B$335=$B40)*($AQ$5:$AQ$335=1)*($AO$5:$AO$335="")*(ROW($AO$5:$AO$335)<ROW())))) -> 7 | AS40: Mais alinhado com a diversificação económica do que o PIB total. | Série 2015-2025 calculada por soma anual do PIB real total menos extração/refino de petróleo no Q5 das CNT.
A41: MAC026 | B41: 2. Estabilidade Macroeconómica | C41: Condições financeiras | D41: Taxa básica do BNA | E41: % | F41: +/- | G41: 0 | H41: 40 | I41: 10 | J41: 1 | K41: BNA — Taxas de Juro do Banco Central | L41: NAT_BNA_TXBASE | M41: BNA — Taxas de Juro do Banco Central | N41: 1 | O41: MAC026 | P41: Alta | Q41: 11 | R41: 16 | S41: 18 | T41: 16.5 | V41: 15.5 | W41: 20 | X41: 19.5 | Y41: 18 | Z41: 19.5 | AA41: 18.5 | AB41: =COUNT(Q41:AA41) -> 10 | AC41: =AB41/11 -> 0.90909091 | AD41: =IFERROR(INDEX($Q$4:$AA$4,MATCH(TRUE,INDEX(ISNUMBER(Q41:AA41),0),0)),"") -> 2015 | AE41: =IFERROR(LOOKUP(2,1/ISNUMBER(Q41:AA41),$Q$4:$AA$4),"") -> 2025 | AF41: =IF(AB41=0,"",AB41/(AE41-AD41+1)) -> 0.90909091 | AG41: =IF(AB41=0,"",'01_Criterios'!$C$8-AE41) -> 0 | AH41: =IF(P41="Em uso",100,IF(P41="Alta",85,IF(P41="Média",55,30))) -> 85 | AI41: =ROUND(100*AC41,1) -> 90.9 | AJ41: =IF(AB41=0,0,ROUND(MAX(0,100*AF41-10*AG41),1)) -> 90.9 | AK41: =ROUND(('01_Criterios'!$C$19*AH41+'01_Criterios'!$C$20*AI41+'01_Criterios'!$C$21*AJ41)/('01_Criterios'!$C$19+'01_Criterios'!$C$20+'01_Criterios'!$C$21)+N41*'01_Criterios'!$C$22,1) -> 100.5 | AL41: =IF(AND(AB41>=3,AC41>='01_Criterios'!$C$11,N(AE41)>='01_Criterios'!$C$12,OR(F41="+",F41="-"),ISNUMBER(G41),ISNUMBER(H41)),1,0) -> 0 | AM41: =IF(AL41=1,"",TRIM(IF(AB41=0,"sem dados no período; ",IF(AB41<3,"série demasiado curta; ",""))&IF(AND(AB41>0,AC41<'01_Criterios'!$C$11),"cobertura insuficiente; ","")&IF(AND(AB41>0,N(AE41)<'01_Criterios'!$C$12),"desactualizado; ","")&IF(AND(F41<>"+",F41<>"-"),"sentido ambíguo; ","")&IF(OR(NOT(ISNUMBER(G41)),NOT(ISNUMBER(H41))),"sem limites min/max; ",""))) -> sentido ambíguo; | AN41: =IF(OR(AL41=0,$AP41="Excluir"),0,IF(SUMPRODUCT(($O$5:$O$335=$O41)*($AL$5:$AL$335=1)*($AP$5:$AP$335<>"Excluir")*(($AK$5:$AK$335>$AK41)+(($AK$5:$AK$335=$AK41)*(ROW($O$5:$O$335)<ROW()))))=0,1,0)) -> 0 | AO41: =IF(AN41=0,"",1+SUMPRODUCT(($B$5:$B$335=$B41)*($AN$5:$AN$335=1)*(($AK$5:$AK$335>$AK41)+(($AK$5:$AK$335=$AK41)*(ROW($B$5:$B$335)<ROW()))))) | AP41: Auto | AQ41: =IF(INDEX('01_Criterios'!$C$26:$C$36,MATCH($B41,'01_Criterios'!$B$26:$B$36,0))<>1,0,IF($AP41="Excluir",0,IF($AP41="Incluir",IF(AND(OR($F41="+",$F41="-"),ISNUMBER($G41),ISNUMBER($H41),COUNT($Q41:$AA41)>0),1,0),IF('01_Criterios'!$C$18="Automática",IF(AND($AN41=1,$AO41<>"",$AO41<=INDEX('01_Criterios'!$E$26:$E$36,MATCH($B41,'01_Criterios'!$B$26:$B$36,0))),1,0),0)))) -> 0 | AR41: =IF(AQ41=0,"",IF($AO41<>"",1+SUMPRODUCT(($B$5:$B$335=$B41)*($AQ$5:$AQ$335=1)*($AO$5:$AO$335<$AO41)),1+SUMPRODUCT(($B$5:$B$335=$B41)*($AQ$5:$AQ$335=1)*ISNUMBER($AO$5:$AO$335))+SUMPRODUCT(($B$5:$B$335=$B41)*($AQ$5:$AQ$335=1)*($AO$5:$AO$335="")*(ROW($AO$5:$AO$335)<ROW())))) | AS41: Disponível nos ficheiros BNA de taxas de juro do banco central; requer harmonização mensal-anual. | BNA, Quadro I.D.1, "Taxa básica BNA"; valor do mês mais recente de cada ano.
A42: MAC027 | B42: 2. Estabilidade Macroeconómica | C42: Inflação | D42: Inflação homóloga nacional - BNA/INE | E42: % | F42: - | G42: 0 | H42: 50 | I42: 10 | J42: 1 | K42: BNA/INE — Preços | L42: NAT_BNA_INFL_NAC | M42: BNA/INE — Preços | N42: 1 | O42: G_INFLACAO | P42: Alta | R42: 41.12 | S42: 23.67 | T42: 18.6 | U42: 16.9 | V42: 25.1 | W42: 27.03 | X42: 13.86 | Y42: 20.01 | Z42: 27.5 | AA42: 15.7 | AB42: =COUNT(Q42:AA42) -> 10 | AC42: =AB42/11 -> 0.90909091 | AD42: =IFERROR(INDEX($Q$4:$AA$4,MATCH(TRUE,INDEX(ISNUMBER(Q42:AA42),0),0)),"") -> 2016 | AE42: =IFERROR(LOOKUP(2,1/ISNUMBER(Q42:AA42),$Q$4:$AA$4),"") -> 2025 | AF42: =IF(AB42=0,"",AB42/(AE42-AD42+1)) -> 1 | AG42: =IF(AB42=0,"",'01_Criterios'!$C$8-AE42) -> 0 | AH42: =IF(P42="Em uso",100,IF(P42="Alta",85,IF(P42="Média",55,30))) -> 85 | AI42: =ROUND(100*AC42,1) -> 90.9 | AJ42: =IF(AB42=0,0,ROUND(MAX(0,100*AF42-10*AG42),1)) -> 100 | AK42: =ROUND(('01_Criterios'!$C$19*AH42+'01_Criterios'!$C$20*AI42+'01_Criterios'!$C$21*AJ42)/('01_Criterios'!$C$19+'01_Criterios'!$C$20+'01_Criterios'!$C$21)+N42*'01_Criterios'!$C$22,1) -> 102.8 | AL42: =IF(AND(AB42>=3,AC42>='01_Criterios'!$C$11,N(AE42)>='01_Criterios'!$C$12,OR(F42="+",F42="-"),ISNUMBER(G42),ISNUMBER(H42)),1,0) -> 1 | AM42: =IF(AL42=1,"",TRIM(IF(AB42=0,"sem dados no período; ",IF(AB42<3,"série demasiado curta; ",""))&IF(AND(AB42>0,AC42<'01_Criterios'!$C$11),"cobertura insuficiente; ","")&IF(AND(AB42>0,N(AE42)<'01_Criterios'!$C$12),"desactualizado; ","")&IF(AND(F42<>"+",F42<>"-"),"sentido ambíguo; ","")&IF(OR(NOT(ISNUMBER(G42)),NOT(ISNUMBER(H42))),"sem limites min/max; ",""))) | AN42: =IF(OR(AL42=0,$AP42="Excluir"),0,IF(SUMPRODUCT(($O$5:$O$335=$O42)*($AL$5:$AL$335=1)*($AP$5:$AP$335<>"Excluir")*(($AK$5:$AK$335>$AK42)+(($AK$5:$AK$335=$AK42)*(ROW($O$5:$O$335)<ROW()))))=0,1,0)) -> 0 | AO42: =IF(AN42=0,"",1+SUMPRODUCT(($B$5:$B$335=$B42)*($AN$5:$AN$335=1)*(($AK$5:$AK$335>$AK42)+(($AK$5:$AK$335=$AK42)*(ROW($B$5:$B$335)<ROW()))))) | AP42: Auto | AQ42: =IF(INDEX('01_Criterios'!$C$26:$C$36,MATCH($B42,'01_Criterios'!$B$26:$B$36,0))<>1,0,IF($AP42="Excluir",0,IF($AP42="Incluir",IF(AND(OR($F42="+",$F42="-"),ISNUMBER($G42),ISNUMBER($H42),COUNT($Q42:$AA42)>0),1,0),IF('01_Criterios'!$C$18="Automática",IF(AND($AN42=1,$AO42<>"",$AO42<=INDEX('01_Criterios'!$E$26:$E$36,MATCH($B42,'01_Criterios'!$B$26:$B$36,0))),1,0),0)))) -> 0 | AR42: =IF(AQ42=0,"",IF($AO42<>"",1+SUMPRODUCT(($B$5:$B$335=$B42)*($AQ$5:$AQ$335=1)*($AO$5:$AO$335<$AO42)),1+SUMPRODUCT(($B$5:$B$335=$B42)*($AQ$5:$AQ$335=1)*ISNUMBER($AO$5:$AO$335))+SUMPRODUCT(($B$5:$B$335=$B42)*($AQ$5:$AQ$335=1)*($AO$5:$AO$335="")*(ROW($AO$5:$AO$335)<ROW())))) | AS42: Fonte BNA: Evolução Mensal da Taxa de Inflação. | Inflação homóloga (Nacional) em Dezembro de cada ano (variação acumulada anual).
A43: MAC028 | B43: 2. Estabilidade Macroeconómica | C43: Contas nacionais | D43: Taxa de crescimento real do PIB (INE) | E43: % | F43: + | G43: -10 | H43: 15 | I43: 5 | J43: 1 | K43: INE — Contas Nacionais | L43: NAT_INE_GDP_GROWTH | M43: INE — Contas Nacionais | N43: 1 | O43: G_PIB_CRESC | P43: Alta | Q43: 0.7632 | R43: -0.2331 | S43: -0.1647 | T43: -0.5067 | U43: -1.0552 | V43: -5.2735 | W43: 1.0906 | X43: 3.5575 | Y43: 1.3202 | Z43: 4.9527 | AA43: 3.1299 | AB43: =COUNT(Q43:AA43) -> 11 | AC43: =AB43/11 -> 1 | AD43: =IFERROR(INDEX($Q$4:$AA$4,MATCH(TRUE,INDEX(ISNUMBER(Q43:AA43),0),0)),"") -> 2015 | AE43: =IFERROR(LOOKUP(2,1/ISNUMBER(Q43:AA43),$Q$4:$AA$4),"") -> 2025 | AF43: =IF(AB43=0,"",AB43/(AE43-AD43+1)) -> 1 | AG43: =IF(AB43=0,"",'01_Criterios'!$C$8-AE43) -> 0 | AH43: =IF(P43="Em uso",100,IF(P43="Alta",85,IF(P43="Média",55,30))) -> 85 | AI43: =ROUND(100*AC43,1) -> 100 | AJ43: =IF(AB43=0,0,ROUND(MAX(0,100*AF43-10*AG43),1)) -> 100 | AK43: =ROUND(('01_Criterios'!$C$19*AH43+'01_Criterios'!$C$20*AI43+'01_Criterios'!$C$21*AJ43)/('01_Criterios'!$C$19+'01_Criterios'!$C$20+'01_Criterios'!$C$21)+N43*'01_Criterios'!$C$22,1) -> 106 | AL43: =IF(AND(AB43>=3,AC43>='01_Criterios'!$C$11,N(AE43)>='01_Criterios'!$C$12,OR(F43="+",F43="-"),ISNUMBER(G43),ISNUMBER(H43)),1,0) -> 1 | AM43: =IF(AL43=1,"",TRIM(IF(AB43=0,"sem dados no período; ",IF(AB43<3,"série demasiado curta; ",""))&IF(AND(AB43>0,AC43<'01_Criterios'!$C$11),"cobertura insuficiente; ","")&IF(AND(AB43>0,N(AE43)<'01_Criterios'!$C$12),"desactualizado; ","")&IF(AND(F43<>"+",F43<>"-"),"sentido ambíguo; ","")&IF(OR(NOT(ISNUMBER(G43)),NOT(ISNUMBER(H43))),"sem limites min/max; ",""))) | AN43: =IF(OR(AL43=0,$AP43="Excluir"),0,IF(SUMPRODUCT(($O$5:$O$335=$O43)*($AL$5:$AL$335=1)*($AP$5:$AP$335<>"Excluir")*(($AK$5:$AK$335>$AK43)+(($AK$5:$AK$335=$AK43)*(ROW($O$5:$O$335)<ROW()))))=0,1,0)) -> 0 | AO43: =IF(AN43=0,"",1+SUMPRODUCT(($B$5:$B$335=$B43)*($AN$5:$AN$335=1)*(($AK$5:$AK$335>$AK43)+(($AK$5:$AK$335=$AK43)*(ROW($B$5:$B$335)<ROW()))))) | AP43: Auto | AQ43: =IF(INDEX('01_Criterios'!$C$26:$C$36,MATCH($B43,'01_Criterios'!$B$26:$B$36,0))<>1,0,IF($AP43="Excluir",0,IF($AP43="Incluir",IF(AND(OR($F43="+",$F43="-"),ISNUMBER($G43),ISNUMBER($H43),COUNT($Q43:$AA43)>0),1,0),IF('01_Criterios'!$C$18="Automática",IF(AND($AN43=1,$AO43<>"",$AO43<=INDEX('01_Criterios'!$E$26:$E$36,MATCH($B43,'01_Criterios'!$B$26:$B$36,0))),1,0),0)))) -> 0 | AR43: =IF(AQ43=0,"",IF($AO43<>"",1+SUMPRODUCT(($B$5:$B$335=$B43)*($AQ$5:$AQ$335=1)*($AO$5:$AO$335<$AO43)),1+SUMPRODUCT(($B$5:$B$335=$B43)*($AQ$5:$AQ$335=1)*ISNUMBER($AO$5:$AO$335))+SUMPRODUCT(($B$5:$B$335=$B43)*($AQ$5:$AQ$335=1)*($AO$5:$AO$335="")*(ROW($AO$5:$AO$335)<ROW())))) | AS43: INE, Contas Nacionais Q1.1, variação real anual do PIB. | 2025 preenchido por agregação dos quatro trimestres INE CNT; reproduz a série anual de 2024.
A44: MAC029 | B44: 2. Estabilidade Macroeconómica | C44: Finanças públicas | D44: Dívida externa pública (stock, BNA) | E44: % PIB | F44: - | G44: 0 | H44: 150 | I44: 60 | J44: 1 | K44: BNA — Estatísticas Externas | L44: NAT_BNA_DEBTPUB_GDP | M44: BNA — Estatísticas Externas | N44: 1 | O44: G_DIV_EXTERNA | P44: Alta | Q44: 27.5616 | R44: 38.1173 | S44: 30.576 | T44: 40.6777 | U44: 51.9201 | V44: 75.791 | W44: 61.0302 | X44: 37.3462 | Y44: 43.9817 | Z44: 39.1088 | AA44: 38.2821 | AB44: =COUNT(Q44:AA44) -> 11 | AC44: =AB44/11 -> 1 | AD44: =IFERROR(INDEX($Q$4:$AA$4,MATCH(TRUE,INDEX(ISNUMBER(Q44:AA44),0),0)),"") -> 2015 | AE44: =IFERROR(LOOKUP(2,1/ISNUMBER(Q44:AA44),$Q$4:$AA$4),"") -> 2025 | AF44: =IF(AB44=0,"",AB44/(AE44-AD44+1)) -> 1 | AG44: =IF(AB44=0,"",'01_Criterios'!$C$8-AE44) -> 0 | AH44: =IF(P44="Em uso",100,IF(P44="Alta",85,IF(P44="Média",55,30))) -> 85 | AI44: =ROUND(100*AC44,1) -> 100 | AJ44: =IF(AB44=0,0,ROUND(MAX(0,100*AF44-10*AG44),1)) -> 100 | AK44: =ROUND(('01_Criterios'!$C$19*AH44+'01_Criterios'!$C$20*AI44+'01_Criterios'!$C$21*AJ44)/('01_Criterios'!$C$19+'01_Criterios'!$C$20+'01_Criterios'!$C$21)+N44*'01_Criterios'!$C$22,1) -> 106 | AL44: =IF(AND(AB44>=3,AC44>='01_Criterios'!$C$11,N(AE44)>='01_Criterios'!$C$12,OR(F44="+",F44="-"),ISNUMBER(G44),ISNUMBER(H44)),1,0) -> 1 | AM44: =IF(AL44=1,"",TRIM(IF(AB44=0,"sem dados no período; ",IF(AB44<3,"série demasiado curta; ",""))&IF(AND(AB44>0,AC44<'01_Criterios'!$C$11),"cobertura insuficiente; ","")&IF(AND(AB44>0,N(AE44)<'01_Criterios'!$C$12),"desactualizado; ","")&IF(AND(F44<>"+",F44<>"-"),"sentido ambíguo; ","")&IF(OR(NOT(ISNUMBER(G44)),NOT(ISNUMBER(H44))),"sem limites min/max; ",""))) | AN44: =IF(OR(AL44=0,$AP44="Excluir"),0,IF(SUMPRODUCT(($O$5:$O$335=$O44)*($AL$5:$AL$335=1)*($AP$5:$AP$335<>"Excluir")*(($AK$5:$AK$335>$AK44)+(($AK$5:$AK$335=$AK44)*(ROW($O$5:$O$335)<ROW()))))=0,1,0)) -> 1 | AO44: =IF(AN44=0,"",1+SUMPRODUCT(($B$5:$B$335=$B44)*($AN$5:$AN$335=1)*(($AK$5:$AK$335>$AK44)+(($AK$5:$AK$335=$AK44)*(ROW($B$5:$B$335)<ROW()))))) -> 8 | AP44: Auto | AQ44: =IF(INDEX('01_Criterios'!$C$26:$C$36,MATCH($B44,'01_Criterios'!$B$26:$B$36,0))<>1,0,IF($AP44="Excluir",0,IF($AP44="Incluir",IF(AND(OR($F44="+",$F44="-"),ISNUMBER($G44),ISNUMBER($H44),COUNT($Q44:$AA44)>0),1,0),IF('01_Criterios'!$C$18="Automática",IF(AND($AN44=1,$AO44<>"",$AO44<=INDEX('01_Criterios'!$E$26:$E$36,MATCH($B44,'01_Criterios'!$B$26:$B$36,0))),1,0),0)))) -> 0 | AR44: =IF(AQ44=0,"",IF($AO44<>"",1+SUMPRODUCT(($B$5:$B$335=$B44)*($AQ$5:$AQ$335=1)*($AO$5:$AO$335<$AO44)),1+SUMPRODUCT(($B$5:$B$335=$B44)*($AQ$5:$AQ$335=1)*ISNUMBER($AO$5:$AO$335))+SUMPRODUCT(($B$5:$B$335=$B44)*($AQ$5:$AQ$335=1)*($AO$5:$AO$335="")*(ROW($AO$5:$AO$335)<ROW())))) | AS44: BNA, Principais Indicadores Externos 1990-2025, linha "Dívida Externa Pública (stock)".
A45: MAC031 | B45: 2. Estabilidade Macroeconómica | C45: Poupança e investimento | D45: Taxa de investimento (FBCF/PIB, INE) | E45: % PIB | F45: + | G45: 0 | H45: 60 | I45: 25 | J45: 1 | K45: INE — Contas Nacionais | L45: NAT_INE_INVRATE | M45: INE — Contas Nacionais | N45: 1 | O45: G_INVESTIMENTO | P45: Alta | Q45: 29.0721 | R45: 29.6348 | S45: 28.7057 | T45: 23.8941 | U45: 24.4514 | V45: 19.6657 | W45: 16.2194 | X45: 14.4654 | Y45: 12.4212 | Z45: 10.6228 | AB45: =COUNT(Q45:AA45) -> 10 | AC45: =AB45/11 -> 0.90909091 | AD45: =IFERROR(INDEX($Q$4:$AA$4,MATCH(TRUE,INDEX(ISNUMBER(Q45:AA45),0),0)),"") -> 2015 | AE45: =IFERROR(LOOKUP(2,1/ISNUMBER(Q45:AA45),$Q$4:$AA$4),"") -> 2024 | AF45: =IF(AB45=0,"",AB45/(AE45-AD45+1)) -> 1 | AG45: =IF(AB45=0,"",'01_Criterios'!$C$8-AE45) -> 1 | AH45: =IF(P45="Em uso",100,IF(P45="Alta",85,IF(P45="Média",55,30))) -> 85 | AI45: =ROUND(100*AC45,1) -> 90.9 | AJ45: =IF(AB45=0,0,ROUND(MAX(0,100*AF45-10*AG45),1)) -> 90 | AK45: =ROUND(('01_Criterios'!$C$19*AH45+'01_Criterios'!$C$20*AI45+'01_Criterios'!$C$21*AJ45)/('01_Criterios'!$C$19+'01_Criterios'!$C$20+'01_Criterios'!$C$21)+N45*'01_Criterios'!$C$22,1) -> 100.3 | AL45: =IF(AND(AB45>=3,AC45>='01_Criterios'!$C$11,N(AE45)>='01_Criterios'!$C$12,OR(F45="+",F45="-"),ISNUMBER(G45),ISNUMBER(H45)),1,0) -> 1 | AM45: =IF(AL45=1,"",TRIM(IF(AB45=0,"sem dados no período; ",IF(AB45<3,"série demasiado curta; ",""))&IF(AND(AB45>0,AC45<'01_Criterios'!$C$11),"cobertura insuficiente; ","")&IF(AND(AB45>0,N(AE45)<'01_Criterios'!$C$12),"desactualizado; ","")&IF(AND(F45<>"+",F45<>"-"),"sentido ambíguo; ","")&IF(OR(NOT(ISNUMBER(G45)),NOT(ISNUMBER(H45))),"sem limites min/max; ",""))) | AN45: =IF(OR(AL45=0,$AP45="Excluir"),0,IF(SUMPRODUCT(($O$5:$O$335=$O45)*($AL$5:$AL$335=1)*($AP$5:$AP$335<>"Excluir")*(($AK$5:$AK$335>$AK45)+(($AK$5:$AK$335=$AK45)*(ROW($O$5:$O$335)<ROW()))))=0,1,0)) -> 1 | AO45: =IF(AN45=0,"",1+SUMPRODUCT(($B$5:$B$335=$B45)*($AN$5:$AN$335=1)*(($AK$5:$AK$335>$AK45)+(($AK$5:$AK$335=$AK45)*(ROW($B$5:$B$335)<ROW()))))) -> 11 | AP45: Auto | AQ45: =IF(INDEX('01_Criterios'!$C$26:$C$36,MATCH($B45,'01_Criterios'!$B$26:$B$36,0))<>1,0,IF($AP45="Excluir",0,IF($AP45="Incluir",IF(AND(OR($F45="+",$F45="-"),ISNUMBER($G45),ISNUMBER($H45),COUNT($Q45:$AA45)>0),1,0),IF('01_Criterios'!$C$18="Automática",IF(AND($AN45=1,$AO45<>"",$AO45<=INDEX('01_Criterios'!$E$26:$E$36,MATCH($B45,'01_Criterios'!$B$26:$B$36,0))),1,0),0)))) -> 0 | AR45: =IF(AQ45=0,"",IF($AO45<>"",1+SUMPRODUCT(($B$5:$B$335=$B45)*($AQ$5:$AQ$335=1)*($AO$5:$AO$335<$AO45)),1+SUMPRODUCT(($B$5:$B$335=$B45)*($AQ$5:$AQ$335=1)*ISNUMBER($AO$5:$AO$335))+SUMPRODUCT(($B$5:$B$335=$B45)*($AQ$5:$AQ$335=1)*($AO$5:$AO$335="")*(ROW($AO$5:$AO$335)<ROW())))) | AS45: INE, Contas Nacionais Q5.1.
A46: MAC032 | B46: 2. Estabilidade Macroeconómica | C46: Sector externo | D46: Saldo da conta corrente (BNA) | E46: % PIB | F46: + | G46: -30 | H46: 30 | I46: 0 | J46: 1 | K46: BNA — Estatísticas Externas | L46: NAT_BNA_CAB_GDP | M46: BNA — Estatísticas Externas | N46: 1 | O46: G_CONTA_CORR | P46: Alta | Q46: -7.8045 | R46: -2.6493 | S46: -0.446 | T46: 6.4093 | U46: 5.3927 | V46: 1.3187 | W46: 10.0001 | X46: 8.4374 | Y46: 3.7076 | Z46: 5.2769 | AA46: 0.3783 | AB46: =COUNT(Q46:AA46) -> 11 | AC46: =AB46/11 -> 1 | AD46: =IFERROR(INDEX($Q$4:$AA$4,MATCH(TRUE,INDEX(ISNUMBER(Q46:AA46),0),0)),"") -> 2015 | AE46: =IFERROR(LOOKUP(2,1/ISNUMBER(Q46:AA46),$Q$4:$AA$4),"") -> 2025 | AF46: =IF(AB46=0,"",AB46/(AE46-AD46+1)) -> 1 | AG46: =IF(AB46=0,"",'01_Criterios'!$C$8-AE46) -> 0 | AH46: =IF(P46="Em uso",100,IF(P46="Alta",85,IF(P46="Média",55,30))) -> 85 | AI46: =ROUND(100*AC46,1) -> 100 | AJ46: =IF(AB46=0,0,ROUND(MAX(0,100*AF46-10*AG46),1)) -> 100 | AK46: =ROUND(('01_Criterios'!$C$19*AH46+'01_Criterios'!$C$20*AI46+'01_Criterios'!$C$21*AJ46)/('01_Criterios'!$C$19+'01_Criterios'!$C$20+'01_Criterios'!$C$21)+N46*'01_Criterios'!$C$22,1) -> 106 | AL46: =IF(AND(AB46>=3,AC46>='01_Criterios'!$C$11,N(AE46)>='01_Criterios'!$C$12,OR(F46="+",F46="-"),ISNUMBER(G46),ISNUMBER(H46)),1,0) -> 1 | AM46: =IF(AL46=1,"",TRIM(IF(AB46=0,"sem dados no período; ",IF(AB46<3,"série demasiado curta; ",""))&IF(AND(AB46>0,AC46<'01_Criterios'!$C$11),"cobertura insuficiente; ","")&IF(AND(AB46>0,N(AE46)<'01_Criterios'!$C$12),"desactualizado; ","")&IF(AND(F46<>"+",F46<>"-"),"sentido ambíguo; ","")&IF(OR(NOT(ISNUMBER(G46)),NOT(ISNUMBER(H46))),"sem limites min/max; ",""))) | AN46: =IF(OR(AL46=0,$AP46="Excluir"),0,IF(SUMPRODUCT(($O$5:$O$335=$O46)*($AL$5:$AL$335=1)*($AP$5:$AP$335<>"Excluir")*(($AK$5:$AK$335>$AK46)+(($AK$5:$AK$335=$AK46)*(ROW($O$5:$O$335)<ROW()))))=0,1,0)) -> 1 | AO46: =IF(AN46=0,"",1+SUMPRODUCT(($B$5:$B$335=$B46)*($AN$5:$AN$335=1)*(($AK$5:$AK$335>$AK46)+(($AK$5:$AK$335=$AK46)*(ROW($B$5:$B$335)<ROW()))))) -> 9 | AP46: Auto | AQ46: =IF(INDEX('01_Criterios'!$C$26:$C$36,MATCH($B46,'01_Criterios'!$B$26:$B$36,0))<>1,0,IF($AP46="Excluir",0,IF($AP46="Incluir",IF(AND(OR($F46="+",$F46="-"),ISNUMBER($G46),ISNUMBER($H46),COUNT($Q46:$AA46)>0),1,0),IF('01_Criterios'!$C$18="Automática",IF(AND($AN46=1,$AO46<>"",$AO46<=INDEX('01_Criterios'!$E$26:$E$36,MATCH($B46,'01_Criterios'!$B$26:$B$36,0))),1,0),0)))) -> 0 | AR46: =IF(AQ46=0,"",IF($AO46<>"",1+SUMPRODUCT(($B$5:$B$335=$B46)*($AQ$5:$AQ$335=1)*($AO$5:$AO$335<$AO46)),1+SUMPRODUCT(($B$5:$B$335=$B46)*($AQ$5:$AQ$335=1)*ISNUMBER($AO$5:$AO$335))+SUMPRODUCT(($B$5:$B$335=$B46)*($AQ$5:$AQ$335=1)*($AO$5:$AO$335="")*(ROW($AO$5:$AO$335)<ROW())))) | AS46: BNA, Principais Indicadores Externos 1990-2025, linha "Conta Corrente".
A47: MAC033 | B47: 2. Estabilidade Macroeconómica | C47: Sector externo | D47: Investimento Directo Estrangeiro líquido (BNA) | E47: % PIB | F47: + | G47: -10 | H47: 20 | I47: 5 | J47: 1 | K47: BNA — Estatísticas Externas | L47: NAT_BNA_FDI_GDP | M47: BNA — Estatísticas Externas | N47: 1 | O47: G_IDE | P47: Alta | Q47: 8.2149 | R47: -0.3885 | S47: -6.1654 | T47: -5.5947 | U47: -1.836 | V47: -2.9597 | W47: -3.9262 | X47: -4.7626 | Y47: -1.9074 | Z47: -0.9562 | AA47: 0.722 | AB47: =COUNT(Q47:AA47) -> 11 | AC47: =AB47/11 -> 1 | AD47: =IFERROR(INDEX($Q$4:$AA$4,MATCH(TRUE,INDEX(ISNUMBER(Q47:AA47),0),0)),"") -> 2015 | AE47: =IFERROR(LOOKUP(2,1/ISNUMBER(Q47:AA47),$Q$4:$AA$4),"") -> 2025 | AF47: =IF(AB47=0,"",AB47/(AE47-AD47+1)) -> 1 | AG47: =IF(AB47=0,"",'01_Criterios'!$C$8-AE47) -> 0 | AH47: =IF(P47="Em uso",100,IF(P47="Alta",85,IF(P47="Média",55,30))) -> 85 | AI47: =ROUND(100*AC47,1) -> 100 | AJ47: =IF(AB47=0,0,ROUND(MAX(0,100*AF47-10*AG47),1)) -> 100 | AK47: =ROUND(('01_Criterios'!$C$19*AH47+'01_Criterios'!$C$20*AI47+'01_Criterios'!$C$21*AJ47)/('01_Criterios'!$C$19+'01_Criterios'!$C$20+'01_Criterios'!$C$21)+N47*'01_Criterios'!$C$22,1) -> 106 | AL47: =IF(AND(AB47>=3,AC47>='01_Criterios'!$C$11,N(AE47)>='01_Criterios'!$C$12,OR(F47="+",F47="-"),ISNUMBER(G47),ISNUMBER(H47)),1,0) -> 1 | AM47: =IF(AL47=1,"",TRIM(IF(AB47=0,"sem dados no período; ",IF(AB47<3,"série demasiado curta; ",""))&IF(AND(AB47>0,AC47<'01_Criterios'!$C$11),"cobertura insuficiente; ","")&IF(AND(AB47>0,N(AE47)<'01_Criterios'!$C$12),"desactualizado; ","")&IF(AND(F47<>"+",F47<>"-"),"sentido ambíguo; ","")&IF(OR(NOT(ISNUMBER(G47)),NOT(ISNUMBER(H47))),"sem limites min/max; ",""))) | AN47: =IF(OR(AL47=0,$AP47="Excluir"),0,IF(SUMPRODUCT(($O$5:$O$335=$O47)*($AL$5:$AL$335=1)*($AP$5:$AP$335<>"Excluir")*(($AK$5:$AK$335>$AK47)+(($AK$5:$AK$335=$AK47)*(ROW($O$5:$O$335)<ROW()))))=0,1,0)) -> 1 | AO47: =IF(AN47=0,"",1+SUMPRODUCT(($B$5:$B$335=$B47)*($AN$5:$AN$335=1)*(($AK$5:$AK$335>$AK47)+(($AK$5:$AK$335=$AK47)*(ROW($B$5:$B$335)<ROW()))))) -> 10 | AP47: Auto | AQ47: =IF(INDEX('01_Criterios'!$C$26:$C$36,MATCH($B47,'01_Criterios'!$B$26:$B$36,0))<>1,0,IF($AP47="Excluir",0,IF($AP47="Incluir",IF(AND(OR($F47="+",$F47="-"),ISNUMBER($G47),ISNUMBER($H47),COUNT($Q47:$AA47)>0),1,0),IF('01_Criterios'!$C$18="Automática",IF(AND($AN47=1,$AO47<>"",$AO47<=INDEX('01_Criterios'!$E$26:$E$36,MATCH($B47,'01_Criterios'!$B$26:$B$36,0))),1,0),0)))) -> 0 | AR47: =IF(AQ47=0,"",IF($AO47<>"",1+SUMPRODUCT(($B$5:$B$335=$B47)*($AQ$5:$AQ$335=1)*($AO$5:$AO$335<$AO47)),1+SUMPRODUCT(($B$5:$B$335=$B47)*($AQ$5:$AQ$335=1)*ISNUMBER($AO$5:$AO$335))+SUMPRODUCT(($B$5:$B$335=$B47)*($AQ$5:$AQ$335=1)*($AO$5:$AO$335="")*(ROW($AO$5:$AO$335)<ROW())))) | AS47: BNA, Principais Indicadores Externos 1990-2025, linha "Investimento Directo Estrangeiro (líq)".
A48: MAC034 | B48: 2. Estabilidade Macroeconómica | C48: Sector externo | D48: Reservas internacionais em meses de importação (BNA) | E48: meses | F48: + | G48: 0 | H48: 12 | I48: 6 | J48: 1 | K48: BNA — Estatísticas Externas | L48: NAT_BNA_RES_MONTHS | M48: BNA — Estatísticas Externas | N48: 1 | O48: G_RESERVAS_MESES | P48: Alta | Q48: 7.7178 | R48: 11.3895 | S48: 7.741 | T48: 7.4957 | U48: 9.2621 | V48: 11.7883 | W48: 9.875 | X48: 6.1721 | Y48: 7.4603 | Z48: 8.3417 | AA48: 7.9385 | AB48: =COUNT(Q48:AA48) -> 11 | AC48: =AB48/11 -> 1 | AD48: =IFERROR(INDEX($Q$4:$AA$4,MATCH(TRUE,INDEX(ISNUMBER(Q48:AA48),0),0)),"") -> 2015 | AE48: =IFERROR(LOOKUP(2,1/ISNUMBER(Q48:AA48),$Q$4:$AA$4),"") -> 2025 | AF48: =IF(AB48=0,"",AB48/(AE48-AD48+1)) -> 1 | AG48: =IF(AB48=0,"",'01_Criterios'!$C$8-AE48) -> 0 | AH48: =IF(P48="Em uso",100,IF(P48="Alta",85,IF(P48="Média",55,30))) -> 85 | AI48: =ROUND(100*AC48,1) -> 100 | AJ48: =IF(AB48=0,0,ROUND(MAX(0,100*AF48-10*AG48),1)) -> 100 | AK48: =ROUND(('01_Criterios'!$C$19*AH48+'01_Criterios'!$C$20*AI48+'01_Criterios'!$C$21*AJ48)/('01_Criterios'!$C$19+'01_Criterios'!$C$20+'01_Criterios'!$C$21)+N48*'01_Criterios'!$C$22,1) -> 106 | AL48: =IF(AND(AB48>=3,AC48>='01_Criterios'!$C$11,N(AE48)>='01_Criterios'!$C$12,OR(F48="+",F48="-"),ISNUMBER(G48),ISNUMBER(H48)),1,0) -> 1 | AM48: =IF(AL48=1,"",TRIM(IF(AB48=0,"sem dados no período; ",IF(AB48<3,"série demasiado curta; ",""))&IF(AND(AB48>0,AC48<'01_Criterios'!$C$11),"cobertura insuficiente; ","")&IF(AND(AB48>0,N(AE48)<'01_Criterios'!$C$12),"desactualizado; ","")&IF(AND(F48<>"+",F48<>"-"),"sentido ambíguo; ","")&IF(OR(NOT(ISNUMBER(G48)),NOT(ISNUMBER(H48))),"sem limites min/max; ",""))) | AN48: =IF(OR(AL48=0,$AP48="Excluir"),0,IF(SUMPRODUCT(($O$5:$O$335=$O48)*($AL$5:$AL$335=1)*($AP$5:$AP$335<>"Excluir")*(($AK$5:$AK$335>$AK48)+(($AK$5:$AK$335=$AK48)*(ROW($O$5:$O$335)<ROW()))))=0,1,0)) -> 0 | AO48: =IF(AN48=0,"",1+SUMPRODUCT(($B$5:$B$335=$B48)*($AN$5:$AN$335=1)*(($AK$5:$AK$335>$AK48)+(($AK$5:$AK$335=$AK48)*(ROW($B$5:$B$335)<ROW()))))) | AP48: Auto | AQ48: =IF(INDEX('01_Criterios'!$C$26:$C$36,MATCH($B48,'01_Criterios'!$B$26:$B$36,0))<>1,0,IF($AP48="Excluir",0,IF($AP48="Incluir",IF(AND(OR($F48="+",$F48="-"),ISNUMBER($G48),ISNUMBER($H48),COUNT($Q48:$AA48)>0),1,0),IF('01_Criterios'!$C$18="Automática",IF(AND($AN48=1,$AO48<>"",$AO48<=INDEX('01_Criterios'!$E$26:$E$36,MATCH($B48,'01_Criterios'!$B$26:$B$36,0))),1,0),0)))) -> 0 | AR48: =IF(AQ48=0,"",IF($AO48<>"",1+SUMPRODUCT(($B$5:$B$335=$B48)*($AQ$5:$AQ$335=1)*($AO$5:$AO$335<$AO48)),1+SUMPRODUCT(($B$5:$B$335=$B48)*($AQ$5:$AQ$335=1)*ISNUMBER($AO$5:$AO$335))+SUMPRODUCT(($B$5:$B$335=$B48)*($AQ$5:$AQ$335=1)*($AO$5:$AO$335="")*(ROW($AO$5:$AO$335)<ROW())))) | AS48: BNA, Principais Indicadores Externos 1990-2025, linha "Reservas Internacionais / Importações de Bens e Serviç".
A49: MAC008 | B49: 2. Estabilidade Macroeconómica | C49: 2. Macroeconomia | D49: Saldo da conta corrente (% PIB) | E49: % | F49: + | G49: -30 | H49: 30 | I49: 0 | J49: 1 | K49: Banco Mundial/WDI | L49: BN.CAB.XOKA.GD.ZS | M49: Banco Mundial — WDI | N49: 0 | O49: G_CONTA_CORR | P49: Alta | Q49: -10.018075 | R49: -5.0768355 | S49: -0.73907522 | T49: 8.1791279 | U49: 6.327323 | V49: 1.4901513 | W49: 10.729472 | X49: 9.1729832 | Y49: 3.9465306 | Z49: 6.1212789 | AA49: 0.4388534 | AB49: =COUNT(Q49:AA49) -> 11 | AC49: =AB49/11 -> 1 | AD49: =IFERROR(INDEX($Q$4:$AA$4,MATCH(TRUE,INDEX(ISNUMBER(Q49:AA49),0),0)),"") -> 2015 | AE49: =IFERROR(LOOKUP(2,1/ISNUMBER(Q49:AA49),$Q$4:$AA$4),"") -> 2025 | AF49: =IF(AB49=0,"",AB49/(AE49-AD49+1)) -> 1 | AG49: =IF(AB49=0,"",'01_Criterios'!$C$8-AE49) -> 0 | AH49: =IF(P49="Em uso",100,IF(P49="Alta",85,IF(P49="Média",55,30))) -> 85 | AI49: =ROUND(100*AC49,1) -> 100 | AJ49: =IF(AB49=0,0,ROUND(MAX(0,100*AF49-10*AG49),1)) -> 100 | AK49: =ROUND(('01_Criterios'!$C$19*AH49+'01_Criterios'!$C$20*AI49+'01_Criterios'!$C$21*AJ49)/('01_Criterios'!$C$19+'01_Criterios'!$C$20+'01_Criterios'!$C$21)+N49*'01_Criterios'!$C$22,1) -> 94 | AL49: =IF(AND(AB49>=3,AC49>='01_Criterios'!$C$11,N(AE49)>='01_Criterios'!$C$12,OR(F49="+",F49="-"),ISNUMBER(G49),ISNUMBER(H49)),1,0) -> 1 | AM49: =IF(AL49=1,"",TRIM(IF(AB49=0,"sem dados no período; ",IF(AB49<3,"série demasiado curta; ",""))&IF(AND(AB49>0,AC49<'01_Criterios'!$C$11),"cobertura insuficiente; ","")&IF(AND(AB49>0,N(AE49)<'01_Criterios'!$C$12),"desactualizado; ","")&IF(AND(F49<>"+",F49<>"-"),"sentido ambíguo; ","")&IF(OR(NOT(ISNUMBER(G49)),NOT(ISNUMBER(H49))),"sem limites min/max; ",""))) | AN49: =IF(OR(AL49=0,$AP49="Excluir"),0,IF(SUMPRODUCT(($O$5:$O$335=$O49)*($AL$5:$AL$335=1)*($AP$5:$AP$335<>"Excluir")*(($AK$5:$AK$335>$AK49)+(($AK$5:$AK$335=$AK49)*(ROW($O$5:$O$335)<ROW()))))=0,1,0)) -> 0 | AO49: =IF(AN49=0,"",1+SUMPRODUCT(($B$5:$B$335=$B49)*($AN$5:$AN$335=1)*(($AK$5:$AK$335>$AK49)+(($AK$5:$AK$335=$AK49)*(ROW($B$5:$B$335)<ROW()))))) | AP49: Auto | AQ49: =IF(INDEX('01_Criterios'!$C$26:$C$36,MATCH($B49,'01_Criterios'!$B$26:$B$36,0))<>1,0,IF($AP49="Excluir",0,IF($AP49="Incluir",IF(AND(OR($F49="+",$F49="-"),ISNUMBER($G49),ISNUMBER($H49),COUNT($Q49:$AA49)>0),1,0),IF('01_Criterios'!$C$18="Automática",IF(AND($AN49=1,$AO49<>"",$AO49<=INDEX('01_Criterios'!$E$26:$E$36,MATCH($B49,'01_Criterios'!$B$26:$B$36,0))),1,0),0)))) -> 0 | AR49: =IF(AQ49=0,"",IF($AO49<>"",1+SUMPRODUCT(($B$5:$B$335=$B49)*($AQ$5:$AQ$335=1)*($AO$5:$AO$335<$AO49)),1+SUMPRODUCT(($B$5:$B$335=$B49)*($AQ$5:$AQ$335=1)*ISNUMBER($AO$5:$AO$335))+SUMPRODUCT(($B$5:$B$335=$B49)*($AQ$5:$AQ$335=1)*($AO$5:$AO$335="")*(ROW($AO$5:$AO$335)<ROW())))) | AS49: Acrescenta sustentabilidade externa, ausente do subíndice atual. | Nome local/API: Current account balance (% of GDP)
A50: MAC009 | B50: 2. Estabilidade Macroeconómica | C50: 2. Macroeconomia | D50: Receita fiscal (% PIB) | E50: % | F50: + | G50: 0 | H50: 40 | I50: 18 | J50: 1 | K50: Banco Mundial/WDI | L50: GC.TAX.TOTL.GD.ZS | M50: Banco Mundial — WDI | N50: 0 | O50: G_RECEITA | P50: Alta | Q50: 9.7095139 | R50: 8.4499371 | S50: 7.9376945 | T50: 9.8199148 | U50: 11.224981 | V50: 20.636979 | W50: 10.877739 | X50: 13.027509 | Y50: 8.9632544 | Z50: 7.5879731 | AB50: =COUNT(Q50:AA50) -> 10 | AC50: =AB50/11 -> 0.90909091 | AD50: =IFERROR(INDEX($Q$4:$AA$4,MATCH(TRUE,INDEX(ISNUMBER(Q50:AA50),0),0)),"") -> 2015 | AE50: =IFERROR(LOOKUP(2,1/ISNUMBER(Q50:AA50),$Q$4:$AA$4),"") -> 2024 | AF50: =IF(AB50=0,"",AB50/(AE50-AD50+1)) -> 1 | AG50: =IF(AB50=0,"",'01_Criterios'!$C$8-AE50) -> 1 | AH50: =IF(P50="Em uso",100,IF(P50="Alta",85,IF(P50="Média",55,30))) -> 85 | AI50: =ROUND(100*AC50,1) -> 90.9 | AJ50: =IF(AB50=0,0,ROUND(MAX(0,100*AF50-10*AG50),1)) -> 90 | AK50: =ROUND(('01_Criterios'!$C$19*AH50+'01_Criterios'!$C$20*AI50+'01_Criterios'!$C$21*AJ50)/('01_Criterios'!$C$19+'01_Criterios'!$C$20+'01_Criterios'!$C$21)+N50*'01_Criterios'!$C$22,1) -> 88.3 | AL50: =IF(AND(AB50>=3,AC50>='01_Criterios'!$C$11,N(AE50)>='01_Criterios'!$C$12,OR(F50="+",F50="-"),ISNUMBER(G50),ISNUMBER(H50)),1,0) -> 1 | AM50: =IF(AL50=1,"",TRIM(IF(AB50=0,"sem dados no período; ",IF(AB50<3,"série demasiado curta; ",""))&IF(AND(AB50>0,AC50<'01_Criterios'!$C$11),"cobertura insuficiente; ","")&IF(AND(AB50>0,N(AE50)<'01_Criterios'!$C$12),"desactualizado; ","")&IF(AND(F50<>"+",F50<>"-"),"sentido ambíguo; ","")&IF(OR(NOT(ISNUMBER(G50)),NOT(ISNUMBER(H50))),"sem limites min/max; ",""))) | AN50: =IF(OR(AL50=0,$AP50="Excluir"),0,IF(SUMPRODUCT(($O$5:$O$335=$O50)*($AL$5:$AL$335=1)*($AP$5:$AP$335<>"Excluir")*(($AK$5:$AK$335>$AK50)+(($AK$5:$AK$335=$AK50)*(ROW($O$5:$O$335)<ROW()))))=0,1,0)) -> 1 | AO50: =IF(AN50=0,"",1+SUMPRODUCT(($B$5:$B$335=$B50)*($AN$5:$AN$335=1)*(($AK$5:$AK$335>$AK50)+(($AK$5:$AK$335=$AK50)*(ROW($B$5:$B$335)<ROW()))))) -> 17 | AP50: Auto | AQ50: =IF(INDEX('01_Criterios'!$C$26:$C$36,MATCH($B50,'01_Criterios'!$B$26:$B$36,0))<>1,0,IF($AP50="Excluir",0,IF($AP50="Incluir",IF(AND(OR($F50="+",$F50="-"),ISNUMBER($G50),ISNUMBER($H50),COUNT($Q50:$AA50)>0),1,0),IF('01_Criterios'!$C$18="Automática",IF(AND($AN50=1,$AO50<>"",$AO50<=INDEX('01_Criterios'!$E$26:$E$36,MATCH($B50,'01_Criterios'!$B$26:$B$36,0))),1,0),0)))) -> 0 | AR50: =IF(AQ50=0,"",IF($AO50<>"",1+SUMPRODUCT(($B$5:$B$335=$B50)*($AQ$5:$AQ$335=1)*($AO$5:$AO$335<$AO50)),1+SUMPRODUCT(($B$5:$B$335=$B50)*($AQ$5:$AQ$335=1)*ISNUMBER($AO$5:$AO$335))+SUMPRODUCT(($B$5:$B$335=$B50)*($AQ$5:$AQ$335=1)*($AO$5:$AO$335="")*(ROW($AO$5:$AO$335)<ROW())))) | AS50: Capta capacidade interna de financiamento do Estado. | Nome local/API: Tax revenue (% of GDP)
A51: MAC010 | B51: 2. Estabilidade Macroeconómica | C51: 2. Macroeconomia | D51: IDE líquido total (% PIB) | E51: % | F51: + | G51: -10 | H51: 20 | I51: 5 | J51: 1 | K51: Banco Mundial/WDI | L51: BX.KLT.DINV.WD.GD.ZS | M51: Banco Mundial — WDI | N51: 0 | O51: G_IDE | P51: Alta | Q51: 9.7795155 | R51: -0.29540476 | S51: -8.6387132 | T51: -7.1333083 | U51: -5.0477722 | V51: -3.1898876 | W51: -5.5632323 | X51: -5.1457919 | Y51: -1.9988544 | Z51: -1.0765011 | AB51: =COUNT(Q51:AA51) -> 10 | AC51: =AB51/11 -> 0.90909091 | AD51: =IFERROR(INDEX($Q$4:$AA$4,MATCH(TRUE,INDEX(ISNUMBER(Q51:AA51),0),0)),"") -> 2015 | AE51: =IFERROR(LOOKUP(2,1/ISNUMBER(Q51:AA51),$Q$4:$AA$4),"") -> 2024 | AF51: =IF(AB51=0,"",AB51/(AE51-AD51+1)) -> 1 | AG51: =IF(AB51=0,"",'01_Criterios'!$C$8-AE51) -> 1 | AH51: =IF(P51="Em uso",100,IF(P51="Alta",85,IF(P51="Média",55,30))) -> 85 | AI51: =ROUND(100*AC51,1) -> 90.9 | AJ51: =IF(AB51=0,0,ROUND(MAX(0,100*AF51-10*AG51),1)) -> 90 | AK51: =ROUND(('01_Criterios'!$C$19*AH51+'01_Criterios'!$C$20*AI51+'01_Criterios'!$C$21*AJ51)/('01_Criterios'!$C$19+'01_Criterios'!$C$20+'01_Criterios'!$C$21)+N51*'01_Criterios'!$C$22,1) -> 88.3 | AL51: =IF(AND(AB51>=3,AC51>='01_Criterios'!$C$11,N(AE51)>='01_Criterios'!$C$12,OR(F51="+",F51="-"),ISNUMBER(G51),ISNUMBER(H51)),1,0) -> 1 | AM51: =IF(AL51=1,"",TRIM(IF(AB51=0,"sem dados no período; ",IF(AB51<3,"série demasiado curta; ",""))&IF(AND(AB51>0,AC51<'01_Criterios'!$C$11),"cobertura insuficiente; ","")&IF(AND(AB51>0,N(AE51)<'01_Criterios'!$C$12),"desactualizado; ","")&IF(AND(F51<>"+",F51<>"-"),"sentido ambíguo; ","")&IF(OR(NOT(ISNUMBER(G51)),NOT(ISNUMBER(H51))),"sem limites min/max; ",""))) | AN51: =IF(OR(AL51=0,$AP51="Excluir"),0,IF(SUMPRODUCT(($O$5:$O$335=$O51)*($AL$5:$AL$335=1)*($AP$5:$AP$335<>"Excluir")*(($AK$5:$AK$335>$AK51)+(($AK$5:$AK$335=$AK51)*(ROW($O$5:$O$335)<ROW()))))=0,1,0)) -> 0 | AO51: =IF(AN51=0,"",1+SUMPRODUCT(($B$5:$B$335=$B51)*($AN$5:$AN$335=1)*(($AK$5:$AK$335>$AK51)+(($AK$5:$AK$335=$AK51)*(ROW($B$5:$B$335)<ROW()))))) | AP51: Auto | AQ51: =IF(INDEX('01_Criterios'!$C$26:$C$36,MATCH($B51,'01_Criterios'!$B$26:$B$36,0))<>1,0,IF($AP51="Excluir",0,IF($AP51="Incluir",IF(AND(OR($F51="+",$F51="-"),ISNUMBER($G51),ISNUMBER($H51),COUNT($Q51:$AA51)>0),1,0),IF('01_Criterios'!$C$18="Automática",IF(AND($AN51=1,$AO51<>"",$AO51<=INDEX('01_Criterios'!$E$26:$E$36,MATCH($B51,'01_Criterios'!$B$26:$B$36,0))),1,0),0)))) -> 0 | AR51: =IF(AQ51=0,"",IF($AO51<>"",1+SUMPRODUCT(($B$5:$B$335=$B51)*($AQ$5:$AQ$335=1)*($AO$5:$AO$335<$AO51)),1+SUMPRODUCT(($B$5:$B$335=$B51)*($AQ$5:$AQ$335=1)*ISNUMBER($AO$5:$AO$335))+SUMPRODUCT(($B$5:$B$335=$B51)*($AQ$5:$AQ$335=1)*($AO$5:$AO$335="")*(ROW($AO$5:$AO$335)<ROW())))) | AS51: Substitui provisoriamente o IDE não-petrolífero quando a série setorial estiver vazia. | Nome local/API: Foreign direct investment, net inflows (% of GDP)
A52: MAC011 | B52: 2. Estabilidade Macroeconómica | C52: 2. Macroeconomia | D52: Rendas petrolíferas (% PIB) | E52: % | F52: - | G52: 0 | H52: 60 | I52: 15 | J52: 1 | K52: Banco Mundial/WDI | L52: NY.GDP.PETR.RT.ZS | M52: Banco Mundial — WDI | N52: 0 | O52: G_RENDAS_PETR | P52: Alta | Q52: 12.71873 | R52: 19.748399 | S52: 24.711006 | T52: 30.730403 | U52: 27.504829 | V52: 18.57196 | W52: 28.27444 | AB52: =COUNT(Q52:AA52) -> 7 | AC52: =AB52/11 -> 0.63636364 | AD52: =IFERROR(INDEX($Q$4:$AA$4,MATCH(TRUE,INDEX(ISNUMBER(Q52:AA52),0),0)),"") -> 2015 | AE52: =IFERROR(LOOKUP(2,1/ISNUMBER(Q52:AA52),$Q$4:$AA$4),"") -> 2021 | AF52: =IF(AB52=0,"",AB52/(AE52-AD52+1)) -> 1 | AG52: =IF(AB52=0,"",'01_Criterios'!$C$8-AE52) -> 4 | AH52: =IF(P52="Em uso",100,IF(P52="Alta",85,IF(P52="Média",55,30))) -> 85 | AI52: =ROUND(100*AC52,1) -> 63.6 | AJ52: =IF(AB52=0,0,ROUND(MAX(0,100*AF52-10*AG52),1)) -> 60 | AK52: =ROUND(('01_Criterios'!$C$19*AH52+'01_Criterios'!$C$20*AI52+'01_Criterios'!$C$21*AJ52)/('01_Criterios'!$C$19+'01_Criterios'!$C$20+'01_Criterios'!$C$21)+N52*'01_Criterios'!$C$22,1) -> 71.3 | AL52: =IF(AND(AB52>=3,AC52>='01_Criterios'!$C$11,N(AE52)>='01_Criterios'!$C$12,OR(F52="+",F52="-"),ISNUMBER(G52),ISNUMBER(H52)),1,0) -> 0 | AM52: =IF(AL52=1,"",TRIM(IF(AB52=0,"sem dados no período; ",IF(AB52<3,"série demasiado curta; ",""))&IF(AND(AB52>0,AC52<'01_Criterios'!$C$11),"cobertura insuficiente; ","")&IF(AND(AB52>0,N(AE52)<'01_Criterios'!$C$12),"desactualizado; ","")&IF(AND(F52<>"+",F52<>"-"),"sentido ambíguo; ","")&IF(OR(NOT(ISNUMBER(G52)),NOT(ISNUMBER(H52))),"sem limites min/max; ",""))) -> cobertura insuficiente; desactualizado; | AN52: =IF(OR(AL52=0,$AP52="Excluir"),0,IF(SUMPRODUCT(($O$5:$O$335=$O52)*($AL$5:$AL$335=1)*($AP$5:$AP$335<>"Excluir")*(($AK$5:$AK$335>$AK52)+(($AK$5:$AK$335=$AK52)*(ROW($O$5:$O$335)<ROW()))))=0,1,0)) -> 0 | AO52: =IF(AN52=0,"",1+SUMPRODUCT(($B$5:$B$335=$B52)*($AN$5:$AN$335=1)*(($AK$5:$AK$335>$AK52)+(($AK$5:$AK$335=$AK52)*(ROW($B$5:$B$335)<ROW()))))) | AP52: Auto | AQ52: =IF(INDEX('01_Criterios'!$C$26:$C$36,MATCH($B52,'01_Criterios'!$B$26:$B$36,0))<>1,0,IF($AP52="Excluir",0,IF($AP52="Incluir",IF(AND(OR($F52="+",$F52="-"),ISNUMBER($G52),ISNUMBER($H52),COUNT($Q52:$AA52)>0),1,0),IF('01_Criterios'!$C$18="Automática",IF(AND($AN52=1,$AO52<>"",$AO52<=INDEX('01_Criterios'!$E$26:$E$36,MATCH($B52,'01_Criterios'!$B$26:$B$36,0))),1,0),0)))) -> 0 | AR52: =IF(AQ52=0,"",IF($AO52<>"",1+SUMPRODUCT(($B$5:$B$335=$B52)*($AQ$5:$AQ$335=1)*($AO$5:$AO$335<$AO52)),1+SUMPRODUCT(($B$5:$B$335=$B52)*($AQ$5:$AQ$335=1)*ISNUMBER($AO$5:$AO$335))+SUMPRODUCT(($B$5:$B$335=$B52)*($AQ$5:$AQ$335=1)*($AO$5:$AO$335="")*(ROW($AO$5:$AO$335)<ROW())))) | AS52: Proxy de dependência petrolífera; menor dependência é melhor para diversificação. | Nome local/API: Oil rents (% of GDP)
A53: MAC016 | B53: 2. Estabilidade Macroeconómica | C53: Finanças públicas | D53: Dívida bruta do governo geral - FMI WEO | E53: % PIB | F53: - | G53: 0 | H53: 150 | I53: 60 | J53: 1 | K53: FMI/WEO | L53: GGXWDG_NGDP | M53: FMI — WEO | N53: 0 | O53: G_DIVIDA_PUB | P53: Alta | Q53: 50.385819 | R53: 65.691623 | S53: 59.607197 | T53: 81.635503 | U53: 100.79929 | V53: 119.83861 | W53: 75.502733 | X53: 57.427174 | Y53: 75.739104 | Z53: 57.106858 | AA53: 51.310898 | AB53: =COUNT(Q53:AA53) -> 11 | AC53: =AB53/11 -> 1 | AD53: =IFERROR(INDEX($Q$4:$AA$4,MATCH(TRUE,INDEX(ISNUMBER(Q53:AA53),0),0)),"") -> 2015 | AE53: =IFERROR(LOOKUP(2,1/ISNUMBER(Q53:AA53),$Q$4:$AA$4),"") -> 2025 | AF53: =IF(AB53=0,"",AB53/(AE53-AD53+1)) -> 1 | AG53: =IF(AB53=0,"",'01_Criterios'!$C$8-AE53) -> 0 | AH53: =IF(P53="Em uso",100,IF(P53="Alta",85,IF(P53="Média",55,30))) -> 85 | AI53: =ROUND(100*AC53,1) -> 100 | AJ53: =IF(AB53=0,0,ROUND(MAX(0,100*AF53-10*AG53),1)) -> 100 | AK53: =ROUND(('01_Criterios'!$C$19*AH53+'01_Criterios'!$C$20*AI53+'01_Criterios'!$C$21*AJ53)/('01_Criterios'!$C$19+'01_Criterios'!$C$20+'01_Criterios'!$C$21)+N53*'01_Criterios'!$C$22,1) -> 94 | AL53: =IF(AND(AB53>=3,AC53>='01_Criterios'!$C$11,N(AE53)>='01_Criterios'!$C$12,OR(F53="+",F53="-"),ISNUMBER(G53),ISNUMBER(H53)),1,0) -> 1 | AM53: =IF(AL53=1,"",TRIM(IF(AB53=0,"sem dados no período; ",IF(AB53<3,"série demasiado curta; ",""))&IF(AND(AB53>0,AC53<'01_Criterios'!$C$11),"cobertura insuficiente; ","")&IF(AND(AB53>0,N(AE53)<'01_Criterios'!$C$12),"desactualizado; ","")&IF(AND(F53<>"+",F53<>"-"),"sentido ambíguo; ","")&IF(OR(NOT(ISNUMBER(G53)),NOT(ISNUMBER(H53))),"sem limites min/max; ",""))) | AN53: =IF(OR(AL53=0,$AP53="Excluir"),0,IF(SUMPRODUCT(($O$5:$O$335=$O53)*($AL$5:$AL$335=1)*($AP$5:$AP$335<>"Excluir")*(($AK$5:$AK$335>$AK53)+(($AK$5:$AK$335=$AK53)*(ROW($O$5:$O$335)<ROW()))))=0,1,0)) -> 0 | AO53: =IF(AN53=0,"",1+SUMPRODUCT(($B$5:$B$335=$B53)*($AN$5:$AN$335=1)*(($AK$5:$AK$335>$AK53)+(($AK$5:$AK$335=$AK53)*(ROW($B$5:$B$335)<ROW()))))) | AP53: Auto | AQ53: =IF(INDEX('01_Criterios'!$C$26:$C$36,MATCH($B53,'01_Criterios'!$B$26:$B$36,0))<>1,0,IF($AP53="Excluir",0,IF($AP53="Incluir",IF(AND(OR($F53="+",$F53="-"),ISNUMBER($G53),ISNUMBER($H53),COUNT($Q53:$AA53)>0),1,0),IF('01_Criterios'!$C$18="Automática",IF(AND($AN53=1,$AO53<>"",$AO53<=INDEX('01_Criterios'!$E$26:$E$36,MATCH($B53,'01_Criterios'!$B$26:$B$36,0))),1,0),0)))) -> 0 | AR53: =IF(AQ53=0,"",IF($AO53<>"",1+SUMPRODUCT(($B$5:$B$335=$B53)*($AQ$5:$AQ$335=1)*($AO$5:$AO$335<$AO53)),1+SUMPRODUCT(($B$5:$B$335=$B53)*($AQ$5:$AQ$335=1)*ISNUMBER($AO$5:$AO$335))+SUMPRODUCT(($B$5:$B$335=$B53)*($AQ$5:$AQ$335=1)*($AO$5:$AO$335="")*(ROW($AO$5:$AO$335)<ROW())))) | AS53: Série FMI alternativa/validação da dívida pública. | Nome local/API: Gross debt, General government, Percent of GDP
A54: MAC019 | B54: 2. Estabilidade Macroeconómica | C54: Finanças públicas | D54: Saldo líquido / necessidade de financiamento do governo geral | E54: % PIB | F54: + | G54: -20 | H54: 20 | I54: 0 | J54: 1 | K54: FMI/WEO | L54: GGXCNL_NGDP | M54: FMI — WEO | N54: 0 | O54: G_SALDO_ORC | P54: Alta | Q54: -2.582085 | R54: -3.934178 | S54: -5.682721 | T54: 1.998796 | U54: -0.19541 | V54: -3.046261 | W54: 1.352043 | X54: 1.779136 | Y54: -2.4918 | Z54: -1.192327 | AA54: -4.070237 | AB54: =COUNT(Q54:AA54) -> 11 | AC54: =AB54/11 -> 1 | AD54: =IFERROR(INDEX($Q$4:$AA$4,MATCH(TRUE,INDEX(ISNUMBER(Q54:AA54),0),0)),"") -> 2015 | AE54: =IFERROR(LOOKUP(2,1/ISNUMBER(Q54:AA54),$Q$4:$AA$4),"") -> 2025 | AF54: =IF(AB54=0,"",AB54/(AE54-AD54+1)) -> 1 | AG54: =IF(AB54=0,"",'01_Criterios'!$C$8-AE54) -> 0 | AH54: =IF(P54="Em uso",100,IF(P54="Alta",85,IF(P54="Média",55,30))) -> 85 | AI54: =ROUND(100*AC54,1) -> 100 | AJ54: =IF(AB54=0,0,ROUND(MAX(0,100*AF54-10*AG54),1)) -> 100 | AK54: =ROUND(('01_Criterios'!$C$19*AH54+'01_Criterios'!$C$20*AI54+'01_Criterios'!$C$21*AJ54)/('01_Criterios'!$C$19+'01_Criterios'!$C$20+'01_Criterios'!$C$21)+N54*'01_Criterios'!$C$22,1) -> 94 | AL54: =IF(AND(AB54>=3,AC54>='01_Criterios'!$C$11,N(AE54)>='01_Criterios'!$C$12,OR(F54="+",F54="-"),ISNUMBER(G54),ISNUMBER(H54)),1,0) -> 1 | AM54: =IF(AL54=1,"",TRIM(IF(AB54=0,"sem dados no período; ",IF(AB54<3,"série demasiado curta; ",""))&IF(AND(AB54>0,AC54<'01_Criterios'!$C$11),"cobertura insuficiente; ","")&IF(AND(AB54>0,N(AE54)<'01_Criterios'!$C$12),"desactualizado; ","")&IF(AND(F54<>"+",F54<>"-"),"sentido ambíguo; ","")&IF(OR(NOT(ISNUMBER(G54)),NOT(ISNUMBER(H54))),"sem limites min/max; ",""))) | AN54: =IF(OR(AL54=0,$AP54="Excluir"),0,IF(SUMPRODUCT(($O$5:$O$335=$O54)*($AL$5:$AL$335=1)*($AP$5:$AP$335<>"Excluir")*(($AK$5:$AK$335>$AK54)+(($AK$5:$AK$335=$AK54)*(ROW($O$5:$O$335)<ROW()))))=0,1,0)) -> 0 | AO54: =IF(AN54=0,"",1+SUMPRODUCT(($B$5:$B$335=$B54)*($AN$5:$AN$335=1)*(($AK$5:$AK$335>$AK54)+(($AK$5:$AK$335=$AK54)*(ROW($B$5:$B$335)<ROW()))))) | AP54: Auto | AQ54: =IF(INDEX('01_Criterios'!$C$26:$C$36,MATCH($B54,'01_Criterios'!$B$26:$B$36,0))<>1,0,IF($AP54="Excluir",0,IF($AP54="Incluir",IF(AND(OR($F54="+",$F54="-"),ISNUMBER($G54),ISNUMBER($H54),COUNT($Q54:$AA54)>0),1,0),IF('01_Criterios'!$C$18="Automática",IF(AND($AN54=1,$AO54<>"",$AO54<=INDEX('01_Criterios'!$E$26:$E$36,MATCH($B54,'01_Criterios'!$B$26:$B$36,0))),1,0),0)))) -> 0 | AR54: =IF(AQ54=0,"",IF($AO54<>"",1+SUMPRODUCT(($B$5:$B$335=$B54)*($AQ$5:$AQ$335=1)*($AO$5:$AO$335<$AO54)),1+SUMPRODUCT(($B$5:$B$335=$B54)*($AQ$5:$AQ$335=1)*ISNUMBER($AO$5:$AO$335))+SUMPRODUCT(($B$5:$B$335=$B54)*($AQ$5:$AQ$335=1)*($AO$5:$AO$335="")*(ROW($AO$5:$AO$335)<ROW())))) | AS54: Alternativa FMI para saldo orçamental. | Nome local/API: Net lending (+) / net borrowing (-), General government, Percent of GDP
A55: MAC015 | B55: 2. Estabilidade Macroeconómica | C55: 2. Macroeconomia | D55: Volatilidade da taxa de câmbio nominal | E55: % variação anual | F55: - | G55: 0 | H55: 80 | I55: 10 | J55: 1 | K55: Banco Mundial/WDI ou BNA | L55: PA.NUS.FCRF | M55: Banco Mundial — WDI | N55: 1 | O55: MAC015 | P55: Média | Q55: 22.134 | R55: 36.3114 | S55: 1.3806 | T55: 52.3999 | U55: 44.2822 | V55: 58.5027 | W55: 9.1971 | X55: 27.061 | Y55: 48.7339 | Z55: 26.9811 | AA55: 4.8453 | AB55: =COUNT(Q55:AA55) -> 11 | AC55: =AB55/11 -> 1 | AD55: =IFERROR(INDEX($Q$4:$AA$4,MATCH(TRUE,INDEX(ISNUMBER(Q55:AA55),0),0)),"") -> 2015 | AE55: =IFERROR(LOOKUP(2,1/ISNUMBER(Q55:AA55),$Q$4:$AA$4),"") -> 2025 | AF55: =IF(AB55=0,"",AB55/(AE55-AD55+1)) -> 1 | AG55: =IF(AB55=0,"",'01_Criterios'!$C$8-AE55) -> 0 | AH55: =IF(P55="Em uso",100,IF(P55="Alta",85,IF(P55="Média",55,30))) -> 55 | AI55: =ROUND(100*AC55,1) -> 100 | AJ55: =IF(AB55=0,0,ROUND(MAX(0,100*AF55-10*AG55),1)) -> 100 | AK55: =ROUND(('01_Criterios'!$C$19*AH55+'01_Criterios'!$C$20*AI55+'01_Criterios'!$C$21*AJ55)/('01_Criterios'!$C$19+'01_Criterios'!$C$20+'01_Criterios'!$C$21)+N55*'01_Criterios'!$C$22,1) -> 94 | AL55: =IF(AND(AB55>=3,AC55>='01_Criterios'!$C$11,N(AE55)>='01_Criterios'!$C$12,OR(F55="+",F55="-"),ISNUMBER(G55),ISNUMBER(H55)),1,0) -> 1 | AM55: =IF(AL55=1,"",TRIM(IF(AB55=0,"sem dados no período; ",IF(AB55<3,"série demasiado curta; ",""))&IF(AND(AB55>0,AC55<'01_Criterios'!$C$11),"cobertura insuficiente; ","")&IF(AND(AB55>0,N(AE55)<'01_Criterios'!$C$12),"desactualizado; ","")&IF(AND(F55<>"+",F55<>"-"),"sentido ambíguo; ","")&IF(OR(NOT(ISNUMBER(G55)),NOT(ISNUMBER(H55))),"sem limites min/max; ",""))) | AN55: =IF(OR(AL55=0,$AP55="Excluir"),0,IF(SUMPRODUCT(($O$5:$O$335=$O55)*($AL$5:$AL$335=1)*($AP$5:$AP$335<>"Excluir")*(($AK$5:$AK$335>$AK55)+(($AK$5:$AK$335=$AK55)*(ROW($O$5:$O$335)<ROW()))))=0,1,0)) -> 1 | AO55: =IF(AN55=0,"",1+SUMPRODUCT(($B$5:$B$335=$B55)*($AN$5:$AN$335=1)*(($AK$5:$AK$335>$AK55)+(($AK$5:$AK$335=$AK55)*(ROW($B$5:$B$335)<ROW()))))) -> 12 | AP55: Auto | AQ55: =IF(INDEX('01_Criterios'!$C$26:$C$36,MATCH($B55,'01_Criterios'!$B$26:$B$36,0))<>1,0,IF($AP55="Excluir",0,IF($AP55="Incluir",IF(AND(OR($F55="+",$F55="-"),ISNUMBER($G55),ISNUMBER($H55),COUNT($Q55:$AA55)>0),1,0),IF('01_Criterios'!$C$18="Automática",IF(AND($AN55=1,$AO55<>"",$AO55<=INDEX('01_Criterios'!$E$26:$E$36,MATCH($B55,'01_Criterios'!$B$26:$B$36,0))),1,0),0)))) -> 0 | AR55: =IF(AQ55=0,"",IF($AO55<>"",1+SUMPRODUCT(($B$5:$B$335=$B55)*($AQ$5:$AQ$335=1)*($AO$5:$AO$335<$AO55)),1+SUMPRODUCT(($B$5:$B$335=$B55)*($AQ$5:$AQ$335=1)*ISNUMBER($AO$5:$AO$335))+SUMPRODUCT(($B$5:$B$335=$B55)*($AQ$5:$AQ$335=1)*($AO$5:$AO$335="")*(ROW($AO$5:$AO$335)<ROW())))) | AS55: Capta instabilidade cambial que afeta preços, dívida e importações. | Nome local/API: Official exchange rate (LCU per US$, period average) | Limites: a série foi recalculada como variação anual absoluta da taxa de câmbio oficial PA.NUS.FCRF; mínimo 0 = ausência de variação e máximo 80% = choque cambial extremo observado/plausível antes de truncagem.
A56: MAC030 | B56: 2. Estabilidade Macroeconómica | C56: Inflação | D56: Inflação homóloga Luanda - Dezembro (BNA/INE) | E56: % | F56: - | G56: 0 | H56: 50 | I56: 10 | J56: 1 | K56: BNA/INE — Preços | L56: NAT_BNA_INFL_LUA | M56: BNA — Preços | N56: 1 | O56: G_INFLACAO | P56: Média | Q56: 14.27 | R56: 41.95 | S56: 26.26 | T56: 18.21 | U56: 17.06 | V56: 25.19 | W56: 30.43 | X56: 13.14 | Y56: 26.02 | Z56: 32.18 | AA56: 14.2 | AB56: =COUNT(Q56:AA56) -> 11 | AC56: =AB56/11 -> 1 | AD56: =IFERROR(INDEX($Q$4:$AA$4,MATCH(TRUE,INDEX(ISNUMBER(Q56:AA56),0),0)),"") -> 2015 | AE56: =IFERROR(LOOKUP(2,1/ISNUMBER(Q56:AA56),$Q$4:$AA$4),"") -> 2025 | AF56: =IF(AB56=0,"",AB56/(AE56-AD56+1)) -> 1 | AG56: =IF(AB56=0,"",'01_Criterios'!$C$8-AE56) -> 0 | AH56: =IF(P56="Em uso",100,IF(P56="Alta",85,IF(P56="Média",55,30))) -> 55 | AI56: =ROUND(100*AC56,1) -> 100 | AJ56: =IF(AB56=0,0,ROUND(MAX(0,100*AF56-10*AG56),1)) -> 100 | AK56: =ROUND(('01_Criterios'!$C$19*AH56+'01_Criterios'!$C$20*AI56+'01_Criterios'!$C$21*AJ56)/('01_Criterios'!$C$19+'01_Criterios'!$C$20+'01_Criterios'!$C$21)+N56*'01_Criterios'!$C$22,1) -> 94 | AL56: =IF(AND(AB56>=3,AC56>='01_Criterios'!$C$11,N(AE56)>='01_Criterios'!$C$12,OR(F56="+",F56="-"),ISNUMBER(G56),ISNUMBER(H56)),1,0) -> 1 | AM56: =IF(AL56=1,"",TRIM(IF(AB56=0,"sem dados no período; ",IF(AB56<3,"série demasiado curta; ",""))&IF(AND(AB56>0,AC56<'01_Criterios'!$C$11),"cobertura insuficiente; ","")&IF(AND(AB56>0,N(AE56)<'01_Criterios'!$C$12),"desactualizado; ","")&IF(AND(F56<>"+",F56<>"-"),"sentido ambíguo; ","")&IF(OR(NOT(ISNUMBER(G56)),NOT(ISNUMBER(H56))),"sem limites min/max; ",""))) | AN56: =IF(OR(AL56=0,$AP56="Excluir"),0,IF(SUMPRODUCT(($O$5:$O$335=$O56)*($AL$5:$AL$335=1)*($AP$5:$AP$335<>"Excluir")*(($AK$5:$AK$335>$AK56)+(($AK$5:$AK$335=$AK56)*(ROW($O$5:$O$335)<ROW()))))=0,1,0)) -> 0 | AO56: =IF(AN56=0,"",1+SUMPRODUCT(($B$5:$B$335=$B56)*($AN$5:$AN$335=1)*(($AK$5:$AK$335>$AK56)+(($AK$5:$AK$335=$AK56)*(ROW($B$5:$B$335)<ROW()))))) | AP56: Auto | AQ56: =IF(INDEX('01_Criterios'!$C$26:$C$36,MATCH($B56,'01_Criterios'!$B$26:$B$36,0))<>1,0,IF($AP56="Excluir",0,IF($AP56="Incluir",IF(AND(OR($F56="+",$F56="-"),ISNUMBER($G56),ISNUMBER($H56),COUNT($Q56:$AA56)>0),1,0),IF('01_Criterios'!$C$18="Automática",IF(AND($AN56=1,$AO56<>"",$AO56<=INDEX('01_Criterios'!$E$26:$E$36,MATCH($B56,'01_Criterios'!$B$26:$B$36,0))),1,0),0)))) -> 0 | AR56: =IF(AQ56=0,"",IF($AO56<>"",1+SUMPRODUCT(($B$5:$B$335=$B56)*($AQ$5:$AQ$335=1)*($AO$5:$AO$335<$AO56)),1+SUMPRODUCT(($B$5:$B$335=$B56)*($AQ$5:$AQ$335=1)*ISNUMBER($AO$5:$AO$335))+SUMPRODUCT(($B$5:$B$335=$B56)*($AQ$5:$AQ$335=1)*($AO$5:$AO$335="")*(ROW($AO$5:$AO$335)<ROW())))) | AS56: Inflação homóloga (Luanda) em Dezembro de cada ano (variação acumulada anual).
A57: MAC035 | B57: 2. Estabilidade Macroeconómica | C57: Contas nacionais | D57: PIB nominal em dólares (BNA) | E57: milhões USD | F57: + | G57: 0 | H57: 188000 | J57: 1 | K57: BNA — Estatísticas Externas | L57: NAT_BNA_PIB_USD | M57: BNA — Estatísticas Externas | N57: 1 | O57: MAC035 | P57: Média | Q57: 131627.79 | R57: 116484.75 | S57: 141910.63 | T57: 115497.62 | U57: 95265.401 | V57: 66121.967 | W57: 83993.29 | X57: 139413.77 | Y57: 112875.54 | Z57: 119574.12 | AA57: 141731.96 | AB57: =COUNT(Q57:AA57) -> 11 | AC57: =AB57/11 -> 1 | AD57: =IFERROR(INDEX($Q$4:$AA$4,MATCH(TRUE,INDEX(ISNUMBER(Q57:AA57),0),0)),"") -> 2015 | AE57: =IFERROR(LOOKUP(2,1/ISNUMBER(Q57:AA57),$Q$4:$AA$4),"") -> 2025 | AF57: =IF(AB57=0,"",AB57/(AE57-AD57+1)) -> 1 | AG57: =IF(AB57=0,"",'01_Criterios'!$C$8-AE57) -> 0 | AH57: =IF(P57="Em uso",100,IF(P57="Alta",85,IF(P57="Média",55,30))) -> 55 | AI57: =ROUND(100*AC57,1) -> 100 | AJ57: =IF(AB57=0,0,ROUND(MAX(0,100*AF57-10*AG57),1)) -> 100 | AK57: =ROUND(('01_Criterios'!$C$19*AH57+'01_Criterios'!$C$20*AI57+'01_Criterios'!$C$21*AJ57)/('01_Criterios'!$C$19+'01_Criterios'!$C$20+'01_Criterios'!$C$21)+N57*'01_Criterios'!$C$22,1) -> 94 | AL57: =IF(AND(AB57>=3,AC57>='01_Criterios'!$C$11,N(AE57)>='01_Criterios'!$C$12,OR(F57="+",F57="-"),ISNUMBER(G57),ISNUMBER(H57)),1,0) -> 1 | AM57: =IF(AL57=1,"",TRIM(IF(AB57=0,"sem dados no período; ",IF(AB57<3,"série demasiado curta; ",""))&IF(AND(AB57>0,AC57<'01_Criterios'!$C$11),"cobertura insuficiente; ","")&IF(AND(AB57>0,N(AE57)<'01_Criterios'!$C$12),"desactualizado; ","")&IF(AND(F57<>"+",F57<>"-"),"sentido ambíguo; ","")&IF(OR(NOT(ISNUMBER(G57)),NOT(ISNUMBER(H57))),"sem limites min/max; ",""))) | AN57: =IF(OR(AL57=0,$AP57="Excluir"),0,IF(SUMPRODUCT(($O$5:$O$335=$O57)*($AL$5:$AL$335=1)*($AP$5:$AP$335<>"Excluir")*(($AK$5:$AK$335>$AK57)+(($AK$5:$AK$335=$AK57)*(ROW($O$5:$O$335)<ROW()))))=0,1,0)) -> 1 | AO57: =IF(AN57=0,"",1+SUMPRODUCT(($B$5:$B$335=$B57)*($AN$5:$AN$335=1)*(($AK$5:$AK$335>$AK57)+(($AK$5:$AK$335=$AK57)*(ROW($B$5:$B$335)<ROW()))))) -> 13 | AP57: Auto | AQ57: =IF(INDEX('01_Criterios'!$C$26:$C$36,MATCH($B57,'01_Criterios'!$B$26:$B$36,0))<>1,0,IF($AP57="Excluir",0,IF($AP57="Incluir",IF(AND(OR($F57="+",$F57="-"),ISNUMBER($G57),ISNUMBER($H57),COUNT($Q57:$AA57)>0),1,0),IF('01_Criterios'!$C$18="Automática",IF(AND($AN57=1,$AO57<>"",$AO57<=INDEX('01_Criterios'!$E$26:$E$36,MATCH($B57,'01_Criterios'!$B$26:$B$36,0))),1,0),0)))) -> 0 | AR57: =IF(AQ57=0,"",IF($AO57<>"",1+SUMPRODUCT(($B$5:$B$335=$B57)*($AQ$5:$AQ$335=1)*($AO$5:$AO$335<$AO57)),1+SUMPRODUCT(($B$5:$B$335=$B57)*($AQ$5:$AQ$335=1)*ISNUMBER($AO$5:$AO$335))+SUMPRODUCT(($B$5:$B$335=$B57)*($AQ$5:$AQ$335=1)*($AO$5:$AO$335="")*(ROW($AO$5:$AO$335)<ROW())))) | AS57: BNA, Principais Indicadores Externos 1990-2025, linha "PIB". | Limites min/max derivados da amplitude histórica.
A58: MAC036 | B58: 2. Estabilidade Macroeconómica | C58: Contas nacionais | D58: Crescimento real do PIB per capita (INE) | E58: % | F58: + | G58: -15 | H58: 12 | I58: 3 | J58: 1 | K58: INE — Contas Nacionais | L58: NAT_INE_GDPPC_GROWTH | M58: INE — Contas Nacionais | N58: 1 | O58: MAC036 | P58: Média | Q58: -2.184 | R58: -3.2146 | S58: -3.1785 | T58: -3.5353 | U58: -4.0901 | V58: -8.1709 | W58: -1.9644 | X58: 0.4632 | Y58: -1.6748 | Z58: -2.2457 | AB58: =COUNT(Q58:AA58) -> 10 | AC58: =AB58/11 -> 0.90909091 | AD58: =IFERROR(INDEX($Q$4:$AA$4,MATCH(TRUE,INDEX(ISNUMBER(Q58:AA58),0),0)),"") -> 2015 | AE58: =IFERROR(LOOKUP(2,1/ISNUMBER(Q58:AA58),$Q$4:$AA$4),"") -> 2024 | AF58: =IF(AB58=0,"",AB58/(AE58-AD58+1)) -> 1 | AG58: =IF(AB58=0,"",'01_Criterios'!$C$8-AE58) -> 1 | AH58: =IF(P58="Em uso",100,IF(P58="Alta",85,IF(P58="Média",55,30))) -> 55 | AI58: =ROUND(100*AC58,1) -> 90.9 | AJ58: =IF(AB58=0,0,ROUND(MAX(0,100*AF58-10*AG58),1)) -> 90 | AK58: =ROUND(('01_Criterios'!$C$19*AH58+'01_Criterios'!$C$20*AI58+'01_Criterios'!$C$21*AJ58)/('01_Criterios'!$C$19+'01_Criterios'!$C$20+'01_Criterios'!$C$21)+N58*'01_Criterios'!$C$22,1) -> 88.3 | AL58: =IF(AND(AB58>=3,AC58>='01_Criterios'!$C$11,N(AE58)>='01_Criterios'!$C$12,OR(F58="+",F58="-"),ISNUMBER(G58),ISNUMBER(H58)),1,0) -> 1 | AM58: =IF(AL58=1,"",TRIM(IF(AB58=0,"sem dados no período; ",IF(AB58<3,"série demasiado curta; ",""))&IF(AND(AB58>0,AC58<'01_Criterios'!$C$11),"cobertura insuficiente; ","")&IF(AND(AB58>0,N(AE58)<'01_Criterios'!$C$12),"desactualizado; ","")&IF(AND(F58<>"+",F58<>"-"),"sentido ambíguo; ","")&IF(OR(NOT(ISNUMBER(G58)),NOT(ISNUMBER(H58))),"sem limites min/max; ",""))) | AN58: =IF(OR(AL58=0,$AP58="Excluir"),0,IF(SUMPRODUCT(($O$5:$O$335=$O58)*($AL$5:$AL$335=1)*($AP$5:$AP$335<>"Excluir")*(($AK$5:$AK$335>$AK58)+(($AK$5:$AK$335=$AK58)*(ROW($O$5:$O$335)<ROW()))))=0,1,0)) -> 1 | AO58: =IF(AN58=0,"",1+SUMPRODUCT(($B$5:$B$335=$B58)*($AN$5:$AN$335=1)*(($AK$5:$AK$335>$AK58)+(($AK$5:$AK$335=$AK58)*(ROW($B$5:$B$335)<ROW()))))) -> 18 | AP58: Auto | AQ58: =IF(INDEX('01_Criterios'!$C$26:$C$36,MATCH($B58,'01_Criterios'!$B$26:$B$36,0))<>1,0,IF($AP58="Excluir",0,IF($AP58="Incluir",IF(AND(OR($F58="+",$F58="-"),ISNUMBER($G58),ISNUMBER($H58),COUNT($Q58:$AA58)>0),1,0),IF('01_Criterios'!$C$18="Automática",IF(AND($AN58=1,$AO58<>"",$AO58<=INDEX('01_Criterios'!$E$26:$E$36,MATCH($B58,'01_Criterios'!$B$26:$B$36,0))),1,0),0)))) -> 0 | AR58: =IF(AQ58=0,"",IF($AO58<>"",1+SUMPRODUCT(($B$5:$B$335=$B58)*($AQ$5:$AQ$335=1)*($AO$5:$AO$335<$AO58)),1+SUMPRODUCT(($B$5:$B$335=$B58)*($AQ$5:$AQ$335=1)*ISNUMBER($AO$5:$AO$335))+SUMPRODUCT(($B$5:$B$335=$B58)*($AQ$5:$AQ$335=1)*($AO$5:$AO$335="")*(ROW($AO$5:$AO$335)<ROW())))) | AS58: INE, Contas Nacionais Q1.2, variação real anual do PIB per capita.
A59: MAC039 | B59: 2. Estabilidade Macroeconómica | C59: Finanças públicas | D59: Dívida externa total (stock, BNA) | E59: % PIB | F59: - | G59: 0 | H59: 150 | I59: 60 | J59: 1 | K59: BNA — Estatísticas Externas | L59: NAT_BNA_DEBTTOT_GDP | M59: BNA — Estatísticas Externas | N59: 1 | O59: G_DIV_EXTERNA | P59: Média | Q59: 39.2137 | R59: 51.8185 | S59: 42.1401 | T59: 52.2051 | U59: 65.3753 | V59: 98.4946 | W59: 77.0862 | X59: 42.1449 | Y59: 49.6086 | Z59: 45.4188 | AA59: 45.3849 | AB59: =COUNT(Q59:AA59) -> 11 | AC59: =AB59/11 -> 1 | AD59: =IFERROR(INDEX($Q$4:$AA$4,MATCH(TRUE,INDEX(ISNUMBER(Q59:AA59),0),0)),"") -> 2015 | AE59: =IFERROR(LOOKUP(2,1/ISNUMBER(Q59:AA59),$Q$4:$AA$4),"") -> 2025 | AF59: =IF(AB59=0,"",AB59/(AE59-AD59+1)) -> 1 | AG59: =IF(AB59=0,"",'01_Criterios'!$C$8-AE59) -> 0 | AH59: =IF(P59="Em uso",100,IF(P59="Alta",85,IF(P59="Média",55,30))) -> 55 | AI59: =ROUND(100*AC59,1) -> 100 | AJ59: =IF(AB59=0,0,ROUND(MAX(0,100*AF59-10*AG59),1)) -> 100 | AK59: =ROUND(('01_Criterios'!$C$19*AH59+'01_Criterios'!$C$20*AI59+'01_Criterios'!$C$21*AJ59)/('01_Criterios'!$C$19+'01_Criterios'!$C$20+'01_Criterios'!$C$21)+N59*'01_Criterios'!$C$22,1) -> 94 | AL59: =IF(AND(AB59>=3,AC59>='01_Criterios'!$C$11,N(AE59)>='01_Criterios'!$C$12,OR(F59="+",F59="-"),ISNUMBER(G59),ISNUMBER(H59)),1,0) -> 1 | AM59: =IF(AL59=1,"",TRIM(IF(AB59=0,"sem dados no período; ",IF(AB59<3,"série demasiado curta; ",""))&IF(AND(AB59>0,AC59<'01_Criterios'!$C$11),"cobertura insuficiente; ","")&IF(AND(AB59>0,N(AE59)<'01_Criterios'!$C$12),"desactualizado; ","")&IF(AND(F59<>"+",F59<>"-"),"sentido ambíguo; ","")&IF(OR(NOT(ISNUMBER(G59)),NOT(ISNUMBER(H59))),"sem limites min/max; ",""))) | AN59: =IF(OR(AL59=0,$AP59="Excluir"),0,IF(SUMPRODUCT(($O$5:$O$335=$O59)*($AL$5:$AL$335=1)*($AP$5:$AP$335<>"Excluir")*(($AK$5:$AK$335>$AK59)+(($AK$5:$AK$335=$AK59)*(ROW($O$5:$O$335)<ROW()))))=0,1,0)) -> 0 | AO59: =IF(AN59=0,"",1+SUMPRODUCT(($B$5:$B$335=$B59)*($AN$5:$AN$335=1)*(($AK$5:$AK$335>$AK59)+(($AK$5:$AK$335=$AK59)*(ROW($B$5:$B$335)<ROW()))))) | AP59: Auto | AQ59: =IF(INDEX('01_Criterios'!$C$26:$C$36,MATCH($B59,'01_Criterios'!$B$26:$B$36,0))<>1,0,IF($AP59="Excluir",0,IF($AP59="Incluir",IF(AND(OR($F59="+",$F59="-"),ISNUMBER($G59),ISNUMBER($H59),COUNT($Q59:$AA59)>0),1,0),IF('01_Criterios'!$C$18="Automática",IF(AND($AN59=1,$AO59<>"",$AO59<=INDEX('01_Criterios'!$E$26:$E$36,MATCH($B59,'01_Criterios'!$B$26:$B$36,0))),1,0),0)))) -> 0 | AR59: =IF(AQ59=0,"",IF($AO59<>"",1+SUMPRODUCT(($B$5:$B$335=$B59)*($AQ$5:$AQ$335=1)*($AO$5:$AO$335<$AO59)),1+SUMPRODUCT(($B$5:$B$335=$B59)*($AQ$5:$AQ$335=1)*ISNUMBER($AO$5:$AO$335))+SUMPRODUCT(($B$5:$B$335=$B59)*($AQ$5:$AQ$335=1)*($AO$5:$AO$335="")*(ROW($AO$5:$AO$335)<ROW())))) | AS59: BNA, Principais Indicadores Externos 1990-2025, linha "Dívida Externa Total (stock)".
A60: MAC040 | B60: 2. Estabilidade Macroeconómica | C60: Finanças públicas | D60: Necessidade/capacidade de financiamento (% PIB, INE) | E60: % PIB | F60: +/- | G60: -20 | H60: 30 | I60: 0 | J60: 1 | K60: INE — Contas Nacionais | L60: NAT_INE_NETFIN | M60: INE — Contas Nacionais | N60: 1 | O60: MAC040 | P60: Média | Q60: -7.7956 | R60: -2.6483 | S60: -0.4441 | T60: 6.4141 | U60: 5.398 | V60: 1.3202 | W60: 10.0024 | X60: 8.4506 | Y60: 3.7084 | Z60: 5.1547 | AB60: =COUNT(Q60:AA60) -> 10 | AC60: =AB60/11 -> 0.90909091 | AD60: =IFERROR(INDEX($Q$4:$AA$4,MATCH(TRUE,INDEX(ISNUMBER(Q60:AA60),0),0)),"") -> 2015 | AE60: =IFERROR(LOOKUP(2,1/ISNUMBER(Q60:AA60),$Q$4:$AA$4),"") -> 2024 | AF60: =IF(AB60=0,"",AB60/(AE60-AD60+1)) -> 1 | AG60: =IF(AB60=0,"",'01_Criterios'!$C$8-AE60) -> 1 | AH60: =IF(P60="Em uso",100,IF(P60="Alta",85,IF(P60="Média",55,30))) -> 55 | AI60: =ROUND(100*AC60,1) -> 90.9 | AJ60: =IF(AB60=0,0,ROUND(MAX(0,100*AF60-10*AG60),1)) -> 90 | AK60: =ROUND(('01_Criterios'!$C$19*AH60+'01_Criterios'!$C$20*AI60+'01_Criterios'!$C$21*AJ60)/('01_Criterios'!$C$19+'01_Criterios'!$C$20+'01_Criterios'!$C$21)+N60*'01_Criterios'!$C$22,1) -> 88.3 | AL60: =IF(AND(AB60>=3,AC60>='01_Criterios'!$C$11,N(AE60)>='01_Criterios'!$C$12,OR(F60="+",F60="-"),ISNUMBER(G60),ISNUMBER(H60)),1,0) -> 0 | AM60: =IF(AL60=1,"",TRIM(IF(AB60=0,"sem dados no período; ",IF(AB60<3,"série demasiado curta; ",""))&IF(AND(AB60>0,AC60<'01_Criterios'!$C$11),"cobertura insuficiente; ","")&IF(AND(AB60>0,N(AE60)<'01_Criterios'!$C$12),"desactualizado; ","")&IF(AND(F60<>"+",F60<>"-"),"sentido ambíguo; ","")&IF(OR(NOT(ISNUMBER(G60)),NOT(ISNUMBER(H60))),"sem limites min/max; ",""))) -> sentido ambíguo; | AN60: =IF(OR(AL60=0,$AP60="Excluir"),0,IF(SUMPRODUCT(($O$5:$O$335=$O60)*($AL$5:$AL$335=1)*($AP$5:$AP$335<>"Excluir")*(($AK$5:$AK$335>$AK60)+(($AK$5:$AK$335=$AK60)*(ROW($O$5:$O$335)<ROW()))))=0,1,0)) -> 0 | AO60: =IF(AN60=0,"",1+SUMPRODUCT(($B$5:$B$335=$B60)*($AN$5:$AN$335=1)*(($AK$5:$AK$335>$AK60)+(($AK$5:$AK$335=$AK60)*(ROW($B$5:$B$335)<ROW()))))) | AP60: Auto | AQ60: =IF(INDEX('01_Criterios'!$C$26:$C$36,MATCH($B60,'01_Criterios'!$B$26:$B$36,0))<>1,0,IF($AP60="Excluir",0,IF($AP60="Incluir",IF(AND(OR($F60="+",$F60="-"),ISNUMBER($G60),ISNUMBER($H60),COUNT($Q60:$AA60)>0),1,0),IF('01_Criterios'!$C$18="Automática",IF(AND($AN60=1,$AO60<>"",$AO60<=INDEX('01_Criterios'!$E$26:$E$36,MATCH($B60,'01_Criterios'!$B$26:$B$36,0))),1,0),0)))) -> 0 | AR60: =IF(AQ60=0,"",IF($AO60<>"",1+SUMPRODUCT(($B$5:$B$335=$B60)*($AQ$5:$AQ$335=1)*($AO$5:$AO$335<$AO60)),1+SUMPRODUCT(($B$5:$B$335=$B60)*($AQ$5:$AQ$335=1)*ISNUMBER($AO$5:$AO$335))+SUMPRODUCT(($B$5:$B$335=$B60)*($AQ$5:$AQ$335=1)*($AO$5:$AO$335="")*(ROW($AO$5:$AO$335)<ROW())))) | AS60: INE, Contas Nacionais Q5.1.
A61: MAC043 | B61: 2. Estabilidade Macroeconómica | C61: Poupança e investimento | D61: Poupança bruta (% PIB, INE) | E61: % PIB | F61: + | G61: 0 | H61: 60 | I61: 25 | J61: 1 | K61: INE — Contas Nacionais | L61: NAT_INE_SAVRATE | M61: INE — Contas Nacionais | N61: 1 | O61: G_POUPANCA | P61: Média | Q61: 21.3082 | R61: 27.0432 | S61: 28.3101 | T61: 30.3463 | U61: 29.932 | V61: 21.0766 | W61: 26.2457 | X61: 22.9584 | Y61: 16.1494 | Z61: 15.8837 | AB61: =COUNT(Q61:AA61) -> 10 | AC61: =AB61/11 -> 0.90909091 | AD61: =IFERROR(INDEX($Q$4:$AA$4,MATCH(TRUE,INDEX(ISNUMBER(Q61:AA61),0),0)),"") -> 2015 | AE61: =IFERROR(LOOKUP(2,1/ISNUMBER(Q61:AA61),$Q$4:$AA$4),"") -> 2024 | AF61: =IF(AB61=0,"",AB61/(AE61-AD61+1)) -> 1 | AG61: =IF(AB61=0,"",'01_Criterios'!$C$8-AE61) -> 1 | AH61: =IF(P61="Em uso",100,IF(P61="Alta",85,IF(P61="Média",55,30))) -> 55 | AI61: =ROUND(100*AC61,1) -> 90.9 | AJ61: =IF(AB61=0,0,ROUND(MAX(0,100*AF61-10*AG61),1)) -> 90 | AK61: =ROUND(('01_Criterios'!$C$19*AH61+'01_Criterios'!$C$20*AI61+'01_Criterios'!$C$21*AJ61)/('01_Criterios'!$C$19+'01_Criterios'!$C$20+'01_Criterios'!$C$21)+N61*'01_Criterios'!$C$22,1) -> 88.3 | AL61: =IF(AND(AB61>=3,AC61>='01_Criterios'!$C$11,N(AE61)>='01_Criterios'!$C$12,OR(F61="+",F61="-"),ISNUMBER(G61),ISNUMBER(H61)),1,0) -> 1 | AM61: =IF(AL61=1,"",TRIM(IF(AB61=0,"sem dados no período; ",IF(AB61<3,"série demasiado curta; ",""))&IF(AND(AB61>0,AC61<'01_Criterios'!$C$11),"cobertura insuficiente; ","")&IF(AND(AB61>0,N(AE61)<'01_Criterios'!$C$12),"desactualizado; ","")&IF(AND(F61<>"+",F61<>"-"),"sentido ambíguo; ","")&IF(OR(NOT(ISNUMBER(G61)),NOT(ISNUMBER(H61))),"sem limites min/max; ",""))) | AN61: =IF(OR(AL61=0,$AP61="Excluir"),0,IF(SUMPRODUCT(($O$5:$O$335=$O61)*($AL$5:$AL$335=1)*($AP$5:$AP$335<>"Excluir")*(($AK$5:$AK$335>$AK61)+(($AK$5:$AK$335=$AK61)*(ROW($O$5:$O$335)<ROW()))))=0,1,0)) -> 1 | AO61: =IF(AN61=0,"",1+SUMPRODUCT(($B$5:$B$335=$B61)*($AN$5:$AN$335=1)*(($AK$5:$AK$335>$AK61)+(($AK$5:$AK$335=$AK61)*(ROW($B$5:$B$335)<ROW()))))) -> 19 | AP61: Auto | AQ61: =IF(INDEX('01_Criterios'!$C$26:$C$36,MATCH($B61,'01_Criterios'!$B$26:$B$36,0))<>1,0,IF($AP61="Excluir",0,IF($AP61="Incluir",IF(AND(OR($F61="+",$F61="-"),ISNUMBER($G61),ISNUMBER($H61),COUNT($Q61:$AA61)>0),1,0),IF('01_Criterios'!$C$18="Automática",IF(AND($AN61=1,$AO61<>"",$AO61<=INDEX('01_Criterios'!$E$26:$E$36,MATCH($B61,'01_Criterios'!$B$26:$B$36,0))),1,0),0)))) -> 0 | AR61: =IF(AQ61=0,"",IF($AO61<>"",1+SUMPRODUCT(($B$5:$B$335=$B61)*($AQ$5:$AQ$335=1)*($AO$5:$AO$335<$AO61)),1+SUMPRODUCT(($B$5:$B$335=$B61)*($AQ$5:$AQ$335=1)*ISNUMBER($AO$5:$AO$335))+SUMPRODUCT(($B$5:$B$335=$B61)*($AQ$5:$AQ$335=1)*($AO$5:$AO$335="")*(ROW($AO$5:$AO$335)<ROW())))) | AS61: INE, Contas Nacionais Q5.1.
A62: MAC044 | B62: 2. Estabilidade Macroeconómica | C62: Sector externo | D62: Exportações de bens (BNA) | E62: % PIB | F62: + | G62: 0 | H62: 100 | J62: 1 | K62: BNA — Estatísticas Externas | L62: NAT_BNA_EXP_GDP | M62: BNA — Estatísticas Externas | N62: 1 | O62: G_EXPORTACOES | P62: Média | Q62: 25.2083 | R62: 23.6845 | S62: 24.391 | T62: 35.2888 | U62: 36.4514 | V62: 31.6649 | W62: 39.9812 | X62: 35.8917 | Y62: 32.6773 | Z62: 30.7717 | AA62: 21.5586 | AB62: =COUNT(Q62:AA62) -> 11 | AC62: =AB62/11 -> 1 | AD62: =IFERROR(INDEX($Q$4:$AA$4,MATCH(TRUE,INDEX(ISNUMBER(Q62:AA62),0),0)),"") -> 2015 | AE62: =IFERROR(LOOKUP(2,1/ISNUMBER(Q62:AA62),$Q$4:$AA$4),"") -> 2025 | AF62: =IF(AB62=0,"",AB62/(AE62-AD62+1)) -> 1 | AG62: =IF(AB62=0,"",'01_Criterios'!$C$8-AE62) -> 0 | AH62: =IF(P62="Em uso",100,IF(P62="Alta",85,IF(P62="Média",55,30))) -> 55 | AI62: =ROUND(100*AC62,1) -> 100 | AJ62: =IF(AB62=0,0,ROUND(MAX(0,100*AF62-10*AG62),1)) -> 100 | AK62: =ROUND(('01_Criterios'!$C$19*AH62+'01_Criterios'!$C$20*AI62+'01_Criterios'!$C$21*AJ62)/('01_Criterios'!$C$19+'01_Criterios'!$C$20+'01_Criterios'!$C$21)+N62*'01_Criterios'!$C$22,1) -> 94 | AL62: =IF(AND(AB62>=3,AC62>='01_Criterios'!$C$11,N(AE62)>='01_Criterios'!$C$12,OR(F62="+",F62="-"),ISNUMBER(G62),ISNUMBER(H62)),1,0) -> 1 | AM62: =IF(AL62=1,"",TRIM(IF(AB62=0,"sem dados no período; ",IF(AB62<3,"série demasiado curta; ",""))&IF(AND(AB62>0,AC62<'01_Criterios'!$C$11),"cobertura insuficiente; ","")&IF(AND(AB62>0,N(AE62)<'01_Criterios'!$C$12),"desactualizado; ","")&IF(AND(F62<>"+",F62<>"-"),"sentido ambíguo; ","")&IF(OR(NOT(ISNUMBER(G62)),NOT(ISNUMBER(H62))),"sem limites min/max; ",""))) | AN62: =IF(OR(AL62=0,$AP62="Excluir"),0,IF(SUMPRODUCT(($O$5:$O$335=$O62)*($AL$5:$AL$335=1)*($AP$5:$AP$335<>"Excluir")*(($AK$5:$AK$335>$AK62)+(($AK$5:$AK$335=$AK62)*(ROW($O$5:$O$335)<ROW()))))=0,1,0)) -> 1 | AO62: =IF(AN62=0,"",1+SUMPRODUCT(($B$5:$B$335=$B62)*($AN$5:$AN$335=1)*(($AK$5:$AK$335>$AK62)+(($AK$5:$AK$335=$AK62)*(ROW($B$5:$B$335)<ROW()))))) -> 14 | AP62: Auto | AQ62: =IF(INDEX('01_Criterios'!$C$26:$C$36,MATCH($B62,'01_Criterios'!$B$26:$B$36,0))<>1,0,IF($AP62="Excluir",0,IF($AP62="Incluir",IF(AND(OR($F62="+",$F62="-"),ISNUMBER($G62),ISNUMBER($H62),COUNT($Q62:$AA62)>0),1,0),IF('01_Criterios'!$C$18="Automática",IF(AND($AN62=1,$AO62<>"",$AO62<=INDEX('01_Criterios'!$E$26:$E$36,MATCH($B62,'01_Criterios'!$B$26:$B$36,0))),1,0),0)))) -> 0 | AR62: =IF(AQ62=0,"",IF($AO62<>"",1+SUMPRODUCT(($B$5:$B$335=$B62)*($AQ$5:$AQ$335=1)*($AO$5:$AO$335<$AO62)),1+SUMPRODUCT(($B$5:$B$335=$B62)*($AQ$5:$AQ$335=1)*ISNUMBER($AO$5:$AO$335))+SUMPRODUCT(($B$5:$B$335=$B62)*($AQ$5:$AQ$335=1)*($AO$5:$AO$335="")*(ROW($AO$5:$AO$335)<ROW())))) | AS62: BNA, Principais Indicadores Externos 1990-2025, linha "Exportações".
A63: MAC045 | B63: 2. Estabilidade Macroeconómica | C63: Sector externo | D63: Reservas internacionais (stock, BNA) | E63: % PIB | F63: + | G63: 0 | H63: 60 | J63: 1 | K63: BNA — Estatísticas Externas | L63: NAT_BNA_RES_GDP | M63: BNA — Estatísticas Externas | N63: 1 | O63: G_RESERVAS_STOCK | P63: Média | Q63: 18.5519 | R63: 20.9062 | S63: 12.8445 | T63: 14.0005 | U63: 18.0669 | V63: 22.5016 | W63: 18.4635 | X63: 10.5159 | Y63: 13.0467 | Z63: 13.1864 | AA63: 11.2151 | AB63: =COUNT(Q63:AA63) -> 11 | AC63: =AB63/11 -> 1 | AD63: =IFERROR(INDEX($Q$4:$AA$4,MATCH(TRUE,INDEX(ISNUMBER(Q63:AA63),0),0)),"") -> 2015 | AE63: =IFERROR(LOOKUP(2,1/ISNUMBER(Q63:AA63),$Q$4:$AA$4),"") -> 2025 | AF63: =IF(AB63=0,"",AB63/(AE63-AD63+1)) -> 1 | AG63: =IF(AB63=0,"",'01_Criterios'!$C$8-AE63) -> 0 | AH63: =IF(P63="Em uso",100,IF(P63="Alta",85,IF(P63="Média",55,30))) -> 55 | AI63: =ROUND(100*AC63,1) -> 100 | AJ63: =IF(AB63=0,0,ROUND(MAX(0,100*AF63-10*AG63),1)) -> 100 | AK63: =ROUND(('01_Criterios'!$C$19*AH63+'01_Criterios'!$C$20*AI63+'01_Criterios'!$C$21*AJ63)/('01_Criterios'!$C$19+'01_Criterios'!$C$20+'01_Criterios'!$C$21)+N63*'01_Criterios'!$C$22,1) -> 94 | AL63: =IF(AND(AB63>=3,AC63>='01_Criterios'!$C$11,N(AE63)>='01_Criterios'!$C$12,OR(F63="+",F63="-"),ISNUMBER(G63),ISNUMBER(H63)),1,0) -> 1 | AM63: =IF(AL63=1,"",TRIM(IF(AB63=0,"sem dados no período; ",IF(AB63<3,"série demasiado curta; ",""))&IF(AND(AB63>0,AC63<'01_Criterios'!$C$11),"cobertura insuficiente; ","")&IF(AND(AB63>0,N(AE63)<'01_Criterios'!$C$12),"desactualizado; ","")&IF(AND(F63<>"+",F63<>"-"),"sentido ambíguo; ","")&IF(OR(NOT(ISNUMBER(G63)),NOT(ISNUMBER(H63))),"sem limites min/max; ",""))) | AN63: =IF(OR(AL63=0,$AP63="Excluir"),0,IF(SUMPRODUCT(($O$5:$O$335=$O63)*($AL$5:$AL$335=1)*($AP$5:$AP$335<>"Excluir")*(($AK$5:$AK$335>$AK63)+(($AK$5:$AK$335=$AK63)*(ROW($O$5:$O$335)<ROW()))))=0,1,0)) -> 1 | AO63: =IF(AN63=0,"",1+SUMPRODUCT(($B$5:$B$335=$B63)*($AN$5:$AN$335=1)*(($AK$5:$AK$335>$AK63)+(($AK$5:$AK$335=$AK63)*(ROW($B$5:$B$335)<ROW()))))) -> 15 | AP63: Auto | AQ63: =IF(INDEX('01_Criterios'!$C$26:$C$36,MATCH($B63,'01_Criterios'!$B$26:$B$36,0))<>1,0,IF($AP63="Excluir",0,IF($AP63="Incluir",IF(AND(OR($F63="+",$F63="-"),ISNUMBER($G63),ISNUMBER($H63),COUNT($Q63:$AA63)>0),1,0),IF('01_Criterios'!$C$18="Automática",IF(AND($AN63=1,$AO63<>"",$AO63<=INDEX('01_Criterios'!$E$26:$E$36,MATCH($B63,'01_Criterios'!$B$26:$B$36,0))),1,0),0)))) -> 0 | AR63: =IF(AQ63=0,"",IF($AO63<>"",1+SUMPRODUCT(($B$5:$B$335=$B63)*($AQ$5:$AQ$335=1)*($AO$5:$AO$335<$AO63)),1+SUMPRODUCT(($B$5:$B$335=$B63)*($AQ$5:$AQ$335=1)*ISNUMBER($AO$5:$AO$335))+SUMPRODUCT(($B$5:$B$335=$B63)*($AQ$5:$AQ$335=1)*($AO$5:$AO$335="")*(ROW($AO$5:$AO$335)<ROW())))) | AS63: BNA, Principais Indicadores Externos 1990-2025, linha "Reservas Internacionais (stock)".
A64: MAC046 | B64: 2. Estabilidade Macroeconómica | C64: Sector externo | D64: Serviço da dívida externa / exportações (BNA) | E64: % | F64: - | G64: 0 | H64: 100 | I64: 15 | J64: 1 | K64: BNA — Estatísticas Externas | L64: NAT_BNA_DEBTSERV_EXP | M64: BNA — Estatísticas Externas | N64: 1 | O64: MAC046 | P64: Média | Q64: 21.4108 | R64: 29.0381 | S64: 30.3019 | T64: 22.8726 | U64: 29.7153 | V64: 41.9637 | W64: 31.1948 | X64: 19.1648 | Y64: 37.9644 | Z64: 30.2412 | AA64: 31.534 | AB64: =COUNT(Q64:AA64) -> 11 | AC64: =AB64/11 -> 1 | AD64: =IFERROR(INDEX($Q$4:$AA$4,MATCH(TRUE,INDEX(ISNUMBER(Q64:AA64),0),0)),"") -> 2015 | AE64: =IFERROR(LOOKUP(2,1/ISNUMBER(Q64:AA64),$Q$4:$AA$4),"") -> 2025 | AF64: =IF(AB64=0,"",AB64/(AE64-AD64+1)) -> 1 | AG64: =IF(AB64=0,"",'01_Criterios'!$C$8-AE64) -> 0 | AH64: =IF(P64="Em uso",100,IF(P64="Alta",85,IF(P64="Média",55,30))) -> 55 | AI64: =ROUND(100*AC64,1) -> 100 | AJ64: =IF(AB64=0,0,ROUND(MAX(0,100*AF64-10*AG64),1)) -> 100 | AK64: =ROUND(('01_Criterios'!$C$19*AH64+'01_Criterios'!$C$20*AI64+'01_Criterios'!$C$21*AJ64)/('01_Criterios'!$C$19+'01_Criterios'!$C$20+'01_Criterios'!$C$21)+N64*'01_Criterios'!$C$22,1) -> 94 | AL64: =IF(AND(AB64>=3,AC64>='01_Criterios'!$C$11,N(AE64)>='01_Criterios'!$C$12,OR(F64="+",F64="-"),ISNUMBER(G64),ISNUMBER(H64)),1,0) -> 1 | AM64: =IF(AL64=1,"",TRIM(IF(AB64=0,"sem dados no período; ",IF(AB64<3,"série demasiado curta; ",""))&IF(AND(AB64>0,AC64<'01_Criterios'!$C$11),"cobertura insuficiente; ","")&IF(AND(AB64>0,N(AE64)<'01_Criterios'!$C$12),"desactualizado; ","")&IF(AND(F64<>"+",F64<>"-"),"sentido ambíguo; ","")&IF(OR(NOT(ISNUMBER(G64)),NOT(ISNUMBER(H64))),"sem limites min/max; ",""))) | AN64: =IF(OR(AL64=0,$AP64="Excluir"),0,IF(SUMPRODUCT(($O$5:$O$335=$O64)*($AL$5:$AL$335=1)*($AP$5:$AP$335<>"Excluir")*(($AK$5:$AK$335>$AK64)+(($AK$5:$AK$335=$AK64)*(ROW($O$5:$O$335)<ROW()))))=0,1,0)) -> 1 | AO64: =IF(AN64=0,"",1+SUMPRODUCT(($B$5:$B$335=$B64)*($AN$5:$AN$335=1)*(($AK$5:$AK$335>$AK64)+(($AK$5:$AK$335=$AK64)*(ROW($B$5:$B$335)<ROW()))))) -> 16 | AP64: Auto | AQ64: =IF(INDEX('01_Criterios'!$C$26:$C$36,MATCH($B64,'01_Criterios'!$B$26:$B$36,0))<>1,0,IF($AP64="Excluir",0,IF($AP64="Incluir",IF(AND(OR($F64="+",$F64="-"),ISNUMBER($G64),ISNUMBER($H64),COUNT($Q64:$AA64)>0),1,0),IF('01_Criterios'!$C$18="Automática",IF(AND($AN64=1,$AO64<>"",$AO64<=INDEX('01_Criterios'!$E$26:$E$36,MATCH($B64,'01_Criterios'!$B$26:$B$36,0))),1,0),0)))) -> 0 | AR64: =IF(AQ64=0,"",IF($AO64<>"",1+SUMPRODUCT(($B$5:$B$335=$B64)*($AQ$5:$AQ$335=1)*($AO$5:$AO$335<$AO64)),1+SUMPRODUCT(($B$5:$B$335=$B64)*($AQ$5:$AQ$335=1)*ISNUMBER($AO$5:$AO$335))+SUMPRODUCT(($B$5:$B$335=$B64)*($AQ$5:$AQ$335=1)*($AO$5:$AO$335="")*(ROW($AO$5:$AO$335)<ROW())))) | AS64: BNA, Principais Indicadores Externos 1990-2025, linha "Serviço da Dívida Externa / Exportações de Bens e Servi".
A65: MAC047 | B65: 2. Estabilidade Macroeconómica | C65: Sector externo | D65: Reservas internacionais (BNA) | E65: milhões USD | F65: + | G65: 0 | H65: 37000 | J65: 1 | K65: BNA — Estatísticas Externas | L65: NAT_BNA_RES_USD | M65: BNA — Estatísticas Externas | N65: 1 | O65: G_RESERVAS_STOCK | P65: Média | Q65: 24419.495 | R65: 24352.542 | S65: 18227.754 | T65: 16170.245 | U65: 17211.496 | V65: 14878.529 | W65: 15508.1 | X65: 14660.603 | Y65: 14726.574 | Z65: 15767.562 | AA65: 15895.33 | AB65: =COUNT(Q65:AA65) -> 11 | AC65: =AB65/11 -> 1 | AD65: =IFERROR(INDEX($Q$4:$AA$4,MATCH(TRUE,INDEX(ISNUMBER(Q65:AA65),0),0)),"") -> 2015 | AE65: =IFERROR(LOOKUP(2,1/ISNUMBER(Q65:AA65),$Q$4:$AA$4),"") -> 2025 | AF65: =IF(AB65=0,"",AB65/(AE65-AD65+1)) -> 1 | AG65: =IF(AB65=0,"",'01_Criterios'!$C$8-AE65) -> 0 | AH65: =IF(P65="Em uso",100,IF(P65="Alta",85,IF(P65="Média",55,30))) -> 55 | AI65: =ROUND(100*AC65,1) -> 100 | AJ65: =IF(AB65=0,0,ROUND(MAX(0,100*AF65-10*AG65),1)) -> 100 | AK65: =ROUND(('01_Criterios'!$C$19*AH65+'01_Criterios'!$C$20*AI65+'01_Criterios'!$C$21*AJ65)/('01_Criterios'!$C$19+'01_Criterios'!$C$20+'01_Criterios'!$C$21)+N65*'01_Criterios'!$C$22,1) -> 94 | AL65: =IF(AND(AB65>=3,AC65>='01_Criterios'!$C$11,N(AE65)>='01_Criterios'!$C$12,OR(F65="+",F65="-"),ISNUMBER(G65),ISNUMBER(H65)),1,0) -> 1 | AM65: =IF(AL65=1,"",TRIM(IF(AB65=0,"sem dados no período; ",IF(AB65<3,"série demasiado curta; ",""))&IF(AND(AB65>0,AC65<'01_Criterios'!$C$11),"cobertura insuficiente; ","")&IF(AND(AB65>0,N(AE65)<'01_Criterios'!$C$12),"desactualizado; ","")&IF(AND(F65<>"+",F65<>"-"),"sentido ambíguo; ","")&IF(OR(NOT(ISNUMBER(G65)),NOT(ISNUMBER(H65))),"sem limites min/max; ",""))) | AN65: =IF(OR(AL65=0,$AP65="Excluir"),0,IF(SUMPRODUCT(($O$5:$O$335=$O65)*($AL$5:$AL$335=1)*($AP$5:$AP$335<>"Excluir")*(($AK$5:$AK$335>$AK65)+(($AK$5:$AK$335=$AK65)*(ROW($O$5:$O$335)<ROW()))))=0,1,0)) -> 0 | AO65: =IF(AN65=0,"",1+SUMPRODUCT(($B$5:$B$335=$B65)*($AN$5:$AN$335=1)*(($AK$5:$AK$335>$AK65)+(($AK$5:$AK$335=$AK65)*(ROW($B$5:$B$335)<ROW()))))) | AP65: Auto | AQ65: =IF(INDEX('01_Criterios'!$C$26:$C$36,MATCH($B65,'01_Criterios'!$B$26:$B$36,0))<>1,0,IF($AP65="Excluir",0,IF($AP65="Incluir",IF(AND(OR($F65="+",$F65="-"),ISNUMBER($G65),ISNUMBER($H65),COUNT($Q65:$AA65)>0),1,0),IF('01_Criterios'!$C$18="Automática",IF(AND($AN65=1,$AO65<>"",$AO65<=INDEX('01_Criterios'!$E$26:$E$36,MATCH($B65,'01_Criterios'!$B$26:$B$36,0))),1,0),0)))) -> 0 | AR65: =IF(AQ65=0,"",IF($AO65<>"",1+SUMPRODUCT(($B$5:$B$335=$B65)*($AQ$5:$AQ$335=1)*($AO$5:$AO$335<$AO65)),1+SUMPRODUCT(($B$5:$B$335=$B65)*($AQ$5:$AQ$335=1)*ISNUMBER($AO$5:$AO$335))+SUMPRODUCT(($B$5:$B$335=$B65)*($AQ$5:$AQ$335=1)*($AO$5:$AO$335="")*(ROW($AO$5:$AO$335)<ROW())))) | AS65: BNA, Principais Indicadores Externos 1990-2025, linha "Reservas Internacionais". | Limites min/max derivados da amplitude histórica.
A66: MAC048 | B66: 2. Estabilidade Macroeconómica | C66: Sector externo | D66: Taxa de câmbio média USD/AOA (BNA) | E66: AOA por USD | F66: +/- | G66: 0 | H66: 1050 | J66: 1 | K66: BNA — Estatísticas Externas | L66: NAT_BNA_FX_AVG | M66: BNA — Estatísticas Externas | N66: 1 | O66: MAC048 | P66: Média | Q66: 120.091 | R66: 163.6398 | S66: 165.916 | T66: 252.7652 | U66: 364.6133 | V66: 578.3804 | W66: 624.1421 | X66: 459.7643 | Y66: 686.5958 | Z66: 869.8462 | AA66: 911.969 | AB66: =COUNT(Q66:AA66) -> 11 | AC66: =AB66/11 -> 1 | AD66: =IFERROR(INDEX($Q$4:$AA$4,MATCH(TRUE,INDEX(ISNUMBER(Q66:AA66),0),0)),"") -> 2015 | AE66: =IFERROR(LOOKUP(2,1/ISNUMBER(Q66:AA66),$Q$4:$AA$4),"") -> 2025 | AF66: =IF(AB66=0,"",AB66/(AE66-AD66+1)) -> 1 | AG66: =IF(AB66=0,"",'01_Criterios'!$C$8-AE66) -> 0 | AH66: =IF(P66="Em uso",100,IF(P66="Alta",85,IF(P66="Média",55,30))) -> 55 | AI66: =ROUND(100*AC66,1) -> 100 | AJ66: =IF(AB66=0,0,ROUND(MAX(0,100*AF66-10*AG66),1)) -> 100 | AK66: =ROUND(('01_Criterios'!$C$19*AH66+'01_Criterios'!$C$20*AI66+'01_Criterios'!$C$21*AJ66)/('01_Criterios'!$C$19+'01_Criterios'!$C$20+'01_Criterios'!$C$21)+N66*'01_Criterios'!$C$22,1) -> 94 | AL66: =IF(AND(AB66>=3,AC66>='01_Criterios'!$C$11,N(AE66)>='01_Criterios'!$C$12,OR(F66="+",F66="-"),ISNUMBER(G66),ISNUMBER(H66)),1,0) -> 0 | AM66: =IF(AL66=1,"",TRIM(IF(AB66=0,"sem dados no período; ",IF(AB66<3,"série demasiado curta; ",""))&IF(AND(AB66>0,AC66<'01_Criterios'!$C$11),"cobertura insuficiente; ","")&IF(AND(AB66>0,N(AE66)<'01_Criterios'!$C$12),"desactualizado; ","")&IF(AND(F66<>"+",F66<>"-"),"sentido ambíguo; ","")&IF(OR(NOT(ISNUMBER(G66)),NOT(ISNUMBER(H66))),"sem limites min/max; ",""))) -> sentido ambíguo; | AN66: =IF(OR(AL66=0,$AP66="Excluir"),0,IF(SUMPRODUCT(($O$5:$O$335=$O66)*($AL$5:$AL$335=1)*($AP$5:$AP$335<>"Excluir")*(($AK$5:$AK$335>$AK66)+(($AK$5:$AK$335=$AK66)*(ROW($O$5:$O$335)<ROW()))))=0,1,0)) -> 0 | AO66: =IF(AN66=0,"",1+SUMPRODUCT(($B$5:$B$335=$B66)*($AN$5:$AN$335=1)*(($AK$5:$AK$335>$AK66)+(($AK$5:$AK$335=$AK66)*(ROW($B$5:$B$335)<ROW()))))) | AP66: Auto | AQ66: =IF(INDEX('01_Criterios'!$C$26:$C$36,MATCH($B66,'01_Criterios'!$B$26:$B$36,0))<>1,0,IF($AP66="Excluir",0,IF($AP66="Incluir",IF(AND(OR($F66="+",$F66="-"),ISNUMBER($G66),ISNUMBER($H66),COUNT($Q66:$AA66)>0),1,0),IF('01_Criterios'!$C$18="Automática",IF(AND($AN66=1,$AO66<>"",$AO66<=INDEX('01_Criterios'!$E$26:$E$36,MATCH($B66,'01_Criterios'!$B$26:$B$36,0))),1,0),0)))) -> 0 | AR66: =IF(AQ66=0,"",IF($AO66<>"",1+SUMPRODUCT(($B$5:$B$335=$B66)*($AQ$5:$AQ$335=1)*($AO$5:$AO$335<$AO66)),1+SUMPRODUCT(($B$5:$B$335=$B66)*($AQ$5:$AQ$335=1)*ISNUMBER($AO$5:$AO$335))+SUMPRODUCT(($B$5:$B$335=$B66)*($AQ$5:$AQ$335=1)*($AO$5:$AO$335="")*(ROW($AO$5:$AO$335)<ROW())))) | AS66: BNA, Principais Indicadores Externos 1990-2025, linha "Taxa de Câmbio Média (USD/AOA)". | Limites min/max derivados da amplitude histórica.
A67: MAC012 | B67: 2. Estabilidade Macroeconómica | C67: 2. Macroeconomia | D67: Exportações de bens e serviços (% PIB) | E67: % | F67: + | G67: 0 | H67: 100 | I67: 40 | J67: 1 | K67: Banco Mundial/WDI | L67: NE.EXP.GNFS.ZS | M67: Banco Mundial — WDI | N67: 0 | O67: G_EXPORTACOES | P67: Média | Q67: 26.148932 | R67: 24.297292 | S67: 25.084825 | T67: 35.848111 | U67: 36.950082 | V67: 31.759536 | W67: 40.092305 | X67: 36.013486 | Y67: 32.669372 | Z67: 30.879522 | AA67: 22.97775 | AB67: =COUNT(Q67:AA67) -> 11 | AC67: =AB67/11 -> 1 | AD67: =IFERROR(INDEX($Q$4:$AA$4,MATCH(TRUE,INDEX(ISNUMBER(Q67:AA67),0),0)),"") -> 2015 | AE67: =IFERROR(LOOKUP(2,1/ISNUMBER(Q67:AA67),$Q$4:$AA$4),"") -> 2025 | AF67: =IF(AB67=0,"",AB67/(AE67-AD67+1)) -> 1 | AG67: =IF(AB67=0,"",'01_Criterios'!$C$8-AE67) -> 0 | AH67: =IF(P67="Em uso",100,IF(P67="Alta",85,IF(P67="Média",55,30))) -> 55 | AI67: =ROUND(100*AC67,1) -> 100 | AJ67: =IF(AB67=0,0,ROUND(MAX(0,100*AF67-10*AG67),1)) -> 100 | AK67: =ROUND(('01_Criterios'!$C$19*AH67+'01_Criterios'!$C$20*AI67+'01_Criterios'!$C$21*AJ67)/('01_Criterios'!$C$19+'01_Criterios'!$C$20+'01_Criterios'!$C$21)+N67*'01_Criterios'!$C$22,1) -> 82 | AL67: =IF(AND(AB67>=3,AC67>='01_Criterios'!$C$11,N(AE67)>='01_Criterios'!$C$12,OR(F67="+",F67="-"),ISNUMBER(G67),ISNUMBER(H67)),1,0) -> 1 | AM67: =IF(AL67=1,"",TRIM(IF(AB67=0,"sem dados no período; ",IF(AB67<3,"série demasiado curta; ",""))&IF(AND(AB67>0,AC67<'01_Criterios'!$C$11),"cobertura insuficiente; ","")&IF(AND(AB67>0,N(AE67)<'01_Criterios'!$C$12),"desactualizado; ","")&IF(AND(F67<>"+",F67<>"-"),"sentido ambíguo; ","")&IF(OR(NOT(ISNUMBER(G67)),NOT(ISNUMBER(H67))),"sem limites min/max; ",""))) | AN67: =IF(OR(AL67=0,$AP67="Excluir"),0,IF(SUMPRODUCT(($O$5:$O$335=$O67)*($AL$5:$AL$335=1)*($AP$5:$AP$335<>"Excluir")*(($AK$5:$AK$335>$AK67)+(($AK$5:$AK$335=$AK67)*(ROW($O$5:$O$335)<ROW()))))=0,1,0)) -> 0 | AO67: =IF(AN67=0,"",1+SUMPRODUCT(($B$5:$B$335=$B67)*($AN$5:$AN$335=1)*(($AK$5:$AK$335>$AK67)+(($AK$5:$AK$335=$AK67)*(ROW($B$5:$B$335)<ROW()))))) | AP67: Auto | AQ67: =IF(INDEX('01_Criterios'!$C$26:$C$36,MATCH($B67,'01_Criterios'!$B$26:$B$36,0))<>1,0,IF($AP67="Excluir",0,IF($AP67="Incluir",IF(AND(OR($F67="+",$F67="-"),ISNUMBER($G67),ISNUMBER($H67),COUNT($Q67:$AA67)>0),1,0),IF('01_Criterios'!$C$18="Automática",IF(AND($AN67=1,$AO67<>"",$AO67<=INDEX('01_Criterios'!$E$26:$E$36,MATCH($B67,'01_Criterios'!$B$26:$B$36,0))),1,0),0)))) -> 0 | AR67: =IF(AQ67=0,"",IF($AO67<>"",1+SUMPRODUCT(($B$5:$B$335=$B67)*($AQ$5:$AQ$335=1)*($AO$5:$AO$335<$AO67)),1+SUMPRODUCT(($B$5:$B$335=$B67)*($AQ$5:$AQ$335=1)*ISNUMBER($AO$5:$AO$335))+SUMPRODUCT(($B$5:$B$335=$B67)*($AQ$5:$AQ$335=1)*($AO$5:$AO$335="")*(ROW($AO$5:$AO$335)<ROW())))) | AS67: Acompanha abertura e capacidade exportadora, mas deve ser lido com composição setorial. | Nome local/API: Exports of goods and services (% of GDP)
A68: MAC013 | B68: 2. Estabilidade Macroeconómica | C68: 2. Macroeconomia | D68: Crédito doméstico ao setor privado (% PIB) | E68: % | F68: + | G68: 0 | H68: 100 | I68: 35 | J68: 1 | K68: Banco Mundial/WDI | L68: FS.AST.PRVT.GD.ZS | M68: Banco Mundial — WDI | N68: 0 | O68: G_CRED_PRIVADO | P68: Média | Q68: 22.274928 | R68: 18.318008 | S68: 14.630258 | T68: 13.110918 | U68: 13.395603 | V68: 11.376559 | W68: 8.8443017 | X68: 7.0250619 | Y68: 7.6457337 | Z68: 7.1689264 | AA68: 6.580883 | AB68: =COUNT(Q68:AA68) -> 11 | AC68: =AB68/11 -> 1 | AD68: =IFERROR(INDEX($Q$4:$AA$4,MATCH(TRUE,INDEX(ISNUMBER(Q68:AA68),0),0)),"") -> 2015 | AE68: =IFERROR(LOOKUP(2,1/ISNUMBER(Q68:AA68),$Q$4:$AA$4),"") -> 2025 | AF68: =IF(AB68=0,"",AB68/(AE68-AD68+1)) -> 1 | AG68: =IF(AB68=0,"",'01_Criterios'!$C$8-AE68) -> 0 | AH68: =IF(P68="Em uso",100,IF(P68="Alta",85,IF(P68="Média",55,30))) -> 55 | AI68: =ROUND(100*AC68,1) -> 100 | AJ68: =IF(AB68=0,0,ROUND(MAX(0,100*AF68-10*AG68),1)) -> 100 | AK68: =ROUND(('01_Criterios'!$C$19*AH68+'01_Criterios'!$C$20*AI68+'01_Criterios'!$C$21*AJ68)/('01_Criterios'!$C$19+'01_Criterios'!$C$20+'01_Criterios'!$C$21)+N68*'01_Criterios'!$C$22,1) -> 82 | AL68: =IF(AND(AB68>=3,AC68>='01_Criterios'!$C$11,N(AE68)>='01_Criterios'!$C$12,OR(F68="+",F68="-"),ISNUMBER(G68),ISNUMBER(H68)),1,0) -> 1 | AM68: =IF(AL68=1,"",TRIM(IF(AB68=0,"sem dados no período; ",IF(AB68<3,"série demasiado curta; ",""))&IF(AND(AB68>0,AC68<'01_Criterios'!$C$11),"cobertura insuficiente; ","")&IF(AND(AB68>0,N(AE68)<'01_Criterios'!$C$12),"desactualizado; ","")&IF(AND(F68<>"+",F68<>"-"),"sentido ambíguo; ","")&IF(OR(NOT(ISNUMBER(G68)),NOT(ISNUMBER(H68))),"sem limites min/max; ",""))) | AN68: =IF(OR(AL68=0,$AP68="Excluir"),0,IF(SUMPRODUCT(($O$5:$O$335=$O68)*($AL$5:$AL$335=1)*($AP$5:$AP$335<>"Excluir")*(($AK$5:$AK$335>$AK68)+(($AK$5:$AK$335=$AK68)*(ROW($O$5:$O$335)<ROW()))))=0,1,0)) -> 0 | AO68: =IF(AN68=0,"",1+SUMPRODUCT(($B$5:$B$335=$B68)*($AN$5:$AN$335=1)*(($AK$5:$AK$335>$AK68)+(($AK$5:$AK$335=$AK68)*(ROW($B$5:$B$335)<ROW()))))) | AP68: Auto | AQ68: =IF(INDEX('01_Criterios'!$C$26:$C$36,MATCH($B68,'01_Criterios'!$B$26:$B$36,0))<>1,0,IF($AP68="Excluir",0,IF($AP68="Incluir",IF(AND(OR($F68="+",$F68="-"),ISNUMBER($G68),ISNUMBER($H68),COUNT($Q68:$AA68)>0),1,0),IF('01_Criterios'!$C$18="Automática",IF(AND($AN68=1,$AO68<>"",$AO68<=INDEX('01_Criterios'!$E$26:$E$36,MATCH($B68,'01_Criterios'!$B$26:$B$36,0))),1,0),0)))) -> 0 | AR68: =IF(AQ68=0,"",IF($AO68<>"",1+SUMPRODUCT(($B$5:$B$335=$B68)*($AQ$5:$AQ$335=1)*($AO$5:$AO$335<$AO68)),1+SUMPRODUCT(($B$5:$B$335=$B68)*($AQ$5:$AQ$335=1)*ISNUMBER($AO$5:$AO$335))+SUMPRODUCT(($B$5:$B$335=$B68)*($AQ$5:$AQ$335=1)*($AO$5:$AO$335="")*(ROW($AO$5:$AO$335)<ROW())))) | AS68: Acrescenta profundidade financeira e apoio ao investimento privado. | Nome local/API: Domestic credit to private sector (% of GDP)
